Workbook

Sheet INICIO
B2: AUTOEVALUACIÓN CONDICIONES DE HABILITACIÓN RESOLUCIÓN 3100/2019
B12: SERVICIOS | M12: HABILITADO | N12: AUTOEVALUADO | O12: CUMPLIMIENTO
B13: TODOS LOS SERVICIOS | M13: SI | N13: =IF(SUM('TODOS SERVICIOS'!C4:E4)=0,"NO","SI") -> SI | O13: ='TODOS SERVICIOS'!C5 -> 0.27692308
B15: GRUPO: CONSULTA EXTERNA
B16: CONSULTA EXTERNA GENERAL | M16: SI | N16: =IF(SUM('CE GENERAL'!C4:E4)=0,"NO","SI") -> NO | O16: ='CE GENERAL'!C5
B17: CONSULTA EXTERNA ESPECIALIZADA | M17: SI | N17: =IF(SUM('CE ESP'!C4:E4)=0,"NO","SI") -> SI | O17: ='CE ESP'!C5 -> 1
B18: VACUNACIÓN | M18: SI | N18: =IF(SUM(VACUN!C4:E4)=0,"NO","SI") -> NO | O18: =VACUN!C5
B19: SEGURIDAD Y SALUD EN EL TRABAJO | M19: NO | N19: =IF(SUM(SST!C4:E4)=0,"NO","SI") -> NO | O19: =SST!C5
B21: GRUPO: APOYO DIAGNOSTICO
B22: TERAPIAS | M22: SI | N22: =IF(SUM(TERAP!C4:E4)=0,"NO","SI") -> NO | O22: =TERAP!C5
B23: SERVICIO FARMACÉUTICO | M23: SI | N23: =IF(SUM(FARMAC!C4:E4)=0,"NO","SI") -> NO | O23: =FARMAC!C5
B24: RADIOLOGÍA ODONTOLÓGICA | M24: NO | N24: =IF(SUM('RAD ODONT'!C4:E4)=0,"NO","SI") -> SI | O24: ='RAD ODONT'!C5 -> 0.9375
B25: IMÁGENES DIAGNÓSTICAS - METODOS DIAGNÓSTICOS CON IMÁGENES OBTENIDAS MEDIANTE EQUIPOS GENERADORES DE RADIACIONES IONIZANTES | M25: SI | N25: =IF(SUM('IMAG DIAG ION'!C4:E4)=0,"NO","SI") -> NO | O25: ='IMAG DIAG ION'!C5
B26: IMÁGENES DIAGNÓSTICAS - MÉTODOS DIAGNÓSTICOS CON IMÁGENES OBTENIDAS MEDIANTE EQUIPOS GENERADORES DE RADIACIONES NO IONIZANTES | M26: SI | N26: =IF(SUM('IMAG DIAG NO ION'!C4:E4)=0,"NO","SI") -> NO | O26: ='IMAG DIAG NO ION'!C5
B27: MEDICINA NUCLEAR | M27: NO | N27: =IF(SUM('MED NUCL'!C4:E4)=0,"NO","SI") -> NO | O27: ='MED NUCL'!C5
B28: RADIOTERAPIA | M28: NO | N28: =IF(SUM(RADIOT!C4:E4)=0,"NO","SI") -> NO | O28: =RADIOT!C5
B29: QUIMIOTERAPIA | M29: NO | N29: =IF(SUM(QUIMIO!C4:E4)=0,"NO","SI") -> NO | O29: =QUIMIO!C5
B30: DIAGNÓSTICO VASCULAR | M30: SI | N30: =IF(SUM('DX VASC'!C4:E4)=0,"NO","SI") -> NO | O30: ='DX VASC'!C5
B31: HEMODINAMIA E INTERVENCIONISMO | M31: NO | N31: =IF(SUM(HEMOD!C4:E4)=0,"NO","SI") -> NO | O31: =HEMOD!C5
B32: GESTIÓN PRE TRANSFUSIONAL | M32: SI | N32: =IF(SUM(PRETRANS!C4:E4)=0,"NO","SI") -> NO | O32: =PRETRANS!C5
B33: TOMA DE MUESTRAS DE LABORATORIO CLÍNICO | M33: SI | N33: =IF(SUM('T MUEST'!C4:E4)=0,"NO","SI") -> NO | O33: ='T MUEST'!C5
B34: LABORATORIO CLÍNICO | M34: SI | N34: =IF(SUM(LABOR!C4:E4)=0,"NO","SI") -> NO | O34: =LABOR!C5
B35: TOMA DE MUESTRAS DE CUELLO UTERINO Y GINECOLÓGICAS | M35: NO | N35: =IF(SUM('TOMA CITO'!C4:E4)=0,"NO","SI") -> NO | O35: ='TOMA CITO'!C5
B36: LABORATORIO DE CITOLOGÍAS CERVICO-UTERINAS | M36: NO | N36: =IF(SUM('LAB CITO'!C4:E4)=0,"NO","SI") -> NO | O36: ='LAB CITO'!C5
B37: LABORATORIO DE HISTOTECNOLOGÍA | M37: NO | N37: =IF(SUM(HISTO!C4:E4)=0,"NO","SI") -> NO | O37: =HISTO!C5
B38: PATOLOGÍA | M38: NO | N38: =IF(SUM(PATOLO!C4:E4)=0,"NO","SI") -> NO | O38: =PATOLO!C5
B39: DIÁLISIS | M39: NO | N39: =IF(SUM(DIALISIS!C4:E4)=0,"NO","SI") -> NO | O39: =DIALISIS!C5
B41: GRUPO: INTERNACIÓN
B42: HOSPITALIZACIÓN | M42: SI | N42: =IF(SUM(HOSPI!C4:E4)=0,"NO","SI") -> NO | O42: =HOSPI!C5
B43: HOSPITALIZACIÓN PACIENTE CRÓNICO | M43: SI | N43: =IF(SUM('HOSP CRON'!C4:E4)=0,"NO","SI") -> NO | O43: ='HOSP CRON'!C5
B44: CUIDADO BÁSICO NEONATAL | M44: SI | N44: =IF(SUM('NEO BAS'!C4:E4)=0,"NO","SI") -> SI | O44: ='NEO BAS'!C5 -> 0.84126984
B45: CUIDADO INTERMEDIO NEONATAL | M45: SI | N45: =IF(SUM('NEO INTER'!C4:E4)=0,"NO","SI") -> SI | O45: ='NEO INTER'!C5 -> 0.91566265
B46: CUIDADO INTENSIVO NEONATAL | M46: SI | N46: =IF(SUM('NEO INTENS'!C4:E4)=0,"NO","SI") -> SI | O46: ='NEO INTENS'!C5 -> 0.90990991
B47: CUIDADO INTERMEDIO PEDIÁTRICO | M47: NO | N47: =IF(SUM('PED INTER'!C4:E4)=0,"NO","SI") -> NO | O47: ='PED INTER'!C5
B48: CUIDADO INTENSIVO PEDIÁTRICO | M48: NO | N48: =IF(SUM('PED INTENS'!C4:E4)=0,"NO","SI") -> NO | O48: ='PED INTENS'!C5
B49: CUIDADO INTERMEDIO ADULTO | M49: SI | N49: =IF(SUM('ADUL INTER'!C4:E4)=0,"NO","SI") -> NO | O49: ='ADUL INTER'!C5
B50: CUIDADO INTENSIVO ADULTOS | M50: SI | N50: =IF(SUM('ADUL INTENS'!C4:E4)=0,"NO","SI") -> NO | O50: ='ADUL INTENS'!C5
B51: HOSPITALIZACIÓN EN SALUD MENTAL O CONSUMO DE SUSTANCIAS PSICOACTIVAS | M51: NO | N51: =IF(SUM('HOSP SMENTAL'!C4:E4)=0,"NO","SI") -> NO | O51: ='HOSP SMENTAL'!C5
B52: HOSPITALIZACIÓN PARCIAL | M52: NO | N52: =IF(SUM('HOSP PARCIAL'!C4:E4)=0,"NO","SI") -> NO | O52: ='HOSP PARCIAL'!C5
B53: CUIDADO BÁSICO DEL CONSUMO DE SUSTANCIAS PSICOACTIVAS | M53: NO | N53: =IF(SUM('CUID BAS SUST'!D4:E4)=0,"NO","SI") -> NO | O53: ='CUID BAS SUST'!C5
B55: GRUPO: QUIRÚRGICO
B56: CIRUGÍA | M56: SI | N56: =IF(SUM(CIRUGIA!C4:E4)=0,"NO","SI") -> NO | O56: =CIRUGIA!C5
B58: GRUPO: ATENCIÓN INMEDIATA
B59: URGENCIAS | M59: SI | N59: =IF(SUM(URGENCIAS!C4:E4)=0,"NO","SI") -> NO | O59: =URGENCIAS!C5
B60: TRANSPORTE ASISTENCIAL | M60: NO | N60: =IF(SUM(TRANSP!C4:E4)=0,"NO","SI") -> NO | O60: =TRANSP!C5
B61: ATENCIÓN PREHOSPITALARIA | M61: NO | N61: =IF(SUM(PREHOS!C4:E4)=0,"NO","SI") -> NO | O61: =PREHOS!C5
B62: ATENCIÓN DEL PARTO | M62: SI | N62: =IF(SUM('AT PARTO'!C4:E4)=0,"NO","SI") -> NO | O62: ='AT PARTO'!C5

Sheet TODOS SERVICIOS
B1: TODOS LOS SERVICIOS CONDICIONES DE HABILITACIÓN RESOLUCIÓN 3100/2019 | O1: ESTADO DE ACCIONES (Número de acciones y % por estado) | S1: ESTADO DE ACCIONES (Número de acciones y % por estado) | W1: ESTADO DE ACCIONES (Número de acciones y % por estado) | AA1: ESTADO DE ACCIONES (Número de acciones y % por estado) | AE1: ESTADO DE ACCIONES (Número de acciones y % por estado) | AI1: ESTADO DE ACCIONES (Número de acciones y % por estado)
O2: SIN INICIAR | P2: =COUNTIFS(Q$10:Q$501,O2) -> 0 | Q2: =IFERROR(P2/SUM(P$2:P$5),"") | S2: SIN INICIAR | T2: =COUNTIFS(U$10:U$501,S2) -> 0 | U2: =IFERROR(T2/SUM(T$2:T$5),"") | W2: SIN INICIAR | X2: =COUNTIFS(Y$10:Y$501,W2) -> 0 | Y2: =IFERROR(X2/SUM(X$2:X$5),"") | AA2: SIN INICIAR | AB2: =COUNTIFS(AC$10:AC$501,AA2) -> 0 | AC2: =IFERROR(AB2/SUM(AB$2:AB$5),"") | AE2: SIN INICIAR | AF2: =COUNTIFS(AG$10:AG$501,AE2) -> 0 | AG2: =IFERROR(AF2/SUM(AF$2:AF$5),"") | AI2: SIN INICIAR | AJ2: =COUNTIFS(AK$10:AK$501,AI2) -> 0 | AK2: =IFERROR(AJ2/SUM(AJ$2:AJ$5),"")
C3: TOTAL CUMPLE | D3: TOTAL NO CUMPLE | E3: TOTAL NO APLICA | O3: EN EJECUCION | P3: =COUNTIFS(Q$10:Q$501,O3) -> 0 | Q3: =IFERROR(P3/SUM(P$2:P$5),"") | S3: EN EJECUCION | T3: =COUNTIFS(U$10:U$501,S3) -> 0 | U3: =IFERROR(T3/SUM(T$2:T$5),"") | W3: EN EJECUCION | X3: =COUNTIFS(Y$10:Y$501,W3) -> 0 | Y3: =IFERROR(X3/SUM(X$2:X$5),"") | AA3: EN EJECUCION | AB3: =COUNTIFS(AC$10:AC$501,AA3) -> 0 | AC3: =IFERROR(AB3/SUM(AB$2:AB$5),"") | AE3: EN EJECUCION | AF3: =COUNTIFS(AG$10:AG$501,AE3) -> 0 | AG3: =IFERROR(AF3/SUM(AF$2:AF$5),"") | AI3: EN EJECUCION | AJ3: =COUNTIFS(AK$10:AK$501,AI3) -> 0 | AK3: =IFERROR(AJ3/SUM(AJ$2:AJ$5),"")
A4: NUMERO DE CRITERIOS EVALUADOS | C4: =COUNTA(G10:G501) -> 18 | D4: =COUNTA(H10:H501) -> 47 | E4: =COUNTA(I10:I501) -> 260 | O4: CERRADA | P4: =COUNTIFS(Q$10:Q$501,O4) -> 0 | Q4: =IFERROR(P4/SUM(P$2:P$5),"") | S4: CERRADA | T4: =COUNTIFS(U$10:U$501,S4) -> 0 | U4: =IFERROR(T4/SUM(T$2:T$5),"") | W4: CERRADA | X4: =COUNTIFS(Y$10:Y$501,W4) -> 0 | Y4: =IFERROR(X4/SUM(X$2:X$5),"") | AA4: CERRADA | AB4: =COUNTIFS(AC$10:AC$501,AA4) -> 0 | AC4: =IFERROR(AB4/SUM(AB$2:AB$5),"") | AE4: CERRADA | AF4: =COUNTIFS(AG$10:AG$501,AE4) -> 0 | AG4: =IFERROR(AF4/SUM(AF$2:AF$5),"") | AI4: CERRADA | AJ4: =COUNTIFS(AK$10:AK$501,AI4) -> 0 | AK4: =IFERROR(AJ4/SUM(AJ$2:AJ$5),"")
A5: CUMPLIMIENTO DEL SERVICIO EVALUADO | C5: =IFERROR(C4/(D4+C4),"") -> 0.27692308 | O5: CANCELADA | P5: =COUNTIFS(Q$10:Q$501,O5) -> 0 | Q5: =IFERROR(P5/SUM(P$2:P$5),"") | S5: CANCELADA | T5: =COUNTIFS(U$10:U$501,S5) -> 0 | U5: =IFERROR(T5/SUM(T$2:T$5),"") | W5: CANCELADA | X5: =COUNTIFS(Y$10:Y$501,W5) -> 0 | Y5: =IFERROR(X5/SUM(X$2:X$5),"") | AA5: CANCELADA | AB5: =COUNTIFS(AC$10:AC$501,AA5) -> 0 | AC5: =IFERROR(AB5/SUM(AB$2:AB$5),"") | AE5: CANCELADA | AF5: =COUNTIFS(AG$10:AG$501,AE5) -> 0 | AG5: =IFERROR(AF5/SUM(AF$2:AF$5),"") | AI5: CANCELADA | AJ5: =COUNTIFS(AK$10:AK$501,AI5) -> 0 | AK5: =IFERROR(AJ5/SUM(AJ$2:AJ$5),"")
O6: TOTAL | P6: =SUM(P2:P5) -> 0 | S6: TOTAL | T6: =SUM(T2:T5) -> 0 | W6: TOTAL | X6: =SUM(X2:X5) -> 0 | AA6: TOTAL | AB6: =SUM(AB2:AB5) -> 0 | AE6: TOTAL | AF6: =SUM(AF2:AF5) -> 0 | AI6: TOTAL | AJ6: =SUM(AJ2:AJ5) -> 0
O8: SEGUIMIENTO 1 - Fecha: 15 noviembre 2020 | S8: SEGUIMIENTO 2 - Fecha: | W8: SEGUIMIENTO 3 - Fecha: | AA8: SEGUIMIENTO 4 - Fecha: | AE8: SEGUIMIENTO 5 - Fecha: | AI8: SEGUIMIENTO 6 - Fecha:
A9: ESTANDAR | B9: MODALIDAD | C9: ARTICULO | D9: SECCIÓN | E9: APARTADO | F9: CRITERIO | G9: CUMPLE | H9: NO CUMPLE | I9: NO APLICA | J9: HALLAZGO | K9: ACCIÓN PARA EL CUMPLIMIENTO | L9: RESPONSABLE | M9: FECHA LIMITE PARA IMPLEMENTAR | O9: SEGUIMIENTO 1 | Q9: ESTADO DE LA ACCIÓN 1 | S9: SEGUIMIENTO 2 | U9: ESTADO DE LA ACCIÓN 2 | W9: SEGUIMIENTO 3 | Y9: ESTADO DE LA ACCIÓN 3 | AA9: SEGUIMIENTO 4 | AC9: ESTADO DE LA ACCIÓN 4 | AE9: SEGUIMIENTO 5 | AG9: ESTADO DE LA ACCIÓN 5 | AI9: SEGUIMIENTO 6 | AK9: ESTADO DE LA ACCIÓN 6
A10: TALENTO HUMANO | B10: Todas las modalidades | C10: 11.1.1 | D10: 1 | F10: El talento humano en salud y otros profesionales que se relacionan con la atención o resultados en salud de los usuarios, cuentan con los títulos, según aplique, de educación superior o certificados de aptitud ocupacional, expedidos por la entidad educativa competente. En el caso de títulos o certificados obtenidos en el extranjero, copia de la resolución de convalidación expedida por el Ministerio de Educación Nacional | H10: X | J10: odontologo -ortodoncia (no cuenta con carnet de vacunas - RETHUS)- auxiliar salud oral(Kenia yibeni mosquera) no cuenta con registro profesional-no cuenta con carnet de vacunas-RETHUS)-auxiliar salud oral (FLORICEL IBASGUE OLAYA)
A11: TALENTO HUMANO | B11: Todas las modalidades | C11: 11.1.1 | D11: 2 | F11: El talento humano en salud cuenta con copia de la resolución de autorización del ejercicio expedido por la autoridad competente o inscripción en el Registro Único Nacional de Talento Humano en Salud -ReTHUS. | H11: X
A12: TALENTO HUMANO | B12: Todas las modalidades | C12: 11.1.1 | D12: 3 | F12: El prestador de servicios de salud determina la cantidad necesaria de talento humano requerido para cada uno de los servicios ofertados y prestados, de acuerdo con la capacidad instalada, la relación entre oferta y demanda, la oportunidad en la prestación, tiempo de la atención y el riesgo en la atención. Este criterio no aplica para el profesional independiente de salud | G12: X | K12: incluir en docuemento de suficiencia de personal y cambiar version | L12: Milena Mesias-Ing Diego | M12: 44264
A13: TALENTO HUMANO | B13: Todas las modalidades | C13: 11.1.1 | D13: 4 | F13: El prestador de servicios de salud que actúe como escenario de práctica formativa en el área de la salud, cuenta con: | I13: X
A14: TALENTO HUMANO | B14: Todas las modalidades | C14: 11.1.1 | D14: 4 | E14: 4.1 | F14: • Convenio vigente con la institución educativa autorizada por la entidad competente. | I14: X
A15: TALENTO HUMANO | B15: Todas las modalidades | C15: 11.1.1 | D15: 4 | E15: 4.2 | F15: • Información documentada de los mecanismos de supervisión permanente del personal en entrenamiento. | I15: X
A16: TALENTO HUMANO | B16: Todas las modalidades | C16: 11.1.1 | D16: 4 | E16: 4.3 | F16: • Estudio de capacidad instalada en el cual se determine el número máximo de estudiantes que simultáneamente puedan acceder por programa de formación y por jornada, para cada uno de los servicios que se utilicen como escenarios de práctica formativa en el área de la salud, estudio que debe ser elaborado teniendo en cuenta los “lineamientos de referencia para la asignación de cupos de estudiantes en escenarios clínicos” publicados por el Ministerio de Salud y Protección Social. | I16: X
A17: TALENTO HUMANO | B17: Todas las modalidades | C17: 11.1.1 | D17: 5 | F17: En los servicios de salud diferentes al servicio de consulta externa especializada de dolor y cuidado paliativo, donde se atienden pacientes con enfermedades terminales, crónicas, degenerativas e irreversibles, a los cuales se les decida como conducta médica; como parte del plan integral de cuidado que gestiona el equipo de salud, o por solicitud del paciente; el manejo del dolor y cuidado paliativo, el profesional de la medicina tratante cuenta con constancia de asistencia en las acciones de formación continua en el manejo del dolor y cuidado paliativo, cuando no sea especialista en dolor y cuidado paliativo | I17: X
A18: TALENTO HUMANO | B18: Todas las modalidades | C18: 11.1.1 | D18: 6 | F18: El talento humano en salud de los servicios de atención del parto, cuidado intensivo y cuidado intermedio neonatal, pediátrico y adultos, cuentan con constancia de asistencia en las acciones de formación continua para la gestión del duelo | I18: X | K18: CAPACITAR AUXILIARES DE ENFERMERIA, ENFERMEROS, TERAPEUTAS, MEDICOS Y ESPECIALISTAS | L18: TALENTO HUMANO/DIR MEDICA | M18: 44265
A19: TALENTO HUMANO | B19: Todas las modalidades | C19: 11.1.1 | D19: 7 | F19: En los servicios de salud donde se realicen imágenes diagnósticas por ultrasonido, cuenta con médico especialista en radiología e imágenes diagnósticas también podrán realizar imágenes diagnosticas aquellos médicos especialistas, quienes en su pensum o formación académica hayan adquirido los conocimientos del manejo e interpretación del espectro electromagnético, del ultrasonido especialmente, así como de las radiaciones ionizantes para establecer el diagnóstico o el tratamiento de las enfermedades inherentes a su especialidad, para lo cual deberá acreditar el respectivo certificado | I19: X
A20: TALENTO HUMANO | B20: Todas las modalidades | C20: 11.1.1 | D20: 8 | F20: Los profesionales de la medicina de los servicios de hospitalización de baja, mediana y alta complejidad, hospitalización paciente crónico con y sin ventilador, cuidados intensivos neonatales, pediátricos y adultos; urgencias y servicios del grupo quirúrgico en modalidad intramural, cuentan con certificación vigente de aprobación de la evaluación de competencias esenciales para el cuidado de la donante expedida por el Instituto Nacional de Salud | I20: X
A21: TALENTO HUMANO | B21: Todas las modalidades | C21: 11.1.1 | D21: 9 | F21: Las Instituciones Prestadoras de Servicios de Salud con servicios de cuidado intensivo pediátrico y adulto que adicionalmente habiliten el servicio quirúrgico de neurocirugía, tienen disponibilidad de coordinador operativo de trasplantes | I21: X
A22: TALENTO HUMANO | B22: Todas las modalidades | C22: 11.1.1 | D22: 10 | F22: El talento humano en salud de los servicios de salud de los grupos de consulta externa, internación y el servicio de urgencias, cuentan con constancia de asistencia en las acciones de formación continua en la atención integral en salud de las personas víctimas de violencia sexual | H22: X | J22: REALIZARLO LOS DOS PROFESIONALES
A23: TALENTO HUMANO | B23: Todas las modalidades | C23: 11.1.1 | D23: 11 | F23: El talento humano en salud de los servicios de transporte asistencial, atención prehospitalaria y urgencias, cuentan con constancia de asistencia en las acciones de formación continua en la atención a personas víctimas de ataques con agentes químicos | I23: X
A24: TALENTO HUMANO | B24: Todas las modalidades | C24: 11.1.1 | D24: 12 | F24: Cuando en un servicio de salud se realicen “pruebas en el punto de atención del paciente – (Point of Care Testing –POCT)”, el talento humano en salud que las realice, con excepción del profesional de bacteriología cuenta con constancia de asistencia en las acciones de formación continua en el manejo de estas pruebas | I24: X
A25: TALENTO HUMANO | B25: Todas las modalidades | C25: 11.1.1 | D25: 13 | F25: Procedimientos bajo sedación
A26: TALENTO HUMANO | B26: Todas las modalidades | C26: 11.1.1 | D26: 13 | E26: 13.1 | F26: • Cuando fuera de salas de cirugía se realicen procedimientos bajo sedación Grado I y II, adicional al profesional de salud que realiza el procedimiento, cuenta con: | I26: X
A27: TALENTO HUMANO | B27: Todas las modalidades | C27: 11.1.1 | D27: 13 | E27: 13.1.1 | F27: • Profesional de la medicina especialista en anestesiología, o profesional de la medicina o profesional de la odontología, según aplique, el cual será el encargado de administrar el medicamento y realizar el monitoreo continuo del paciente (registro de signos vitales y la respuesta a la sedación). | I27: X
A28: TALENTO HUMANO | B28: Todas las modalidades | C28: 11.1.1 | D28: 13 | E28: 13.1.2 | F28: • Todos los profesionales, a excepción del profesional de la medicina especialista en anestesiología, deben demostrar constancia de asistencia a curso de formación continua en soporte vital básico y sedación. | I28: X
A29: TALENTO HUMANO | B29: Todas las modalidades | C29: 11.1.1 | D29: 13 | E29: 13.1.3 | F29: • Para sedación con óxido nitroso en odontología, el profesional de la odontología cuenta con constancia de asistencia en las acciones de formación continua para el uso clínico y práctico de este gas. | I29: X
A30: TALENTO HUMANO | B30: Todas las modalidades | C30: 11.1.1 | D30: 13 | E30: 13.2 | F30: • Cuando fuera de salas de cirugía, se realicen procedimientos bajo sedación Grado III, adicional al profesional de salud que realiza el procedimiento, cuenta con profesional de la medicina con especialidad médico - quirúrgica, quien será el responsable de administrar la sedación. | I30: X
A31: TALENTO HUMANO | B31: Todas las modalidades | C31: 11.1.1 | D31: 13 | E31: 13.3 | F31: • Cuando fuera de salas de cirugía, se realicen procedimientos bajo sedación Grado IV, adicional al profesional de salud que realiza el procedimiento, cuenta con profesional de la medicina especialista en anestesiología, quien será el responsable de administrar la sedación | I31: X
A32: TALENTO HUMANO | B32: Todas las modalidades | C32: 11.1.1 | D32: 13 | E32: 13.4 | F32: • Cuenta con profesional de la medicina especialista en anestesiología cuando la atención se trate de pacientes con características particulares: poco colaboradores; edades extremas; con enfermedades severas: cardíacas, pulmonares, hepáticas, renales o del sistema nervioso central; cualquier alteración del grado de consciencia, con obesidad mórbida, con apnea del sueño, embarazadas, o quienes abusan del alcohol o de las drogas; antecedentes de sedación fallida o que presentaron efectos adversos a algún medicamento utilizado en la sedación, por tener un elevado riesgo de desarrollar complicaciones relacionadas con la sedación o analgesia. | I32: X
A33: TALENTO HUMANO | B33: Modalidad de telemedicina prestador remisor - prestador de referencia | C33: 11.1.1 | D33: 14 | F33: Adicional a los criterios del estándar de talento humano enunciados que le aplique, el talento humano en salud que presta directamente un servicio de salud bajo la modalidad de telemedicina cuenta con constancia de asistencia en las acciones de formación continua en el manejo de la tecnología utilizada por el prestador, los procesos y herramientas inherentes a la prestación de servicios bajo esta modalidad. | I33: X
A34: INFRAESTRUCTURA | B34: Edificaciones de uso exclusivo en salud | C34: 11.1.2 | D34: 1 | F34: Los servicios de salud de urgencias, de atención del parto, hospitalarios y de cirugía que realicen procedimientos quirúrgicos no ambulatorios, solo se pueden prestar en edificaciones de uso exclusivo de salud. | I34: X
A35: INFRAESTRUCTURA | B35: Edificaciones de uso exclusivo en salud | C35: 11.1.2 | D35: 2 | F35: Los servicios de salud de: urgencias, cirugía y del grupo de internación, así como en los servicios de salud donde se realice el proceso de esterilización, deben contar con ambiente de aseo de uso exclusivo | I35: X
A36: INFRAESTRUCTURA | B36: Edificaciones de uso exclusivo en salud | C36: 11.1.2 | D36: 3 | F36: Cuando en una edificación de uso exclusivo de salud funcione más de un prestador de servicios de salud con servicios de los grupos de consulta externa y apoyo diagnóstico y complementación terapéutica, cada prestador cuenta con infraestructura separada y delimitada físicamente. Se pueden compartir los siguientes ambientes y áreas: aseo, salas de espera y unidades sanitarias. | G36: X
A37: INFRAESTRUCTURA | B37: Edificaciones de uso exclusivo en salud | C37: 11.1.2 | D37: 4 | F37: Las edificaciones donde se presten servicios de salud de urgencias y del grupo de internación, cuentan con tanque de almacenamiento de agua para el consumo humano que garantice como mínimo una reserva de 24 horas de servicio continuo, calculado con base en el consumo de 600 lt por cama/camilla día | I37: X
A38: INFRAESTRUCTURA | B38: Edificaciones de uso exclusivo en salud | C38: 11.1.2 | D38: 5 | F38: Cuando el prestador de servicios de salud cuente con más de una infraestructura y estas se puedan vincular funcionalmente entre sí, lo harán mediante túnel o puente cubierto, o muro(s) colindante(s) que cuente(n) con acceso(s) que intercomunique(n) las infraestructuras, de uso exclusivo del prestador y adicionalmente cumplen con las siguientes características: | I38: X
A39: INFRAESTRUCTURA | B39: Edificaciones de uso exclusivo en salud | C39: 11.1.2 | D39: 5 | E39: 5.1 | F39: • Ancho que permita la movilización de camas, camillas, sillas de ruedas, equipos biomédicos y personal para el traslado de los pacientes en condiciones seguras. | I39: X
A40: INFRAESTRUCTURA | B40: Edificaciones de uso exclusivo en salud | C40: 11.1.2 | D40: 5 | E40: 5.2 | F40: • El piso del túnel o puente debe ser uniforme y de material antideslizante o con elementos que garanticen esta propiedad en todo su recorrido, con pasamanos a ambos lados y con protecciones laterales hacia espacios libres | I40: X
A41: INFRAESTRUCTURA | B41: Edificaciones de uso exclusivo en salud | C41: 11.1.2 | D41: 5 | E41: 5.3 | F41: • Lo anterior siempre y cuando la norma urbanística de la jurisdicción donde se localizan las sedes haya aprobado esta forma de vinculación funcional entre las mismas | I41: X
A42: INFRAESTRUCTURA | B42: Edificaciones de uso exclusivo en salud | C42: 11.1.2 | D42: 5 | E42: 5.4 | F42: • Esta edificación se podrá habilitar como una o varias sedes, de acuerdo con lo que determine el prestador de servicios de salud. Todo lo anterior siempre y cuando la norma urbanística de la jurisdicción donde se localizan las sedes haya aprobado esta forma de vinculación funcional entre las mismas | I42: X
A43: INFRAESTRUCTURA | B43: Edificaciones de uso mixto | C43: 11.1.2 | D43: 6 | F43: Cuando en una edificación de uso mixto funcione más de un prestador de servicios de salud, cada uno cuenta con infraestructura separada y delimitada físicamente. Se pueden compartir las salas de espera y las unidades sanitarias | I43: X
A44: INFRAESTRUCTURA | B44: Edificaciones de uso mixto | C44: 11.1.2 | D44: 7 | F44: En edificaciones de uso mixto pueden funcionar los prestadores de servicios de salud que oferten y presten servicios de los grupos de consulta externa, de apoyo diagnóstico y complementación terapéutica y los servicios del grupo quirúrgico que realicen exclusivamente procedimientos de cirugía ambulatoria | I44: X
A45: INFRAESTRUCTURA | B45: Edificaciones de uso exclusivo en salud y edificaciones de uso mixto | C45: 11.1.2 | D45: 8 | F45: Los prestadores de servicios de salud ubicados en edificaciones de hasta tres (3) pisos o niveles contados a partir del nivel más bajo construido, y que funcionen en segundo o tercer nivel o piso, cuentan con ascensor o rampa o sistema alternativo de elevación. El sistema alternativo de elevación no puede ser utilizado cuando se presten servicios hospitalarios, cirugía, urgencias, o de atención del parto | I45: X
A46: INFRAESTRUCTURA | B46: Edificaciones de uso exclusivo en salud y edificaciones de uso mixto | C46: 11.1.2 | D46: 9 | F46: Los sistemas alternativos de elevación deben cumplir con las siguientes condiciones | I46: X
A47: INFRAESTRUCTURA | B47: Edificaciones de uso exclusivo en salud y edificaciones de uso mixto | C47: 11.1.2 | D47: 9 | E47: 9.1 | F47: • Su ubicación no interfiera con el acceso y evacuación de los usuarios por las escaleras. | I47: X
A48: INFRAESTRUCTURA | B48: Edificaciones de uso exclusivo en salud y edificaciones de uso mixto | C48: 11.1.2 | D48: 9 | E48: 9.2 | F48: • Estén disponibles tanto para el acceso como para la evacuación de los usuarios. | I48: X
A49: INFRAESTRUCTURA | B49: Edificaciones de uso exclusivo en salud y edificaciones de uso mixto | C49: 11.1.2 | D49: 9 | E49: 9.3 | F49: • Su manejo sea autónomo. | I49: X
A50: INFRAESTRUCTURA | B50: Edificaciones de uso exclusivo en salud y edificaciones de uso mixto | C50: 11.1.2 | D50: 9 | E50: 9.4 | F50: • Garanticen seguridad durante su uso | I50: X
A51: INFRAESTRUCTURA | B51: Edificaciones de uso exclusivo en salud y edificaciones de uso mixto | C51: 11.1.2 | D51: 10 | F51: Las edificaciones con más de tres (3) pisos o niveles, contados a partir del nivel más bajo construido, cuentan con ascensor | I51: X
A52: INFRAESTRUCTURA | B52: Edificaciones de uso exclusivo en salud y edificaciones de uso mixto | C52: 11.1.2 | D52: 11 | F52: En edificaciones donde se presten servicios de los grupos de internación, atención del parto, quirúrgicos o urgencias para la movilización de pacientes en camilla, la cabina de los ascensores debe tener las dimensiones interiores mínimas de 2.20 de profundidad y de 1.20 de ancho, que garantice el traslado seguro de los pacientes. Las dimensiones de la cabina podrán ser variables en el o los ascensores que el prestador determine para la movilización de usuarios a pie o en sillas de ruedas | I52: X
A53: INFRAESTRUCTURA | B53: Edificaciones de uso exclusivo en salud y edificaciones de uso mixto | C53: 11.1.2 | D53: 12 | F53: Si se tienen escaleras o rampas, el piso debe ser uniforme y de material antideslizante o con elementos que garanticen esta propiedad en todo su recorrido, con pasamanos a uno o ambos lados y con protecciones laterales hacia espacios libres | H53: X | J53: INGRESO
A54: INFRAESTRUCTURA | B54: Edificaciones de uso exclusivo en salud y edificaciones de uso mixto | C54: 11.1.2 | D54: 13 | F54: Las edificaciones donde se presten servicios de salud cuentan con suministro de agua, energía eléctrica, conexión a la red de alcantarillado y sistemas de comunicaciones | G54: X
A55: INFRAESTRUCTURA | B55: Edificaciones de uso exclusivo en salud y edificaciones de uso mixto | C55: 11.1.2 | D55: 14 | F55: En edificaciones donde se presten servicios de cirugía, atención del parto, laboratorio clínico, urgencias, gestión pre transfusional, diálisis, hospitalarios, imágenes diagnósticas, vacunación, servicio farmacéutico y los que requieran cadena de frio, cuentan con planta eléctrica | I55: X
A56: INFRAESTRUCTURA | B56: Edificaciones de uso exclusivo en salud y edificaciones de uso mixto | C56: 11.1.2 | D56: 15 | F56: El prestador de servicios de salud que utilice equipos generadores de radiaciones ionizantes, cuenta con licencia de práctica médica vigente expedida por la entidad competente | H56: X | J56: VALIDAR FECHA DE VENCIMIENTO (X PERIAPICAL Y PANORAMICO)
A57: INFRAESTRUCTURA | B57: Edificaciones de uso exclusivo en salud y edificaciones de uso mixto | C57: 11.1.2 | D57: 16 | F57: El prestador de servicios de salud que utilice fuentes radioactivas cuenta con autorización vigente de empleo de material radiactivo, expedida por la entidad reguladora competente | G57: X
A58: INFRAESTRUCTURA | B58: Edificaciones de uso exclusivo en salud y edificaciones de uso mixto | C58: 11.1.2 | D58: 17 | F58: Cada prestador de servicios de salud debe contar con el respectivo concepto sanitario que dé cumplimiento a lo establecido en la normatividad sanitaria vigente en aspectos tales como agua para consumo humano, gestión de residuos, control de vectores, orden y aseo, condiciones locativas, entre otros. Este concepto será emitido por las autoridades sanitarias correspondientes, en el marco de sus competencias y debe considerar los servicios de apoyo como lavandería y servicio de alimentación. Cuando estos servicios de apoyo son contratados con terceros, dichos proveedores deben contar con el concepto sanitario correspondiente a la actividad de bienes y servicios que presta | H58: X | J58: USO DEL SUELO-
A59: INFRAESTRUCTURA | B59: Generalidades de los ambientes y las áreas de los servicios y sus características | C59: 11.1.2 | D59: 18 | F59: Las áreas y ambientes de todos los servicios de salud cuentan con ventilación e iluminación natural o artificia | G59: X
A60: INFRAESTRUCTURA | B60: Generalidades de los ambientes y las áreas de los servicios y sus características | C60: 11.1.2 | D60: 19 | F60: Las áreas de circulación de los servicios están libres de obstáculos de manera que permitan la movilización de pacientes, talento humano, usuarios y equipos biomédicos | G60: X
A61: INFRAESTRUCTURA | B61: Generalidades de los ambientes y las áreas de los servicios y sus características | C61: 11.1.2 | D61: 20 | F61: Los ambientes y áreas que hagan parte de cualquier servicio de salud, deben permitir la instalación y movilización de equipos biomédicos y personal necesarios para la atención del paciente en condiciones de rutina o de emergencia | G61: X
A62: INFRAESTRUCTURA | B62: Generalidades de los ambientes y las áreas de los servicios y sus características | C62: 11.1.2 | D62: 21 | F62: En los servicios del grupo quirúrgico, los ambientes y áreas clasificados como no restringidos, semi- restringidos y restringidos, deben señalizarse mediante la demarcación permanente en piso con material lavable y resistente al tráfico pesado, utilizando los siguientes colores: | J62: PORCELANATO EN CONSULTORIOS Y EN LAS OTRAS AREAS TIENE CERAMICA
A63: INFRAESTRUCTURA | B63: Generalidades de los ambientes y las áreas de los servicios y sus características | C63: 11.1.2 | D63: 21 | E63: 21.1 | F63: • Verde: Ambientes o áreas no restringidas | I63: X
A64: INFRAESTRUCTURA | B64: Generalidades de los ambientes y las áreas de los servicios y sus características | C64: 11.1.2 | D64: 21 | E64: 21.2 | F64: • Amarillo: Ambientes o áreas semi-restringidas | I64: X
A65: INFRAESTRUCTURA | B65: Generalidades de los ambientes y las áreas de los servicios y sus características | C65: 11.1.2 | D65: 21 | E65: 21.3 | F65: • Roja: Ambientes o áreas restringidas | I65: X
A66: INFRAESTRUCTURA | B66: Generalidades de los ambientes y las áreas de los servicios y sus características | C66: 11.1.2 | D66: 22 | F66: Cada uno de los pisos o niveles de la edificación cuenta con señalización y planos indicativos de las rutas de evacuación, salidas de emergencia y puntos de encuentro, visible al público en general | H66: X
A67: INFRAESTRUCTURA | B67: Generalidades de los ambientes y las áreas de los servicios y sus características | C67: 11.1.2 | D67: 23 | F67: Si el prestador de servicios de salud no tiene habilitado el servicio de gestión pre transfusional, pero realiza procedimientos de transfusión sanguínea en alguno de sus servicios habilitados, tiene disponibilidad de un área con iluminación y ventilación natural o artificial, para la ubicación de la dotación requerida de acuerdo con los componentes sanguíneos a transfundir | I67: X
A68: INFRAESTRUCTURA | B68: Generalidades de los ambientes y las áreas de los servicios y sus características | C68: 11.1.2 | D68: 24 | F68: Cuando un prestador de servicios de salud realice procedimientos bajo sedación fuera de salas de cirugía, tiene disponibilidad de área o ambiente para la recuperación de pacientes que puede ser la misma área o ambiente donde se realiza el procedimiento, garantizando la privacidad del usuario | I68: X
A69: INFRAESTRUCTURA | B69: Generalidades de los ambientes y las áreas de los servicios y sus características | C69: 11.1.2 | D69: 25 | F69: El prestador de servicios de salud que realice el proceso de esterilización, cuenta con: | H69: X
A70: INFRAESTRUCTURA | B70: Generalidades de los ambientes y las áreas de los servicios y sus características | C70: 11.1.2 | D70: 25 | E70: 25.1 | F70: • Ambiente o área de recibo de material contaminado. | H70: X
A71: INFRAESTRUCTURA | B71: Generalidades de los ambientes y las áreas de los servicios y sus características | C71: 11.1.2 | D71: 25 | E71: 25.2 | F71: • Ambiente o área de lavado. | H71: X
A72: INFRAESTRUCTURA | B72: Generalidades de los ambientes y las áreas de los servicios y sus características | C72: 11.1.2 | D72: 25 | E72: 25.3 | F72: • Ambiente o área de secado. | H72: X
A73: INFRAESTRUCTURA | B73: Generalidades de los ambientes y las áreas de los servicios y sus características | C73: 11.1.2 | D73: 25 | E73: 25.4 | F73: • Ambiente o área de empaque. | H73: X
A74: INFRAESTRUCTURA | B74: Generalidades de los ambientes y las áreas de los servicios y sus características | C74: 11.1.2 | D74: 25 | E74: 25.5 | F74: • Ambiente o área de esterilización | H74: X
A75: INFRAESTRUCTURA | B75: Generalidades de los ambientes y las áreas de los servicios y sus características | C75: 11.1.2 | D75: 25 | E75: 25.6 | F75: • Ambiente o área para almacenamiento del material estéril. | H75: X
A76: INFRAESTRUCTURA | B76: Generalidades de los ambientes y las áreas de los servicios y sus características | C76: 11.1.2 | D76: 25 | E76: 25.7 | F76: • Mesón de trabajo con poceta. | H76: X
A77: INFRAESTRUCTURA | B77: Generalidades de los ambientes y las áreas de los servicios y sus características | C77: 11.1.2 | D77: 25 | E77: 25.8 | F77: • Lavamanos, cuando el proceso se realice fuera del servicio de salud | G77: X
A78: INFRAESTRUCTURA | B78: Generalidades de los ambientes y las áreas de los servicios y sus características | C78: 11.1.2 | D78: 26 | F78: El prestador de servicios de salud que contrate el proceso de esterilización, dentro de su infraestructura cuenta con: | I78: X
A79: INFRAESTRUCTURA | B79: Generalidades de los ambientes y las áreas de los servicios y sus características | C79: 11.1.2 | D79: 26 | E79: 26.1 | F79: • Ambiente o área para lavado, limpieza y desinfección y entrega de material limpio al proveedor | I79: X
A80: INFRAESTRUCTURA | B80: Generalidades de los ambientes y las áreas de los servicios y sus características | C80: 11.1.2 | D80: 26 | E80: 26.2 | F80: • Ambiente o área para la recepción y almacenamiento de material estéril | I80: X
A81: INFRAESTRUCTURA | B81: Generalidades de los ambientes y las áreas de los servicios y sus características | C81: 11.1.2 | D81: 27 | F81: El prestador de servicios de salud que realice el proceso de esterilización en una central de esterilización cuenta con los siguientes ambientes y áreas señalizadas unidireccionales y de circulación restringida: | I81: X
A82: INFRAESTRUCTURA | B82: Generalidades de los ambientes y las áreas de los servicios y sus características | C82: 11.1.2 | D82: 27 | E82: 27.1 | F82: • Ambiente de recibo y lavado de material contaminado. | I82: X
A83: INFRAESTRUCTURA | B83: Generalidades de los ambientes y las áreas de los servicios y sus características | C83: 11.1.2 | D83: 27 | E83: 27.2 | F83: • Ambiente limpio con las siguientes áreas: | I83: X
A84: INFRAESTRUCTURA | B84: Generalidades de los ambientes y las áreas de los servicios y sus características | C84: 11.1.2 | D84: 27 | E84: 27.2.1 | F84: • Área de secado. | I84: X
A85: INFRAESTRUCTURA | B85: Generalidades de los ambientes y las áreas de los servicios y sus características | C85: 11.1.2 | D85: 27 | E85: 27.2.2 | F85: • Área de empaque. | I85: X
A86: INFRAESTRUCTURA | B86: Generalidades de los ambientes y las áreas de los servicios y sus características | C86: 11.1.2 | D86: 27 | E86: 27.2.3 | F86: • Área de esterilización | I86: X
A87: INFRAESTRUCTURA | B87: Generalidades de los ambientes y las áreas de los servicios y sus características | C87: 11.1.2 | D87: 27 | E87: 27.3 | F87: • Ambiente para almacenamiento del material estéril. | I87: X
A88: INFRAESTRUCTURA | B88: Características de los ambientes y áreas que pueden ser requeridos en varios servicios de salud | C88: 11.1.2 | D88: 28 | F88: Consultorio: Para efectos del presente Manual se definen los siguientes tipos de consultorios de acuerdo con la oferta de servicios: | I88: X
A89: INFRAESTRUCTURA | B89: Características de los ambientes y áreas que pueden ser requeridos en varios servicios de salud | C89: 11.1.2 | D89: 28 | E89: 28.1 | F89: Consultorio donde se realiza examen físico: Ambiente con mínimo 10 m2 (sin incluir la unidad sanitaria) que cuenta con: | I89: X
A90: INFRAESTRUCTURA | B90: Características de los ambientes y áreas que pueden ser requeridos en varios servicios de salud | C90: 11.1.2 | D90: 28 | E90: 28.1.1 | F90: • Área para entrevista. | I90: X
A91: INFRAESTRUCTURA | B91: Características de los ambientes y áreas que pueden ser requeridos en varios servicios de salud | C91: 11.1.2 | D91: 28 | E91: 28.1.2 | F91: • Área de examen. | I91: X
A92: INFRAESTRUCTURA | B92: Características de los ambientes y áreas que pueden ser requeridos en varios servicios de salud | C92: 11.1.2 | D92: 28 | E92: 28.1.3 | F92: • Lavamanos. No se exige adicional si el consultorio cuenta con unidad sanitaria. | I92: X
A93: INFRAESTRUCTURA | B93: Características de los ambientes y áreas que pueden ser requeridos en varios servicios de salud | C93: 11.1.2 | D93: 28 | E93: 28.1.4 | F93: • Las áreas están separadas entre sí por barrera física fija o móvil, con excepción de los consultorios del servicio de urgencias, optometría y oftalmología, donde no se requiere. | I93: X
A94: INFRAESTRUCTURA | B94: Características de los ambientes y áreas que pueden ser requeridos en varios servicios de salud | C94: 11.1.2 | D94: 28 | E94: 28.2 | F94: Consultorio donde se realizan procedimientos: Ambiente con mínimo 10 m2 (sin incluir la unidad sanitaria) que cuenta con: | H94: X
A95: INFRAESTRUCTURA | B95: Características de los ambientes y áreas que pueden ser requeridos en varios servicios de salud | C95: 11.1.2 | D95: 28 | E95: 28.2.1 | F95: • Área para entrevista | H95: X
A96: INFRAESTRUCTURA | B96: Características de los ambientes y áreas que pueden ser requeridos en varios servicios de salud | C96: 11.1.2 | D96: 28 | E96: 28.2.2 | F96: • Área de procedimientos. | H96: X
A97: INFRAESTRUCTURA | B97: Características de los ambientes y áreas que pueden ser requeridos en varios servicios de salud | C97: 11.1.2 | D97: 28 | E97: 28.2.3 | F97: • Las áreas están separadas entre sí por barrera física fija. | H97: X
A98: INFRAESTRUCTURA | B98: Características de los ambientes y áreas que pueden ser requeridos en varios servicios de salud | C98: 11.1.2 | D98: 28 | E98: 28.2.4 | F98: • Mesón de trabajo | H98: X
A99: INFRAESTRUCTURA | B99: Características de los ambientes y áreas que pueden ser requeridos en varios servicios de salud | C99: 11.1.2 | D99: 28 | E99: 28.2.5 | F99: • Poceta, cuando la requiera, según los procedimientos que el prestador documente en el estándar de procesos prioritarios. | H99: X
A100: INFRAESTRUCTURA | B100: Características de los ambientes y áreas que pueden ser requeridos en varios servicios de salud | C100: 11.1.2 | D100: 28 | E100: 28.2.6 | F100: • Lavamanos. No se exige adicional si el consultorio cuenta con una unidad sanitaria. | H100: X
A101: INFRAESTRUCTURA | B101: Características de los ambientes y áreas que pueden ser requeridos en varios servicios de salud | C101: 11.1.2 | D101: 28 | E101: 28.3 | F101: Consultorio odontológico con una unidad odontológica: Ambiente con mínimo 10 m2 (sin incluir la unidad sanitaria) que cuenta con: | H101: X
...

Sheet CE GENERAL
B1: CONSULTA EXTERNA GENERAL CONDICIONES DE HABILITACIÓN RESOLUCIÓN 3100/2019 | P1: ESTADO DE ACCIONES (Número de acciones y % por estado) | T1: ESTADO DE ACCIONES (Número de acciones y % por estado) | X1: ESTADO DE ACCIONES (Número de acciones y % por estado) | AB1: ESTADO DE ACCIONES (Número de acciones y % por estado) | AF1: ESTADO DE ACCIONES (Número de acciones y % por estado) | AJ1: ESTADO DE ACCIONES (Número de acciones y % por estado)
P2: SIN INICIAR | Q2: =COUNTIFS(R$10:R$501,P2) -> 0 | R2: =IFERROR(Q2/SUM(Q$2:Q$5),"") | T2: SIN INICIAR | U2: =COUNTIFS(V$10:V$501,T2) -> 0 | V2: =IFERROR(U2/SUM(U$2:U$5),"") | X2: SIN INICIAR | Y2: =COUNTIFS(Z$10:Z$501,X2) -> 0 | Z2: =IFERROR(Y2/SUM(Y$2:Y$5),"") | AB2: SIN INICIAR | AC2: =COUNTIFS(AD$10:AD$501,AB2) -> 0 | AD2: =IFERROR(AC2/SUM(AC$2:AC$5),"") | AF2: SIN INICIAR | AG2: =COUNTIFS(AH$10:AH$501,AF2) -> 0 | AH2: =IFERROR(AG2/SUM(AG$2:AG$5),"") | AJ2: SIN INICIAR | AK2: =COUNTIFS(AL$10:AL$501,AJ2) -> 0 | AL2: =IFERROR(AK2/SUM(AK$2:AK$5),"")
C3: TOTAL CUMPLE | D3: TOTAL NO CUMPLE | E3: TOTAL NO APLICA | P3: EN EJECUCION | Q3: =COUNTIFS(R$10:R$501,P3) -> 0 | R3: =IFERROR(Q3/SUM(Q$2:Q$5),"") | T3: EN EJECUCION | U3: =COUNTIFS(V$10:V$501,T3) -> 0 | V3: =IFERROR(U3/SUM(U$2:U$5),"") | X3: EN EJECUCION | Y3: =COUNTIFS(Z$10:Z$501,X3) -> 0 | Z3: =IFERROR(Y3/SUM(Y$2:Y$5),"") | AB3: EN EJECUCION | AC3: =COUNTIFS(AD$10:AD$501,AB3) -> 0 | AD3: =IFERROR(AC3/SUM(AC$2:AC$5),"") | AF3: EN EJECUCION | AG3: =COUNTIFS(AH$10:AH$501,AF3) -> 0 | AH3: =IFERROR(AG3/SUM(AG$2:AG$5),"") | AJ3: EN EJECUCION | AK3: =COUNTIFS(AL$10:AL$501,AJ3) -> 0 | AL3: =IFERROR(AK3/SUM(AK$2:AK$5),"")
A4: NUMERO DE CRITERIOS EVALUADOS | C4: =COUNTA(H10:H115) -> 0 | D4: =COUNTA(I10:I115) -> 0 | E4: =COUNTA(J10:J115) -> 0 | P4: CERRADA | Q4: =COUNTIFS(R$10:R$501,P4) -> 0 | R4: =IFERROR(Q4/SUM(Q$2:Q$5),"") | T4: CERRADA | U4: =COUNTIFS(V$10:V$501,T4) -> 0 | V4: =IFERROR(U4/SUM(U$2:U$5),"") | X4: CERRADA | Y4: =COUNTIFS(Z$10:Z$501,X4) -> 0 | Z4: =IFERROR(Y4/SUM(Y$2:Y$5),"") | AB4: CERRADA | AC4: =COUNTIFS(AD$10:AD$501,AB4) -> 0 | AD4: =IFERROR(AC4/SUM(AC$2:AC$5),"") | AF4: CERRADA | AG4: =COUNTIFS(AH$10:AH$501,AF4) -> 0 | AH4: =IFERROR(AG4/SUM(AG$2:AG$5),"") | AJ4: CERRADA | AK4: =COUNTIFS(AL$10:AL$501,AJ4) -> 0 | AL4: =IFERROR(AK4/SUM(AK$2:AK$5),"")
A5: CUMPLIMIENTO DEL SERVICIO EVALUADO | C5: =IFERROR(C4/(D4+C4),"") | P5: CANCELADA | Q5: =COUNTIFS(R$10:R$501,P5) -> 0 | R5: =IFERROR(Q5/SUM(Q$2:Q$5),"") | T5: CANCELADA | U5: =COUNTIFS(V$10:V$501,T5) -> 0 | V5: =IFERROR(U5/SUM(U$2:U$5),"") | X5: CANCELADA | Y5: =COUNTIFS(Z$10:Z$501,X5) -> 0 | Z5: =IFERROR(Y5/SUM(Y$2:Y$5),"") | AB5: CANCELADA | AC5: =COUNTIFS(AD$10:AD$501,AB5) -> 0 | AD5: =IFERROR(AC5/SUM(AC$2:AC$5),"") | AF5: CANCELADA | AG5: =COUNTIFS(AH$10:AH$501,AF5) -> 0 | AH5: =IFERROR(AG5/SUM(AG$2:AG$5),"") | AJ5: CANCELADA | AK5: =COUNTIFS(AL$10:AL$501,AJ5) -> 0 | AL5: =IFERROR(AK5/SUM(AK$2:AK$5),"")
P6: TOTAL | Q6: =SUM(Q2:Q5) -> 0 | T6: TOTAL | U6: =SUM(U2:U5) -> 0 | X6: TOTAL | Y6: =SUM(Y2:Y5) -> 0 | AB6: TOTAL | AC6: =SUM(AC2:AC5) -> 0 | AF6: TOTAL | AG6: =SUM(AG2:AG5) -> 0 | AJ6: TOTAL | AK6: =SUM(AK2:AK5) -> 0
P8: SEGUIMIENTO 1 - Fecha: | T8: SEGUIMIENTO 2 - Fecha: | X8: SEGUIMIENTO 3 - Fecha: | AB8: SEGUIMIENTO 4 - Fecha: | AF8: SEGUIMIENTO 5 - Fecha: | AJ8: SEGUIMIENTO 6 - Fecha:
A9: ESTANDAR | B9: COMPLEJIDAD | C9: MODALIDAD | D9: ARTICULO | E9: SECCIÓN | F9: APARTADO | G9: CRITERIO | H9: CUMPLE | I9: NO CUMPLE | J9: NO APLICA | K9: HALLAZGOS | M9: ACCIÓN PARA EL CUMPLIMIENTO | N9: RESPONSABLE | O9: FECHA LIMITE PARA IMPLEMENTAR | P9: SEGUIMIENTO 1 | R9: ESTADO DE LA ACCIÓN 1 | T9: SEGUIMIENTO 2 | V9: ESTADO DE LA ACCIÓN 2 | X9: SEGUIMIENTO 3 | Z9: ESTADO DE LA ACCIÓN 3 | AB9: SEGUIMIENTO 4 | AD9: ESTADO DE LA ACCIÓN 4 | AF9: SEGUIMIENTO 5 | AH9: ESTADO DE LA ACCIÓN 5 | AJ9: SEGUIMIENTO 6 | AL9: ESTADO DE LA ACCIÓN 6
A10: TALENTO HUMANO | B10: Baja | C10: Modalidades intramural, extramural unidad móvil, jornada de salud y domiciliaria | D10: 11.2.1 | E10: 1 | F10: 1 | G10: Cumple con los criterios que le sean aplicables de todos los servicios y adicionalmente,
A11: TALENTO HUMANO | B11: Baja | C11: Modalidades intramural, extramural unidad móvil, jornada de salud y domiciliaria | D11: 11.2.1 | E11: 2 | F11: 2 | G11: Cuenta con el profesional de la salud de acuerdo con el servicio a ofertar.
A12: TALENTO HUMANO | B12: Baja | C12: Modalidades intramural, extramural unidad móvil, jornada de salud y domiciliaria | D12: 11.2.1 | E12: 3 | F12: 3 | G12: Cuando se oferte la estrategia para el manejo de la Enfermedad Respiratoria Aguda (ERA), el servicio tiene disponibilidad de:
A13: TALENTO HUMANO | B13: Baja | C13: Modalidades intramural, extramural unidad móvil, jornada de salud y domiciliaria | D13: 11.2.1 | E13: 3 | F13: 3.1 | G13: • Profesional de la medicina.
A14: TALENTO HUMANO | B14: Baja | C14: Modalidades intramural, extramural unidad móvil, jornada de salud y domiciliaria | D14: 11.2.1 | E14: 3 | F14: 3.2 | G14: • Profesional de la enfermería o terapia respiratoria o fisioterapia.
A15: TALENTO HUMANO | B15: Baja | C15: Modalidad telemedicina: Categoría interactiva y no interactiva – prestador de referencia | D15: 11.2.1 | E15: 4 | G15: Cumple con los criterios que le sean aplicables de todos los servicios y adicionalmente, cuenta con:
A16: TALENTO HUMANO | B16: Baja | C16: Modalidad telemedicina: Categoría interactiva y no interactiva – prestador de referencia | D16: 11.2.1 | E16: 4 | F16: 4.1 | G16: • Profesional de la salud de acuerdo con el servicio a ofertar.
A17: TALENTO HUMANO | B17: Baja | C17: Modalidad telemedicina: Categoría telexperticia - prestador remisor | D17: 11.2.1 | E17: 5 | G17: Cumple con los criterios que le sean aplicables de todos los servicios y adicionalmente:
A18: TALENTO HUMANO | B18: Baja | C18: Modalidad telemedicina: Categoría telexperticia - prestador remisor | D18: 11.2.1 | E18: 5 | F18: 5.1 | G18: • Cuando se realice telexperticia entre profesionales de la salud cuenta con el profesional de la salud de acuerdo con el servicio a ofertar.
A19: TALENTO HUMANO | B19: Baja | C19: Modalidad telemedicina: Categoría telexperticia - prestador remisor | D19: 11.2.1 | E19: 5 | F19: 5.2 | G19: • Cuando realice telexperticia entre personal de salud no profesional y un profesional de la salud, el prestador remisor cuenta con técnico, tecnólogo o auxiliar que atiende presencialmente al usuario.
A20: TALENTO HUMANO | B20: Baja | C20: Modalidad telemedicina: Categoría telexperticia - prestador de referencia | D20: 11.2.1 | E20: 6 | G20: Cumple con los criterios que le sean aplicables de todos los servicios y adicionalmente cuenta con profesional de la salud que atiende a distancia, de acuerdo con el servicio a ofertar
A21: TALENTO HUMANO | B21: Baja | C21: Modalidad telemedicina: Categoría telemonitoreo - prestador de referencia | D21: 11.2.1 | E21: 7 | G21: Cumple con los criterios que le sean aplicables de todos los servicios y adicionalmente cuenta con el personal de salud profesional que se requiera para realizar el telemonitoreo de acuerdo con lo documentado por el prestador de servicios de salud en el estándar de procesos prioritarios
A22: INFRAESTRUCTURA | B22: Baja | C22: Modalidad intramural | D22: 11.2.1 | E22: 8 | G22: Cumple con los criterios que le sean aplicables de todos los servicios y adicionalmente,
A23: INFRAESTRUCTURA | B23: Baja | C23: Modalidad intramural | D23: 11.2.1 | E23: 9 | G23: Cuenta con:
A24: INFRAESTRUCTURA | B24: Baja | C24: Modalidad intramural | D24: 11.2.1 | E24: 9 | F24: 9.1 | G24: • El tipo de ambiente o consultorio de acuerdo con la oferta, así:
A25: INFRAESTRUCTURA | B25: Baja | C25: Modalidad intramural | D25: 11.2.1 | E25: 9 | F25: 9.1.1 | G25: • Consultorio donde se realiza examen físico.
A26: INFRAESTRUCTURA | B26: Baja | C26: Modalidad intramural | D26: 11.2.1 | E26: 9 | F26: 9.1.2 | G26: • Ambiente de entrevista donde no se realiza examen físico ni procedimientos.
A27: INFRAESTRUCTURA | B27: Baja | C27: Modalidad intramural | D27: 11.2.1 | E27: 9 | F27: 9.1.3 | G27: • Consultorio donde se realizan procedimientos.
A28: INFRAESTRUCTURA | B28: Baja | C28: Modalidad intramural | D28: 11.2.1 | E28: 9 | F28: 9.1.4 | G28: • Consultorio odontológico con una unidad odontológica o más.
A29: INFRAESTRUCTURA | B29: Baja | C29: Modalidad intramural | D29: 11.2.1 | E29: 9 | F29: 9.2 | G29: • Sala de procedimientos, cuando se requiera.
A30: INFRAESTRUCTURA | B30: Baja | C30: Modalidad intramural | D30: 11.2.1 | E30: 10 | G30: Disponibilidad de:
A31: INFRAESTRUCTURA | B31: Baja | C31: Modalidad intramural | D31: 11.2.1 | E31: 10 | F31: 10.1 | G31: • Sala de espera.
A32: INFRAESTRUCTURA | B32: Baja | C32: Modalidad intramural | D32: 11.2.1 | E32: 10 | F32: 10.2 | G32: Mínimo una (1) unidad sanitaria de uso mixto, apta para personas con movilidad reducida, cuando el prestador cuente con hasta dos consultorios o ambientes de entrevista.
A33: INFRAESTRUCTURA | B33: Baja | C33: Modalidad intramural | D33: 11.2.1 | E33: 10 | F33: 10.3 | G33: • Mínimo una (1) unidad sanitaria discriminada por sexo apta para personas con movilidad reducida, o batería sanitaria discriminada por sexo con mínimo una (1) unidad sanitaria apta para personas con movilidad reducida, cuando el prestador cuente con más de dos consultorios o ambientes de entrevista.
A34: INFRAESTRUCTURA | B34: Baja | C34: Modalidad intramural | D34: 11.2.1 | E34: 11 | G34: Cuando se oferte la estrategia para el manejo de la Enfermedad Respiratoria Aguda (ERA), el ambiente cuenta con:
A35: INFRAESTRUCTURA | B35: Baja | C35: Modalidad intramural | D35: 11.2.1 | E35: 11 | F35: 11.1 | G35: • Lavamanos.
A36: INFRAESTRUCTURA | B36: Baja | C36: Modalidad intramural | D36: 11.2.1 | E36: 11 | F36: 11.2 | G36: • Mesón de trabajo.
A37: INFRAESTRUCTURA | B37: Baja | C37: Modalidad intramural | D37: 11.2.1 | E37: 11 | F37: 11.3 | G37: • Poceta, cuando la requiera, según los procedimientos que documente.
A38: INFRAESTRUCTURA | B38: Baja | C38: Modalidad intramural | D38: 11.2.1 | E38: 11 | F38: 11.4 | G38: • Barrera física móvil o fija, para separación entre sillas.
A39: INFRAESTRUCTURA | B39: Baja | C39: Modalidad intramural | D39: 11.2.1 | E39: 12 | G39: Cuando se realicen terapias e intervenciones grupales para la atención de personas con consumo de sustancias psicoactivas o alteraciones en salud mental, cuenta con ambiente con dimensión variable para su realización.
A40: INFRAESTRUCTURA | B40: Baja | C40: Modalidad intramural | D40: 11.2.1 | E40: 13 | G40: Cuando se realicen actividades grupales de educación para la salud, tiene disponibilidad de un ambiente con dimensión variable
A41: INFRAESTRUCTURA | B41: Baja | C41: Modalidad extramural: unidad móvil, jornada de salud, y domiciliaria | D41: 11.2.1 | E41: 14 | G41: Cumple con los criterios que le sean aplicables de todos los servicios
A42: INFRAESTRUCTURA | B42: Baja | C42: Modalidad telemedicina: Categoría interactiva y no interactiva – prestador de referencia | D42: 11.2.1 | E42: 15 | G42: Cumple con los criterios que le sean aplicables de todos los servicios
A43: INFRAESTRUCTURA | B43: Baja | C43: Modalidad telemedicina: Categoría telexperticia - prestador remisor | D43: 11.2.1 | E43: 16 | G43: Cumple con los criterios establecidos en el servicio de consulta externa genera
A44: INFRAESTRUCTURA | B44: Baja | C44: Modalidad telemedicina: Categoría telexperticia - prestador de referencia | D44: 11.2.1 | E44: 17 | G44: Cumple con los criterios que le sean aplicables de todos los servicios
A45: INFRAESTRUCTURA | B45: Baja | C45: Modalidad telemedicina: Categoría telemonitoreo - prestador de referencia | D45: 11.2.1 | E45: 18 | G45: Cumple con los criterios que le sean aplicables de todos los servicios.
A46: DOTACIÓN | B46: Baja | C46: Modalidad intramural | D46: 11.2.1 | E46: 19 | G46: El consultorio donde se realice examen físico cumple con los criterios que le sean aplicables de todos los servicios y adicionalmente cuenta con:
A47: DOTACIÓN | B47: Baja | C47: Modalidad intramural | D47: 11.2.1 | E47: 19 | F47: 19.1 | G47: • Camilla fija.
A48: DOTACIÓN | B48: Baja | C48: Modalidad intramural | D48: 11.2.1 | E48: 19 | F48: 19.2 | G48: • Escalerilla.
A49: DOTACIÓN | B49: Baja | C49: Modalidad intramural | D49: 11.2.1 | E49: 19 | F49: 19.3 | G49: • Tensiómetro para adulto o pediátrico según la oferta del servicio.
A50: DOTACIÓN | B50: Baja | C50: Modalidad intramural | D50: 11.2.1 | E50: 19 | F50: 19.4 | G50: • Fonendoscopio para adulto o pediátrico según la oferta del servicio.
A51: DOTACIÓN | B51: Baja | C51: Modalidad intramural | D51: 11.2.1 | E51: 19 | F51: 19.5 | G51: • Equipo de órganos de los sentidos.
A52: DOTACIÓN | B52: Baja | C52: Modalidad intramural | D52: 11.2.1 | E52: 19 | F52: 19.6 | G52: • Martillo de reflejos.
A53: DOTACIÓN | B53: Baja | C53: Modalidad intramural | D53: 11.2.1 | E53: 19 | F53: 19.7 | G53: • Tallímetro o infantómetro según la oferta del servicio.
A54: DOTACIÓN | B54: Baja | C54: Modalidad intramural | D54: 11.2.1 | E54: 19 | F54: 19.8 | G54: • Cinta métrica.
A55: DOTACIÓN | B55: Baja | C55: Modalidad intramural | D55: 11.2.1 | E55: 19 | F55: 19.9 | G55: • Báscula grado médico o pesa bebé, según la oferta del servicio.
A56: DOTACIÓN | B56: Baja | C56: Modalidad intramural | D56: 11.2.1 | E56: 19 | F56: 19.10 | G56: • Termómetro, cuando lo requiera.
A57: DOTACIÓN | B57: Baja | C57: Modalidad intramural | D57: 11.2.1 | E57: 19 | F57: 19.11 | G57: • Negatoscopio cuando se requiera o sistema de visualización según la tecnología utilizada por el prestador.
A58: DOTACIÓN | B58: Baja | C58: Modalidad intramural | D58: 11.2.1 | E58: 20 | G58: Para el consultorio donde no se realiza examen físico ni procedimientos, no se exige la dotación anterior. El prestador de servicios de salud cuenta con la dotación necesaria de acuerdo con lo documentado en el estándar de procesos prioritarios.
A59: DOTACIÓN | B59: Baja | C59: Modalidad intramural | D59: 11.2.1 | E59: 21 | G59: El consultorio donde se realicen procedimientos cuenta con la dotación mínima definida para el consultorio donde se realice examen físico y adicionalmente cuenta con la dotación necesaria para realizar los procedimientos documentados en el estándar de procesos prioritarios.
A60: DOTACIÓN | B60: Baja | C60: Modalidad intramural | D60: 11.2.1 | E60: 22 | G60: Si realiza procedimientos en sala de procedimientos, cuenta con:
A61: DOTACIÓN | B61: Baja | C61: Modalidad intramural | D61: 11.2.1 | E61: 22 | F61: 22.1 | G61: • Dotación necesaria para realizar los procedimientos documentados en el estándar de procesos prioritarios.
A62: DOTACIÓN | B62: Baja | C62: Modalidad intramural | D62: 11.2.1 | E62: 22 | F62: 22.2 | G62: • Camilla con barandas, ruedas y freno., cuando los procedimientos requieran estas características.
A63: DOTACIÓN | B63: Baja | C63: Modalidad intramural | D63: 11.2.1 | E63: 23 | F63: 23 | G63: El consultorio odontológico cuenta con:
A64: DOTACIÓN | B64: Baja | C64: Modalidad intramural | D64: 11.2.1 | E64: 23 | F64: 23.1 | G64: • Unidad odontológica fija.
A65: DOTACIÓN | B65: Baja | C65: Modalidad intramural | D65: 11.2.1 | E65: 23 | F65: 23.2 | G65: • Lámpara de fotocurado o amalgamador según la oferta del servicio.
A66: DOTACIÓN | B66: Baja | C66: Modalidad intramural | D66: 11.2.1 | E66: 23 | F66: 23.3 | G66: • Negatoscopio cuando se requiera o sistema de visualización según la tecnología utilizada por el prestador.
A67: DOTACIÓN | B67: Baja | C67: Modalidad intramural | D67: 11.2.1 | E67: 23 | F67: 23.4 | G67: • Sistema de succión que podrá estar incorporado a la unidad odontológica.
A68: DOTACIÓN | B68: Baja | C68: Modalidad intramural | D68: 11.2.1 | E68: 23 | F68: 23.5 | G68: • Compresor de aire para uso odontológico.
A69: DOTACIÓN | B69: Baja | C69: Modalidad intramural | D69: 11.2.1 | E69: 23 | F69: 23.6 | G69: • Instrumental básico definido por el prestador de acuerdo con la oferta del servicio (adultos o pediatría), la capacidad instalada, los procedimientos documentados en el estándar de procesos prioritarios y la técnica de esterilización y numero de ciclos de esterilización al día.
A70: DOTACIÓN | B70: Baja | C70: Modalidad intramural | D70: 11.2.1 | E70: 23 | F70: 23.7 | G70: • Cuando se realice el proceso de esterilización dentro del servicio, cuenta con equipos para esterilización según los procedimientos realizados y documentados en el estándar de procesos prioritarios.
A71: DOTACIÓN | B71: Baja | C71: Modalidad extramural: unidad móvil, jornada de salud, y domiciliaria | D71: 11.2.1 | E71: 24 | G71: Para la consulta externa de medicina general, cuenta con:
A72: DOTACIÓN | B72: Baja | C72: Modalidad extramural: unidad móvil, jornada de salud, y domiciliaria | D72: 11.2.1 | E72: 24 | F72: 24.1 | G72: • Fonendoscopio para adulto o pediátrico según la oferta del servicio
A73: DOTACIÓN | B73: Baja | C73: Modalidad extramural: unidad móvil, jornada de salud, y domiciliaria | D73: 11.2.1 | E73: 24 | F73: 24.2 | G73: • Tensiómetro para adulto o pediátrico según la oferta del servicio
A74: DOTACIÓN | B74: Baja | C74: Modalidad extramural: unidad móvil, jornada de salud, y domiciliaria | D74: 11.2.1 | E74: 24 | F74: 24.3 | G74: • Equipo de órganos de los sentidos.
A75: DOTACIÓN | B75: Baja | C75: Modalidad extramural: unidad móvil, jornada de salud, y domiciliaria | D75: 11.2.1 | E75: 24 | F75: 24.4 | G75: • Oxímetro
A76: DOTACIÓN | B76: Baja | C76: Modalidad extramural: unidad móvil, jornada de salud, y domiciliaria | D76: 11.2.1 | E76: 24 | F76: 24.5 | G76: • Glucómetro.
A77: DOTACIÓN | B77: Baja | C77: Modalidad extramural: unidad móvil, jornada de salud, y domiciliaria | D77: 11.2.1 | E77: 24 | F77: 24.6 | G77: • Martillo de reflejos.
A78: DOTACIÓN | B78: Baja | C78: Modalidad extramural: unidad móvil, jornada de salud, y domiciliaria | D78: 11.2.1 | E78: 24 | F78: 24.7 | G78: • Termómetro, cuanto lo requiera.
A79: DOTACIÓN | B79: Baja | C79: Modalidad extramural: unidad móvil, jornada de salud, y domiciliaria | D79: 11.2.1 | E79: 24 | F79: 24.8 | G79: • Cinta métrica.
A80: DOTACIÓN | B80: Baja | C80: Modalidad extramural: unidad móvil, jornada de salud, y domiciliaria | D80: 11.2.1 | E80: 24 | F80: 24.9 | G80: • Báscula grado médico o pesa bebé, según la oferta del servicio.
A81: DOTACIÓN | B81: Baja | C81: Modalidad extramural: unidad móvil, jornada de salud, y domiciliaria | D81: 11.2.1 | E81: 25 | G81: El prestador de servicios de salud cuenta con la dotación necesaria para realizar los procedimientos documentados en el estándar de procesos prioritarios.
A82: DOTACIÓN | B82: Baja | C82: Modalidad extramural: unidad móvil, jornada de salud, y domiciliaria | D82: 11.2.1 | E82: 26 | G82: Para la consulta odontológica, cuenta con:
A83: DOTACIÓN | B83: Baja | C83: Modalidad extramural: unidad móvil, jornada de salud, y domiciliaria | D83: 11.2.1 | E83: 26 | F83: 26.1 | G83: • Unidad odontológica portátil.
A84: DOTACIÓN | B84: Baja | C84: Modalidad extramural: unidad móvil, jornada de salud, y domiciliaria | D84: 11.2.1 | E84: 26 | F84: 26.2 | G84: • Lámpara de fotocurado o amalgamador según la oferta del servicio.
A85: DOTACIÓN | B85: Baja | C85: Modalidad extramural: unidad móvil, jornada de salud, y domiciliaria | D85: 11.2.1 | E85: 26 | F85: 26.3 | G85: • Negatoscopio cuando se requiera o sistema de visualización según la tecnología utilizada por el prestador.
A86: DOTACIÓN | B86: Baja | C86: Modalidad extramural: unidad móvil, jornada de salud, y domiciliaria | D86: 11.2.1 | E86: 26 | F86: 26.4 | G86: • Sistema de succión que podrá estar incorporado a la unidad odontológica.
A87: DOTACIÓN | B87: Baja | C87: Modalidad extramural: unidad móvil, jornada de salud, y domiciliaria | D87: 11.2.1 | E87: 26 | F87: 26.5 | G87: • Compresor de aire para uso odontológico.
A88: DOTACIÓN | B88: Baja | C88: Modalidad extramural: unidad móvil, jornada de salud, y domiciliaria | D88: 11.2.1 | E88: 26 | F88: 26.6 | G88: • Instrumental básico estéril definido por el prestador de acuerdo con la oferta del servicio (adultos o pediatría), la capacidad instalada y los procedimientos documentados en el estándar de procesos prioritarios.
A89: DOTACIÓN | B89: Baja | C89: Modalidad extramural: unidad móvil, jornada de salud, y domiciliaria | D89: 11.2.1 | E89: 27 | G89: Cumple con los criterios que le sean aplicables de todos los servicios.
A90: DOTACIÓN | B90: Baja | C90: Modalidad telemedicina: Categoría interactiva y no interactiva – prestador de referencia | D90: 11.2.1 | E90: 28 | G90: Cumple con los criterios que le sean aplicables de todos los servicios.
A91: DOTACIÓN | B91: Baja | C91: Modalidad telemedicina: Categoría telexperticia - prestador remisor | D91: 11.2.1 | E91: 29 | G91: Cumple con los criterios que le sean aplicables de todos los servicios y los establecidos en el servicio de consulta externa general.
A92: DOTACIÓN | B92: Baja | C92: Modalidad telemedicina: Categoría telexperticia - prestador de referencia | D92: 11.2.1 | E92: 30 | G92: Cumple con los criterios que le sean aplicables de todos los servicios
A93: DOTACIÓN | B93: Baja | C93: Modalidad telemedicina: Categoría telemonitoreo - prestador de referencia | D93: 11.2.1 | E93: 31 | G93: Cumple con los criterios que le sean aplicables de todos los servicios
A94: MEDICAMENTOS, DM E INSUMOS | B94: Baja | C94: Modalidades intramural, extramural unidad móvil, jornada de salud y domiciliaria | D94: 11.2.1 | E94: 32 | G94: Cumple con los criterios que le sean aplicables de todos los servicios
A95: MEDICAMENTOS, DM E INSUMOS | B95: Baja | C95: Modalidades intramural, extramural unidad móvil, jornada de salud y domiciliaria | D95: 11.2.1 | E95: 33 | G95: Cuando se oferte la estrategia para el manejo de la Enfermedad Respiratoria Aguda (ERA), el ambiente cuenta con oxígeno medicinal
A96: MEDICAMENTOS, DM E INSUMOS | B96: Baja | C96: Modalidad telemedicina. Categoría interactiva y no interactiva – prestador de referencia Categoría telexperticia - prestador remisor- prestador de referencia Categoría telemonitoreo - prestador de referencia | D96: 11.2.1 | E96: 34 | G96: Cumple con los criterios que le sean aplicables de todos los servicios.
A97: PROCESOS PRIORITARIOS | B97: Baja | C97: Modalidades intramural, extramural unidad móvil, jornada de salud y domiciliaria | D97: 11.2.1 | E97: 35 | G97: Cumple con los criterios que le sean aplicables de todos los servicios y adicionalmente cuando se realicen procedimientos, cuenta con la siguiente información documentada:
A98: PROCESOS PRIORITARIOS | B98: Baja | C98: Modalidades intramural, extramural unidad móvil, jornada de salud y domiciliaria | D98: 11.2.1 | E98: 35 | F98: 35.1 | G98: • Procedimientos que se pueden realizar, incluyendo aquellos que requieran anestesia local y no impliquen anestesia regional ni general.
A99: PROCESOS PRIORITARIOS | B99: Baja | C99: Modalidades intramural, extramural unidad móvil, jornada de salud y domiciliaria | D99: 11.2.1 | E99: 35 | F99: 35.2 | G99: • Información al paciente sobre:
A100: PROCESOS PRIORITARIOS | B100: Baja | C100: Modalidades intramural, extramural unidad móvil, jornada de salud y domiciliaria | D100: 11.2.1 | E100: 35 | F100: 35.2.1 | G100: • Preparación.
A101: PROCESOS PRIORITARIOS | B101: Baja | C101: Modalidades intramural, extramural unidad móvil, jornada de salud y domiciliaria | D101: 11.2.1 | E101: 35 | F101: 35.2.2 | G101: • Recomendaciones post procedimiento.
...

Sheet CE ESP
B1: CONSULTA EXTERNA ESPECIALIZADA CONDICIONES DE HABILITACIÓN RESOLUCIÓN 3100/2019 | P1: ESTADO DE ACCIONES (Número de acciones y % por estado) | T1: ESTADO DE ACCIONES (Número de acciones y % por estado) | X1: ESTADO DE ACCIONES (Número de acciones y % por estado) | AB1: ESTADO DE ACCIONES (Número de acciones y % por estado) | AF1: ESTADO DE ACCIONES (Número de acciones y % por estado) | AJ1: ESTADO DE ACCIONES (Número de acciones y % por estado)
P2: SIN INICIAR | Q2: =COUNTIFS(R$10:R$501,P2) -> 0 | R2: =IFERROR(Q2/SUM(Q$2:Q$5),"") | T2: SIN INICIAR | U2: =COUNTIFS(V$10:V$501,T2) -> 0 | V2: =IFERROR(U2/SUM(U$2:U$5),"") | X2: SIN INICIAR | Y2: =COUNTIFS(Z$10:Z$501,X2) -> 0 | Z2: =IFERROR(Y2/SUM(Y$2:Y$5),"") | AB2: SIN INICIAR | AC2: =COUNTIFS(AD$10:AD$501,AB2) -> 0 | AD2: =IFERROR(AC2/SUM(AC$2:AC$5),"") | AF2: SIN INICIAR | AG2: =COUNTIFS(AH$10:AH$501,AF2) -> 0 | AH2: =IFERROR(AG2/SUM(AG$2:AG$5),"") | AJ2: SIN INICIAR | AK2: =COUNTIFS(AL$10:AL$501,AJ2) -> 0 | AL2: =IFERROR(AK2/SUM(AK$2:AK$5),"")
C3: TOTAL CUMPLE | D3: TOTAL NO CUMPLE | E3: TOTAL NO APLICA | P3: EN EJECUCION | Q3: =COUNTIFS(R$10:R$501,P3) -> 0 | R3: =IFERROR(Q3/SUM(Q$2:Q$5),"") | T3: EN EJECUCION | U3: =COUNTIFS(V$10:V$501,T3) -> 0 | V3: =IFERROR(U3/SUM(U$2:U$5),"") | X3: EN EJECUCION | Y3: =COUNTIFS(Z$10:Z$501,X3) -> 0 | Z3: =IFERROR(Y3/SUM(Y$2:Y$5),"") | AB3: EN EJECUCION | AC3: =COUNTIFS(AD$10:AD$501,AB3) -> 0 | AD3: =IFERROR(AC3/SUM(AC$2:AC$5),"") | AF3: EN EJECUCION | AG3: =COUNTIFS(AH$10:AH$501,AF3) -> 0 | AH3: =IFERROR(AG3/SUM(AG$2:AG$5),"") | AJ3: EN EJECUCION | AK3: =COUNTIFS(AL$10:AL$501,AJ3) -> 0 | AL3: =IFERROR(AK3/SUM(AK$2:AK$5),"")
A4: NUMERO DE CRITERIOS EVALUADOS | C4: =COUNTA(H10:H47) -> 2 | D4: =COUNTA(I10:I47) -> 0 | E4: =COUNTA(J10:J47) -> 5 | P4: CERRADA | Q4: =COUNTIFS(R$10:R$501,P4) -> 0 | R4: =IFERROR(Q4/SUM(Q$2:Q$5),"") | T4: CERRADA | U4: =COUNTIFS(V$10:V$501,T4) -> 0 | V4: =IFERROR(U4/SUM(U$2:U$5),"") | X4: CERRADA | Y4: =COUNTIFS(Z$10:Z$501,X4) -> 0 | Z4: =IFERROR(Y4/SUM(Y$2:Y$5),"") | AB4: CERRADA | AC4: =COUNTIFS(AD$10:AD$501,AB4) -> 0 | AD4: =IFERROR(AC4/SUM(AC$2:AC$5),"") | AF4: CERRADA | AG4: =COUNTIFS(AH$10:AH$501,AF4) -> 0 | AH4: =IFERROR(AG4/SUM(AG$2:AG$5),"") | AJ4: CERRADA | AK4: =COUNTIFS(AL$10:AL$501,AJ4) -> 0 | AL4: =IFERROR(AK4/SUM(AK$2:AK$5),"")
A5: CUMPLIMIENTO DEL SERVICIO EVALUADO | C5: =IFERROR(C4/(D4+C4),"") -> 1 | P5: CANCELADA | Q5: =COUNTIFS(R$10:R$501,P5) -> 0 | R5: =IFERROR(Q5/SUM(Q$2:Q$5),"") | T5: CANCELADA | U5: =COUNTIFS(V$10:V$501,T5) -> 0 | V5: =IFERROR(U5/SUM(U$2:U$5),"") | X5: CANCELADA | Y5: =COUNTIFS(Z$10:Z$501,X5) -> 0 | Z5: =IFERROR(Y5/SUM(Y$2:Y$5),"") | AB5: CANCELADA | AC5: =COUNTIFS(AD$10:AD$501,AB5) -> 0 | AD5: =IFERROR(AC5/SUM(AC$2:AC$5),"") | AF5: CANCELADA | AG5: =COUNTIFS(AH$10:AH$501,AF5) -> 0 | AH5: =IFERROR(AG5/SUM(AG$2:AG$5),"") | AJ5: CANCELADA | AK5: =COUNTIFS(AL$10:AL$501,AJ5) -> 0 | AL5: =IFERROR(AK5/SUM(AK$2:AK$5),"")
P6: TOTAL | Q6: =SUM(Q2:Q5) -> 0 | T6: TOTAL | U6: =SUM(U2:U5) -> 0 | X6: TOTAL | Y6: =SUM(Y2:Y5) -> 0 | AB6: TOTAL | AC6: =SUM(AC2:AC5) -> 0 | AF6: TOTAL | AG6: =SUM(AG2:AG5) -> 0 | AJ6: TOTAL | AK6: =SUM(AK2:AK5) -> 0
P8: SEGUIMIENTO 1 - Fecha: | T8: SEGUIMIENTO 2 - Fecha: | X8: SEGUIMIENTO 3 - Fecha: | AB8: SEGUIMIENTO 4 - Fecha: | AF8: SEGUIMIENTO 5 - Fecha: | AJ8: SEGUIMIENTO 6 - Fecha:
A9: ESTANDAR | B9: COMPLEJIDAD | C9: MODALIDAD | D9: ARTICULO | E9: SECCIÓN | F9: APARTADO | G9: CRITERIO | H9: CUMPLE | I9: NO CUMPLE | J9: NO APLICA | K9: HALLAZGOS | M9: ACCIÓN PARA EL CUMPLIMIENTO | N9: RESPONSABLE | O9: FECHA LIMITE PARA IMPLEMENTAR | P9: SEGUIMIENTO 1 | R9: ESTADO DE LA ACCIÓN 1 | T9: SEGUIMIENTO 2 | V9: ESTADO DE LA ACCIÓN 2 | X9: SEGUIMIENTO 3 | Z9: ESTADO DE LA ACCIÓN 3 | AB9: SEGUIMIENTO 4 | AD9: ESTADO DE LA ACCIÓN 4 | AF9: SEGUIMIENTO 5 | AH9: ESTADO DE LA ACCIÓN 5 | AJ9: SEGUIMIENTO 6 | AL9: ESTADO DE LA ACCIÓN 6
A10: TALENTO HUMANO | B10: Mediana | C10: Modalidades intramural, extramural unidad móvil, jornada de salud y domiciliaria | D10: 11.2.2 | E10: 1 | G10: Cumple con los criterios definidos para el servicio de consulta externa general y adicionalmente cuenta con:
A11: TALENTO HUMANO | B11: Mediana | C11: Modalidades intramural, extramural unidad móvil, jornada de salud y domiciliaria | D11: 11.2.2 | E11: 1 | F11: 1.1 | G11: • Profesional de la salud con título de especialista, según los programas académicos autorizados por el Ministerio de Educación Nacional.
A12: TALENTO HUMANO | B12: Mediana | C12: Modalidades intramural, extramural unidad móvil, jornada de salud y domiciliaria | D12: 11.2.2 | E12: 1 | F12: 1.2 | G12: • Para medicina alternativa y terapias alternativas y complementarias, cuenta con profesional de la salud con título de especialista en el ámbito de su disciplina, para lo cual deberá acreditar la respectiva certificación académica de esa norma de competencia, expedida por una institución de educación superior legalmente reconocida por el Estado y de acuerdo con lo documentado por el prestador de servicios de salud en el estándar de procesos prioritarios.
A13: TALENTO HUMANO | B13: Mediana | C13: Modalidad telemedicina: Categoría interactiva y no interactiva – prestador de referencia | D13: 11.2.2 | E13: 2 | G13: Cumple con los criterios que le sean aplicables de todos los servicios y adicionalmente, cuenta con: Profesional de la salud con título de especialista de acuerdo con el servicio a ofertar.
A14: TALENTO HUMANO | B14: Mediana | C14: Modalidad telemedicina: Categoría telexperticia - prestador remisor | D14: 11.2.2 | E14: 3 | G14: Cumple con los criterios que le sean aplicables de todos los servicios y adicionalmente
A15: TALENTO HUMANO | B15: Mediana | C15: Modalidad telemedicina: Categoría telexperticia - prestador remisor | D15: 11.2.2 | E15: 3 | F15: 3.1 | G15: • Cuando se realice telexperticia entre profesionales de la salud cuenta con el profesional de la salud con título de especialista de acuerdo con el servicio a ofertar.
A16: TALENTO HUMANO | B16: Mediana | C16: Modalidad telemedicina: Categoría telexperticia - prestador remisor | D16: 11.2.2 | E16: 3 | F16: 3.2 | G16: • Cuando realice telexperticia entre personal de salud no profesional y un profesional de la salud con título de especialista, el prestador remisor cuenta con técnico, tecnólogo o auxiliar que atiende presencialmente al usuario.
A17: TALENTO HUMANO | B17: Mediana | C17: Modalidad telemedicina: Categoría telexperticia - prestador de referencia | D17: 11.2.2 | E17: 4 | G17: Cumple con los criterios que le sean aplicables de todos los servicios y adicionalmente cuenta con profesional de la salud con título de especialista que atiende a distancia, de acuerdo con el servicio a ofertar
A18: TALENTO HUMANO | B18: Mediana | C18: Modalidad telemedicina: Categoría telemonitoreo - prestador de referencia | D18: 11.2.2 | E18: 5 | G18: Cumple con los criterios que le sean aplicables de todos los servicios y adicionalmente cuenta con el personal de salud profesional con título de especialista que se requiera para realizar el telemonitoreo de acuerdo con lo documentado por el prestador de servicios de salud en el estándar de procesos prioritarios
A19: INFRAESTRUCTURA | B19: Mediana | C19: Modalidad intramural | D19: 11.2.2 | E19: 6 | G19: Cumple con los criterios definidos para el servicio de consulta externa general, de acuerdo con la oferta.
A20: INFRAESTRUCTURA | B20: Mediana | C20: Modalidad intramural | D20: 11.2.2 | E20: 7 | G20: El consultorio de las especialidades de ginecoobstetricia y urología, cuentan con unidad sanitaria.
A21: INFRAESTRUCTURA | B21: Mediana | C21: Modalidad extramural: unidad móvil, jornada de salud, y domiciliaria | D21: 11.2.2 | E21: 8 | G21: Cumple con los criterios que le sean aplicables de todos los servicios
A22: INFRAESTRUCTURA | B22: Mediana | C22: Modalidad telemedicina: Categoría interactiva y no interactiva – prestador de referencia | D22: 11.2.2 | E22: 9 | G22: Cumple con los criterios que le sean aplicables de todos los servicios.
A23: INFRAESTRUCTURA | B23: Mediana | C23: Modalidad telemedicina: Categoría telexperticia - prestador remisor | D23: 11.2.2 | E23: 10 | G23: Cumple con los criterios establecidos en el servicio de consulta externa general.
A24: INFRAESTRUCTURA | B24: Mediana | C24: Modalidad telemedicina: Categoría telexperticia - prestador de referencia | D24: 11.2.2 | E24: 11 | G24: Cumple con los criterios que le sean aplicables de todos los servicios
A25: INFRAESTRUCTURA | B25: Mediana | C25: Modalidad telemedicina: Categoría telemonitoreo - prestador de referencia | D25: 11.2.2 | E25: 12 | G25: Cumple con los criterios que le sean aplicables de todos los servicios
A26: DOTACIÓN | B26: Mediana | C26: Modalidades intramural, extramural unidad móvil, jornada de salud y domiciliaria | D26: 11.2.2 | E26: 13 | G26: Cumple con los criterios definidos para el servicio de consulta externa general y adicionalmente: Los consultorios de los especialistas cuentan con la dotación necesaria para realizar los procedimientos documentados en el estándar de procesos prioritarios
A27: DOTACIÓN | B27: Mediana | C27: Modalidad telemedicina: Categoría interactiva y no interactiva – prestador de referencia | D27: 11.2.2 | E27: 14 | G27: Cumple con los criterios que le sean aplicables de todos los servicios
A28: DOTACIÓN | B28: Mediana | C28: Modalidad telemedicina: Categoría telexperticia - prestador remisor | D28: 11.2.2 | E28: 15 | G28: Cumple con los criterios que le sean aplicables de todos los servicios y los establecidos en el servicio de consulta externa especializada
... A34: PROCESOS PRIORITARIOS | B34: Mediana | C34: Modalidades intramural, extramural unidad móvil, jornada de salud y domiciliaria | D34: 11.2.2 | E34: 21 | G34: Adicionalmente para el caso de medicina y terapias alternativas y complementarias, cuenta con información documentada de:
A35: PROCESOS PRIORITARIOS | B35: Mediana | C35: Modalidades intramural, extramural unidad móvil, jornada de salud y domiciliaria | D35: 11.2.2 | E35: 21 | F35: 21.1 | G35: • Criterios explícitos y documentados sobre el tipo de procedimientos que se pueden realizar y de los que no se pueden realizar teniendo como marco el ámbito de la competencia.
A36: PROCESOS PRIORITARIOS | B36: Mediana | C36: Modalidades intramural, extramural unidad móvil, jornada de salud y domiciliaria | D36: 11.2.2 | E36: 21 | F36: 21.2 | G36: • Procedimientos para la información al paciente sobre preparación y recomendaciones post procedimiento, controles, posibles complicaciones y disponibilidad de consulta permanente y en general las previsiones que se requieran para proteger al paciente de los riesgos de procedimientos que se realicen en la consulta.
A37: PROCESOS PRIORITARIOS | B37: Mediana | C37: Modalidad telemedicina: Categoría interactiva y no interactiva – prestador de referencia | D37: 11.2.2 | E37: 22 | G37: Cumple con los criterios que le sean aplicables de todos los servicios
A38: PROCESOS PRIORITARIOS | B38: Mediana | C38: Modalidad telemedicina: Categoría telexperticia - prestador remisor | D38: 11.2.2 | E38: 23 | G38: Cumple con los criterios que le sean aplicables de todos los servicios y los establecidos en el servicio de consulta externa especializada
A39: PROCESOS PRIORITARIOS | B39: Mediana | C39: Modalidad telemedicina: Categoría telexperticia - prestador de referencia | D39: 11.2.2 | E39: 24 | G39: Cumple con los criterios que le sean aplicables de todos los servicios
A40: PROCESOS PRIORITARIOS | B40: Mediana | C40: Modalidad telemedicina: Categoría telemonitoreo - prestador de referencia | D40: 11.2.2 | E40: 25 | G40: Cumple con los criterios que le sean aplicables de todos los servicios
A41: HISTORIA CLÍNICA Y REGISTRO | B41: Mediana | C41: Modalidades intramural, extramural unidad móvil, jornada de salud y domiciliaria | D41: 11.2.2 | E41: 26 | G41: Cumple con los criterios que le sean aplicables de todos los servicios | H41: x
A42: HISTORIA CLÍNICA Y REGISTRO | B42: Mediana | C42: Modalidad telemedicina. Categoría interactiva y no interactiva – prestador de referencia Categoría telexperticia - prestador remisor- prestador de referencia Categoría telemonitoreo - prestador de referencia | D42: 11.2.2 | E42: 27 | G42: Cumple con los criterios que le sean aplicables de todos los servicios | H42: x
A43: INTERDEPENDENCIA | B43: Mediana | C43: Modalidades intramural, extramural unidad móvil, jornada de salud y domiciliaria y telemedicina | D43: 11.2.2 | E43: 28 | G43: No aplica para la consulta externa médica especializada | J43: x
A44: INTERDEPENDENCIA | B44: Mediana | C44: Modalidades intramural, extramural unidad móvil, jornada de salud y domiciliaria y telemedicina | D44: 11.2.2 | E44: 29 | G44: Para la consulta odontológica especializada disponibilidad de: | J44: x
A45: INTERDEPENDENCIA | B45: Mediana | C45: Modalidades intramural, extramural unidad móvil, jornada de salud y domiciliaria y telemedicina | D45: 11.2.2 | E45: 29 | F45: 29.1 | G45: • Servicio de radiología odontológica | J45: x
A46: INTERDEPENDENCIA | B46: Mediana | C46: Modalidades intramural, extramural unidad móvil, jornada de salud y domiciliaria y telemedicina | D46: 11.2.2 | E46: 29 | F46: 29.2 | G46: • Transporte asistencial cuando se realicen procedimientos bajo sedación grado I y II. | J46: x
A47: INTERDEPENDENCIA | B47: Mediana | C47: Modalidad telemedicina. Categoría interactiva y no interactiva – prestador de referencia Categoría telexperticia - prestador remisor- prestador de referencia Categoría telemonitoreo - prestador de referencia | D47: 11.2.2 | E47: 30 | G47: No aplica | J47: x
H48: =COUNTA(H10:H47) -> 2 | I48: =COUNTA(I10:I47) -> 0 | J48: =COUNTA(J10:J47) -> 5
A49: RESULTADO POR ESTANDAR CONSULTA EXTERNA ESPECIALIZADA
A50: ESTANDAR | B50: TOTAL CRITERIOS CUMPLE | C50: TOTAL CRITERIOS NO CUMPLE | D50: TOTAL CRITERIOS NO APLICA | E50: % CUMPLIMIENTO
A51: TALENTO HUMANO | B51: =COUNTIFS($A$10:$A$47,A51,$H$10:$H$47,"<>") -> 0 | C51: =COUNTIFS($A$10:$A$47,A51,$I$10:$I$47,"<>") -> 0 | D51: =COUNTIFS($A$10:$A$47,A51,$J$10:$J$47,"<>") -> 0 | E51: =IFERROR(B51/(B51+C51),"")
A52: INFRAESTRUCTURA | B52: =COUNTIFS($A$10:$A$47,A52,$H$10:$H$47,"<>") -> 0 | C52: =COUNTIFS($A$10:$A$47,A52,$I$10:$I$47,"<>") -> 0 | D52: =COUNTIFS($A$10:$A$47,A52,$J$10:$J$47,"<>") -> 0 | E52: =IFERROR(B52/(B52+C52),"")
A53: DOTACIÓN | B53: =COUNTIFS($A$10:$A$47,A53,$H$10:$H$47,"<>") -> 0 | C53: =COUNTIFS($A$10:$A$47,A53,$I$10:$I$47,"<>") -> 0 | D53: =COUNTIFS($A$10:$A$47,A53,$J$10:$J$47,"<>") -> 0 | E53: =IFERROR(B53/(B53+C53),"")
A54: MEDICAMENTOS, DM E INSUMOS | B54: =COUNTIFS($A$10:$A$47,A54,$H$10:$H$47,"<>") -> 0 | C54: =COUNTIFS($A$10:$A$47,A54,$I$10:$I$47,"<>") -> 0 | D54: =COUNTIFS($A$10:$A$47,A54,$J$10:$J$47,"<>") -> 0 | E54: =IFERROR(B54/(B54+C54),"")
A55: PROCESOS PRIORITARIOS | B55: =COUNTIFS($A$10:$A$47,A55,$H$10:$H$47,"<>") -> 0 | C55: =COUNTIFS($A$10:$A$47,A55,$I$10:$I$47,"<>") -> 0 | D55: =COUNTIFS($A$10:$A$47,A55,$J$10:$J$47,"<>") -> 0 | E55: =IFERROR(B55/(B55+C55),"")
A56: HISTORIA CLÍNICA Y REGISTRO | B56: =COUNTIFS($A$10:$A$47,A56,$H$10:$H$47,"<>") -> 2 | C56: =COUNTIFS($A$10:$A$47,A56,$I$10:$I$47,"<>") -> 0 | D56: =COUNTIFS($A$10:$A$47,A56,$J$10:$J$47,"<>") -> 0 | E56: =IFERROR(B56/(B56+C56),"") -> 1
A57: INTERDEPENDENCIA | B57: =COUNTIFS($A$10:$A$47,A57,$H$10:$H$47,"<>") -> 0 | C57: =COUNTIFS($A$10:$A$47,A57,$I$10:$I$47,"<>") -> 0 | D57: =COUNTIFS($A$10:$A$47,A57,$J$10:$J$47,"<>") -> 5 | E57: =IFERROR(B57/(B57+C57),"")
A58: TOTAL | B58: =SUM(B51:B57) -> 2 | C58: =SUM(C51:C57) -> 0 | D58: =SUM(D51:D57) -> 5 | E58: =IFERROR(B58/(B58+C58),"") -> 1

Sheet VACUN
B1: VACUNACIÓN CONDICIONES DE HABILITACIÓN RESOLUCIÓN 3100/2019 | P1: ESTADO DE ACCIONES (Número de acciones y % por estado) | T1: ESTADO DE ACCIONES (Número de acciones y % por estado) | X1: ESTADO DE ACCIONES (Número de acciones y % por estado) | AB1: ESTADO DE ACCIONES (Número de acciones y % por estado) | AF1: ESTADO DE ACCIONES (Número de acciones y % por estado) | AJ1: ESTADO DE ACCIONES (Número de acciones y % por estado)
P2: SIN INICIAR | Q2: =COUNTIFS(R$10:R$501,P2) -> 0 | R2: =IFERROR(Q2/SUM(Q$2:Q$5),"") | T2: SIN INICIAR | U2: =COUNTIFS(V$10:V$501,T2) -> 0 | V2: =IFERROR(U2/SUM(U$2:U$5),"") | X2: SIN INICIAR | Y2: =COUNTIFS(Z$10:Z$501,X2) -> 0 | Z2: =IFERROR(Y2/SUM(Y$2:Y$5),"") | AB2: SIN INICIAR | AC2: =COUNTIFS(AD$10:AD$501,AB2) -> 0 | AD2: =IFERROR(AC2/SUM(AC$2:AC$5),"") | AF2: SIN INICIAR | AG2: =COUNTIFS(AH$10:AH$501,AF2) -> 0 | AH2: =IFERROR(AG2/SUM(AG$2:AG$5),"") | AJ2: SIN INICIAR | AK2: =COUNTIFS(AL$10:AL$501,AJ2) -> 0 | AL2: =IFERROR(AK2/SUM(AK$2:AK$5),"")
C3: TOTAL CUMPLE | D3: TOTAL NO CUMPLE | E3: TOTAL NO APLICA | P3: EN EJECUCION | Q3: =COUNTIFS(R$10:R$501,P3) -> 0 | R3: =IFERROR(Q3/SUM(Q$2:Q$5),"") | T3: EN EJECUCION | U3: =COUNTIFS(V$10:V$501,T3) -> 0 | V3: =IFERROR(U3/SUM(U$2:U$5),"") | X3: EN EJECUCION | Y3: =COUNTIFS(Z$10:Z$501,X3) -> 0 | Z3: =IFERROR(Y3/SUM(Y$2:Y$5),"") | AB3: EN EJECUCION | AC3: =COUNTIFS(AD$10:AD$501,AB3) -> 0 | AD3: =IFERROR(AC3/SUM(AC$2:AC$5),"") | AF3: EN EJECUCION | AG3: =COUNTIFS(AH$10:AH$501,AF3) -> 0 | AH3: =IFERROR(AG3/SUM(AG$2:AG$5),"") | AJ3: EN EJECUCION | AK3: =COUNTIFS(AL$10:AL$501,AJ3) -> 0 | AL3: =IFERROR(AK3/SUM(AK$2:AK$5),"")
A4: NUMERO DE CRITERIOS EVALUADOS | C4: =COUNTA(H10:H67) -> 0 | D4: =COUNTA(I10:I67) -> 0 | E4: =COUNTA(J10:J67) -> 0 | P4: CERRADA | Q4: =COUNTIFS(R$10:R$501,P4) -> 0 | R4: =IFERROR(Q4/SUM(Q$2:Q$5),"") | T4: CERRADA | U4: =COUNTIFS(V$10:V$501,T4) -> 0 | V4: =IFERROR(U4/SUM(U$2:U$5),"") | X4: CERRADA | Y4: =COUNTIFS(Z$10:Z$501,X4) -> 0 | Z4: =IFERROR(Y4/SUM(Y$2:Y$5),"") | AB4: CERRADA | AC4: =COUNTIFS(AD$10:AD$501,AB4) -> 0 | AD4: =IFERROR(AC4/SUM(AC$2:AC$5),"") | AF4: CERRADA | AG4: =COUNTIFS(AH$10:AH$501,AF4) -> 0 | AH4: =IFERROR(AG4/SUM(AG$2:AG$5),"") | AJ4: CERRADA | AK4: =COUNTIFS(AL$10:AL$501,AJ4) -> 0 | AL4: =IFERROR(AK4/SUM(AK$2:AK$5),"")
A5: CUMPLIMIENTO DEL SERVICIO EVALUADO | C5: =IFERROR(C4/(D4+C4),"") | P5: CANCELADA | Q5: =COUNTIFS(R$10:R$501,P5) -> 0 | R5: =IFERROR(Q5/SUM(Q$2:Q$5),"") | T5: CANCELADA | U5: =COUNTIFS(V$10:V$501,T5) -> 0 | V5: =IFERROR(U5/SUM(U$2:U$5),"") | X5: CANCELADA | Y5: =COUNTIFS(Z$10:Z$501,X5) -> 0 | Z5: =IFERROR(Y5/SUM(Y$2:Y$5),"") | AB5: CANCELADA | AC5: =COUNTIFS(AD$10:AD$501,AB5) -> 0 | AD5: =IFERROR(AC5/SUM(AC$2:AC$5),"") | AF5: CANCELADA | AG5: =COUNTIFS(AH$10:AH$501,AF5) -> 0 | AH5: =IFERROR(AG5/SUM(AG$2:AG$5),"") | AJ5: CANCELADA | AK5: =COUNTIFS(AL$10:AL$501,AJ5) -> 0 | AL5: =IFERROR(AK5/SUM(AK$2:AK$5),"")
P6: TOTAL | Q6: =SUM(Q2:Q5) -> 0 | T6: TOTAL | U6: =SUM(U2:U5) -> 0 | X6: TOTAL | Y6: =SUM(Y2:Y5) -> 0 | AB6: TOTAL | AC6: =SUM(AC2:AC5) -> 0 | AF6: TOTAL | AG6: =SUM(AG2:AG5) -> 0 | AJ6: TOTAL | AK6: =SUM(AK2:AK5) -> 0
P8: SEGUIMIENTO 1 - Fecha: | T8: SEGUIMIENTO 2 - Fecha: | X8: SEGUIMIENTO 3 - Fecha: | AB8: SEGUIMIENTO 4 - Fecha: | AF8: SEGUIMIENTO 5 - Fecha: | AJ8: SEGUIMIENTO 6 - Fecha:
A9: ESTANDAR | B9: COMPLEJIDAD | C9: MODALIDAD | D9: ARTICULO | E9: SECCIÓN | F9: APARTADO | G9: CRITERIO | H9: CUMPLE | I9: NO CUMPLE | J9: NO APLICA | K9: HALLAZGOS | M9: ACCIÓN PARA EL CUMPLIMIENTO | N9: RESPONSABLE | O9: FECHA LIMITE PARA IMPLEMENTAR | P9: SEGUIMIENTO 1 | R9: ESTADO DE LA ACCIÓN 1 | T9: SEGUIMIENTO 2 | V9: ESTADO DE LA ACCIÓN 2 | X9: SEGUIMIENTO 3 | Z9: ESTADO DE LA ACCIÓN 3 | AB9: SEGUIMIENTO 4 | AD9: ESTADO DE LA ACCIÓN 4 | AF9: SEGUIMIENTO 5 | AH9: ESTADO DE LA ACCIÓN 5 | AJ9: SEGUIMIENTO 6 | AL9: ESTADO DE LA ACCIÓN 6
A10: TALENTO HUMANO | B10: Baja | C10: Modalidades intramural, extramural unidad móvil, jornada de salud y domiciliaria | D10: 11.2.3 | E10: 1 | G10: Cumple con los criterios que le sean aplicables de todos los servicios y adicionalmente, cuenta con:
A11: TALENTO HUMANO | B11: Baja | C11: Modalidades intramural, extramural unidad móvil, jornada de salud y domiciliaria | D11: 11.2.3 | E11: 1 | F11: 1.1 | G11: • Profesional de la medicina o profesional de la enfermería.
A12: TALENTO HUMANO | B12: Baja | C12: Modalidades intramural, extramural unidad móvil, jornada de salud y domiciliaria | D12: 11.2.3 | E12: 2 | G12: Si se requiere personal adicional para:
A13: TALENTO HUMANO | B13: Baja | C13: Modalidades intramural, extramural unidad móvil, jornada de salud y domiciliaria | D13: 11.2.3 | E13: 2 | F13: 2.1 | G13: • La administración de la vacuna cuenta con auxiliar de enfermería o auxiliar de salud pública bajo la supervisión del profesional de la medicina o profesional de la enfermería.
A14: TALENTO HUMANO | B14: Baja | C14: Modalidades intramural, extramural unidad móvil, jornada de salud y domiciliaria | D14: 11.2.3 | E14: 2 | F14: 2.2 | G14: • El manejo de la cadena de frío puede disponer de auxiliar de enfermería o auxiliar en salud pública o gestor comunitario en salud (en zonas de dispersión geográfica) o regentes de farmacia o químico farmacéutico con experiencia en cadena de frío.
A15: INFRAESTRUCTURA | B15: Baja | C15: Modalidad intramural | D15: 11.2.3 | E15: 3 | G15: Cumple con los criterios que le sean aplicables de todos los servicios y adicionalmente cuenta con:
A16: INFRAESTRUCTURA | B16: Baja | C16: Modalidad intramural | D16: 11.2.3 | E16: 4 | G16: Consultorio o ambiente que, de acuerdo con la oferta, cumple con los siguientes requisitos:
A17: INFRAESTRUCTURA | B17: Baja | C17: Modalidad intramural | D17: 11.2.3 | E17: 4 | G17: Para los servicios en modalidad intramural de prestadores de servicios de salud que separen el servicio de vacunación en dos ambientes cuenta con:
A18: INFRAESTRUCTURA | B18: Baja | C18: Modalidad intramural | D18: 11.2.3 | E18: 4 | F18: 4.1 | G18: • Consultorio para administración de medicamentos biológicos que cuenta con:
A19: INFRAESTRUCTURA | B19: Baja | C19: Modalidad intramural | D19: 11.2.3 | E19: 4 | F19: 4.1.1 | G19: • Área para entrevista.
A20: INFRAESTRUCTURA | B20: Baja | C20: Modalidad intramural | D20: 11.2.3 | E20: 4 | F20: 4.1.2 | G20: Área para el alistamiento y administración de medicamentos biológicos.
A21: INFRAESTRUCTURA | B21: Baja | C21: Modalidad intramural | D21: 11.2.3 | E21: 4 | F21: 4.1.3 | G21: • Lavamanos.
A22: INFRAESTRUCTURA | B22: Baja | C22: Modalidad intramural | D22: 11.2.3 | E22: 4 | F22: 4.2 | G22: • Ambiente para almacenamiento y alistamiento de dispositivos y termos que cuenta con:
A23: INFRAESTRUCTURA | B23: Baja | C23: Modalidad intramural | D23: 11.2.3 | E23: 4 | F23: 4.2.1 | G23: • Área para el alistamiento de termos o cajas térmicas.
A24: INFRAESTRUCTURA | B24: Baja | C24: Modalidad intramural | D24: 11.2.3 | E24: 4 | F24: 4.2.2 | G24: • Área de cadena de frío que incluye un mesón con poceta, con capacidad para el lavado de termos, con grifo cuello de cisne o ducha teléfono; que puede estar ubicado en otro ambiente diferente al consultorio.
A25: INFRAESTRUCTURA | B25: Baja | C25: Modalidad intramural | D25: 11.2.3 | E25: 4 | F25: 4.2.3 | G25: • Área para el almacenamiento de dispositivos médicos e insumos, que puede estar ubicado en otro ambiente diferente al consultorio.
A26: INFRAESTRUCTURA | B26: Baja | C26: Modalidad intramural | D26: 11.2.3 | E26: 4 | F26: 4.2.4 | G26: • Lavamanos.
A27: INFRAESTRUCTURA | B27: Baja | C27: Modalidad intramural | D27: 11.2.3 | E27: 4 | F27: 4.3 | G27: • Disponibilidad de:
A28: INFRAESTRUCTURA | B28: Baja | C28: Modalidad intramural | D28: 11.2.3 | E28: 4 | F28: 4.3.1 | G28: • Sala de espera.
A29: INFRAESTRUCTURA | B29: Baja | C29: Modalidad intramural | D29: 11.2.3 | E29: 4 | F29: 4.3.2 | G29: • Unidades sanitarias discriminadas por sexo.
A30: INFRAESTRUCTURA | B30: Baja | C30: Modalidad intramural | D30: 11.2.3 | E30: 4 | G30: Para los servicios en modalidad intramural de prestadores de servicios de salud que integren en un solo ambiente el servicio de vacunación cuenta con:
A31: INFRAESTRUCTURA | B31: Baja | C31: Modalidad intramural | D31: 11.2.3 | E31: 4 | F31: 4.4 | G31: • Ambiente de vacunación, para administración de medicamentos biológicos, que cuenta con:
A32: INFRAESTRUCTURA | B32: Baja | C32: Modalidad intramural | D32: 11.2.3 | E32: 4 | F32: 4.4.1 | G32: • Área para entrevista.
A33: INFRAESTRUCTURA | B33: Baja | C33: Modalidad intramural | D33: 11.2.3 | E33: 4 | F33: 4.4.2 | G33: • Área para el alistamiento y administración de medicamentos biológicos.
A34: INFRAESTRUCTURA | B34: Baja | C34: Modalidad intramural | D34: 11.2.3 | E34: 4 | F34: 4.4.3 | G34: • Área para el alistamiento de termos o cajas térmicas.
A35: INFRAESTRUCTURA | B35: Baja | C35: Modalidad intramural | D35: 11.2.3 | E35: 4 | F35: 4.4.4 | G35: • Área de cadena de frío que incluye un mesón con poceta, con capacidad para el lavado de los termos, con grifo cuello de cisne o ducha teléfono, que puede estar ubicado en otro ambiente diferente al consultorio.
A36: INFRAESTRUCTURA | B36: Baja | C36: Modalidad intramural | D36: 11.2.3 | E36: 4 | F36: 4.4.5 | G36: • Área para el almacenamiento de dispositivos médicos e insumos, que puede estar ubicado en otro ambiente diferente al consultorio.
A37: INFRAESTRUCTURA | B37: Baja | C37: Modalidad intramural | D37: 11.2.3 | E37: 4 | F37: 4.4.6 | G37: • Lavamanos.
A38: INFRAESTRUCTURA | B38: Baja | C38: Modalidad intramural | D38: 11.2.3 | E38: 4 | F38: 4.5 | G38: • Disponibilidad de:
A39: INFRAESTRUCTURA | B39: Baja | C39: Modalidad intramural | D39: 11.2.3 | E39: 4 | F39: 4.5.1 | G39: • Sala de espera.
A40: INFRAESTRUCTURA | B40: Baja | C40: Modalidad intramural | D40: 11.2.3 | E40: 4 | F40: 4.5.2 | G40: • Unidades sanitarias discriminadas por sexo.
A41: INFRAESTRUCTURA | B41: Baja | C41: Modalidades extramural unidad móvil, jornada de salud y domiciliaria | D41: 11.2.3 | E41: 5 | G41: Adicional a los criterios definidos para todos los servicios, la sede del prestador de servicios de salud que habilite el servicio de vacunación cuenta con:
A42: INFRAESTRUCTURA | B42: Baja | C42: Modalidades extramural unidad móvil, jornada de salud y domiciliaria | D42: 11.2.3 | E42: 5 | F42: 5.1 | G42: • Ambiente para el alistamiento de termos y cajas térmicas.
A43: INFRAESTRUCTURA | B43: Baja | C43: Modalidades extramural unidad móvil, jornada de salud y domiciliaria | D43: 11.2.3 | E43: 5 | F43: 5.2 | G43: • Ambiente de cadena de frío, que puede ser el mismo de la modalidad intramural, que incluye un mesón con poceta, con capacidad para el lavado de los termos, con grifo cuello de cisne o ducha teléfono.
A44: INFRAESTRUCTURA | B44: Baja | C44: Modalidades extramural unidad móvil, jornada de salud y domiciliaria | D44: 11.2.3 | E44: 5 | F44: 5.3 | G44: • Área para el almacenamiento de dispositivos médicos e insumos, que puede estar ubicado en otro ambiente diferente al consultorio.
A45: INFRAESTRUCTURA | B45: Baja | C45: Modalidades extramural unidad móvil, jornada de salud y domiciliaria | D45: 11.2.3 | E45: 5 | F45: 5.4 | G45: • Lavamanos.
A46: DOTACIÓN | B46: Baja | C46: Modalidad intramural | D46: 11.2.3 | E46: 6 | G46: Cumple con los criterios que le sean aplicables de todos los servicios y adicionalmente, cuenta con:
A47: DOTACIÓN | B47: Baja | C47: Modalidad intramural | D47: 11.2.3 | E47: 6 | F47: 6.1 | G47: • Refrigerador precalificado por la Organización Mundial de la Salud para almacenamiento de vacunas.
A48: DOTACIÓN | B48: Baja | C48: Modalidad intramural | D48: 11.2.3 | E48: 6 | F48: 6.2 | G48: • Para los refrigeradores con alimentación eléctrica cuenta con regulador o estabilizador electrónico de voltaje independiente, o conexión a una fuente regulada con indicador de polo a tierra.
A49: DOTACIÓN | B49: Baja | C49: Modalidad intramural | D49: 11.2.3 | E49: 6 | F49: 6.3 | G49: • Papelería, cajas de transporte y termos portavacunas precalificados por la Organización Mundial de la Salud para manejo de vacunas; y los demás insumos necesarios para la prestación del servicio.
A50: DOTACIÓN | B50: Baja | C50: Modalidades extramural unidad móvil, jornada de salud y domiciliaria | D50: 11.2.3 | E50: 7 | G50: Cumple con los criterios que le sean aplicables de todos los servicios y adicionalmente cuenta con:
A51: DOTACIÓN | B51: Baja | C51: Modalidades extramural unidad móvil, jornada de salud y domiciliaria | D51: 11.2.3 | E51: 7 | F51: 7.1 | G51: • Congelador con la capacidad suficiente para almacenar los paquetes fríos necesarios para el alistamiento de la totalidad de las cajas térmicas y termos.
A52: DOTACIÓN | B52: Baja | C52: Modalidades extramural unidad móvil, jornada de salud y domiciliaria | D52: 11.2.3 | E52: 7 | F52: 7.2 | G52: • Refrigerador precalificado por la Organización Mundial de la Salud para almacenamiento de vacunas.
A53: DOTACIÓN | B53: Baja | C53: Modalidades extramural unidad móvil, jornada de salud y domiciliaria | D53: 11.2.3 | E53: 7 | F53: 7.3 | G53: • Caja térmica o termo porta vacunas precalificados por la Organización Mundial de la Salud, para el traslado de los biológicos.
A54: MEDICAMENTOS, DM E INSUMOS | B54: Baja | C54: Modalidades intramural, extramural unidad móvil, jornada de salud y domiciliaria | D54: 11.2.3 | E54: 8 | G54: Cumple con los criterios que le sean aplicables de todos los servicios y adicionalmente cuenta con: Si se presenta interrupción de la cadena de frío, el prestador de servicios de salud realiza notificación según el procedimiento establecido por el Invima.
A55: PROCESOS PRIORITARIOS | B55: Baja | C55: Modalidad intramural | D55: 11.2.3 | E55: 9 | G55: Cumple con los criterios que le sean aplicables de todos los servicios y adicionalmente cuenta con la siguiente información documentada:
A56: PROCESOS PRIORITARIOS | B56: Baja | C56: Modalidad intramural | D56: 11.2.3 | E56: 9 | F56: 9.1 | G56: • Vacunación segura.
A57: PROCESOS PRIORITARIOS | B57: Baja | C57: Modalidad intramural | D57: 11.2.3 | E57: 9 | F57: 9.2 | G57: • Reporte y manejo de Eventos Supuestamente Adversos Atribuidos a la Vacunación o Inmunización -ESAVI (medición, análisis, reporte, gestión y monitoreo).
A58: PROCESOS PRIORITARIOS | B58: Baja | C58: Modalidad intramural | D58: 11.2.3 | E58: 9 | F58: 9.3 | G58: • Vigilancia de inmunoprevenibles.
A59: PROCESOS PRIORITARIOS | B59: Baja | C59: Modalidad intramural | D59: 11.2.3 | E59: 9 | F59: 9.4 | G59: • Seguimiento al sistema de información del Programa Ampliado de Inmunizaciones -PAI y seguimiento a cohortes.
A60: PROCESOS PRIORITARIOS | B60: Baja | C60: Modalidad intramural | D60: 11.2.3 | E60: 9 | F60: 9.5 | G60: • Protocolo para la inmunización en casos de urgencia o para víctimas de violencia sexual por medio de la respuesta en red.
A61: PROCESOS PRIORITARIOS | B61: Baja | C61: Modalidad intramural | D61: 11.2.3 | E61: 9 | F61: 9.6 | G61: • Vacunación sin barreras.
A62: PROCESOS PRIORITARIOS | B62: Baja | C62: Modalidades extramural unidad móvil, jornada de salud y domiciliaria | D62: 11.2.3 | E62: 10 | G62: Cumple con los criterios que le sean aplicables de todos los servicios, la modalidad intramural y adicionalmente cuenta con: Si el prestador de servicios de salud administra la vacuna en un ambiente diferente al consultorio de vacunación cuenta con información documentada para el alistamiento de los biológicos para uso diario, así como la conservación de la cadena de frio.
A63: HISTORIA CLÍNICA Y REGISTRO | B63: Baja | C63: Modalidades intramural, extramural unidad móvil, jornada de salud y domiciliaria | D63: 11.2.3 | E63: 11 | G63: Cumple con los criterios que le sean aplicables de todos los servicios y adicionalmente cuenta con:
A64: HISTORIA CLÍNICA Y REGISTRO | B64: Baja | C64: Modalidades intramural, extramural unidad móvil, jornada de salud y domiciliaria | D64: 11.2.3 | E64: 11 | F64: 11.1 | G64: • Instrumentos de registros establecidos para el PAI bajo los lineamientos del Ministerio de Salud y Protección Social.
A65: HISTORIA CLÍNICA Y REGISTRO | B65: Baja | C65: Modalidades intramural, extramural unidad móvil, jornada de salud y domiciliaria | D65: 11.2.3 | E65: 11 | F65: 11.2 | G65: • Registro nominal de la información del PAI, durante la atención.
A66: HISTORIA CLÍNICA Y REGISTRO | B66: Baja | C66: Modalidades intramural, extramural unidad móvil, jornada de salud y domiciliaria | D66: 11.2.3 | E66: 11 | F66: 11.3 | G66: • Registro del carné de vacunación definido por el Ministerio de Salud y Protección Social en forma clara, legible, sin tachones, enmendaduras y sin dejar espacios en blanco.
A67: INTERDEPENDENCIA | B67: Baja | C67: Modalidades intramural, extramural unidad móvil, jornada de salud y domiciliaria | D67: 11.2.3 | E67: 12 | G67: No aplica
H68: =COUNTA(H10:H67) -> 0 | I68: =COUNTA(I10:I67) -> 0 | J68: =COUNTA(J10:J67) -> 0
A69: RESULTADO POR ESTANDAR VACUNACIÓN
A70: ESTANDAR | B70: TOTAL CRITERIOS CUMPLE | C70: TOTAL CRITERIOS NO CUMPLE | D70: TOTAL CRITERIOS NO APLICA | E70: % CUMPLIMIENTO
A71: TALENTO HUMANO | B71: =COUNTIFS($A$10:$A$67,A71,$H$10:$H$67,"<>") -> 0 | C71: =COUNTIFS($A$10:$A$67,A71,$I$10:$I$67,"<>") -> 0 | D71: =COUNTIFS($A$10:$A$67,A71,$J$10:$J$67,"<>") -> 0 | E71: =IFERROR(B71/(B71+C71),"")
A72: INFRAESTRUCTURA | B72: =COUNTIFS($A$10:$A$67,A72,$H$10:$H$67,"<>") -> 0 | C72: =COUNTIFS($A$10:$A$67,A72,$I$10:$I$67,"<>") -> 0 | D72: =COUNTIFS($A$10:$A$67,A72,$J$10:$J$67,"<>") -> 0 | E72: =IFERROR(B72/(B72+C72),"")
A73: DOTACIÓN | B73: =COUNTIFS($A$10:$A$67,A73,$H$10:$H$67,"<>") -> 0 | C73: =COUNTIFS($A$10:$A$67,A73,$I$10:$I$67,"<>") -> 0 | D73: =COUNTIFS($A$10:$A$67,A73,$J$10:$J$67,"<>") -> 0 | E73: =IFERROR(B73/(B73+C73),"")
A74: MEDICAMENTOS, DM E INSUMOS | B74: =COUNTIFS($A$10:$A$67,A74,$H$10:$H$67,"<>") -> 0 | C74: =COUNTIFS($A$10:$A$67,A74,$I$10:$I$67,"<>") -> 0 | D74: =COUNTIFS($A$10:$A$67,A74,$J$10:$J$67,"<>") -> 0 | E74: =IFERROR(B74/(B74+C74),"")
A75: PROCESOS PRIORITARIOS | B75: =COUNTIFS($A$10:$A$67,A75,$H$10:$H$67,"<>") -> 0 | C75: =COUNTIFS($A$10:$A$67,A75,$I$10:$I$67,"<>") -> 0 | D75: =COUNTIFS($A$10:$A$67,A75,$J$10:$J$67,"<>") -> 0 | E75: =IFERROR(B75/(B75+C75),"")
A76: HISTORIA CLÍNICA Y REGISTRO | B76: =COUNTIFS($A$10:$A$67,A76,$H$10:$H$67,"<>") -> 0 | C76: =COUNTIFS($A$10:$A$67,A76,$I$10:$I$67,"<>") -> 0 | D76: =COUNTIFS($A$10:$A$67,A76,$J$10:$J$67,"<>") -> 0 | E76: =IFERROR(B76/(B76+C76),"")
A77: INTERDEPENDENCIA | B77: =COUNTIFS($A$10:$A$67,A77,$H$10:$H$67,"<>") -> 0 | C77: =COUNTIFS($A$10:$A$67,A77,$I$10:$I$67,"<>") -> 0 | D77: =COUNTIFS($A$10:$A$67,A77,$J$10:$J$67,"<>") -> 0 | E77: =IFERROR(B77/(B77+C77),"")
A78: TOTAL | B78: =SUM(B71:B77) -> 0 | C78: =SUM(C71:C77) -> 0 | D78: =SUM(D71:D77) -> 0 | E78: =IFERROR(B78/(B78+C78),"")

Sheet SST
B1: SEGURIDAD Y SALUD EN EL TRABAJO CONDICIONES DE HABILITACIÓN RESOLUCIÓN 3100/2019 | P1: ESTADO DE ACCIONES (Número de acciones y % por estado) | T1: ESTADO DE ACCIONES (Número de acciones y % por estado) | X1: ESTADO DE ACCIONES (Número de acciones y % por estado) | AB1: ESTADO DE ACCIONES (Número de acciones y % por estado) | AF1: ESTADO DE ACCIONES (Número de acciones y % por estado) | AJ1: ESTADO DE ACCIONES (Número de acciones y % por estado)
P2: SIN INICIAR | Q2: =COUNTIFS(R$10:R$501,P2) -> 0 | R2: =IFERROR(Q2/SUM(Q$2:Q$5),"") | T2: SIN INICIAR | U2: =COUNTIFS(V$10:V$501,T2) -> 0 | V2: =IFERROR(U2/SUM(U$2:U$5),"") | X2: SIN INICIAR | Y2: =COUNTIFS(Z$10:Z$501,X2) -> 0 | Z2: =IFERROR(Y2/SUM(Y$2:Y$5),"") | AB2: SIN INICIAR | AC2: =COUNTIFS(AD$10:AD$501,AB2) -> 0 | AD2: =IFERROR(AC2/SUM(AC$2:AC$5),"") | AF2: SIN INICIAR | AG2: =COUNTIFS(AH$10:AH$501,AF2) -> 0 | AH2: =IFERROR(AG2/SUM(AG$2:AG$5),"") | AJ2: SIN INICIAR | AK2: =COUNTIFS(AL$10:AL$501,AJ2) -> 0 | AL2: =IFERROR(AK2/SUM(AK$2:AK$5),"")
C3: TOTAL CUMPLE | D3: TOTAL NO CUMPLE | E3: TOTAL NO APLICA | P3: EN EJECUCION | Q3: =COUNTIFS(R$10:R$501,P3) -> 0 | R3: =IFERROR(Q3/SUM(Q$2:Q$5),"") | T3: EN EJECUCION | U3: =COUNTIFS(V$10:V$501,T3) -> 0 | V3: =IFERROR(U3/SUM(U$2:U$5),"") | X3: EN EJECUCION | Y3: =COUNTIFS(Z$10:Z$501,X3) -> 0 | Z3: =IFERROR(Y3/SUM(Y$2:Y$5),"") | AB3: EN EJECUCION | AC3: =COUNTIFS(AD$10:AD$501,AB3) -> 0 | AD3: =IFERROR(AC3/SUM(AC$2:AC$5),"") | AF3: EN EJECUCION | AG3: =COUNTIFS(AH$10:AH$501,AF3) -> 0 | AH3: =IFERROR(AG3/SUM(AG$2:AG$5),"") | AJ3: EN EJECUCION | AK3: =COUNTIFS(AL$10:AL$501,AJ3) -> 0 | AL3: =IFERROR(AK3/SUM(AK$2:AK$5),"")
A4: NUMERO DE CRITERIOS EVALUADOS | C4: =COUNTA(H10:H37) -> 0 | D4: =COUNTA(I10:I37) -> 0 | E4: =COUNTA(J10:J37) -> 0 | P4: CERRADA | Q4: =COUNTIFS(R$10:R$501,P4) -> 0 | R4: =IFERROR(Q4/SUM(Q$2:Q$5),"") | T4: CERRADA | U4: =COUNTIFS(V$10:V$501,T4) -> 0 | V4: =IFERROR(U4/SUM(U$2:U$5),"") | X4: CERRADA | Y4: =COUNTIFS(Z$10:Z$501,X4) -> 0 | Z4: =IFERROR(Y4/SUM(Y$2:Y$5),"") | AB4: CERRADA | AC4: =COUNTIFS(AD$10:AD$501,AB4) -> 0 | AD4: =IFERROR(AC4/SUM(AC$2:AC$5),"") | AF4: CERRADA | AG4: =COUNTIFS(AH$10:AH$501,AF4) -> 0 | AH4: =IFERROR(AG4/SUM(AG$2:AG$5),"") | AJ4: CERRADA | AK4: =COUNTIFS(AL$10:AL$501,AJ4) -> 0 | AL4: =IFERROR(AK4/SUM(AK$2:AK$5),"")
A5: CUMPLIMIENTO DEL SERVICIO EVALUADO | C5: =IFERROR(C4/(D4+C4),"") | P5: CANCELADA | Q5: =COUNTIFS(R$10:R$501,P5) -> 0 | R5: =IFERROR(Q5/SUM(Q$2:Q$5),"") | T5: CANCELADA | U5: =COUNTIFS(V$10:V$501,T5) -> 0 | V5: =IFERROR(U5/SUM(U$2:U$5),"") | X5: CANCELADA | Y5: =COUNTIFS(Z$10:Z$501,X5) -> 0 | Z5: =IFERROR(Y5/SUM(Y$2:Y$5),"") | AB5: CANCELADA | AC5: =COUNTIFS(AD$10:AD$501,AB5) -> 0 | AD5: =IFERROR(AC5/SUM(AC$2:AC$5),"") | AF5: CANCELADA | AG5: =COUNTIFS(AH$10:AH$501,AF5) -> 0 | AH5: =IFERROR(AG5/SUM(AG$2:AG$5),"") | AJ5: CANCELADA | AK5: =COUNTIFS(AL$10:AL$501,AJ5) -> 0 | AL5: =IFERROR(AK5/SUM(AK$2:AK$5),"")
P6: TOTAL | Q6: =SUM(Q2:Q5) -> 0 | T6: TOTAL | U6: =SUM(U2:U5) -> 0 | X6: TOTAL | Y6: =SUM(Y2:Y5) -> 0 | AB6: TOTAL | AC6: =SUM(AC2:AC5) -> 0 | AF6: TOTAL | AG6: =SUM(AG2:AG5) -> 0 | AJ6: TOTAL | AK6: =SUM(AK2:AK5) -> 0
P8: SEGUIMIENTO 1 - Fecha: | T8: SEGUIMIENTO 2 - Fecha: | X8: SEGUIMIENTO 3 - Fecha: | AB8: SEGUIMIENTO 4 - Fecha: | AF8: SEGUIMIENTO 5 - Fecha: | AJ8: SEGUIMIENTO 6 - Fecha:
A9: ESTANDAR | B9: COMPLEJIDAD | C9: MODALIDAD | D9: ARTICULO | E9: SECCIÓN | F9: APARTADO | G9: CRITERIO | H9: CUMPLE | I9: NO CUMPLE | J9: NO APLICA | K9: HALLAZGOS | M9: ACCIÓN PARA EL CUMPLIMIENTO | N9: RESPONSABLE | O9: FECHA LIMITE PARA IMPLEMENTAR | P9: SEGUIMIENTO 1 | R9: ESTADO DE LA ACCIÓN 1 | T9: SEGUIMIENTO 2 | V9: ESTADO DE LA ACCIÓN 2 | X9: SEGUIMIENTO 3 | Z9: ESTADO DE LA ACCIÓN 3 | AB9: SEGUIMIENTO 4 | AD9: ESTADO DE LA ACCIÓN 4 | AF9: SEGUIMIENTO 5 | AH9: ESTADO DE LA ACCIÓN 5 | AJ9: SEGUIMIENTO 6 | AL9: ESTADO DE LA ACCIÓN 6
A10: TALENTO HUMANO | B10: Mediana | C10: Modalidades intramural, extramural unidad móvil y jornada de salud | D10: 11.2.4 | E10: 1 | G10: Cumple con los criterios que le sean aplicables de todos los servicios y adicionalmente cuenta con:
A11: TALENTO HUMANO | B11: Mediana | C11: Modalidades intramural, extramural unidad móvil y jornada de salud | D11: 11.2.4 | E11: 1 | F11: 1.1 | G11: • Profesional de la medicina especialista en medicina del trabajo o medicina laboral o seguridad y salud en el trabajo con licencia vigente de seguridad y salud en el trabajo expedida por autoridad competente.
A12: TALENTO HUMANO | B12: Mediana | C12: Modalidades intramural, extramural unidad móvil y jornada de salud | D12: 11.2.4 | E12: 1 | F12: 1.2 | G12: • Cuando se realicen pruebas complementarias de tamización (audiometría, visiometría, espirometría según aplique), disponibilidad de profesionales de la salud de conformidad con lo documentado en el estándar de procesos prioritarios.
A13: TALENTO HUMANO | B13: Mediana | C13: Modalidad telemedicina - prestador remisor | D13: 11.2.4 | E13: 2 | G13: Cumple con los criterios que le sean aplicables de todos los servicios y adicionalmente:
A14: TALENTO HUMANO | B14: Mediana | C14: Modalidad telemedicina - prestador remisor | D14: 11.2.4 | F14: 2.1 | G14: • Cuando se realice telexperticia entre profesionales de la salud cuenta con el profesional de la salud.
A15: TALENTO HUMANO | B15: Mediana | C15: Modalidad telemedicina - prestador de referencia | D15: 11.2.4 | E15: 3 | G15: Cumple con los criterios que le sean aplicables de todos los servicios y adicionalmente cuenta con: Profesional en salud según la oferta definida por el prestador de servicios de salud en el estándar de procesos prioritarios.
A16: INFRAESTRUCTURA | B16: Mediana | C16: Modalidades intramural y extramural unidad móvil, jornada de salud y telemedicina - prestador remisor | D16: 11.2.4 | E16: 4 | G16: Cumple con los criterios definidos del servicio de consulta externa para consultorio donde se realiza examen físico.
A17: INFRAESTRUCTURA | B17: Mediana | C17: Modalidad telemedicina - prestador de referencia | D17: 11.2.4 | E17: 5 | G17: Cumple con los criterios que le sean aplicables de todos los servicios
A18: DOTACIÓN | B18: Mediana | C18: Modalidades intramural y extramural unidad móvil, jornada de salud y telemedicina - prestador remisor | D18: 11.2.4 | E18: 6 | G18: Cumple con los criterios que le sean aplicables de todos los servicios y adicionalmente:
A19: DOTACIÓN | B19: Mediana | C19: Modalidades intramural y extramural unidad móvil, jornada de salud y telemedicina - prestador remisor | D19: 11.2.4 | E19: 7 | G19: El consultorio, cuenta con:
A20: DOTACIÓN | B20: Mediana | C20: Modalidades intramural y extramural unidad móvil, jornada de salud y telemedicina - prestador remisor | D20: 11.2.4 | E20: 7 | F20: 7.1 | G20: • Camilla fija.
A21: DOTACIÓN | B21: Mediana | C21: Modalidades intramural y extramural unidad móvil, jornada de salud y telemedicina - prestador remisor | D21: 11.2.4 | E21: 7 | F21: 7.2 | G21: • Escalerilla.
A22: DOTACIÓN | B22: Mediana | C22: Modalidades intramural y extramural unidad móvil, jornada de salud y telemedicina - prestador remisor | D22: 11.2.4 | E22: 7 | F22: 7.3 | G22: • Tensiómetro.
A23: DOTACIÓN | B23: Mediana | C23: Modalidades intramural y extramural unidad móvil, jornada de salud y telemedicina - prestador remisor | D23: 11.2.4 | E23: 7 | F23: 7.4 | G23: • Fonendoscopio.
A24: DOTACIÓN | B24: Mediana | C24: Modalidades intramural y extramural unidad móvil, jornada de salud y telemedicina - prestador remisor | D24: 11.2.4 | E24: 7 | F24: 7.5 | G24: • Equipo de órganos de los sentidos.
A25: DOTACIÓN | B25: Mediana | C25: Modalidades intramural y extramural unidad móvil, jornada de salud y telemedicina - prestador remisor | D25: 11.2.4 | E25: 7 | F25: 7.6 | G25: • Martillo de reflejos.
A26: DOTACIÓN | B26: Mediana | C26: Modalidades intramural y extramural unidad móvil, jornada de salud y telemedicina - prestador remisor | D26: 11.2.4 | E26: 7 | F26: 7.7 | G26: • Tallímetro
A27: DOTACIÓN | B27: Mediana | C27: Modalidades intramural y extramural unidad móvil, jornada de salud y telemedicina - prestador remisor | D27: 11.2.4 | E27: 7 | F27: 7.8 | G27: • Cinta métrica.
A28: DOTACIÓN | B28: Mediana | C28: Modalidades intramural y extramural unidad móvil, jornada de salud y telemedicina - prestador remisor | D28: 11.2.4 | E28: 7 | F28: 7.9 | G28: • Báscula.
A29: DOTACIÓN | B29: Mediana | C29: Modalidades intramural y extramural unidad móvil, jornada de salud y telemedicina - prestador remisor | D29: 11.2.4 | E29: 7 | F29: 7.10 | G29: • Termómetro.
A30: DOTACIÓN | B30: Mediana | C30: Modalidades intramural y extramural unidad móvil, jornada de salud y telemedicina - prestador remisor | D30: 11.2.4 | E30: 7 | F30: 7.11 | G30: • Negatoscopio cuando se requiera o sistema de visualización según la tecnología utilizada por el prestador.
A31: DOTACIÓN | B31: Mediana | C31: Modalidades intramural y extramural unidad móvil, jornada de salud y telemedicina - prestador remisor | D31: 11.2.4 | E31: 8 | G31: Para la realización de pruebas complementarias de tamización (audiometría, visiometría, espirometría), cuenta con la dotación y los equipos biomédicos necesarios de acuerdo con lo documentado en el estándar de procesos prioritarios.
A32: DOTACIÓN | B32: Mediana | C32: Modalidad telemedicina - prestador de referencia | D32: 11.2.4 | E32: 9 | G32: Cumple con los criterios que le sean aplicables de todos los servicios
A33: MEDICAMENTOS, DM E INSUMOS | B33: Mediana | C33: Modalidades intramural y extramural unidad móvil, jornada de salud y telemedicina – prestador remisor y prestador de referencia | D33: 11.2.4 | E33: 10 | G33: Cumple con los criterios que le sean aplicables de todos los servicios
A34: PROCESOS PRIORITARIOS | B34: Mediana | C34: Modalidades intramural y extramural unidad móvil, jornada de salud y telemedicina - prestador remisor | D34: 11.2.4 | E34: 11 | G34: Cumple con los criterios que le sean aplicables de todos los servicios y adicionalmente cuenta con la siguiente información documentada: Pruebas complementarias de tamización documentadas (audiometría, visiometría, espirometría), cuando se realicen.
A35: PROCESOS PRIORITARIOS | B35: Mediana | C35: Modalidad telemedicina - prestador de referencia | D35: 11.2.4 | E35: 12 | G35: Cumple con los criterios que le sean aplicables de todos los servicios
A36: HISTORIA CLÍNICA Y REGISTRO | B36: Mediana | C36: Modalidades intramural y extramural unidad móvil, jornada de salud y telemedicina – prestador remisor y prestador de referencia | D36: 11.2.4 | E36: 13 | G36: Cumple con los criterios que le sean aplicables de todos los servicios
A37: INTERDEPENDENCIA | B37: Mediana | C37: Modalidades intramural y extramural unidad móvil, jornada de salud y telemedicina – prestador remisor y prestador de referencia | D37: 11.2.4 | E37: 14 | G37: No aplica
H38: =COUNTA(H10:H37) -> 0 | I38: =COUNTA(I10:I37) -> 0 | J38: =COUNTA(J10:J37) -> 0
A39: RESULTADO POR ESTANDAR SEGURIDAD Y SALUD EN EL TRABAJO
A40: ESTANDAR | B40: TOTAL CRITERIOS CUMPLE | C40: TOTAL CRITERIOS NO CUMPLE | D40: TOTAL CRITERIOS NO APLICA | E40: % CUMPLIMIENTO
A41: TALENTO HUMANO | B41: =COUNTIFS($A$10:$A$37,A41,$H$10:$H$37,"<>") -> 0 | C41: =COUNTIFS($A$10:$A$37,A41,$I$10:$I$37,"<>") -> 0 | D41: =COUNTIFS($A$10:$A$37,A41,$J$10:$J$37,"<>") -> 0 | E41: =IFERROR(B41/(B41+C41),"")
A42: INFRAESTRUCTURA | B42: =COUNTIFS($A$10:$A$37,A42,$H$10:$H$37,"<>") -> 0 | C42: =COUNTIFS($A$10:$A$37,A42,$I$10:$I$37,"<>") -> 0 | D42: =COUNTIFS($A$10:$A$37,A42,$J$10:$J$37,"<>") -> 0 | E42: =IFERROR(B42/(B42+C42),"")
A43: DOTACIÓN | B43: =COUNTIFS($A$10:$A$37,A43,$H$10:$H$37,"<>") -> 0 | C43: =COUNTIFS($A$10:$A$37,A43,$I$10:$I$37,"<>") -> 0 | D43: =COUNTIFS($A$10:$A$37,A43,$J$10:$J$37,"<>") -> 0 | E43: =IFERROR(B43/(B43+C43),"")
A44: MEDICAMENTOS, DM E INSUMOS | B44: =COUNTIFS($A$10:$A$37,A44,$H$10:$H$37,"<>") -> 0 | C44: =COUNTIFS($A$10:$A$37,A44,$I$10:$I$37,"<>") -> 0 | D44: =COUNTIFS($A$10:$A$37,A44,$J$10:$J$37,"<>") -> 0 | E44: =IFERROR(B44/(B44+C44),"")
A45: PROCESOS PRIORITARIOS | B45: =COUNTIFS($A$10:$A$37,A45,$H$10:$H$37,"<>") -> 0 | C45: =COUNTIFS($A$10:$A$37,A45,$I$10:$I$37,"<>") -> 0 | D45: =COUNTIFS($A$10:$A$37,A45,$J$10:$J$37,"<>") -> 0 | E45: =IFERROR(B45/(B45+C45),"")
A46: HISTORIA CLÍNICA Y REGISTRO | B46: =COUNTIFS($A$10:$A$37,A46,$H$10:$H$37,"<>") -> 0 | C46: =COUNTIFS($A$10:$A$37,A46,$I$10:$I$37,"<>") -> 0 | D46: =COUNTIFS($A$10:$A$37,A46,$J$10:$J$37,"<>") -> 0 | E46: =IFERROR(B46/(B46+C46),"")
A47: INTERDEPENDENCIA | B47: =COUNTIFS($A$10:$A$37,A47,$H$10:$H$37,"<>") -> 0 | C47: =COUNTIFS($A$10:$A$37,A47,$I$10:$I$37,"<>") -> 0 | D47: =COUNTIFS($A$10:$A$37,A47,$J$10:$J$37,"<>") -> 0 | E47: =IFERROR(B47/(B47+C47),"")
A48: TOTAL | B48: =SUM(B41:B47) -> 0 | C48: =SUM(C41:C47) -> 0 | D48: =SUM(D41:D47) -> 0 | E48: =IFERROR(B48/(B48+C48),"")

Sheet TERAP
B1: TERAPIAS CONDICIONES DE HABILITACIÓN RESOLUCIÓN 3100/2019 | P1: ESTADO DE ACCIONES (Número de acciones y % por estado) | T1: ESTADO DE ACCIONES (Número de acciones y % por estado) | X1: ESTADO DE ACCIONES (Número de acciones y % por estado) | AB1: ESTADO DE ACCIONES (Número de acciones y % por estado) | AF1: ESTADO DE ACCIONES (Número de acciones y % por estado) | AJ1: ESTADO DE ACCIONES (Número de acciones y % por estado)
P2: SIN INICIAR | Q2: =COUNTIFS(R$10:R$501,P2) -> 0 | R2: =IFERROR(Q2/SUM(Q$2:Q$5),"") | T2: SIN INICIAR | U2: =COUNTIFS(V$10:V$501,T2) -> 0 | V2: =IFERROR(U2/SUM(U$2:U$5),"") | X2: SIN INICIAR | Y2: =COUNTIFS(Z$10:Z$501,X2) -> 0 | Z2: =IFERROR(Y2/SUM(Y$2:Y$5),"") | AB2: SIN INICIAR | AC2: =COUNTIFS(AD$10:AD$501,AB2) -> 0 | AD2: =IFERROR(AC2/SUM(AC$2:AC$5),"") | AF2: SIN INICIAR | AG2: =COUNTIFS(AH$10:AH$501,AF2) -> 0 | AH2: =IFERROR(AG2/SUM(AG$2:AG$5),"") | AJ2: SIN INICIAR | AK2: =COUNTIFS(AL$10:AL$501,AJ2) -> 0 | AL2: =IFERROR(AK2/SUM(AK$2:AK$5),"")
C3: TOTAL CUMPLE | D3: TOTAL NO CUMPLE | E3: TOTAL NO APLICA | P3: EN EJECUCION | Q3: =COUNTIFS(R$10:R$501,P3) -> 0 | R3: =IFERROR(Q3/SUM(Q$2:Q$5),"") | T3: EN EJECUCION | U3: =COUNTIFS(V$10:V$501,T3) -> 0 | V3: =IFERROR(U3/SUM(U$2:U$5),"") | X3: EN EJECUCION | Y3: =COUNTIFS(Z$10:Z$501,X3) -> 0 | Z3: =IFERROR(Y3/SUM(Y$2:Y$5),"") | AB3: EN EJECUCION | AC3: =COUNTIFS(AD$10:AD$501,AB3) -> 0 | AD3: =IFERROR(AC3/SUM(AC$2:AC$5),"") | AF3: EN EJECUCION | AG3: =COUNTIFS(AH$10:AH$501,AF3) -> 0 | AH3: =IFERROR(AG3/SUM(AG$2:AG$5),"") | AJ3: EN EJECUCION | AK3: =COUNTIFS(AL$10:AL$501,AJ3) -> 0 | AL3: =IFERROR(AK3/SUM(AK$2:AK$5),"")
A4: NUMERO DE CRITERIOS EVALUADOS | C4: =COUNTA(H10:H54) -> 0 | D4: =COUNTA(I10:I54) -> 0 | E4: =COUNTA(J10:J54) -> 0 | P4: CERRADA | Q4: =COUNTIFS(R$10:R$501,P4) -> 0 | R4: =IFERROR(Q4/SUM(Q$2:Q$5),"") | T4: CERRADA | U4: =COUNTIFS(V$10:V$501,T4) -> 0 | V4: =IFERROR(U4/SUM(U$2:U$5),"") | X4: CERRADA | Y4: =COUNTIFS(Z$10:Z$501,X4) -> 0 | Z4: =IFERROR(Y4/SUM(Y$2:Y$5),"") | AB4: CERRADA | AC4: =COUNTIFS(AD$10:AD$501,AB4) -> 0 | AD4: =IFERROR(AC4/SUM(AC$2:AC$5),"") | AF4: CERRADA | AG4: =COUNTIFS(AH$10:AH$501,AF4) -> 0 | AH4: =IFERROR(AG4/SUM(AG$2:AG$5),"") | AJ4: CERRADA | AK4: =COUNTIFS(AL$10:AL$501,AJ4) -> 0 | AL4: =IFERROR(AK4/SUM(AK$2:AK$5),"")
A5: CUMPLIMIENTO DEL SERVICIO EVALUADO | C5: =IFERROR(C4/(D4+C4),"") | P5: CANCELADA | Q5: =COUNTIFS(R$10:R$501,P5) -> 0 | R5: =IFERROR(Q5/SUM(Q$2:Q$5),"") | T5: CANCELADA | U5: =COUNTIFS(V$10:V$501,T5) -> 0 | V5: =IFERROR(U5/SUM(U$2:U$5),"") | X5: CANCELADA | Y5: =COUNTIFS(Z$10:Z$501,X5) -> 0 | Z5: =IFERROR(Y5/SUM(Y$2:Y$5),"") | AB5: CANCELADA | AC5: =COUNTIFS(AD$10:AD$501,AB5) -> 0 | AD5: =IFERROR(AC5/SUM(AC$2:AC$5),"") | AF5: CANCELADA | AG5: =COUNTIFS(AH$10:AH$501,AF5) -> 0 | AH5: =IFERROR(AG5/SUM(AG$2:AG$5),"") | AJ5: CANCELADA | AK5: =COUNTIFS(AL$10:AL$501,AJ5) -> 0 | AL5: =IFERROR(AK5/SUM(AK$2:AK$5),"")
P6: TOTAL | Q6: =SUM(Q2:Q5) -> 0 | T6: TOTAL | U6: =SUM(U2:U5) -> 0 | X6: TOTAL | Y6: =SUM(Y2:Y5) -> 0 | AB6: TOTAL | AC6: =SUM(AC2:AC5) -> 0 | AF6: TOTAL | AG6: =SUM(AG2:AG5) -> 0 | AJ6: TOTAL | AK6: =SUM(AK2:AK5) -> 0
P8: SEGUIMIENTO 1 - Fecha: | T8: SEGUIMIENTO 2 - Fecha: | X8: SEGUIMIENTO 3 - Fecha: | AB8: SEGUIMIENTO 4 - Fecha: | AF8: SEGUIMIENTO 5 - Fecha: | AJ8: SEGUIMIENTO 6 - Fecha:
A9: ESTANDAR | B9: COMPLEJIDAD | C9: MODALIDAD | D9: ARTICULO | E9: SECCIÓN | F9: APARTADO | G9: CRITERIO | H9: CUMPLE | I9: NO CUMPLE | J9: NO APLICA | K9: HALLAZGOS | M9: ACCIÓN PARA EL CUMPLIMIENTO | N9: RESPONSABLE | O9: FECHA LIMITE PARA IMPLEMENTAR | P9: SEGUIMIENTO 1 | R9: ESTADO DE LA ACCIÓN 1 | T9: SEGUIMIENTO 2 | V9: ESTADO DE LA ACCIÓN 2 | X9: SEGUIMIENTO 3 | Z9: ESTADO DE LA ACCIÓN 3 | AB9: SEGUIMIENTO 4 | AD9: ESTADO DE LA ACCIÓN 4 | AF9: SEGUIMIENTO 5 | AH9: ESTADO DE LA ACCIÓN 5 | AJ9: SEGUIMIENTO 6 | AL9: ESTADO DE LA ACCIÓN 6
A10: TALENTO HUMANO | B10: No aplica | C10: Modalidades intramural y extramural unidad móvil, jornada de salud y domiciliaria | D10: 11.3.1 | E10: 1 | G10: Cumple con los criterios que le sean aplicables de todos los servicios y adicionalmente cuenta con:
A11: TALENTO HUMANO | B11: No aplica | C11: Modalidades intramural y extramural unidad móvil, jornada de salud y domiciliaria | D11: 11.3.1 | E11: 1 | F11: 1.1 | G11: • Profesional de la salud con título según los programas académicos autorizados por el Ministerio de Educación Nacional en el ámbito de la rehabilitación, según oferta.
A12: TALENTO HUMANO | B12: No aplica | C12: Modalidades intramural y extramural unidad móvil, jornada de salud y domiciliaria | D12: 11.3.1 | E12: 1 | F12: 1.2 | G12: • Si oferta evaluación y tratamiento desde el enfoque de integración neurosensorial, cuenta con constancia de asistencia en las acciones de formación continua para la realización de los procedimientos según la oferta.
A13: TALENTO HUMANO | B13: No aplica | C13: Modalidad telemedicina: Categoría interactiva y no interactiva – prestador de referencia | D13: 11.3.1 | E13: 2 | G13: Cumple con los criterios que le sean aplicables de todos los servicios y adicionalmente, cuenta con:
A14: TALENTO HUMANO | B14: No aplica | C14: Modalidad telemedicina: Categoría interactiva y no interactiva – prestador de referencia | D14: 11.3.1 | E14: 2 | F14: 2.1 | G14: • Profesional de la salud de acuerdo con el servicio a ofertar
A15: TALENTO HUMANO | B15: No aplica | C15: Modalidad telemedicina: Categoría telexperticia - prestador remisor | D15: 11.3.1 | E15: 3 | G15: Cumple con los criterios que le sean aplicables de todos los servicios y adicionalmente:
A16: TALENTO HUMANO | B16: No aplica | C16: Modalidad telemedicina: Categoría telexperticia - prestador remisor | D16: 11.3.1 | E16: 3 | F16: 3.1 | G16: • Cuando se realice telexperticia entre profesionales de la salud cuenta con el profesional de la salud de acuerdo con el servicio a ofertar.
A17: TALENTO HUMANO | B17: No aplica | C17: Modalidad telemedicina: Categoría telexperticia - prestador de referencia | D17: 11.3.1 | E17: 4 | G17: Cumple con los criterios que le sean aplicables de todos los servicios y adicionalmente cuenta con profesional de la salud que atiende a distancia, de acuerdo con el servicio a ofertar
A18: TALENTO HUMANO | B18: No aplica | C18: Modalidad telemedicina: Categoría telemonitoreo - prestador de referencia | D18: 11.3.1 | E18: 5 | G18: Cumple con los criterios que le sean aplicables de todos los servicios y adicionalmente cuenta con el personal de salud profesional que se requiera para realizar el telemonitoreo de acuerdo con lo documentado por el prestador de servicios de salud en el estándar de procesos prioritarios.
A19: INFRAESTRUCTURA | B19: No aplica | C19: Modalidad intramural | D19: 11.3.1 | E19: 6 | G19: Cumple con los criterios que le sean aplicables de todos los servicios, y adicionalmente,
A20: INFRAESTRUCTURA | B20: No aplica | C20: Modalidad intramural | D20: 11.3.1 | E20: 7 | G20: De acuerdo con el tipo de terapia ofertada, el servicio cuenta con:
A21: INFRAESTRUCTURA | B21: No aplica | C21: Modalidad intramural | D21: 11.3.1 | E21: 7 | F21: 7.1 | G21: • Área para camillas, sillas de ruedas y demás aditamentos o ayudas ortopédicas, cuando se requiera.
A22: INFRAESTRUCTURA | B22: No aplica | C22: Modalidad intramural | D22: 11.3.1 | E22: 7 | F22: 7.2 | G22: • Vestidor de pacientes, con área para casilleros y unidad sanitaria de uso mixto, cuando el tipo de terapia lo requiera de acuerdo con lo documentado en procesos prioritarios.
A23: INFRAESTRUCTURA | B23: No aplica | C23: Modalidad intramural | D23: 11.3.1 | E23: 7 | F23: 7.3 | G23: • Ambiente para realizar entrevista, cuando se requiera de acuerdo con lo documentado en procesos prioritarios.
A24: INFRAESTRUCTURA | B24: No aplica | C24: Modalidad intramural | D24: 11.3.1 | E24: 7 | F24: 7.4 | G24: • Área para atención individual, con barrera física fija o móvil, cuando el tipo de terapia requiera privacidad para el paciente.
A25: INFRAESTRUCTURA | B25: No aplica | C25: Modalidad intramural | D25: 11.3.1 | E25: 7 | F25: 7.5 | G25: • Área de depósito para almacenamiento de insumos, equipos biomédicos y materiales, cuando el tipo de terapia lo requiera de acuerdo con lo documentado en procesos prioritarios.
A26: INFRAESTRUCTURA | B26: No aplica | C26: Modalidad intramural | D26: 11.3.1 | E26: 7 | F26: 7.6 | G26: • Área con equipamiento para actividades de terapia ocupacional, cuando se requiera de acuerdo con lo documentado en procesos prioritarios.
A27: INFRAESTRUCTURA | B27: No aplica | C27: Modalidad intramural | D27: 11.3.1 | E27: 7 | F27: 7.7 | G27: • Área húmeda o de hidroterapia (cuando se oferte), que debe garantizar pisos antideslizantes y tomas eléctricas con protección para ambientes húmedos cuando se requiera de acuerdo con lo documentado en procesos prioritarios.
A28: INFRAESTRUCTURA | B28: No aplica | C28: Modalidad intramural | D28: 11.3.1 | E28: 8 | G28: Para fonoaudiología o terapia ocupacional, cuenta con:
A29: INFRAESTRUCTURA | B29: No aplica | C29: Modalidad intramural | D29: 11.3.1 | E29: 8 | F29: 8.1 | G29: • Área para sillas y mesas para trabajo individual o grupal para niños o adultos, según la oferta.
A30: INFRAESTRUCTURA | B30: No aplica | C30: Modalidad intramural | D30: 11.3.1 | E30: 8 | F30: 8.2 | G30: • Ambiente para cabina sono-amortiguada o equipo de audiometría, depende del procedimiento que se oferte.
A31: INFRAESTRUCTURA | B31: No aplica | C31: Modalidad intramural | D31: 11.3.1 | E31: 9 | G31: Disponibilidad de:
A32: INFRAESTRUCTURA | B32: No aplica | C32: Modalidad intramural | D32: 11.3.1 | E32: 9 | F32: 9.1 | G32: • Sala de espera
A33: INFRAESTRUCTURA | B33: No aplica | C33: Modalidad intramural | D33: 11.3.1 | E33: 9 | F33: 9.2 | G33: • Unidades sanitarias discriminadas por sexo.
A34: INFRAESTRUCTURA | B34: No aplica | C34: Modalidades extramural unidad móvil, jornada de salud y domiciliaria | D34: 11.3.1 | E34: 10 | G34: Cumple con los criterios que le sean aplicables de todos los servicios
A35: INFRAESTRUCTURA | B35: No aplica | C35: Modalidad telemedicina: Categoría interactiva y no interactiva – prestador de referencia | D35: 11.3.1 | E35: 11 | G35: Cumple con los criterios que le sean aplicables de todos los servicios
A36: INFRAESTRUCTURA | B36: No aplica | C36: Categoría telexperticia - prestador remisor | D36: 11.3.1 | E36: 12 | G36: Cumple con los criterios establecidos en el servicio de terapias
A37: INFRAESTRUCTURA | B37: No aplica | C37: Categoría telexperticia - prestador de referencia | D37: 11.3.1 | E37: 13 | G37: Cumple con los criterios que le sean aplicables de todos los servicios
A38: INFRAESTRUCTURA | B38: No aplica | C38: Categoría telemonitoreo - prestador de referencia | D38: 11.3.1 | E38: 14 | G38: Cumple con los criterios que le sean aplicables de todos los servicios
A39: DOTACIÓN | B39: No aplica | C39: Modalidades intramural, extramural unidad móvil, jornada de salud y domiciliaria | D39: 11.3.1 | E39: 15 | G39: Cumple con los criterios que le sean aplicables de todos los servicios y adicionalmente cuenta con: La dotación requerida para realizar los procedimientos de acuerdo con lo documentado en el estándar de procesos prioritarios
A40: DOTACIÓN | B40: No aplica | C40: Modalidad telemedicina: Categoría interactiva y no interactiva – prestador de referencia | D40: 11.3.1 | E40: 16 | G40: Cumple con los criterios que le sean aplicables de todos los servicios
A41: DOTACIÓN | B41: No aplica | C41: Modalidad telemedicina: Categoría telexperticia - prestador remisor | D41: 11.3.1 | E41: 17 | G41: Cumple con los criterios que le sean aplicables de todos los servicios y los establecidos en el servicio de terapias
A42: DOTACIÓN | B42: No aplica | C42: Modalidad telemedicina: Categoría telexperticia - prestador de referencia | D42: 11.3.1 | E42: 18 | G42: Cumple con los criterios que le sean aplicables de todos los servicios
A43: DOTACIÓN | B43: No aplica | C43: Modalidad telemedicina: Categoría telemonitoreo - prestador de referencia | D43: 11.3.1 | E43: 19 | G43: Cumple con los criterios que le sean aplicables de todos los servicios.
A44: MEDICAMENTOS, DM E INSUMOS | B44: No aplica | C44: Modalidades intramural, extramural unidad móvil, jornada de salud y domiciliaria | D44: 11.3.1 | E44: 20 | G44: Cumple con los criterios que le sean aplicables de todos los servicios.
A45: MEDICAMENTOS, DM E INSUMOS | B45: No aplica | C45: Modalidad telemedicina: Categoría interactiva y no interactiva – prestador de referencia Categoría telexperticia - prestador remisor- prestador de referencia Categoría telemonitoreo - prestador de referencia | D45: 11.3.1 | E45: 21 | G45: Cumple con los criterios que le sean aplicables de todos los servicios.
... A54: INTERDEPENDENCIA | B54: No aplica | C54: Modalidad telemedicina: Categoría interactiva y no interactiva – prestador de referencia Categoría telexperticia - prestador remisor- prestador de referencia Categoría telemonitoreo - prestador de referencia | D54: 11.3.1 | E54: 30 | G54: No aplica
H55: =COUNTA(H10:H54) -> 0 | I55: =COUNTA(I10:I54) -> 0 | J55: =COUNTA(J10:J54) -> 0
A56: RESULTADO POR ESTANDAR TERAPIAS
A57: ESTANDAR | B57: TOTAL CRITERIOS CUMPLE | C57: TOTAL CRITERIOS NO CUMPLE | D57: TOTAL CRITERIOS NO APLICA | E57: % CUMPLIMIENTO
A58: TALENTO HUMANO | B58: =COUNTIFS($A$10:$A$54,A58,$H$10:$H$54,"<>") -> 0 | C58: =COUNTIFS($A$10:$A$54,A58,$I$10:$I$54,"<>") -> 0 | D58: =COUNTIFS($A$10:$A$54,A58,$J$10:$J$54,"<>") -> 0 | E58: =IFERROR(B58/(B58+C58),"")
A59: INFRAESTRUCTURA | B59: =COUNTIFS($A$10:$A$54,A59,$H$10:$H$54,"<>") -> 0 | C59: =COUNTIFS($A$10:$A$54,A59,$I$10:$I$54,"<>") -> 0 | D59: =COUNTIFS($A$10:$A$54,A59,$J$10:$J$54,"<>") -> 0 | E59: =IFERROR(B59/(B59+C59),"")
A60: DOTACIÓN | B60: =COUNTIFS($A$10:$A$54,A60,$H$10:$H$54,"<>") -> 0 | C60: =COUNTIFS($A$10:$A$54,A60,$I$10:$I$54,"<>") -> 0 | D60: =COUNTIFS($A$10:$A$54,A60,$J$10:$J$54,"<>") -> 0 | E60: =IFERROR(B60/(B60+C60),"")
A61: MEDICAMENTOS, DM E INSUMOS | B61: =COUNTIFS($A$10:$A$54,A61,$H$10:$H$54,"<>") -> 0 | C61: =COUNTIFS($A$10:$A$54,A61,$I$10:$I$54,"<>") -> 0 | D61: =COUNTIFS($A$10:$A$54,A61,$J$10:$J$54,"<>") -> 0 | E61: =IFERROR(B61/(B61+C61),"")
A62: PROCESOS PRIORITARIOS | B62: =COUNTIFS($A$10:$A$54,A62,$H$10:$H$54,"<>") -> 0 | C62: =COUNTIFS($A$10:$A$54,A62,$I$10:$I$54,"<>") -> 0 | D62: =COUNTIFS($A$10:$A$54,A62,$J$10:$J$54,"<>") -> 0 | E62: =IFERROR(B62/(B62+C62),"")
A63: HISTORIA CLÍNICA Y REGISTROS | B63: =COUNTIFS($A$10:$A$54,A63,$H$10:$H$54,"<>") -> 0 | C63: =COUNTIFS($A$10:$A$54,A63,$I$10:$I$54,"<>") -> 0 | D63: =COUNTIFS($A$10:$A$54,A63,$J$10:$J$54,"<>") -> 0 | E63: =IFERROR(B63/(B63+C63),"")
A64: INTERDEPENDENCIA | B64: =COUNTIFS($A$10:$A$54,A64,$H$10:$H$54,"<>") -> 0 | C64: =COUNTIFS($A$10:$A$54,A64,$I$10:$I$54,"<>") -> 0 | D64: =COUNTIFS($A$10:$A$54,A64,$J$10:$J$54,"<>") -> 0 | E64: =IFERROR(B64/(B64+C64),"")
A65: TOTAL | B65: =SUM(B58:B64) -> 0 | C65: =SUM(C58:C64) -> 0 | D65: =SUM(D58:D64) -> 0 | E65: =IFERROR(B65/(B65+C65),"")

Sheet FARMAC
B1: SERVICIO FARMACEUTICO CONDICIONES DE HABILITACIÓN RESOLUCIÓN 3100/2019 | P1: ESTADO DE ACCIONES (Número de acciones y % por estado) | T1: ESTADO DE ACCIONES (Número de acciones y % por estado) | X1: ESTADO DE ACCIONES (Número de acciones y % por estado) | AB1: ESTADO DE ACCIONES (Número de acciones y % por estado) | AF1: ESTADO DE ACCIONES (Número de acciones y % por estado) | AJ1: ESTADO DE ACCIONES (Número de acciones y % por estado)
P2: SIN INICIAR | Q2: =COUNTIFS(R$10:R$501,P2) -> 0 | R2: =IFERROR(Q2/SUM(Q$2:Q$5),"") | T2: SIN INICIAR | U2: =COUNTIFS(V$10:V$501,T2) -> 0 | V2: =IFERROR(U2/SUM(U$2:U$5),"") | X2: SIN INICIAR | Y2: =COUNTIFS(Z$10:Z$501,X2) -> 0 | Z2: =IFERROR(Y2/SUM(Y$2:Y$5),"") | AB2: SIN INICIAR | AC2: =COUNTIFS(AD$10:AD$501,AB2) -> 0 | AD2: =IFERROR(AC2/SUM(AC$2:AC$5),"") | AF2: SIN INICIAR | AG2: =COUNTIFS(AH$10:AH$501,AF2) -> 0 | AH2: =IFERROR(AG2/SUM(AG$2:AG$5),"") | AJ2: SIN INICIAR | AK2: =COUNTIFS(AL$10:AL$501,AJ2) -> 0 | AL2: =IFERROR(AK2/SUM(AK$2:AK$5),"")
C3: TOTAL CUMPLE | D3: TOTAL NO CUMPLE | E3: TOTAL NO APLICA | P3: EN EJECUCION | Q3: =COUNTIFS(R$10:R$501,P3) -> 0 | R3: =IFERROR(Q3/SUM(Q$2:Q$5),"") | T3: EN EJECUCION | U3: =COUNTIFS(V$10:V$501,T3) -> 0 | V3: =IFERROR(U3/SUM(U$2:U$5),"") | X3: EN EJECUCION | Y3: =COUNTIFS(Z$10:Z$501,X3) -> 0 | Z3: =IFERROR(Y3/SUM(Y$2:Y$5),"") | AB3: EN EJECUCION | AC3: =COUNTIFS(AD$10:AD$501,AB3) -> 0 | AD3: =IFERROR(AC3/SUM(AC$2:AC$5),"") | AF3: EN EJECUCION | AG3: =COUNTIFS(AH$10:AH$501,AF3) -> 0 | AH3: =IFERROR(AG3/SUM(AG$2:AG$5),"") | AJ3: EN EJECUCION | AK3: =COUNTIFS(AL$10:AL$501,AJ3) -> 0 | AL3: =IFERROR(AK3/SUM(AK$2:AK$5),"")
A4: NUMERO DE CRITERIOS EVALUADOS | C4: =COUNTA(H10:H45) -> 0 | D4: =COUNTA(I10:I45) -> 0 | E4: =COUNTA(J10:J45) -> 0 | P4: CERRADA | Q4: =COUNTIFS(R$10:R$501,P4) -> 0 | R4: =IFERROR(Q4/SUM(Q$2:Q$5),"") | T4: CERRADA | U4: =COUNTIFS(V$10:V$501,T4) -> 0 | V4: =IFERROR(U4/SUM(U$2:U$5),"") | X4: CERRADA | Y4: =COUNTIFS(Z$10:Z$501,X4) -> 0 | Z4: =IFERROR(Y4/SUM(Y$2:Y$5),"") | AB4: CERRADA | AC4: =COUNTIFS(AD$10:AD$501,AB4) -> 0 | AD4: =IFERROR(AC4/SUM(AC$2:AC$5),"") | AF4: CERRADA | AG4: =COUNTIFS(AH$10:AH$501,AF4) -> 0 | AH4: =IFERROR(AG4/SUM(AG$2:AG$5),"") | AJ4: CERRADA | AK4: =COUNTIFS(AL$10:AL$501,AJ4) -> 0 | AL4: =IFERROR(AK4/SUM(AK$2:AK$5),"")
A5: CUMPLIMIENTO DEL SERVICIO EVALUADO | C5: =IFERROR(C4/(D4+C4),"") | P5: CANCELADA | Q5: =COUNTIFS(R$10:R$501,P5) -> 0 | R5: =IFERROR(Q5/SUM(Q$2:Q$5),"") | T5: CANCELADA | U5: =COUNTIFS(V$10:V$501,T5) -> 0 | V5: =IFERROR(U5/SUM(U$2:U$5),"") | X5: CANCELADA | Y5: =COUNTIFS(Z$10:Z$501,X5) -> 0 | Z5: =IFERROR(Y5/SUM(Y$2:Y$5),"") | AB5: CANCELADA | AC5: =COUNTIFS(AD$10:AD$501,AB5) -> 0 | AD5: =IFERROR(AC5/SUM(AC$2:AC$5),"") | AF5: CANCELADA | AG5: =COUNTIFS(AH$10:AH$501,AF5) -> 0 | AH5: =IFERROR(AG5/SUM(AG$2:AG$5),"") | AJ5: CANCELADA | AK5: =COUNTIFS(AL$10:AL$501,AJ5) -> 0 | AL5: =IFERROR(AK5/SUM(AK$2:AK$5),"")
P6: TOTAL | Q6: =SUM(Q2:Q5) -> 0 | T6: TOTAL | U6: =SUM(U2:U5) -> 0 | X6: TOTAL | Y6: =SUM(Y2:Y5) -> 0 | AB6: TOTAL | AC6: =SUM(AC2:AC5) -> 0 | AF6: TOTAL | AG6: =SUM(AG2:AG5) -> 0 | AJ6: TOTAL | AK6: =SUM(AK2:AK5) -> 0
P8: SEGUIMIENTO 1 - Fecha: | T8: SEGUIMIENTO 2 - Fecha: | X8: SEGUIMIENTO 3 - Fecha: | AB8: SEGUIMIENTO 4 - Fecha: | AF8: SEGUIMIENTO 5 - Fecha: | AJ8: SEGUIMIENTO 6 - Fecha:
A9: ESTANDAR | B9: COMPLEJIDAD | C9: MODALIDAD | D9: ARTICULO | E9: SECCIÓN | F9: APARTADO | G9: CRITERIO | H9: CUMPLE | I9: NO CUMPLE | J9: NO APLICA | K9: HALLAZGOS | M9: ACCIÓN PARA EL CUMPLIMIENTO | N9: RESPONSABLE | O9: FECHA LIMITE PARA IMPLEMENTAR | P9: SEGUIMIENTO 1 | R9: ESTADO DE LA ACCIÓN 1 | T9: SEGUIMIENTO 2 | V9: ESTADO DE LA ACCIÓN 2 | X9: SEGUIMIENTO 3 | Z9: ESTADO DE LA ACCIÓN 3 | AB9: SEGUIMIENTO 4 | AD9: ESTADO DE LA ACCIÓN 4 | AF9: SEGUIMIENTO 5 | AH9: ESTADO DE LA ACCIÓN 5 | AJ9: SEGUIMIENTO 6 | AL9: ESTADO DE LA ACCIÓN 6
A10: TALENTO HUMANO | B10: Todas | C10: Modalidades intramural y extramural domiciliaria | D10: 11.3.2 | E10: 1 | G10: Cumple con los criterios que le sean aplicables de todos los servicios y adicionalmente: Cumple con lo definido en el Decreto 2200 de 2005, compilado en el Decreto 780 de 2016 (Art 2.5.3.10.9), y la Resolución 1403 de 2007 (Manual de condiciones esenciales y procedimientos del servicio farmacéutico Título I Capítulo II Numerales 3.2, 3.2.1; 3.2.2 y Capítulo III Numeral 1.2), o las normas que los modifiquen, adicionen o sustituyan
A11: TALENTO HUMANO | B11: Todas | C11: Modalidad telemedicina: Categoría interactiva y no interactiva – prestador de referencia Categoría telexperticia – prestador remisor – prestador de referencia | D11: 11.3.2 | E11: 2 | G11: Cumple con los criterios que le sean aplicables de todos los servicios y adicionalmente, cuenta con lo definido con el numeral 1 del servicio farmacéutico.
A12: TALENTO HUMANO | B12: Todas | C12: Modalidad telemedicina: Categoría interactiva y no interactiva – prestador de referencia Categoría telexperticia – prestador remisor – prestador de referencia | D12: 11.3.2 | E12: 3 | G12: El talento humano brinda en esta modalidad lo relacionado con la atención farmacéutica a los pacientes que lo requieran, a través de telemedicina – categorías interactiva y no interactiva, telexperticia sincrónico y asincrónico. El apoyo a distancia del profesional Químico Farmacéutico no reemplaza el contar con el talento humano definido en el servicio
A13: INFRAESTRUCTURA | B13: Baja | C13: Modalidades intramural, extramural domiciliaria, telemedicina categoría telexperticia – prestador remisor | D13: 11.3.2 | E13: 4 | G13: Cumple con los criterios que le sean aplicables de todos los servicios
A14: INFRAESTRUCTURA | B14: Baja | C14: Modalidades intramural, extramural domiciliaria, telemedicina categoría telexperticia – prestador remisor | D14: 11.3.2 | E14: 5 | G14: Cuenta con:
A15: INFRAESTRUCTURA | B15: Baja | C15: Modalidades intramural, extramural domiciliaria, telemedicina categoría telexperticia – prestador remisor | D15: 11.3.2 | E15: 5 | F15: 5.1 | G15: • Ambiente o área administrativa.
A16: INFRAESTRUCTURA | B16: Baja | C16: Modalidades intramural, extramural domiciliaria, telemedicina categoría telexperticia – prestador remisor | D16: 11.3.2 | E16: 5 | F16: 5.2 | G16: • Ambiente o área de recepción de medicamentos y dispositivos médicos.
A17: INFRAESTRUCTURA | B17: Baja | C17: Modalidades intramural, extramural domiciliaria, telemedicina categoría telexperticia – prestador remisor | D17: 11.3.2 | E17: 5 | F17: 5.3 | G17: • Ambiente o área de dispensación de medicamentos y entrega de dispositivos médicos.
A18: INFRAESTRUCTURA | B18: Baja | C18: Modalidades intramural, extramural domiciliaria, telemedicina categoría telexperticia – prestador remisor | D18: 11.3.2 | E18: 5 | F18: 5.4 | G18: • Ambiente o área de almacenamiento, que garantice las condiciones temperatura y humedad recomendadas por el fabricante. Incluye cadena de frio, cuando aplique.
A19: INFRAESTRUCTURA | B19: Baja | C19: Modalidades intramural, extramural domiciliaria, telemedicina categoría telexperticia – prestador remisor | D19: 11.3.2 | E19: 5 | F19: 5.5 | G19: • Ambiente o área independiente de medicamentos de control especial cuando aplique, que garantice las condiciones temperatura y humedad recomendadas por el fabricante.
A20: INFRAESTRUCTURA | B20: Baja | C20: Modalidades intramural, extramural domiciliaria, telemedicina categoría telexperticia – prestador remisor | D20: 11.3.2 | E20: 5 | F20: 5.6 | G20: • Ambiente o área para almacenamiento de productos rechazados, devueltos y retirados.
A21: INFRAESTRUCTURA | B21: Baja | C21: Modalidades intramural, extramural domiciliaria, telemedicina categoría telexperticia – prestador remisor | D21: 11.3.2 | E21: 5 | F21: 5.7 | G21: • Ambiente o área para almacenamiento de productos destruidos o desnaturalizados por vencimiento o deterioro.
A22: INFRAESTRUCTURA | B22: Baja | C22: Modalidades intramural, extramural domiciliaria, telemedicina categoría telexperticia – prestador remisor | D22: 11.3.2 | E22: 5 | F22: 5.8 | G22: • Ambiente o área de cuarentena de medicamentos
A23: INFRAESTRUCTURA | B23: Baja | C23: Modalidad telemedicina: Categoría interactiva y no interactiva – prestador de referencia Categoría telexperticia – prestador de referencia | D23: 11.3.2 | E23: 6 | G23: Cumple con los criterios que le sean aplicables de todos los servicios
A24: INFRAESTRUCTURA | B24: Mediana y alta | C24: Modalidades intramural, extramural domiciliaria, telemedicina categoría telexperticia – prestador remisor | D24: 11.3.2 | E24: 7 | G24: Cumple con los criterios definidos para el servicio farmacéutico de baja complejidad y adicionalmente cumple con lo definido en el Manual que adopta la Resolución 1403 de 2007, en el Título I Capítulo II numeral 1.2.2 y Título I Capítulo III numeral 1, o las normas que los modifiquen, adicionen o sustituyan
A25: INFRAESTRUCTURA | B25: Mediana y alta | C25: Modalidad telemedicina: Categoría interactiva y no interactiva – prestador de referencia Categoría telexperticia – prestador de referencia | D25: 11.3.2 | E25: 8 | G25: Cumple con los criterios que le sean aplicables de todos los servicios
A26: DOTACIÓN | B26: Todas | C26: Modalidades intramural, extramural domiciliaria, telemedicina categoría telexperticia – prestador remisor | D26: 11.3.2 | E26: 9 | G26: Cumple con los criterios que le sean aplicables de todos los servicios y adicionalmente cuenta con:
A27: DOTACIÓN | B27: Todas | C27: Modalidades intramural, extramural domiciliaria, telemedicina categoría telexperticia – prestador remisor | D27: 11.3.2 | E27: 9 | F27: 9.1 | G27: • La dotación y mobiliario exclusivos y necesarios para el cumplimiento de los objetivos de los procesos generales y especiales que brinda el servicio, de acuerdo con las recomendaciones dadas por los fabricantes.
A28: DOTACIÓN | B28: Todas | C28: Modalidades intramural, extramural domiciliaria, telemedicina categoría telexperticia – prestador remisor | D28: 11.3.2 | E28: 9 | F28: 9.2 | G28: • Instrumentos para medir la humedad relativa y la temperatura, en donde se almacenen medicamentos y dispositivos médicos.
A29: DOTACIÓN | B29: Todas | C29: Modalidad telemedicina Categoría interactiva y no interactiva – prestador de referencia Categoría telexperticia – prestador de referencia | D29: 11.3.2 | E29: 10 | G29: Cumple con los criterios que le sean aplicables de todos los servicios
A30: MEDICAMENTOS, DM E INSUMOS | B30: Baja | C30: Modalidades intramural, extramural domiciliaria, telemedicina categoría telexperticia – prestador remisor | D30: 11.3.2 | E30: 11 | G30: Cumple con los criterios que le sean aplicables de todos los servicios
A31: MEDICAMENTOS, DM E INSUMOS | B31: Baja | C31: Modalidad telemedicina Categoría interactiva y no interactiva – prestador de referencia Categoría telexperticia – prestador de referencia | D31: 11.3.2 | E31: 12 | G31: Cumple con los criterios que le sean aplicables de todos los servicios
A32: MEDICAMENTOS, DM E INSUMOS | B32: Mediana y alta | C32: Modalidades intramural, extramural domiciliaria, telemedicina categoría telexperticia – prestador remisor | D32: 11.3.2 | E32: 13 | G32: Cumple con los criterios definidos para el servicio farmacéutico de baja complejidad y adicionalmente cuenta con: Certificación en buenas prácticas de elaboración vigente, expedida por el Invima para los procesos especiales que se realicen en la central de mezclas ya sea propia o contratada.
A33: MEDICAMENTOS, DM E INSUMOS | B33: Mediana y alta | C33: Modalidad telemedicina: Categoría interactiva y no interactiva – prestador de referencia Categoría telexperticia – prestador de referencia | D33: 11.3.2 | E33: 14 | G33: Cumple con los criterios que le sean aplicables de todos los servicios
A34: PROCESOS PRIORITARIOS | B34: Baja | C34: Modalidades intramural, extramural domiciliaria, telemedicina categoría telexperticia - prestador remisor | D34: 11.3.2 | E34: 15 | G34: Cumple con los criterios que le sean aplicables de todos los servicios y adicionalmente cuenta con la siguiente información documentada:
A35: PROCESOS PRIORITARIOS | B35: Baja | C35: Modalidades intramural, extramural domiciliaria, telemedicina categoría telexperticia - prestador remisor | D35: 11.3.2 | E35: 15 | F35: 15.1 | G35: • Procesos generales que realice, elaborado por el responsable del servicio.
A36: PROCESOS PRIORITARIOS | B36: Baja | C36: Modalidades intramural, extramural domiciliaria, telemedicina categoría telexperticia - prestador remisor | D36: 11.3.2 | E36: 15 | F36: 15.2 | G36: • Información visible al usuario que prohíba la asesoría farmacológica, por parte de personal diferente al profesional químico farmacéutico o al Profesional en Medicina tratante.
A37: PROCESOS PRIORITARIOS | B37: Baja | C37: Modalidades intramural, extramural domiciliaria, telemedicina categoría telexperticia - prestador remisor | D37: 11.3.2 | E37: 15 | F37: 15.3 | G37: • Manejo de medicamentos de control especial cuando lo realice.
A38: PROCESOS PRIORITARIOS | B38: Baja | C38: Modalidades intramural, extramural domiciliaria, telemedicina categoría telexperticia - prestador remisor | D38: 11.3.2 | E38: 15 | F38: 15.4 | G38: • Seguimiento a condiciones ambientales de temperatura y humedad.
A39: PROCESOS PRIORITARIOS | B39: Baja | C39: Modalidad telemedicina: Categoría interactiva y no interactiva – prestador de referencia Categoría telexperticia – prestador de referencia | D39: 11.3.2 | E39: 16 | G39: Cumple con los criterios que le sean aplicables de todos los servicios
A40: PROCESOS PRIORITARIOS | B40: Mediana y alta | C40: Modalidades intramural, extramural domiciliaria, telemedicina categoría telexperticia - prestador remisor | D40: 11.3.2 | E40: 17 | G40: Cumple con los criterios definidos para el servicio farmacéutico en baja complejidad y adicionalmente, cuenta con información documentada de cada uno de los procesos especiales que se realicen en el servicio
A41: PROCESOS PRIORITARIOS | B41: Mediana y alta | C41: Modalidad telemedicina: Categoría interactiva y no interactiva – prestador de referencia Categoría telexperticia – prestador de referencia | D41: 11.3.2 | E41: 18 | G41: Cumple con los criterios que le sean aplicables de todos los servicios
A42: HISTORIA CLÍNICA Y REGISTROS | B42: Todas | C42: Modalidades intramural, extramural domiciliaria, telemedicina categoría telexperticia - prestador remisor | D42: 11.3.2 | E42: 19 | G42: Cumple con los criterios que le sean aplicables de todos los servicios
A43: HISTORIA CLÍNICA Y REGISTROS | B43: Todas | C43: Modalidad telemedicina: Categoría interactiva y no interactiva – prestador de referencia Categoría telexperticia – prestador de referencia | D43: 11.3.2 | E43: 20 | G43: Cumple con los criterios que le sean aplicables de todos los servicios
A44: INTERDEPENDENCIA | B44: Todas | C44: Modalidades intramural, extramural domiciliaria, telemedicina categoría telexperticia - prestador remisor | D44: 11.3.2 | E44: 21 | G44: No aplica
A45: INTERDEPENDENCIA | B45: Todas | C45: Modalidad telemedicina: Categoría interactiva y no interactiva – prestador de referencia Categoría telexperticia – prestador de referencia | D45: 11.3.2 | E45: 22 | G45: No aplica
H46: =COUNTA(H10:H45) -> 0 | I46: =COUNTA(I10:I45) -> 0 | J46: =COUNTA(J10:J45) -> 0
A47: RESULTADO POR ESTANDAR SERVICIO FARMACEUTICO
A48: ESTANDAR | B48: TOTAL CRITERIOS CUMPLE | C48: TOTAL CRITERIOS NO CUMPLE | D48: TOTAL CRITERIOS NO APLICA | E48: % CUMPLIMIENTO
A49: TALENTO HUMANO | B49: =COUNTIFS($A$10:$A$45,A49,$H$10:$H$45,"<>") -> 0 | C49: =COUNTIFS($A$10:$A$45,A49,$I$10:$I$45,"<>") -> 0 | D49: =COUNTIFS($A$10:$A$45,A49,$J$10:$J$45,"<>") -> 0 | E49: =IFERROR(B49/(B49+C49),"")
A50: INFRAESTRUCTURA | B50: =COUNTIFS($A$10:$A$45,A50,$H$10:$H$45,"<>") -> 0 | C50: =COUNTIFS($A$10:$A$45,A50,$I$10:$I$45,"<>") -> 0 | D50: =COUNTIFS($A$10:$A$45,A50,$J$10:$J$45,"<>") -> 0 | E50: =IFERROR(B50/(B50+C50),"")
A51: DOTACIÓN | B51: =COUNTIFS($A$10:$A$45,A51,$H$10:$H$45,"<>") -> 0 | C51: =COUNTIFS($A$10:$A$45,A51,$I$10:$I$45,"<>") -> 0 | D51: =COUNTIFS($A$10:$A$45,A51,$J$10:$J$45,"<>") -> 0 | E51: =IFERROR(B51/(B51+C51),"")
A52: MEDICAMENTOS, DM E INSUMOS | B52: =COUNTIFS($A$10:$A$45,A52,$H$10:$H$45,"<>") -> 0 | C52: =COUNTIFS($A$10:$A$45,A52,$I$10:$I$45,"<>") -> 0 | D52: =COUNTIFS($A$10:$A$45,A52,$J$10:$J$45,"<>") -> 0 | E52: =IFERROR(B52/(B52+C52),"")
A53: PROCESOS PRIORITARIOS | B53: =COUNTIFS($A$10:$A$45,A53,$H$10:$H$45,"<>") -> 0 | C53: =COUNTIFS($A$10:$A$45,A53,$I$10:$I$45,"<>") -> 0 | D53: =COUNTIFS($A$10:$A$45,A53,$J$10:$J$45,"<>") -> 0 | E53: =IFERROR(B53/(B53+C53),"")
A54: HISTORIA CLÍNICA Y REGISTROS | B54: =COUNTIFS($A$10:$A$45,A54,$H$10:$H$45,"<>") -> 0 | C54: =COUNTIFS($A$10:$A$45,A54,$I$10:$I$45,"<>") -> 0 | D54: =COUNTIFS($A$10:$A$45,A54,$J$10:$J$45,"<>") -> 0 | E54: =IFERROR(B54/(B54+C54),"")
A55: INTERDEPENDENCIA | B55: =COUNTIFS($A$10:$A$45,A55,$H$10:$H$45,"<>") -> 0 | C55: =COUNTIFS($A$10:$A$45,A55,$I$10:$I$45,"<>") -> 0 | D55: =COUNTIFS($A$10:$A$45,A55,$J$10:$J$45,"<>") -> 0 | E55: =IFERROR(B55/(B55+C55),"")
A56: TOTAL | B56: =SUM(B49:B55) -> 0 | C56: =SUM(C49:C55) -> 0 | D56: =SUM(D49:D55) -> 0 | E56: =IFERROR(B56/(B56+C56),"")

Sheet RAD ODONT
B1: RADIOLOGÍA ODONTOLÓGICA CONDICIONES DE HABILITACIÓN RESOLUCIÓN 3100/2019 | P1: ESTADO DE ACCIONES (Número de acciones y % por estado) | T1: ESTADO DE ACCIONES (Número de acciones y % por estado) | X1: ESTADO DE ACCIONES (Número de acciones y % por estado) | AB1: ESTADO DE ACCIONES (Número de acciones y % por estado) | AF1: ESTADO DE ACCIONES (Número de acciones y % por estado) | AJ1: ESTADO DE ACCIONES (Número de acciones y % por estado)
P2: SIN INICIAR | Q2: =COUNTIFS(R$10:R$501,P2) -> 0 | R2: =IFERROR(Q2/SUM(Q$2:Q$5),"") | T2: SIN INICIAR | U2: =COUNTIFS(V$10:V$501,T2) -> 0 | V2: =IFERROR(U2/SUM(U$2:U$5),"") | X2: SIN INICIAR | Y2: =COUNTIFS(Z$10:Z$501,X2) -> 0 | Z2: =IFERROR(Y2/SUM(Y$2:Y$5),"") | AB2: SIN INICIAR | AC2: =COUNTIFS(AD$10:AD$501,AB2) -> 0 | AD2: =IFERROR(AC2/SUM(AC$2:AC$5),"") | AF2: SIN INICIAR | AG2: =COUNTIFS(AH$10:AH$501,AF2) -> 0 | AH2: =IFERROR(AG2/SUM(AG$2:AG$5),"") | AJ2: SIN INICIAR | AK2: =COUNTIFS(AL$10:AL$501,AJ2) -> 0 | AL2: =IFERROR(AK2/SUM(AK$2:AK$5),"")
C3: TOTAL CUMPLE | D3: TOTAL NO CUMPLE | E3: TOTAL NO APLICA | P3: EN EJECUCION | Q3: =COUNTIFS(R$10:R$501,P3) -> 0 | R3: =IFERROR(Q3/SUM(Q$2:Q$5),"") | T3: EN EJECUCION | U3: =COUNTIFS(V$10:V$501,T3) -> 0 | V3: =IFERROR(U3/SUM(U$2:U$5),"") | X3: EN EJECUCION | Y3: =COUNTIFS(Z$10:Z$501,X3) -> 0 | Z3: =IFERROR(Y3/SUM(Y$2:Y$5),"") | AB3: EN EJECUCION | AC3: =COUNTIFS(AD$10:AD$501,AB3) -> 0 | AD3: =IFERROR(AC3/SUM(AC$2:AC$5),"") | AF3: EN EJECUCION | AG3: =COUNTIFS(AH$10:AH$501,AF3) -> 0 | AH3: =IFERROR(AG3/SUM(AG$2:AG$5),"") | AJ3: EN EJECUCION | AK3: =COUNTIFS(AL$10:AL$501,AJ3) -> 0 | AL3: =IFERROR(AK3/SUM(AK$2:AK$5),"")
A4: NUMERO DE CRITERIOS EVALUADOS | C4: =COUNTA(H10:H55) -> 15 | D4: =COUNTA(I10:I55) -> 1 | E4: =COUNTA(J10:J55) -> 13 | P4: CERRADA | Q4: =COUNTIFS(R$10:R$501,P4) -> 0 | R4: =IFERROR(Q4/SUM(Q$2:Q$5),"") | T4: CERRADA | U4: =COUNTIFS(V$10:V$501,T4) -> 0 | V4: =IFERROR(U4/SUM(U$2:U$5),"") | X4: CERRADA | Y4: =COUNTIFS(Z$10:Z$501,X4) -> 0 | Z4: =IFERROR(Y4/SUM(Y$2:Y$5),"") | AB4: CERRADA | AC4: =COUNTIFS(AD$10:AD$501,AB4) -> 0 | AD4: =IFERROR(AC4/SUM(AC$2:AC$5),"") | AF4: CERRADA | AG4: =COUNTIFS(AH$10:AH$501,AF4) -> 0 | AH4: =IFERROR(AG4/SUM(AG$2:AG$5),"") | AJ4: CERRADA | AK4: =COUNTIFS(AL$10:AL$501,AJ4) -> 0 | AL4: =IFERROR(AK4/SUM(AK$2:AK$5),"")
A5: CUMPLIMIENTO DEL SERVICIO EVALUADO | C5: =IFERROR(C4/(D4+C4),"") -> 0.9375 | P5: CANCELADA | Q5: =COUNTIFS(R$10:R$501,P5) -> 0 | R5: =IFERROR(Q5/SUM(Q$2:Q$5),"") | T5: CANCELADA | U5: =COUNTIFS(V$10:V$501,T5) -> 0 | V5: =IFERROR(U5/SUM(U$2:U$5),"") | X5: CANCELADA | Y5: =COUNTIFS(Z$10:Z$501,X5) -> 0 | Z5: =IFERROR(Y5/SUM(Y$2:Y$5),"") | AB5: CANCELADA | AC5: =COUNTIFS(AD$10:AD$501,AB5) -> 0 | AD5: =IFERROR(AC5/SUM(AC$2:AC$5),"") | AF5: CANCELADA | AG5: =COUNTIFS(AH$10:AH$501,AF5) -> 0 | AH5: =IFERROR(AG5/SUM(AG$2:AG$5),"") | AJ5: CANCELADA | AK5: =COUNTIFS(AL$10:AL$501,AJ5) -> 0 | AL5: =IFERROR(AK5/SUM(AK$2:AK$5),"")
P6: TOTAL | Q6: =SUM(Q2:Q5) -> 0 | T6: TOTAL | U6: =SUM(U2:U5) -> 0 | X6: TOTAL | Y6: =SUM(Y2:Y5) -> 0 | AB6: TOTAL | AC6: =SUM(AC2:AC5) -> 0 | AF6: TOTAL | AG6: =SUM(AG2:AG5) -> 0 | AJ6: TOTAL | AK6: =SUM(AK2:AK5) -> 0
P8: SEGUIMIENTO 1 - Fecha: | T8: SEGUIMIENTO 2 - Fecha: | X8: SEGUIMIENTO 3 - Fecha: | AB8: SEGUIMIENTO 4 - Fecha: | AF8: SEGUIMIENTO 5 - Fecha: | AJ8: SEGUIMIENTO 6 - Fecha:
A9: ESTANDAR | B9: COMPLEJIDAD | C9: MODALIDAD | D9: ARTICULO | E9: SECCIÓN | F9: APARTADO | G9: CRITERIO | H9: CUMPLE | I9: NO CUMPLE | J9: NO APLICA | K9: HALLAZGOS | M9: ACCIÓN PARA EL CUMPLIMIENTO | N9: RESPONSABLE | O9: FECHA LIMITE PARA IMPLEMENTAR | P9: SEGUIMIENTO 1 | R9: ESTADO DE LA ACCIÓN 1 | T9: SEGUIMIENTO 2 | V9: ESTADO DE LA ACCIÓN 2 | X9: SEGUIMIENTO 3 | Z9: ESTADO DE LA ACCIÓN 3 | AB9: SEGUIMIENTO 4 | AD9: ESTADO DE LA ACCIÓN 4 | AF9: SEGUIMIENTO 5 | AH9: ESTADO DE LA ACCIÓN 5 | AJ9: SEGUIMIENTO 6 | AL9: ESTADO DE LA ACCIÓN 6
A10: TALENTO HUMANO | B10: No aplica | C10: Modalidades intramural y extramural unidad móvil | D10: 11.3.3 | E10: 1 | G10: Cumple con los criterios que le sean aplicables de todos los servicios y adicionalmente, cuenta con: Profesional de odontología o tecnólogo en radiología e imágenes diagnósticas, o técnico profesional o auxiliar de odontología o auxiliar en salud oral o auxiliar de higiene oral. | H10: X
A11: TALENTO HUMANO | B11: No aplica | C11: Modalidades intramural y extramural unidad móvil | D11: 11.3.3 | E11: 2 | G11: Disponibilidad de profesional de la odontología, si la toma de radiografías la realiza un auxiliar de odontología o auxiliar en salud oral o auxiliar de higiene oral. | H11: X
A12: TALENTO HUMANO | B12: No aplica | C12: Modalidades intramural y extramural unidad móvil | D12: 11.3.3 | E12: 3 | G12: La interpretación de las radiografías odontológicas es realizada por el profesional de la odontología. | H12: X
A13: TALENTO HUMANO | B13: No aplica | C13: Modalidad telemedicina: Categoría telexperticia - prestador remisor | D13: 11.3.3 | E13: 4 | G13: Cumple con los criterios que le sean aplicables de todos los servicios y adicionalmente: | J13: X
A14: TALENTO HUMANO | B14: No aplica | C14: Modalidad telemedicina: Categoría telexperticia - prestador remisor | D14: 11.3.3 | E14: 4 | F14: 4.1 | G14: • Cuando se realice telexperticia entre profesionales de la salud cuenta con el profesional de la salud. | J14: X
A15: TALENTO HUMANO | B15: No aplica | C15: Modalidad telemedicina: Categoría telexperticia - prestador remisor | D15: 11.3.3 | E15: 4 | F15: 4.2 | G15: • Cuando realice telexperticia entre personal de salud no profesional y un profesional de la salud, el prestador remisor cuenta con técnico, tecnólogo o auxiliar que atiende presencialmente al usuario. | J15: X
A16: TALENTO HUMANO | B16: No aplica | C16: Modalidad telemedicina: Categoría telexperticia - prestador de referencia | D16: 11.3.3 | E16: 5 | G16: Cumple con los criterios que le sean aplicables de todos los servicios y adicionalmente cuenta con profesional de la salud que atiende a distancia | J16: X
A17: INFRAESTRUCTURA | B17: No aplica | C17: Modalidades intramural, telemedicina - prestador remisor | D17: 11.3.3 | E17: 6 | G17: Cumple con los criterios que le sean aplicables de todos los servicios y adicionalmente cuenta con:
A18: INFRAESTRUCTURA | B18: No aplica | C18: Modalidades intramural, telemedicina - prestador remisor | D18: 11.3.3 | E18: 6 | F18: 6.1 | G18: • Ambiente de radiología odontológica, si la tecnología lo requiere. Las dimensiones estarán determinadas según la ficha técnica del equipo. | H18: X
A19: INFRAESTRUCTURA | B19: No aplica | C19: Modalidades intramural, telemedicina - prestador remisor | D19: 11.3.3 | E19: 6 | F19: 6.2 | G19: • Área de revelado o ambiente oscuro con extracción de gases e iluminación adecuada, con mesón de trabajo con poceta, si la tecnología lo requiere. | H19: X
A20: INFRAESTRUCTURA | B20: No aplica | C20: Modalidades intramural, telemedicina - prestador remisor | D20: 11.3.3 | E20: 7 | G20: Disponibilidad de:
A21: INFRAESTRUCTURA | B21: No aplica | C21: Modalidades intramural, telemedicina - prestador remisor | D21: 11.3.3 | E21: 7 | F21: 7.1 | G21: • Sala de espera | H21: X
A22: INFRAESTRUCTURA | B22: No aplica | C22: Modalidades intramural, telemedicina - prestador remisor | D22: 11.3.3 | E22: 7 | F22: 7.2 | G22: • Unidades sanitarias discriminadas por sexo | I22: X
A23: INFRAESTRUCTURA | B23: No aplica | C23: Modalidades extramural unidad móvil, telemedicina - prestador remisor | D23: 11.3.3 | E23: 8 | G23: Adicional a lo establecido en la modalidad intramural, cuenta con acceso al servicio de energía eléctrica o fuente de energía alternativa | H23: X
A24: INFRAESTRUCTURA | B24: No aplica | C24: Modalidad telemedicina - prestador de referencia | D24: 11.3.3 | E24: 9 | G24: Cumple con los criterios que le sean aplicables de todos los servicios. | H24: X
A25: DOTACIÓN | B25: No aplica | C25: Modalidades intramural, telemedicina - prestador remisor | D25: 11.3.3 | E25: 10 | G25: Cumple con los criterios que le sean aplicables de todos los servicios y adicionalmente, cuenta con: | H25: X
A26: DOTACIÓN | B26: No aplica | C26: Modalidades intramural, telemedicina - prestador remisor | D26: 11.3.3 | E26: 10 | F26: 10.1 | G26: • Equipo generador de radiación ionizante según los exámenes diagnósticos realizados. | H26: X
A27: DOTACIÓN | B27: No aplica | C27: Modalidades intramural, telemedicina - prestador remisor | D27: 11.3.3 | E27: 10 | F27: 10.2 | G27: • Elementos de protección radiológica adulto o pediátrico, según oferta, protocolos y especificaciones técnicas del equipo: | H27: X
A28: DOTACIÓN | B28: No aplica | C28: Modalidades intramural, telemedicina - prestador remisor | D28: 11.3.3 | E28: 10 | F28: 10.2.1 | G28: • Delantal plomado | H28: X
A29: DOTACIÓN | B29: No aplica | C29: Modalidades intramural, telemedicina - prestador remisor | D29: 11.3.3 | E29: 10 | F29: 10.2.2 | G29: • Protector de tiroides | H29: X
A30: DOTACIÓN | B30: No aplica | C30: Modalidades extramural - unidad móvil, telemedicina - prestador remisor | D30: 11.3.3 | E30: 11 | G30: Adicional a lo establecido en la modalidad intramural, cuenta con:
A31: DOTACIÓN | B31: No aplica | C31: Modalidades extramural - unidad móvil, telemedicina - prestador remisor | D31: 11.3.3 | E31: 11 | F31: 11.1 | G31: • Equipo generador de radiación ionizante según la oferta, cuyas indicaciones del fabricante refieran que está diseñado para ser instalado y operado y mantenido en una unidad móvil. | J31: X
A32: DOTACIÓN | B32: No aplica | C32: Modalidades extramural - unidad móvil, telemedicina - prestador remisor | D32: 11.3.3 | E32: 11 | F32: 11.2 | G32: • La unidad móvil está dotada con señal luminosa o sonora indicando la presencia de radiación. | J32: X
A33: DOTACIÓN | B33: No aplica | C33: Modalidad telemedicina - prestador remisor | D33: 11.3.3 | E33: 12 | G33: Adicional a lo establecido en el numeral 11 del servicio de radiología odontológica, cuenta con equipo de captura y transmisión de datos e imágenes que asegure las condiciones de visualización de imagen y lectura, el cual puede estar integrado al equipo generador de radiaciones ionizantes | J33: X
A34: DOTACIÓN | B34: No aplica | C34: Modalidad telemedicina - prestador de referencia | D34: 11.3.3 | E34: 13 | G34: Cumple con los criterios que le sean aplicables de todos los servicios y adicionalmente, cuenta con pantalla o monitor grado médico para imágenes radiológicas | J34: X
A35: MEDICAMENTOS, DM E INSUMOS | B35: No aplica | C35: Modalidades intramural, extramural unidad móvil, telemedicina - prestador remisor - prestador de referencia | D35: 11.3.3 | E35: 14 | G35: Cumple con los criterios que le sean aplicables de todos los servicios | H35: X
A36: PROCESOS PRIORITARIOS | B36: No aplica | C36: Modalidades intramural, telemedicina - prestador remisor | D36: 11.3.3 | E36: 15 | G36: Cumple con los criterios que le sean aplicables de todos los servicios y adicionalmente cuenta con la siguiente información documentada:
A37: PROCESOS PRIORITARIOS | B37: No aplica | C37: Modalidades intramural, telemedicina - prestador remisor | D37: 11.3.3 | E37: 15 | F37: 15.1 | G37: • Toma de exámenes que impliquen el manejo de cualquier tipo de radiación ionizante, que incluya las acciones para evitar el efecto nocivo de las radiaciones para los pacientes, el personal, los visitantes y el público en general.
A38: PROCESOS PRIORITARIOS | B38: No aplica | C38: Modalidades intramural, telemedicina - prestador remisor | D38: 11.3.3 | E38: 15 | F38: 15.2 | G38: • Verificación de la calidad de la imagen, del equipo generador de radiación ionizante, que incluye la toma de medidas preventivas y correctivas cuando apliquen.
A39: PROCESOS PRIORITARIOS | B39: No aplica | C39: Modalidades intramural, telemedicina - prestador remisor | D39: 11.3.3 | E39: 15 | F39: 15.3 | G39: • Verificación de la adherencia a los procedimientos realizados en la instalación y cualquier otra consideración sobre la protección radiológica de la instalación.
A40: PROCESOS PRIORITARIOS | B40: No aplica | C40: Modalidades intramural, telemedicina - prestador remisor | D40: 11.3.3 | E40: 15 | F40: 15.4 | G40: • Realización y supervisión de toma de radiografías odontológicas cuando no sea realizada por el odontólogo, que incluya como mínimo la calidad de la imagen y radioprotección.
A41: PROCESOS PRIORITARIOS | B41: No aplica | C41: Modalidades intramural, telemedicina - prestador remisor | D41: 11.3.3 | E41: 15 | F41: 15.5 | G41: • Interpretación y lectura de las radiografías odontológicas por parte del Odontólogo.
A42: PROCESOS PRIORITARIOS | B42: No aplica | C42: Modalidad extramural unidad móvil, telemedicina - prestador remisor | D42: 11.3.3 | E42: 16 | G42: Adicional a lo anterior cuenta con la siguiente información documentada: | J42: X
A43: PROCESOS PRIORITARIOS | B43: No aplica | C43: Modalidad extramural unidad móvil, telemedicina - prestador remisor | D43: 11.3.3 | E43: 16 | F43: 16.1 | G43: • Verificación de la calidad de la imagen, para cada desplazamiento realizado por la Unidad móvil en la que está instalado el equipo generador de radiación ionizante, que incluye la toma de medidas preventivas y correctivas cuando apliquen. | J43: X
A44: PROCESOS PRIORITARIOS | B44: No aplica | C44: Modalidad extramural unidad móvil, telemedicina - prestador remisor | D44: 11.3.3 | E44: 16 | F44: 16.2 | G44: • Evaluación de los niveles de exposición ocupacional del personal involucrado en la práctica y del público, así como la inspección del blindaje del vehículo (carrocería) donde se pretende realizar la práctica. | J44: X
A45: PROCESOS PRIORITARIOS | B45: No aplica | C45: Modalidad telemedicina - prestador de referencia | D45: 11.3.3 | E45: 17 | G45: Cumple con los criterios que le sean aplicables de todos los servicios | J45: X
A46: HISTORIA CLÍNICA Y REGISTROS | B46: No aplica | C46: Modalidades intramural, telemedicina - prestador remisor | D46: 11.3.3 | E46: 18 | G46: Cumple con los criterios que le sean aplicables de todos los servicios y adicionalmente, cuenta con los siguientes registros: | H46: X
A47: HISTORIA CLÍNICA Y REGISTROS | B47: No aplica | C47: Modalidades intramural, telemedicina - prestador remisor | D47: 11.3.3 | E47: 18 | F47: 18.1 | G47: • Número de exposiciones, e imágenes tomadas que incluya el nombre del paciente, y nombre del estudio realizado.
A48: HISTORIA CLÍNICA Y REGISTROS | B48: No aplica | C48: Modalidades intramural, telemedicina - prestador remisor | D48: 11.3.3 | E48: 18 | F48: 18.2 | G48: • Dosis de radiación expresadas en unidades según sea la tecnología del equipo.
A49: HISTORIA CLÍNICA Y REGISTROS | B49: No aplica | C49: Modalidades intramural, telemedicina - prestador remisor | D49: 11.3.3 | E49: 18 | F49: 18.3 | G49: • Número de estudios rechazados de acuerdo a la tecnología empleada
A50: HISTORIA CLÍNICA Y REGISTROS | B50: No aplica | C50: Modalidades extramural unidad móvil, telemedicina - prestador remisor | D50: 11.3.3 | E50: 19 | G50: Adicional a lo anterior cuenta con:
A51: HISTORIA CLÍNICA Y REGISTROS | B51: No aplica | C51: Modalidades extramural unidad móvil, telemedicina - prestador remisor | D51: 11.3.3 | E51: 19 | F51: 19.1 | G51: • Registro de verificación de la calidad de imagen.
A52: HISTORIA CLÍNICA Y REGISTROS | B52: No aplica | C52: Modalidades extramural unidad móvil, telemedicina - prestador remisor | D52: 11.3.3 | E52: 19 | F52: 19.2 | G52: • Registro del control de calidad general.
A53: HISTORIA CLÍNICA Y REGISTROS | B53: No aplica | C53: Modalidades extramural unidad móvil, telemedicina - prestador remisor | D53: 11.3.3 | E53: 19 | F53: 19.3 | G53: • Registro de la evaluación de los niveles de exposición ocupacional tanto del personal involucrado en la práctica, como del público.
A54: HISTORIA CLÍNICA Y REGISTROS | B54: No aplica | C54: Modalidad telemedicina - prestador de referencia | D54: 11.3.3 | E54: 20 | G54: Cumple con los criterios que le sean aplicables de todos los servicios
A55: INTERDEPENDENCIA | B55: No aplica | C55: Modalidades intramural, extramural unidad móvil, telemedicina – prestador remisor – prestador de referencia | D55: 11.3.3 | E55: 21 | G55: No aplica | J55: X
H56: =COUNTA(H10:H55) -> 15 | I56: =COUNTA(I10:I55) -> 1 | J56: =COUNTA(J10:J55) -> 13
A57: RESULTADO POR ESTANDAR RADIOLOGÍA ODONTOLÓGICA
A58: ESTANDAR | B58: TOTAL CRITERIOS CUMPLE | C58: TOTAL CRITERIOS NO CUMPLE | D58: TOTAL CRITERIOS NO APLICA | E58: % CUMPLIMIENTO
A59: TALENTO HUMANO | B59: =COUNTIFS($A$10:$A$55,A59,$H$10:$H$55,"<>") -> 3 | C59: =COUNTIFS($A$10:$A$55,A59,$I$10:$I$55,"<>") -> 0 | D59: =COUNTIFS($A$10:$A$55,A59,$J$10:$J$55,"<>") -> 4 | E59: =IFERROR(B59/(B59+C59),"") -> 1
A60: INFRAESTRUCTURA | B60: =COUNTIFS($A$10:$A$55,A60,$H$10:$H$55,"<>") -> 5 | C60: =COUNTIFS($A$10:$A$55,A60,$I$10:$I$55,"<>") -> 1 | D60: =COUNTIFS($A$10:$A$55,A60,$J$10:$J$55,"<>") -> 0 | E60: =IFERROR(B60/(B60+C60),"") -> 0.83333333
A61: DOTACIÓN | B61: =COUNTIFS($A$10:$A$55,A61,$H$10:$H$55,"<>") -> 5 | C61: =COUNTIFS($A$10:$A$55,A61,$I$10:$I$55,"<>") -> 0 | D61: =COUNTIFS($A$10:$A$55,A61,$J$10:$J$55,"<>") -> 4 | E61: =IFERROR(B61/(B61+C61),"") -> 1
A62: MEDICAMENTOS, DM E INSUMOS | B62: =COUNTIFS($A$10:$A$55,A62,$H$10:$H$55,"<>") -> 1 | C62: =COUNTIFS($A$10:$A$55,A62,$I$10:$I$55,"<>") -> 0 | D62: =COUNTIFS($A$10:$A$55,A62,$J$10:$J$55,"<>") -> 0 | E62: =IFERROR(B62/(B62+C62),"") -> 1
A63: PROCESOS PRIORITARIOS | B63: =COUNTIFS($A$10:$A$55,A63,$H$10:$H$55,"<>") -> 0 | C63: =COUNTIFS($A$10:$A$55,A63,$I$10:$I$55,"<>") -> 0 | D63: =COUNTIFS($A$10:$A$55,A63,$J$10:$J$55,"<>") -> 4 | E63: =IFERROR(B63/(B63+C63),"")
A64: HISTORIA CLÍNICA Y REGISTROS | B64: =COUNTIFS($A$10:$A$55,A64,$H$10:$H$55,"<>") -> 1 | C64: =COUNTIFS($A$10:$A$55,A64,$I$10:$I$55,"<>") -> 0 | D64: =COUNTIFS($A$10:$A$55,A64,$J$10:$J$55,"<>") -> 0 | E64: =IFERROR(B64/(B64+C64),"") -> 1
A65: INTERDEPENDENCIA | B65: =COUNTIFS($A$10:$A$55,A65,$H$10:$H$55,"<>") -> 0 | C65: =COUNTIFS($A$10:$A$55,A65,$I$10:$I$55,"<>") -> 0 | D65: =COUNTIFS($A$10:$A$55,A65,$J$10:$J$55,"<>") -> 1 | E65: =IFERROR(B65/(B65+C65),"")
A66: TOTAL | B66: =SUM(B59:B65) -> 15 | C66: =SUM(C59:C65) -> 1 | D66: =SUM(D59:D65) -> 13 | E66: =IFERROR(B66/(B66+C66),"") -> 0.9375

Sheet IMAG DIAG ION
B1: IMÁGENES DIAGNÓSTICAS - METODOS DIAGNÓSTICOS CON IMÁGENES OBTENIDAS MEDIANTE EQUIPOS GENERADORES DE RADIACIONES IONIZANTES CONDICIONES DE HABILITACIÓN RESOLUCIÓN 3100/2019 | P1: ESTADO DE ACCIONES (Número de acciones y % por estado) | T1: ESTADO DE ACCIONES (Número de acciones y % por estado) | X1: ESTADO DE ACCIONES (Número de acciones y % por estado) | AB1: ESTADO DE ACCIONES (Número de acciones y % por estado) | AF1: ESTADO DE ACCIONES (Número de acciones y % por estado) | AJ1: ESTADO DE ACCIONES (Número de acciones y % por estado)
P2: SIN INICIAR | Q2: =COUNTIFS(R$10:R$500,P2) -> 0 | R2: =IFERROR(Q2/SUM(Q$2:Q$5),"") | T2: SIN INICIAR | U2: =COUNTIFS(V$10:V$500,T2) -> 0 | V2: =IFERROR(U2/SUM(U$2:U$5),"") | X2: SIN INICIAR | Y2: =COUNTIFS(Z$10:Z$500,X2) -> 0 | Z2: =IFERROR(Y2/SUM(Y$2:Y$5),"") | AB2: SIN INICIAR | AC2: =COUNTIFS(AD$10:AD$500,AB2) -> 0 | AD2: =IFERROR(AC2/SUM(AC$2:AC$5),"") | AF2: SIN INICIAR | AG2: =COUNTIFS(AH$10:AH$500,AF2) -> 0 | AH2: =IFERROR(AG2/SUM(AG$2:AG$5),"") | AJ2: SIN INICIAR | AK2: =COUNTIFS(AL$10:AL$500,AJ2) -> 0 | AL2: =IFERROR(AK2/SUM(AK$2:AK$5),"")
C3: TOTAL CUMPLE | D3: TOTAL NO CUMPLE | E3: TOTAL NO APLICA | P3: EN EJECUCION | Q3: =COUNTIFS(R$10:R$500,P3) -> 0 | R3: =IFERROR(Q3/SUM(Q$2:Q$5),"") | T3: EN EJECUCION | U3: =COUNTIFS(V$10:V$500,T3) -> 0 | V3: =IFERROR(U3/SUM(U$2:U$5),"") | X3: EN EJECUCION | Y3: =COUNTIFS(Z$10:Z$500,X3) -> 0 | Z3: =IFERROR(Y3/SUM(Y$2:Y$5),"") | AB3: EN EJECUCION | AC3: =COUNTIFS(AD$10:AD$500,AB3) -> 0 | AD3: =IFERROR(AC3/SUM(AC$2:AC$5),"") | AF3: EN EJECUCION | AG3: =COUNTIFS(AH$10:AH$500,AF3) -> 0 | AH3: =IFERROR(AG3/SUM(AG$2:AG$5),"") | AJ3: EN EJECUCION | AK3: =COUNTIFS(AL$10:AL$500,AJ3) -> 0 | AL3: =IFERROR(AK3/SUM(AK$2:AK$5),"")
A4: NUMERO DE CRITERIOS EVALUADOS | C4: =COUNTA(H10:H98) -> 0 | D4: =COUNTA(I10:I98) -> 0 | E4: =COUNTA(J10:J98) -> 0 | P4: CERRADA | Q4: =COUNTIFS(R$10:R$500,P4) -> 0 | R4: =IFERROR(Q4/SUM(Q$2:Q$5),"") | T4: CERRADA | U4: =COUNTIFS(V$10:V$500,T4) -> 0 | V4: =IFERROR(U4/SUM(U$2:U$5),"") | X4: CERRADA | Y4: =COUNTIFS(Z$10:Z$500,X4) -> 0 | Z4: =IFERROR(Y4/SUM(Y$2:Y$5),"") | AB4: CERRADA | AC4: =COUNTIFS(AD$10:AD$500,AB4) -> 0 | AD4: =IFERROR(AC4/SUM(AC$2:AC$5),"") | AF4: CERRADA | AG4: =COUNTIFS(AH$10:AH$500,AF4) -> 0 | AH4: =IFERROR(AG4/SUM(AG$2:AG$5),"") | AJ4: CERRADA | AK4: =COUNTIFS(AL$10:AL$500,AJ4) -> 0 | AL4: =IFERROR(AK4/SUM(AK$2:AK$5),"")
A5: CUMPLIMIENTO DEL SERVICIO EVALUADO | C5: =IFERROR(C4/(D4+C4),"") | P5: CANCELADA | Q5: =COUNTIFS(R$10:R$500,P5) -> 0 | R5: =IFERROR(Q5/SUM(Q$2:Q$5),"") | T5: CANCELADA | U5: =COUNTIFS(V$10:V$500,T5) -> 0 | V5: =IFERROR(U5/SUM(U$2:U$5),"") | X5: CANCELADA | Y5: =COUNTIFS(Z$10:Z$500,X5) -> 0 | Z5: =IFERROR(Y5/SUM(Y$2:Y$5),"") | AB5: CANCELADA | AC5: =COUNTIFS(AD$10:AD$500,AB5) -> 0 | AD5: =IFERROR(AC5/SUM(AC$2:AC$5),"") | AF5: CANCELADA | AG5: =COUNTIFS(AH$10:AH$500,AF5) -> 0 | AH5: =IFERROR(AG5/SUM(AG$2:AG$5),"") | AJ5: CANCELADA | AK5: =COUNTIFS(AL$10:AL$500,AJ5) -> 0 | AL5: =IFERROR(AK5/SUM(AK$2:AK$5),"")
P6: TOTAL | Q6: =SUM(Q2:Q5) -> 0 | T6: TOTAL | U6: =SUM(U2:U5) -> 0 | X6: TOTAL | Y6: =SUM(Y2:Y5) -> 0 | AB6: TOTAL | AC6: =SUM(AC2:AC5) -> 0 | AF6: TOTAL | AG6: =SUM(AG2:AG5) -> 0 | AJ6: TOTAL | AK6: =SUM(AK2:AK5) -> 0
P8: SEGUIMIENTO 1 - Fecha: | T8: SEGUIMIENTO 2 - Fecha: | X8: SEGUIMIENTO 3 - Fecha: | AB8: SEGUIMIENTO 4 - Fecha: | AF8: SEGUIMIENTO 5 - Fecha: | AJ8: SEGUIMIENTO 6 - Fecha:
A9: ESTANDAR | B9: COMPLEJIDAD | C9: MODALIDAD | D9: ARTICULO | E9: SECCIÓN | F9: APARTADO | G9: CRITERIO | H9: CUMPLE | I9: NO CUMPLE | J9: NO APLICA | K9: HALLAZGOS | M9: ACCIÓN PARA EL CUMPLIMIENTO | N9: RESPONSABLE | O9: FECHA LIMITE PARA IMPLEMENTAR | P9: SEGUIMIENTO 1 | R9: ESTADO DE LA ACCIÓN 1 | T9: SEGUIMIENTO 2 | V9: ESTADO DE LA ACCIÓN 2 | X9: SEGUIMIENTO 3 | Z9: ESTADO DE LA ACCIÓN 3 | AB9: SEGUIMIENTO 4 | AD9: ESTADO DE LA ACCIÓN 4 | AF9: SEGUIMIENTO 5 | AH9: ESTADO DE LA ACCIÓN 5 | AJ9: SEGUIMIENTO 6 | AL9: ESTADO DE LA ACCIÓN 6
A10: TALENTO HUMANO | B10: Baja | C10: Modalidades intramural, extramural unidad móvil, telemedicina - prestador remisor | D10: 11.3.4.1 | E10: 1 | G10: Cumple con los criterios que le sean aplicables de todos los servicios y adicionalmente,
A11: TALENTO HUMANO | B11: Baja | C11: Modalidades intramural, extramural unidad móvil, telemedicina - prestador remisor | D11: 11.3.4.1 | E11: 2 | G11: Cuenta con: Técnico profesional o tecnólogo en imágenes diagnósticas, para la operación de equipos y adquisición de imágenes.
A12: TALENTO HUMANO | B12: Baja | C12: Modalidades intramural, extramural unidad móvil, telemedicina - prestador remisor | D12: 11.3.4.1 | E12: 3 | G12: Disponibilidad de: Médico especializado en radiología e imágenes diagnósticas o aquellos médicos especialistas quienes en su pensum o formación académica hayan adquirido los conocimientos del manejo e interpretación del espectro electromagnético, del ultrasonido especialmente, así como de las radiaciones ionizantes para establecer el diagnóstico y/o el tratamiento de las enfermedades inherentes a sus especialidades, para lo cual deberán acreditar el respectivo certificado. La interpretación de las radiografías e imágenes diagnósticas y la supervisión del técnico profesional o tecnólogo en imágenes diagnósticas es realizada por dichos profesionales.
A13: TALENTO HUMANO | B13: Mediana | C13: Modalidades extramural unidad móvil, telemedicina - prestador remisor | D13: 11.3.4.1 | E13: 4 | G13: Cumple con los criterios que le sean aplicables de todos los servicios y adicionalmente cuenta con:
A14: TALENTO HUMANO | B14: Mediana | C14: Modalidades extramural unidad móvil, telemedicina - prestador remisor | D14: 11.3.4.1 | E14: 4 | F14: 4.1 | G14: • Tecnólogo en radiología e imágenes diagnósticas para la operación de equipos y adquisición de imágenes, con supervisión por el profesional de la medicina especialista en radiología e imágenes diagnósticas.
A15: TALENTO HUMANO | B15: Mediana | C15: Modalidades extramural unidad móvil, telemedicina - prestador remisor | D15: 11.3.4.1 | E15: 4 | F15: 4.2 | G15: • Médico especializado en radiología e imágenes diagnósticas o aquellos médicos especialistas quienes en su pensum o formación académica hayan adquirido los conocimientos del manejo e interpretación del espectro electromagnético, del ultrasonido especialmente, así como de las radiaciones ionizantes para establecer el diagnóstico y/o el tratamiento de las enfermedades inherentes a sus especialidades, para lo cual deberán acreditar el respectivo certificado. La interpretación de las radiografías e imágenes diagnósticas y la supervisión del técnico profesional o tecnólogo en imágenes diagnósticas es realizada por dichos profesionales.
A16: TALENTO HUMANO | B16: Mediana y alta | C16: Modalidades intramural, telemedicina - prestador remisor | D16: 11.3.4.1 | E16: 5 | G16: Cumple con los criterios que le sean aplicables de todos los servicios y adicionalmente cuenta con:
A17: TALENTO HUMANO | B17: Mediana y alta | C17: Modalidades intramural, telemedicina - prestador remisor | D17: 11.3.4.1 | E17: 5 | F17: 5.1 | G17: • Tecnólogo en radiología e imágenes diagnósticas para la operación de equipos y adquisición de imágenes, con supervisión por el profesional de la medicina especialista en radiología e imágenes diagnósticas.
A18: TALENTO HUMANO | B18: Mediana y alta | C18: Modalidades intramural, telemedicina - prestador remisor | D18: 11.3.4.1 | E18: 5 | F18: 5.2 | G18: • Médico especializado en radiología e imágenes diagnósticas o aquellos médicos especialistas quienes en su pensum o formación académica hayan adquirido los conocimientos del manejo e interpretación del espectro electromagnético, del ultrasonido especialmente, así como de las radiaciones ionizantes para establecer el diagnóstico y/o el tratamiento de las enfermedades inherentes a sus especialidades, para lo cual deberán acreditar el respectivo certificado. La interpretación de las radiografías e imágenes diagnósticas y la supervisión del técnico profesional o tecnólogo en imágenes diagnósticas es realizada por dichos profesionales.
A19: TALENTO HUMANO | B19: Todas | C19: Modalidad telemedicina - prestador de referencia | D19: 11.3.4.1 | E19: 6 | G19: Cumple con los criterios que le sean aplicables de todos los servicios.
A20: TALENTO HUMANO | B20: Todas | C20: Modalidad telemedicina - prestador de referencia | D20: 11.3.4.1 | E20: 7 | G20: La interpretación de las imágenes diagnósticas es realizada médico especializado en radiología e imágenes diagnósticas o aquellos médicos especialistas quienes en su pensum o formación académica hayan adquirido los conocimientos del manejo e interpretación del espectro electromagnético, del ultrasonido especialmente, así como de las radiaciones ionizantes para establecer el diagnóstico y/o el tratamiento de las enfermedades inherentes a sus especialidades, para lo cual deberán acreditar el respectivo certificado
A21: INFRAESTRUCTURA | B21: Todas | C21: Modalidades intramural, telemedicina - prestador remisor | D21: 11.3.4.1 | E21: 8 | G21: Cumple con los criterios que le sean aplicables de todos los servicios y adicionalmente cuenta con:
A22: INFRAESTRUCTURA | B22: Todas | C22: Modalidades intramural, telemedicina - prestador remisor | D22: 11.3.4.1 | E22: 8 | F22: 8.1 | G22: • Vestidor de pacientes, con disponibilidad de área para casilleros, que puede ser compartido con los ambientes de la baja, mediana y alta complejidad.
A23: INFRAESTRUCTURA | B23: Todas | C23: Modalidades intramural, telemedicina - prestador remisor | D23: 11.3.4.1 | E23: 8 | F23: 8.2 | G23: • Área para almacenamiento de dispositivos médicos e insumos, que puede ser compartido con los ambientes de la baja, mediana y alta complejidad.
A24: INFRAESTRUCTURA | B24: Todas | C24: Modalidades intramural, telemedicina - prestador remisor | D24: 11.3.4.1 | E24: 8 | F24: 8.3 | G24: • Ambiente oscuro con luz de seguridad de acuerdo con la tecnología del equipo o, área o ambiente de procesamiento de imágenes, cuando se requiera. Puede ser compartido con los ambientes de la baja, mediana y alta complejidad.
A25: INFRAESTRUCTURA | B25: Todas | C25: Modalidades intramural, telemedicina - prestador remisor | D25: 11.3.4.1 | E25: 9 | G25: Disponibilidad de:
A26: INFRAESTRUCTURA | B26: Todas | C26: Modalidades intramural, telemedicina - prestador remisor | D26: 11.3.4.1 | E26: 9 | F26: 9.1 | G26: • Sala de espera
A27: INFRAESTRUCTURA | B27: Todas | C27: Modalidades intramural, telemedicina - prestador remisor | D27: 11.3.4.1 | E27: 9 | F27: 9.2 | G27: • Unidades sanitarias discriminadas por sexo.
A28: INFRAESTRUCTURA | B28: Todas | C28: Modalidades intramural, telemedicina - prestador remisor | D28: 11.3.4.1 | E28: 9 | F28: 9.3 | G28: • Ambiente de lectura y transcripción de resultados
A29: INFRAESTRUCTURA | B29: Baja | C29: Modalidades intramural, telemedicina - prestador remisor | D29: 11.3.4.1 | E29: 10 | G29: Cuando se realicen procedimientos de radiología, adicionalmente cuenta con:
A30: INFRAESTRUCTURA | B30: Baja | C30: Modalidades intramural, telemedicina - prestador remisor | D30: 11.3.4.1 | E30: 10 | F30: 10.1 | G30: • Ambiente exclusivo, para el equipo generador de radiación ionizante. La dimensión de este ambiente debe ser acorde al tipo de equipo generador de radiación ionizante, su ficha técnica y a los procedimientos que se realicen, debe permitir movilización del talento humano, pacientes, usuarios y equipos biomédicos.
A31: INFRAESTRUCTURA | B31: Baja | C31: Modalidades intramural, telemedicina - prestador remisor | D31: 11.3.4.1 | E31: 10 | F31: 10.2 | G31: • Área o ambiente de control / comando del equipo, de acuerdo con la tecnología a utilizar, que permita visualización del paciente.
A32: INFRAESTRUCTURA | B32: Mediana | C32: Modalidades intramural, telemedicina - prestador remisor | D32: 11.3.4.1 | E32: 11 | G32: Cuando se realicen procedimientos de radiología sin medio de contraste, cumple con los criterios de la complejidad baja.
A33: INFRAESTRUCTURA | B33: Mediana | C33: Modalidades intramural, telemedicina - prestador remisor | D33: 11.3.4.1 | E33: 12 | G33: Cuando se realicen procedimientos con medio de contraste, cuenta con:
A34: INFRAESTRUCTURA | B34: Mediana | C34: Modalidades intramural, telemedicina - prestador remisor | D34: 11.3.4.1 | E34: 12 | F34: 12.1 | G34: • Ambiente exclusivo acorde al tipo de equipo generador de radiación ionizante, su ficha técnica y a los procedimientos que se realicen, debe permitir movilización del talento humano, pacientes, usuarios y equipos biomédicos.
A35: INFRAESTRUCTURA | B35: Mediana | C35: Modalidades intramural, telemedicina - prestador remisor | D35: 11.3.4.1 | E35: 12 | F35: 12.2 | G35: • Área o ambiente de control / comando del equipo, de acuerdo con la tecnología a utilizar, que permita visualización del paciente.
A36: INFRAESTRUCTURA | B36: Mediana | C36: Modalidades intramural, telemedicina - prestador remisor | D36: 11.3.4.1 | E36: 12 | F36: 12.3 | G36: • Área de preparación de pacientes.
A37: INFRAESTRUCTURA | B37: Mediana | C37: Modalidades intramural, telemedicina - prestador remisor | D37: 11.3.4.1 | E37: 12 | F37: 12.4 | G37: • Disponibilidad de área o ambiente de trabajo sucio.
A38: INFRAESTRUCTURA | B38: Alta | C38: Modalidades intramural, telemedicina - prestador remisor | D38: 11.3.4.1 | E38: 13 | G38: Cuando se realicen procedimientos de radiología sin medio de contraste, cumple con los criterios de la complejidad baja.
A39: INFRAESTRUCTURA | B39: Alta | C39: Modalidades intramural, telemedicina - prestador remisor | D39: 11.3.4.1 | E39: 14 | G39: Cuando se realicen procedimientos con medio de contraste, cumple con los criterios de la complejidad mediana.
A40: INFRAESTRUCTURA | B40: Alta | C40: Modalidades intramural, telemedicina - prestador remisor | D40: 11.3.4.1 | E40: 15 | G40: Cuando se realicen procedimientos de radiología intervencionista fuera de salas de cirugía, cuenta con:
A41: INFRAESTRUCTURA | B41: Alta | C41: Modalidades intramural, telemedicina - prestador remisor | D41: 11.3.4.1 | E41: 15 | F41: 15.1 | G41: • Área para lavamanos quirúrgico, ubicada al ingreso del ambiente de procedimientos de radiología intervencionista.
A42: INFRAESTRUCTURA | B42: Alta | C42: Modalidades intramural, telemedicina - prestador remisor | D42: 11.3.4.1 | E42: 15 | F42: 15.2 | G42: • Ambiente exclusivo acorde al tipo de equipo generador de radiación ionizante, su ficha técnica y a los procedimientos que se realicen, debe permitir movilización del talento humano, pacientes, usuarios y equipos biomédicos.
A43: INFRAESTRUCTURA | B43: Alta | C43: Modalidades intramural, telemedicina - prestador remisor | D43: 11.3.4.1 | E43: 15 | F43: 15.3 | G43: • Área de recepción y entrega de pacientes.
A44: INFRAESTRUCTURA | B44: Alta | C44: Modalidades intramural, telemedicina - prestador remisor | D44: 11.3.4.1 | E44: 15 | F44: 15.4 | G44: • Ambiente o área de recuperación con disponibilidad de oxígeno medicinal y succión. Pueden ser suministrados a través de red central de oxígeno medicinal y succión o a través de oxígeno medicinal portátil y equipos de succión.
A45: INFRAESTRUCTURA | B45: Alta | C45: Modalidades intramural, telemedicina - prestador remisor | D45: 11.3.4.1 | E45: 15 | F45: 15.5 | G45: • Área o ambiente de control / comando del equipo, de acuerdo con la tecnología a utilizar, que permita visualización del paciente.
A46: INFRAESTRUCTURA | B46: Alta | C46: Modalidades intramural, telemedicina - prestador remisor | D46: 11.3.4.1 | E46: 15 | F46: 15.6 | G46: • Disponibilidad de unidad sanitaria de uso mixto.
A47: INFRAESTRUCTURA | B47: Baja y mediana | C47: Modalidades extramural unidad móvil, telemedicina - prestador remisor | D47: 11.3.4.1 | E47: 16 | G47: Cumple con los criterios que le sean aplicables de todos los servicios y con los de la baja y mediana complejidad de la modalidad intramural y adicionalmente cuenta con: Sistema de alimentación eléctrica, según indicaciones del fabricante para el tipo de equipo y tecnología, con fijación piso-techo cuando aplique
A48: INFRAESTRUCTURA | B48: Todas | C48: Modalidad telemedicina - prestador de referencia | D48: 11.3.4.1 | E48: 17 | G48: Cumple con los criterios que le sean aplicables de todos los servicios
A49: DOTACIÓN | B49: Baja | C49: Modalidades intramural, telemedicina - prestador remisor | D49: 11.3.4.1 | E49: 18 | G49: Cumple con los criterios que le sean aplicables de todos los servicios y adicionalmente,
A50: DOTACIÓN | B50: Baja | C50: Modalidades intramural, telemedicina - prestador remisor | D50: 11.3.4.1 | E50: 19 | G50: Cuenta con:
A51: DOTACIÓN | B51: Baja | C51: Modalidades intramural, telemedicina - prestador remisor | D51: 11.3.4.1 | E51: 19 | F51: 19.1 | G51: • Equipo generador de radiación ionizante según los exámenes diagnósticos realizados.
A52: DOTACIÓN | B52: Baja | C52: Modalidades intramural, telemedicina - prestador remisor | D52: 11.3.4.1 | E52: 19 | F52: 19.2 | G52: • Pantalla o monitor grado médico para imágenes radiológicas.
A53: DOTACIÓN | B53: Baja | C53: Modalidades intramural, telemedicina - prestador remisor | D53: 11.3.4.1 | E53: 19 | F53: 19.3 | G53: • Elementos de protección radiológica adulto o pediátrico, según oferta, protocolos y especificaciones del equipo:
A54: DOTACIÓN | B54: Baja | C54: Modalidades intramural, telemedicina - prestador remisor | D54: 11.3.4.1 | E54: 19 | F54: 19.3.1 | G54: • Delantal plomado
A55: DOTACIÓN | B55: Baja | C55: Modalidades intramural, telemedicina - prestador remisor | D55: 11.3.4.1 | E55: 19 | F55: 19.3.2 | G55: • Protector de tiroides
A56: DOTACIÓN | B56: Baja | C56: Modalidades intramural, telemedicina - prestador remisor | D56: 11.3.4.1 | E56: 19 | F56: 19.3.3 | G56: • Protector de gónadas
A57: DOTACIÓN | B57: Baja | C57: Modalidades intramural, telemedicina - prestador remisor | D57: 11.3.4.1 | E57: 19 | F57: 19.3.4 | G57: • Gafas plomadas cuando se requiera
A58: DOTACIÓN | B58: Mediana y alta | C58: Modalidades intramural, telemedicina - prestador remisor | D58: 11.3.4.1 | E58: 20 | G58: Adicional a lo definido para baja complejidad, cuando se realicen procedimientos invasivos (biopsias, drenajes y punciones) con guía ecográfica, cuenta con:
A59: DOTACIÓN | B59: Mediana y alta | C59: Modalidades intramural, telemedicina - prestador remisor | D59: 11.3.4.1 | E59: 20 | F59: 20.1 | G59: • Mesa para instrumental.
A60: DOTACIÓN | B60: Mediana y alta | C60: Modalidades intramural, telemedicina - prestador remisor | D60: 11.3.4.1 | E60: 21 | G60: Adicional a lo definido para baja complejidad, cuando se realicen procedimientos especiales menores (estudios con medio de contraste), cuenta con:
A61: DOTACIÓN | B61: Mediana y alta | C61: Modalidades intramural, telemedicina - prestador remisor | D61: 11.3.4.1 | E61: 21 | F61: 21.1 | G61: • Fluoroscopio.
A62: DOTACIÓN | B62: Mediana y alta | C62: Modalidades intramural, telemedicina - prestador remisor | D62: 11.3.4.1 | E62: 21 | F62: 21.2 | G62: • Inyector de medios de contraste, cuando se requiera.
A63: DOTACIÓN | B63: Mediana y alta | C63: Modalidades intramural, telemedicina - prestador remisor | D63: 11.3.4.1 | E63: 22 | G63: Disponibilidad de carro de paro cuando se utilice medio de contraste
A64: DOTACIÓN | B64: Baja y mediana | C64: Modalidades extramural unidad móvil, telemedicina - prestador remisor | D64: 11.3.4.1 | E64: 23 | G64: Cumple con los criterios que le sean aplicables de todos los servicios y los de la modalidad intramural baja complejidad y adicionalmente cuenta con:
A65: DOTACIÓN | B65: Baja y mediana | C65: Modalidades extramural unidad móvil, telemedicina - prestador remisor | D65: 11.3.4.1 | E65: 23 | F65: 23.1 | G65: • El o los equipos generadores de radiaciones ionizantes, cuyas indicaciones del fabricante refieran que está diseñado para ser instalado y operado en una unidad móvil.
A66: DOTACIÓN | B66: Baja y mediana | C66: Modalidades extramural unidad móvil, telemedicina - prestador remisor | D66: 11.3.4.1 | E66: 23 | F66: 23.2 | G66: • La unidad móvil está dotada con señal luminosa o sonora indicando la presencia de radiación
A67: DOTACIÓN | B67: Todas | C67: Modalidad telemedicina - prestador remisor | D67: 11.3.4.1 | E67: 24 | G67: Cumple con los criterios que le sean aplicables de todos los servicios y los de la modalidad intramural y adicionalmente cuenta con equipo de captura y transmisión de datos e imágenes que asegure las condiciones de visualización de imagen y lectura, el cual puede estar integrado al equipo generador de radiaciones ionizantes.
A68: DOTACIÓN | B68: Todas | C68: Modalidad telemedicina - prestador de referencia | D68: 11.3.4.1 | E68: 25 | G68: Cumple con los criterios que le sean aplicables de todos los servicios y adicionalmente, cuenta con pantalla o monitor grado médico para imágenes radiológicas.
A69: MEDICAMENTOS, DM E INSUMOS | B69: Todas | C69: Modalidades intramural – extramural unidad móvil, telemedicina - prestador remisor – prestador de referencia | D69: 11.3.4.1 | E69: 26 | G69: Cumple con los criterios que le sean aplicables de todos los servicios
A70: MEDICAMENTOS, DM E INSUMOS | B70: Mediana y alta | C70: Modalidades intramural, telemedicina - prestador remisor | D70: 11.3.4.1 | E70: 27 | G70: Adicional al cumplimiento de los criterios definidos para todos los servicios, si realiza procedimientos con medio de contraste o intervencionismo, cuenta con oxígeno medicinal
A71: PROCESOS PRIORITARIOS | B71: Baja | C71: Modalidades intramural, telemedicina - prestador remisor | D71: 11.3.4.1 | E71: 28 | G71: Cumple con los criterios que le sean aplicables de todos los servicios y adicionalmente, cuenta con la siguiente información documentada:
A72: PROCESOS PRIORITARIOS | B72: Baja | C72: Modalidades intramural, telemedicina - prestador remisor | D72: 11.3.4.1 | E72: 28 | F72: 28.1 | G72: • Realización y supervisión de los exámenes diagnósticos que incluya como mínimo: técnica diagnóstica, calidad de la imagen y radio protección
A73: PROCESOS PRIORITARIOS | B73: Baja | C73: Modalidades intramural, telemedicina - prestador remisor | D73: 11.3.4.1 | E73: 28 | F73: 28.2 | G73: • Instrucciones a los pacientes sobre la preparación de los procedimientos diagnósticos.
A74: PROCESOS PRIORITARIOS | B74: Baja | C74: Modalidades intramural, telemedicina - prestador remisor | D74: 11.3.4.1 | E74: 28 | F74: 28.3 | G74: • Acciones para evitar el efecto nocivo de las radiaciones para los pacientes, el personal, los visitantes y el público en general.
A75: PROCESOS PRIORITARIOS | B75: Baja | C75: Modalidades intramural, telemedicina - prestador remisor | D75: 11.3.4.1 | E75: 28 | F75: 28.4 | G75: • Verificación de la calidad de la imagen, incluida la toma de medidas preventivas y correctivas, cuando se requiera.
A76: PROCESOS PRIORITARIOS | B76: Baja | C76: Modalidades intramural, telemedicina - prestador remisor | D76: 11.3.4.1 | E76: 28 | F76: 28.5 | G76: • Control de calidad del equipo generador de radiación ionizante, que incluye la toma de medidas correctivas cuando aplique.
A77: PROCESOS PRIORITARIOS | B77: Mediana | C77: Modalidades intramural, telemedicina - prestador remisor | D77: 11.3.4.1 | E77: 29 | G77: Cumple con los criterios definidos para la baja complejidad y adicionalmente, cuenta con la siguiente información documentada:
A78: PROCESOS PRIORITARIOS | B78: Mediana | C78: Modalidades intramural, telemedicina - prestador remisor | D78: 11.3.4.1 | E78: 29 | F78: 29.1 | G78: • Procedimiento cuando se administre medio de contraste.
A79: PROCESOS PRIORITARIOS | B79: Alta | C79: Modalidades intramural, telemedicina - prestador remisor | D79: 11.3.4.1 | E79: 30 | G79: Cumple con los criterios definidos para la baja y mediana complejidad y adicionalmente cuenta con la siguiente información documentada:
A80: PROCESOS PRIORITARIOS | B80: Alta | C80: Modalidades intramural, telemedicina - prestador remisor | D80: 11.3.4.1 | E80: 30 | F80: 30.1 | G80: • Procedimiento para radiología intervencionista, cuando lo realice
A81: PROCESOS PRIORITARIOS | B81: Baja y mediana | C81: Modalidades extramural unidad móvil, telemedicina - prestador remisor | D81: 11.3.4.1 | E81: 31 | G81: Adicional a lo definido en la modalidad intramural en baja complejidad, cuenta con la siguiente información documentada: Verificación de la calidad de la imagen, para cada desplazamiento realizado por la Unidad móvil en la que está instalado el equipo generador de radiación ionizante, que incluye la toma de medidas preventivas y correctivas cuando aplique.
A82: PROCESOS PRIORITARIOS | B82: Todas | C82: Modalidad telemedicina - prestador de referencia | D82: 11.3.4.1 | E82: 32 | G82: Cumple con los criterios que le sean aplicables de todos los servicios
A83: HISTORIA CLÍNICA Y REGISTROS | B83: Todas | C83: Modalidades intramural, telemedicina - prestador remisor | D83: 11.3.4.1 | E83: 33 | G83: Cumple con los criterios que le sean aplicables de todos los servicios y adicionalmente, cuenta con los siguientes registros:
A84: HISTORIA CLÍNICA Y REGISTROS | B84: Todas | C84: Modalidades intramural, telemedicina - prestador remisor | D84: 11.3.4.1 | E84: 33 | F84: 33.1 | G84: • Número de exposiciones e imágenes tomadas que incluya el nombre del paciente y nombre del estudio realizado.
A85: HISTORIA CLÍNICA Y REGISTROS | B85: Todas | C85: Modalidades intramural, telemedicina - prestador remisor | D85: 11.3.4.1 | E85: 33 | F85: 33.2 | G85: • Dosis de radiación expresadas en unidades según la tecnología del equipo.
A86: HISTORIA CLÍNICA Y REGISTROS | B86: Todas | C86: Modalidades intramural, telemedicina - prestador remisor | D86: 11.3.4.1 | E86: 33 | F86: 33.3 | G86: • Número de imágenes rechazadas por el tecnólogo y el profesional de la medicina especialista en radiología e imágenes diagnósticas que incluya sus causas.
A87: HISTORIA CLÍNICA Y REGISTROS | B87: Todas | C87: Modalidades intramural, telemedicina - prestador remisor | D87: 11.3.4.1 | E87: 33 | F87: 33.4 | G87: • Número de estudios repetidos y sus causas, cuando aplique.
A88: HISTORIA CLÍNICA Y REGISTROS | B88: Todas | C88: Modalidades intramural, telemedicina - prestador remisor | D88: 11.3.4.1 | E88: 33 | F88: 33.5 | G88: • Control de calidad vigente, de los equipos generadores de radiación ionizante
A89: HISTORIA CLÍNICA Y REGISTROS | B89: Baja y mediana | C89: Modalidades extramural unidad móvil, telemedicina - prestador remisor | D89: 11.3.4.1 | E89: 34 | G89: Cumple con los criterios que le sean aplicables de todos los servicios y adicional a lo definido en la Modalidad intramural cuenta con los siguientes registros: Verificación de la calidad de imagen para cada desplazamiento de la Unidad Móvil donde está ubicado el equipo generador de radiación ionizante, que incluye la toma de medidas correctivas, cuando aplique.
A90: HISTORIA CLÍNICA Y REGISTROS | B90: Todas | C90: Modalidad telemedicina - prestador de referencia | D90: 11.3.4.1 | E90: 35 | G90: Cumple con los criterios que le sean aplicables de todos los servicios
A91: INTERDEPENDENCIA | B91: Baja | C91: Modalidad intramural | D91: 11.3.4.1 | E91: 36 | G91: Cumple con los criterios que le sean aplicables de todos los servicios y adicionalmente
A92: INTERDEPENDENCIA | B92: Baja | C92: Modalidad intramural | D92: 11.3.4.1 | E92: 37 | G92: Servicio de transporte asistencial cuando fuera de salas de cirugía se realicen procedimientos bajo sedación
A93: INTERDEPENDENCIA | B93: Mediana y alta | C93: Modalidad intramural | D93: 11.3.4.1 | E93: 38 | G93: Cumple con los criterios que le sean aplicables de todos los servicios y adicionalmente
A94: INTERDEPENDENCIA | B94: Mediana y alta | C94: Modalidad intramural | D94: 11.3.4.1 | E94: 39 | G94: Cuando se realicen procedimientos con administración de medio de contraste e intervencionismo, disponibilidad de:
A95: INTERDEPENDENCIA | B95: Mediana y alta | C95: Modalidad intramural | D95: 11.3.4.1 | E95: 39 | F95: 39.1 | G95: • Servicio de urgencias.
A96: INTERDEPENDENCIA | B96: Mediana y alta | C96: Modalidad intramural | D96: 11.3.4.1 | E96: 39 | F96: 39.2 | G96: • Servicio de transporte asistencial.
A97: INTERDEPENDENCIA | B97: Todas | C97: Modalidad extramural unidad móvil | D97: 11.3.4.1 | E97: 40 | G97: Cumple con los criterios que le sean aplicables de todos los servicios
A98: INTERDEPENDENCIA | B98: Todas | C98: Modalidad telemedicina – prestador remisor – prestador de referencia | D98: 11.3.4.1 | E98: 41 | G98: No aplica
H99: =COUNTA(H10:H98) -> 0 | I99: =COUNTA(I10:I98) -> 0 | J99: =COUNTA(J10:J98) -> 0
A100: RESULTADO POR ESTANDAR IMÁGENES DIAGNÓSTICAS - METODOS DIAGNÓSTICOS CON IMÁGENES OBTENIDAS MEDIANTE EQUIPOS GENERADORES DE RADIACIONES IONIZANTES
A101: ESTANDAR | B101: TOTAL CRITERIOS CUMPLE | C101: TOTAL CRITERIOS NO CUMPLE | D101: TOTAL CRITERIOS NO APLICA | E101: % CUMPLIMIENTO
...

Sheet IMAG DIAG NO ION
B1: IMÁGENES DIAGNÓSTICAS - MÉTODOS DIAGNÓSTICOS CON IMÁGENES OBTENIDAS MEDIANTE EQUIPOS GENERADORES DE RADIACIONES NO IONIZANTES CONDICIONES DE HABILITACIÓN RESOLUCIÓN 3100/2019 | P1: ESTADO DE ACCIONES (Número de acciones y % por estado) | T1: ESTADO DE ACCIONES (Número de acciones y % por estado) | X1: ESTADO DE ACCIONES (Número de acciones y % por estado) | AB1: ESTADO DE ACCIONES (Número de acciones y % por estado) | AF1: ESTADO DE ACCIONES (Número de acciones y % por estado) | AJ1: ESTADO DE ACCIONES (Número de acciones y % por estado)
P2: SIN INICIAR | Q2: =COUNTIFS(R$10:R$500,P2) -> 0 | R2: =IFERROR(Q2/SUM(Q$2:Q$5),"") | T2: SIN INICIAR | U2: =COUNTIFS(V$10:V$500,T2) -> 0 | V2: =IFERROR(U2/SUM(U$2:U$5),"") | X2: SIN INICIAR | Y2: =COUNTIFS(Z$10:Z$500,X2) -> 0 | Z2: =IFERROR(Y2/SUM(Y$2:Y$5),"") | AB2: SIN INICIAR | AC2: =COUNTIFS(AD$10:AD$500,AB2) -> 0 | AD2: =IFERROR(AC2/SUM(AC$2:AC$5),"") | AF2: SIN INICIAR | AG2: =COUNTIFS(AH$10:AH$500,AF2) -> 0 | AH2: =IFERROR(AG2/SUM(AG$2:AG$5),"") | AJ2: SIN INICIAR | AK2: =COUNTIFS(AL$10:AL$500,AJ2) -> 0 | AL2: =IFERROR(AK2/SUM(AK$2:AK$5),"")
C3: TOTAL CUMPLE | D3: TOTAL NO CUMPLE | E3: TOTAL NO APLICA | P3: EN EJECUCION | Q3: =COUNTIFS(R$10:R$500,P3) -> 0 | R3: =IFERROR(Q3/SUM(Q$2:Q$5),"") | T3: EN EJECUCION | U3: =COUNTIFS(V$10:V$500,T3) -> 0 | V3: =IFERROR(U3/SUM(U$2:U$5),"") | X3: EN EJECUCION | Y3: =COUNTIFS(Z$10:Z$500,X3) -> 0 | Z3: =IFERROR(Y3/SUM(Y$2:Y$5),"") | AB3: EN EJECUCION | AC3: =COUNTIFS(AD$10:AD$500,AB3) -> 0 | AD3: =IFERROR(AC3/SUM(AC$2:AC$5),"") | AF3: EN EJECUCION | AG3: =COUNTIFS(AH$10:AH$500,AF3) -> 0 | AH3: =IFERROR(AG3/SUM(AG$2:AG$5),"") | AJ3: EN EJECUCION | AK3: =COUNTIFS(AL$10:AL$500,AJ3) -> 0 | AL3: =IFERROR(AK3/SUM(AK$2:AK$5),"")
A4: NUMERO DE CRITERIOS EVALUADOS | C4: =COUNTA(H10:H40) -> 0 | D4: =COUNTA(I10:I40) -> 0 | E4: =COUNTA(J10:J40) -> 0 | P4: CERRADA | Q4: =COUNTIFS(R$10:R$500,P4) -> 0 | R4: =IFERROR(Q4/SUM(Q$2:Q$5),"") | T4: CERRADA | U4: =COUNTIFS(V$10:V$500,T4) -> 0 | V4: =IFERROR(U4/SUM(U$2:U$5),"") | X4: CERRADA | Y4: =COUNTIFS(Z$10:Z$500,X4) -> 0 | Z4: =IFERROR(Y4/SUM(Y$2:Y$5),"") | AB4: CERRADA | AC4: =COUNTIFS(AD$10:AD$500,AB4) -> 0 | AD4: =IFERROR(AC4/SUM(AC$2:AC$5),"") | AF4: CERRADA | AG4: =COUNTIFS(AH$10:AH$500,AF4) -> 0 | AH4: =IFERROR(AG4/SUM(AG$2:AG$5),"") | AJ4: CERRADA | AK4: =COUNTIFS(AL$10:AL$500,AJ4) -> 0 | AL4: =IFERROR(AK4/SUM(AK$2:AK$5),"")
A5: CUMPLIMIENTO DEL SERVICIO EVALUADO | C5: =IFERROR(C4/(D4+C4),"") | P5: CANCELADA | Q5: =COUNTIFS(R$10:R$500,P5) -> 0 | R5: =IFERROR(Q5/SUM(Q$2:Q$5),"") | T5: CANCELADA | U5: =COUNTIFS(V$10:V$500,T5) -> 0 | V5: =IFERROR(U5/SUM(U$2:U$5),"") | X5: CANCELADA | Y5: =COUNTIFS(Z$10:Z$500,X5) -> 0 | Z5: =IFERROR(Y5/SUM(Y$2:Y$5),"") | AB5: CANCELADA | AC5: =COUNTIFS(AD$10:AD$500,AB5) -> 0 | AD5: =IFERROR(AC5/SUM(AC$2:AC$5),"") | AF5: CANCELADA | AG5: =COUNTIFS(AH$10:AH$500,AF5) -> 0 | AH5: =IFERROR(AG5/SUM(AG$2:AG$5),"") | AJ5: CANCELADA | AK5: =COUNTIFS(AL$10:AL$500,AJ5) -> 0 | AL5: =IFERROR(AK5/SUM(AK$2:AK$5),"")
P6: TOTAL | Q6: =SUM(Q2:Q5) -> 0 | T6: TOTAL | U6: =SUM(U2:U5) -> 0 | X6: TOTAL | Y6: =SUM(Y2:Y5) -> 0 | AB6: TOTAL | AC6: =SUM(AC2:AC5) -> 0 | AF6: TOTAL | AG6: =SUM(AG2:AG5) -> 0 | AJ6: TOTAL | AK6: =SUM(AK2:AK5) -> 0
P8: SEGUIMIENTO 1 - Fecha: | T8: SEGUIMIENTO 2 - Fecha: | X8: SEGUIMIENTO 3 - Fecha: | AB8: SEGUIMIENTO 4 - Fecha: | AF8: SEGUIMIENTO 5 - Fecha: | AJ8: SEGUIMIENTO 6 - Fecha:
A9: ESTANDAR | B9: COMPLEJIDAD | C9: MODALIDAD | D9: ARTICULO | E9: SECCIÓN | F9: APARTADO | G9: CRITERIO | H9: CUMPLE | I9: NO CUMPLE | J9: NO APLICA | K9: HALLAZGOS | M9: ACCIÓN PARA EL CUMPLIMIENTO | N9: RESPONSABLE | O9: FECHA LIMITE PARA IMPLEMENTAR | P9: SEGUIMIENTO 1 | R9: ESTADO DE LA ACCIÓN 1 | T9: SEGUIMIENTO 2 | V9: ESTADO DE LA ACCIÓN 2 | X9: SEGUIMIENTO 3 | Z9: ESTADO DE LA ACCIÓN 3 | AB9: SEGUIMIENTO 4 | AD9: ESTADO DE LA ACCIÓN 4 | AF9: SEGUIMIENTO 5 | AH9: ESTADO DE LA ACCIÓN 5 | AJ9: SEGUIMIENTO 6 | AL9: ESTADO DE LA ACCIÓN 6
A10: TALENTO HUMANO | B10: Mediana | C10: Modalidades intramural, extramural jornada de salud, unidad móvil y domiciliaria, telemedicina - prestador remisor | D10: 11.3.4.2 | E10: 1 | G10: Cumple con los criterios que le sean aplicables de todos los servicios y adicionalmente cuenta con:
A11: TALENTO HUMANO | B11: Mediana | C11: Modalidades intramural, extramural jornada de salud, unidad móvil y domiciliaria, telemedicina - prestador remisor | D11: 11.3.4.2 | E11: 1 | F11: 1.1 | G11: • Médico especializado en radiología e imágenes diagnósticas o aquellos médicos especialistas quienes en su pensum o formación académica hayan adquirido los conocimientos del manejo e interpretación del espectro electromagnético, del ultrasonido especialmente, así como de las radiaciones ionizantes para establecer el diagnóstico y/o el tratamiento de las enfermedades inherentes a sus especialidades. Para lo cual deberá acreditar el respectivo certificado.
A12: TALENTO HUMANO | B12: Mediana | C12: Modalidades intramural, extramural jornada de salud, unidad móvil y domiciliaria, telemedicina - prestador remisor | D12: 11.3.4.2 | E12: 1 | F12: 1.2 | G12: • Cuando se realicen procedimientos de resonancia magnética cuenta con Técnico profesional o tecnólogo en imágenes diagnósticas, para la operación de equipos y adquisición de imágenes.
A13: TALENTO HUMANO | B13: Mediana | C13: Modalidad telemedicina - prestador de referencia | D13: 11.3.4.2 | E13: 2 | G13: Cumple con los criterios que le sean aplicables de todos los servicios.
A14: TALENTO HUMANO | B14: Mediana | C14: Modalidad telemedicina - prestador de referencia | D14: 11.3.4.2 | E14: 3 | G14: La interpretación de las imágenes diagnósticas es realizada médico especializado en radiología e imágenes diagnósticas o aquellos médicos especialistas quienes en su pensum o formación académica hayan adquirido los conocimientos del manejo e interpretación del espectro electromagnético, del ultrasonido especialmente, así como de las radiaciones ionizantes para establecer el diagnóstico y/o el tratamiento de las enfermedades inherentes a sus especialidades. Para lo cual deberá acreditar el respectivo certificado
A15: INFRAESTRUCTURA | B15: Mediana | C15: Modalidades intramural, extramural unidad móvil, telemedicina - prestador remisor | D15: 11.3.4.2 | E15: 4 | G15: Cumple con los criterios que le sean aplicables de todos los servicios y adicionalmente, cuenta con:
A16: INFRAESTRUCTURA | B16: Mediana | C16: Modalidades intramural, extramural unidad móvil, telemedicina - prestador remisor | D16: 11.3.4.2 | E16: 4 | F16: 4.1 | G16: • Ambiente exclusivo para el equipo generador de radiación no ionizante. La dimensión de este ambiente debe ser acorde al tipo de equipo generador de radiación no ionizante, su ficha técnica y a los procedimientos que se realicen, debe permitir movilización del talento humano, pacientes, usuarios y equipos biomédicos.
A17: INFRAESTRUCTURA | B17: Mediana | C17: Modalidades intramural, extramural unidad móvil, telemedicina - prestador remisor | D17: 11.3.4.2 | E17: 4 | F17: 4.2 | G17: • Unidad sanitaria, cuando el procedimiento lo requiera.
A18: INFRAESTRUCTURA | B18: Mediana | C18: Modalidades intramural, extramural unidad móvil, telemedicina - prestador remisor | D18: 11.3.4.2 | E18: 5 | G18: Disponibilidad de:
A19: INFRAESTRUCTURA | B19: Mediana | C19: Modalidades intramural, extramural unidad móvil, telemedicina - prestador remisor | D19: 11.3.4.2 | E19: 5 | F19: 5.1 | G19: • Vestidor para pacientes y área para casilleros, cuando el procedimiento lo requiera.
A20: INFRAESTRUCTURA | B20: Mediana | C20: Modalidades intramural, extramural unidad móvil, telemedicina - prestador remisor | D20: 11.3.4.2 | E20: 5 | F20: 5.2 | G20: • Área para almacenamiento de dispositivos médicos e insumos.
A21: INFRAESTRUCTURA | B21: Mediana | C21: Modalidades intramural, extramural unidad móvil, telemedicina - prestador remisor | D21: 11.3.4.2 | E21: 5 | F21: 5.3 | G21: • Sala de espera.
A22: INFRAESTRUCTURA | B22: Mediana | C22: Modalidades intramural, extramural unidad móvil, telemedicina - prestador remisor | D22: 11.3.4.2 | E22: 5 | F22: 5.4 | G22: • Unidades sanitarias discriminadas por sexo.
A23: INFRAESTRUCTURA | B23: Mediana | C23: Modalidades extramural jornada de salud, domiciliaria, telemedicina - prestador remisor | D23: 11.3.4.2 | E23: 6 | G23: Cumple con los criterios que le sean aplicables de todos los servicios.
A24: INFRAESTRUCTURA | B24: Mediana | C24: Modalidad telemedicina - prestador de referencia | D24: 11.3.4.2 | E24: 7 | G24: Cumple con los criterios que le sean aplicables de todos los servicios.
A25: DOTACIÓN | B25: Mediana | C25: Modalidades intramural, telemedicina - prestador remisor | D25: 11.3.4.2 | E25: 8 | G25: Cumple con los criterios que le sean aplicables de todos los servicios y adicionalmente,
A26: DOTACIÓN | B26: Mediana | C26: Modalidades intramural, telemedicina - prestador remisor | D26: 11.3.4.2 | E26: 8 | F26: 8.1 | G26: • Cuenta con él o los equipos generadores de radiaciones no ionizantes, según los exámenes diagnósticos realizados.
A27: DOTACIÓN | B27: Mediana | C27: Modalidades intramural, telemedicina - prestador remisor | D27: 11.3.4.2 | E27: 8 | F27: 8.2 | G27: • Cuando se realice resonancia magnética y ultrasonido cuenta con pantalla o monitor grado médico.
A28: DOTACIÓN | B28: Mediana | C28: Modalidades extramural unidad móvil, domiciliaria y jornada de salud, telemedicina - prestador remisor | D28: 11.3.4.2 | E28: 9 | G28: Cumple con los criterios que le sean aplicables de todos los servicios y adicionalmente cuenta con: El o los equipos generadores de radiaciones no ionizantes, según los exámenes diagnósticos realizados, cuyas indicaciones del fabricante refieran que es un equipo portátil
A29: DOTACIÓN | B29: Mediana | C29: Modalidad telemedicina - prestador remisor | D29: 11.3.4.2 | E29: 10 | G29: Cumple con los criterios que le sean aplicables de todos los servicios y los de la modalidad intramural y adicionalmente cuenta con equipo de captura y transmisión de datos e imágenes que asegure las condiciones de visualización de imagen y lectura
A30: DOTACIÓN | B30: Mediana | C30: Modalidad telemedicina - prestador de referencia | D30: 11.3.4.2 | E30: 11 | G30: Cumple con los criterios que le sean aplicables de todos los servicios y adicionalmente, cuenta con pantalla o monitor grado médico
A31: MEDICAMENTOS, DM E INSUMOS | B31: Mediana | C31: Modalidades intramural y extramural unidad móvil, domiciliaria y jornada de salud, telemedicina - prestador remisor – prestador de referencia | D31: 11.3.4.2 | E31: 12 | G31: Cumple con los criterios que le sean aplicables de todos los servicios
