Workbook

Sheet Tabla de contenido
A2: Grupo servicio | B2: Servicio | C2: Páginas
A3: 11.1. ESTÁNDARES Y CRITERIOS APLICABLES A TODOS LOS SERVICIOS | B3: 11.1.1 TALENTO HUMANO | C3: 59 -61
B4: 11.1.2. INFRAESTRUCTURA | C4: 61 - 68
B5: 11.1.3. DOTACIÓN | C5: 68 - 71
B6: 11.1.4. MEDICAMENTOS, DISPOSITIVOS MÉDICOS E INSUMOS | C6: 71 - 73
B7: 11.1.5. PROCESOS PRIORITARIOS | C7: 73 - 77
B8: 11.1.6. HISTORIA CLÍNICA Y REGISTROS | C8: 77 - 79
B9: 11.1.7. INTERDEPENDENCIA | C9: 79
A10: 11.2. GRUPO CONSULTA EXTERNA | B10: 11.2.1. SERVICIO DE CONSULTA EXTERNA GENERAL | C10: 80-84
B11: 11.2.2. SERVICIO DE CONSULTA EXTERNA ESPECIALIZADA | C11: 85-88
B12: 11.2.3. SERVICIO DE VACUNACIÓN | C12: 88-91
B13: 11.2.4. SERVICIO DE SEGURIDAD Y SALUD EN EL TRABAJO | C13: 91-93
A14: 11.3. GRUPO APOYO DIAGNÓSTICO Y COMPLEMENTACIÓN TERAPÉUTICA | B14: 11.3.1. SERVICIO DE TERAPIAS | C14: 94-97
B15: 11.3.2. SERVICIO FARMACÉUTICO | C15: 97-101
B16: 11.3.3 SERVICIO DE RADIOLOGiA ODONTOLÓGICA | C16: 101-103
B17: 11.3.4 SERVICIO DE IMÁGENES DIAGNÓSTICAS | C17: 103-104
B18: 11.3.5 SERVICIO DE MEDICINA NUCLEAR | C18: 112-115
B19: 11.3.6 SERVICIO DE RADIOTERAPIA | C19: 116-119
B20: 11.3.7 SERVICIO DE QUIMIOTERAPIA | C20: 119-123
B21: 11.3.8 SERVICIO DE DIAGNÓSTICO VASCULAR | C21: 123-125
B22: 11.3.9 SERVICIO DE HEMODINAMIA E INTERVENCIONISMO | C22: 125-128
B23: 11.3.10 SERVICIO DE GESTIÓN PRE TRANSFUSIONAL | C23: 129-130
B24: 11.3.11. SERVICIO DE TOMA DE MUESTRAS DE LABORATORIO CLÍNICO
B25: 11.3.12 SERVICIO DE LABORATORIO CLÍNICO | C25: 132-135
B26: 11.3.13 SERVICIO DE TOMA DE MUESTRAS DE CUELLO UTERINO Y GINECOLÓGICAS | C26: 135-137
B27: 11.3.14 SERVICIO DE LABORATORIO DE CITOLOGiAS CERVICO-UTERINAS | C27: 137-138
B28: 11.3.15 SERVICIO DE LABORATORIO DE HISTOTECNOLOGIA | C28: 138-139
B29: 11.3.16 SERVICIO DE PATOLOGÍA | C29: 140-142
B30: 11.3.17 SERVICIO DE DIÁLISIS | C30: 142-146
A31: 11.4 GRUPO INTERNACIÓN | B31: 11.4.1 SERVICIO DE HOSPITALIZACIÓN | C31: 146-154
B32: 11.4.2 SERVICIO DE HOSPITALIZACIÓN PACIENTE CRÓNICO | C32: 154-162
B33: 11.4.3 SERVICIO DE CUIDADO BÁSICO NEONATAL | C33: 162-165
B34: 11.4.4 SERVICIO DE CUIDADO INTERMEDIO NEONATAL | C34: 165-168
B35: 11.4.5 SERVICIO DE CUIDADO INTENSIVO NEONATAL | C35: 168-172
B36: 11.4.6 SERVICIO DE CUIDADO INTERMEDIO PEDIÁTRICO | C36: 172-175
B37: 11.4.7 SERVICIO DE CUIDADO INTENSIVO PEDIÁTRICO | C37: 175-179
B38: 11.4.8 SERVICIO DE CUIDADO INTERMEDIO ADULTO | C38: 179-182
B39: 11.4.9 SERVICIO DE CUIDADO INTENSIVO ADULTOS | C39: 182-186
B40: 11.4.10 SERVICIO DE HOSPITALIZACIÓN EN SALUD MENTAL O CONSUMO DE SUSTANCIAS PSICOACTIVAS | C40: 186-190
B41: 11.4.11 SERVICIO DE HOSPITALIZACIÓN PARCIAL | C41: 190-195
B42: 11.4.12 SERVICIO PARA EL CUIDADO BÁSICO DEL CONSUMO DE SUSTANCIAS PSICOACTIVAS | C42: 195-199
A43: 11.5 GRUPO QUIRÚRGICO | B43: 11.5.1 SERVICIO DE CIRUGÍA | C43: 199-206
A44: 11.6 GRUPO ATENCIÓN INMEDIATA | B44: 11.6.1 SERVICIO DE URGENCIAS | C44: 206-213
B45: 11.6.2 SERVICIO DE TRANSPORTE ASISTENCIAL | C45: 213-222
B46: 11.6.3 SERVICIO ATENCIÓN PREHOSPITALARIA | C46: 222-225
B47: 11.6.4 SERVICIO PARA LA ATENCIÓN DEL PARTO | C47: 225-230

Sheet Consolidado
B3: Estándares y criterios aplicables a todos los servicios | C3: Total criterios | D3: C | E3: NC | F3: NA | G3: Cumplimiento
B4: TS - Talento Humano | C4: 21 | D4: ='11.1.1TH'!C30 -> 19 | E4: ='11.1.1TH'!C31 -> 1 | F4: ='11.1.1TH'!C32 -> 1 | G4: =D4/(C4-F4) -> 0.95
B5: TS - Infraestructura | C5: 167 | D5: ='11.1.2.INF'!C202 -> 1 | E5: ='11.1.2.INF'!C203 -> 1 | F5: ='11.1.2.INF'!C204 -> 1 | G5: =D5/(C5-F5) -> 0.0060240964
B6: TS - Dotación | C6: 52 | D6: ='11.1.3.DOT'!C68 -> 1 | E6: ='11.1.3.DOT'!C69 -> 1 | F6: ='11.1.3.DOT'!C70 -> 1 | G6: =D6/(C6-F6) -> 0.019607843
B7: TS - Medicamentos, dispositivos médicos e insumos | C7: 51 | D7: ='11.1.4MD'!C65 -> 1 | E7: ='11.1.4MD'!C66 -> 1 | F7: ='11.1.4MD'!C67 -> 1 | G7: =D7/(C7-F7) -> 0.02
B8: TS - Procesos prioritarios | C8: 91 | D8: ='11.1.5.PP'!C115 -> 2 | E8: ='11.1.5.PP'!C116 -> 1 | F8: ='11.1.5.PP'!C117 -> 1 | G8: =D8/(C8-F8) -> 0.022222222
B9: TS - Historia clinica y registros | C9: 50 | D9: ='11.1.6.HCR'!C64 -> 1 | E9: ='11.1.6.HCR'!C65 -> 1 | F9: ='11.1.6.HCR'!C66 -> 1 | G9: =D9/(C9-F9) -> 0.020408163
B10: TS - Interdependencia | C10: 5 | D10: ='11.1.7INT'!C12 -> 1 | E10: ='11.1.7INT'!C13 -> 1 | F10: ='11.1.7INT'!C14 -> 1 | G10: =D10/(C10-F10) -> 0.25
B23: Grupo consulta externa | C23: Total criterios | D23: C | E23: NC | F23: NA | G23: Cumplimiento
B24: Servicio de consulta externa general | C24: 95 | D24: ='11.2.1.S_CE_G'!C161 -> 1 | E24: ='11.2.1.S_CE_G'!C162 -> 1 | F24: ='11.2.1.S_CE_G'!C163 -> 1 | G24: =D24/(C24-F24) -> 0.010638298
B25: Servicio de consulta externa especializada | C25: 39 | D25: ='11.2.2.S_CE_E'!C94 -> 1 | E25: ='11.2.2.S_CE_E'!C95 -> 1 | F25: ='11.2.2.S_CE_E'!C96 -> 1 | G25: =D25/(C25-F25) -> 0.026315789
B26: Servicio de vacunación | C26: 57 | D26: ='11.2.3.S_CE_V'!C84 -> 1 | E26: ='11.2.3.S_CE_V'!C85 -> 1 | F26: ='11.2.3.S_CE_V'!C86 -> 1 | G26: =D26/(C26-F26) -> 0.017857143
B27: Servicio de seguridad y salud en el trabajo | C27: 29 | D27: ='11.2.4.S_CE_SST'!C56 -> 1 | E27: ='11.2.4.S_CE_SST'!C57 -> 1 | F27: ='11.2.4.S_CE_SST'!C58 -> 1 | G27: =D27/(C27-F27) -> 0.035714286
B40: Grupo apoyo diagnóstico y complementación terapéutica | C40: Total criterios | D40: C | E40: NC | F40: NA | G40: Cumplimiento
B41: Servicio de terapias | C41: 44 | D41: ='11.3.1.S_TR'!C80 -> 1 | E41: ='11.3.1.S_TR'!C81 -> 1 | F41: ='11.3.1.S_TR'!C82 -> 1 | G41: =D41/(C41-F41) -> 0.023255814
B42: Servicio farmacéutico | C42: 38 | D42: =' 11.3.2.SF'!C74 -> 1 | E42: =' 11.3.2.SF'!C75 -> 1 | F42: =' 11.3.2.SF'!C76 -> 1 | G42: =D42/(C42-F42) -> 0.027027027
B43: Servicio de radiología odontológica | C43: 44 | D43: ='11.3.3.S_Rx_OD'!C72 -> 1 | E43: ='11.3.3.S_Rx_OD'!C73 -> 1 | F43: ='11.3.3.S_Rx_OD'!C74 -> 1 | G43: =D43/(C43-F43) -> 0.023255814
B44: Servicio de imágenes diagnósticas | C44: =88+31 -> 119 | D44: ='11.3.4.S_IDx'!C218 -> 1 | E44: ='11.3.4.S_IDx'!C219 -> 1 | F44: ='11.3.4.S_IDx'!C220 -> 1 | G44: =D44/(C44-F44) -> 0.0084745763
B45: Servicio de medicina nuclear | C45: 63 | D45: =' 11.3.5.S_MNuc'!C102 -> 1 | E45: =' 11.3.5.S_MNuc'!C103 -> 1 | F45: =' 11.3.5.S_MNuc'!C104 -> 1 | G45: =D45/(C45-F45) -> 0.016129032
B46: Servicio de radioterapia | C46: 82 | D46: ='11.3.6.S_Radio'!C118 -> 1 | E46: ='11.3.6.S_Radio'!C119 -> 1 | F46: ='11.3.6.S_Radio'!C120 -> 1 | G46: =D46/(C46-F46) -> 0.012345679
B47: Servicio de quimioterapia | C47: 80 | D47: ='11.3.7.S_Quimio'!C110 -> 1 | E47: ='11.3.7.S_Quimio'!C111 -> 1 | F47: ='11.3.7.S_Quimio'!C112 -> 1 | G47: =D47/(C47-F47) -> 0.012658228
B48: Servicio de diagnóstico vascular 1 | C48: 33 | D48: ='11.3.8 S_Dx VASC'!C56 -> 1 | E48: ='11.3.8 S_Dx VASC'!C57 -> 1 | F48: ='11.3.8 S_Dx VASC'!C58 -> 1 | G48: =D48/(C48-F48) -> 0.03125
B49: Servicio de diagnóstico vascular 2 | C49: 33 | D49: ='11.3.8 S_Dx VASC'!F56 -> 1 | E49: ='11.3.8 S_Dx VASC'!F57 -> 1 | F49: ='11.3.8 S_Dx VASC'!F58 -> 1 | G49: =D49/(C49-F49) -> 0.03125
B50: Servicio de diagnóstico vascular 3 | C50: 33 | D50: ='11.3.8 S_Dx VASC'!I56 -> 1 | E50: ='11.3.8 S_Dx VASC'!I57 -> 1 | F50: ='11.3.8 S_Dx VASC'!I58 -> 1 | G50: =D50/(C50-F50) -> 0.03125
B51: Servicio de diagnóstico vascular 4 | C51: 33 | D51: ='11.3.8 S_Dx VASC'!L56 -> 1 | E51: ='11.3.8 S_Dx VASC'!L57 -> 1 | F51: ='11.3.8 S_Dx VASC'!L58 -> 1 | G51: =D51/(C51-F51) -> 0.03125
B52: Servicio de diagnóstico vascular 5 | C52: 33 | D52: ='11.3.8 S_Dx VASC'!O56 -> 1 | E52: ='11.3.8 S_Dx VASC'!O57 -> 1 | F52: ='11.3.8 S_Dx VASC'!O58 -> 1 | G52: =D52/(C52-F52) -> 0.03125
B53: Servicio de diagnóstico vascular 6 | C53: 33 | D53: ='11.3.8 S_Dx VASC'!R56 -> 1 | E53: ='11.3.8 S_Dx VASC'!R57 -> 1 | F53: ='11.3.8 S_Dx VASC'!R58 -> 1 | G53: =D53/(C53-F53) -> 0.03125
B54: Servicio de diagnóstico vascular 7 | C54: 33 | D54: ='11.3.8 S_Dx VASC'!U56 -> 1 | E54: ='11.3.8 S_Dx VASC'!U57 -> 1 | F54: ='11.3.8 S_Dx VASC'!U58 -> 1 | G54: =D54/(C54-F54) -> 0.03125
B55: Servicio de hemodinamia e intervencionismo | C55: 91 | D55: ='11.3.9S_HI'!C119 -> 1 | E55: ='11.3.9S_HI'!C120 -> 1 | F55: ='11.3.9S_HI'!C121 -> 1 | G55: =D55/(C55-F55) -> 0.011111111
B56: Servicio de gestión pre transfusional | C56: 40 | D56: ='11.3.10 S_GPT'!C50 -> 1 | E56: ='11.3.10 S_GPT'!C51 -> 1 | F56: ='11.3.10 S_GPT'!C52 -> 1 | G56: =D56/(C56-F56) -> 0.025641026
B57: Servicio de toma de muestras de laboratorio clínico | C57: 29 | D57: ='11.3.11.S_TMLC'!C48 -> 1 | E57: ='11.3.11.S_TMLC'!C49 -> 1 | F57: ='11.3.11.S_TMLC'!C50 -> 1 | G57: =D57/(C57-F57) -> 0.035714286
B58: Servicio de laboratorio clínico | C58: 59 | D58: ='11.3.12.S_LC'!C81 -> 1 | E58: ='11.3.12.S_LC'!C82 -> 1 | F58: ='11.3.12.S_LC'!C83 -> 1 | G58: =D58/(C58-F58) -> 0.017241379
B59: Servicio de toma de muestras de cuello uterino y ginecológicas | C59: 42 | D59: =' 11.3.13 S_TM_CU'!C60 -> 2 | E59: =' 11.3.13 S_TM_CU'!C61 -> 0 | F59: =' 11.3.13 S_TM_CU'!C62 -> 1 | G59: =D59/(C59-F59) -> 0.048780488
B60: Servicio de laboratorio de citologías cérvico-uterinas | C60: 32 | D60: ='11.3.14.S_LCU'!C55 -> 1 | E60: ='11.3.14.S_LCU'!C56 -> 1 | F60: ='11.3.14.S_LCU'!C57 -> 1 | G60: =D60/(C60-F60) -> 0.032258065
B61: Servicio de laboratorio de histotecnología | C61: 33 | D61: ='11.3.15.S_LHT'!C46 -> 1 | E61: ='11.3.15.S_LHT'!C47 -> 1 | F61: ='11.3.15.S_LHT'!C48 -> 1 | G61: =D61/(C61-F61) -> 0.03125
B62: Servicio de patología | C62: 51 | D62: ='11.3.16.S_LPT'!C75 -> 1 | E62: ='11.3.16.S_LPT'!C76 -> 1 | F62: ='11.3.16.S_LPT'!C77 -> 1 | G62: =D62/(C62-F62) -> 0.02
B63: Servicio de diálisis | C63: 100 | D63: ='11.3.17.S_Dial'!C127 -> 1 | E63: ='11.3.17.S_Dial'!C128 -> 1 | F63: ='11.3.17.S_Dial'!C129 -> 1 | G63: =D63/(C63-F63) -> 0.01010101
B66: Grupo de internación | C66: Total criterios | D66: C | E66: NC | F66: NA | G66: Cumplimiento
B67: Servicio de hospitalización | C67: 183 | D67: ='11.4.1.S_HP'!C266 -> 1 | E67: ='11.4.1.S_HP'!C267 -> 1 | F67: ='11.4.1.S_HP'!C268 -> 1 | G67: =D67/(C67-F67) -> 0.0054945055
B68: Servicio de hospitalización paciente crónico | C68: 167 | D68: ='11.4.2.S_HP_PC'!C247 -> 1 | E68: ='11.4.2.S_HP_PC'!C248 -> 1 | F68: ='11.4.2.S_HP_PC'!C249 -> 1 | G68: =D68/(C68-F68) -> 0.0060240964
B69: Servicio de cuidado básico neonatal | C69: 67 | D69: ='11.4.3.S_CBN'!C91 -> 1 | E69: ='11.4.3.S_CBN'!C92 -> 1 | F69: ='11.4.3.S_CBN'!C93 -> 1 | G69: =D69/(C69-F69) -> 0.015151515
B70: Servicio de cuidado intermedio neonatal | C70: 88 | D70: ='11.4.4.S_CIN '!C113 -> 1 | E70: ='11.4.4.S_CIN '!C114 -> 1 | F70: ='11.4.4.S_CIN '!C115 -> 1 | G70: =D70/(C70-F70) -> 0.011494253
B71: Servicio de cuidado intensivo neonatal | C71: 119 | D71: ='11.4.5.S_CINN'!C144 -> 1 | E71: ='11.4.5.S_CINN'!C145 -> 1 | F71: ='11.4.5.S_CINN'!C146 -> 1 | G71: =D71/(C71-F71) -> 0.0084745763
B72: Servicio de cuidado intermedio pediátrico | C72: 85 | D72: ='11.4.6. S_CINP'!C114 -> 1 | E72: ='11.4.6. S_CINP'!C115 -> 1 | F72: ='11.4.6. S_CINP'!C116 -> 1 | G72: =D72/(C72-F72) -> 0.011904762
B73: Servicio de cuidado intensivo pediátrico | C73: 112 | D73: ='11.4.7.S_CIP'!C140 -> 1 | E73: ='11.4.7.S_CIP'!C141 -> 1 | F73: ='11.4.7.S_CIP'!C142 -> 1 | G73: =D73/(C73-F73) -> 0.009009009
B74: Servicio de cuidado intermedio adulto | C74: 82 | D74: ='11.4.8.S_CIMA'!C111 -> 1 | E74: ='11.4.8.S_CIMA'!C112 -> 1 | F74: ='11.4.8.S_CIMA'!C113 -> 1 | G74: =D74/(C74-F74) -> 0.012345679
B75: Servicio de cuidado intensivo adultos | C75: 97 | D75: ='11.4.9.S_CIA'!C126 -> 1 | E75: ='11.4.9.S_CIA'!C127 -> 1 | F75: ='11.4.9.S_CIA'!C128 -> 1 | G75: =D75/(C75-F75) -> 0.010416667
B76: Servicio de hospitalización en salud mental o consumo de sustancias psicoactivas | C76: 104 | D76: ='11.4.10.S_HSM CSP'!C138 -> 1 | E76: ='11.4.10.S_HSM CSP'!C139 -> 1 | F76: ='11.4.10.S_HSM CSP'!C140 -> 1 | G76: =D76/(C76-F76) -> 0.0097087379
B77: Servicio de hospitalización parcial | C77: 127 | D77: ='11.4.11.S_HSP'!C176 -> 1 | E77: ='11.4.11.S_HSP'!C177 -> 1 | F77: ='11.4.11.S_HSP'!C178 -> 1 | G77: =D77/(C77-F77) -> 0.0079365079
B78: Servicio para el cuidado básico del consumo de sustancias psicoactivas | C78: 86 | D78: ='11.4.12.S_CB_CSP'!C116 -> 1 | E78: ='11.4.12.S_CB_CSP'!C117 -> 1 | F78: ='11.4.12.S_CB_CSP'!C118 -> 1 | G78: =D78/(C78-F78) -> 0.011764706
B90: Grupo quirúrgico | C90: Total criterios | D90: C | E90: NC | F90: NA | G90: Cumplimiento
B91: Servicio de cirugía | C91: 189 | D91: ='11.5.1.S_CX'!C239 -> 1 | E91: ='11.5.1.S_CX'!C240 -> 1 | F91: ='11.5.1.S_CX'!C241 -> 1 | G91: =D91/(C91-F91) -> 0.0053191489
B106: Grupo atención inmediata | C106: Total criterios | D106: C | E106: NC | F106: NA | G106: Cumplimiento
B107: Servicio de urgencias | C107: 197 | D107: ='11.6.1.S_UR'!C249 -> 1 | E107: ='11.6.1.S_UR'!C250 -> 1 | F107: ='11.6.1.S_UR'!C251 -> 1 | G107: =D107/(C107-F107) -> 0.0051020408
B108: Servicio de transporte asistencial | C108: 208 | D108: ='11.6.2.S_TR_AS'!C288 -> 1 | E108: ='11.6.2.S_TR_AS'!C289 -> 1 | F108: ='11.6.2.S_TR_AS'!C290 -> 1 | G108: =D108/(C108-F108) -> 0.0048309179
B109: Servicio atención prehospitalaria | C109: 74 | D109: ='11.6.3.S_AT_PH'!C100 -> 1 | E109: ='11.6.3.S_AT_PH'!C101 -> 1 | F109: ='11.6.3.S_AT_PH'!C102 -> 1 | G109: =D109/(C109-F109) -> 0.01369863
B110: Servicio para la atención del parto | C110: 169 | D110: ='11.6.4.S_A.parto'!C219 -> 1 | E110: ='11.6.4.S_A.parto'!C220 -> 1 | F110: ='11.6.4.S_A.parto'!C221 -> 1 | G110: =D110/(C110-F110) -> 0.005952381

Sheet 11.1.1TH
B1: VOLVER A TABLA DE CONTENIDO
B2: Estandar de Talento Humano
A3: Estandar | B3: Criterios | C3: Estado | D3: Comentarios
A4: TSTH | B4: 1. El talento humano en salud y otros profesionales que se relacionan con la atención o resultados en salud de los usuarios, cuentan con los titulos, según aplique, de educación superior o certificados de aptitud ocupacional, expedidos por la entidad educativa competente. En el caso de títulos o certificados obtenidos en el extranjero, copia de la resolución de convalidación expedida por el Ministerio de Educación Nacional | C4: C
A5: TSTH | B5: 2. El talento humano en salud cuenta con copia de la resolución de autorización del ejercicio expedido por la autoridad competente o inscripción e en el ReTHUS | C5: NC
A6: TSTH | B6: 3. El prestador de servicios de salud determina la cantidad necesaria de talento humano requerido para cada uno de los servicios ofertados y prestados, de acuerdo con la capacidad instalada, la relación entre la oferta y demanda, la oportunidad en la prestación, tiempo de la atención y el riesgo en la atención. Este criterio no aplica para profesionales independientes de salud | C6: NA
A7: TSTH | B7: 4. El prestador de servicios de salud que actúe como escenario de práctica formativa en el área de la salud, cuenta con:
A8: TSTH | B8: 4.1. Convenio vigente con la institución educativa autorizada por la entidad competente | C8: C
A9: TSTH | B9: 4.2. Información documentada de los mecanismos de supervisión permanente del personal en entrnamiento | C9: C
A10: TSTH | B10: 4.3. Estudio de la capacidad instalada en el cual se dtermine el número máximo de estudiantes que simultaneamente puedan acceder por programa de formación y por jornada, para cada uno de los servicios que se utilicen como escenarios de práctica formativa en el área de la salud, estudio que debe ser elaborado teniendo en cuenta los "lineamientos de referencia para la asignación de cupos de estudiantes en escenarios clinicos" publicados por el Ministerio de Salud y Protección Social | C10: C
A11: TSTH | B11: 5. En los servicios de salud diferentes a los servicios de consulta externa especializada de dolor y cuidado paliativo, donde se atienden pacientes con enfermedades terminales, crónicas, degenerativas e irreversibles, a los cuales se les decida como conducta médica: como parte del plan integral de cuidado que gestiona el equipo de salud, o por solicitud del paciente; el manejo de dolor y cuidado paliativo, el profesional en medicina tratante cuenta con constancia de asistencia en las acciones de formación continua en el manejo de dolor y cuidado paliativo, cuando no sea especialista en dolor y cuidado paliativo | C11: C
A12: TSTH | B12: 6. El talento humano en salud de los servicios de atención del parto, cuidado intensivo y cuidado intermedio neonatal, pediátrico y adultos, cuentan con constancia de asistencia en las acciones de formación continua para la gestión del duelo | C12: C
A13: TSTH | B13: 7. En los servicios de salud donde se realicen imagenes diagnósticas por ultrasonido, cuenta con médico especialista en radiologia e imagenes diagnósticas también podrán realizar imagenes diagnósticas aquellos médicos especialistas, quienes en su pensum o formación académica hayan adquirido los conocimientos del manejo e interpretación del espectro electromagnetico, del ultrasonido especialmente, así como de la radiaciones ionizantes para establecer el diagnóstico o el tratamiento de las enfermedades inherentes a su especialidad, para lo cual deberá acreditar el respectivo certificado. | C13: C
A14: TSTH | B14: 8. Los profesionales de la medicina de los servicios de hospitalización de baja, mediana y alta complejidad, hospitalización paciente crónico con y sin ventilador, cuidados intensivos neonatales, pediátricos y adultos; urgencias, y servicios del grupo quirurgico en modalidad intramural,cuentan con certificación vigente de aprobación de la evaluación de competencias esenciales para el cuidado de la donante expedida por el Instituto Nacional de Salud. | C14: C
A15: TSTH | B15: 9. Las instituciones prestadoras de servicios de salud con servicios de cuidado intensivo pediatrico y adulto que adicionalmente habiliten servicio quirurgico de neurocirugía, tienen disponibilidad de coordinador operativo de trasplantes. | C15: C
A16: TSTH | B16: 10. El talento humano en salud de los servicios de salud de los grupos de consulta externa, internación y el servicio de urgencias, cuentan con constancia de asistencia en las acciones de formación continua en la atención integral en salud de las personas victimas de violencia sexual. | C16: C
A17: TSTH | B17: 11. El talento humano en salud de los servicios de transporte asistencial, atención prehospitalaria y urgencias, cuentasn con constancia de asistencia en las acciones de formación continua en la atención a personas víctimas de ataques con agentes químicos. | C17: C
A18: TSTH | B18: 12. Cuando en un servicio de salud se realicen "pruebas en punto de atención del paciente - (point of care testing - POCT)", el talento humano en salud qeu las realice, a excepción del profesional en bacteriologia cuenta con constancia de asistencia en las acciones de formación continua en la atención a personas víctimas de ataques con agentes químicos. | C18: C
A19: TSTH | B19: 13. Procedimientos bajo sedación:
A20: TSTH | B20: 13.1 Cuando fuera de salas de cirugía, se realicen procedimientos bajo sedación Grado I y II, adicional al profesional de salud que realiza el procedimiento, cuenta con:
A21: TSTH | B21: 13.1.1. Profesional en la medicina especialista en anestesiologia, o profesional de la medicina o profesional en odontologia, según aplique, el cual será el encargado de administrar el medicamento y realizar el monitoreo continuo del paciente (registro de signos vitales y la respuesta a la sedación) | C21: C
A22: TSTH | B22: 13.1.2. Todos los profesionales, a excepción del profesional de la medicina especialista en anestesiologia, deben demostrar constancia de asistencia a curso de formación continua en soporte vital básico y sedación | C22: C
A23: TSTH | B23: 13.1.3 Para sedacción con óxido nitroso en odontologia, el profesional de la odontología cuenta con constancia de asistencia en las acciones de formación continua para uso clínico y práctico de este gas. | C23: C
A24: TSTH | B24: 13.2. Cuando fuera de las salas de cirugia, se realicen procedimientos bajo sedación grado III, adicional al profesional de salud que realiza el procedimiento, cuenta con profesional de la medicina con especialidad médico - quirúrgica, quién será el responsable de administrar la sedación | C24: C
A25: TSTH | B25: 13.3. Cuando fuera de las salas de cirugía, se realicen procedimientos bajo sedación grado IV, adicional al profesional de salud que realiza el procedimiento, cuenta con profesional de la medicina especialisa en anestesiologia, quién será el responsable de administrar la sedación | C25: C
A26: TSTH | B26: 13.4 Cuenta con profesional de la medicina especialista en anestesiologia cuando la atención de trate de pacientes con caracteristicas particulares: poco colaboradores; edades extremas; con enfermedades severas:cardíacas, pulmonares, hepáticas, renales o del sistema nervioso central;cualquier alteración del grado de consciencia, con obesidad mórbida, con apnea del sueño, embarazadas, o quienes abusan del alcohol o de las drogas; antecedentes de sedación fallida o que presentaron efectos adversos a algún medicamento utilizado en la sedación, por tener un elevado riesgo de desarrollar complicaciones relacionadas con la sedación analgesia | C26: C
A27: TSTH | B27: Modalidad de telemedicina prestador remisor - prestador de referencia
A28: TSTH | B28: 14. Adicional a los criterios del estándar de talento humano enunciados que le aplique, el talento humano en salud que preste directamente un servicio de salud bajo la modalidad telemedicina cuentan con constancia de asistencia en las acciones de formación continua en el manejo de tecnología utilizada por el prestador, los procesos y herramientas inherentes a la prestación de servicios bajo esta modalidad | C28: C
B30: CUMPLE | C30: =COUNTIF($C$4:$C$28,"C") -> 19
B31: NO CUMPLE | C31: =COUNTIF($C$4:$C$28,"NC") -> 1
B32: NO APLICA | C32: =COUNTIF($C$4:$C$28,"NA") -> 1

Sheet 11.1.2.INF
B1: VOLVER A TABLA DE CONTENIDO
B2: Estandar de Infraestructura
A3: Estandar | B3: Criterios | C3: Estado | D3: Comentarios
A4: TSINF | B4: Edificaciones de uso exclusivo en salud
A5: TSINF | B5: 1. Los servicios de salud de urgencias, de atención del parto, hospitalarios y de cirugía que realicen procedimientos quirúrgicos no ambulatorios, solo se pueden prestar en edificaciones de uso exclusivo de salud. | C5: C
A6: TSINF | B6: 2. Los servicios de salud de: urgencias, cirugía y del grupo de internación, así como en los servicios de salud donde se realice el proceso de esterilización, deben contar con ambiente de aseo de uso exclusivo | C6: NC
A7: TSINF | B7: 3. Cuando en una edificación de uso exclusivo de salud funcione más de un prestador de servicios de salud con servicios de los grupos de consulta externa y apoyo diagnóstico y complementación terapeutica, cada prestador cuenta con infraestructura separada delimitada fisicamente. Se pueden compartir los siguientes ambientes y áreas: aseo, salas de espera y unidades sanitarias. | C7: NA
A8: TSINF | B8: 4. Las edificaciones donde se presten servicios de salud de urgencias y del grupo de internación, cuentan con tanque de almacenamientode agua para el consumo humano que garantice como mínimo una reserva de 24 horas de servicio continuo, calculando con base en el consumo de 600 lt por cama/camilla al día.
A9: TSINF | B9: 5. Cuando el prestador de servicios de salud cuente con mas de una infraestructura y estas se puedan vincular funcionalmente entre si, lo harán mediante tunel o puente cubierto, o muro(s) colindante(s) que cuenten con acceso (s) que intercomuniquen las infraestructuras, de uso exclusivo del prestador y adicionalmente cumplen con las siguientes caracteristicas:
A10: TSINF | B10: 5.1. Ancho que permita la movilización de camas, camillas, sillas de ruedas, equipos biomédicos y personal para el traslado de los pacientes en condiciones seguras.
A11: TSINF | B11: 5.2. El piso del túnel o puente debe ser uniforme y de material antideslizante o con elementos que garanticen esta propiedad en todo su recorrido, con pasamanos d a ambos lados y con protecciones laterales hacia espacios libres.
A12: TSINF | B12: 5.3. Lo anterior siempre y cuando la norma urbanística de la jurisdicción donde se localizan las sedes hayan aprobado esta forma de vinculación funcional entre las mismas.
A13: TSINF | B13: 5.4. Esta edificación se podrá habilitar como una o varias sedes, de acuerdo con lo que determine el prestador de servicios de salud
A14: TSINF | B14: Edificaciones de uso mixto
A15: TSINF | B15: 6. Cuando en una edificación de uso mixto funcione más de un prestador de servicios de salud, cada uno cuenta con infraestructura separada y delimitada físicamente. Se pueden compartir las salas de espera y las unidades sanitarias.
A16: TSINF | B16: 7. En edificaciones de uso mixto pueden funsionar los prestadores de servicios de salud que oferten y presten servicios de los grupos de consulta externa. de apoyo diagnóstico y complementación terapeutica y los servicios del grupo quirurgico que realicen exclusivamente procedimientos de cirugia ambulatoria.
A17: TSINF | B17: Edificaciones de uso exclusivo en salud y edificaciones de uso mixto
A18: TSINF | B18: 8. Los prestadores de servicios de salud ubicados en edificaciones de hasta tres (3) pisos o niveles contados a partir del nivel más bajo construido, y que funcione en segundo o tercer nivel o piso, cuentan con ascensor o rampa o sistema alternativo de elevación. El sistema alternativo de elevación no puede ser utilizado cuando se presten servicios hospitalarios, cirugía, urgencias o de atención del parto.
A19: TSINF | B19: 9. Los sistemas alternativos de elevación deben cumplir con las siguientes condiciones:
... A200: TSINF | B200: 53.5. Nivel de iluminación homogénea.
B202: CUMPLE | C202: =COUNTIF($C$5:$C$200,"C") -> 1
B203: NO CUMPLE | C203: =COUNTIF($C$5:$C$200,"NC") -> 1
B204: NO APLICA | C204: =COUNTIF($C$5:$C$200,"NA") -> 1

Sheet 11.1.3.DOT
B1: VOLVER A TABLA DE CONTENIDO
B2: Estandar de Dotación
A3: Estandar | B3: Criterios | C3: Estado | D3: Comentarios
A4: TSDOT | B4: 1. El prestador de servicios de salud cuenta con el registro de la relación de los equipos biomédicos requeridos para la prestación de servicios de salud, este registro cuenta como mínimo con la siguiente información:
A5: TSDOT | B5: 1.1. Nombre del equipo biomédico. | C5: C
A6: TSDOT | B6: 1.2. Marca. | C6: NC
A7: TSDOT | B7: 1.3. Modelo. | C7: NA
A8: TSDOT | B8: 1.4. Serie.
A9: TSDOT | B9: 1.5. Registro sanitario para dispositivos médicos o permiso de comercialización para equipos biomédicos de tecnología controlada, cuando lo requiera.
A10: TSDOT | B10: 1.6. Clasificación por riesgo, cuando el equipo lo requiera.
A11: TSDOT | B11: 2. El prestador de servicios de salud garantiza las condiciones técnicas de calidad de los equipos biomédicos, para lo cual cuenta con:
A12: TSDOT | B12: 2.1. Programa de mantenimiento preventivo de los equipos biomédicos, que incluya el cumplimiento de las recomendaciones establecidas por el fabricante o de acuerdo con el protocolo de mantenimiento que tenga definido el prestador, éste último cuando no esté definido por el fabricante.
A13: TSDOT | B13: 2.2. Hoja(s) de vida del(los) equipo(s) biomédico(s), con los registros de los mantenimientos preventivos y correctivos, según corresponda.
A14: TSDOT | B14: 3. El prestador de servicios de salud cuenta con un programa de capacitación en el uso de dispositivos médicos cuando éstos lo requieran, el cual puede ser desarrollado por el fabricante, importador o por el mismo prestador.
A15: TSDOT | B15: 4. La dotación de los servicios de salud está en concordancia con lo definido por el prestador en el estándar de procesos prioritarios.
A16: TSDOT | B16: 5. La suficiencia de equipos biomédicos está relacionada con la frecuencia de uso de los mismo, incluyendo los tiempos del proceso de esterilización, cuando aplique.
A17: TSDOT | B17: 6. El mantenimiento de los equipos biomédicps es ejecutado por el talento humano profesional, tecnólogo o técnico en áreas relacionadas. Este mantenimiento puede ser realizado directamente por el prestador de servicios de salud o mediante contrato o convenio con un tercero.
A18: TSDOT | B18: 7. Los prestadores que oferten servicios de salud en modalidad extramural no pueden elaborar ni adaptar dispositivos médicos sobre medida.
A19: TSDOT | B19: 8. Los servicios de salud que requieren carro de paro, cuenta con la siguiente dotación:
... A66: TSDOT | B66: 17.2.2. Las pantallas o monitores grado médico utilizados para el despliegue de imágenes cuentan con una distancia máxima de 0.19 milímetros entre pixeles (dot pitch), resolución mínima de 1024 x 768 pixeles, como mínimo un ratio de contraste de 500:1 y mínimo de luminancia (brillo) de 250 cd/m2 que permita garantizar la interpretación adecuada de la información recibida.
B68: CUMPLE | C68: =COUNTIF($C$5:$C$66,"C") -> 1
B69: NO CUMPLE | C69: =COUNTIF($C$5:$C$66,"NC") -> 1
B70: NO APLICA | C70: =COUNTIF($C$5:$C$66,"NA") -> 1

Sheet 11.1.4MD
B1: VOLVER A TABLA DE CONTENIDO
B2: Estandar de Medicamentos, dispositivos médicos e insumos
A3: Estandar | B3: Criterios | C3: Estado | D3: Comentarios
A4: TSMD | B4: 1. El prestador de servicios de salud lleva registros con la información de todos los medicamentos para uso humano requeridos en la prestación de los servicios que oferte; dichos registros cuentan con la siguiente información:
A5: TSMD | B5: 1.1. Principio activo. | C5: C
A6: TSMD | B6: 1.2. Forma farmacéutica. | C6: NC
A7: TSMD | B7: 1.3. Concentración | C7: NA
A8: TSMD | B8: 1.4. Lote.
A9: TSMD | B9: 1.5. Fecha de vencimiento.
A10: TSMD | B10: 1.6. Presentación comercial.
A11: TSMD | B11: 1.7. Unidad de medida.
A12: TSMD | B12: 1.8. Registro sanitario vigente o permiso cuando se autorice, expedido por el Invima.
A13: TSMD | B13: 2. Los dispositivos médicos de uso humano requeridos para la prestación de los servicios de salud cuentan con información documentada que dé cuenta de la verificación y seguimiento de la siguiente información:
A14: TSMD | B14: 2.1. Descripción.
A15: TSMD | B15: 2.2. Marca del dispositivo.
A16: TSMD | B16: 2.3. Serie (cuando le aplique).
A17: TSMD | B17: 2.4. Presentación comercial.
A18: TSMD | B18: 2.5. Registro sanitario vigente o permiso de comercialización expedido por el Invima.
A19: TSMD | B19: 2.6. Clasificación por riesgo (información consignada en el registro sanitario o permiso de comercialización).
... A62: TSMD | B62: 17. El prestador de servicio de salud cumple con los criterios que le apliquen del presente estándar.
B65: CUMPLE | C65: =COUNTIF($C$5:$C$62,"C") -> 1
B66: NO CUMPLE | C66: =COUNTIF($C$5:$C$62,"NC") -> 1
B67: NO APLICA | C67: =COUNTIF($C$5:$C$62,"NA") -> 1

Sheet 11.1.5.PP
B1: VOLVER A TABLA DE CONTENIDO
B2: Estandar de Procesos Prioritarios
A3: Estandar | B3: Criterios | C3: Estado | D3: Comentarios
A4: TSPP | B4: 1. El prestador de servicios de salud cuenta con una política de seguridad del paciente acorde con los lineamientos expedidos por el Ministerio de Salud y Protección Social. | C4: C
A5: TSPP | B5: 2. El prestador de servicios de salud realiza actividades encaminadas a gestionar la seguridad del paciente. | C5: NC
A6: TSPP | B6: 3. El prestador de servicios de salud cuenta con un comité o instancia que orienta y promueve la política de seguridad del paciente, el control de infecciones y ta optimización del uso de antibióticos, cuando tos prescriba o administre. En el caso de profesionales independientes de salud podrá ser el mismo prestador. | C6: NA
A7: TSPP | B7: 4. El prestador de servicios de salud adopta y realiza las siguientes prácticas seguras, según aplique a su servicio de salud y cuenta con información documentada para:
A8: TSPP | B8: 4.1. Asegurar la correcta identificación del paciente en los procesos asistenciales. (que incluya como mínimo dos identificadores: nombre completo y número de identificación)
A9: TSPP | B9: 4.2. Gestionar y desarrollar una adecuada comunicación entre las personas que atienden y cuidan a los pacientes que incluyan enfoques diferenciales.
A10: TSPP | B10: 4.3. Detectar, prevenir y reducir infecciones asociadas con la atención en salud (que incluya protocolo de higiene de manos o higienización con soluciones a base de alcohol).
A11: TSPP | B11: 4.4. Detectar, ana!izar y gestionar eventos adversos.
A12: TSPP | B12: 4.5. Garantizar la funcionalidad de los procedimientos de consentimiento informado.
A13: TSPP | B13: 4.6. Mejorar la seguridad en la utilización de medicamentos, en los servicios donde aplique.
A14: TSPP | B14: 4.7. Prevenir y reducir la frecuencia de caídas, en los servicios donde aplique.
A15: TSPP | B15: 4.8. Garantizar la atención segura de ta gestante y el recién nacido, en los servicios donde aplique.
A16: TSPP | B16: 4.9. Prevenir complicaciones asociadas a disponibilidad y manejo de sangre, componentes y a la transfusión sanguínea, en los servicios donde aplique.
A17: TSPP | B17: 4.10. Prevenir úlceras por presión, en los servicios donde aplique.
A18: TSPP | B18: 4.11. Mejorar la seguridad en los procedimientos quirúrgicos, en los servicios donde aplique. | C18: C
A19: TSPP | B19: 5. El prestador de servicios de salud promueve la cultura de seguridad del paciente que involucra a todo el personal de manera sistemática con un enfoque educativo no punitivo mediante:
A20: TSPP | B20: 5.1. Capacitación del personal en el tema de seguridad del paciente y en los principales riesgos de la atención.
A21: TSPP | B21: 5.2. Actividades donde se ilustra al paciente y sus allegados en el autocuidado de su seguridad.
A22: TSPP | B22: 6. El prestador de servicios de salud cuenta con información documentada de las actividades y procedimientos que se realizan en el servicio acordes con su objeto, alcance y enfoque diferencial, mediante guías de práctica clínica- GPC, procedimientos de atención, protocolos de atención y otros documentos que el prestador de servicios de salud determine, dicha información incluye talento humano, equipos biomédicos, medicamentos y dispositivos médicos e insumos requeridos.
A23: TSPP | B23: 7. La información documentada es conocida mediante acciones de formación continua por el talento humano encargado y responsable de su aplicación, incluyendo el talento humano en entrenamiento, y existe evidencia de su socialización.
A24: TSPP | B24: 8. Las guías de práctica clínica y protocolos a adoptar son en primera medida los que disponga el Ministerio de Salud y Protección Social. En caso de no estar disponibles, o si existe nueva evidencia científica que actualice alguna o algunas de las recomendaciones de las guías de práctica clínica o requerimientos de los protocolos, el prestador de servicios de salud adopta, adapta o desarrolla guías de práctica clínica o protocolos basados en evidencia científica, publicados nacional o internacionalmente.
A25: TSPP | B25: 9. El prestador de servicios de salud de acuerdo con las patologías más frecuentes en el servicio define la guía o guías de práctica clínica a adoptar, o adaptar o desarrollar.
A26: TSPP | B26: 10. El prestador de servicios de salud cuenta con información documentada de la adopción, o adaptación o desarrollo de guías práctica clínica o protocolos basados en evidencia científica.
A27: TSPP | B27: 11. Los servicios de salud donde se atiendan pacientes con enfermedades terminales, crónicas, degenerativas e irreversibles, a los cuales se determine el manejo del dolor y cuidado paliativo, cuentan con información documentada para su manejo.
A28: TSPP | B28: 12. El prestador de servicios de salud cuenta con la siguiente información documentada:
A29: TSPP | B29: 12.1. Detección, prevención y disminución del riesgo de accidentes e incidentes de carácter radiológico, en los servicios donde aplique.
A30: TSPP | B30: 12.2. Aseo, limpieza y desinfección de áreas y superficies.
... A112: TSPP | B112: 32. Adicional a los criterios solicitados para el prestador remisor, cuenta con información documentada de las actividades y procedimientos de los servicios que oferte, acordes con su objeto, alcance y enfoque diferencial, mediante guías de práctica clínica- GPC, procedimientos de atención, protocolos de atención y otros documentos que el prestador de servicios de salud determine, dicha información incluye talento humano, equipos biomédicos, medicamentos y dispositivos médicos e insumos requeridos.
B115: CUMPLE | C115: =COUNTIF($C$4:$C$112,"C") -> 2
B116: NO CUMPLE | C116: =COUNTIF($C$4:$C$112,"NC") -> 1
B117: NO APLICA | C117: =COUNTIF($C$4:$C$112,"NA") -> 1

Sheet 11.1.6.HCR
B1: VOLVER A TABLA DE CONTENIDO
B2: Estandar de Historia Clínica y Registros
B3: Modalidades intramural, extramural: unidad movil, domicialiria, jornada de salud y telemedicina prestador remisor - prestador de referencia.
A4: Estandar | B4: Criterios | C4: Estado | D4: Comentarios
A5: TSHCR | B5: 1. Toda atención de primera vez a un usuario debe incluir el proceso de apertura de historia clínica. Todos los pacientes atendidos cuentan con historia clínica. | C5: C
A6: TSHCR | B6: 2. El prestador de servicios de salud cuenta con procedimientos para utilizar una historia única y para el registro de entrada y salida de historias del archivo físico. Ello implica que el prestador de servicios de salud cuente con un mecanismo para unificar la información de cada paciente y su disponibilidad para el equipo de salud. | C6: NC
A7: TSHCR | B7: 3. Los medios electrónicos para la gestión de la historia clínica garantizan la confidencialidad y seguridad, así como el carácter permanente de registrar en ésta y en otros registros asistenciales, sin que se puedan modificar los datos una vez se guarden los registros. | C7: NA
A8: TSHCR | B8: 4. Las historias clínicas cuentan con los componentes y los contenidos mínimos definidos en la normatividad que regula la materia
A9: TSHCR | B9: 5. La historia clínica y los registros asistenciales se diligencian en forma clara, legible, sin tachones, enmendaduras, intercalaciones, sin dejar espacios en blanco y sin utilizar siglas.
A10: TSHCR | B10: 6. Cada anotación lleva la fecha y hora en la que se realiza, con el nombre completo y firma del autor de la misma.
A11: TSHCR | B11: 7. El diligenciamiento de los registros de atención de la historia clínica se realiza simultánea o inmediatamente después de la atención en salud.
A12: TSHCR | B12: 8. La historia clínica y demás registros son conservados en archivo único garantizando la custodia y confidencialidad de los documentos o registros protegidos legalmente por reserva.
A13: TSHCR | B13: 9. El prestador de servicios de salud cuenta con un procedimiento de consentimiento informado que incluye mecanismos para verificar su aplicación, para que el paciente o su responsable, aprueben o no documentalmente, el procedimiento e intervención en salud a que va a ser sometido, previa información de los beneficios, riesgos, alternativas e implicaciones del acto asistencial
A14: TSHCR | B14: 10. Cuando el prestador de servicios de salud utilice mecanismos electrónicos, ópticos o similares para generar, recibir, almacenar, o disponer datos de la historia clínica y para conservarlos, debe avalar que el mecanismo utilizado cumple con características de: autenticidad, fiabilidad, integridad y disponibilidad del documento, de acuerdo con lo establecido en la normatividad vigente expedida por el Archivo General de la Nación, la Superintendencia de Industria y Comercio y el Ministerio de Tecnologías de información y Comunicaciones, para lo cual, el prestador presentará un documento firmado por un ingeniero de sistemas con tarjeta profesional vigente, certificando que el mecanismo usado por el prestador cumple con la normatividad mencionada
A15: TSHCR | B15: Cuenta con los siguientes registros, cuando los prestadores de servicios de salud realicen el proceso de esterilización dentro del servicio y fuera de centrales de esterilización:
A16: TSHCR | B16: 11.1. Actividades documentadas y realizadas en el procedimiento de reúso de dispositivos médicos acorde con las recomendaciones del fabricante, incluyendo el número de reúsos por cada dispositivo esterilizado.
A17: TSHCR | B17: 11.2. Registro de cargas.
A18: TSHCR | B18: 11.3. Resultados del control de calidad.
A19: TSHCR | B19: 11.4. Listas del contenido de los paquetes que se esterilizan.
... A32: TSHCR | B32: 13.1. Registro de donantes detectados
B33: 13.2. Registro de consulta del documento de voluntad anticipada de todos los pacientes facellidos
A34: TSHCR | B34: 13.3. Registros en la historia clínica de la información sobre el proceso de donación efectuado por los profesionales de salud inscritos ante el Instituto Nacional de Salud
A35: TSHCR | B35: Modalidad Extramural
A36: TSHCR | B36: 14. La historia clínica utilizada en la modalidad extramural es custodiada por el prestador de servicios de salud que oferta y presta el servicio de salud en la modalidad extramural y cuenta con los siguientes registros:
A37: TSHCR | B37: Modalidad Extramural Domiciliaria
A38: TSHCR | B38: 14.1. Valoración de ingreso con el respectivo plan de tratamiento
A39: TSHCR | B39: 14.2. Nombre de los pacientes atendidos
A40: TSHCR | B40: 14.3. Registros de referencia y contrarreferencia, cuando se requieran
A41: TSHCR | B41: 14.4. Cuidados por parte del personal de salud
A42: TSHCR | B42: 14.5. Cuidados encargados a la familia cuando aplique
A43: TSHCR | B43: Modalidad Extramural Jornada de Salud y Unidad Móvil
A44: TSHCR | B44: 14.6. Registro de rutas, horarios y frecuencias de la prestación de los servicios ofertados
A45: TSHCR | B45: 14.7. Nombre de los pacientes atendidos.
... A61: TSHCR | B61: 18. Registro de las atenciones realizadas en la modalidad de telemedicina
B64: CUMPLE | C64: =COUNTIF($C$5:$C$61,"C") -> 1
B65: NO CUMPLE | C65: =COUNTIF($C$5:$C$61,"NC") -> 1
B66: NO APLICA | C66: =COUNTIF($C$5:$C$61,"NA") -> 1

Sheet 11.1.7INT
B1: VOLVER A TABLA DE CONTENIDO
B2: Estandar de Interdependencia
A3: Estandar | B3: Criterios | C3: Estado | D3: Comentarios
A4: TSINT | B4: 1. Cuando el servicio interdependiente sea contratado, debe mediar un contrato o un acuerdo escrito entre las dos partes, en el que se establezca que el servicio interdependiente apoya el servicio principal, estableciendo como mínimo:
A5: TSINT | B5: 1.1 Calidad en la entrega de los productos | C5: C
A6: TSINT | B6: 1.2. Procedimientos documentados de atención en cada servicio independiente | C6: NC
A7: TSINT | B7: 1.3 Tiempos de entrega de los productos | C7: NA
A8: TSINT | B8: 1.4 Supervisión al contratista que garantice la seguridad del resultado del producto contratado.
A9: TSINT | B9: 2. Cuando fuera de salas de cirugía, se realicen procedimientos bajo sedación y monitorización electroencelfalografica con video y radio; el prestador de servicios de salud tendrá disponibilidad del servicio de transporte asistencial
B12: CUMPLE | C12: =COUNTIF($C$5:$C$9,"C") -> 1
B13: NO CUMPLE | C13: =COUNTIF($C$5:$C$9,"NC") -> 1
B14: NO APLICA | C14: =COUNTIF($C$5:$C$9,"NA") -> 1

Sheet 11.2.1.S_CE_G
B1: VOLVER A TABLA DE CONTENIDO
B2: Grupo Consulta Externa
B3: Servicio de Consulta Externa General
A4: Estandar | B4: Criterios | C4: Estado | D4: Comentarios
A5: CEG_TH | B5: Complejidad baja
A6: CEG_TH | B6: Modalidad intramural, extramural unidad móvil, jornada de salud y domiciliaria
A7: CEG_TH | B7: 1. Cumple con los criterios que le sean aplicables de todos los servicios y adicionalmente. | C7: C
A8: CEG_TH | B8: 2. Cuenta con el profesional de la salud de acuerdo con el servicio a ofertar. | C8: NC
A9: CEG_TH | B9: 3. Cuando se oferte la estrategia para el majo de la Enfermedad Respiratoria Aguda (ERA), el servicio tiene disponibilidad de:
A10: CEG_TH | B10: 3.1. Profesional de la medicina. | C10: NA
A11: CEG_TH | B11: 3.2. Profesional de la enfermería o terapia respiratoria o fisioterapia.
A12: CEG_TH | B12: Modalidad telemedicina
A13: CEG_TH | B13: Categoría interactiva y no interactiva-prestador de referencia
A14: CEG_TH | B14: 4. Cumple con los criterios que le sean aplicables de todos los servicios y adicionalmente, cuenta con:
A15: CEG_TH | B15: 4.1. Profesional de la salud de acuerdo con el servicio a ofertar.
A16: CEG_TH | B16: Categoria telexperticia- prestador de remisor
A17: CEG_TH | B17: 5. Cumple con los criterios que le sean aplicables de todos los servicios y adicionalmente:
A18: CEG_TH | B18: 5.1. Cuando se realice telexperticia entre profesionales de la salud cuenta con el profesional de la salud de acuerdo con el servicio a ofertar.
A19: CEG_TH | B19: 5.2. Cuando realice telexperticia entre personal de salud no profesional y un profesional de la salud, el prestador remisor cuenta con técnico, tecnólogo o auxiliar que atiende presencialmente al usuario.
A20: CEG_TH | B20: Categoria telexperticia-prestador de referencia
A21: CEG_TH | B21: 6. Cumple con los criterios que le sean aplicables de todos los servicios y adicionalmente cuenta con profesional de la salud que atiende a distancia, de acuerdo con el servicio a ofertar.
A22: CEG_TH | B22: Categoría telemonitoreo-prestador de referencia
... A158: CEG_INT | B158: 44. No aplica
B161: CUMPLE | C161: =COUNTIF($C$5:$C$158,"C") -> 1
B162: NO CUMPLE | C162: =COUNTIF($C$5:$C$158,"NC") -> 1
B163: NO APLICA | C163: =COUNTIF($C$5:$C$158,"NA") -> 1

Sheet 11.2.2.S_CE_E
B1: VOLVER A TABLA DE CONTENIDO
B2: Grupo Consulta Externa
B3: Servicio de Consulta Externa Especializada | C3: Servicio xxx
A4: Estandar | B4: Criterios | C4: Estado | D4: Comentarios
A5: CEE_TH | B5: Complejidad mediana
A6: CEE_TH | B6: Modalidades intramural, extramural unidad móvil, jornada de salud y domiciliaria
A7: CEE_TH | B7: 1. Cumple con los criterios definidos para el servicio de consulta externa general y adicionalmente cuenta con: | C7: C
A8: CEE_TH | B8: 1.1. Profesional de la salud con titulo de especialista, según los programas académicos autorizados por el Ministerio de Educación Nacional. | C8: NC
A9: CEE_TH | B9: 1.2. Para medicina alternativa y terapias alternativas y complementarias, cuenta con profesional de la salud con título de especialista en el ámbito de su disciplina, para lo cual deberá acreditar la respectiva certificación académica de esa norma de competencia, expedida por una institución de educación superior legalmente reconocida por el Estado y de acuerdo con lo documentado por el prestador de servicios de salud en el estándar de procesos prioritarios. | C9: NA
A10: CEE_TH | B10: Modalidad telemedicina
A11: CEE_TH | B11: Categoría interactiva y no interactiva-prestador de referencia
A12: CEE_TH | B12: 2. Cumple con los criterios que le sean aplicables de todos los servicios y adicionalmente, cuenta con:
A13: CEE_TH | B13: Profesional de la salud con título de especialista de acuerdo con el servicio a o ofertar
A14: CEE_TH | B14: Categoría telexperticia -prestador remisor
A15: CEE_TH | B15: 3. Cumple con los criterios que le sean aplicables de todos los servicios y adicionalmente:
A16: CEE_TH | B16: 3.1. Cuando se realice telexperticia entre profesionales de la salud cuenta con el profesional de salud con título de especialista de acuerdo con el servicio a ofertar.
A17: CEE_TH | B17: 3.2. Cuando realice telexperticia entre personal de salud no profesional y un profesional de la salud con título de especialista, el prestador remisor cuenta con técnico, tecnólogo o auxiliar que atiende presencialmente al usuario.
A18: CEE_TH | B18: Categoría telexperticia-prestador de referencia
A19: CEE_TH | B19: 4. Cumple con los criterios que le sean aplicables de todos los servicios y adicionalmente cuenta con profesional de la salud con título de especailista que atiende a distancia, de acuedo con el servicio a ofertar.
A20: CEE_TH | B20: Categoría telemonitoreo-prestador referencia
A21: CEE_TH | B21: 5. Cumple con los criterios que le sean aplicables de todos los servicios y adicionalmente cuenta con el personal de salud profesional con título de especialista que se requiera para realizar el telemonitoreo de acuerdo con lo documentado por el prestador de servicios de salud en el estándar de procesos prioritarios.
... A91: CEE_ INT | B91: 30. No aplica
B94: CUMPLE | C94: =COUNTIF($C$5:$C$91,"C") -> 1
B95: NO CUMPLE | C95: =COUNTIF($C$5:$C$91,"NC") -> 1
B96: NO APLICA | C96: =COUNTIF($C$5:$C$91,"NA") -> 1

Sheet 11.2.3.S_CE_V
B1: VOLVER A TABLA DE CONTENIDO
B2: Grupo Consulta Externa
B3: Servicio de Vacunación
A4: Estandar | B4: Criterios | C4: Estado | D4: Comentarios
A5: CEV_TH | B5: Complejidad baja
A6: CEV_TH | B6: Modalidades intramural, extramural unidad móvil, jornada de salud y domiciliaria
A7: CEV_TH | B7: 1. Cumple con los criterios que le sean aplicables de todos los servicios y adicionalmente, cuenta con: | C7: C
A8: CEV_TH | B8: 1.1 Profesional de la medicina o profesional de la enfermeria. | C8: NC
A9: CEV_TH | B9: 2. Si se requiere personal adicional para:
A10: CEV_TH | B10: 2.1 La administración de la vacuna cuenta con auxiliar de enfermerla o auxiliar de salud pública bajo la supervisión del profesional de la medicina o profesional de la enfermería. | C10: NA
A11: CEV_TH | B11: 2.2. El manejo de la cadena de frio puede disponer de auxiliar de enfermeria o auxiliar en salud pública o gestor comunitario en salud (en zonas de dispersión geográfica) o regentes de farmacia o qulmico farmaceutico con experiencia en cadena de frio.
A12: CEV_INF | B12: Complejidad baja
A13: CEV_INF | B13: Modalidad intramural
A14: CEV_INF | B14: 3. Cumple con los criterios que le sean aplicables de todos los servicios y adicionalmente cuenta con:
A15: CEV_INF | B15: Para los servicios en modalidad intramural de prestadores de servicios de salud que separen el servicio de vacunación en dos ambientes cuenta con:
A16: CEV_INF | B16: 4. Consultorio o ambiente que, de acuerdo con la oferta, cumple con los siguientes requisitos:
A17: CEV_INF | B17: 4.1 Consultorio para administración de medicamentos biologicos que cuenta con:
A18: CEV_INF | B18: 4.1.1. Área para entrevista.
A19: CEV_INF | B19: 4.1.2. Área para el alistamiento y administración de medicamentos biológicos.
A20: CEV_INF | B20: 4.1.3. Lavamanos
A21: CEV_INF | B21: 4.2. Ambiente para almacenamiento y alistamiento de dispositivos y termos que cuenta con:
A22: CEV_INF | B22: 4.2.1. Área para el alistamiento de termos o cajas témicas.
... A81: CEV_INT | B81: 12. No aplica
B84: CUMPLE | C84: =COUNTIF($C$5:$C$81,"C") -> 1
B85: NO CUMPLE | C85: =COUNTIF($C$5:$C$81,"NC") -> 1
B86: NO APLICA | C86: =COUNTIF($C$5:$C$81,"NA") -> 1

Sheet 11.2.4.S_CE_SST
B1: VOLVER A TABLA DE CONTENIDO
B2: Grupo Consulta Externa
B3: Servicio de Seguridad y Salud en el Trabajo
A4: Estandar | B4: Criterios | C4: Estado | D4: Comentarios
A5: CESST_TH | B5: Complejidad mediana
A6: CESST_TH | B6: Modalidades intramural, extramural unidad móvil y jornada de salud
A7: CESST_TH | B7: 1. Cumple con los criterios que le sean aplicables de todos los servicios y adicionalmente cuenta con: | C7: C
A8: CESST_TH | B8: 1.1. Profesional de la medicina especialista en medicina del trabajo o medicina laboral o seguridad y salud en el trabajo con licencia vigente de seguridad y salud en el trabajo expedida por autoridad competente. | C8: NC
A9: CESST_TH | B9: 1.2. Cuando se realicen pruebas complementarlas de tamización (audiometria, visiometria, espirometrla según aplique), disponibilidad de profesionales de la salud de conformidad con lo documentado en el estándar de procesos prioritarios. | C9: NA
A10: CESST_TH | B10: Modalidad telemedicina-prestador remisor
A11: CESST_TH | B11: 2. Cumple con los criterios que le sean aplicables de todos los servicios y adicionalmente:
A12: CESST_TH | B12: 2.1. Cuando se realice telexperticia entre profesionales de la salud cuenta con el profesional de la salud.
A13: CESST_TH | B13: Modalidad telemedicina-prestador de referencia
A14: CESST_TH | B14: 3. Cumple con los criterios que le sean aplicables de todos los servicios y adicionalmente cuenta con:
A15: CESST_TH | B15: Profesional en salud según la oferta definida por el prestador de servicios de salud en el estándar de procesos prioritarios.
A16: CESST_INF | B16: Complejidad mediana
A17: CESST_INF | B17: Modalidades intramural y extramural unidad móvil, jornada de salud y telemedicina-prestador remisor
A18: CESST_INF | B18: 4. Cumple con los criterios definidos del servicio de consulta externa para consultorio donde se realiza examen físico.
A19: CESST_INF | B19: Modalidad telemedicina -prestador de referencia
A20: CESST_INF | B20: 5. Cumple con los criterios que le sean aplicables de todos los servicios.
A21: CESST_DOT | B21: Complejidad mediana
... A53: CESST_INT | B53: 14. No aplica
B56: CUMPLE | C56: =COUNTIF($C$5:$C$53,"C") -> 1
B57: NO CUMPLE | C57: =COUNTIF($C$5:$C$53,"NC") -> 1
B58: NO APLICA | C58: =COUNTIF($C$5:$C$53,"NA") -> 1

Sheet 11.3.1.S_TR
B1: VOLVER A TABLA DE CONTENIDO
B2: Grupo apoyo diagnóstico y complementación tereapeutica
B3: Servicio de Terapias
A4: Estandar | B4: Criterios | C4: Estado | D4: Comentarios
A5: TR_TH | B5: Modalidad intramural y extramural unidad móvil, jornada de salud y domiciliaria
A6: TR_TH | B6: 1. Cumple con los criterios definidos para todos los servicios y adicionalmente cuenta con: | C6: C
A7: TR_TH | B7: 1.1. Profesionales de la salud con título según los programas académicos autorizados por el Ministerio de Educación Nacional en el ámbito de la rehabilitación, según oferta. | C7: NC
A8: TR_TH | B8: 1.2. Si oferta evaluación y tratamiento desde el enfoque de integración neurosensorial, cuenta con constancia de asistencia en las acciones de formación continua para la realización de los procedimientos según la oferta. | C8: NA
A9: TR_TH | B9: Modalidad telemedicina Categoría interactiva y no interactiva - prestador de referencia
A10: TR_TH | B10: 2. Cumple con los criterios que le sean aplicables de todos los servicios y adicionalmente, cuenta con:
A11: TR_TH | B11: 2.1 Profesional de la salud de acuerdo con el servicio a ofertar.
A12: TR_TH | B12: Categoría telexperticia - prestador remisor
A13: TR_TH | B13: 3. Cumple con los criterios que le sean aplicables de todos los servicios y adicionalmente
A14: TR_TH | B14: 3.1. Cuando se realice telexperticia entre profesionales de la salud cuenta con el profesional de la salud de acuerdo con el servicio a ofertar
A15: TR_TH | B15: Categoría telexperticia - prestador de referencia
A16: TR_TH | B16: 4. Cumple con los criterios que le sean aplicablesde todos los servicios y adicionalmente cuenta con profesional de la salud que atiende a distancia, de acuerdo con el servicio a ofertar.
A17: TR_TH | B17: Categoría telemonitoreo - prestador de referencia
A18: TR_TH | B18: 5. Cumple con los criterios que le sean aplicables de todos los servicios y adicionalmente cuenta con el personal de la salud profesional que se requiere para realizar el telemonitoreo de acuerdo con lo documentado por el prestador de servicios de salud en el estándar de procesos prioritarios.
A19: TR_INF | B19: 6. Cumple con los criterios que le sean aplicables de todos los servicios, y adicionalmente
A20: TR_INF | B20: 7. De acuerdo con el tipo de terapia ofertada, el servicio cuenta con:
... A77: TER_INT | B77: 30. No aplica.
B80: CUMPLE | C80: =COUNTIF($C$5:$C$77,"C") -> 1
B81: NO CUMPLE | C81: =COUNTIF($C$5:$C$77,"NC") -> 1
B82: NO APLICA | C82: =COUNTIF($C$5:$C$77,"NA") -> 1

Sheet  11.3.2.SF
B1: VOLVER A TABLA DE CONTENIDO
B2: Grupo apoyo diagnóstico y complementación tereapeutica
B3: Servicio Farmacéutico
A4: Estandar | B4: Criterios | C4: Estado | D4: Comentarios
A5: SF_TH | B5: Modalidades intramural y extramural domiciliaria
A6: SF_TH | B6: 1. Cumple con los criterios definidos para todos los servicios y adicionalmente: | C6: C
A7: SF_TH | B7: Cumple con lo definido en el Decreto 2200 de 2005 compilado en el Decreto 780 de 2016 (Art 2.5.3.10.9) y la Resolución 1403 de 2007 (Manual de condiciones esenciales y procedimientos del servicio farmacéutico Título I Capitulo II Numeral 3.2 y Capítulo III Numeral 1.2), o las normas que los modifiquen, adicionen o sustituyan. | C7: NC
A8: SF_TH | B8: Modalidad telemedicina Categoría interactiva y no interactiva – prestador de referencia Categoría telexperticia – prestador remisor – prestador de referencia
A9: SF_TH | B9: 2. Cumple con los criterios que le sean aplicables de todos los servicios y adicionalmente, cuenta con lo definido con el numeral 1 del servicio farmacéutico. | C9: NA
A10: SF_TH | B10: 3. El talento humano brinda en esta modalidad lo relacionado con la atención farmacéutica a los pacientes que lo requieran, a través de telemedicina – categorías interactiva y no interactiva, telexperticia sincrónico y asincrónico.
A11: SF_TH | B11: El apoyo a distancia del profesional Químico Farmacéutico no reemplaza el contar con el talento humano definido en el servicio
A12: SF_INF | B12: Complejidad baja
A13: SF_INF | B13: Modalidades intramural, extramural domiciliaria, telemedicina categoría telexperticia – prestador remisor
A14: SF_INF | B14: 4. Cumple con los criterios que le sean aplicables a todos los servicios
A15: SF_INF | B15: 5. Cuenta con:
A16: SF_INF | B16: 5.1. Ambiente o área administrativa.
A17: SF_INF | B17: 5.2. Ambiente o área de recepción de medicamentos y dispositivos médicos.
A18: SF_INF | B18: 5.3. Ambiente o área de dispensación de medicamentos y entrega de dispositivos médicos.
A19: SF_INF | B19: 5.4. Ambiente o área de almacenamiento, que garantice las condiciones temperatura y humedad recomendadas por el fabricante. Incluye cadena de frio, cuando aplique.
A20: SF_INF | B20: 5.5. Ambiente o área independiente de medicamentos de control especial cuando aplique, que garantice las condiciones temperatura y humedad recomendadas por el fabricante.
A21: SF_INF | B21: 5.6. Ambiente o área para almacenamiento de productos rechazados, devueltos y retirados.
... A71: SF_INT | B71: 22. No aplica.
B74: CUMPLE | C74: =COUNTIF($C$5:$C$71,"C") -> 1
B75: NO CUMPLE | C75: =COUNTIF($C$5:$C$71,"NC") -> 1
B76: NO APLICA | C76: =COUNTIF($C$5:$C$71,"NA") -> 1

Sheet 11.3.3.S_Rx_OD
B1: VOLVER A TABLA DE CONTENIDO
B2: Grupo apoyo diagnóstico y complementación tereapeutica
B3: Servicio de Radiologia Odontológica
A4: Estandar | B4: Criterios | C4: Estado | D4: Comentarios
A5: Rx_OD_TH | B5: Modalidades intramural y extramural unidad móvil
A6: Rx_OD_TH | B6: 1. Cumple con los criterios que le sean aplicables de todos los servicios y adicionalmente, cuenta con: | C6: C
A7: Rx_OD_TH | B7: Profesional de odontología o tecnólogo en radiología e imágenes diagnósticas, o técnico profesional o auxiliar de odontología o auxiliar en salud oral o auxiliar de higiene oral. | C7: NC
A8: Rx_OD_TH | B8: 2. Disponibilidad de profesional de la odontología, si la toma de radiografías la realiza un auxiliar de odontología o auxiliar en salud oral o auxiliar de higiene oral. | C8: NA
A9: Rx_OD_TH | B9: 3. La interpretación de las radiografías odontológicas es realizada por el profesional de la odontología.
A10: Rx_OD_TH | B10: Modalidad Telemedicina: Categoría telexperticia - prestador remisor
A11: Rx_OD_TH | B11: 4. Cumple con los criterios que le sean aplicables de todos los servicios y adicionalmente:
A12: Rx_OD_TH | B12: 4.1. Cuando se realice telexperticia entre profesionales de la salud cuenta con el profesional de la salud.
A13: Rx_OD_TH | B13: 4.2. Cuando realice telexperticia entre personal de salud no profesional y un profesional de la salud, el prestador remisor cuenta con técnico, tecnólogo o auxiliar que atiende presencialmente al usuario.
A14: Rx_OD_TH | B14: Categoría telexperticia - prestador de referencia
A15: Rx_OD_TH | B15: 5. Cumple con los criterios que le sean aplicables de todos los servicios y adicionalmente cuenta con profesional de la salud que atiende a distancia.
A16: RX_OD_INF | B16: Modalidades intramural, telemedicina - prestador remisor
A17: RX_OD_INF | B17: 6. Cumple con los criterios que le sean aplicables de todos los servicios y adicionalmente cuenta con:
A18: RX_OD_INF | B18: 6.1. Ambiente de radiología odontológica, si la tecnología lo requiere. Las dimensiones estarán determinadas según la ficha técnica del equipo.
A19: RX_OD_INF | B19: 6.2. Área de revelado o ambiente oscuro con extracción de gases e iluminación adecuada, con mesón de trabajo con poceta, si la tecnología lo requiere.
A20: RX_OD_INF | B20: 7. Disponibilidad de:
... A69: RX_OD_INT | B69: 21. No aplica.
B72: CUMPLE | C72: =COUNTIF($C$5:$C$69,"C") -> 1
B73: NO CUMPLE | C73: =COUNTIF($C$5:$C$69,"NC") -> 1
B74: NO APLICA | C74: =COUNTIF($C$5:$C$69,"NA") -> 1

Sheet 11.3.4.S_IDx
B1: VOLVER A TABLA DE CONTENIDO
B2: Grupo apoyo diagnóstico y complementación tereapeutica
B3: Servicio de imágenes diagnósticas
B4: Métodos diagnósticos con imágenes obtenidas mediante equipos generadores de radiaciones ionizantes
A5: Estandar | B5: Criterios | C5: Estado | D5: Comentarios
A6: IDX_TH | B6: Complejidad baja
A7: IDX_TH | B7: Modalidades intramural, extramural unidad móvil, telemedicina - prestador remisor
A8: IDX_TH | B8: 1. Cumple con los criterios definidos para todos los servicios y adicionalmente, | C8: C
A9: IDX_TH | B9: 2. Cuenta con:
A10: IDX_TH | B10: Técnico profesional o tecnólogo en imágenes diagnósticas, para la operación de equipos y adquisición de imágenes. | C10: NC
A11: IDX_TH | B11: 3. Disponibilidad de:
A12: IDX_TH | B12: Médico especializado en radiología e imágenes diagnósticas o aquellos médicos especialistas quienes en su pensum o formación académica hayan adquirido los conocimientos del manejo e interpretación del espectro electromagnético, del ultrasonido especialmente, así como de las radiaciones ionizantes para establecer el diagnóstico y/o el tratamiento de las enfermedades inherentes a sus especialidades, para lo cual deberán acreditar el respectivo certificado. La interpretación de las radiografías e imágenes diagnósticas y la supervisión del técnico profesional o tecnólogo en imágenes diagnósticas es realizada por dichos profesionales. | C12: NA
A13: IDX_TH | B13: Complejidad mediana
A14: IDX_TH | B14: Modalidades extramural unidad móvil, telemedicina - prestador remisor
A15: IDX_TH | B15: 4. Cumple con los criterios que le sean aplicables de todos los servicios y adicionalmente cuenta con:
A16: IDX_TH | B16: 4.1. Tecnólogo en radiología e imágenes diagnósticas para la operación de equipos y adquisición de imágenes, con supervisión por el profesional de la medicina especialista en radiología e imágenes diagnósticas.
A17: IDX_TH | B17: 4.2. Médico especializado en radiología e imágenes diagnósticas o aquellos médicos especialistas quienes en su pensum o formación académica hayan adquirido los conocimientos del manejo e interpretación del espectro electromagnético, del ultrasonido especialmente, así como de las radiaciones ionizantes para establecer el diagnóstico y/o el tratamiento de las enfermedades inherentes a sus especialidades. Para lo cual deberá acreditar el respectivo certificado. La interpretación de las radiografías e imágenes diagnósticas y la supervisión del técnico profesional o tecnólogo en imágenes diagnósticas es realizada por dichos profesionales.
A18: IDX_TH | B18: Complejidades mediana y alta
A19: IDX_TH | B19: Modalidades intramural, telemedicina - prestador remisor
A20: IDX_TH | B20: 5. Cumple con los criterios que le sean aplicables de todos los servicios y adicionalmente cuenta con:
A21: IDX_TH | B21: 5.1. Tecnólogo en radiología e imágenes diagnósticas para la operación de equipos y adquisición de imágenes, con supervisión por el profesional de la medicina especialista en radiología e imágenes diagnósticas.
A22: IDX_TH | B22: 5.2. Médico especializado en radiología e imágenes diagnósticas o aquellos médicos especialistas quienes en su pensum o formación académica hayan adquirido los conocimientos del manejo e interpretación del espectro electromagnético, del ultrasonido especialmente, así como de las radiaciones ionizantes para establecer el diagnóstico y/o el tratamiento de las enfermedades inherentes a sus especialidades, para lo cual deberán acreditar el respectivo certificado. La interpretación de las radiografías e imágenes diagnósticas y la supervisión del técnico profesional o tecnólogo en imágenes diagnósticas es realizada por dichos profesionales.
A23: IDX_TH | B23: Complejidad baja, mediana y alta
A24: IDX_TH | B24: Modalidad telemedicina - prestador de referencia
... A154: IDX_INT | B154: 41. No aplica.
B159: Servicio de imágenes diagnósticas
B160: Métodos diagnósticos con imágenes obtenidas mediante equipos generadores de radiaciones NO ionizantes
A161: Estandar | B161: Criterios | C161: Estado | D161: Comentarios
A162: IDX_TH | B162: Complejidad mediana
A163: IDX_TH | B163: Modalidades intramural, extramural jornada de salud, unidad móvil y domiciliaria, telemedicina - prestador remisor
A164: IDX_TH | B164: 1. Cumple con los criterios que le sean aplicables de todos los servicios y adicionalmente cuenta con:
A165: IDX_TH | B165: 1.1. Médico especializado en radiología e imágenes diagnósticas o aquellos médicos especialistas quienes en su pensum o formación académica hayan adquirido los conocimientos del manejo e interpretación del espectro electromagnético, del ultrasonido especialmente, así como de las radiaciones ionizantes para establecer el diagnóstico y/o el tratamiento de las enfermedades inherentes a sus especialidades. Para lo cual deberá acreditar el respectivo certificado.
A166: IDX_TH | B166: 1.2. Cuando se realicen procedimientos de resonancia magnética cuenta con Técnico profesional o tecnólogo en imágenes diagnósticas, para la operación de equipos y adquisición de imágenes.
A167: IDX_TH | B167: Modalidad telemedicina - prestador de referencia
A168: IDX_TH | B168: 2. Cumple con los criterios que le sean aplicables de todos los servicios.
A169: IDX_TH | B169: 3. La interpretación de las imágenes diagnósticas es realizada médico especializado en radiología e imágenes diagnósticas o aquellos médicos especialistas quienes en su pensum o formación académica hayan adquirido los conocimientos del manejo e interpretación del espectro electromagnético, del ultrasonido especialmente, así como de las radiaciones ionizantes para establecer el diagnóstico y/o el tratamiento de las enfermedades inherentes a sus especialidades. Para lo cual deberá acreditar el respectivo certificado.
A170: IDX_INF | B170: Complejidad mediana
A171: IDX_INF | B171: Modalidades intramural, extramural unidad móvil, telemedicina - prestador remisor
A172: IDX_INF | B172: 4. Cumple con los criterios que le sean aplicables de todos los servicios y adicionalmente, cuenta con:
A173: IDX_INF | B173: 4.1 Ambiente exclusivo para el equipo generador de radiación no ionizante. La dimensión de este ambiente debe ser acorde al tipo de equipo generador de radiación no ionizante, su ficha técnica y a los procedimientos que se realicen, debe permitir movilización del talento humano, pacientes, usuarios y equipos biomédicos.
... A215: IDX_INT | B215: 17. No aplica
B218: CUMPLE | C218: =COUNTIF($C$5:$C$215,"C") -> 1
B219: NO CUMPLE | C219: =COUNTIF($C$5:$C$215,"NC") -> 1
B220: NO APLICA | C220: =COUNTIF($C$5:$C$215,"NA") -> 1

Sheet  11.3.5.S_MNuc
B1: VOLVER A TABLA DE CONTENIDO
A2: Grupo | B2: Apoyo diagnóstico y complementación terapeútica
A3: Descripción | B3: Servicio Medicina Nuclear: Servicio en el que se realizan procedimientos diagnósticos o terapeúticos mediante fuentes no selladas de radicación constituidas por isótopos radiactivos, radiofármacos o radionúclidos de uso en humanos.
A4: Complejidad | B4: Alta
A5: Modalidad | B5: Intramural
B6: Telemedicina: Telexperticia sincrónico, prestador remisor y prestador de referencia, entre dos profesionales.
A7: Estandar | B7: Criterios | C7: Estado | D7: Comentarios
A8: TH | B8: Modalidades intramural, telemedicina - prestador remisor
A9: TH | B9: 1. Cumple con los criterios que le sean aplicables de todos los servicios y adicionalmente cuenta con:
A10: TH | B10: 1.1 Profesional de la enfermería, cuando en el servicio se administren terapias con radionúclidos con actividad mayor a 30 mCi, que cuenta con constancia de asistencia en las acciones de formación continua en protección radiológica, radiofarmacia y radiofármacos. | C10: C
A11: TH | B11: 1.2 Tecnólogo en medicina nuclear o tecnólogo en manejo de fuentes no selladas de uso diagnóstico y terapéutico o tecnólogo en imágenes diagnósticas, que cuenta con constancia de asistencia en las acciones de formación continua en protección radiológica, radiofarmacia y radiofármacos. | C11: NC
A12: TH | B12: 1.3 Oficial de protección radiológica para toda la institución. | C12: NA
A13: TH | B13: 2. Disponibilidad de:
A14: TH | B14: 2.1 Profesional de la medicina especialista en medicina nuclear, con permanencia durante los procedimientos definidos por el prestador de servicios de salud en el estándar de procesos prioritarios.
A15: TH | B15: 2.2 Profesional con título de postgrado en física médica con permanencia durante los procedimientos definidos por el prestador de servicios de salud en el estándar de procesos prioritarios.
A16: TH | B16: Modalidad telemedicina - prestador de referencia
A17: TH | B17: 3. Cumple con los criterios que le sean aplicables de todos los servicios.
A18: TH | B18: 4. El profesional de la medicina especialista en medicina nuclear, cuando esté en disponibilidad y no se requiera su permanencia, puede hacer uso de la categoría telexperticia sincrónica entre profesionales de la salud, de acuerdo con lo definido por el prestador de servicios de salud en el estándar de procesos prioritarios.
A19: Infraestructura | B19: Modalidades intramural, telemedicina - prestador remisor
A20: Infraestructura | B20: 5. Cumple con los criterios que le sean aplicables de todos los servicios y adicionalmente cuenta con:
A21: Infraestructura | B21: 5.1 Ducha de seguridad
A22: Infraestructura | B22: 6. Disponibilidad de:
A23: Infraestructura | B23: 6.1 Sala de espera.
A24: Infraestructura | B24: 6.2 Unidades sanitarias discriminadas por sexo.
... A99: Interdependencia | B99: 24. No aplica
B102: CUMPLE | C102: =COUNTIF($C$5:$C$99,"C") -> 1
B103: NO CUMPLE | C103: =COUNTIF($C$5:$C$99,"NC") -> 1
B104: NO APLICA | C104: =COUNTIF($C$5:$C$99,"NA") -> 1

Sheet 11.3.6.S_Radio
B1: VOLVER A TABLA DE CONTENIDO
A2: Grupo | B2: Apoyo diagnóstico y complementación tereapeutica
A3: Descripción | B3: Servicio Radioterapia: Servicio en el que se lleva a cabo tratamiento médico que hace uso de radiación ionizante con et fin de erradicar un volumen tumoral benigno o maligno y en patologías no tumorales.
A4: Complejidad | B4: Alta
A5: Modalidades | B5: Intramural
B6: Telemedicina: Telexperticia sincrónico, prestador remisor y prestador de referencia, entre dos profesionales.
A7: Estandar | B7: Criterios | C7: Estado | D7: Comentarios
A8: Talento Humano | B8: Modalidades intramural, telemedicina - prestador remisor
A9: Talento Humano | B9: 1. Cumple con los criterios que le sean aplicables de todos los servicios y adicionalmente cuenta con: | C9: C
A10: Talento Humano | B10: 1.1. Tecnólogo en radioterapia. | C10: NC
A11: Talento Humano | B11: 1.2. Profesional con título de postgrado en física médica. | C11: NA
A12: Talento Humano | B12: 1.3. Oficial de protección radiológica para toda la institución.
A13: Talento Humano | B13: 2. Disponibilidad de:
A14: Talento Humano | B14: Profesional de la medicina especialista en radioterapia u oncología radioterápica, con permanencia durante los procedimientos definidos por el prestador de servicios de salud en el estándar de procesos prioritarios.
A15: Talento Humano | B15: Modalidad telemedicina - prestador de referencia
A16: Talento Humano | B16: 3. Cumple con los criterios que le sean aplicables de todos los servicios.
A17: Talento Humano | B17: 4. El profesional de la medicina especialista en radioterapia u oncología radioterápica, cuando esté en disponibilidad y no se requiera su permanencia, puede hacer uso de la categor!a telexperticia sincrónica entre profesionales de la salud, de acuerdo con lo definido por el prestador de servicios de salud en e1 estándar de procesos prioritarios.
A18: Infraestructura | B18: Modalidades intramural, telemedicina - prestador remisor
A19: Infraestructura | B19: 5. Cumple con los criterios que le sean aplicables de todos los servicios y adicionalmente cuenta con:
A20: Infraestructura | B20: 5.1. Ambiente de moldeo con disponibilidad de área para mesón de trabajo con poceta, cuando la tecnologia utilizada la requiera.
A21: Infraestructura | B21: 5.2. Ambiente para delimitación, planeación y dosimetría clinica de tratamientos, con ambiente o área para el almacenamiento de equipos de dosimetría.
A22: Infraestructura | B22: 5.3. Ambiente de tratamiento de teleterapia con unidades de mega voltaje (acelerador lineal). La dimensión de este ambiente debe ser acorde al tipo de equipo, su ficha técnica y a los procedimientos que se realicen, debe permitir movilización del talento humano, pacientes, usuarios y equipos biomédicos.
A23: Infraestructura | B23: Cuenta con:
... A115: Interdependencias | B115: 17. No aplica
B118: CUMPLE | C118: =COUNTIF($C$5:$C$115,"C") -> 1
B119: NO CUMPLE | C119: =COUNTIF($C$5:$C$115,"NC") -> 1
B120: NO APLICA | C120: =COUNTIF($C$5:$C$115,"NA") -> 1

Sheet 11.3.7.S_Quimio
B1: VOLVER A TABLA DE CONTENIDO
A2: Grupo | B2: Apoyo diagnóstico y complementación tereapeutica
A3: Descripción | B3: Servicio Quimioterapia: Servicio de administración de medicamentos oncológicos.
A4: Complejidad | B4: Alta
A5: Modaliadades | B5: Intramural
B6: Telemedicina - prestador remisor
A7: Estandar | B7: Criterios | C7: Estado | D7: Comentarios
A8: Talento Humano | B8: Modalidades intramural, telemedicina - prestador remisor
A9: Talento Humano | B9: 1. Cumple con los criterios que le sean aplicables de todos los servicios y adicionalmente cuenta con: | C9: C
A10: Talento Humano | B10: 1.1. Profesional de la enfermerfa especialista en oncologfa o profesional de la enfermerla con constancia de asistencia en las acciones de formación continua en el cuidado integral del paciente adulto o pediátrico con quimioterapia, segün oferta. | C10: NC
A11: Talento Humano | B11: 1.2. Auxiliares de enfermerra con constancia de asistencia en las acciones de formación continua en el cuidado integral del paciente adulto o pediátrico con quimioterapia, según oferta. | C11: NA
A12: Talento Humano | B12: 1.3. Qufmico (a) Farmacéutico (a) con constancia de asistencia en las acciones de formación continua en el cuidado integral del paciente adulto o pediátrico con quimioterapia, según oferta.
A13: Talento Humano | B13: 2. Disponibilidad de:
A14: Talento Humano | B14: Profesional de la medicina especialista en oncologla o especialista en hemato-oncologla o especialista en hematotogla, según el tipo de cáncer a tratar.
A15: Talento Humano | B15: 3. Si se ofrecen servicios de oncologra pediátrica, el talento humano en salud cuenta con constancia de asistencia en las acciones de formación continua del cuidado del paciente pediátrico con quimioterapia o con patología onco-hematológica a excepción del Profesional de la medicina especialista en pediatría.
A16: Talento Humano | B16: Modalidad telemedicina - prestador de referencia
A17: Talento Humano | B17: 4. Cumple con ros criterios que le sean aplicables de todos los servicios.
A18: Talento Humano | B18: 5. El profesional de la medicina especialista en oncología o especialista en hemato-oncologia o especialista en hematología, según el tipo de cáncer a tratar, puede realizar la disponibilidad en la categoría tetexperticia sincrónica entre profesionales de la salud de acuerdo con lo definido por el prestador de servicios de salud en el estándar de procesos prioritarios.
A19: Infraestructura | B19: Modalidades intramural, telemedicina - prestador remisor
A20: Infraestructura | B20: 6. Cumple con los criterios que le sean aplicables de todos los servicios y adicionalmente cuenta con:
A21: Infraestructura | B21: 6.1. Sala de espera.
A22: Infraestructura | B22: 6.2. Unidades sanitarias discriminadas por sexo.
A23: Infraestructura | B23: 6.3. Ambiente de quimioterapia que cuenta con área para casilleros.
... A107: Interdependencias | B107: 20. No aplica
B110: CUMPLE | C110: =COUNTIF($C$5:$C$107,"C") -> 1
B111: NO CUMPLE | C111: =COUNTIF($C$5:$C$107,"NC") -> 1
B112: NO APLICA | C112: =COUNTIF($C$5:$C$107,"NA") -> 1

Sheet 11.3.8 S_Dx VASC
B1: VOLVER A TABLA DE CONTENIDO
C2: 1 | F2: 2 | I2: 3 | L2: 4 | O2: 5 | R2: 6 | U2: 7
B3: Grupo apoyo diagnóstico y complementación tereapeutica
B4: 11.3.2 Servicio de Diagnóstico Vascular | C4: Servicio X1 | F4: Servicio X2 | I4: Servicio X3 | L4: Servicio X4 | O4: Servicio X5 | R4: Servicio X6 | U4: Servicio X7 | V4: Comentarios
B5: Complejidad mediana
A6: Estandar | B6: Criterios | C6: Estado | D6: Comentarios | F6: Estado | G6: Comentarios | I6: Estado | J6: Comentarios | L6: Estado | M6: Comentarios | O6: Estado | P6: Comentarios | R6: Estado | S6: Comentarios | U6: Estado
A7: DXVASC_TH | B7: Modalidades intramural, telemedicina, prestador remisor
A8: DXVASC_TH | B8: 1. Cumple con los criterios definidos para todos los servicios y adicionalmente cuenta con: | C8: C | F8: C | I8: C | L8: C | O8: C | R8: C | U8: C
A9: DXVASC_TH | B9: 1.1. Profesional de la medicina especialista en cardiología, o profesional de la medicina especialista en cirugía vascular, o profesional de la medicina especialista en medicina vascular o profesional de la medicina especialista en angiología clínica o profesional de la medicina especialista en radiología e imágenes diagnósticas. Este talento humano realiza procedimientos y su interpretación, en el ámbito de su competencia | C9: NC | F9: NC | I9: NC | L9: NC | O9: NC | R9: NC | U9: NC
A10: DXVASC_TH | B10: 1.2. Profesional de la enfermería que cuenta con constancia de asistencia en acciones de formación continua en soporte vital básico y para la realización del o los procedimientos ofertados. | C10: NA | F10: NA | I10: NA | L10: NA | O10: NA | R10: NA | U10: NA
A11: DXVASC_TH | B11: Modalidad de Telemedicina - prestador de referencia
A12: DXVASC_TH | B12: 2. Cumple con los criterios que le sean aplicables de todos los servicios.
A13: DXVASC_TH | B13: 3. El profesional de la medicina especialista en cardiología, o profesional de la medicina especialista en cirugía vascular, o profesional de la medicina especialista en medicina vascular o profesional de la medicina especialista en angiología clínica o profesional de la medicina especiallsta en radiología e imágenes diagnósticas puede hacer uso de la categoría telexperticia sincrónica o asincrónica entre profesionales de la salud de acuerdo con lo definido por el prestador de servicios de salud en el estándar de procesos prioritarios.
A14: DXVASC_INF | B14: Modalidades intramural, telemedicina - prestador remisor
A15: DXVASC_INF | B15: 4. Cumple con los criterios que le sean aplicables de todos los servicios y adicionalmente,
A16: DXVASC_INF | B16: 5. Cuenta con:
A17: DXVASC_INF | B17: 5.1. Lavamanos
A18: DXVASC_INF | B18: 5.2. Vestidor de pacientes con área para casilleros.
A19: DXVASC_INF | B19: 5.3. Sala de procedimientos.
A20: DXVASC_INF | B20: 6. Disponibilidad de:
A21: DXVASC_INF | B21: 6.1. Sala de espera.
A22: DXVASC_INF | B22: 6.2.Unidades sanitarias discriminadas por sexo.
... A53: DXVAC_INT | B53: 16. No aplica.
B56: CUMPLE | C56: =COUNTIF($C$5:$C$53,"C") -> 1 | F56: =COUNTIF($F$5:$F$53,"C") -> 1 | I56: =COUNTIF($I$5:$I$53,"C") -> 1 | L56: =COUNTIF($L$5:$L$53,"C") -> 1 | O56: =COUNTIF($O$5:$O$53,"C") -> 1 | R56: =COUNTIF($R$5:$R$53,"C") -> 1 | U56: =COUNTIF($U$5:$U$53,"C") -> 1
B57: NO CUMPLE | C57: =COUNTIF($C$5:$C$53,"NC") -> 1 | F57: =COUNTIF($F$5:$F$53,"NC") -> 1 | I57: =COUNTIF($I$5:$I$53,"NC") -> 1 | L57: =COUNTIF($L$5:$L$53,"NC") -> 1 | O57: =COUNTIF($O$5:$O$53,"NC") -> 1 | R57: =COUNTIF($R$5:$R$53,"NC") -> 1 | U57: =COUNTIF($U$5:$U$53,"NC") -> 1
B58: NO APLICA | C58: =COUNTIF($C$5:$C$53,"NA") -> 1 | F58: =COUNTIF($F$5:$F$53,"NA") -> 1 | I58: =COUNTIF($I$5:$I$53,"NA") -> 1 | L58: =COUNTIF($L$5:$L$53,"NA") -> 1 | O58: =COUNTIF($O$5:$O$53,"NA") -> 1 | R58: =COUNTIF($R$5:$R$53,"NA") -> 1 | U58: =COUNTIF($U$5:$U$53,"NA") -> 1

Sheet 11.3.9S_HI
B1: VOLVER A TABLA DE CONTENIDO
B2: Grupo apoyo diagnóstico y complementación tereapeutica
B3: 11.3.9Servicio de Hemodinamia e Intervencionismo
A4: Estandar | B4: Criterios | C4: Estado | D4: Comentarios
A5: HI_TH | B5: Complejidad alta
A6: HI_TH | B6: Modalidades intramural, tefemedicina - prestador remisor
A7: HI_TH | B7: 1.Cumple con los criterios que le sean aplicables de todos los servicios y adicionalmente cuenta con: | C7: C
A8: HI_TH | B8: 1.1. Profesional de la medicina especialista en cardiología intervencionista y hemodinámia o profesional de la medicina especialista en electrofisiología o profesional de la medicina especialista en cirugía vascular o profesional de la medicina especialista en radiología intervencionista. | C8: NC
A9: HI_TH | B9: 1.2. Profesional de la enfermería que cuenta con constancia de asistencia en las acciones de formación continua en la realización del procedimiento ofertado y en soporte vital avanzado. | C9: NA
A10: HI_TH | B10: 1.3. Tecnólogo en radiología e imágenes diagnósticas.
A11: HI_TH | B11: 2. Disponibilidad de profesional de la medicina especialista en anestesiología.
A12: HI_TH | B12: Modalidad telemedicina - prestador de referencia
A13: HI_TH | B13: 3. Cumple con los criterios que le sean aplicables de todos los servicios.
A14: HI_TH | B14: 4. El profesional de la medicina especialista en cardiología intervencionista y hemodinámia o profesional de la medicina especialista en electrofisiología o profesional de la medicina especialista en cirugía vascular o profesional de la medicina especialista en radiología intervencionista, puede hacer uso de la categoría telexperticia sincrónica o asincrónica entre profesionales de la salud de acuerdo con lo definido por el prestador de servicios de salud en el estándar de procesos prioritarios
A15: HI_INF | B15: Modalidades intramural, telemedicina - prestador remisor
A16: HI_INF | B16: 5. Cumple con los criterios que le sean aplicables de todos los servicios y adicionalmente cuenta con:
A17: HI_INF | B17: 5.1. Área para recepción y entrega de pacientes.
A18: HI_INF | B18: 5.2. Área para almacenamiento de material estéril.
A19: HI_INF | B19: 5.3. Vestidor de personal que funciona como filtro
A20: HI_INF | B20: 5.4. Vestidor de pacientes y área para casilleros.
A21: HI_INF | B21: 5.5. Unidad sanitaria.
... A116: HCA_INT | B116: 20. No aplica.
B119: CUMPLE | C119: =COUNTIF($C$5:$C116,"C") -> 1
B120: NO CUMPLE | C120: =COUNTIF($C$5:$C$116,"NC") -> 1
B121: NO APLICA | C121: =COUNTIF($C$5:$C$116,"NA") -> 1

Sheet 11.3.10 S_GPT
B1: VOLVER A TABLA DE CONTENIDO
B2: Grupo apoyo diagnóstico y complementación tereapeutica
B3: Servicio de Gestión Pre-Trasfusional
A4: Estandar | B4: Criterios | C4: Estado | D4: Comentarios
A5: GPT_TH | B5: 1. Cumple con los criterios que le sean aplicables de todos los servicios y adicionalmente, cuando el servicio de gestión pre- transfusional sea interdependiente de: | C5: C
A6: GPT_TH | B6: Servicios de salud de alta complejidad:
A7: GPT_TH | B7: 1.1 Cuenta con profesional de bacteriología. | C7: NC
A8: GPT_TH | B8: Servicios de salud de baja y mediana complejidad:
A9: GPT_TH | B9: 1.2. Disponibilidad de profesional de bacteriología. | C9: NA
A10: GPT_TH | B10: 2. El profesional de bacteriología cuenta con constancia de asistencia en las acciones de formación continua en el manejo de la gestión pre transfusional.
A11: GPT_INF | B11: 3. Cumple con los criterios que le sean aplicables de todos los servicios y adicionalmente.
A12: GPT_INF | B12: 4. Cuenta con:
A13: GPT_INF | B13: 4.1 Área para recepción, información y entrega de componentes sanguíneos.
A14: GPT_INF | B14: 4.2.1. Lavamanos.
A15: GPT_INF | B15: 4.2.2. Mesón de trabajo.
A16: GPT_INF | B16: 4.2.3. Poceta, cuando la requiera, según los procedimientos que documente en el estándar de procesos prioritarios.
A17: GPT_INF | B17: 4.2.4. Área para refrigeración y congelación.
A18: GPT_DOT | B18: 5. Cumple con los criterios que le sean aplicables de todos los servicios y adicionalmente cuenta con
A19: GPT_DOT | B19: 5.1. Nevera o depósito frío para el almacenamiento de sangre o sus componentes con sistema de control de temperatura entre 1ºC y 6ºC y alarma audible o sistema de monitoreo que alerte cambios próximos al limite en que la sangre o sus componentes puedan deteriorarse.
A20: GPT_DOT | B20: 5.2. Equipo para descongelar plasma cuando se requiera, con sistema de control de temperatura
A21: GPT_DOT | B21: 5.3. Congelador para la conservación de plasma o crioprecipitados, cuando se requiera, éste cuenta con sistema de control de temperatura por debajo de -18ºC y alarma audible o sistema de monitoreo que alerte cambios próximos al límite en que el componente almacenado pueda deteriorarse
... A47: GPT_INT | B47: 9. No aplica.
B50: CUMPLE | C50: =COUNTIF($C$4:$C$47,"C") -> 1
B51: NO CUMPLE | C51: =COUNTIF($C$4:$C$47,"NC") -> 1
B52: NO APLICA | C52: =COUNTIF($C$4:$C$47,"NA") -> 1

Sheet 11.3.11.S_TMLC
B1: VOLVER A TABLA DE CONTENIDO
B2: Grupo apoyo diagnóstico y complementación tereapeutica
B3: Servicio de Toma de Muestras de Laboratorio Clinico
A4: Estandar | B4: Criterios | C4: Estado | D4: Comentarios
A5: TMLC_TH | B5: Modalidades intramural, extramural unidad móvil, jornada de salud y domiciliaria
A6: TMLC_TH | B6: 1. Cumple con los criterios que le sean aplicables de todos los servicios y adicionalmente cuenta con: | C6: C
A7: TMLC_TH | B7: Profesional de bacteriología o auxiliar de laboratorio clínico o auxiliar de enfermería. | C7: NC
A8: TMLC_TH | B8: 2. Disponibilidad de:
A9: TMLC_TH | B9: Profesional de bacteriología quien realiza la supervisión cuando la toma de muestras es realizada por el auxiliar. | C9: NA
A10: TMLC_INF | B10: Modalidad intramural
A11: TMLC_INF | B11: Modalidad intramural
A12: TMLC_INF | B12: 3. Cumple con los criterios que le sean aplicables de todos los servicios y adicionalmente,
A13: TMLC_INF | B13: 4. Cuenta con:
A14: TMLC_INF | B14: 4.1. Área para recepción de muestras, información y entrega de resultados.
A15: TMLC_INF | B15: 4.2. Cubículo para la toma de muestras.
A16: TMLC_INF | B16: 4.3. Ambiente para la toma de muestras especiales cuando lo oferte, cuenta con unidad sanitaria y perchero (si el procedimiento lo indica).
A17: TMLC_INF | B17: 4.4. Lavamanos.
A18: TMLC_INF | B18: 4.5. Área de preparación, embalaje y remisión de las muestras que cuenta con:
A19: TMLC_INF | B19: 4.5.1. Mesón de trabajo, con poceta cuando ésta se requiera.
A20: TMLC_INF | B20: 5. Disponibilidad de:
A21: TMLC_INF | B21: 5.1. Sala de espera.
... A45: TM_INT | B45: Servicio de laboratorio clínico.
B48: CUMPLE | C48: =COUNTIF($C$4:$C$45,"C") -> 1
B49: NO CUMPLE | C49: =COUNTIF($C$4:$C$45,"NC") -> 1
B50: NO APLICA | C50: =COUNTIF($C$4:$C$45,"NA") -> 1

Sheet 11.3.12.S_LC
B1: VOLVER A TABLA DE CONTENIDO
B2: Grupo apoyo diagnóstico y complementación tereapeutica
B3: Servicio de Laboratorio Clinico
A4: Estandar | B4: Criterios | C4: Estado | D4: Comentarios
A5: LC_TH | B5: Modalidades intramural, extramural unidad móvil, jornada de salud y telemedicina - prestador remisor.
A6: LC_TH | B6: 1. Cumple con los criterios definidos para todos los servicios y adicionalmente, | C6: C
A7: LC_TH | B7: 1.1. Cuenta con:
A8: LC_TH | B8: 1.1.1. Bacteriólogo (a). | C8: NC
A9: LC_TH | B9: 1.1.2. Talento humano profesional que cuenta con constancia de asistencia en las acciones de formación continua en las actividades relacionadas con el laboratorio clínico, cuando se requiera. | C9: NA
A10: LC_TH | B10: 1.1.3. Auxiliar(es) de laboratorio clínico o de enfermería, cuando se requiera.
A11: LC_TH | B11: 1.1.4. Talento humano que cuenta con constancia de asistencia en las acciones de formación continua para el desarrollo de los programas para diagnóstico y control de enfermedades transmitidas por vectores, cuando se requiera.
A12: LC_TH | B12: 2. Disponibilidad de bacteriólogo en zonas dispersas con permanencia de acuerdo con lo definido por el prestador de servicios de salud en el estándar de procesos prioritarios.
A13: LC_TH | B13: 3. Cuando se realicen pruebas de inmunología para trasplantes, el profesional de bacteriología cuenta con constancia de asistencia en las acciones de formación continua en la realización de dichas pruebas.
A14: LC_TH | B14: 4. Cuando se realicen controles de calidad a las “pruebas en el punto de atención del paciente - (Point of Care Testing - POCT)” a otros servicios de salud que hacen uso de estas pruebas, el/la bacteriólogo (a) cuenta con constancia de asistencia en las acciones de formación continua en el manejo de las mismas.
A15: LC_TH | B15: Modalidad telemedicina - prestador de referencia
A16: LC_TH | B16: 5. Cumple con los criterios que le sean aplicables de todos los servicios.
A17: LC_TH | B17: 6. El Profesional de bacteriología, puede hacer uso de la categoría telexperticia sincrónica o asincrónica entre profesionales de la salud de acuerdo con lo definido por el prestador de servicios de salud en el estándar de procesos prioritarios.
A18: LC_INF | B18: Modalidades intramural, telemedicina - prestador remisor
A19: LC_INF | B19: 7. Cumple con los criterios definidos para todos los servicios.
A20: LC_INF | B20: 8. Cuenta con:
A21: LC_INF | B21: 8.1. Área para recepción de muestras, información y entrega de resultados.
... A78: LC_INT | B78: 20. No aplica.
B81: CUMPLE | C81: =COUNTIF($C$4:$C$78,"C") -> 1
B82: NO CUMPLE | C82: =COUNTIF($C$4:$C$78,"NC") -> 1
B83: NO APLICA | C83: =COUNTIF($C$4:$C$78,"NA") -> 1

Sheet  11.3.13 S_TM_CU
B1: VOLVER A TABLA DE CONTENIDO
B2: Grupo apoyo diagnóstico y complementación tereapeutica
B3: Servicio de Toma de Muestras de Cuello Uterino y Ginecológicas
A4: Estandar | B4: Criterios | C4: Estado | D4: Comentarios
A5: TM_CU_TH | B5: Modalidades intramural, extramural unidad móvil. Jornada de salud y domiciliaria
A6: TM_CU_TH | B6: 1. Cumple con los criterios que le sean aplicables de todos los servicios y adicionalmente cuenta con: | C6: C
A7: TM_CU_TH | B7: 1.1. Profesional de la medicina o profesional de la enfermería o profesional de bacteriología o citohistotecnólogo (a) o histocitotecnólogo (a) | C7: C
A8: TM_CU_TH | B8: 1.2. El personal que realice toma de citologías cuenta con constancia de asistencia en las acciones de formación continua en esta actividad. | C8: NA
A9: TM_CU_TH | B9: 1.3. La técnica VIA VILI solo podrá ser realizada por profesional de la medicina o profesional en enfermería
A10: TM_CU_TH | B10: En zonas especiales de dispersión geográfica:
A11: TM_CU_TH | B11: 2. Cuenta con:
A12: TM_CU_TH | B12: 2.1. Auxiliar de enfermería o profesional de la medicina o profesional de la enfermería o profesional de bacteriología o citohistotecnólogo (a) o histocitotecnólogo (a).
A13: TM_CU_TH | B13: 2.2. El personal que realice toma de citologías cuenta con constancia de asistencia en las acciones de formación continua para esta actividad.
A14: TM_CU_INF | B14: Modalidad intramural
A15: TM_CU_INF | B15: 3. Cumple con los criterios que le sean aplicables de todos los servicios y adicionalmente cuenta con:
A16: TM_CU_INF | B16: 3.1. Ambiente para la toma de muestras especiales, con unidad sanitaria y perchero.
A17: TM_CU_INF | B17: Disponibilidad de:
A18: TM_CU_INF | B18: 3.2. Área de información y entrega de resultados.
A19: TM_CU_INF | B19: 3.3. Área o ambiente de preparación, embalaje y remisión de las muestras con mesón de trabajo.
A20: TM_CU_INF | B20: 3.4. Área o ambiente para el almacenamiento de materiales, insumos y reactivos.
... A57: TM_CU_INT | B57: 10. Cumple con los criterios que le sean aplicables de todos los servicios y adicionalmente disponibilidad de laboratorio de citología cervico-uterinas o servicio de patología.
B60: CUMPLE | C60: =COUNTIF($C$4:$C$57,"C") -> 2
B61: NO CUMPLE | C61: =COUNTIF($C$4:$C$57,"NC") -> 0
B62: NO APLICA | C62: =COUNTIF($C$4:$C$57,"NA") -> 1

Sheet 11.3.14.S_LCU
B1: VOLVER A TABLA DE CONTENIDO
B2: Grupo apoyo diagnóstico y complementación tereapeutica
B3: Servicio de Laboratorio de Citologías Cervico-Uterinas
A4: Estandar | B4: Criterios | C4: Estado | D4: Comentarios
A5: LCU_TH | B5: Estándar de talento humano
A6: LCU_TH | B6: Modalidad intramuraf, telemedicina prestador remisor
A7: LCU_TH | B7: 1. Cumple con los criterios definidos para todos los servicios y adicionalmente, cuenta con: | C7: C
A8: LCU_TH | B8: 1.1. Citotecnólogo o citohistotecnólogo o citólogo o histocitotecnólogo. | C8: NC
A9: LCU_TH | B9: 1. Disponibilidad de profesional de ta medicina especialista en patología. | C9: NA
A10: LCU_TH | B10: Modalidad telemedicina - prestador de referencia
A11: LCU_TH | B11: 3. Cumple con los criterios definidos para todos los servicios.
A12: LCU_TH | B12: 4. El Profesional de la medicina especialista en patología, puede realizar la disponibilidad en la categoría telexperticia sincrónica o asincrónica, entre profesionales de !a salud de acuerdo con lo definido por el prestador de servicios de salud en el estándar de procesos prioritarios.
A13: LCU_INF | B13: Modalidades intramuraf, tefemedicína -prestador remisor
A14: LCU_INF | B14: 5. Cumple con los criterios que le sean aplicables de todos los servicios y adicionalmente,
A15: LCU_INF | B15: 6. Cuenta con:
A16: LCU_INF | B16: 6.1. Area para recepción de muestras, información y entrega de resultados, con superticie de trabajo
A17: LCU_INF | B17: 6.2. Ambiente técnico de procedimientos que cuenta con:
A18: LCU_INF | B18: 6.2.1. Mesón de trabajo.
A19: LCU_INF | B19: 6.2.2. Poceta, cuando la requiera, según los procedimientos que documente.
A20: LCU_INF | B20: 6.2.3.Lavamanos.
A21: LCU_INF | B21: Modalidad de telemedicina - prestador de referencia
... A52: LCU_INT | B52: 16. No aplica.
B55: CUMPLE | C55: =COUNTIF($C$4:$C$52,"C") -> 1
B56: NO CUMPLE | C56: =COUNTIF($C$4:$C$52,"NC") -> 1
B57: NO APLICA | C57: =COUNTIF($C$4:$C$52,"NA") -> 1

Sheet 11.3.15.S_LHT
B1: VOLVER A TABLA DE CONTENIDO
B2: Grupo apoyo diagnóstico y complementación tereapeutica
B3: Servicio de Laboratorio de Histotecnología
A4: Estandar | B4: Criterios | C4: Estado | D4: Comentarios
A5: LHT_TH | B5: 1. Cumple con los criterios que le sean aplicables de todos tos servicios y adicionalmente cuenta con: | C5: C
A6: LHT_TH | B6: 1.1. Citotecnólogo o citohistotecnólogo o histocitotecnólogo o citólogo. | C6: NC
A8: LHT_INF | B8: 2. Cumple con los criterios que le sean aplicables de todos los servicios y adicionalmente cuenta con | C8: NA
A9: LHT_INF | B9: 2.1. Area para recepción de muestras
A10: LHT_INF | B10: 2.2. Ambiente técnico de procedimientos que cuenta con:
A11: LHT_INF | B11: 2.2.1.Ducha manual o lavaojos.
A12: LHT_INF | B12: 2.2.2.Lavamanos.
A13: LHT_INF | B13: 2.2.3. Mesón de trabajo
A14: LHT_INF | B14: 2.2.4. Poceta, cuando la requiera, según los procedimientos documentados por el prestador de servicios de salud en el estándar de procesos prioritarios.
A15: LHT_INF | B15: 2.3. Ambiente donde se realicen las coloraciones que cuenta con extractor de sustancias quimicas.
A16: LHT_INF | B16: 2.4. Área o ambiente para el almacenamiento de materiales, insumos y reactivos.
A18: LHT_DOT | B18: 3. Cumple con los criterios que le sean aplicables de todos tos servicios y adicionalmente cuenta con:
A19: LHT_DOT | B19: 3.1. Microscopio.
A20: LHT_DOT | B20: 3.2. Procesador de tejidos.
A21: LHT_DOT | B21: 3.3. Dispensador de parafina o estación de inclusión
... A43: LHT_INT | B43: 7. No aplica.
B46: CUMPLE | C46: =COUNTIF($C$4:$C$43,"C") -> 1
B47: NO CUMPLE | C47: =COUNTIF($C$4:$C$43,"NC") -> 1
B48: NO APLICA | C48: =COUNTIF($C$4:$C$43,"NA") -> 1

Sheet 11.3.16.S_LPT
B1: VOLVER A TABLA DE CONTENIDO
B2: Grupo apoyo diagnóstico y complementación tereapeutica
B3: Servicio Laboratorio de Patologia
A4: Estandar | B4: Criterios | C4: Estado | D4: Comentarios
A5: LPT_TH | B5: 1. Cumple con los criterios definidos para todos los servicios y adicionalmente cuenta con:
A6: LPT_TH | B6: 1.1. profesional de la medicina especialista en patología. | C6: C
A7: LPT_TH | B7: 2.Disponibilidad de Histotecnólogo o citohistotecnólogo o Histocitotecnólogo o Citotecnólogo o Citólogo. | C7: NC
A8: LPT_TH | B8: Modalidad telemedicina - prestador de referencia
A9: LPT_TH | B9: 3. Cumple con los criterios que le sean aplicables de todos los servicios. | C9: NA
A10: LPT_TH | B10: 4. El Profesional de la medicina especialista en patología puede hacer uso de la categoría telexperticia sincrónica o asincrónica entre profesionales de la salud de acuerdo con lo definido por el prestador de servicios de salud en el estándar de procesos prioritarios.
A11: LPT_INF | B11: Modalidades intramural y telemedicina - prestador remisor
A12: LPT_INF | B12: 5. Cumple con los criterios definidos para todos los servicios y adicionalmente cuenta con:
A13: LPT_INF | B13: 5.1.Área para recepción de muestras, información y entrega de resultados..
A14: LPT_INF | B14: 5.2. Ambiente técnico de procedimientos que cuenta con:
A15: LPT_INF | B15: 5.2.1.Area de histotecnologla, cuando se realice
A16: LPT_INF | B16: 5.2.2.Area de microscopia.
A17: LPT_INF | B17: 5.2.3. Ambiente donde se realicen las coloraciones que cuenta con extractor de sustancias químicas, cuando lo requiera
A18: LPT_INF | B18: 5.2.4. Mesón de trabajo
A19: LPT_INF | B19: 5.2.5. Poceta, cuando la requiera, según los procedimientos que documente en el estándar de procesos prioritarios.
A20: LPT_INF | B20: 5.2.6. Ducha manual o lavaojos (Puede ser la misma del ambiente de macroscopia)
A21: LPT_INF | B21: 5.2.7.Lavamanos
... A72: LPT_INT | B72: 16. No aplica.
B75: CUMPLE | C75: =COUNTIF($C$4:$C$72,"C") -> 1
B76: NO CUMPLE | C76: =COUNTIF($C$4:$C$72,"NC") -> 1
B77: NO APLICA | C77: =COUNTIF($C$4:$C$72,"NA") -> 1

Sheet 11.3.17.S_Dial
B1: VOLVER A TABLA DE CONTENIDO
B2: Grupo apoyo diagnóstico y complementación tereapeutica
B3: Servicio de Dialisis
A4: Estandar | B4: Criterios | C4: Estado | D4: Comentarios
A5: D_TH | B5: Modalidad lntramural - prestador remisor.
A6: D_TH | B6: 1. Cumple con los criterios que le sean aplicables de todos los servicios y adicionalmente cuenta con: | C6: C
A7: D_TH | B7: 1 1 Profesional de la medicina, que cuenta con constancia de asistencia en las acciones de formación continua en el control de las complicaciones más frecuentes en el servicio y soporte vital avanzado. | C7: NC
A8: D_TH | B8: 1.2. Profesional de la enfermeria que cuenta con constancia de asistencia en las acciones de fonnación continua en la atención del paciente en diálisis renal. | C8: NA
A9: D_TH | B9: 1.3. Auxiliar de enfermería que cuenta con constancja de asistencia en las acciones de formación continua en la atención del paciente en diálisis renal.
A10: D_TH | B10: 2. Disponibilidad de:
A11: D_TH | B11: 2.1. Profesional de la medicina especialista en nefrologla con permanencia durante los procedimienlos definidos por er prestador de servicios de salud en el estandar de procesos prioritarios.
A12: D_TH | B12: 2.2. Profesional de la psicologla.
A13: D_TH | B13: 2.3. Profesional de nutrición y dietética
A14: D_TH | B14: 2.4. Profesional de trabajo social.
A15: D_TH | B15: Modalidad extramural jornada de salud
A16: D_TH | B16: 3. Cuenta con prescripción previa del nefrólogo y permanencia del profesional de la enfermería en la conexión, monitorización y desconexión del paciente.
A17: D_TH | B17: Modalidad telemedicina - prestador de referencia
A18: D_TH | B18: 4. Cumple con los criterios que le sean aplicables de todos los servicios.
A19: D_TH | B19: 5. Profesional de la medicina especialista en nefrología, cuando esté en disponibilidad y no se requiera su permanencia, puede hacer uso de la categoría telexperticia sincrónica, entre profesionales de la salud de acuerdo con lo definido por el prestador de servicios de salud en el estándar de procesos prioritarios.
A20: D_ INF | B20: Modalidades intramural. tefemedicina - prestador remisor
... A124: D_INT | B124: 29. No aplica.
B127: CUMPLE | C127: =COUNTIF($C$4:$C$124,"C") -> 1
B128: NO CUMPLE | C128: =COUNTIF($C$4:$C$124,"NC") -> 1
B129: NO APLICA | C129: =COUNTIF($C$4:$C$124,"NA") -> 1

Sheet 11.4.1.S_HP
B1: VOLVER A TABLA DE CONTENIDO
B2: Grupo Internación
B3: Servicio Hospitalización
A4: Estandar | B4: Criterios | C4: Estado | D4: Comentarios
A5: HP_TH | B5: COMPLEJIDAD BAJA
A6: HP_TH | B6: Modalidad intramural y extramural domiciliaria
A7: HP_TH | B7: 1. Cumple con los criterios definidos para todos los servicios y adicionalmente, disponibilidad de: | C7: C
A8: HP_TH | B8: 1 1. Profesional de la medicina | C8: NC
A9: HP_TH | B9: 1.2. Profesional de la enfermeria. | C9: NA
A10: HP_TH | B10: 1.3. Auxiliar de enfermería
A11: HP_TH | B11: Modalidad telemedicina
A12: HP_TH | B12: Categoría telexperticia – prestador remisor
A13: HP_TH | B13: 2. Cumple con los criterios que le sean aplicables de todos los servicios y adicionalmente
A14: HP_TH | B14: 2.1. Cuando se realice telexperticia entre profesionales de la salud cumple con los criterios establecidos en la modalidad intramural del servicio de hospitalización de baja complejidad.
A15: HP_TH | B15: 2.2. Cuando realice telexperticia entre personal de salud no profesional y un profesional de la salud, en la modalidad domiciliaria, el prestador remisor cuenta con auxiliar de enfermería que atiende presencialmente al usuario.
A16: HP_TH | B16: Categoría telexperticia – prestador de referencia
A17: HP_TH | B17: 3. Cumple con los criterios que le sean aplicables de todos los servicios, y adicionalmente cuenta con profesional de la salud, de acuerdo con lo definido por el prestador de servicios de salud en el estándar de procesos prioritarios.
A18: HP_TH | B18: Categoría telemonitoreo – prestador remisor en modalidad extramural domiciliaria
A19: HP_TH | B19: 4. Cumple con los criterios que le sean aplicables de todos los servicios.
A20: HP_TH | B20: 5. La permanencia del talento humano en salud en el domicilio del paciente será determinada según la condición clínica del paciente y la información documentada en el estándar de procesos prioritarios.
A21: HP_TH | B21: Categoría telemonitoreo – prestador remisor en modalidad extramural domiciliaria
... A263: HP_INT | B263: 57. No aplica.
B266: CUMPLE | C266: =COUNTIF($C$4:$C$263,"C") -> 1
B267: NO CUMPLE | C267: =COUNTIF($C$4:$C$263,"NC") -> 1
B268: NO APLICA | C268: =COUNTIF($C$4:$C$263,"NA") -> 1

Sheet 11.4.2.S_HP_PC
B1: VOLVER A TABLA DE CONTENIDO
B2: Grupo Internación
B3: Servicio Hospitalización - Paciente Cronico
A4: Estandar | B4: Criterios | C4: Estado | D4: Comentarios
A5: SHPPC_TH | B5: Complejidad baja
A6: SHPPC_TH | B6: Hospitalización del paciente crónico sin ventilador
A7: SHPPC_TH | B7: Modalidades intramural y extramural domiciliaria
A8: SHPPC_TH | B8: 1. Cumple con los criterios que le sean aplicables de todos los servicios y adicionalmente cuenta con: | C8: C
A9: SHPPC_TH | B9: 1.1. Profesional de la enfermería | C9: NC
A10: SHPPC_TH | B10: 1.2. Auxiliar de enfermería. | C10: NA
A11: SHPPC_TH | B11: 2. La permanencia del profesional de la enfermería y la auxiliar de enfermería en el domicilio del paciente será determinada según la condición clínica del paciente y la información documentada en el estándar de procesos prioritarios.
A12: SHPPC_TH | B12: 3. Disponibilidad de:
A13: SHPPC_TH | B13: 3.1. Profesional de la medicina con permanencia durante los procedimientos definidos por el prestador de servicios de salud en el estándar de procesos prioritarios.
A14: SHPPC_TH | B14: 3.2. Profesional de nutrición y dietética.
A15: SHPPC_TH | B15: 3.3. Profesional de la psicología.
A16: SHPPC_TH | B16: 3.4. Profesionales de terapia de acuerdo con el plan de tratamiento.
A17: SHPPC_TH | B17: Modalidad telemedicina
A18: SHPPC_TH | B18: Categoría telexperticia – prestador remisor
A19: SHPPC_TH | B19: 4. Cumple con los criterios que le sean aplicables de todos los servicios y adicionalmente:
A20: SHPPC_TH | B20: 4.1. Cuando se realice telexperticia entre profesionales de la salud cumple con los criterios establecidos en la modalidad intramural del servicio de hospitalización del paciente crónico sin ventilador baja complejidad.
A21: SHPPC_TH | B21: 4.2. Cuando realice telexperticia entre personal de salud no profesional y un profesional de la salud, en la modalidad domiciliaria, el prestador remisor cuenta con auxiliar de enfermería que atiende presencialmente al usuario.
A22: SHPPC_TH | B22: Categoría telexperticia - prestador de referencia
... A244: SHPPC_INT | B244: 54. No aplica.
B247: CUMPLE | C247: =COUNTIF($C$4:$C$244,"C") -> 1
B248: NO CUMPLE | C248: =COUNTIF($C$4:$C$244,"NC") -> 1
B249: NO APLICA | C249: =COUNTIF($C$4:$C$244,"NA") -> 1

Sheet 11.4.3.S_CBN
B1: VOLVER A TABLA DE CONTENIDO
B2: Grupo Internación
B3: Servicio Cuidado Básico Neonatal
B4: Complejidad: Baja
B5: Modalidad de prestación: Intramural Telemedicina - categorías: Telexperticia sincrónica o asincrónica - prestador remisor y prestador de referencia Entre dos profesionales
A6: Estandar | B6: Criterios | C6: Estado | D6: Comentarios
A7: CBN-TH | B7: Modalidad intramural y telemedicina - prestador remisor
A8: CBN-TH | B8: 1. Cumple con los criterios que le sean aplicables de todos los servicios y adicionalmente, | C8: C
A9: CBN-TH | B9: 1.1 cuenta con auxiliar de enfermería. | C9: NC
A10: CBN-TH | B10: 2. Disponibilidad de:
A11: CBN-TH | B11: 2.1. Profesional de la medicina con constancia de acciones de formación continua en atención del paciente neonatal. | C11: NA
A12: CBN-TH | B12: 2.2. Profesional de la enfermería con constancia de acciones de formación continua en atención del paciente neonatal.
A13: CBN-TH | B13: Modalidad telemedicina - prestador de referencia
A14: CBN-TH | B14: 3. Cumple con los criterios que le sean aplicables de todos los servicios.
A15: CBN-TH | B15: 4. El profesional de la salud puede hacer uso de la telexperticia sincrónica o asincrónica entre profesionales de la salud, de acuerdo con lo definido por el prestador de servicios de salud en el estándar de procesos prioritarios.
A16: CBN_INF | B16: Modalidades intramural, telemedicina - prestador remisor
A17: CBN_INF | B17: 5. Cumple con los criterios que le sean aplicables de todos los servicios y adicionalmente cuenta con:
A18: CBN_INF | B18: 5.1. Ambiente a manera de filtro, para acceso del talento humano en salud y visitantes, con lavamanos y área de casilleros.
A19: CBN_INF | B19: 5.2. Estación de enfermería.
A20: CBN_INF | B20: 5.3. Ambiente o área para brindar información a familiares.
A21: CBN_INF | B21: 5.4. Área de incubadoras o cunas (4 m2 ), señalizado y de circulación restringida solo para personal autorizado
A22: CBN_INF | B22: 6. Disponibilidad en el servicio de lavamanos.
A23: CBN_INF | B23: 7. Los anteriores ambientes o áreas pueden ser compartidos entre los servicios de cuidado básico, intermedio e intensivo neonatal.
... A88: CBN_INT | B88: 19. No aplica.
B91: CUMPLE | C91: =COUNTIF($C$4:$C$88,"C") -> 1
B92: NO CUMPLE | C92: =COUNTIF($C$4:$C$88,"NC") -> 1
B93: NO APLICA | C93: =COUNTIF($C$4:$C$88,"NA") -> 1

Sheet 11.4.4.S_CIN 
B1: VOLVER A TABLA DE CONTENIDO
B2: Grupo Internación
B3: Servicio Cuidado Intermedio Neonatal
B4: Complejidad: Mediana
B5: Modalidad de prestación: Intramural Telemedicina – categorías: Telexperticia sincrónica prestador remisor y prestador referencia Entre dos profesionales
A6: Estandar | B6: Criterios | C6: Estado | D6: Comentarios
A7: CIN_TH | B7: Modalidades intramural, telemedicina - prestador remisor
A8: CIN_TH | B8: 1. Cumple con los criterios definidos para todos los servicios y adicionalmente cuenta con: | C8: C
A9: CIN_TH | B9: 1.1. Profesional de la medicina especialista en pediatría. | C9: NC
A10: CIN_TH | B10: 1.2. Profesional de la enfermería. | C10: NA
A11: CIN_TH | B11: 1.3. Auxiliar de enfermería.
A12: CIN_TH | B12: 2. Disponibilidad de:
A13: CIN_TH | B13: 2.1. Profesional de la medicina especialista en neonatología.
A14: CIN_TH | B14: 2.2. Profesional de terapia respiratoria o fisioterapia.
A15: CIN_TH | B15: 2.3. Profesional de nutrición y dietética.
A16: CIN_TH | B16: 3. Todo el personal mencionado cuenta con constancia de asistencia en las acciones de formación continua para la atención del neonato, a excepción del médico especialista en neonatología.
A17: CIN_TH | B17: Modalidad telemedicina - prestador de referencia
A18: CIN_TH | B18: 4. Cumple con los criterios que le sean aplicables de todos los servicios.
A19: CIN_TH | B19: 5. El profesional de salud puede hacer uso de la categoría telexperticia sincrónica entre profesionales de la salud de acuerdo con lo definido por el prestador de servicios de salud en el estándar de procesos prioritarios.
A20: CIN_TH | B20: 6. Profesional de la medicina especialista en neonatología, puede realizar la disponibilidad en la categoría telexperticia sincrónica entre profesionales de la salud de acuerdo con lo definido por el prestador de servicios de salud en el estándar de procesos prioritarios.
A21: CIN_INF | B21: Modalidades intramural y telemedicina - prestador remisor
A22: CIN_INF | B22: 7. Cumple con los criterios que le sean aplicables de todos los servicios y adicionalmente cuenta con:
... A110: CIN_INT | B110: 21. No aplica.
B113: CUMPLE | C113: =COUNTIF($C$4:$C$110,"C") -> 1
B114: NO CUMPLE | C114: =COUNTIF($C$4:$C$110,"NC") -> 1
B115: NO APLICA | C115: =COUNTIF($C$4:$C$110,"NA") -> 1

Sheet 11.4.5.S_CINN
B1: VOLVER A TABLA DE CONTENIDO
B2: Grupo Internación
B3: Servicio Cuidado Intensivo Neonatal
B4: Complejidad: Alta
B5: Modalidad de prestación: Intramural Telemedicina – categorías: Telexperticia sincrónica prestador remisor y prestador referencia Entre dos profesionales
A6: Estandar | B6: Criterios | C6: Estado | D6: Comentarios
A7: CINN_TH | B7: Modalidad intramural, telemedicina - prestador remisor
A8: CINN_TH | B8: 1. Cumple con los criterios que le sean aplicables de todos los servicios y adicionalmente cuenta con: | C8: C
A9: CINN_TH | B9: 1.1. Profesional de la medicina especialista en pediatría | C9: NC
A10: CINN_TH | B10: 1.2. Profesional de la enfermería especialista en cuidado intensivo neonatal o con constancia de asistencia en las acciones de formación continua para la atención al paciente de cuidado intensivo neonatal. | C10: NA
A11: CINN_TH | B11: 1.3. Profesional de terapia respiratoria o fisioterapia.
A12: CINN_TH | B12: 1.4. Auxiliar de enfermería.
A13: CINN_TH | B13: 2. Disponibilidad de:
A14: CINN_TH | B14: 2.1. Profesional de la medicina especialista en neonatología, con permanencia mínima de 6 horas por cada 24 horas.
A15: CINN_TH | B15: 2.2. Profesional de la medicina especialista en oftalmología.
A16: CINN_TH | B16: 2.3. Profesional de la medicina especialista en cardiología.
A17: CINN_TH | B17: 2.4. Profesional de la medicina especialista en cirugía pediátrica.
A18: CINN_TH | B18: 2.5. Profesional de nutrición y dietética.
A19: CINN_TH | B19: 3. Todo el talento humano en salud cuenta con constancia de asistencia en las acciones de formación continua para la atención del paciente de cuidado intensivo neonatal, a excepción del médico (a) especialista en neonatología.
A20: CINN_TH | B20: Modalidad telemedicina - prestador de referencia
A21: CINN_TH | B21: 4. Cumple con los criterios que le sean aplicables de todos los servicios.
A22: CINN_TH | B22: 5. El profesional de salud puede hacer uso de la categoría telexperticia sincrónica entre profesionales de la salud de acuerdo con lo definido por el prestador de servicios de salud en el estándar de procesos prioritarios.
... A141: CINN_INT | B141: 24. No aplica.
B144: CUMPLE | C144: =COUNTIF($C$4:$C$141,"C") -> 1
B145: NO CUMPLE | C145: =COUNTIF($C$4:$C$141,"NC") -> 1
B146: NO APLICA | C146: =COUNTIF($C$4:$C$141,"NA") -> 1

Sheet 11.4.6. S_CINP
B1: VOLVER A TABLA DE CONTENIDO
B2: Grupo Internación
B3: Servicio Cuidado Intermedio Pediátrico
B4: Complejidad mediana
A5: Estandar | B5: Criterios | C5: Estado | D5: Comentarios
A6: CUIP_TH | B6: Modalidad intramural, telemedicina - prestador remisor
A7: CUIP_TH | B7: 1. Cumple con los criterios que le sean aplicables de todos los servicios y adicionalmente cuenta con | C7: C
A8: CUIP_TH | B8: 1.1. Profesional de la medicina con especialidad en pediatria. | C8: NC
A9: CUIP_TH | B9: 1.2. Profesional de la enfermería. | C9: NA
A10: CUIP_TH | B10: 1.3. Auxiliar de enfermería.
A11: CUIP_TH | B11: 2. Disponibilidad de:
A12: CUIP_TH | B12: 2.1. Profesional de la medicina especialista en cuidado intensivo pediátrico.
A13: CUIP_TH | B13: 2.2. Profesional de terapia respiratoria o de fisioterapia.
A14: CUIP_TH | B14: 2.3. Profesional de nutrición y dietética.
A15: CUIP_TH | B15: 3. Todo el talento humano en salud cuenta con constancia de asistencia en las acciones de formación continua en atención del paciente de cuidado intermedio pediátrico con excepción del profesional especialista en cuidado intensivo pediátrico.
A16: CUIP_TH | B16: Modalidad tefemedicina - prestador de referencia
A17: CUIP_TH | B17: 4. Cumple con los criterios que le sean aplicables de todos los servicios.
A18: CUIP_TH | B18: 5. El profesional de salud puede hacer uso de la categoría telexperticia sincrónica entre profesionales de la salud de acuerdo con lo definido por el prestador de servicios de salud en el estándar de procesos prioritarios.
A19: CUIP_TH | B19: 6. Profesional de la medicina especialista en cuidado intensivo pediátrico, puede realizar la disponibilidad en la categoría telexperticia sincrónica entre profesionales de la salud de acuerdo con lo definido por el prestador de servicios de salud en el estándar de procesos prioritarios.
A20: CUIP_INF | B20: Complejidad mediana
A21: CUIP_INF | B21: Modalidades intramural, telemedicina - prestador remisor
... A111: CUIP_INT | B111: 22. No aplica.
B114: CUMPLE | C114: =COUNTIF($C$4:$C$111,"C") -> 1
B115: NO CUMPLE | C115: =COUNTIF($C$4:$C$111,"NC") -> 1
B116: NO APLICA | C116: =COUNTIF($C$4:$C$111,"NA") -> 1

Sheet 11.4.7.S_CIP
B1: VOLVER A TABLA DE CONTENIDO
B2: Grupo Internación
B3: Servicio Cuidado Intensivo Pediátrico
B4: Complejidad: Alta Modalidad de prestación: lntramural Telemedicina - categorías: Telexperticia sincrónica prestador remisor y prestador referencia Entre dos profesionales
A5: Estandar | B5: Criterios | C5: Estado | D5: Comentarios
A6: CIP_TH | B6: Modalidad intramural, telemedicina - prestador remisor
A7: CIP_TH | B7: 1. Cumple con los criterios que le sean aplicables de todos los servicios y adicionalmente cuenta con | C7: C
A8: CIP_TH | B8: 1.1. Profesional de la medicina especialista en pediatria | C8: NC
A9: CIP_TH | B9: 1.2. Profesional de la enfermería especialista en cuidado crítico o cuidado crítico pediátrico o profesional de la enfermería con constancia de asistencia en las acciones de formación continua del control del paciente de cuidado intensivo pediátrico | C9: NA
A10: CIP_TH | B10: 1.3. Profesional de terapia respiratoria o fisioterapia
A11: CIP_TH | B11: 1.4. Auxiliar de enfermería con constancia de asistencia en acciones de formación continua en asistencia en soporte vital básico.
A12: CIP_TH | B12: 2. Disponibilidad de:
A13: CIP_TH | B13: 2.1. Profesional de la medicina especialista en cuidado intensivo pediátrico, con permanencia mínima de 6 horas por cada 24 horas.
A14: CIP_TH | B14: 2.2. Si oferta atención a pacientes quemados en condición crítica, disponibilidad de especialista en cirugía plástica.
A15: CIP_TH | B15: 2.3. Profesional de la medicina especialista en cirugía pediátrica.
A16: CIP_TH | B16: 2.4. Profesional de la medicina especialista en cardiología pediátrica
A17: CIP_TH | B17: 2.5. Profesional de Psicología.
A18: CIP_TH | B18: 2.6. Profesional de Fonoaudiología.
A19: CIP_TH | B19: 2.7. Profesional de Terapia ocupacional si atiende pacientes quemados en condición crítica.
A20: CIP_TH | B20: 2.8. Profesional de nutrición y dietética.
A21: CIP_TH | B21: 3. El profesional de la medicina especialista en cuidado intensivo pediátrico cuenta con constancia de asistencia, en acciones de formación continua de la gestión operativa de la donación de conformidad con las normas que regulen la materia, o aquellas que las adicionen, modifiquen o sustituyan.
... A137: CIP_INT | B137: 30. No aplica.
B140: CUMPLE | C140: =COUNTIF($C$4:$C$137,"C") -> 1
B141: NO CUMPLE | C141: =COUNTIF($C$4:$C$137,"NC") -> 1
B142: NO APLICA | C142: =COUNTIF($C$4:$C$137,"NA") -> 1

Sheet 11.4.8.S_CIMA
B1: VOLVER A TABLA DE CONTENIDO
B2: Grupo Internación
B3: Servicio Cuidado Intermedio Adulto
A4: Estandar | B4: Criterios | C4: Estado | D4: Comentarios
A5: CIMA_TH | B5: Complejidad mediana
A6: CIMA_TH | B6: Modalidad intramural, telemedicina - prestador remisor
A7: CIMA_TH | B7: 1. Cumple con los criterios definidos para todos los servicios y adicionalmente cuenta con: | C7: C
A8: CIMA_TH | B8: 1.1. Profesional de la medicina especialista en medicina interna. | C8: NC
A9: CIMA_TH | B9: 1.2. Profesional de la enfermería. | C9: NA
A10: CIMA_TH | B10: 1.3. Auxiliar de enfermería.
A11: CIMA_TH | B11: 2. Disponibilidad de:
A12: CIMA_TH | B12: 2.1. Profesional de la medicina especialista en medicina crítica o cuidado intensivo o anestesiología o cirugía general o medicina de urgencias.
A13: CIMA_TH | B13: 2.2. Profesional en terapia respiratoria o fisioterapia
A14: CIMA_TH | B14: 2.3. Profesional en nutrición y dietética.
A15: CIMA_TH | B15: 3. Todo el personal cuenta con acciones de formación continua en atención del paciente de cuidado intermedio adultos, a excepción de los especialistas en medicina critica o cuidado intensivo.
A16: CIMA_TH | B16: Modalidad telemedicina - prestador de referencia
A17: CIMA_TH | B17: 4. Cumple con los criterios que le sean aplicables de todos los servicios.
A18: CIMA_TH | B18: 5. Profesional de la medicina especialista en medicina crítica o cuidado intensivo o anestesiologia o cirugía general o medicina de urgencias, puede realizar la disponibilidad en la categoría telexperticia sincrónica entre profesionales de la salud de acuerdo con lo definido por el prestador de servicios de salud en e! estándar de procesos prioritarios.
A19: CIMA_TH | B19: 6.El profesional de la salud puede hacer uso de la telexperticia sincrónica entre profesionales de la salud, de acuerdo con lo definido por el prestador de servicios de salud en el estándar de procesos prioritarios.
A20: CIMA_INF | B20: Complejidad mediana
A21: CIMA_INF | B21: Modalidad intramural, telemedicina - prestador remisor
... A108: CIMA_INT | B108: 22. No aplica
B111: CUMPLE | C111: =COUNTIF($C$4:$C$108,"C") -> 1
B112: NO CUMPLE | C112: =COUNTIF($C$4:$C$108,"NC") -> 1
B113: NO APLICA | C113: =COUNTIF($C$4:$C$108,"NA") -> 1

Sheet 11.4.9.S_CIA
B1: VOLVER A TABLA DE CONTENIDO
B2: Grupo Internación
B3: Servicio Cuidado Intensivo Adultos
A4: Estandar | B4: Criterios | C4: Estado | D4: Comentarios
A5: CIA_TH | B5: Complejidad alta
A6: CIA_TH | B6: Modalidades intramural, telemedicina - prestador remisor
A7: CIA_TH | B7: 1. Cumple con los criterios que le sean aplicables de todos los servicios y adicionalmente cuenta con: | C7: C
A8: CIA_TH | B8: 1.1. Profesional de la medicina especialista en medicina crítica y cuidado intensivo o profesional de la medicina especialista en anestesiología o neurología o neurocirugía o medicina Interna o cirugía general o medicina de urgencias, según la oferta de servicios. | C8: NC
A9: CIA_TH | B9: 1.2. Profesional de la enfermería especialista en cuidado crítico o profesional en enfermería con acciones de formación continua en el control del paciente de cuidado intensivo adultos. | C9: NA
A10: CIA_TH | B10: 1.3. Profesional de terapia respiratoria o fisioterapia
A11: CIA_TH | B11: 1.4. Auxiliar de enfermería con constancia de asistencia en acciones de formación continua en asistencia en soporte vital básico.
A12: CIA_TH | B12: 2. Disponibilidad de:
A13: CIA_TH | B13: 2.1. Profesional de la medicina especialista en medicina crítica y cuidado Intensivo, con permanencia mínima de 6 horas por cada 24 horas.
A14: CIA_TH | B14: 2.2. Cuando se oferte atención a pacientes críticamente quemados, profesional de la medicina especialista en cirugía plástica.
A15: CIA_TH | B15: 2.3. Cuando se oferte atención a pacientes críticamente quemados, profesional de terapia ocupacional.
A16: CIA_TH | B16: 2.4. Profesional de nutrición y dietética.
A17: CIA_TH | B17: 2.5. Profesional de psicología
A18: CIA_TH | B18: 3. El profesional de la medicina especialista en medicina crítica y cuidado intensivo cuenta con constancia de asistencia en acciones de formación continua para la gestión operativa de la donación, de conformidad con las normas que regulen la materia, o aquellas que las adicionen, modifiquen o sustituyan.
A19: CIA_TH | B19: 4. Todo el talento humano en salud cuenta con constancia de asistencia en acciones de formación continua en atención del paciente de cuidado intensivo adultos, con excepción de los profesionales especialistas en cuidado intensivo y cuando se oferte atención a pacientes criticamente quemados con excepción del profesional de la medicina especialista en cirugía plástica.
A20: CIA_TH | B20: Modalidades telemedicina - prestador de referencia
A21: CIA_TH | B21: 5. Cumple con los criterios que le sean aplicables de todos los servicios.
... A123: CIA_INT | B123: 27. No aplica.
B126: CUMPLE | C126: =COUNTIF($C$4:$C$123,"C") -> 1
B127: NO CUMPLE | C127: =COUNTIF($C$4:$C$123,"NC") -> 1
B128: NO APLICA | C128: =COUNTIF($C$4:$C$123,"NA") -> 1

Sheet 11.4.10.S_HSM CSP
B1: VOLVER A TABLA DE CONTENIDO
B2: Grupo Internación
B3: Servicio Hospitalización Salud Mental o Consumo de Sustancias Psicoactivas
A4: Estandar | B4: Criterios | C4: Estado | D4: Comentarios
A5: HSM_TH | B5: Compleiidad mediana
A6: HSM_TH | B6: Modalidades intramural, telemedicina - prestador remisor
A7: HSM_TH | B7: 1. Cumple con los criterios que le sean aplicables de todos los servicios y adicionalmente, cuenta con: | C7: C
A8: HSM_TH | B8: 1.1. Profesional de la medicina. | C8: NC
A9: HSM_TH | B9: 1.2. Profesional de la enfermería. | C9: NA
A10: HSM_TH | B10: 1.3. Auxiliar de enfermería.
A11: HSM_TH | B11: 2.Disponibilidad de:
A12: HSM_TH | B12: 2.1. Profesional de la medicina especialista en psiquiatría o psiquiatría infantil con permanencia mínimo una vez a la semana en los horarios definidos en los procedimientos documentados en el estándar de procesos prioritarios.
A13: HSM_TH | B13: 2.2. Profesional de la medicina especialista en anestesiología con permanencia cuando se realicen procedimientos de terapia electroconvulsiva con anestesia relajante- TECAR.
A14: HSM_TH | B14: 2.3. Profesional en nutrición y dietética.
A15: HSM_TH | B15: 2.4. Profesional en psicología
A16: HSM_TH | B16: 2.5. Profesional en terapia ocupacional.
A17: HSM_TH | B17: 2.6 Profesional en trabajo social.
A18: HSM_TH | B18: 3. El talento humano en salud cuenta con:
A19: HSM_TH | B19: 3.1. Constancia de asistencia en las acciones de formación continua para la atención y el tratamiento en salud mental y consumo de sustancias psicoactivas y adicciones, según oferta.
A20: HSM_TH | B20: 3.2. Los profesionales de la medicina y de la enfermería cuentan con constancia de asistencia en las acciones de formación continua en soporte vital avanzado.
A21: HSM_TH | B21: Modalidad telemedicina - prestador de referencia
... A135: HSM_INT | B135: 27. No aplica.
B138: CUMPLE | C138: =COUNTIF($C$4:$C$135,"C") -> 1
B139: NO CUMPLE | C139: =COUNTIF($C$4:$C$135,"NC") -> 1
B140: NO APLICA | C140: =COUNTIF($C$4:$C$135,"NA") -> 1

Sheet 11.4.11.S_HSP
B1: VOLVER A TABLA DE CONTENIDO
B2: Grupo Internación
B3: Servicio Hospitalización Parcial
A4: Estandar | B4: Criterios | C4: Estado | D4: Comentarios
A5: HSP_TH | B5: Complejidad mediana
A6: HSP_TH | B6: Para el tratamiento en salud mental y consumo de sustancias psicoactivas
A7: HSP_TH | B7: Modalidades intramural, telemedicina - prestador remisor
A8: HSP_TH | B8: 1. Cuenta con:
A9: HSP_TH | B9: 1.1. Profesional de la medicina. | C9: C
A10: HSP_TH | B10: 1.2. Profesional de la enfermería. | C10: NC
A11: HSP_TH | B11: 2. Disponibilidad de:
A12: HSP_TH | B12: 2.1. Profesional de la medicina especialista en psiquiatría o psiquiatría infantil con permanencia mínimo tres (3) días por semana en los horarios definidos en los procedimientos documentados en el estándar de procesos prioritarios | C12: NA
A13: HSP_TH | B13: 2.2. Profesional de la psicología
A14: HSP_TH | B14: 2.3. Profesional de terapia ocupacional.
A15: HSP_TH | B15: 2.4 Profesional de trabajo Social
A16: HSP_TH | B16: 3. El talento humano en salud cuenta con constancia de asistencia en las acciones de formación continua para la atención y el tratamiento del consumidor de sustancias psicoactivas, adicciones y en salud mental.
A17: HSP_TH | B17: Modalidad telemedicina - prestador de referencia
A18: HSP_TH | B18: 4. Cumple con los criterios que le sean aplicables de todos los servicios.
A19: HSP_TH | B19: 5. El profesional de salud puede hacer uso de la categoría telexperticia sincrónica o asincrónica entre profesionales de la salud de acuerdo con lo definido por el prestador de servicios de salud en el estándar de procesos prioritarios.
A20: HSP_TH | B20: 6. Profesional de la medicina especialista en psiquiatría o psiquiatría infantil, cuando esté en disponibilidad y no se requiera su permanencia, puede utilizar la categoría telexperticia sincrónica o asincrónica entre profesionales de la salud, de acuerdo con lo definido por el prestador de servicios de salud en el estándar de procesos prioritarios.
A21: HSP_TH | B21: 7. El profesional de psicología puede realizar la disponibilidad en la categoría telexperticia sincrónica o asincrónica entre profesionales de la salud, de acuerdo con lo definido por el prestador de servicios de salud en el estándar de procesos prioritarios.
A22: HSP_TH | B22: Complejidad mediana Para la atención de pacientes con otras patologías:
A23: HSP_TH | B23: 8. Cumple con los criterios que le sean aplicables de todos los servicios y adicionalmente, cuenta con:
A24: HSP_TH | B24: 8.1. Profesional de la medicina.
... A173: HSP_INT | B173: 40. No aplica.
B176: CUMPLE | C176: =COUNTIF($C$4:$C$173,"C") -> 1
B177: NO CUMPLE | C177: =COUNTIF($C$4:$C$173,"NC") -> 1
B178: NO APLICA | C178: =COUNTIF($C$4:$C$173,"NA") -> 1

Sheet 11.4.12.S_CB_CSP
B1: VOLVER A TABLA DE CONTENIDO
B2: Grupo Internación
B3: Servicio para el cuidado básico del consumo de sustancias psicoactivas
A4: Estandar | B4: Criterios | C4: Estado | D4: Comentarios
A5: CBCSP_TH | B5: Complejidad mediana
A6: CBCSP_TH | B6: Modalidades intramural, telemedicina - prestador remisor
A7: CBCSP_TH | B7: 1. Cumple los criterios definidos para todos los servicios y adicionalmente, | C7: C
A8: CBCSP_TH | B8: 2. En horario diurno cuenta con: | C8: NC
A9: CBCSP_TH | B9: 2.1. Profesional de la enfermería | C9: NA
A10: CBCSP_TH | B10: 2.2. Profesional de psicología.
A11: CBCSP_TH | B11: 2.3. Profesional de trabajo social.
A12: CBCSP_TH | B12: 2.4. Profesional de terapia ocupacional.
A13: CBCSP_TH | B13: 3. Disponibilidad de:
A14: CBCSP_TH | B14: 3.1 Profesional de la medicina con permanencia mínima de tres (3) días a la semana, en los horarios definidos en los procedimientos documentados en el estándar de procesos prioritarios
A15: CBCSP_TH | B15: 3.2. Profesional de la medicina especialista en psiquiatría.
A16: CBCSP_TH | B16: 3.3. Profesional de nutrición y dietética.
A17: CBCSP_TH | B17: 4. En horario nocturno
A18: CBCSP_TH | B18: 4.1. Cuenta con auxiliar de enfermería.
A19: CBCSP_TH | B19: 4.2. Disponibilidad de profesional de la medicina.
A20: CBCSP_TH | B20: 5. Todo el talento humano en salud cuenta con constancia de asistencia en las acciones de formación continua para la atención y el tratamiento del consumidor de sustancias psicoactivas y salud mental.
A21: CBCSP_TH | B21: 6. Los profesionales de la medicina y de la enfermería cuentan con constancia de asistencia en las acciones de formación continua de soporte vital avanzado.
... A113: CBCSP_INT | B113: 27. No aplica.
B116: CUMPLE | C116: =COUNTIF($C$4:$C$113,"C") -> 1
B117: NO CUMPLE | C117: =COUNTIF($C$4:$C$113,"NC") -> 1
B118: NO APLICA | C118: =COUNTIF($C$4:$C$113,"NA") -> 1

Sheet 11.5.1.S_CX
B1: VOLVER A TABLA DE CONTENIDO
B2: Grupo Quirúrgico
B3: Servicio cirugia Descripción del servicio: Servicio destinado a la realización de procedimientos e intervenciones quirúrgicas, que requieren total asepsia. Los procedimientos e intervenciones pueden requerir o no internación para el manejo post operatorio. Cuando se realicen procedimientos de trasplante de órganos y tejidos, los autorizados son: Órganos: Riñón, hígado, corazón, páncreas, pulmón, intestino, multivisceral y los demás que et Ministerio de Salud y Protección Social autorice. Tejidos: Tejidos oculares, osteomuscular, cardiovascular, piel y componentes de la piel y los demás que el Ministerio de Salud y Protección Social autorice. Estructura del servicio: Complejidades: Mediana y alta Modalidades de prestación: Intramural Extramural, Jornada de salud y Unidad movil - No aplica para transplantes Telemedicina - Categoria: Telexperticia sincrónica o asincrónica entre 2 profesionales
A4: Estandar | B4: Criterios | C4: Estado | D4: Comentarios
A5: CX_TH | B5: Complejidad Mediana y Alta
A6: CX_TH | B6: Modalidades Intramural, extramural jornada de salud, unidad móvil y telemedicina - prestador remisor
A7: CX_TH | B7: 1. Cumple con los criterios que le sea aplicables a todos los servicios y adicionalmente cuenta con: | C7: C
A8: CX_TH | B8: 1.1. Auxiliar en enfermería. | C8: NC
A9: CX_TH | B9: 1.2. Profesional en Instrumentación quirúrgica para cada uno de los procedimientos que lo requieran. | C9: NA
A10: CX_TH | B10: 2. Disponibilidad de:
A11: CX_TH | B11: 2.1 Profesional de la medicina o de la odontología especialista según la oferta del prestador de servicios de salud con permanencia durante los procedimientos quirúrgicos y de conformidad con lo documentado en el estándar de procesos prioritarios.
A12: CX_TH | B12: 2.2 Profesional de la medicina especialista en anestesiología, con permanencia durante los procedimientos documentados por el prestador de servicios de salud en el estándar de procesos prioritarios, quien realizará solo un procedimiento a la vez y estará presente durante todo el acto quirúrgico
A13: CX_TH | B13: 2.3 Si oferta cirugía oncológica, profesional de la medicina especialista en cirugía oncológica o especialista que demuestre haber adquirido en su formación académica conocimientos en el manejo quirúrgico de las patologías oncológicas.
A14: CX_TH | B14: 2.4 En zonas especiales de dispersión geográfica, los profesionales de la medicina pueden practicar procedimientos quirúrgicos en casos de urgencia y en casos no remisibles, debido a la condición clínica del paciente o por limitaciones de acceso geográfico.
A15: CX_TH | B15: 3.Si ofrece trasplante de tejidos adicional a lo anterior, disponibilidad con permanencia de profesionales de la medicina especialistas quirúrgicos durante los procedimientos quirúrgicos y de conformidad con lo definido en el estándar de procesos prioritarios, así:
A16: CX_TH | B16: 3.1 Para el trasplante de tejido ocular: profesional de la medicina especialista en oftalmología.
A17: CX_TH | B17: 3.2 Para el trasplante osteomuscular: Profesional de la medicina especialista en cirugía que demuestre haber adquirido en su formación académica conocimientos en el manejo quirúrgico del trasplante osteomuscular. según la oferta del servicio.
A18: CX_TH | B18: 3.3 Para el trasplante cardiovascular: profesional de la medicina especialista en cirugía cardiovascular.
A19: CX_TH | B19: 3.4 Para trasplante de piel y componentes de la piel: profesional de la medicina especialista en cirugía que demuestre haber adquirido en su formación académica conocimientos en el manejo quirúrgico del trasplante de piel y componentes de la piel.
A20: CX_TH | B20: 4 Si ofrece trasplante de órganos cumple con los criterios definidos para el servicio de cirugía en mediana complejidad y adicionalmente, cuenta con:
A21: CX_TH | B21: 4.1 Coordinador operativo de trasplantes.
... A236: CX_INT | B236: 44. No Aplica.
B239: CUMPLE | C239: =COUNTIF($C$4:$C$236,"C") -> 1
B240: NO CUMPLE | C240: =COUNTIF($C$4:$C$236,"NC") -> 1
B241: NO APLICA | C241: =COUNTIF($C$4:$C$236,"NA") -> 1

Sheet 11.6.1.S_UR
B1: VOLVER A TABLA DE CONTENIDO
B2: Grupo de atención inmediata
B3: Servicio Urgencias
A4: Estandar | B4: Criterios | C4: Estado | D4: Comentarios
A5: URG_TH | B5: Complejidad baja
A6: URG_TH | B6: Modalidades Intramural, telemedicina - prestador remisor.
A7: URG_TH | B7: 1. Cumple con los criterios que le sean aplicables de todos los servicios y adicionalmente cuenta con: | C7: C
A8: URG_TH | B8: 1.1. Profesional de la medicina que cuenta con constancia de asistencia en las acciones de formación continua en soporte vital avanzado. | C8: NC
A9: URG_TH | B9: 1.2. Auxiliar de enfermería que cuenta con constancia de asistencia en las acciones de formación continua en soporte vital básico. | C9: NA
A10: URG_TH | B10: 2. En zonas dispersas, de dispersión geográfica, disponibilidad de:
A11: URG_TH | B11: 2.1. Profesional de la medicinal que cuenta con constancia de asistencia en las acciones de formación continua en soporte vital avanzado.
A12: URG_TH | B12: 2.2. Auxiliar de enfermería que cuenta con constancia de asistencia en las acciones de formación continua en soporte vital básico.
A13: URG_TH | B13: Modalidad telemedicina - prestador de referencia
A14: URG_TH | B14: 3. Cumple con los criterios que le sean aplicables de todos los servicios.
A15: URG_TH | B15: 4. El profesional de la medicina puede hacer uso de la categoria telexperticia sincronica o asincrónicaentre profesionales de la salud de acuerdo por el prestador de servicios de salud en el estándar de procesos prioritarios.
A16: URG_TH | B16: Complejidad media
A17: URG_TH | B17: Modalidades Intramural, telemedicina - prestador remisor.
A18: URG_TH | B18: 5. Cuenta con:
A19: URG_TH | B19: 5.1. Profesional de la medicina o profesional de la medicina especialista en medicina de urgencias o medicina familiar.
A20: URG_TH | B20: 5.2.Profesional de la enfermería..
A21: URG_TH | B21: 5.3. Auxiliar de enfermería que cuenta con constancia de asistencia en las acciones de formación continua en soporte vital básico.
... A246: URG_INT | B246: 48. No aplica
B249: CUMPLE | C249: =COUNTIF($C$4:$C$246,"C") -> 1
B250: NO CUMPLE | C250: =COUNTIF($C$4:$C$246,"NC") -> 1
B251: NO APLICA | C251: =COUNTIF($C$4:$C$246,"NA") -> 1

Sheet 11.6.2.S_TR_AS
B1: VOLVER A TABLA DE CONTENIDO
B2: Grupo de atención inmediata
B3: 11.6.2 Servicio de transporte asistencial
B4: Descripciòn del servicio: Es el servicio de salud donde se realiza el traslado y se brinda atenciòn oportuna y permanente al paciente en ambulancias terrestres, mariítimas, fluviales y aéreas Estructura del servicio: Complejidad Baja: Transporte terrestre, maritimo y fluvial Complejidad Mediana: Transporte terrestre, maritimo, fluvial y aéreo Modalidades de prestación: Extramural Telemedicina - categoría: Telexperticia sincrónico - prestador remisor y prestador de referencia Entre dos profesionales Entre personal no profesional de salud y profesional de salud
A5: Estandar | B5: Criterios | C5: Estado | D5: Comentarios
A6: TR__AS_TH | B6: Complejidad baja
A7: TR__AS_TH | B7: Modalidades extramural y telemedicina - prestador remisor
A8: TR__AS_TH | B8: Para ambulancias terrestres:
A9: TR__AS_TH | B9: 1. Cumple con los criterios que le sean aplicables de todos los servicios y adicionalmente cuenta con: | C9: C
A10: TR__AS_TH | B10: 1.1. Tecnólogo en atención prehospitalaria o técnico profesional en atención prehospitalaria o auxiliar en enfermería, en cualquier caso, cuenta con constancia de asistencia en las acciones de formación continua en soporte vital básico. | C10: NC
A11: TR__AS_TH | B11: 1.2. Conductor que cuenta con licencia para la conducción del respectivo vehículo, expedida por la autoridad competente y adicionalmente cuenta con constancia de asistencia en las acciones de formación continua en primeros auxilios o de primer respondiente. | C11: NA
A12: TR__AS_TH | B12: Para ambulancias fluviales y marítimas:
A13: TR__AS_TH | B13: 2. Cumple con los criterios que le sean aplicables de todos los servicios y adicionalmente cuenta con:
A14: TR__AS_TH | B14: 2.1. Tecnólogo en atención prehospitalaria o técnico profesional en atención prehospitalaria o auxiliar en enfermería, en cualquier caso, cuenta con constancia de asistencia en las acciones de formación continua en soporte vital básico.
A15: TR__AS_TH | B15: 2.2. Para embarcaciones menores (cuya capacidad de transporte no excede las 25 toneladas) cuenta con:
A16: TR__AS_TH | B16: 2.2.1. Motorista y tripulante (que puede ser ayudante fluvial), que cuentan con permiso expedido por la autoridad competente y adicionalmente cuentan con constancia de asistencia en las acciones de formación continua en primeros auxilios o de primer respondiente.
A17: TR__AS_TH | B17: 2.2.2. Para embarcaciones mayores (cuya capacidad de transporte excede las 25 toneladas) la tripulación mínima será la que determina el Ministerio de Transporte para las 6 categorías que conforman este grupo de embarcaciones, cuenta con licencia expedidos por la autoridad competente y adicionalmente cuentan con constancia de asistencia en las acciones de formación continua en primeros auxilios o de primer respondiente.
A18: TR__AS_TH | B18: Complejidad mediana
A19: TR__AS_TH | B19: Modalidades extramural y telemedicina - prestador remisor
A20: TR__AS_TH | B20: Para ambulancias terrestres, fluviales y marítimas
A21: TR__AS_TH | B21: 3. Cumple con los criterios que le sean aplicables de todos los servicios y adicionalmente cuenta con:
A22: TR__AS_TH | B22: 3.1. Coordinador responsable de la totalidad de las ambulancias con las que cuente el servicio, que puede ser profesional de la medicina o profesional de la enfermería.
A23: TR__AS_TH | B23: 4. La ambulancia cuenta con la siguiente tripulación:
... A285: TR_AS_INT | B285: 45. No Aplica
B288: CUMPLE | C288: =COUNTIF($C$4:$C$285,"C") -> 1
B289: NO CUMPLE | C289: =COUNTIF($C$4:$C$285,"NC") -> 1
B290: NO APLICA | C290: =COUNTIF($C$4:$C$285,"NA") -> 1

Sheet 11.6.3.S_AT_PH
B1: VOLVER A TABLA DE CONTENIDO
B2: Grupo de atención inmediata
B3: Servicio de atención prehospitalaria
A4: Estandar | B4: Criterios | C4: Estado | D4: Comentarios
A5: S_AT_PH_TH | B5: Complejidad baja
A6: S_AT_PH_TH | B6: Modalidades extramural y tefemedicina - prestador remisor
A7: S_AT_PH_TH | B7: 1. Cumple con los criterios que le sean aplicables de todos los servicios y adicionalmente cuenta con: | C7: C
A8: S_AT_PH_TH | B8: 1.1 Tecnólogo en atención prehospitalaria o técnico profesional en atención prehospitalaria o profesional de la medicina. | C8: NC
A9: S_AT_PH_TH | B9: 1.2 El talento humano en salud cuenta con constancia de asistencia en las acciones de formación continua en soporte vital avanzado | C9: NA
A10: S_AT_PH_TH | B10: Modalidad de telemedicina - prestador de referencia
A11: S_AT_PH_TH | B11: 2. Cumple con los criterios que te sean aplicables de todos los servicios.
A12: S_AT_PH_TH | B12: 3. El profesional de la salud puede hacer uso de la categoría telexperticia sincrónica entre profesionales de la salud, de acuerdo con lo definido por el prestador de servicios de salud en el estándar de procesos prioritarios
A13: S_AT_PH_TH | B13: 4. El personal de salud no profesional puede hacer uso de la categoría telexperticia sincrónica con profesionales de la salud de acuerdo con lo definido por el prestador de servicios de salud en e! estándar de procesos prioritarios.
A14: S_AT_PH_INF | B14: Complejidad baja
A15: S_AT_PH_INF | B15: Modalidades extramural y telemedicina - prestador remisor
A16: S_AT_PH_INF | B16: 5. Cumple con los criterios que le sean aplicables de todos los servicios y adicionalmente, cuenta con:
A17: S_AT_PH_INF | B17: 5.1. Sede donde se manejen los procesos administrativos del servicio, que cuenta con:
A18: S_AT_PH_INF | B18: 5.1.1 Ambiente para el almacenamiento de medicamentos y dispositivos médicos e insumos
A19: S_AT_PH_INF | B19: 5.1.2.Ambiente o área para e! almacenamiento de equipos biomédicos
A20: S_AT_PH_INF | B20: 5.1.3.Sistema eléctrico que permita la conexión de los equipos biomédicos
A21: S_AT_PH_INF | B21: 5.1.4.Ambiente para el archivo de las historias clínicos y registros
... A97: S_AT_PH_INT | B97: 18. No aplica.
B100: CUMPLE | C100: =COUNTIF($C$4:$C$97,"C") -> 1
B101: NO CUMPLE | C101: =COUNTIF($C$4:$C$97,"NC") -> 1
B102: NO APLICA | C102: =COUNTIF($C$4:$C$97,"NA") -> 1

Sheet 11.6.4.S_A.parto
B1: VOLVER A TABLA DE CONTENIDO
B2: Grupo de atención inmediata
B3: Servicio para la atención del parto
A4: Estandar | B4: Criterios | C4: Estado | D4: Comentarios
A5: S_Aparto_TH | B5: Complejidad baja
A6: S_Aparto_TH | B6: Modalidades intramural y telemedicina - prestador remisor
A7: S_Aparto_TH | B7: 1. Cumple con los criterios que le sean aplicables de todos los servicios y adicionalmente, cuenta con: | C7: C
A8: S_Aparto_TH | B8: 1.1. Auxiliar en enfermería. | C8: NC
A9: S_Aparto_TH | B9: 2. Disponibilidad de:
A10: S_Aparto_TH | B10: 2.1. Profesional de la medicina general. | C10: NA
A11: S_Aparto_TH | B11: 2.2. Profesional de la enfermería.
A12: S_Aparto_TH | B12: Complejidades mediana y alta
A13: S_Aparto_TH | B13: Modalidades intramural y telemedicina - prestador remisor
A14: S_Aparto_TH | B14: 3. Cumple con los criterios que le sean aplicables de todos los servicios y adicionalmente, cuenta con:
A15: S_Aparto_TH | B15: 3.1. Profesional de la medicina especialista en ginecobstetricia
A16: S_Aparto_TH | B16: 3.2. Profesional de la enfermería.
A17: S_Aparto_TH | B17: 3.3. Auxiliar de enfermería.
A18: S_Aparto_TH | B18: 4. Disponibilidad de:
A19: S_Aparto_TH | B19: 4.1. Profesional de la medicina especialista en pediatría.
A20: S_Aparto_TH | B20: 4.2. Profesional de la medicina especialista en anestesiología.
A21: S_Aparto_TH | B21: 4.3. Profesional de psicología.
A22: S_Aparto_TH | B22: 5. Disponibilidad de:
... A216: S_Aparto_INT | B216: 36. No aplica.
B219: CUMPLE | C219: =COUNTIF($C$4:$C$216,"C") -> 1
B220: NO CUMPLE | C220: =COUNTIF($C$4:$C$216,"NC") -> 1
B221: NO APLICA | C221: =COUNTIF($C$4:$C$216,"NA") -> 1
