Workbook
Name acciones: planaccion[Qué / Acción]
Name alcance: 'DOCUMENTO PAMEC'!$B$47
Name Apoyo_Diagnóstico_Compl._Terapéutica: Datos!$D$2:$D$23
Name Atención_Inmediata: Datos!$E$2:$E$6
Name categoria: 'AUTOEV CUALIT'!$E$5:$E$204
Name Cirugía: Datos!$B$2:$B$25
Name Consulta_Externa: Datos!$A$2:$A$92
Name criterio: 'AUTOEV CUALIT'!$F$5:$F$204
Name criterio_priorizado: planaccion[Criterio]
Name duracion: 'DOCUMENTO PAMEC'!$B$60
Name Eje_de_Seguridad: 'AUTOEV CUALIT'!$C$5:$C$204
Name eje_priorizado: planaccion[Eje Seguridad]
Name fortaleza: 'AUTOEV CUALIT'!$G$5:$G$204
Name institucion: 'DOCUMENTO PAMEC'!$B$64
Name Internación: Datos!$C$2:$C$16
Name intro: 'DOCUMENTO PAMEC'!$B$18
Name justifica: 'DOCUMENTO PAMEC'!$B$36
Name justificacion: 'DOCUMENTO PAMEC'!$B$37
Name legal: 'DOCUMENTO PAMEC'!$B$26
Name marco: 'DOCUMENTO PAMEC'!$B$74
Name marcolegal: 'DOCUMENTO PAMEC'!$B$27
Name MARCOTEO: 'DOCUMENTO PAMEC'!$B$75
Name metodologia: 'DOCUMENTO PAMEC'!$B$99
Name nivelauditoria: 'DOCUMENTO PAMEC'!$B$56
Name objetivo: 'DOCUMENTO PAMEC'!$B$39
Name OBJETIVOPAMEC: 'DOCUMENTO PAMEC'!$B$40
Name om: 'AUTOEV CUALIT'!$H$5:$H$204
Name om_priorizada: planaccion[Oportunidad de Mejora]
Name practica_priorizada: planaccion[Práctica Segura]
Name practica_segura: 'AUTOEV CUALIT'!$D$5:$D$204
Name proceso1: PROCESOS!$D$5
Name proceso10: PROCESOS!$L$7
Name proceso11: PROCESOS!$D$9
Name proceso12: PROCESOS!$F$9
Name proceso13: PROCESOS!$H$9
Name proceso14: PROCESOS!$J$9
Name proceso15: PROCESOS!$L$9
Name proceso16: PROCESOS!$D$13
Name proceso17: PROCESOS!$F$13
Name proceso18: PROCESOS!$H$13
Name proceso19: PROCESOS!$J$13
Name proceso2: PROCESOS!$F$5
Name proceso20: PROCESOS!$L$13
Name proceso21: PROCESOS!$D$15
Name proceso22: PROCESOS!$F$15
Name proceso23: PROCESOS!$H$15
Name proceso24: PROCESOS!$J$15
Name proceso25: PROCESOS!$L$15
Name proceso26: PROCESOS!$D$17
Name proceso27: PROCESOS!$F$17
Name proceso28: PROCESOS!$H$17
Name proceso29: PROCESOS!$J$17
Name proceso3: PROCESOS!$H$5
Name proceso30: PROCESOS!$L$17
Name proceso31: PROCESOS!$D$19
Name proceso32: PROCESOS!$F$19
Name proceso33: PROCESOS!$H$19
Name proceso34: PROCESOS!$J$19
Name proceso35: PROCESOS!$L$19
Name proceso36: PROCESOS!$D$23

Sheet RUTA CRITICA

Sheet IDENTIFICACIÓN
C1: Información del Prestador y Servicios Habilitados
C3: Desde | D3: Hasta
B4: Ciclo de Mejora
B6: Nombre del Prestador | C6: IPS ABC
B8: NIT
B10: Código REPS
B12: Ciudad Sede
B14: Nombre de la Sede
B16: Código REPS de la Sede
B18: Dirección y teléfono sede
B20: Gerente / Director / Responsable Sede
B22: Contratos Activos
B24: ="Servicios Habilitados por el Prestador en la Sede "&C14 -> Servicios Habilitados por el Prestador en la Sede
B26: Grupo | C26: Servicio | D26: Complejidad | E26: Modalidad (Intramural-Unidad móvil-Domiciliario-Jornada salud-Extramural-Prestador Ref. Telem. Interactiva-Prestador Ref. Telem. no interactiva-Prestador Ref. Telexperticia-Prestador Ref. Telemonitoreo-Prestador Rem. Telemonitoreo-Prestador Rem. Telexpert

Sheet LOGO
C1: <--- Inserte su logo en esta celda "A1"

Sheet PROCESOS
D1: ="Mapa de Procesos "&IDENTIFICACIÓN!C14 -> Mapa de Procesos
B3: Cliente | D3: Procesos de Planeación o Estratégicos | N3: Cliente
D11: Procesos Misionales
D21: Procesos de Apoyo o Soporte

Sheet DOCUMENTO PAMEC
C1: ="Documento PAMEC "&IDENTIFICACIÓN!C14 -> Documento PAMEC
B3: Contenido
C5: Introducción
C6: Marco legal
C7: Justificación
C8: Objetivo
C9: Alcance
C10: Duración y cronograma Ruta Crítica
C11: Tipos de acciones
C12: Niveles de auditoria
C13: Presentación Institucional y Contexto Operativo
C14: Marco Conceptual
C15: Metodología de Implementación
B18: Introducción
B19: La gestión de la calidad en el ámbito de la salud desempeña un papel fundamental en asegurar que los servicios proporcionados alcancen los estándares más elevados, garantizando así la seguridad y el bienestar de los pacientes. En este contexto, el Programa de Auditoría para el Mejoramiento de la Calidad en Salud (PAMEC) emerge como una herramienta estratégica crucial para evaluar y fortalecer los procesos internos de las instituciones.
B20: El propósito fundamental del Programa de Auditoría para el Mejoramiento de Calidad en Salud con enfoque en la Política Nacional de Seguridad del Paciente en la institución ____________________ consiste en llevar a cabo un proceso de mejora continua, iniciando con un análisis exhaustivo a través de la autoevaluación. Este proceso permite identificar posibles deficiencias en la calidad de los servicios ofrecidos, considerando estas deficiencias como áreas prioritarias para la implementación de mejoras continuas.
B21: La siguiente fase implica la identificación de procesos institucionales con brechas de calidad, estrechamente relacionados con el proceso de atención, orientados hacia el usuario. En consonancia con la disponibilidad de recursos institucionales, estos procesos serán priorizados para su intervención.
B22: Posteriormente, después de identificar los procesos que requieren mejora, se da un paso crucial al definir el nivel de calidad esperado en su ejecución y resultados mediante una planificación cuantitativa de la calidad. Con base en estos parámetros, se formulan acciones de mejora y se establecen las herramientas y mecanismos de auditoría necesarios para su seguimiento.
B23: La fase de ejecución y seguimiento de las actividades definidas, marca otro hito en el proceso de mejora continua. La creación de espacios dedicados al seguimiento minucioso del cumplimiento de los planes de acción y la evaluación de los resultados obtenidos, mediante los indicadores designados se vuelve prioritaria. La efectividad de las estrategias se evalúa a través del seguimiento de indicadores y la verificación de los resultados de las auditorías.
B24: Al concluir el ciclo de mejora, se realiza un análisis integral de las oportunidades de mejora abordadas, junto con un resumen detallado que destaca la naturaleza del problema, el análisis realizado, las causas identificadas y las acciones emprendidas. Este resumen proporciona una visión clara del progreso alcanzado y permite llevar a cabo una evaluación de la efectividad y eficiencia de la implementación de acciones y auditorías. Esto permite una evaluación completa de los resultados obtenidos a lo largo de la Ruta Crítica del PAMEC.
B26: Marco Legal
B27: • Decreto 780 de 2016: Por medio del cual se expide el Decreto Único Reglamentario del Sector Salud y Protección Social. Establece lo referente al PAMEC en el Parte 5, Titulo 1, Capitulo 4.
B28: • Resolución 3100 del 2019: Por la cual se definen los procedimientos y condiciones de inscripción de los prestadores de servicios de salud y de habilitación de los servicios de salud y se adopta el Manual de Inscripción de Prestadores y Habilitación de Servicios de Salud
B29: • Resolución 0256 de 2016: Por la cual se dictan disposiciones en relación con el Sistema de Información para la Calidad y se establecen los indicadores para el monitoreo de la calidad en salud
B30: • Circular 012 de 2016: Por la cual se hacen adiciones, eliminaciones y modificaciones a la Circular 047 de 2007 y se imparten instrucciones en lo relacionado con el programa de auditoria para el mejoramiento de la calidad de la atención en salud y el sistema de información de la calidad.
... B49: Tipos de Acciones
B50: ="En "&IDENTIFICACIÓN!C6&" se contemplan tres tipos de acciones para la auditoría de la calidad de la atención en salud:" -> En IPS ABC se contemplan tres tipos de acciones para la auditoría de la calidad de la atención en salud:
B51: Acciones Preventivas: Comprenden un conjunto de procedimientos, actividades o mecanismos de auditoría sobre los procesos prioritarios definidos por la entidad, que tanto las personas como la organización deben llevar a cabo antes de la atención de los usuarios, con el objetivo de garantizar la calidad. Estas acciones están orientadas a evitar la aparición de problemas de calidad ya identificados. Entre las acciones preventivas definidas en la institución se encuentran: (AJUSTE LAS ACCIONES SEGÚN LAS PRÁCTICAS DE LA INSTITUCIÓN) - Adopción de guías de práctica clínica basadas en las principales causas de consulta. - Documentación y estandarización de procesos mediante el sistema de gestión de calidad. - Inducción a nuevos colaboradores, incluyendo los procesos prioritarios. - Jornadas de capacitación al personal asistencial en temas clave para la calidad y seguridad en la atención. - Programa de mantenimiento preventivo de equipos biomédicos e infraestructura.
B52: Acciones de Seguimiento: Son aquellas que se realizan lo más cercano posible al tiempo real de la ejecución de los procesos, con el fin de identificar y resolver de manera oportuna los problemas reales o potenciales. Estas acciones buscan evidenciar brechas de desempeño y asegurar la correcta aplicación de guías, normas y procedimientos conforme a los referentes legales y de calidad adoptados. Las acciones de seguimiento incluyen: (AJUSTE LAS ACCIONES SEGÚN LAS PRÁCTICAS DE LA INSTITUCIÓN) - Rondas de seguridad del paciente. - Auditorías de calidad a procesos. - Encuestas de satisfacción del usuario. - Auditoría de historias clínicas. Acciones Coyunturales: Estas acciones comprenden procedimientos, actividades o mecanismos de auditoría que se realizan con el objetivo de alertar, informar y analizar la ocurrencia de eventos adversos durante la atención en salud, facilitando intervenciones inmediatas para resolver los problemas detectados y prevenir su recurrencia. Estas acciones tienen un enfoque retrospectivo, permitiendo detectar, informar y analizar resultados no esperados. Las acciones coyunturales incluyen: (AJUSTE LAS ACCIONES SEGÚN LAS PRÁCTICAS DE LA INSTITUCIÓN) - Análisis y gestión de eventos adversos. - Seguimiento y gestión de PQRS (Peticiones, Quejas, Reclamos y Sugerencias) de los usuarios. - Gestión de no conformidades.
B55: Niveles de Auditoria
B56: El programa de auditoría para el mejoramiento de la calidad se concibe como un sistema de monitoreo continuo que compara la calidad observada con la calidad esperada. Para garantizar su efectividad, se establecen tres niveles de auditoría: autocontrol, auditoría interna y auditoría externa. Autocontrol: Este es el nivel más eficiente de auditoría, en el cual cada miembro de la organización se responsabiliza por planear, ejecutar, verificar y ajustar los procedimientos en los que participa, asegurándose de que se cumplan los estándares de calidad establecidos tanto por la normativa vigente como por la entidad. Entre los mecanismos de autocontrol definidos se incluyen: (AJUSTE LAS PRÁCTICAS DE AUDITORIA EN CADA NIVEL SEGÚN LA REALIDAD DE LA INSTITUCIÓN) - Diseño y estandarización de los procesos de atención. - Capacitación y entrenamiento de los colaboradores en las actividades bajo su responsabilidad. - Implementación de mecanismos de auto-chequeo en prácticas seguras durante la atención.
B57: Auditoría Interna: Es una evaluación sistemática realizada dentro de la institución, cuyo objetivo es monitorear la adherencia a los protocolos y prácticas institucionales, así como verificar la correcta ejecución del autocontrol. Para llevar a cabo la auditoría interna, se establecen procedimientos, programas y herramientas de auditoría. Sus principales objetivos son: (AJUSTE LAS PRÁCTICAS DE AUDITORIA EN CADA NIVEL SEGÚN LA REALIDAD DE LA INSTITUCIÓN) - Analizar las causas que impiden alcanzar los resultados esperados en los procesos priorizados. - Implementar acciones necesarias para alcanzar el nivel de calidad deseado. - Acompañar a los responsables de los procesos en su seguimiento y mejora continua. Auditoría Externa: Esta auditoría es llevada a cabo por una entidad externa a la organización y tiene como propósito evaluar la efectividad de la auditoría interna y del autocontrol. Las auditorías externas son comúnmente realizadas por aseguradoras, clientes, y las Secretarías de Salud Pública a nivel municipal y departamental.
B59: Duración y Cronograma de la Ruta Crítica
B60: ="Se ha definido un cronograma de trabajo que inicia el "&DAY(IDENTIFICACIÓN!C4)&"/"&MONTH(IDENTIFICACIÓN!C4)&"/"&YEAR(IDENTIFICACIÓN!C4)&" y culmina el "&DAY(IDENTIFICACIÓN!D4)&"/"&MONTH(IDENTIFICACIÓN!D4)&"/"&YEAR(IDENTIFICACIÓN!D4)&". A continuación, se detallan las fases clave y sus respectivas fechas estimadas:" -> Se ha definido un cronograma de trabajo que inicia el 0/1/1900 y culmina el 0/1/1900. A continuación, se detallan las fases clave y sus respectivas fechas estimadas:
B61: Ver Cronograma en este vinculo
B63: Presentación Institucional y Contexto Operativo
B64: En esta sección realice una descripción exhaustiva de la institución, abordando aspectos como la gama de servicios ofrecidos y el marco estratégico en el cual la institución se desenvuelve, destacando los elementos fundamentales que respaldan sus objetivos y metas a largo plazo. Nam tellus nisi, lacinia nec pretium in, euismod nec purus. Mauris eleifend lacus lectus, et euismod leo maximus non. Cras justo tellus, semper vel sapien et, ultricies pellentesque ex. Lorem ipsum dolor sit amet, consectetur adipiscing elit. Vivamus vitae leo justo. Nulla lacus purus, lobortis in elementum id, convallis vestibulum arcu. Phasellus viverra lectus ut aliquam tristique. Sed nec massa nec libero fringilla efficitur ut quis mi. Ut condimentum mollis tortor a pharetra. Nam venenatis finibus enim nec ultricies. Quisque nec blandit sem
B65: Ver ficha técnica de información del prestador y servicios habilitados en este vínculo
B67: Registre la misión corporativa Phasellus imperdiet arcu et maximus vestibulum. Nullam finibus posuere semper. Pellentesque egestas lobortis odio, quis fringilla est. In turpis arcu, mollis ut accumsan quis, pretium dapibus ante. Aenean elementum convallis mollis.
B69: Registre la visión corporativa Aliquam ac cursus arcu. Morbi blandit lobortis congue. Maecenas iaculis neque sit amet feugiat vulputate. In imperdiet velit eget libero volutpat fermentum. Nulla accumsan sem sed ligula scelerisque, sit amet tempus libero pulvinar.
B71: A continuación, se presenta el mapa de procesos institucional que es una representación gráfica de la secuencia de actividades y funciones clave que sustentan el funcionamiento integral de nuestra institución. Este mapa ofrece una visión global de cómo se interconectan y relacionan los diversos procesos, proporcionando una guía visual para comprender la dinámica operativa de la organización. Cada uno de los elementos en el mapa representa un proceso específico, y sus interconexiones reflejan la integración necesaria para alcanzar los objetivos institucionales. Este enfoque visual no solo facilita la comprensión de la estructura operativa, sino que también resalta áreas estratégicas que son esenciales para la efectiva implementación de iniciativas de mejora, como la Ruta Crítica que estamos llevando a cabo.
B72: Ver Mapa de procesos en este vinculo
B74: Marco Conceptual
B76: El desarrollo del PAMEC incluye las siguientes etapas de la ruta crítica:
B78: La autoevaluación, punto de partida crucial en la Ruta Crítica del Programa de Auditoría para el Mejoramiento de la Calidad en Salud (PAMEC), es un proceso integral destinado a realizar un análisis introspectivo de la institución. Este primer paso se enfoca en identificar a fondo problemas o deficiencias de calidad que puedan afectar directamente a la organización y, en última instancia, a los usuarios de los servicios de salud. La participación activa en este proceso involucra a diferentes actores dentro de la institución, incluyendo la gerencia, el equipo directivo, el personal asistencial, la auditoría, el control interno y los equipos de mejoramiento de la calidad. Esta diversidad de perspectivas garantiza una evaluación holística de los procesos internos y su impacto en la calidad de la atención. La pregunta esencial que motiva esta autoevaluación es "¿qué puede mejorarse?". Aquí, se abordan procesos, momentos de verdad y resultados que tienen un impacto directo en la calidad de la atención. Es relevante subrayar que este diagnóstico básico no solo arroja un inventario de problemas, sino que sienta las bases para identificar los procesos que contribuyen a su generación
B79: Esta fase crucial se desglosa en dos aspectos fundamentales, cada uno aportando perspectivas valiosas para el perfeccionamiento global de los procesos de atención y servicios de salud. - Primera Parte: Evaluación Cualitativa Donde se propone una exploración detallada para identificar oportunidades de mejora y reconocer las fortalezas de la organización. Esta evaluación, basada en un análisis cualitativo, no solo destaca los aspectos a potenciar, sino que también resalta los logros y prácticas exitosas. La clave radica en comprender a fondo el panorama actual para trazar estrategias efectivas de mejoramiento. - Segunda Parte: Evaluación Cuantitativa La segunda parte de la autoevaluación introduce un enfoque cuantitativo, permitiendo la medición objetiva de diferentes parámetros. Este análisis puede llevarse a cabo individualmente o involucrar a múltiples evaluadores, ofreciendo una perspectiva más completa y diversa. La rigurosidad de esta evaluación cuantitativa proporciona datos concretos que respaldan decisiones informadas y estrategias específicas de mejora. En conjunto, estas dos fases de autoevaluación constituyen una herramienta poderosa dentro del PAMEC, proporcionando una visión completa y equilibrada de la calidad de la atención en salud. Al abordar tanto aspectos cualitativos como cuantitativos, se establece una base sólida para la planificación estratégica y la implementación efectiva de acciones correctivas y de mejora.
... B146: Ver Resumen Aprendizaje Organizacional

Sheet EQUIPO
C1: Conformación de Equipo PAMEC
B3: Ciudad y Fecha
B5: Lugar de reunión
B7: Asistentes
B9: Objetivo | C9: Formalizar la creación del equipo de PAMEC en [Nombre de la institución de salud] y definir sus responsabilidades y funciones.
B11: Reuniones | C11: El equipo de PAMEC se reunirá de manera regular [especificar la frecuencia, por ejemplo, mensual] para revisar y discutir los resultados de sus auditorías y otras actividades.
B13: Recursos | C13: La Gerencia/Dirección se compromete a proporcionar los recursos necesarios, como personal, tiempo y capacitación, para que el equipo de PAMEC pueda llevar a cabo sus funciones de manera efectiva.
B15: Funciones del equipo | C15: El equipo de PAMEC tendrá las siguientes funciones y responsabilidades: • Desarrollar cada una de las etapas de la ruta crítica • Desarrollar los planes de acción definidos a las brechas de calidad identificadas • Realizar un seguimiento regular de la implementación de las acciones para garantizar que se estén llevando a cabo según lo planeado • Proporcionar retroalimentación a los equipos responsables de la implementación y realizar ajustes según sea necesario • Evaluar los resultados de las acciones de mejora implementadas • Comunicar de manera efectiva los resultados y logros al equipo de alta dirección y demás interesados • Promover una cultura de calidad en la institución a través de la capacitación, la sensibilización y la participación activa de los colaboradores en los esfuerzos de mejora continua.
B17: Líder del Equipo (cargo)
B19: Miembros del Equipo (cargo)

Sheet CRONOGRAMA
C1: Cronograma Ruta Crítica
B3: % Cumplimiento de la Ruta Crítica | C3: =IFERROR((COUNT(cronograma[Fecha de fin Real]))/COUNT(cronograma[Fecha de inicio Programada (¿Cuándo?)]),"") | K3: Hoy es: | L3: =TODAY() -> 46176
B4: Actividad (¿Qué?) | C4: Responsable (¿Quién?) | D4: Propósito o Actividad (¿Por Qué?) | E4: Fecha de inicio Programada (¿Cuándo?) | F4: Fecha de fin Programada (¿Cuándo?) | G4: Días estimados | H4: Fecha de inicio Real | I4: Fecha de fin Real | J4: Días reales | K4: % Ejecución | L4: Estado
B5: Actividades de Sensibilización | C5: Líder de calidad- Líderes de procesos | D5: Informar y educar a todos los integrantes de la organización sobre los objetivos, metas y beneficios del PAMEC | G5: =IF(cronograma[[#This Row],[Fecha de fin Programada (¿Cuándo?)]]="","",cronograma[[#This Row],[Fecha de fin Programada (¿Cuándo?)]]-cronograma[[#This Row],[Fecha de inicio Programada (¿Cuándo?)]]) | J5: =IF(cronograma[[#This Row],[Fecha de fin Real]]="","",cronograma[[#This Row],[Fecha de fin Real]]-cronograma[[#This Row],[Fecha de inicio Real]]) | L5: =IF(cronograma[[#This Row],[Fecha de fin Programada (¿Cuándo?)]]="","",IF(cronograma[[#This Row],[Fecha de fin Real]]<>"","Actividad cumplida",IF(TODAY()-F5>0,"Actividad atrasada "&ABS(TODAY()-F5)&" días","Tiene disponibles "&ABS(TODAY()-F5)&" días")))
B6: Conceptualización teórica | C6: Líder de calidad | D6: Proporcionar a los participantes una visión integral de los elementos estructurales que sustentan esta metodología, comprendiendo su importancia y su aplicación práctica | G6: =IF(cronograma[[#This Row],[Fecha de fin Programada (¿Cuándo?)]]="","",cronograma[[#This Row],[Fecha de fin Programada (¿Cuándo?)]]-cronograma[[#This Row],[Fecha de inicio Programada (¿Cuándo?)]]) | J6: =IF(cronograma[[#This Row],[Fecha de fin Real]]="","",cronograma[[#This Row],[Fecha de fin Real]]-cronograma[[#This Row],[Fecha de inicio Real]]) | L6: =IF(cronograma[[#This Row],[Fecha de fin Programada (¿Cuándo?)]]="","",IF(cronograma[[#This Row],[Fecha de fin Real]]<>"","Actividad cumplida",IF(TODAY()-F6>0,"Actividad atrasada "&ABS(TODAY()-F6)&" días","Tiene disponibles "&ABS(TODAY()-F6)&" días")))
B7: Formación equipo PAMEC | C7: Líder de calidad | D7: Identificar y seleccionar a las personas que formarán parte de los equipos de autoevaluación y mejora | G7: =IF(cronograma[[#This Row],[Fecha de fin Programada (¿Cuándo?)]]="","",cronograma[[#This Row],[Fecha de fin Programada (¿Cuándo?)]]-cronograma[[#This Row],[Fecha de inicio Programada (¿Cuándo?)]]) | J7: =IF(cronograma[[#This Row],[Fecha de fin Real]]="","",cronograma[[#This Row],[Fecha de fin Real]]-cronograma[[#This Row],[Fecha de inicio Real]]) | L7: =IF(cronograma[[#This Row],[Fecha de fin Programada (¿Cuándo?)]]="","",IF(cronograma[[#This Row],[Fecha de fin Real]]<>"","Actividad cumplida",IF(TODAY()-F7>0,"Actividad atrasada "&ABS(TODAY()-F7)&" días","Tiene disponibles "&ABS(TODAY()-F7)&" días")))
B8: Autoevaluación | C8: Líderes de procesos | D8: Identificar principales problemas de calidad y oportunidades de mejora | G8: =IF(cronograma[[#This Row],[Fecha de fin Programada (¿Cuándo?)]]="","",cronograma[[#This Row],[Fecha de fin Programada (¿Cuándo?)]]-cronograma[[#This Row],[Fecha de inicio Programada (¿Cuándo?)]]) | J8: =IF(cronograma[[#This Row],[Fecha de fin Real]]="","",cronograma[[#This Row],[Fecha de fin Real]]-cronograma[[#This Row],[Fecha de inicio Real]]) | L8: =IF(cronograma[[#This Row],[Fecha de fin Programada (¿Cuándo?)]]="","",IF(cronograma[[#This Row],[Fecha de fin Real]]<>"","Actividad cumplida",IF(TODAY()-F8>0,"Actividad atrasada "&ABS(TODAY()-F8)&" días","Tiene disponibles "&ABS(TODAY()-F8)&" días")))
B9: Selección de procesos a mejorar | C9: Líderes de procesos | D9: Identificar los procesos a mejorar | G9: =IF(cronograma[[#This Row],[Fecha de fin Programada (¿Cuándo?)]]="","",cronograma[[#This Row],[Fecha de fin Programada (¿Cuándo?)]]-cronograma[[#This Row],[Fecha de inicio Programada (¿Cuándo?)]]) | J9: =IF(cronograma[[#This Row],[Fecha de fin Real]]="","",cronograma[[#This Row],[Fecha de fin Real]]-cronograma[[#This Row],[Fecha de inicio Real]]) | L9: =IF(cronograma[[#This Row],[Fecha de fin Programada (¿Cuándo?)]]="","",IF(cronograma[[#This Row],[Fecha de fin Real]]<>"","Actividad cumplida",IF(TODAY()-F9>0,"Actividad atrasada "&ABS(TODAY()-F9)&" días","Tiene disponibles "&ABS(TODAY()-F9)&" días")))
B10: Priorización de procesos a mejorar | C10: Líderes de procesos | D10: Seleccionar los procesos a intervenir en el corto, mediano y largo plazo | G10: =IF(cronograma[[#This Row],[Fecha de fin Programada (¿Cuándo?)]]="","",cronograma[[#This Row],[Fecha de fin Programada (¿Cuándo?)]]-cronograma[[#This Row],[Fecha de inicio Programada (¿Cuándo?)]]) | J10: =IF(cronograma[[#This Row],[Fecha de fin Real]]="","",cronograma[[#This Row],[Fecha de fin Real]]-cronograma[[#This Row],[Fecha de inicio Real]]) | L10: =IF(cronograma[[#This Row],[Fecha de fin Programada (¿Cuándo?)]]="","",IF(cronograma[[#This Row],[Fecha de fin Real]]<>"","Actividad cumplida",IF(TODAY()-F10>0,"Actividad atrasada "&ABS(TODAY()-F10)&" días","Tiene disponibles "&ABS(TODAY()-F10)&" días")))
B11: Definición de la calidad esperada | C11: Líderes de procesos | D11: Establecer la meta a alcanzar | G11: =IF(cronograma[[#This Row],[Fecha de fin Programada (¿Cuándo?)]]="","",cronograma[[#This Row],[Fecha de fin Programada (¿Cuándo?)]]-cronograma[[#This Row],[Fecha de inicio Programada (¿Cuándo?)]]) | J11: =IF(cronograma[[#This Row],[Fecha de fin Real]]="","",cronograma[[#This Row],[Fecha de fin Real]]-cronograma[[#This Row],[Fecha de inicio Real]]) | L11: =IF(cronograma[[#This Row],[Fecha de fin Programada (¿Cuándo?)]]="","",IF(cronograma[[#This Row],[Fecha de fin Real]]<>"","Actividad cumplida",IF(TODAY()-F11>0,"Actividad atrasada "&ABS(TODAY()-F11)&" días","Tiene disponibles "&ABS(TODAY()-F11)&" días")))
B12: Medición del desempeño de los procesos | C12: Líder de calidad | D12: Definir los procedimientos de auditoría sobre el desempeño de los procesos. | G12: =IF(cronograma[[#This Row],[Fecha de fin Programada (¿Cuándo?)]]="","",cronograma[[#This Row],[Fecha de fin Programada (¿Cuándo?)]]-cronograma[[#This Row],[Fecha de inicio Programada (¿Cuándo?)]]) | J12: =IF(cronograma[[#This Row],[Fecha de fin Real]]="","",cronograma[[#This Row],[Fecha de fin Real]]-cronograma[[#This Row],[Fecha de inicio Real]]) | L12: =IF(cronograma[[#This Row],[Fecha de fin Programada (¿Cuándo?)]]="","",IF(cronograma[[#This Row],[Fecha de fin Real]]<>"","Actividad cumplida",IF(TODAY()-F12>0,"Actividad atrasada "&ABS(TODAY()-F12)&" días","Tiene disponibles "&ABS(TODAY()-F12)&" días")))
B13: Elaboración de planes de acción | C13: Líderes de procesos | D13: Establecer acciones que permitan garantizar el mejoramiento continuo de los procesos y la disminución de la diferencia entre la calidad esperada y la calidad encontrada | G13: =IF(cronograma[[#This Row],[Fecha de fin Programada (¿Cuándo?)]]="","",cronograma[[#This Row],[Fecha de fin Programada (¿Cuándo?)]]-cronograma[[#This Row],[Fecha de inicio Programada (¿Cuándo?)]]) | J13: =IF(cronograma[[#This Row],[Fecha de fin Real]]="","",cronograma[[#This Row],[Fecha de fin Real]]-cronograma[[#This Row],[Fecha de inicio Real]]) | L13: =IF(cronograma[[#This Row],[Fecha de fin Programada (¿Cuándo?)]]="","",IF(cronograma[[#This Row],[Fecha de fin Real]]<>"","Actividad cumplida",IF(TODAY()-F13>0,"Actividad atrasada "&ABS(TODAY()-F13)&" días","Tiene disponibles "&ABS(TODAY()-F13)&" días")))
B14: Ejecución y seguimiento de planes de acción | C14: Líderes de procesos | D14: Garantizar la ejecución de las acciones de mejora establecidas | G14: =IF(cronograma[[#This Row],[Fecha de fin Programada (¿Cuándo?)]]="","",cronograma[[#This Row],[Fecha de fin Programada (¿Cuándo?)]]-cronograma[[#This Row],[Fecha de inicio Programada (¿Cuándo?)]]) | J14: =IF(cronograma[[#This Row],[Fecha de fin Real]]="","",cronograma[[#This Row],[Fecha de fin Real]]-cronograma[[#This Row],[Fecha de inicio Real]]) | L14: =IF(cronograma[[#This Row],[Fecha de fin Programada (¿Cuándo?)]]="","",IF(cronograma[[#This Row],[Fecha de fin Real]]<>"","Actividad cumplida",IF(TODAY()-F14>0,"Actividad atrasada "&ABS(TODAY()-F14)&" días","Tiene disponibles "&ABS(TODAY()-F14)&" días")))
B15: Evaluación del mejoramiento | C15: Líder de calidad | D15: Evaluar el cumplimiento y calidad del programa de auditoria y verificar si los planes de acción fueron eficaces | G15: =IF(cronograma[[#This Row],[Fecha de fin Programada (¿Cuándo?)]]="","",cronograma[[#This Row],[Fecha de fin Programada (¿Cuándo?)]]-cronograma[[#This Row],[Fecha de inicio Programada (¿Cuándo?)]]) | J15: =IF(cronograma[[#This Row],[Fecha de fin Real]]="","",cronograma[[#This Row],[Fecha de fin Real]]-cronograma[[#This Row],[Fecha de inicio Real]]) | L15: =IF(cronograma[[#This Row],[Fecha de fin Programada (¿Cuándo?)]]="","",IF(cronograma[[#This Row],[Fecha de fin Real]]<>"","Actividad cumplida",IF(TODAY()-F15>0,"Actividad atrasada "&ABS(TODAY()-F15)&" días","Tiene disponibles "&ABS(TODAY()-F15)&" días")))
B16: Aprendizaje organizacional | C16: Líderes de procesos | D16: Tomar de decisiones de acuerdo a los resultados obtenidos para realizarle mejoras al proceso Retroalimentar a todo el personal | G16: =IF(cronograma[[#This Row],[Fecha de fin Programada (¿Cuándo?)]]="","",cronograma[[#This Row],[Fecha de fin Programada (¿Cuándo?)]]-cronograma[[#This Row],[Fecha de inicio Programada (¿Cuándo?)]]) | J16: =IF(cronograma[[#This Row],[Fecha de fin Real]]="","",cronograma[[#This Row],[Fecha de fin Real]]-cronograma[[#This Row],[Fecha de inicio Real]]) | L16: =IF(cronograma[[#This Row],[Fecha de fin Programada (¿Cuándo?)]]="","",IF(cronograma[[#This Row],[Fecha de fin Real]]<>"","Actividad cumplida",IF(TODAY()-F16>0,"Actividad atrasada "&ABS(TODAY()-F16)&" días","Tiene disponibles "&ABS(TODAY()-F16)&" días")))

Sheet Datos
A1: Consulta_Externa | B1: Cirugía | C1: Internación | D1: Apoyo_Diagnóstico_Compl._Terapéutica | E1: Atención_Inmediata | F1: COMPLEJIDAD | G1: Fuentes OM | H1: Procesos orden | I1: Procesos | J1: Auxiliar | K1: Orden | L1: Procesos | M1: Cantidad procesos vs OM | O1: Atributos calidad | P1: Valores unicos practicas seguras
A2: 301-ANESTESIA | B2: 201-CIRUGÍA DE CABEZA Y CUELLO | C2: 105-CUIDADO INTERMEDIO NEONATAL | D2: 706-LABORATORIO CLÍNICO | E2: 1101-ATENCIÓN DEL PARTO | F2: Baja | G2: Resultado auditorías Internas | H2: 1 | I2: =proceso1 -> 0 | J2: =IF(I2="",0,I2<>0)*1 -> 0 | K2: =(RANK($J2,$J$2:$J$56,0)+COUNTIF($J$2:$J2,J2)-1)*J2 -> 0 | L2: =IFERROR(INDEX($H$2:$K$51,MATCH(H2,$K$2:$K$51,0),2),"") | M2: =IF(L2<>"",COUNTIFS(cualitativa[[#All],[Proceso 1]:[Proceso 5]],L2),"") | O2: Accesibilidad | P2: {=IFERROR(INDEX(cualitativa[Práctica Segura],MATCH(0,INDEX(COUNTIF($P$1:P1,cualitativa[Práctica Segura]),0,0),0)),"")} -> 0
A3: 302-CARDIOLOGÍA | B3: 202-CIRUGÍA CARDIOVASCULAR | C3: 106-CUIDADO INTERMEDIO PEDIÁTRICO | D3: 709-QUIMIOTERAPIA | E3: 1102-URGENCIAS | F3: Mediana | G3: Resultado Auditorías externas | H3: 2 | I3: =proceso2 -> 0 | J3: =IF(I3="",0,I3<>0)*1 -> 0 | K3: =(RANK($J3,$J$2:$J$56,0)+COUNTIF($J$2:$J3,J3)-1)*J3 -> 0 | L3: =IFERROR(INDEX($H$2:$K$51,MATCH(H3,$K$2:$K$51,0),2),"") | M3: =IF(L3<>"",COUNTIFS(cualitativa[[#All],[Proceso 1]:[Proceso 5]],L3),"") | O3: Continuidad | P3: {=IFERROR(INDEX(cualitativa[Práctica Segura],MATCH(0,INDEX(COUNTIF($P$1:P2,cualitativa[Práctica Segura]),0,0),0)),"")}
A4: 361-CARDIOLOGÍA PEDIÁTRICA | B4: 203-CIRUGÍA GENERAL | C4: 107-CUIDADO INTERMEDIO ADULTOS | D4: 711-RADIOTERAPIA | E4: 1103-TRANSPORTE ASISTENCIAL BASICO | F4: Alta | G4: Comités Institucionales | H4: 3 | I4: =proceso3 -> 0 | J4: =IF(I4="",0,I4<>0)*1 -> 0 | K4: =(RANK($J4,$J$2:$J$56,0)+COUNTIF($J$2:$J4,J4)-1)*J4 -> 0 | L4: =IFERROR(INDEX($H$2:$K$51,MATCH(H4,$K$2:$K$51,0),2),"") | M4: =IF(L4<>"",COUNTIFS(cualitativa[[#All],[Proceso 1]:[Proceso 5]],L4),"") | O4: Oportunidad | P4: {=IFERROR(INDEX(cualitativa[Práctica Segura],MATCH(0,INDEX(COUNTIF($P$1:P3,cualitativa[Práctica Segura]),0,0),0)),"")}
A5: 303-CIRUGÍA CARDIOVASCULAR | B5: 204-CIRUGÍA GINECOLÓGICA | C5: 108-CUIDADO INTENSIVO NEONATAL | D5: 712-TOMA DE MUESTRAS DE LABORATORIO CLÍNICO | E5: 1104-TRANSPORTE ASISTENCIAL MEDICALIZADO | F5: Sin complejidad | G5: Resultado de Indicadores | H5: 4 | I5: =proceso4 -> 0 | J5: =IF(I5="",0,I5<>0)*1 -> 0 | K5: =(RANK($J5,$J$2:$J$56,0)+COUNTIF($J$2:$J5,J5)-1)*J5 -> 0 | L5: =IFERROR(INDEX($H$2:$K$51,MATCH(H5,$K$2:$K$51,0),2),"") | M5: =IF(L5<>"",COUNTIFS(cualitativa[[#All],[Proceso 1]:[Proceso 5]],L5),"") | O5: Pertinencia | P5: {=IFERROR(INDEX(cualitativa[Práctica Segura],MATCH(0,INDEX(COUNTIF($P$1:P4,cualitativa[Práctica Segura]),0,0),0)),"")}
A6: 362-CIRUGÍA DE CABEZA Y CUELLO | B6: 205-CIRUGÍA MAXILOFACIAL | C6: 109-CUIDADO INTENSIVO PEDIÁTRICO | D6: 714-SERVICIO FARMACÉUTICO | E6: 1105-ATENCIÓN PREHOSPITALARIA | G6: Voz del cliente | H6: 5 | I6: =proceso5 -> 0 | J6: =IF(I6="",0,I6<>0)*1 -> 0 | K6: =(RANK($J6,$J$2:$J$56,0)+COUNTIF($J$2:$J6,J6)-1)*J6 -> 0 | L6: =IFERROR(INDEX($H$2:$K$51,MATCH(H6,$K$2:$K$51,0),2),"") | M6: =IF(L6<>"",COUNTIFS(cualitativa[[#All],[Proceso 1]:[Proceso 5]],L6),"") | O6: Satisfacción del Usuario | P6: {=IFERROR(INDEX(cualitativa[Práctica Segura],MATCH(0,INDEX(COUNTIF($P$1:P5,cualitativa[Práctica Segura]),0,0),0)),"")}
A7: 364-CIRUGÍA DE MAMA Y TUMORES TEJIDOS BLANDOS | B7: 207-CIRUGÍA ORTOPÉDICA | C7: 110-CUIDADO INTENSIVO ADULTOS | D7: 715-MEDICINA NUCLEAR | G7: Mejoramiento continuo | H7: 6 | I7: =proceso6 -> 0 | J7: =IF(I7="",0,I7<>0)*1 -> 0 | K7: =(RANK($J7,$J$2:$J$56,0)+COUNTIF($J$2:$J7,J7)-1)*J7 -> 0 | L7: =IFERROR(INDEX($H$2:$K$51,MATCH(H7,$K$2:$K$51,0),2),"") | M7: =IF(L7<>"",COUNTIFS(cualitativa[[#All],[Proceso 1]:[Proceso 5]],L7),"") | O7: Seguridad | P7: {=IFERROR(INDEX(cualitativa[Práctica Segura],MATCH(0,INDEX(COUNTIF($P$1:P6,cualitativa[Práctica Segura]),0,0),0)),"")}
A8: 363-CIRUGÍA DE MANO | B8: 208-CIRUGÍA OFTALMOLÓGICA | C8: 120-CUIDADO BÁSICO NEONATAL | D8: 717-LABORATORIO CITOLOGÍAS CERVICO-UTERINAS | H8: 7 | I8: =proceso7 -> 0 | J8: =IF(I8="",0,I8<>0)*1 -> 0 | K8: =(RANK($J8,$J$2:$J$56,0)+COUNTIF($J$2:$J8,J8)-1)*J8 -> 0 | L8: =IFERROR(INDEX($H$2:$K$51,MATCH(H8,$K$2:$K$51,0),2),"") | M8: =IF(L8<>"",COUNTIFS(cualitativa[[#All],[Proceso 1]:[Proceso 5]],L8),"") | P8: {=IFERROR(INDEX(cualitativa[Práctica Segura],MATCH(0,INDEX(COUNTIF($P$1:P7,cualitativa[Práctica Segura]),0,0),0)),"")}
A9: 366-CIRUGÍA DE TÓRAX | B9: 209-CIRUGÍA OTORRINOLARINGOLOGÍA | C9: 129-HOSPITALIZACIÓN ADULTOS | D9: 728-TERAPIA OCUPACIONAL | H9: 8 | I9: =proceso8 -> 0 | J9: =IF(I9="",0,I9<>0)*1 -> 0 | K9: =(RANK($J9,$J$2:$J$56,0)+COUNTIF($J$2:$J9,J9)-1)*J9 -> 0 | L9: =IFERROR(INDEX($H$2:$K$51,MATCH(H9,$K$2:$K$51,0),2),"") | M9: =IF(L9<>"",COUNTIFS(cualitativa[[#All],[Proceso 1]:[Proceso 5]],L9),"") | P9: {=IFERROR(INDEX(cualitativa[Práctica Segura],MATCH(0,INDEX(COUNTIF($P$1:P8,cualitativa[Práctica Segura]),0,0),0)),"")}
A10: 365-CIRUGÍA DERMATOLÓGICA | B10: 210-CIRUGÍA ONCOLÓGICA | C10: 130-HOSPITALIZACIÓN PEDIÁTRICA | D10: 729-TERAPIA RESPIRATORIA | H10: 9 | I10: =proceso9 -> 0 | J10: =IF(I10="",0,I10<>0)*1 -> 0 | K10: =(RANK($J10,$J$2:$J$56,0)+COUNTIF($J$2:$J10,J10)-1)*J10 -> 0 | L10: =IFERROR(INDEX($H$2:$K$51,MATCH(H10,$K$2:$K$51,0),2),"") | M10: =IF(L10<>"",COUNTIFS(cualitativa[[#All],[Proceso 1]:[Proceso 5]],L10),"") | P10: {=IFERROR(INDEX(cualitativa[Práctica Segura],MATCH(0,INDEX(COUNTIF($P$1:P9,cualitativa[Práctica Segura]),0,0),0)),"")}
A11: 367-CIRUGÍA GASTROINTESTINAL | B11: 211-CIRUGÍA ORAL | C11: 131-HOSPITALIZACIÓN EN SALUD MENTAL | D11: 731-LABORATORIO DE HISTOTECNOLOGÍA | H11: 10 | I11: =proceso10 -> 0 | J11: =IF(I11="",0,I11<>0)*1 -> 0 | K11: =(RANK($J11,$J$2:$J$56,0)+COUNTIF($J$2:$J11,J11)-1)*J11 -> 0 | L11: =IFERROR(INDEX($H$2:$K$51,MATCH(H11,$K$2:$K$51,0),2),"") | M11: =IF(L11<>"",COUNTIFS(cualitativa[[#All],[Proceso 1]:[Proceso 5]],L11),"") | P11: {=IFERROR(INDEX(cualitativa[Práctica Segura],MATCH(0,INDEX(COUNTIF($P$1:P10,cualitativa[Práctica Segura]),0,0),0)),"")}
A12: 304-CIRUGÍA GENERAL | B12: 212-CIRUGÍA PEDIÁTRICA | C12: 132-HOSPITALIZACIÓN PARCIAL | D12: 733-HEMODIÁLISIS | H12: 11 | I12: =proceso11 -> 0 | J12: =IF(I12="",0,I12<>0)*1 -> 0 | K12: =(RANK($J12,$J$2:$J$56,0)+COUNTIF($J$2:$J12,J12)-1)*J12 -> 0 | L12: =IFERROR(INDEX($H$2:$K$51,MATCH(H12,$K$2:$K$51,0),2),"") | M12: =IF(L12<>"",COUNTIFS(cualitativa[[#All],[Proceso 1]:[Proceso 5]],L12),"") | P12: {=IFERROR(INDEX(cualitativa[Práctica Segura],MATCH(0,INDEX(COUNTIF($P$1:P11,cualitativa[Práctica Segura]),0,0),0)),"")}
A13: 368-CIRUGÍA GINECOLÓGICA LAPAROSCÓPICA | B13: 213-CIRUGÍA PLÁSTICA Y ESTÉTICA | C13: 133-HOSPITALIZACIÓN PACIENTE CRÓNICO CON VENTILADOR | D13: 734-DIÁLISIS PERITONEAL | H13: 12 | I13: =proceso12 -> 0 | J13: =IF(I13="",0,I13<>0)*1 -> 0 | K13: =(RANK($J13,$J$2:$J$56,0)+COUNTIF($J$2:$J13,J13)-1)*J13 -> 0 | L13: =IFERROR(INDEX($H$2:$K$51,MATCH(H13,$K$2:$K$51,0),2),"") | M13: =IF(L13<>"",COUNTIFS(cualitativa[[#All],[Proceso 1]:[Proceso 5]],L13),"") | P13: {=IFERROR(INDEX(cualitativa[Práctica Segura],MATCH(0,INDEX(COUNTIF($P$1:P12,cualitativa[Práctica Segura]),0,0),0)),"")}
A14: 411-CIRUGÍA MAXILOFACIAL | B14: 214-CIRUGÍA VASCULAR Y ANGIOLÓGICA | C14: 134-HOSPITALIZACIÓN PACIENTE CRÓNICO SIN VENTILADOR | D14: 739-FISIOTERAPIA | H14: 13 | I14: =proceso13 -> 0 | J14: =IF(I14="",0,I14<>0)*1 -> 0 | K14: =(RANK($J14,$J$2:$J$56,0)+COUNTIF($J$2:$J14,J14)-1)*J14 -> 0 | L14: =IFERROR(INDEX($H$2:$K$51,MATCH(H14,$K$2:$K$51,0),2),"") | M14: =IF(L14<>"",COUNTIFS(cualitativa[[#All],[Proceso 1]:[Proceso 5]],L14),"") | P14: {=IFERROR(INDEX(cualitativa[Práctica Segura],MATCH(0,INDEX(COUNTIF($P$1:P13,cualitativa[Práctica Segura]),0,0),0)),"")}
A15: 373-CIRUGÍA ONCOLÓGICA | B15: 215-CIRUGÍA UROLÓGICA | C15: 135-HOSPITALIZACIÓN EN CONSUMO DE SUSTANCIAS PSICOACTIVAS | D15: 740-FONOAUDIOLOGÍA Y/O TERAPIA DEL LENGUAJE | H15: 14 | I15: =proceso14 -> 0 | J15: =IF(I15="",0,I15<>0)*1 -> 0 | K15: =(RANK($J15,$J$2:$J$56,0)+COUNTIF($J$2:$J15,J15)-1)*J15 -> 0 | L15: =IFERROR(INDEX($H$2:$K$51,MATCH(H15,$K$2:$K$51,0),2),"") | M15: =IF(L15<>"",COUNTIFS(cualitativa[[#All],[Proceso 1]:[Proceso 5]],L15),"") | P15: {=IFERROR(INDEX(cualitativa[Práctica Segura],MATCH(0,INDEX(COUNTIF($P$1:P14,cualitativa[Práctica Segura]),0,0),0)),"")}
A16: 374-CIRUGÍA ONCOLÓGICA PEDIÁTRICA | B16: 217-OTRAS CIRUGÍAS | C16: 138-CUIDADO BÁSICO DEL CONSUMO DE SUSTANCIAS PSICOACTIVAS | D16: 742-DIAGNÓSTICO VASCULAR | H16: 15 | I16: =proceso15 -> 0 | J16: =IF(I16="",0,I16<>0)*1 -> 0 | K16: =(RANK($J16,$J$2:$J$56,0)+COUNTIF($J$2:$J16,J16)-1)*J16 -> 0 | L16: =IFERROR(INDEX($H$2:$K$51,MATCH(H16,$K$2:$K$51,0),2),"") | M16: =IF(L16<>"",COUNTIFS(cualitativa[[#All],[Proceso 1]:[Proceso 5]],L16),"") | P16: {=IFERROR(INDEX(cualitativa[Práctica Segura],MATCH(0,INDEX(COUNTIF($P$1:P15,cualitativa[Práctica Segura]),0,0),0)),"")}
A17: 410-CIRUGÍA ORAL | B17: 218-CIRUGÍA ENDOVASCULAR NEUROLÓGICA | D17: 743-HEMODINAMIA E INTERVENCIONISMO | H17: 16 | I17: =proceso16 -> 0 | J17: =IF(I17="",0,I17<>0)*1 -> 0 | K17: =(RANK($J17,$J$2:$J$56,0)+COUNTIF($J$2:$J17,J17)-1)*J17 -> 0 | L17: =IFERROR(INDEX($H$2:$K$51,MATCH(H17,$K$2:$K$51,0),2),"") | M17: =IF(L17<>"",COUNTIFS(cualitativa[[#All],[Proceso 1]:[Proceso 5]],L17),"") | P17: {=IFERROR(INDEX(cualitativa[Práctica Segura],MATCH(0,INDEX(COUNTIF($P$1:P16,cualitativa[Práctica Segura]),0,0),0)),"")}
A18: 306-CIRUGÍA PEDIÁTRICA | B18: 227-CIRUGÍA ONCOLÓGICA PEDIÁTRICA | D18: 744-IMÁGENES DIAGNOSTICAS- IONIZANTES | H18: 17 | I18: =proceso17 -> 0 | J18: =IF(I18="",0,I18<>0)*1 -> 0 | K18: =(RANK($J18,$J$2:$J$56,0)+COUNTIF($J$2:$J18,J18)-1)*J18 -> 0 | L18: =IFERROR(INDEX($H$2:$K$51,MATCH(H18,$K$2:$K$51,0),2),"") | M18: =IF(L18<>"",COUNTIFS(cualitativa[[#All],[Proceso 1]:[Proceso 5]],L18),"") | P18: {=IFERROR(INDEX(cualitativa[Práctica Segura],MATCH(0,INDEX(COUNTIF($P$1:P17,cualitativa[Práctica Segura]),0,0),0)),"")}
A19: 370-CIRUGÍA PLÁSTICA ONCOLÓGICA | B19: 231-CIRUGÍA DE LA MANO | D19: 745-IMÁGENES DIAGNOSTICAS - NO IONIZANTES | H19: 18 | I19: =proceso18 -> 0 | J19: =IF(I19="",0,I19<>0)*1 -> 0 | K19: =(RANK($J19,$J$2:$J$56,0)+COUNTIF($J$2:$J19,J19)-1)*J19 -> 0 | L19: =IFERROR(INDEX($H$2:$K$51,MATCH(H19,$K$2:$K$51,0),2),"") | M19: =IF(L19<>"",COUNTIFS(cualitativa[[#All],[Proceso 1]:[Proceso 5]],L19),"") | P19: {=IFERROR(INDEX(cualitativa[Práctica Segura],MATCH(0,INDEX(COUNTIF($P$1:P18,cualitativa[Práctica Segura]),0,0),0)),"")}
A20: 369-CIRUGÍA PLÁSTICA Y ESTÉTICA | B20: 232-CIRUGÍA DE MAMA Y TUMORES TEJIDOS BLANDOS | D20: 746-GESTION PRE-TRANSFUSIONAL | H20: 19 | I20: =proceso19 -> 0 | J20: =IF(I20="",0,I20<>0)*1 -> 0 | K20: =(RANK($J20,$J$2:$J$56,0)+COUNTIF($J$2:$J20,J20)-1)*J20 -> 0 | L20: =IFERROR(INDEX($H$2:$K$51,MATCH(H20,$K$2:$K$51,0),2),"") | M20: =IF(L20<>"",COUNTIFS(cualitativa[[#All],[Proceso 1]:[Proceso 5]],L20),"") | P20: {=IFERROR(INDEX(cualitativa[Práctica Segura],MATCH(0,INDEX(COUNTIF($P$1:P19,cualitativa[Práctica Segura]),0,0),0)),"")}
A21: 372-CIRUGÍA VASCULAR | B21: 233-CIRUGÍA DERMATOLÓGICA | D21: 747-PATOLOGÍA | H21: 20 | I21: =proceso20 -> 0 | J21: =IF(I21="",0,I21<>0)*1 -> 0 | K21: =(RANK($J21,$J$2:$J$56,0)+COUNTIF($J$2:$J21,J21)-1)*J21 -> 0 | L21: =IFERROR(INDEX($H$2:$K$51,MATCH(H21,$K$2:$K$51,0),2),"") | M21: =IF(L21<>"",COUNTIFS(cualitativa[[#All],[Proceso 1]:[Proceso 5]],L21),"") | P21: {=IFERROR(INDEX(cualitativa[Práctica Segura],MATCH(0,INDEX(COUNTIF($P$1:P20,cualitativa[Práctica Segura]),0,0),0)),"")}
A22: 377-COLOPROCTOLOGÍA | B22: 234-CIRUGÍA DE TÓRAX | D22: 748-RADIOLOGÍA ODONTOLÓGICA | H22: 21 | I22: =proceso21 -> 0 | J22: =IF(I22="",0,I22<>0)*1 -> 0 | K22: =(RANK($J22,$J$2:$J$56,0)+COUNTIF($J$2:$J22,J22)-1)*J22 -> 0 | L22: =IFERROR(INDEX($H$2:$K$51,MATCH(H22,$K$2:$K$51,0),2),"") | M22: =IF(L22<>"",COUNTIFS(cualitativa[[#All],[Proceso 1]:[Proceso 5]],L22),"") | P22: {=IFERROR(INDEX(cualitativa[Práctica Segura],MATCH(0,INDEX(COUNTIF($P$1:P21,cualitativa[Práctica Segura]),0,0),0)),"")}
A23: 308-DERMATOLOGÍA | B23: 235-CIRUGÍA GASTROINTESTINAL | D23: 749-TOMA DE MUESTRAS DE CUELLO UTERINO Y GINECOLÓGICAS | H23: 22 | I23: =proceso22 -> 0 | J23: =IF(I23="",0,I23<>0)*1 -> 0 | K23: =(RANK($J23,$J$2:$J$56,0)+COUNTIF($J$2:$J23,J23)-1)*J23 -> 0 | L23: =IFERROR(INDEX($H$2:$K$51,MATCH(H23,$K$2:$K$51,0),2),"") | M23: =IF(L23<>"",COUNTIFS(cualitativa[[#All],[Proceso 1]:[Proceso 5]],L23),"") | P23: {=IFERROR(INDEX(cualitativa[Práctica Segura],MATCH(0,INDEX(COUNTIF($P$1:P22,cualitativa[Práctica Segura]),0,0),0)),"")}
A24: 375-DERMATOLOGÍA ONCOLÓGICA | B24: 237-CIRUGÍA PLÁSTICA ONCOLÓGICA | H24: 23 | I24: =proceso23 -> 0 | J24: =IF(I24="",0,I24<>0)*1 -> 0 | K24: =(RANK($J24,$J$2:$J$56,0)+COUNTIF($J$2:$J24,J24)-1)*J24 -> 0 | L24: =IFERROR(INDEX($H$2:$K$51,MATCH(H24,$K$2:$K$51,0),2),"") | M24: =IF(L24<>"",COUNTIFS(cualitativa[[#All],[Proceso 1]:[Proceso 5]],L24),"") | P24: {=IFERROR(INDEX(cualitativa[Práctica Segura],MATCH(0,INDEX(COUNTIF($P$1:P23,cualitativa[Práctica Segura]),0,0),0)),"")}
A25: 309-DOLOR Y CUIDADOS PALIATIVOS | B25: 245-NEUROCIRUGÍA | H25: 24 | I25: =proceso24 -> 0 | J25: =IF(I25="",0,I25<>0)*1 -> 0 | K25: =(RANK($J25,$J$2:$J$56,0)+COUNTIF($J$2:$J25,J25)-1)*J25 -> 0 | L25: =IFERROR(INDEX($H$2:$K$51,MATCH(H25,$K$2:$K$51,0),2),"") | M25: =IF(L25<>"",COUNTIFS(cualitativa[[#All],[Proceso 1]:[Proceso 5]],L25),"") | P25: {=IFERROR(INDEX(cualitativa[Práctica Segura],MATCH(0,INDEX(COUNTIF($P$1:P24,cualitativa[Práctica Segura]),0,0),0)),"")}
A26: 310-ENDOCRINOLOGÍA | H26: 25 | I26: =proceso25 -> 0 | J26: =IF(I26="",0,I26<>0)*1 -> 0 | K26: =(RANK($J26,$J$2:$J$56,0)+COUNTIF($J$2:$J26,J26)-1)*J26 -> 0 | L26: =IFERROR(INDEX($H$2:$K$51,MATCH(H26,$K$2:$K$51,0),2),"") | M26: =IF(L26<>"",COUNTIFS(cualitativa[[#All],[Proceso 1]:[Proceso 5]],L26),"") | P26: {=IFERROR(INDEX(cualitativa[Práctica Segura],MATCH(0,INDEX(COUNTIF($P$1:P25,cualitativa[Práctica Segura]),0,0),0)),"")}
A27: 311-ENDODONCIA | H27: 26 | I27: =proceso26 -> 0 | J27: =IF(I27="",0,I27<>0)*1 -> 0 | K27: =(RANK($J27,$J$2:$J$56,0)+COUNTIF($J$2:$J27,J27)-1)*J27 -> 0 | L27: =IFERROR(INDEX($H$2:$K$51,MATCH(H27,$K$2:$K$51,0),2),"") | M27: =IF(L27<>"",COUNTIFS(cualitativa[[#All],[Proceso 1]:[Proceso 5]],L27),"") | P27: {=IFERROR(INDEX(cualitativa[Práctica Segura],MATCH(0,INDEX(COUNTIF($P$1:P26,cualitativa[Práctica Segura]),0,0),0)),"")}
A28: 312-ENFERMERÍA | H28: 27 | I28: =proceso27 -> 0 | J28: =IF(I28="",0,I28<>0)*1 -> 0 | K28: =(RANK($J28,$J$2:$J$56,0)+COUNTIF($J$2:$J28,J28)-1)*J28 -> 0 | L28: =IFERROR(INDEX($H$2:$K$51,MATCH(H28,$K$2:$K$51,0),2),"") | M28: =IF(L28<>"",COUNTIFS(cualitativa[[#All],[Proceso 1]:[Proceso 5]],L28),"") | P28: {=IFERROR(INDEX(cualitativa[Práctica Segura],MATCH(0,INDEX(COUNTIF($P$1:P27,cualitativa[Práctica Segura]),0,0),0)),"")}
A29: 313-ESTOMATOLOGÍA | H29: 28 | I29: =proceso28 -> 0 | J29: =IF(I29="",0,I29<>0)*1 -> 0 | K29: =(RANK($J29,$J$2:$J$56,0)+COUNTIF($J$2:$J29,J29)-1)*J29 -> 0 | L29: =IFERROR(INDEX($H$2:$K$51,MATCH(H29,$K$2:$K$51,0),2),"") | M29: =IF(L29<>"",COUNTIFS(cualitativa[[#All],[Proceso 1]:[Proceso 5]],L29),"") | P29: {=IFERROR(INDEX(cualitativa[Práctica Segura],MATCH(0,INDEX(COUNTIF($P$1:P28,cualitativa[Práctica Segura]),0,0),0)),"")}
A30: 316-GASTROENTEROLOGÍA | H30: 29 | I30: =proceso29 -> 0 | J30: =IF(I30="",0,I30<>0)*1 -> 0 | K30: =(RANK($J30,$J$2:$J$56,0)+COUNTIF($J$2:$J30,J30)-1)*J30 -> 0 | L30: =IFERROR(INDEX($H$2:$K$51,MATCH(H30,$K$2:$K$51,0),2),"") | M30: =IF(L30<>"",COUNTIFS(cualitativa[[#All],[Proceso 1]:[Proceso 5]],L30),"") | P30: {=IFERROR(INDEX(cualitativa[Práctica Segura],MATCH(0,INDEX(COUNTIF($P$1:P29,cualitativa[Práctica Segura]),0,0),0)),"")}
A31: 317-GENÉTICA | H31: 30 | I31: =proceso30 -> 0 | J31: =IF(I31="",0,I31<>0)*1 -> 0 | K31: =(RANK($J31,$J$2:$J$56,0)+COUNTIF($J$2:$J31,J31)-1)*J31 -> 0 | L31: =IFERROR(INDEX($H$2:$K$51,MATCH(H31,$K$2:$K$51,0),2),"") | M31: =IF(L31<>"",COUNTIFS(cualitativa[[#All],[Proceso 1]:[Proceso 5]],L31),"") | P31: {=IFERROR(INDEX(cualitativa[Práctica Segura],MATCH(0,INDEX(COUNTIF($P$1:P30,cualitativa[Práctica Segura]),0,0),0)),"")}
A32: 318-GERIATRÍA | H32: 31 | I32: =proceso31 -> 0 | J32: =IF(I32="",0,I32<>0)*1 -> 0 | K32: =(RANK($J32,$J$2:$J$56,0)+COUNTIF($J$2:$J32,J32)-1)*J32 -> 0 | L32: =IFERROR(INDEX($H$2:$K$51,MATCH(H32,$K$2:$K$51,0),2),"") | M32: =IF(L32<>"",COUNTIFS(cualitativa[[#All],[Proceso 1]:[Proceso 5]],L32),"") | P32: {=IFERROR(INDEX(cualitativa[Práctica Segura],MATCH(0,INDEX(COUNTIF($P$1:P31,cualitativa[Práctica Segura]),0,0),0)),"")}
A33: 320-GINECOBSTETRICIA | H33: 32 | I33: =proceso32 -> 0 | J33: =IF(I33="",0,I33<>0)*1 -> 0 | K33: =(RANK($J33,$J$2:$J$56,0)+COUNTIF($J$2:$J33,J33)-1)*J33 -> 0 | L33: =IFERROR(INDEX($H$2:$K$51,MATCH(H33,$K$2:$K$51,0),2),"") | M33: =IF(L33<>"",COUNTIFS(cualitativa[[#All],[Proceso 1]:[Proceso 5]],L33),"") | P33: {=IFERROR(INDEX(cualitativa[Práctica Segura],MATCH(0,INDEX(COUNTIF($P$1:P32,cualitativa[Práctica Segura]),0,0),0)),"")}
A34: 379-GINECOLOGÍA ONCOLÓGICA | H34: 33 | I34: =proceso33 -> 0 | J34: =IF(I34="",0,I34<>0)*1 -> 0 | K34: =(RANK($J34,$J$2:$J$56,0)+COUNTIF($J$2:$J34,J34)-1)*J34 -> 0 | L34: =IFERROR(INDEX($H$2:$K$51,MATCH(H34,$K$2:$K$51,0),2),"") | M34: =IF(L34<>"",COUNTIFS(cualitativa[[#All],[Proceso 1]:[Proceso 5]],L34),"") | P34: {=IFERROR(INDEX(cualitativa[Práctica Segura],MATCH(0,INDEX(COUNTIF($P$1:P33,cualitativa[Práctica Segura]),0,0),0)),"")}
A35: 321-HEMATOLOGÍA | H35: 34 | I35: =proceso34 -> 0 | J35: =IF(I35="",0,I35<>0)*1 -> 0 | K35: =(RANK($J35,$J$2:$J$56,0)+COUNTIF($J$2:$J35,J35)-1)*J35 -> 0 | L35: =IFERROR(INDEX($H$2:$K$51,MATCH(H35,$K$2:$K$51,0),2),"") | M35: =IF(L35<>"",COUNTIFS(cualitativa[[#All],[Proceso 1]:[Proceso 5]],L35),"") | P35: {=IFERROR(INDEX(cualitativa[Práctica Segura],MATCH(0,INDEX(COUNTIF($P$1:P34,cualitativa[Práctica Segura]),0,0),0)),"")}
A36: 406-HEMATOLOGÍA ONCOLÓGICA | H36: 35 | I36: =proceso35 -> 0 | J36: =IF(I36="",0,I36<>0)*1 -> 0 | K36: =(RANK($J36,$J$2:$J$56,0)+COUNTIF($J$2:$J36,J36)-1)*J36 -> 0 | L36: =IFERROR(INDEX($H$2:$K$51,MATCH(H36,$K$2:$K$51,0),2),"") | M36: =IF(L36<>"",COUNTIFS(cualitativa[[#All],[Proceso 1]:[Proceso 5]],L36),"") | P36: {=IFERROR(INDEX(cualitativa[Práctica Segura],MATCH(0,INDEX(COUNTIF($P$1:P35,cualitativa[Práctica Segura]),0,0),0)),"")}
A37: 323-INFECTOLOGÍA | H37: 36 | I37: =proceso36 -> 0 | J37: =IF(I37="",0,I37<>0)*1 -> 0 | K37: =(RANK($J37,$J$2:$J$56,0)+COUNTIF($J$2:$J37,J37)-1)*J37 -> 0 | L37: =IFERROR(INDEX($H$2:$K$51,MATCH(H37,$K$2:$K$51,0),2),"") | M37: =IF(L37<>"",COUNTIFS(cualitativa[[#All],[Proceso 1]:[Proceso 5]],L37),"") | P37: {=IFERROR(INDEX(cualitativa[Práctica Segura],MATCH(0,INDEX(COUNTIF($P$1:P36,cualitativa[Práctica Segura]),0,0),0)),"")}
A38: 324-INMUNOLOGÍA | H38: 37 | I38: =proceso37 -> 0 | J38: =IF(I38="",0,I38<>0)*1 -> 0 | K38: =(RANK($J38,$J$2:$J$56,0)+COUNTIF($J$2:$J38,J38)-1)*J38 -> 0 | L38: =IFERROR(INDEX($H$2:$K$51,MATCH(H38,$K$2:$K$51,0),2),"") | M38: =IF(L38<>"",COUNTIFS(cualitativa[[#All],[Proceso 1]:[Proceso 5]],L38),"") | P38: {=IFERROR(INDEX(cualitativa[Práctica Segura],MATCH(0,INDEX(COUNTIF($P$1:P37,cualitativa[Práctica Segura]),0,0),0)),"")}
A39: 413-MEDICINA ALTERNATIVA Y COMPLEMENTARIA - AYURVÉDICA | H39: 38 | I39: =proceso38 -> 0 | J39: =IF(I39="",0,I39<>0)*1 -> 0 | K39: =(RANK($J39,$J$2:$J$56,0)+COUNTIF($J$2:$J39,J39)-1)*J39 -> 0 | L39: =IFERROR(INDEX($H$2:$K$51,MATCH(H39,$K$2:$K$51,0),2),"") | M39: =IF(L39<>"",COUNTIFS(cualitativa[[#All],[Proceso 1]:[Proceso 5]],L39),"") | P39: {=IFERROR(INDEX(cualitativa[Práctica Segura],MATCH(0,INDEX(COUNTIF($P$1:P38,cualitativa[Práctica Segura]),0,0),0)),"")}
A40: 412-MEDICINA ALTERNATIVA Y COMPLEMENTARIA - HOMEOPÁTICA | H40: 39 | I40: =proceso39 -> 0 | J40: =IF(I40="",0,I40<>0)*1 -> 0 | K40: =(RANK($J40,$J$2:$J$56,0)+COUNTIF($J$2:$J40,J40)-1)*J40 -> 0 | L40: =IFERROR(INDEX($H$2:$K$51,MATCH(H40,$K$2:$K$51,0),2),"") | M40: =IF(L40<>"",COUNTIFS(cualitativa[[#All],[Proceso 1]:[Proceso 5]],L40),"") | P40: {=IFERROR(INDEX(cualitativa[Práctica Segura],MATCH(0,INDEX(COUNTIF($P$1:P39,cualitativa[Práctica Segura]),0,0),0)),"")}
A41: 415-MEDICINA ALTERNATIVA Y COMPLEMENTARIA - NATUROPÁTICA | H41: 40 | I41: =proceso40 -> 0 | J41: =IF(I41="",0,I41<>0)*1 -> 0 | K41: =(RANK($J41,$J$2:$J$56,0)+COUNTIF($J$2:$J41,J41)-1)*J41 -> 0 | L41: =IFERROR(INDEX($H$2:$K$51,MATCH(H41,$K$2:$K$51,0),2),"") | M41: =IF(L41<>"",COUNTIFS(cualitativa[[#All],[Proceso 1]:[Proceso 5]],L41),"") | P41: {=IFERROR(INDEX(cualitativa[Práctica Segura],MATCH(0,INDEX(COUNTIF($P$1:P40,cualitativa[Práctica Segura]),0,0),0)),"")}
A42: 416-MEDICINA ALTERNATIVA Y COMPLEMENTARIA - NEURALTERAPÉUTICA | H42: 41 | I42: =proceso41 -> 0 | J42: =IF(I42="",0,I42<>0)*1 -> 0 | K42: =(RANK($J42,$J$2:$J$56,0)+COUNTIF($J$2:$J42,J42)-1)*J42 -> 0 | L42: =IFERROR(INDEX($H$2:$K$51,MATCH(H42,$K$2:$K$51,0),2),"") | M42: =IF(L42<>"",COUNTIFS(cualitativa[[#All],[Proceso 1]:[Proceso 5]],L42),"") | P42: {=IFERROR(INDEX(cualitativa[Práctica Segura],MATCH(0,INDEX(COUNTIF($P$1:P41,cualitativa[Práctica Segura]),0,0),0)),"")}
A43: 422-MEDICINA ALTERNATIVA Y COMPLEMENTARIA - OSTEOPÁTICA | H43: 42 | I43: =proceso42 -> 0 | J43: =IF(I43="",0,I43<>0)*1 -> 0 | K43: =(RANK($J43,$J$2:$J$56,0)+COUNTIF($J$2:$J43,J43)-1)*J43 -> 0 | L43: =IFERROR(INDEX($H$2:$K$51,MATCH(H43,$K$2:$K$51,0),2),"") | M43: =IF(L43<>"",COUNTIFS(cualitativa[[#All],[Proceso 1]:[Proceso 5]],L43),"") | P43: {=IFERROR(INDEX(cualitativa[Práctica Segura],MATCH(0,INDEX(COUNTIF($P$1:P42,cualitativa[Práctica Segura]),0,0),0)),"")}
A44: 414-MEDICINA ALTERNATIVA Y COMPLEMENTARIA - TRADICIONAL CHINA | H44: 43 | I44: =proceso43 -> 0 | J44: =IF(I44="",0,I44<>0)*1 -> 0 | K44: =(RANK($J44,$J$2:$J$56,0)+COUNTIF($J$2:$J44,J44)-1)*J44 -> 0 | L44: =IFERROR(INDEX($H$2:$K$51,MATCH(H44,$K$2:$K$51,0),2),"") | M44: =IF(L44<>"",COUNTIFS(cualitativa[[#All],[Proceso 1]:[Proceso 5]],L44),"") | P44: {=IFERROR(INDEX(cualitativa[Práctica Segura],MATCH(0,INDEX(COUNTIF($P$1:P43,cualitativa[Práctica Segura]),0,0),0)),"")}
A45: 407-MEDICINA DEL TRABAJO Y MEDICINA LABORAL | H45: 44 | I45: =proceso44 -> 0 | J45: =IF(I45="",0,I45<>0)*1 -> 0 | K45: =(RANK($J45,$J$2:$J$56,0)+COUNTIF($J$2:$J45,J45)-1)*J45 -> 0 | L45: =IFERROR(INDEX($H$2:$K$51,MATCH(H45,$K$2:$K$51,0),2),"") | M45: =IF(L45<>"",COUNTIFS(cualitativa[[#All],[Proceso 1]:[Proceso 5]],L45),"") | P45: {=IFERROR(INDEX(cualitativa[Práctica Segura],MATCH(0,INDEX(COUNTIF($P$1:P44,cualitativa[Práctica Segura]),0,0),0)),"")}
A46: 397-MEDICINA ESTÉTICA | H46: 45 | I46: =proceso45 -> 0 | J46: =IF(I46="",0,I46<>0)*1 -> 0 | K46: =(RANK($J46,$J$2:$J$56,0)+COUNTIF($J$2:$J46,J46)-1)*J46 -> 0 | L46: =IFERROR(INDEX($H$2:$K$51,MATCH(H46,$K$2:$K$51,0),2),"") | M46: =IF(L46<>"",COUNTIFS(cualitativa[[#All],[Proceso 1]:[Proceso 5]],L46),"") | P46: {=IFERROR(INDEX(cualitativa[Práctica Segura],MATCH(0,INDEX(COUNTIF($P$1:P45,cualitativa[Práctica Segura]),0,0),0)),"")}
A47: 325-MEDICINA FAMILIAR | H47: 46 | I47: =proceso46 -> 0 | J47: =IF(I47="",0,I47<>0)*1 -> 0 | K47: =(RANK($J47,$J$2:$J$56,0)+COUNTIF($J$2:$J47,J47)-1)*J47 -> 0 | L47: =IFERROR(INDEX($H$2:$K$51,MATCH(H47,$K$2:$K$51,0),2),"") | M47: =IF(L47<>"",COUNTIFS(cualitativa[[#All],[Proceso 1]:[Proceso 5]],L47),"") | P47: {=IFERROR(INDEX(cualitativa[Práctica Segura],MATCH(0,INDEX(COUNTIF($P$1:P46,cualitativa[Práctica Segura]),0,0),0)),"")}
A48: 326-MEDICINA FÍSICA Y DEL DEPORTE | H48: 47 | I48: =proceso47 -> 0 | J48: =IF(I48="",0,I48<>0)*1 -> 0 | K48: =(RANK($J48,$J$2:$J$56,0)+COUNTIF($J$2:$J48,J48)-1)*J48 -> 0 | L48: =IFERROR(INDEX($H$2:$K$51,MATCH(H48,$K$2:$K$51,0),2),"") | M48: =IF(L48<>"",COUNTIFS(cualitativa[[#All],[Proceso 1]:[Proceso 5]],L48),"") | P48: {=IFERROR(INDEX(cualitativa[Práctica Segura],MATCH(0,INDEX(COUNTIF($P$1:P47,cualitativa[Práctica Segura]),0,0),0)),"")}
A49: 327-MEDICINA FÍSICA Y REHABILITACIÓN | H49: 48 | I49: =proceso48 -> 0 | J49: =IF(I49="",0,I49<>0)*1 -> 0 | K49: =(RANK($J49,$J$2:$J$56,0)+COUNTIF($J$2:$J49,J49)-1)*J49 -> 0 | L49: =IFERROR(INDEX($H$2:$K$51,MATCH(H49,$K$2:$K$51,0),2),"") | M49: =IF(L49<>"",COUNTIFS(cualitativa[[#All],[Proceso 1]:[Proceso 5]],L49),"") | P49: {=IFERROR(INDEX(cualitativa[Práctica Segura],MATCH(0,INDEX(COUNTIF($P$1:P48,cualitativa[Práctica Segura]),0,0),0)),"")}
A50: 328-MEDICINA GENERAL | H50: 49 | I50: =proceso49 -> 0 | J50: =IF(I50="",0,I50<>0)*1 -> 0 | K50: =(RANK($J50,$J$2:$J$56,0)+COUNTIF($J$2:$J50,J50)-1)*J50 -> 0 | L50: =IFERROR(INDEX($H$2:$K$51,MATCH(H50,$K$2:$K$51,0),2),"") | M50: =IF(L50<>"",COUNTIFS(cualitativa[[#All],[Proceso 1]:[Proceso 5]],L50),"") | P50: {=IFERROR(INDEX(cualitativa[Práctica Segura],MATCH(0,INDEX(COUNTIF($P$1:P49,cualitativa[Práctica Segura]),0,0),0)),"")}
A51: 329-MEDICINA INTERNA | H51: 50 | I51: =proceso50 -> 0 | J51: =IF(I51="",0,I51<>0)*1 -> 0 | K51: =(RANK($J51,$J$2:$J$56,0)+COUNTIF($J$2:$J51,J51)-1)*J51 -> 0 | L51: =IFERROR(INDEX($H$2:$K$51,MATCH(H51,$K$2:$K$51,0),2),"") | M51: =IF(L51<>"",COUNTIFS(cualitativa[[#All],[Proceso 1]:[Proceso 5]],L51),"") | P51: {=IFERROR(INDEX(cualitativa[Práctica Segura],MATCH(0,INDEX(COUNTIF($P$1:P50,cualitativa[Práctica Segura]),0,0),0)),"")}
A52: 383-MEDICINA NUCLEAR | P52: {=IFERROR(INDEX(cualitativa[Práctica Segura],MATCH(0,INDEX(COUNTIF($P$1:P51,cualitativa[Práctica Segura]),0,0),0)),"")}
A53: 330-NEFROLOGÍA | P53: {=IFERROR(INDEX(cualitativa[Práctica Segura],MATCH(0,INDEX(COUNTIF($P$1:P52,cualitativa[Práctica Segura]),0,0),0)),"")}
A54: 384-NEFROLOGÍA PEDIÁTRICA | P54: {=IFERROR(INDEX(cualitativa[Práctica Segura],MATCH(0,INDEX(COUNTIF($P$1:P53,cualitativa[Práctica Segura]),0,0),0)),"")}
A55: 385-NEONATOLOGÍA | P55: {=IFERROR(INDEX(cualitativa[Práctica Segura],MATCH(0,INDEX(COUNTIF($P$1:P54,cualitativa[Práctica Segura]),0,0),0)),"")}
A56: 331-NEUMOLOGÍA | P56: {=IFERROR(INDEX(cualitativa[Práctica Segura],MATCH(0,INDEX(COUNTIF($P$1:P55,cualitativa[Práctica Segura]),0,0),0)),"")}
A57: 386-NEUMOLOGÍA PEDIÁTRICA | P57: {=IFERROR(INDEX(cualitativa[Práctica Segura],MATCH(0,INDEX(COUNTIF($P$1:P56,cualitativa[Práctica Segura]),0,0),0)),"")}
A58: 387-NEUROCIRUGÍA | P58: {=IFERROR(INDEX(cualitativa[Práctica Segura],MATCH(0,INDEX(COUNTIF($P$1:P57,cualitativa[Práctica Segura]),0,0),0)),"")}
A59: 332-NEUROLOGÍA | P59: {=IFERROR(INDEX(cualitativa[Práctica Segura],MATCH(0,INDEX(COUNTIF($P$1:P58,cualitativa[Práctica Segura]),0,0),0)),"")}
A60: 388-NEUROPEDIATRÍA | P60: {=IFERROR(INDEX(cualitativa[Práctica Segura],MATCH(0,INDEX(COUNTIF($P$1:P59,cualitativa[Práctica Segura]),0,0),0)),"")}
A61: 333-NUTRICIÓN Y DIETÉTICA | P61: {=IFERROR(INDEX(cualitativa[Práctica Segura],MATCH(0,INDEX(COUNTIF($P$1:P60,cualitativa[Práctica Segura]),0,0),0)),"")}
A62: 334-ODONTOLOGÍA GENERAL | P62: {=IFERROR(INDEX(cualitativa[Práctica Segura],MATCH(0,INDEX(COUNTIF($P$1:P61,cualitativa[Práctica Segura]),0,0),0)),"")}
A63: 396-ODONTOPEDIATRÍA | P63: {=IFERROR(INDEX(cualitativa[Práctica Segura],MATCH(0,INDEX(COUNTIF($P$1:P62,cualitativa[Práctica Segura]),0,0),0)),"")}
... A92: 420-VACUNACIÓN | P92: {=IFERROR(INDEX(cualitativa[Práctica Segura],MATCH(0,INDEX(COUNTIF($P$1:P91,cualitativa[Práctica Segura]),0,0),0)),"")}
P93: {=IFERROR(INDEX(cualitativa[Práctica Segura],MATCH(0,INDEX(COUNTIF($P$1:P92,cualitativa[Práctica Segura]),0,0),0)),"")}
P94: {=IFERROR(INDEX(cualitativa[Práctica Segura],MATCH(0,INDEX(COUNTIF($P$1:P93,cualitativa[Práctica Segura]),0,0),0)),"")}
P95: {=IFERROR(INDEX(cualitativa[Práctica Segura],MATCH(0,INDEX(COUNTIF($P$1:P94,cualitativa[Práctica Segura]),0,0),0)),"")}
P96: {=IFERROR(INDEX(cualitativa[Práctica Segura],MATCH(0,INDEX(COUNTIF($P$1:P95,cualitativa[Práctica Segura]),0,0),0)),"")}
P97: {=IFERROR(INDEX(cualitativa[Práctica Segura],MATCH(0,INDEX(COUNTIF($P$1:P96,cualitativa[Práctica Segura]),0,0),0)),"")}
P98: {=IFERROR(INDEX(cualitativa[Práctica Segura],MATCH(0,INDEX(COUNTIF($P$1:P97,cualitativa[Práctica Segura]),0,0),0)),"")}
P99: {=IFERROR(INDEX(cualitativa[Práctica Segura],MATCH(0,INDEX(COUNTIF($P$1:P98,cualitativa[Práctica Segura]),0,0),0)),"")}
P100: {=IFERROR(INDEX(cualitativa[Práctica Segura],MATCH(0,INDEX(COUNTIF($P$1:P99,cualitativa[Práctica Segura]),0,0),0)),"")}
P101: {=IFERROR(INDEX(cualitativa[Práctica Segura],MATCH(0,INDEX(COUNTIF($P$1:P100,cualitativa[Práctica Segura]),0,0),0)),"")}
P102: {=IFERROR(INDEX(cualitativa[Práctica Segura],MATCH(0,INDEX(COUNTIF($P$1:P101,cualitativa[Práctica Segura]),0,0),0)),"")}
P103: {=IFERROR(INDEX(cualitativa[Práctica Segura],MATCH(0,INDEX(COUNTIF($P$1:P102,cualitativa[Práctica Segura]),0,0),0)),"")}
P104: {=IFERROR(INDEX(cualitativa[Práctica Segura],MATCH(0,INDEX(COUNTIF($P$1:P103,cualitativa[Práctica Segura]),0,0),0)),"")}
... P205: {=IFERROR(INDEX(cualitativa[Práctica Segura],MATCH(0,INDEX(COUNTIF($P$1:P204,cualitativa[Práctica Segura]),0,0),0)),"")}

Sheet AUTOEV CUALIT
D1: Anexo 1. Autoevaluación Cualitativa
J3: Proceso Relacionado
B4: Num. | C4: Eje de Seguridad | D4: Práctica Segura | E4: Categoría | F4: Criterio | G4: Fortaleza | H4: Oportunidad de Mejora | I4: Fuente Oportunidad Mejora | J4: Proceso 1 | K4: Proceso 2 | L4: Proceso 3 | M4: Proceso 4 | N4: Proceso 5
B5: 1
B6: 2
B7: 3
B8: 4
B9: 5
B10: 6
B11: 7
B12: 8
B13: 9
B14: 10
B15: 11
B16: 12
... B204: 200

Sheet RADAR
C1: Hoja Radar
B3: Fuente: Resolucion-2082-de-2014
B4: ENFOQUE | C4: 1 | D4: 2 | E4: 3 | F4: 4 | G4: 5
B5: Enfoque Sistémico: Ejercicio de aplicación disciplinado que abarca todos los procesos y el contenido del estandar; que hace una visión de conjunto de la institucion; que contempla un ciclo PHVA. | C5: El enfoque es esporádico, no está presente en todos los servicios o procesos, no es sistemico y no se relaciona con el direccionamiento estratégico. | D5: Comienzo de un enfoque sistemico para los propósitos básicos del estándar y empieza a estar presente en algunos servicios o procesos. El enfoque y los procesos a través de los cuales se despliega esta documentado. | E5: El enfoque es sistemico, alcanzable para lograr los propósitos del estándar que se desea evaluar en procesos claves. | F5: El enfoque es sistemico tiene buen grado de integración que responde a todos los propósitos del estándar en la mayoría de los procesos. Relacionado con el direccionamiento estratégico. | G5: El enfoque es explícito y se aplica de manera organizada en todos los procesos, responde a los distintos criterios del estándar y está relacionado con el direccionamiento estratégico.
B6: Enfoque Proactivo: Grado en que el enfoque es preventivo y se adelanta a la ocurrencia del problema de calidad, a partir de la gestion del riesgo. | C6: Los enfoques son mayoritariamente reactivos, la informacion presentada es anecdotica y desarticulada, sin evidencia de la gestion del riesgo. | D6: Etapas iniciales de transición de la reacción a la prevención de problemas. Etapas iniciales de la gestion del riesgo. | E6: Enfoque mayoritariamente preventivo hacia el manejo y control de los procesos aún cuando existen algunos procesos en donde se actúa reactivamente. Se identifican herramientas de gestion del riesgo. | F6: El enfoque es mayoritariamente proactivo y preventivo en todos los procesos y se evidencian resultados parciales de la gestion del riesgo. | G6: El enfoque es proactivo y preventivo en todos los procesos. Hay evidencia de la gestion del riesgo.
B7: Enfoque evaluado y mejorado: Forma en que se evalua y mejora el enfoque y su asimilación | C7: La información presentada es anecdótica y desarticulada, no hay evidencias (hechos y datos) . | D7: La evidencia de un proceso de evaluación y mejoramiento del enfoque es limitada. Esbozo de algunos hechos y datos, desarticulados. | E7: El proceso de mejoramiento está basado en hechos y datos (acciones específicas realizadas y registradas) sobre procesos claves que abarcan la mayoría de productos y servicios. | F7: Existe un proceso de mejoramiento basado en hechos y datos como herramienta básica de dirección. | G7: Existen ciclos sistemáticos de evaluación, la información recogida es consistente y válida, oportuna y se emplea para la evaluación y definir acciones de mejoramiento.
B8: IMPLEMENTACIÓN | C8: 1 | D8: 2 | E8: 3 | F8: 4 | G8: 5
B9: Despliegue en la institución: Grado en que se ha implementado el enfoque y es consistente en los distintos servicios o procesos de la organización. | C9: El enfoque se ha implementado en algunos servicios o procesos pero se refleja su debilidad. | D9: La implementación del enfoque se da en algunos servicios o procesos operativos principales y existen brechas muy significativas en procesos importantes. | E9: La implementación está más avanzada en servicios o procesos claves y no existen grandes brechas con respecto a otros servicios o procesos. | F9: Existe un enfoque bien desplegado en todos los servicios o procesos, con brechas no significativas en aquellos de soporte. | G9: La implementación del enfoque se amplía continuamente para cubrir nuevos servicios o procesos en forma integral y responde al enfoque definido en todos los servicios o procesos claves.
B10: Apropiación por el cliente interno y/o externo: Grado en que el cliente del despliegue (cliente interno y/o externo) entiende y aplica el enfoque, según la naturaleza y propositos del estandar. | C10: El enfoque no lo apropian los clientes. | D10: Hay evidencias de apropiación a unos pocos clientes internos o externos, pero éste no es consistente. | E10: Hay evidencias de apropiación parcial del enfoque en los principales clientes con un grado mínimo de consistencia. | F10: El enfoque lo apropian la mayoría de los usuarios y es medianamente consistente. | G10: El enfoque está apropiado en la totalidad de los usuarios y es totalmente consistente.
B11: RESULTADOS | C11: 1 | D11: 2 | E11: 3 | F11: 4 | G11: 5
B12: Pertinencia: Grado en que los resultados referidos (hechos, datos e indicadores) se relacionan con los criterios y requisitos del estándar. | C12: Los datos presentados no responden a los factores, productos o servicios claves del estándar. | D12: Los datos presentados son parciales y se refieren a unos pocos factores, productos o servicios claves solicitados en el estándar. | E12: Los datos presentados se refieren al desempeño de algunos servicios o procesos claves, factores, productos y/o servicios solicitados. | F12: La mayoría de los resultados referidos se relacionan con el servicio o proceso, factores, productos y/o servicios solicitados en el estándar, alcanzando los objetivos y metas propuestas. | G12: Todos los resultados se relacionan con el servicio o proceso o el punto del estándar a evaluar y alcanzan los objetivos y metas propuestas
B13: Consistencia: Relacion de los resultados como producto de la implementacion del enfoque. | C13: Solo existen ejemplos anecdóticos de aspectos poco relevantes y no hay evidencia de que sean resultado de la implementación del enfoque. | D13: Se comienzan a obtener resultados todavía incipientes de la aplicación del enfoque. | E13: Existe evidencia de algunos logros son causados por el enfoque implementado y por las acciones de mejoramiento | F13: La mayoría de los resultados responden a la implementación del enfoque y a las acciones de mejoramiento | G13: Todos los resultados son causados por la implementación de enfoques y a las acciones sistemáticas de mejoramiento
B14: Avance de la medición: Grado en que la medicion responde a una práctica sistémica de la organización en un periodo de tiempo que le permita su consolidacion y existen indicadores definidos para la medicion del estandar evaluado, calidad y pertinencia de los mismos. | C14: No existen indicadores que muestren tendencias en la calidad y el desempeño de los procesos. La organización se encuentra en una etapa muy temprana de medición. | D14: Existen algunos indicadores que muestran el desempeño de procesos. La organización se encuentra en una etapa media del desarrollo de la medición | E14: Existen indicadores que monitorean los procesos y muestran ya tendencias positivas de mejoramiento en algunos servicios o procesos claves, factores, productos y/o servicios solicitados en el estándar. Algunos servicios o procesos reportados pueden estar en etapas recientes de medición. | F14: Existen procesos de medición sistemáticos para la mayoría de los servicios o procesos y factores claves de éxito solicitados en el estándar | G14: Los resultados son monitoreados directamente por los líderes de todos los niveles de la organización y la información se utiliza para la toma de decisiones y el mejoramiento de los procesos.
B15: Tendencia: Desempeño de los indicadores en el tiempo. Puede ser positiva cuando los datos muestran una mejoria general a lo largo del tiempo. | C15: El estadio de la medición y por lo tanto de los resultados, no garantizan tendencias confiables | D15: Se muestran resultados muy recientes que aunque no permiten tener suficientes bases para establecer tendencias, el proceso es sistemático y se empiezan a tomar decisiones operativas con base en la información | E15: Se presentan tendencias de mejoramiento de algunos factores claves del estándar. Proceso sistemático y estructurado. | F15: La mayoría de los indicadores alcanzan niveles satisfactorios y muestran firmes tendencias de mejoramiento de los servicios o procesos claves, factores, productos y/o servicios, lo cual se refleja en que van de bueno a excelente | G15: Se observan tendencias positivas y sostenidas de mejoramiento de todos los datos a lo largo del tiempo
B16: Comparación: Grado en que los resultados son comparados con referentes nacionales e internacionales y la calidad de los mismos. | C16: No existen políticas, ni prácticas de comparación de los procesos de la organización con los mejores. | D16: Se encuentran algunas prácticas independientes de comparación, poco estructuradas y no sistemáticas. | E16: Existe una política de comparación con las mejores prácticas y se encuentra en etapa temprana de comparación de algunos procesos, productos críticos y servicios solicitados en el estándar. | F16: Se encuentra en etapa madura de comparación con las mejores prácticas a nivel nacional de servicios o procesos, productos, factores y/o servicios claves solicitados en el estándar. | G16: Los resultados son comparados con referentes nacionales e internacionales y se ubican en niveles cercanos a las tendencias de clase mundial. Cuenta con un sistema de evaluación y mejora de los sistemas de comparación.

Sheet AUTOEV CUANTI IND
D1: Anexo 1A. Autoevaluación Cuantitativa Registro Individual
B3: Atención: esta hoja está formulada y muestra los criterios que se han registrado en la hoja Autoev Cualit. Para evaluar filtre sólo los criterios que tengan oportunidad de mejora asociada | H3: ENFOQUE | K3: IMPLEMENTACION | M3: RESULTADO
B4: Num. | C4: Eje de Seguridad | D4: Práctica Segura | E4: Criterio | F4: Fortaleza | G4: Oportunidad de Mejora | H4: Enfoque sistémico | I4: Enfoque proactivo | J4: Enfoque evaluado y mejorado | K4: Despliegue en la institución | L4: Apropiación por cliente interno y/o externo | M4: Pertinencia | N4: Consistencia | O4: Avance de la medición | P4: Tendencia | Q4: Comparación | R4: Calificación total
B5: 1 | C5: {=Eje_de_Seguridad} -> 0 | D5: {=practica_segura} -> 0 | E5: {=criterio} -> 0 | F5: {=fortaleza} -> 0 | G5: {=om} -> 0 | R5: =IFERROR(AVERAGE('AUTOEV CUANTI IND'!$H5:$Q5),"")
B6: 2 | C6: 0 | D6: 0 | E6: 0 | F6: 0 | G6: 0 | R6: =IFERROR(AVERAGE('AUTOEV CUANTI IND'!$H6:$Q6),"")
B7: 3 | C7: 0 | D7: 0 | E7: 0 | F7: 0 | G7: 0 | R7: =IFERROR(AVERAGE('AUTOEV CUANTI IND'!$H7:$Q7),"")
B8: 4 | C8: 0 | D8: 0 | E8: 0 | F8: 0 | G8: 0 | R8: =IFERROR(AVERAGE('AUTOEV CUANTI IND'!$H8:$Q8),"")
B9: 5 | C9: 0 | D9: 0 | E9: 0 | F9: 0 | G9: 0 | R9: =IFERROR(AVERAGE('AUTOEV CUANTI IND'!$H9:$Q9),"")
B10: 6 | C10: 0 | D10: 0 | E10: 0 | F10: 0 | G10: 0 | R10: =IFERROR(AVERAGE('AUTOEV CUANTI IND'!$H10:$Q10),"")
B11: 7 | C11: 0 | D11: 0 | E11: 0 | F11: 0 | G11: 0 | R11: =IFERROR(AVERAGE('AUTOEV CUANTI IND'!$H11:$Q11),"")
B12: 8 | C12: 0 | D12: 0 | E12: 0 | F12: 0 | G12: 0 | R12: =IFERROR(AVERAGE('AUTOEV CUANTI IND'!$H12:$Q12),"")
B13: 9 | C13: 0 | D13: 0 | E13: 0 | F13: 0 | G13: 0 | R13: =IFERROR(AVERAGE('AUTOEV CUANTI IND'!$H13:$Q13),"")
B14: 10 | C14: 0 | D14: 0 | E14: 0 | F14: 0 | G14: 0 | R14: =IFERROR(AVERAGE('AUTOEV CUANTI IND'!$H14:$Q14),"")
B15: 11 | C15: 0 | D15: 0 | E15: 0 | F15: 0 | G15: 0 | R15: =IFERROR(AVERAGE('AUTOEV CUANTI IND'!$H15:$Q15),"")
B16: 12 | C16: 0 | D16: 0 | E16: 0 | F16: 0 | G16: 0 | R16: =IFERROR(AVERAGE('AUTOEV CUANTI IND'!$H16:$Q16),"")
B17: 13 | C17: 0 | D17: 0 | E17: 0 | F17: 0 | G17: 0 | R17: =IFERROR(AVERAGE('AUTOEV CUANTI IND'!$H17:$Q17),"")
... B204: 200 | C204: 0 | D204: 0 | E204: 0 | F204: 0 | G204: 0 | R204: =IFERROR(AVERAGE('AUTOEV CUANTI IND'!$H204:$Q204),"")

Sheet AUTOEV CUANTI MULT
D1: Anexo 1A. Autoevaluación Cuantitativa Registro de hasta 10 calificaciones por criterio
H3: ENFOQUE | AL3: Implementación | BF3: Resultados
B4: Atención: esta hoja está formulada y muestra los criterios que se han registrado en la hoja Autoev Cualit | H4: Enfoque sistémico | R4: Enfoque proactivo | AB4: Enfoque evaluado y mejorado | AL4: Despliegue en la institución | AV4: Apropiación por cliente interno y/o externo | BF4: Pertinencia | BP4: Consistencia | BZ4: Avance de la medición | CJ4: Tendencia | CT4: Comparación
B5: Num. | C5: Eje de Seguridad | D5: Práctica Segura | E5: Criterio | F5: Fortaleza | G5: Oportunidad de Mejora | H5: Eval1ES | I5: Eval2ES | J5: Eval3ES | K5: Eval4ES | L5: Eval5ES | M5: Eval6ES | N5: Eval7ES | O5: Eval8ES | P5: Eval9ES | Q5: Eval10ES | R5: Eval1EP | S5: Eval2EP | T5: Eval3EP | U5: Eval4EP | V5: Eval5EP | W5: Eval6EP | X5: Eval7EP | Y5: Eval8EP | Z5: Eval9EP | AA5: Eval10EP | AB5: Eval1EV | AC5: Eval2EV | AD5: Eval3EV | AE5: Eval4EV | AF5: Eval5EV | AG5: Eval6EV | AH5: Eval7EV | AI5: Eval8EV | AJ5: Eval9EV | AK5: Eval10EV | AL5: Eval1DI | AM5: Eval2DI | AN5: Eval3DI | AO5: Eval4DI | AP5: Eval5DI | AQ5: Eval6DI | AR5: Eval7DI | AS5: Eval8DI | AT5: Eval9DI | AU5: Eval10DI | AV5: Eval1AC | AW5: Eval2AC | AX5: Eval3AC | AY5: Eval4AC | AZ5: Eval5AC | BA5: Eval6AC | BB5: Eval7AC | BC5: Eval8AC | BD5: Eval9AC | BE5: Eval10AC | BF5: Eval1PE | BG5: Eval2PE | BH5: Eval3PE | BI5: Eval4PE | BJ5: Eval5PE | BK5: Eval6PE | BL5: Eval7PE | BM5: Eval8PE | BN5: Eval9PE | BO5: Eval10PE | BP5: Eval1CO | BQ5: Eval2CO | BR5: Eval3CO | BS5: Eval4CO | BT5: Eval5CO | BU5: Eval6CO | BV5: Eval7CO | BW5: Eval8CO | BX5: Eval9CO | BY5: Eval10CO | BZ5: Eval1AV | CA5: Eval2AV | CB5: Eval3AV | CC5: Eval4AV | CD5: Eval5AV | CE5: Eval6AV | CF5: Eval7AV | CG5: Eval8AV | CH5: Eval9AV | CI5: Eval10AV | CJ5: Eval1TE | CK5: Eval2TE | CL5: Eval3TE | CM5: Eval4TE | CN5: Eval5TE | CO5: Eval6TE | CP5: Eval7TE | CQ5: Eval8TE | CR5: Eval9TE | CS5: Eval10TE | CT5: Eval1COM | CU5: Eval2COM | CV5: Eval3COM | CW5: Eval4COM | CX5: Eval5COM | CY5: Eval6COM | CZ5: Eval7COM | DA5: Eval8COM | DB5: Eval9COM | DC5: Eval10COM | DD5: Calificación total
B6: 1 | C6: {=Eje_de_Seguridad} -> 0 | D6: {=practica_segura} -> 0 | E6: {=criterio} -> 0 | F6: {=fortaleza} -> 0 | G6: {=om} -> 0 | DD6: =IFERROR(AVERAGE('AUTOEV CUANTI MULT'!$H6:$DC6),"")
B7: 2 | C7: 0 | D7: 0 | E7: 0 | F7: 0 | G7: 0 | DD7: =IFERROR(AVERAGE('AUTOEV CUANTI MULT'!$H7:$DC7),"")
B8: 3 | C8: 0 | D8: 0 | E8: 0 | F8: 0 | G8: 0 | DD8: =IFERROR(AVERAGE('AUTOEV CUANTI MULT'!$H8:$DC8),"")
B9: 4 | C9: 0 | D9: 0 | E9: 0 | F9: 0 | G9: 0 | DD9: =IFERROR(AVERAGE('AUTOEV CUANTI MULT'!$H9:$DC9),"")
B10: 5 | C10: 0 | D10: 0 | E10: 0 | F10: 0 | G10: 0 | DD10: =IFERROR(AVERAGE('AUTOEV CUANTI MULT'!$H10:$DC10),"")
B11: 6 | C11: 0 | D11: 0 | E11: 0 | F11: 0 | G11: 0 | DD11: =IFERROR(AVERAGE('AUTOEV CUANTI MULT'!$H11:$DC11),"")
B12: 7 | C12: 0 | D12: 0 | E12: 0 | F12: 0 | G12: 0 | DD12: =IFERROR(AVERAGE('AUTOEV CUANTI MULT'!$H12:$DC12),"")
B13: 8 | C13: 0 | D13: 0 | E13: 0 | F13: 0 | G13: 0 | DD13: =IFERROR(AVERAGE('AUTOEV CUANTI MULT'!$H13:$DC13),"")
B14: 9 | C14: 0 | D14: 0 | E14: 0 | F14: 0 | G14: 0 | DD14: =IFERROR(AVERAGE('AUTOEV CUANTI MULT'!$H14:$DC14),"")
B15: 10 | C15: 0 | D15: 0 | E15: 0 | F15: 0 | G15: 0 | DD15: =IFERROR(AVERAGE('AUTOEV CUANTI MULT'!$H15:$DC15),"")
B16: 11 | C16: 0 | D16: 0 | E16: 0 | F16: 0 | G16: 0 | DD16: =IFERROR(AVERAGE('AUTOEV CUANTI MULT'!$H16:$DC16),"")
B17: 12 | C17: 0 | D17: 0 | E17: 0 | F17: 0 | G17: 0 | DD17: =IFERROR(AVERAGE('AUTOEV CUANTI MULT'!$H17:$DC17),"")
B18: 13 | C18: 0 | D18: 0 | E18: 0 | F18: 0 | G18: 0 | DD18: =IFERROR(AVERAGE('AUTOEV CUANTI MULT'!$H18:$DC18),"")
... B205: 200 | C205: 0 | D205: 0 | E205: 0 | F205: 0 | G205: 0 | DD205: =IFERROR(AVERAGE('AUTOEV CUANTI MULT'!$H205:$DC205),"")

Sheet CONS AUTOEV
D1: Selección de Procesos a Mejorar y Priorización
L2: Priorizar Calificación total entre >= 75 y 125 Calificación total entre >= 26 y 74 Calificación total entre 1 y 25 | O2: 75 | R2: 26 | S2: 1 | T2: <--- Modifique según necesidad
B3: Atención: esta hoja está formulada y muestra los criterios que se han registrado en la hoja Autoev Cualit | L3: Factores Criticos de Éxito (Califique 1 - 3 o 5)
B4: Num. | C4: Eje de Seguridad | D4: Práctica Segura | E4: Criterio | F4: Fortaleza | G4: Oportunidad de Mejora | H4: Calificación Cuantitativa | I4: Cantidad de procesos asociados | J4: Procesos involucrados | K4: ¿Seleccionar Proceso? | L4: Costo | M4: Riesgo | N4: Volumen | O4: Total Priorización | P4: Auxiliar | Q4: Consecutivo
B5: 1 | C5: {=Eje_de_Seguridad} -> 0 | D5: {=practica_segura} -> 0 | E5: {=criterio} -> 0 | F5: {=fortaleza} -> 0 | G5: {=om} -> 0 | H5: =IF('AUTOEV CUANTI IND'!R5<>"",'AUTOEV CUANTI IND'!R5,IF('AUTOEV CUANTI MULT'!DD6<>"",'AUTOEV CUANTI MULT'!DD6,"")) | I5: =IF(COUNTIFS(cualitativa[Num.],B5)<>0,(5-COUNTBLANK(cualitativa[[#This Row],[Proceso 1]:[Proceso 5]])),"") -> 0 | J5: =IF(COUNTIFS(cualitativa[Num.],B5)<>0,cualitativa[[#This Row],[Proceso 1]]&" "&cualitativa[[#This Row],[Proceso 2]]&" "&cualitativa[[#This Row],[Proceso 3]]&" "&cualitativa[[#This Row],[Proceso 4]]&" "&cualitativa[[#This Row],[Proceso 5]],"") | O5: ='CONS AUTOEV'!$L5*'CONS AUTOEV'!$M5*'CONS AUTOEV'!$N5 -> 0 | P5: =IF(O5="",0,O5>=$O$2)*1 -> 0 | Q5: =(RANK($P5,$P$5:$P$204,0)+COUNTIF($P$5:$P5,P5)-1)*P5 -> 0
B6: 2 | C6: 0 | D6: 0 | E6: 0 | F6: 0 | G6: 0 | H6: =IF('AUTOEV CUANTI IND'!R6<>"",'AUTOEV CUANTI IND'!R6,IF('AUTOEV CUANTI MULT'!DD7<>"",'AUTOEV CUANTI MULT'!DD7,"")) | I6: =IF(COUNTIFS(cualitativa[Num.],B6)<>0,(5-COUNTBLANK(cualitativa[[#This Row],[Proceso 1]:[Proceso 5]])),"") -> 0 | J6: =IF(COUNTIFS(cualitativa[Num.],B6)<>0,cualitativa[[#This Row],[Proceso 1]]&" "&cualitativa[[#This Row],[Proceso 2]]&" "&cualitativa[[#This Row],[Proceso 3]]&" "&cualitativa[[#This Row],[Proceso 4]]&" "&cualitativa[[#This Row],[Proceso 5]],"") | O6: ='CONS AUTOEV'!$L6*'CONS AUTOEV'!$M6*'CONS AUTOEV'!$N6 -> 0 | P6: =IF(O6="",0,O6>=$O$2)*1 -> 0 | Q6: =(RANK($P6,$P$5:$P$204,0)+COUNTIF($P$5:$P6,P6)-1)*P6 -> 0
B7: 3 | C7: 0 | D7: 0 | E7: 0 | F7: 0 | G7: 0 | H7: =IF('AUTOEV CUANTI IND'!R7<>"",'AUTOEV CUANTI IND'!R7,IF('AUTOEV CUANTI MULT'!DD8<>"",'AUTOEV CUANTI MULT'!DD8,"")) | I7: =IF(COUNTIFS(cualitativa[Num.],B7)<>0,(5-COUNTBLANK(cualitativa[[#This Row],[Proceso 1]:[Proceso 5]])),"") -> 0 | J7: =IF(COUNTIFS(cualitativa[Num.],B7)<>0,cualitativa[[#This Row],[Proceso 1]]&" "&cualitativa[[#This Row],[Proceso 2]]&" "&cualitativa[[#This Row],[Proceso 3]]&" "&cualitativa[[#This Row],[Proceso 4]]&" "&cualitativa[[#This Row],[Proceso 5]],"") | O7: ='CONS AUTOEV'!$L7*'CONS AUTOEV'!$M7*'CONS AUTOEV'!$N7 -> 0 | P7: =IF(O7="",0,O7>=$O$2)*1 -> 0 | Q7: =(RANK($P7,$P$5:$P$204,0)+COUNTIF($P$5:$P7,P7)-1)*P7 -> 0
B8: 4 | C8: 0 | D8: 0 | E8: 0 | F8: 0 | G8: 0 | H8: =IF('AUTOEV CUANTI IND'!R8<>"",'AUTOEV CUANTI IND'!R8,IF('AUTOEV CUANTI MULT'!DD9<>"",'AUTOEV CUANTI MULT'!DD9,"")) | I8: =IF(COUNTIFS(cualitativa[Num.],B8)<>0,(5-COUNTBLANK(cualitativa[[#This Row],[Proceso 1]:[Proceso 5]])),"") -> 0 | J8: =IF(COUNTIFS(cualitativa[Num.],B8)<>0,cualitativa[[#This Row],[Proceso 1]]&" "&cualitativa[[#This Row],[Proceso 2]]&" "&cualitativa[[#This Row],[Proceso 3]]&" "&cualitativa[[#This Row],[Proceso 4]]&" "&cualitativa[[#This Row],[Proceso 5]],"") | O8: ='CONS AUTOEV'!$L8*'CONS AUTOEV'!$M8*'CONS AUTOEV'!$N8 -> 0 | P8: =IF(O8="",0,O8>=$O$2)*1 -> 0 | Q8: =(RANK($P8,$P$5:$P$204,0)+COUNTIF($P$5:$P8,P8)-1)*P8 -> 0
B9: 5 | C9: 0 | D9: 0 | E9: 0 | F9: 0 | G9: 0 | H9: =IF('AUTOEV CUANTI IND'!R9<>"",'AUTOEV CUANTI IND'!R9,IF('AUTOEV CUANTI MULT'!DD10<>"",'AUTOEV CUANTI MULT'!DD10,"")) | I9: =IF(COUNTIFS(cualitativa[Num.],B9)<>0,(5-COUNTBLANK(cualitativa[[#This Row],[Proceso 1]:[Proceso 5]])),"") -> 0 | J9: =IF(COUNTIFS(cualitativa[Num.],B9)<>0,cualitativa[[#This Row],[Proceso 1]]&" "&cualitativa[[#This Row],[Proceso 2]]&" "&cualitativa[[#This Row],[Proceso 3]]&" "&cualitativa[[#This Row],[Proceso 4]]&" "&cualitativa[[#This Row],[Proceso 5]],"") | O9: ='CONS AUTOEV'!$L9*'CONS AUTOEV'!$M9*'CONS AUTOEV'!$N9 -> 0 | P9: =IF(O9="",0,O9>=$O$2)*1 -> 0 | Q9: =(RANK($P9,$P$5:$P$204,0)+COUNTIF($P$5:$P9,P9)-1)*P9 -> 0
B10: 6 | C10: 0 | D10: 0 | E10: 0 | F10: 0 | G10: 0 | H10: =IF('AUTOEV CUANTI IND'!R10<>"",'AUTOEV CUANTI IND'!R10,IF('AUTOEV CUANTI MULT'!DD11<>"",'AUTOEV CUANTI MULT'!DD11,"")) | I10: =IF(COUNTIFS(cualitativa[Num.],B10)<>0,(5-COUNTBLANK(cualitativa[[#This Row],[Proceso 1]:[Proceso 5]])),"") -> 0 | J10: =IF(COUNTIFS(cualitativa[Num.],B10)<>0,cualitativa[[#This Row],[Proceso 1]]&" "&cualitativa[[#This Row],[Proceso 2]]&" "&cualitativa[[#This Row],[Proceso 3]]&" "&cualitativa[[#This Row],[Proceso 4]]&" "&cualitativa[[#This Row],[Proceso 5]],"") | O10: ='CONS AUTOEV'!$L10*'CONS AUTOEV'!$M10*'CONS AUTOEV'!$N10 -> 0 | P10: =IF(O10="",0,O10>=$O$2)*1 -> 0 | Q10: =(RANK($P10,$P$5:$P$204,0)+COUNTIF($P$5:$P10,P10)-1)*P10 -> 0
B11: 7 | C11: 0 | D11: 0 | E11: 0 | F11: 0 | G11: 0 | H11: =IF('AUTOEV CUANTI IND'!R11<>"",'AUTOEV CUANTI IND'!R11,IF('AUTOEV CUANTI MULT'!DD12<>"",'AUTOEV CUANTI MULT'!DD12,"")) | I11: =IF(COUNTIFS(cualitativa[Num.],B11)<>0,(5-COUNTBLANK(cualitativa[[#This Row],[Proceso 1]:[Proceso 5]])),"") -> 0 | J11: =IF(COUNTIFS(cualitativa[Num.],B11)<>0,cualitativa[[#This Row],[Proceso 1]]&" "&cualitativa[[#This Row],[Proceso 2]]&" "&cualitativa[[#This Row],[Proceso 3]]&" "&cualitativa[[#This Row],[Proceso 4]]&" "&cualitativa[[#This Row],[Proceso 5]],"") | O11: ='CONS AUTOEV'!$L11*'CONS AUTOEV'!$M11*'CONS AUTOEV'!$N11 -> 0 | P11: =IF(O11="",0,O11>=$O$2)*1 -> 0 | Q11: =(RANK($P11,$P$5:$P$204,0)+COUNTIF($P$5:$P11,P11)-1)*P11 -> 0
B12: 8 | C12: 0 | D12: 0 | E12: 0 | F12: 0 | G12: 0 | H12: =IF('AUTOEV CUANTI IND'!R12<>"",'AUTOEV CUANTI IND'!R12,IF('AUTOEV CUANTI MULT'!DD13<>"",'AUTOEV CUANTI MULT'!DD13,"")) | I12: =IF(COUNTIFS(cualitativa[Num.],B12)<>0,(5-COUNTBLANK(cualitativa[[#This Row],[Proceso 1]:[Proceso 5]])),"") -> 0 | J12: =IF(COUNTIFS(cualitativa[Num.],B12)<>0,cualitativa[[#This Row],[Proceso 1]]&" "&cualitativa[[#This Row],[Proceso 2]]&" "&cualitativa[[#This Row],[Proceso 3]]&" "&cualitativa[[#This Row],[Proceso 4]]&" "&cualitativa[[#This Row],[Proceso 5]],"") | O12: ='CONS AUTOEV'!$L12*'CONS AUTOEV'!$M12*'CONS AUTOEV'!$N12 -> 0 | P12: =IF(O12="",0,O12>=$O$2)*1 -> 0 | Q12: =(RANK($P12,$P$5:$P$204,0)+COUNTIF($P$5:$P12,P12)-1)*P12 -> 0
B13: 9 | C13: 0 | D13: 0 | E13: 0 | F13: 0 | G13: 0 | H13: =IF('AUTOEV CUANTI IND'!R13<>"",'AUTOEV CUANTI IND'!R13,IF('AUTOEV CUANTI MULT'!DD14<>"",'AUTOEV CUANTI MULT'!DD14,"")) | I13: =IF(COUNTIFS(cualitativa[Num.],B13)<>0,(5-COUNTBLANK(cualitativa[[#This Row],[Proceso 1]:[Proceso 5]])),"") -> 0 | J13: =IF(COUNTIFS(cualitativa[Num.],B13)<>0,cualitativa[[#This Row],[Proceso 1]]&" "&cualitativa[[#This Row],[Proceso 2]]&" "&cualitativa[[#This Row],[Proceso 3]]&" "&cualitativa[[#This Row],[Proceso 4]]&" "&cualitativa[[#This Row],[Proceso 5]],"") | O13: ='CONS AUTOEV'!$L13*'CONS AUTOEV'!$M13*'CONS AUTOEV'!$N13 -> 0 | P13: =IF(O13="",0,O13>=$O$2)*1 -> 0 | Q13: =(RANK($P13,$P$5:$P$204,0)+COUNTIF($P$5:$P13,P13)-1)*P13 -> 0
B14: 10 | C14: 0 | D14: 0 | E14: 0 | F14: 0 | G14: 0 | H14: =IF('AUTOEV CUANTI IND'!R14<>"",'AUTOEV CUANTI IND'!R14,IF('AUTOEV CUANTI MULT'!DD15<>"",'AUTOEV CUANTI MULT'!DD15,"")) | I14: =IF(COUNTIFS(cualitativa[Num.],B14)<>0,(5-COUNTBLANK(cualitativa[[#This Row],[Proceso 1]:[Proceso 5]])),"") -> 0 | J14: =IF(COUNTIFS(cualitativa[Num.],B14)<>0,cualitativa[[#This Row],[Proceso 1]]&" "&cualitativa[[#This Row],[Proceso 2]]&" "&cualitativa[[#This Row],[Proceso 3]]&" "&cualitativa[[#This Row],[Proceso 4]]&" "&cualitativa[[#This Row],[Proceso 5]],"") | O14: ='CONS AUTOEV'!$L14*'CONS AUTOEV'!$M14*'CONS AUTOEV'!$N14 -> 0 | P14: =IF(O14="",0,O14>=$O$2)*1 -> 0 | Q14: =(RANK($P14,$P$5:$P$204,0)+COUNTIF($P$5:$P14,P14)-1)*P14 -> 0
B15: 11 | C15: 0 | D15: 0 | E15: 0 | F15: 0 | G15: 0 | H15: =IF('AUTOEV CUANTI IND'!R15<>"",'AUTOEV CUANTI IND'!R15,IF('AUTOEV CUANTI MULT'!DD16<>"",'AUTOEV CUANTI MULT'!DD16,"")) | I15: =IF(COUNTIFS(cualitativa[Num.],B15)<>0,(5-COUNTBLANK(cualitativa[[#This Row],[Proceso 1]:[Proceso 5]])),"") -> 0 | J15: =IF(COUNTIFS(cualitativa[Num.],B15)<>0,cualitativa[[#This Row],[Proceso 1]]&" "&cualitativa[[#This Row],[Proceso 2]]&" "&cualitativa[[#This Row],[Proceso 3]]&" "&cualitativa[[#This Row],[Proceso 4]]&" "&cualitativa[[#This Row],[Proceso 5]],"") | O15: ='CONS AUTOEV'!$L15*'CONS AUTOEV'!$M15*'CONS AUTOEV'!$N15 -> 0 | P15: =IF(O15="",0,O15>=$O$2)*1 -> 0 | Q15: =(RANK($P15,$P$5:$P$204,0)+COUNTIF($P$5:$P15,P15)-1)*P15 -> 0
B16: 12 | C16: 0 | D16: 0 | E16: 0 | F16: 0 | G16: 0 | H16: =IF('AUTOEV CUANTI IND'!R16<>"",'AUTOEV CUANTI IND'!R16,IF('AUTOEV CUANTI MULT'!DD17<>"",'AUTOEV CUANTI MULT'!DD17,"")) | I16: =IF(COUNTIFS(cualitativa[Num.],B16)<>0,(5-COUNTBLANK(cualitativa[[#This Row],[Proceso 1]:[Proceso 5]])),"") -> 0 | J16: =IF(COUNTIFS(cualitativa[Num.],B16)<>0,cualitativa[[#This Row],[Proceso 1]]&" "&cualitativa[[#This Row],[Proceso 2]]&" "&cualitativa[[#This Row],[Proceso 3]]&" "&cualitativa[[#This Row],[Proceso 4]]&" "&cualitativa[[#This Row],[Proceso 5]],"") | O16: ='CONS AUTOEV'!$L16*'CONS AUTOEV'!$M16*'CONS AUTOEV'!$N16 -> 0 | P16: =IF(O16="",0,O16>=$O$2)*1 -> 0 | Q16: =(RANK($P16,$P$5:$P$204,0)+COUNTIF($P$5:$P16,P16)-1)*P16 -> 0
B17: 13 | C17: 0 | D17: 0 | E17: 0 | F17: 0 | G17: 0 | H17: =IF('AUTOEV CUANTI IND'!R17<>"",'AUTOEV CUANTI IND'!R17,IF('AUTOEV CUANTI MULT'!DD18<>"",'AUTOEV CUANTI MULT'!DD18,"")) | I17: =IF(COUNTIFS(cualitativa[Num.],B17)<>0,(5-COUNTBLANK(cualitativa[[#This Row],[Proceso 1]:[Proceso 5]])),"") -> 0 | J17: =IF(COUNTIFS(cualitativa[Num.],B17)<>0,cualitativa[[#This Row],[Proceso 1]]&" "&cualitativa[[#This Row],[Proceso 2]]&" "&cualitativa[[#This Row],[Proceso 3]]&" "&cualitativa[[#This Row],[Proceso 4]]&" "&cualitativa[[#This Row],[Proceso 5]],"") | O17: ='CONS AUTOEV'!$L17*'CONS AUTOEV'!$M17*'CONS AUTOEV'!$N17 -> 0 | P17: =IF(O17="",0,O17>=$O$2)*1 -> 0 | Q17: =(RANK($P17,$P$5:$P$204,0)+COUNTIF($P$5:$P17,P17)-1)*P17 -> 0
... B204: 200 | C204: 0 | D204: 0 | E204: 0 | F204: 0 | G204: 0 | H204: =IF('AUTOEV CUANTI IND'!R204<>"",'AUTOEV CUANTI IND'!R204,IF('AUTOEV CUANTI MULT'!DD205<>"",'AUTOEV CUANTI MULT'!DD205,"")) | I204: =IF(COUNTIFS(cualitativa[Num.],B204)<>0,(5-COUNTBLANK(cualitativa[[#This Row],[Proceso 1]:[Proceso 5]])),"") -> 0 | J204: =IF(COUNTIFS(cualitativa[Num.],B204)<>0,cualitativa[[#This Row],[Proceso 1]]&" "&cualitativa[[#This Row],[Proceso 2]]&" "&cualitativa[[#This Row],[Proceso 3]]&" "&cualitativa[[#This Row],[Proceso 4]]&" "&cualitativa[[#This Row],[Proceso 5]],"") | O204: ='CONS AUTOEV'!$L204*'CONS AUTOEV'!$M204*'CONS AUTOEV'!$N204 -> 0 | P204: =IF(O204="",0,O204>=$O$2)*1 -> 0 | Q204: =(RANK($P204,$P$5:$P$204,0)+COUNTIF($P$5:$P204,P204)-1)*P204 -> 0

Sheet PROCESOS VS OM
D1: ="Mapa de Procesos "&IDENTIFICACIÓN!C14&" Cantidad de Oportunidades de Mejora por Proceso" -> Mapa de Procesos Cantidad de Oportunidades de Mejora por Proceso
B3: Cliente | D3: Procesos de Planeación o Estratégicos | S3: Cliente
D5: =proceso1 -> 0 | E5: =IFERROR(VLOOKUP(D5,Datos!$L$1:$M$51,2,FALSE),"") | G5: =proceso2 -> 0 | H5: =IFERROR(VLOOKUP(G5,Datos!$L$1:$M$51,2,FALSE),"") | J5: =proceso3 -> 0 | K5: =IFERROR(VLOOKUP(J5,Datos!$L$1:$M$51,2,FALSE),"") | M5: =proceso4 -> 0 | N5: =IFERROR(VLOOKUP(M5,Datos!$L$1:$M$51,2,FALSE),"") | P5: =proceso5 -> 0 | Q5: =IFERROR(VLOOKUP(P5,Datos!$L$1:$M$51,2,FALSE),"")
D7: =proceso6 -> 0 | E7: =IFERROR(VLOOKUP(D7,Datos!$L$1:$M$51,2,FALSE),"") | G7: =proceso7 -> 0 | H7: =IFERROR(VLOOKUP(G7,Datos!$L$1:$M$51,2,FALSE),"") | J7: =proceso8 -> 0 | K7: =IFERROR(VLOOKUP(J7,Datos!$L$1:$M$51,2,FALSE),"") | M7: =proceso9 -> 0 | N7: =IFERROR(VLOOKUP(M7,Datos!$L$1:$M$51,2,FALSE),"") | P7: =proceso10 -> 0 | Q7: =IFERROR(VLOOKUP(P7,Datos!$L$1:$M$51,2,FALSE),"")
D9: =proceso11 -> 0 | E9: =IFERROR(VLOOKUP(D9,Datos!$L$1:$M$51,2,FALSE),"") | G9: =proceso12 -> 0 | H9: =IFERROR(VLOOKUP(G9,Datos!$L$1:$M$51,2,FALSE),"") | J9: =proceso13 -> 0 | K9: =IFERROR(VLOOKUP(J9,Datos!$L$1:$M$51,2,FALSE),"") | M9: =proceso14 -> 0 | N9: =IFERROR(VLOOKUP(M9,Datos!$L$1:$M$51,2,FALSE),"") | P9: =proceso15 -> 0 | Q9: =IFERROR(VLOOKUP(P9,Datos!$L$1:$M$51,2,FALSE),"")
D11: Procesos Misionales
D13: =proceso16 -> 0 | E13: =IFERROR(VLOOKUP(D13,Datos!$L$1:$M$51,2,FALSE),"") | G13: =proceso17 -> 0 | H13: =IFERROR(VLOOKUP(G13,Datos!$L$1:$M$51,2,FALSE),"") | J13: =proceso18 -> 0 | K13: =IFERROR(VLOOKUP(J13,Datos!$L$1:$M$51,2,FALSE),"") | M13: =proceso19 -> 0 | N13: =IFERROR(VLOOKUP(M13,Datos!$L$1:$M$51,2,FALSE),"") | P13: =proceso20 -> 0 | Q13: =IFERROR(VLOOKUP(P13,Datos!$L$1:$M$51,2,FALSE),"")
D15: =proceso21 -> 0 | E15: =IFERROR(VLOOKUP(D15,Datos!$L$1:$M$51,2,FALSE),"") | G15: =proceso22 -> 0 | H15: =IFERROR(VLOOKUP(G15,Datos!$L$1:$M$51,2,FALSE),"") | J15: =proceso23 -> 0 | K15: =IFERROR(VLOOKUP(J15,Datos!$L$1:$M$51,2,FALSE),"") | M15: =proceso24 -> 0 | N15: =IFERROR(VLOOKUP(M15,Datos!$L$1:$M$51,2,FALSE),"") | P15: =proceso25 -> 0 | Q15: =IFERROR(VLOOKUP(P15,Datos!$L$1:$M$51,2,FALSE),"")
D17: =proceso26 -> 0 | E17: =IFERROR(VLOOKUP(D17,Datos!$L$1:$M$51,2,FALSE),"") | G17: =proceso27 -> 0 | H17: =IFERROR(VLOOKUP(G17,Datos!$L$1:$M$51,2,FALSE),"") | J17: =proceso28 -> 0 | K17: =IFERROR(VLOOKUP(J17,Datos!$L$1:$M$51,2,FALSE),"") | M17: =proceso29 -> 0 | N17: =IFERROR(VLOOKUP(M17,Datos!$L$1:$M$51,2,FALSE),"") | P17: =proceso30 -> 0 | Q17: =IFERROR(VLOOKUP(P17,Datos!$L$1:$M$51,2,FALSE),"")
D19: =proceso31 -> 0 | E19: =IFERROR(VLOOKUP(D19,Datos!$L$1:$M$51,2,FALSE),"") | G19: =proceso32 -> 0 | H19: =IFERROR(VLOOKUP(G19,Datos!$L$1:$M$51,2,FALSE),"") | J19: =proceso33 -> 0 | K19: =IFERROR(VLOOKUP(J19,Datos!$L$1:$M$51,2,FALSE),"") | M19: =proceso34 -> 0 | N19: =IFERROR(VLOOKUP(M19,Datos!$L$1:$M$51,2,FALSE),"") | P19: =proceso35 -> 0 | Q19: =IFERROR(VLOOKUP(P19,Datos!$L$1:$M$51,2,FALSE),"")
D21: Procesos de Apoyo o Soporte
D23: =proceso36 -> 0 | E23: =IFERROR(VLOOKUP(D23,Datos!$L$1:$M$51,2,FALSE),"") | G23: =proceso37 -> 0 | H23: =IFERROR(VLOOKUP(G23,Datos!$L$1:$M$51,2,FALSE),"") | J23: =proceso38 -> 0 | K23: =IFERROR(VLOOKUP(J23,Datos!$L$1:$M$51,2,FALSE),"") | M23: =proceso39 -> 0 | N23: =IFERROR(VLOOKUP(M23,Datos!$L$1:$M$51,2,FALSE),"") | P23: =proceso40 -> 0 | Q23: =IFERROR(VLOOKUP(P23,Datos!$L$1:$M$51,2,FALSE),"")
D25: =proceso41 -> 0 | E25: =IFERROR(VLOOKUP(D25,Datos!$L$1:$M$51,2,FALSE),"") | G25: =proceso42 -> 0 | H25: =IFERROR(VLOOKUP(G25,Datos!$L$1:$M$51,2,FALSE),"") | J25: =proceso43 -> 0 | K25: =IFERROR(VLOOKUP(J25,Datos!$L$1:$M$51,2,FALSE),"") | M25: =proceso44 -> 0 | N25: =IFERROR(VLOOKUP(M25,Datos!$L$1:$M$51,2,FALSE),"") | P25: =proceso45 -> 0 | Q25: =IFERROR(VLOOKUP(P25,Datos!$L$1:$M$51,2,FALSE),"")
D27: =proceso46 -> 0 | E27: =IFERROR(VLOOKUP(D27,Datos!$L$1:$M$51,2,FALSE),"") | G27: =proceso47 -> 0 | H27: =IFERROR(VLOOKUP(G27,Datos!$L$1:$M$51,2,FALSE),"") | J27: =proceso48 -> 0 | K27: =IFERROR(VLOOKUP(J27,Datos!$L$1:$M$51,2,FALSE),"") | M27: =proceso49 -> 0 | N27: =IFERROR(VLOOKUP(M27,Datos!$L$1:$M$51,2,FALSE),"") | P27: =proceso50 -> 0 | Q27: =IFERROR(VLOOKUP(P27,Datos!$L$1:$M$51,2,FALSE),"")

Sheet RESUM AUTOEV
C1: Resumen Autoevaluación Cuantitativa
B3: Eje de Seguridad | C3: (Todas)
B5: Práctica Segura | C5: Calificación Cuantitativa Promedio
B6: Total general

Sheet INDICADORES
D1: Definición de Calidad Esperada y Medición del Desempeño Ficha Técnica de Indicadores y Registro de Resultados
B3: Consecutivo | C3: Práctica(s) segura asociada(s) | D3: Nombre del Indicador | E3: Objetivo | F3: Calidad Esperada / Meta | G3: Medición Inicial del Desempeño | H3: Brecha | I3: Acceso
B4: 1 | C4: ='FT1'!$E$11&" - "&'FT1'!$N$11&" - "&'FT1'!$V$11 -> - - | D4: ='FT1'!E7 -> 0 | E4: ='FT1'!Q7 -> 0 | F4: ='FT1'!AA13 -> 0 | G4: ='FT1'!F26 -> 0 | H4: =indicadores[[#This Row],[Calidad Esperada / Meta]]-indicadores[[#This Row],[Medición Inicial del Desempeño]] -> 0 | I4: Ver ficha técnica y registrar resultados
B5: 2 | C5: ='FT2'!$E$11&" - "&'FT2'!$N$11&" - "&'FT2'!$V$11 -> - - | D5: ='FT2'!E7 -> 0 | E5: ='FT2'!Q7 -> 0 | F5: ='FT2'!AA13 -> 0 | G5: ='FT2'!F26 -> 0 | H5: =indicadores[[#This Row],[Calidad Esperada / Meta]]-indicadores[[#This Row],[Medición Inicial del Desempeño]] -> 0 | I5: Ver ficha técnica y registrar resultados
B6: 3 | C6: ='FT3'!$E$11&" - "&'FT3'!$N$11&" - "&'FT3'!$V$11 -> - - | D6: ='FT3'!E7 -> 0 | E6: ='FT3'!Q7 -> 0 | F6: ='FT3'!AA13 -> 0 | G6: ='FT3'!F26 -> 0 | H6: =indicadores[[#This Row],[Calidad Esperada / Meta]]-indicadores[[#This Row],[Medición Inicial del Desempeño]] -> 0 | I6: Ver ficha técnica y registrar resultados
B7: 4 | C7: ='FT4'!$E$11&" - "&'FT4'!$N$11&" - "&'FT4'!$V$11 -> - - | D7: ='FT4'!E7 -> 0 | E7: ='FT4'!Q7 -> 0 | F7: ='FT4'!AA13 -> 0 | G7: ='FT4'!F26 -> 0 | H7: =indicadores[[#This Row],[Calidad Esperada / Meta]]-indicadores[[#This Row],[Medición Inicial del Desempeño]] -> 0 | I7: Ver ficha técnica y registrar resultados
B8: 5 | C8: ='FT5'!$E$11&" - "&'FT5'!$N$11&" - "&'FT5'!$V$11 -> - - | D8: ='FT5'!E7 -> 0 | E8: ='FT5'!Q7 -> 0 | F8: ='FT5'!AA13 -> 0 | G8: ='FT5'!F26 -> 0 | H8: =indicadores[[#This Row],[Calidad Esperada / Meta]]-indicadores[[#This Row],[Medición Inicial del Desempeño]] -> 0 | I8: Ver ficha técnica y registrar resultados
B9: 6 | C9: ='FT6'!$E$11&" - "&'FT6'!$N$11&" - "&'FT6'!$V$11 -> - - | D9: ='FT6'!E7 -> 0 | E9: ='FT6'!Q7 -> 0 | F9: ='FT6'!AA13 -> 0 | G9: ='FT6'!F26 -> 0 | H9: =indicadores[[#This Row],[Calidad Esperada / Meta]]-indicadores[[#This Row],[Medición Inicial del Desempeño]] -> 0 | I9: Ver ficha técnica y registrar resultados
B10: 7 | C10: ='FT7'!$E$11&" - "&'FT7'!$N$11&" - "&'FT7'!$V$11 -> - - | D10: ='FT7'!E7 -> 0 | E10: ='FT7'!Q7 -> 0 | F10: ='FT7'!AA13 -> 0 | G10: ='FT7'!F26 -> 0 | H10: =indicadores[[#This Row],[Calidad Esperada / Meta]]-indicadores[[#This Row],[Medición Inicial del Desempeño]] -> 0 | I10: Ver ficha técnica y registrar resultados
B11: 8 | C11: ='FT8'!$E$11&" - "&'FT8'!$N$11&" - "&'FT8'!$V$11 -> - - | D11: ='FT8'!E7 -> 0 | E11: ='FT8'!Q7 -> 0 | F11: ='FT8'!AA13 -> 0 | G11: ='FT8'!F26 -> 0 | H11: =indicadores[[#This Row],[Calidad Esperada / Meta]]-indicadores[[#This Row],[Medición Inicial del Desempeño]] -> 0 | I11: Ver ficha técnica y registrar resultados
B12: 9 | C12: ='FT9'!$E$11&" - "&'FT9'!$N$11&" - "&'FT9'!$V$11 -> - - | D12: ='FT9'!E7 -> 0 | E12: ='FT9'!Q7 -> 0 | F12: ='FT9'!AA13 -> 0 | G12: ='FT9'!F26 -> 0 | H12: =indicadores[[#This Row],[Calidad Esperada / Meta]]-indicadores[[#This Row],[Medición Inicial del Desempeño]] -> 0 | I12: Ver ficha técnica y registrar resultados
B13: 10 | C13: ='FT10'!$E$11&" - "&'FT10'!$N$11&" - "&'FT10'!$V$11 -> - - | D13: ='FT10'!E7 -> 0 | E13: ='FT10'!Q7 -> 0 | F13: ='FT10'!AA13 -> 0 | G13: ='FT10'!F26 -> 0 | H13: =indicadores[[#This Row],[Calidad Esperada / Meta]]-indicadores[[#This Row],[Medición Inicial del Desempeño]] -> 0 | I13: Ver ficha técnica y registrar resultados
B14: 11 | C14: ='FT11'!$E$11&" - "&'FT11'!$N$11&" - "&'FT11'!$V$11 -> - - | D14: ='FT11'!E7 -> 0 | E14: ='FT11'!Q7 -> 0 | F14: ='FT11'!AA13 -> 0 | G14: ='FT11'!F26 -> 0 | H14: =indicadores[[#This Row],[Calidad Esperada / Meta]]-indicadores[[#This Row],[Medición Inicial del Desempeño]] -> 0 | I14: Ver ficha técnica y registrar resultados
B15: 12 | C15: ='FT12'!$E$11&" - "&'FT12'!$N$11&" - "&'FT12'!$V$11 -> - - | D15: ='FT12'!E7 -> 0 | E15: ='FT12'!Q7 -> 0 | F15: ='FT12'!AA13 -> 0 | G15: ='FT12'!F26 -> 0 | H15: =indicadores[[#This Row],[Calidad Esperada / Meta]]-indicadores[[#This Row],[Medición Inicial del Desempeño]] -> 0 | I15: Ver ficha técnica y registrar resultados
B16: 13 | C16: ='FT13'!$E$11&" - "&'FT13'!$N$11&" - "&'FT13'!$V$11 -> - - | D16: ='FT13'!E7 -> 0 | E16: ='FT13'!Q7 -> 0 | F16: ='FT13'!AA13 -> 0 | G16: ='FT13'!F26 -> 0 | H16: =indicadores[[#This Row],[Calidad Esperada / Meta]]-indicadores[[#This Row],[Medición Inicial del Desempeño]] -> 0 | I16: Ver ficha técnica y registrar resultados
B17: 14 | C17: ='FT14'!$E$11&" - "&'FT14'!$N$11&" - "&'FT14'!$V$11 -> - - | D17: ='FT14'!E7 -> 0 | E17: ='FT14'!Q7 -> 0 | F17: ='FT14'!AA13 -> 0 | G17: ='FT14'!F26 -> 0 | H17: =indicadores[[#This Row],[Calidad Esperada / Meta]]-indicadores[[#This Row],[Medición Inicial del Desempeño]] -> 0 | I17: Ver ficha técnica y registrar resultados
B18: 15 | C18: ='FT15'!$E$11&" - "&'FT15'!$N$11&" - "&'FT15'!$V$11 -> - - | D18: ='FT15'!E7 -> 0 | E18: ='FT15'!Q7 -> 0 | F18: ='FT15'!AA13 -> 0 | G18: ='FT15'!F26 -> 0 | H18: =indicadores[[#This Row],[Calidad Esperada / Meta]]-indicadores[[#This Row],[Medición Inicial del Desempeño]] -> 0 | I18: Ver ficha técnica y registrar resultados
B19: 16 | C19: ='FT16'!$E$11&" - "&'FT16'!$N$11&" - "&'FT16'!$V$11 -> - - | D19: ='FT16'!E7 -> 0 | E19: ='FT16'!Q7 -> 0 | F19: ='FT16'!AA13 -> 0 | G19: ='FT16'!F26 -> 0 | H19: =indicadores[[#This Row],[Calidad Esperada / Meta]]-indicadores[[#This Row],[Medición Inicial del Desempeño]] -> 0 | I19: Ver ficha técnica y registrar resultados
B20: 17 | C20: ='FT17'!$E$11&" - "&'FT17'!$N$11&" - "&'FT17'!$V$11 -> - - | D20: ='FT17'!E7 -> 0 | E20: ='FT17'!Q7 -> 0 | F20: ='FT17'!AA13 -> 0 | G20: ='FT17'!F26 -> 0 | H20: =indicadores[[#This Row],[Calidad Esperada / Meta]]-indicadores[[#This Row],[Medición Inicial del Desempeño]] -> 0 | I20: Ver ficha técnica y registrar resultados
B21: 18 | C21: ='FT18'!$E$11&" - "&'FT18'!$N$11&" - "&'FT18'!$V$11 -> - - | D21: ='FT18'!E7 -> 0 | E21: ='FT18'!Q7 -> 0 | F21: ='FT18'!AA13 -> 0 | G21: ='FT18'!F26 -> 0 | H21: =indicadores[[#This Row],[Calidad Esperada / Meta]]-indicadores[[#This Row],[Medición Inicial del Desempeño]] -> 0 | I21: Ver ficha técnica y registrar resultados
B22: 19 | C22: ='FT19'!$E$11&" - "&'FT19'!$N$11&" - "&'FT19'!$V$11 -> - - | D22: ='FT19'!E7 -> 0 | E22: ='FT19'!Q7 -> 0 | F22: ='FT19'!AA13 -> 0 | G22: ='FT19'!F26 -> 0 | H22: =indicadores[[#This Row],[Calidad Esperada / Meta]]-indicadores[[#This Row],[Medición Inicial del Desempeño]] -> 0 | I22: Ver ficha técnica y registrar resultados
B23: 20 | C23: ='FT20'!$E$11&" - "&'FT20'!$N$11&" - "&'FT20'!$V$11 -> - - | D23: ='FT20'!E7 -> 0 | E23: ='FT20'!Q7 -> 0 | F23: ='FT20'!AA13 -> 0 | G23: ='FT20'!F26 -> 0 | H23: =indicadores[[#This Row],[Calidad Esperada / Meta]]-indicadores[[#This Row],[Medición Inicial del Desempeño]] -> 0 | I23: Ver ficha técnica y registrar resultados
B24: 21 | C24: ='FT21'!$E$11&" - "&'FT21'!$N$11&" - "&'FT21'!$V$11 -> - - | D24: ='FT21'!E7 -> 0 | E24: ='FT21'!Q7 -> 0 | F24: ='FT21'!AA13 -> 0 | G24: ='FT21'!F26 -> 0 | H24: =indicadores[[#This Row],[Calidad Esperada / Meta]]-indicadores[[#This Row],[Medición Inicial del Desempeño]] -> 0 | I24: Ver ficha técnica y registrar resultados
B25: 22 | C25: ='FT22'!$E$11&" - "&'FT22'!$N$11&" - "&'FT22'!$V$11 -> - - | D25: ='FT22'!E7 -> 0 | E25: ='FT22'!Q7 -> 0 | F25: ='FT22'!AA13 -> 0 | G25: ='FT22'!F26 -> 0 | H25: =indicadores[[#This Row],[Calidad Esperada / Meta]]-indicadores[[#This Row],[Medición Inicial del Desempeño]] -> 0 | I25: Ver ficha técnica y registrar resultados
B26: 23 | C26: ='FT23'!$E$11&" - "&'FT23'!$N$11&" - "&'FT23'!$V$11 -> - - | D26: ='FT23'!E7 -> 0 | E26: ='FT23'!Q7 -> 0 | F26: ='FT23'!AA13 -> 0 | G26: ='FT23'!F26 -> 0 | H26: =indicadores[[#This Row],[Calidad Esperada / Meta]]-indicadores[[#This Row],[Medición Inicial del Desempeño]] -> 0 | I26: Ver ficha técnica y registrar resultados
B27: 24 | C27: ='FT24'!$E$11&" - "&'FT24'!$N$11&" - "&'FT24'!$V$11 -> - - | D27: ='FT24'!E7 -> 0 | E27: ='FT24'!Q7 -> 0 | F27: ='FT24'!AA13 -> 0 | G27: ='FT24'!F26 -> 0 | H27: =indicadores[[#This Row],[Calidad Esperada / Meta]]-indicadores[[#This Row],[Medición Inicial del Desempeño]] -> 0 | I27: Ver ficha técnica y registrar resultados
B28: 25 | C28: ='FT25'!$E$11&" - "&'FT25'!$N$11&" - "&'FT25'!$V$11 -> - - | D28: ='FT25'!E7 -> 0 | E28: ='FT25'!Q7 -> 0 | F28: ='FT25'!AA13 -> 0 | G28: ='FT25'!F26 -> 0 | H28: =indicadores[[#This Row],[Calidad Esperada / Meta]]-indicadores[[#This Row],[Medición Inicial del Desempeño]] -> 0 | I28: Ver ficha técnica y registrar resultados
B29: 26 | C29: ='FT26'!$E$11&" - "&'FT26'!$N$11&" - "&'FT26'!$V$11 -> - - | D29: ='FT26'!E7 -> 0 | E29: ='FT26'!Q7 -> 0 | F29: ='FT26'!AA13 -> 0 | G29: ='FT26'!F26 -> 0 | H29: =indicadores[[#This Row],[Calidad Esperada / Meta]]-indicadores[[#This Row],[Medición Inicial del Desempeño]] -> 0 | I29: Ver ficha técnica y registrar resultados
B30: 27 | C30: ='FT27'!$E$11&" - "&'FT27'!$N$11&" - "&'FT27'!$V$11 -> - - | D30: ='FT27'!E7 -> 0 | E30: ='FT27'!Q7 -> 0 | F30: ='FT27'!AA13 -> 0 | G30: ='FT27'!F26 -> 0 | H30: =indicadores[[#This Row],[Calidad Esperada / Meta]]-indicadores[[#This Row],[Medición Inicial del Desempeño]] -> 0 | I30: Ver ficha técnica y registrar resultados
B31: 28 | C31: ='FT28'!$E$11&" - "&'FT28'!$N$11&" - "&'FT28'!$V$11 -> - - | D31: ='FT28'!E7 -> 0 | E31: ='FT28'!Q7 -> 0 | F31: ='FT28'!AA13 -> 0 | G31: ='FT28'!F26 -> 0 | H31: =indicadores[[#This Row],[Calidad Esperada / Meta]]-indicadores[[#This Row],[Medición Inicial del Desempeño]] -> 0 | I31: Ver ficha técnica y registrar resultados
B32: 29 | C32: ='FT29'!$E$11&" - "&'FT29'!$N$11&" - "&'FT29'!$V$11 -> - - | D32: ='FT29'!E7 -> 0 | E32: ='FT29'!Q7 -> 0 | F32: ='FT29'!AA13 -> 0 | G32: ='FT29'!F26 -> 0 | H32: =indicadores[[#This Row],[Calidad Esperada / Meta]]-indicadores[[#This Row],[Medición Inicial del Desempeño]] -> 0 | I32: Ver ficha técnica y registrar resultados
B33: 30 | C33: ='FT30'!$E$11&" - "&'FT30'!$N$11&" - "&'FT30'!$V$11 -> - - | D33: ='FT30'!E7 -> 0 | E33: ='FT30'!Q7 -> 0 | F33: ='FT30'!AA13 -> 0 | G33: ='FT30'!F26 -> 0 | H33: =indicadores[[#This Row],[Calidad Esperada / Meta]]-indicadores[[#This Row],[Medición Inicial del Desempeño]] -> 0 | I33: Ver ficha técnica y registrar resultados

Sheet AUDITORIAS
C1: Programación de Auditorias para la Medición del Desempeño
B3: Etapa | C3: Proceso a auditar | D3: Procedimiento/ Actividad a auditar | E3: Objetivo de la auditoria | F3: Criterios a auditar | G3: Fecha programada de la auditoria | H3: Responsable (s) | I3: Fecha de ejecución de la auditoria | J3: Causas de incumplimiento | K3: Observaciones

Sheet RESULT AUDITORIAS
C1: Resultado de Auditorias para la Medición del Desempeño y Evaluación del Mejoramiento
B3: Escala resultados Cualitativos | C3: Óptimo (mayor o igual que) | D3: 4
C4: Aceptable (mayor o igual que) | D4: 3
C5: Insuficiente (menor que) | D5: 3
B7: Etapa | C7: Proceso auditado | D7: Procedimiento auditado | E7: Fecha de ejecución | F7: ¿Se cumplió la auditoria? | G7: Causas de incumplimiento | H7: Calificación Enfoque | I7: Calificación Implemen. | J7: Calificación Resultados | K7: Calificación Total | L7: Calificación cualitativa | M7: Fortalezas evidenciadas | N7: Hallazgos evidenciados | O7: Oportunidades de Mejora en el proceso / práctica segura
B8: =AUDITORIAS!B4 -> 0 | C8: =AUDITORIAS!C4 -> 0 | D8: =AUDITORIAS!D4 -> 0 | E8: =AUDITORIAS!I4 -> 0 | K8: =IFERROR(AVERAGE(resultadoauditorias[[#This Row],[Calificación Enfoque]:[Calificación Resultados]]),"") | L8: =IF(resultadoauditorias[[#This Row],[Calificación Total]]="","",IF(resultadoauditorias[[#This Row],[Calificación Total]]>=$D$3,"Óptimo",IF(resultadoauditorias[[#This Row],[Calificación Total]]>=$D$4,"Aceptable",IF(resultadoauditorias[[#This Row],[Calificación Total]]<$D$5,"Insuficiente",""))))
B9: =AUDITORIAS!B5 -> 0 | C9: =AUDITORIAS!C5 -> 0 | D9: =AUDITORIAS!D5 -> 0 | E9: =AUDITORIAS!I5 -> 0 | K9: =IFERROR(AVERAGE(resultadoauditorias[[#This Row],[Calificación Enfoque]:[Calificación Resultados]]),"") | L9: =IF(resultadoauditorias[[#This Row],[Calificación Total]]="","",IF(resultadoauditorias[[#This Row],[Calificación Total]]>=$D$3,"Óptimo",IF(resultadoauditorias[[#This Row],[Calificación Total]]>=$D$4,"Aceptable",IF(resultadoauditorias[[#This Row],[Calificación Total]]<$D$5,"Insuficiente",""))))
B10: =AUDITORIAS!B6 -> 0 | C10: =AUDITORIAS!C6 -> 0 | D10: =AUDITORIAS!D6 -> 0 | E10: =AUDITORIAS!I6 -> 0 | K10: =IFERROR(AVERAGE(resultadoauditorias[[#This Row],[Calificación Enfoque]:[Calificación Resultados]]),"") | L10: =IF(resultadoauditorias[[#This Row],[Calificación Total]]="","",IF(resultadoauditorias[[#This Row],[Calificación Total]]>=$D$3,"Óptimo",IF(resultadoauditorias[[#This Row],[Calificación Total]]>=$D$4,"Aceptable",IF(resultadoauditorias[[#This Row],[Calificación Total]]<$D$5,"Insuficiente",""))))
B11: =AUDITORIAS!B7 -> 0 | C11: =AUDITORIAS!C7 -> 0 | D11: =AUDITORIAS!D7 -> 0 | E11: =AUDITORIAS!I7 -> 0 | K11: =IFERROR(AVERAGE(resultadoauditorias[[#This Row],[Calificación Enfoque]:[Calificación Resultados]]),"") | L11: =IF(resultadoauditorias[[#This Row],[Calificación Total]]="","",IF(resultadoauditorias[[#This Row],[Calificación Total]]>=$D$3,"Óptimo",IF(resultadoauditorias[[#This Row],[Calificación Total]]>=$D$4,"Aceptable",IF(resultadoauditorias[[#This Row],[Calificación Total]]<$D$5,"Insuficiente",""))))
B12: =AUDITORIAS!B8 -> 0 | C12: =AUDITORIAS!C8 -> 0 | D12: =AUDITORIAS!D8 -> 0 | E12: =AUDITORIAS!I8 -> 0 | K12: =IFERROR(AVERAGE(resultadoauditorias[[#This Row],[Calificación Enfoque]:[Calificación Resultados]]),"") | L12: =IF(resultadoauditorias[[#This Row],[Calificación Total]]="","",IF(resultadoauditorias[[#This Row],[Calificación Total]]>=$D$3,"Óptimo",IF(resultadoauditorias[[#This Row],[Calificación Total]]>=$D$4,"Aceptable",IF(resultadoauditorias[[#This Row],[Calificación Total]]<$D$5,"Insuficiente",""))))
B13: =AUDITORIAS!B9 -> 0 | C13: =AUDITORIAS!C9 -> 0 | D13: =AUDITORIAS!D9 -> 0 | E13: =AUDITORIAS!I9 -> 0 | K13: =IFERROR(AVERAGE(resultadoauditorias[[#This Row],[Calificación Enfoque]:[Calificación Resultados]]),"") | L13: =IF(resultadoauditorias[[#This Row],[Calificación Total]]="","",IF(resultadoauditorias[[#This Row],[Calificación Total]]>=$D$3,"Óptimo",IF(resultadoauditorias[[#This Row],[Calificación Total]]>=$D$4,"Aceptable",IF(resultadoauditorias[[#This Row],[Calificación Total]]<$D$5,"Insuficiente",""))))
B14: =AUDITORIAS!B10 -> 0 | C14: =AUDITORIAS!C10 -> 0 | D14: =AUDITORIAS!D10 -> 0 | E14: =AUDITORIAS!I10 -> 0 | K14: =IFERROR(AVERAGE(resultadoauditorias[[#This Row],[Calificación Enfoque]:[Calificación Resultados]]),"") | L14: =IF(resultadoauditorias[[#This Row],[Calificación Total]]="","",IF(resultadoauditorias[[#This Row],[Calificación Total]]>=$D$3,"Óptimo",IF(resultadoauditorias[[#This Row],[Calificación Total]]>=$D$4,"Aceptable",IF(resultadoauditorias[[#This Row],[Calificación Total]]<$D$5,"Insuficiente",""))))
B15: =AUDITORIAS!B11 -> 0 | C15: =AUDITORIAS!C11 -> 0 | D15: =AUDITORIAS!D11 -> 0 | E15: =AUDITORIAS!I11 -> 0 | K15: =IFERROR(AVERAGE(resultadoauditorias[[#This Row],[Calificación Enfoque]:[Calificación Resultados]]),"") | L15: =IF(resultadoauditorias[[#This Row],[Calificación Total]]="","",IF(resultadoauditorias[[#This Row],[Calificación Total]]>=$D$3,"Óptimo",IF(resultadoauditorias[[#This Row],[Calificación Total]]>=$D$4,"Aceptable",IF(resultadoauditorias[[#This Row],[Calificación Total]]<$D$5,"Insuficiente",""))))
B16: =AUDITORIAS!B12 -> 0 | C16: =AUDITORIAS!C12 -> 0 | D16: =AUDITORIAS!D12 -> 0 | E16: =AUDITORIAS!I12 -> 0 | K16: =IFERROR(AVERAGE(resultadoauditorias[[#This Row],[Calificación Enfoque]:[Calificación Resultados]]),"") | L16: =IF(resultadoauditorias[[#This Row],[Calificación Total]]="","",IF(resultadoauditorias[[#This Row],[Calificación Total]]>=$D$3,"Óptimo",IF(resultadoauditorias[[#This Row],[Calificación Total]]>=$D$4,"Aceptable",IF(resultadoauditorias[[#This Row],[Calificación Total]]<$D$5,"Insuficiente",""))))
B17: =AUDITORIAS!B13 -> 0 | C17: =AUDITORIAS!C13 -> 0 | D17: =AUDITORIAS!D13 -> 0 | E17: =AUDITORIAS!I13 -> 0 | K17: =IFERROR(AVERAGE(resultadoauditorias[[#This Row],[Calificación Enfoque]:[Calificación Resultados]]),"") | L17: =IF(resultadoauditorias[[#This Row],[Calificación Total]]="","",IF(resultadoauditorias[[#This Row],[Calificación Total]]>=$D$3,"Óptimo",IF(resultadoauditorias[[#This Row],[Calificación Total]]>=$D$4,"Aceptable",IF(resultadoauditorias[[#This Row],[Calificación Total]]<$D$5,"Insuficiente",""))))
B18: =AUDITORIAS!B14 -> 0 | C18: =AUDITORIAS!C14 -> 0 | D18: =AUDITORIAS!D14 -> 0 | E18: =AUDITORIAS!I14 -> 0 | K18: =IFERROR(AVERAGE(resultadoauditorias[[#This Row],[Calificación Enfoque]:[Calificación Resultados]]),"") | L18: =IF(resultadoauditorias[[#This Row],[Calificación Total]]="","",IF(resultadoauditorias[[#This Row],[Calificación Total]]>=$D$3,"Óptimo",IF(resultadoauditorias[[#This Row],[Calificación Total]]>=$D$4,"Aceptable",IF(resultadoauditorias[[#This Row],[Calificación Total]]<$D$5,"Insuficiente",""))))
B19: =AUDITORIAS!B15 -> 0 | C19: =AUDITORIAS!C15 -> 0 | D19: =AUDITORIAS!D15 -> 0 | E19: =AUDITORIAS!I15 -> 0 | K19: =IFERROR(AVERAGE(resultadoauditorias[[#This Row],[Calificación Enfoque]:[Calificación Resultados]]),"") | L19: =IF(resultadoauditorias[[#This Row],[Calificación Total]]="","",IF(resultadoauditorias[[#This Row],[Calificación Total]]>=$D$3,"Óptimo",IF(resultadoauditorias[[#This Row],[Calificación Total]]>=$D$4,"Aceptable",IF(resultadoauditorias[[#This Row],[Calificación Total]]<$D$5,"Insuficiente",""))))
... B57: =AUDITORIAS!B53 -> 0 | C57: =AUDITORIAS!C53 -> 0 | D57: =AUDITORIAS!D53 -> 0 | E57: =AUDITORIAS!I53 -> 0 | K57: =IFERROR(AVERAGE(resultadoauditorias[[#This Row],[Calificación Enfoque]:[Calificación Resultados]]),"") | L57: =IF(resultadoauditorias[[#This Row],[Calificación Total]]="","",IF(resultadoauditorias[[#This Row],[Calificación Total]]>=$D$3,"Óptimo",IF(resultadoauditorias[[#This Row],[Calificación Total]]>=$D$4,"Aceptable",IF(resultadoauditorias[[#This Row],[Calificación Total]]<$D$5,"Insuficiente",""))))

Sheet PLAN ACCION
D1: Definición de Plan de Acción Prácticas Seguras y Procesos Priorizados
B3: Consec. | C3: Eje Seguridad | D3: Práctica Segura | E3: Criterio | F3: Oportunidad de Mejora | G3: Qué / Acción | H3: Cómo | I3: Por qué | J3: Dónde | K3: Quién | L3: Cuándo inicia | M3: Cuando Finaliza | N3: Estado
B4: 1 | C4: =IFERROR(INDEX('CONS AUTOEV'!$C$5:$C$204,MATCH('PLAN ACCION'!B4,'CONS AUTOEV'!$Q$5:$Q$204,0)), "") | D4: =IFERROR(INDEX('CONS AUTOEV'!$D$5:$D$204,MATCH('PLAN ACCION'!B4,'CONS AUTOEV'!$Q$5:$Q$204,0)), "") | E4: =IFERROR(INDEX('CONS AUTOEV'!$E$5:$E$204,MATCH('PLAN ACCION'!B4,'CONS AUTOEV'!$Q$5:$Q$204,0)), "") | F4: =IFERROR(INDEX('CONS AUTOEV'!$G$5:$G$204,MATCH('PLAN ACCION'!B4,'CONS AUTOEV'!$Q$5:$Q$204,0)), "") | G4: P: H: V: A: | N4: =IF(planaccion[[#This Row],[Eje Seguridad]]="","",seguimientoplan[[#This Row],[Estado Actual]])
B5: 2 | C5: =IFERROR(INDEX('CONS AUTOEV'!$C$5:$C$204,MATCH('PLAN ACCION'!B5,'CONS AUTOEV'!$Q$5:$Q$204,0)), "") | D5: =IFERROR(INDEX('CONS AUTOEV'!$D$5:$D$204,MATCH('PLAN ACCION'!B5,'CONS AUTOEV'!$Q$5:$Q$204,0)), "") | E5: =IFERROR(INDEX('CONS AUTOEV'!$E$5:$E$204,MATCH('PLAN ACCION'!B5,'CONS AUTOEV'!$Q$5:$Q$204,0)), "") | F5: =IFERROR(INDEX('CONS AUTOEV'!$G$5:$G$204,MATCH('PLAN ACCION'!B5,'CONS AUTOEV'!$Q$5:$Q$204,0)), "") | G5: P: H: V: A: | N5: =IF(planaccion[[#This Row],[Eje Seguridad]]="","",seguimientoplan[[#This Row],[Estado Actual]])
B6: 3 | C6: =IFERROR(INDEX('CONS AUTOEV'!$C$5:$C$204,MATCH('PLAN ACCION'!B6,'CONS AUTOEV'!$Q$5:$Q$204,0)), "") | D6: =IFERROR(INDEX('CONS AUTOEV'!$D$5:$D$204,MATCH('PLAN ACCION'!B6,'CONS AUTOEV'!$Q$5:$Q$204,0)), "") | E6: =IFERROR(INDEX('CONS AUTOEV'!$E$5:$E$204,MATCH('PLAN ACCION'!B6,'CONS AUTOEV'!$Q$5:$Q$204,0)), "") | F6: =IFERROR(INDEX('CONS AUTOEV'!$G$5:$G$204,MATCH('PLAN ACCION'!B6,'CONS AUTOEV'!$Q$5:$Q$204,0)), "") | G6: P: H: V: A: | N6: =IF(planaccion[[#This Row],[Eje Seguridad]]="","",seguimientoplan[[#This Row],[Estado Actual]])
B7: 4 | C7: =IFERROR(INDEX('CONS AUTOEV'!$C$5:$C$204,MATCH('PLAN ACCION'!B7,'CONS AUTOEV'!$Q$5:$Q$204,0)), "") | D7: =IFERROR(INDEX('CONS AUTOEV'!$D$5:$D$204,MATCH('PLAN ACCION'!B7,'CONS AUTOEV'!$Q$5:$Q$204,0)), "") | E7: =IFERROR(INDEX('CONS AUTOEV'!$E$5:$E$204,MATCH('PLAN ACCION'!B7,'CONS AUTOEV'!$Q$5:$Q$204,0)), "") | F7: =IFERROR(INDEX('CONS AUTOEV'!$G$5:$G$204,MATCH('PLAN ACCION'!B7,'CONS AUTOEV'!$Q$5:$Q$204,0)), "") | G7: P: H: V: A: | N7: =IF(planaccion[[#This Row],[Eje Seguridad]]="","",seguimientoplan[[#This Row],[Estado Actual]])
B8: 5 | C8: =IFERROR(INDEX('CONS AUTOEV'!$C$5:$C$204,MATCH('PLAN ACCION'!B8,'CONS AUTOEV'!$Q$5:$Q$204,0)), "") | D8: =IFERROR(INDEX('CONS AUTOEV'!$D$5:$D$204,MATCH('PLAN ACCION'!B8,'CONS AUTOEV'!$Q$5:$Q$204,0)), "") | E8: =IFERROR(INDEX('CONS AUTOEV'!$E$5:$E$204,MATCH('PLAN ACCION'!B8,'CONS AUTOEV'!$Q$5:$Q$204,0)), "") | F8: =IFERROR(INDEX('CONS AUTOEV'!$G$5:$G$204,MATCH('PLAN ACCION'!B8,'CONS AUTOEV'!$Q$5:$Q$204,0)), "") | G8: P: H: V: A: | N8: =IF(planaccion[[#This Row],[Eje Seguridad]]="","",seguimientoplan[[#This Row],[Estado Actual]])
B9: 6 | C9: =IFERROR(INDEX('CONS AUTOEV'!$C$5:$C$204,MATCH('PLAN ACCION'!B9,'CONS AUTOEV'!$Q$5:$Q$204,0)), "") | D9: =IFERROR(INDEX('CONS AUTOEV'!$D$5:$D$204,MATCH('PLAN ACCION'!B9,'CONS AUTOEV'!$Q$5:$Q$204,0)), "") | E9: =IFERROR(INDEX('CONS AUTOEV'!$E$5:$E$204,MATCH('PLAN ACCION'!B9,'CONS AUTOEV'!$Q$5:$Q$204,0)), "") | F9: =IFERROR(INDEX('CONS AUTOEV'!$G$5:$G$204,MATCH('PLAN ACCION'!B9,'CONS AUTOEV'!$Q$5:$Q$204,0)), "") | G9: P: H: V: A: | N9: =IF(planaccion[[#This Row],[Eje Seguridad]]="","",seguimientoplan[[#This Row],[Estado Actual]])
B10: 7 | C10: =IFERROR(INDEX('CONS AUTOEV'!$C$5:$C$204,MATCH('PLAN ACCION'!B10,'CONS AUTOEV'!$Q$5:$Q$204,0)), "") | D10: =IFERROR(INDEX('CONS AUTOEV'!$D$5:$D$204,MATCH('PLAN ACCION'!B10,'CONS AUTOEV'!$Q$5:$Q$204,0)), "") | E10: =IFERROR(INDEX('CONS AUTOEV'!$E$5:$E$204,MATCH('PLAN ACCION'!B10,'CONS AUTOEV'!$Q$5:$Q$204,0)), "") | F10: =IFERROR(INDEX('CONS AUTOEV'!$G$5:$G$204,MATCH('PLAN ACCION'!B10,'CONS AUTOEV'!$Q$5:$Q$204,0)), "") | G10: P: H: V: A: | N10: =IF(planaccion[[#This Row],[Eje Seguridad]]="","",seguimientoplan[[#This Row],[Estado Actual]])
B11: 8 | C11: =IFERROR(INDEX('CONS AUTOEV'!$C$5:$C$204,MATCH('PLAN ACCION'!B11,'CONS AUTOEV'!$Q$5:$Q$204,0)), "") | D11: =IFERROR(INDEX('CONS AUTOEV'!$D$5:$D$204,MATCH('PLAN ACCION'!B11,'CONS AUTOEV'!$Q$5:$Q$204,0)), "") | E11: =IFERROR(INDEX('CONS AUTOEV'!$E$5:$E$204,MATCH('PLAN ACCION'!B11,'CONS AUTOEV'!$Q$5:$Q$204,0)), "") | F11: =IFERROR(INDEX('CONS AUTOEV'!$G$5:$G$204,MATCH('PLAN ACCION'!B11,'CONS AUTOEV'!$Q$5:$Q$204,0)), "") | G11: P: H: V: A: | N11: =IF(planaccion[[#This Row],[Eje Seguridad]]="","",seguimientoplan[[#This Row],[Estado Actual]])
B12: 9 | C12: =IFERROR(INDEX('CONS AUTOEV'!$C$5:$C$204,MATCH('PLAN ACCION'!B12,'CONS AUTOEV'!$Q$5:$Q$204,0)), "") | D12: =IFERROR(INDEX('CONS AUTOEV'!$D$5:$D$204,MATCH('PLAN ACCION'!B12,'CONS AUTOEV'!$Q$5:$Q$204,0)), "") | E12: =IFERROR(INDEX('CONS AUTOEV'!$E$5:$E$204,MATCH('PLAN ACCION'!B12,'CONS AUTOEV'!$Q$5:$Q$204,0)), "") | F12: =IFERROR(INDEX('CONS AUTOEV'!$G$5:$G$204,MATCH('PLAN ACCION'!B12,'CONS AUTOEV'!$Q$5:$Q$204,0)), "") | G12: P: H: V: A: | N12: =IF(planaccion[[#This Row],[Eje Seguridad]]="","",seguimientoplan[[#This Row],[Estado Actual]])
B13: 10 | C13: =IFERROR(INDEX('CONS AUTOEV'!$C$5:$C$204,MATCH('PLAN ACCION'!B13,'CONS AUTOEV'!$Q$5:$Q$204,0)), "") | D13: =IFERROR(INDEX('CONS AUTOEV'!$D$5:$D$204,MATCH('PLAN ACCION'!B13,'CONS AUTOEV'!$Q$5:$Q$204,0)), "") | E13: =IFERROR(INDEX('CONS AUTOEV'!$E$5:$E$204,MATCH('PLAN ACCION'!B13,'CONS AUTOEV'!$Q$5:$Q$204,0)), "") | F13: =IFERROR(INDEX('CONS AUTOEV'!$G$5:$G$204,MATCH('PLAN ACCION'!B13,'CONS AUTOEV'!$Q$5:$Q$204,0)), "") | G13: P: H: V: A: | N13: =IF(planaccion[[#This Row],[Eje Seguridad]]="","",seguimientoplan[[#This Row],[Estado Actual]])
B14: 11 | C14: =IFERROR(INDEX('CONS AUTOEV'!$C$5:$C$204,MATCH('PLAN ACCION'!B14,'CONS AUTOEV'!$Q$5:$Q$204,0)), "") | D14: =IFERROR(INDEX('CONS AUTOEV'!$D$5:$D$204,MATCH('PLAN ACCION'!B14,'CONS AUTOEV'!$Q$5:$Q$204,0)), "") | E14: =IFERROR(INDEX('CONS AUTOEV'!$E$5:$E$204,MATCH('PLAN ACCION'!B14,'CONS AUTOEV'!$Q$5:$Q$204,0)), "") | F14: =IFERROR(INDEX('CONS AUTOEV'!$G$5:$G$204,MATCH('PLAN ACCION'!B14,'CONS AUTOEV'!$Q$5:$Q$204,0)), "") | G14: P: H: V: A: | N14: =IF(planaccion[[#This Row],[Eje Seguridad]]="","",seguimientoplan[[#This Row],[Estado Actual]])
B15: 12 | C15: =IFERROR(INDEX('CONS AUTOEV'!$C$5:$C$204,MATCH('PLAN ACCION'!B15,'CONS AUTOEV'!$Q$5:$Q$204,0)), "") | D15: =IFERROR(INDEX('CONS AUTOEV'!$D$5:$D$204,MATCH('PLAN ACCION'!B15,'CONS AUTOEV'!$Q$5:$Q$204,0)), "") | E15: =IFERROR(INDEX('CONS AUTOEV'!$E$5:$E$204,MATCH('PLAN ACCION'!B15,'CONS AUTOEV'!$Q$5:$Q$204,0)), "") | F15: =IFERROR(INDEX('CONS AUTOEV'!$G$5:$G$204,MATCH('PLAN ACCION'!B15,'CONS AUTOEV'!$Q$5:$Q$204,0)), "") | G15: P: H: V: A: | N15: =IF(planaccion[[#This Row],[Eje Seguridad]]="","",seguimientoplan[[#This Row],[Estado Actual]])
... B203: 200 | C203: =IFERROR(INDEX('CONS AUTOEV'!$C$5:$C$204,MATCH('PLAN ACCION'!B203,'CONS AUTOEV'!$Q$5:$Q$204,0)), "") | D203: =IFERROR(INDEX('CONS AUTOEV'!$D$5:$D$204,MATCH('PLAN ACCION'!B203,'CONS AUTOEV'!$Q$5:$Q$204,0)), "") | E203: =IFERROR(INDEX('CONS AUTOEV'!$E$5:$E$204,MATCH('PLAN ACCION'!B203,'CONS AUTOEV'!$Q$5:$Q$204,0)), "") | F203: =IFERROR(INDEX('CONS AUTOEV'!$G$5:$G$204,MATCH('PLAN ACCION'!B203,'CONS AUTOEV'!$Q$5:$Q$204,0)), "") | G203: P: H: V: A: | N203: =IF(planaccion[[#This Row],[Eje Seguridad]]="","",seguimientoplan[[#This Row],[Estado Actual]])

Sheet SEGUIM PLAN
D1: Seguimiento a la Ejecución del Plan de Acción Prácticas Seguras y Procesos Priorizados
B3: Consec. | C3: Práctica segura | D3: Criterio | E3: Oportunidad de Mejora | F3: Qué / Acción | G3: Fecha inicio | H3: Estado Actual | I3: Fecha Seg. 1 | J3: Observaciones Seg. 1 | K3: Estado Acción Seg. 1 | L3: Desafíos en la Ejecución del Plan Seg 1 | M3: Fecha Seg. 2 | N3: Observaciones Seg. 2 | O3: Estado Acción Seg. 2 | P3: Desafíos en la Ejecución del Plan Seg 2 | Q3: Fecha Seg. 3 | R3: Observaciones Seg. 3 | S3: Estado Acción Seg. 3 | T3: Desafíos en la Ejecución del Plan Seg 3 | U3: Fecha Seg. 4 | V3: Observaciones Seg. 4 | W3: Estado Acción Seg. 4 | X3: Desafíos en la Ejecución del Plan Seg 4 | Y3: Fecha Seg. 5 | Z3: Observaciones Seg. 5 | AA3: Estado Acción Seg. 5 | AB3: Desafíos en la Ejecución del Plan Seg 5 | AC3: Fecha Seg. 6 | AD3: Observaciones Seg. 6 | AE3: Estado Acción Seg. 6 | AF3: Desafíos en la Ejecución del Plan Seg 6 | AG3: Fecha Seg. 7 | AH3: Observaciones Seg. 7 | AI3: Estado Acción Seg. 7 | AJ3: Desafíos en la Ejecución del Plan Seg 7 | AK3: Fecha Seg. 8 | AL3: Observaciones Seg. 8 | AM3: Estado Acción Seg. 8 | AN3: Desafíos en la Ejecución del Plan Seg 8 | AO3: Fecha Seg. 9 | AP3: Observaciones Seg. 9 | AQ3: Estado Acción Seg. 9 | AR3: Desafíos en la Ejecución del Plan Seg 9 | AS3: Fecha Seg. 10 | AT3: Observaciones Seg. 10 | AU3: Estado Acción Seg. 10 | AV3: Desafíos en la Ejecución del Plan Seg 10 | AW3: Fecha Seg. 11 | AX3: Observaciones Seg. 11 | AY3: Estado Acción Seg. 11 | AZ3: Desafíos en la Ejecución del Plan Seg 11 | BA3: Fecha Seg. 12 | BB3: Observaciones Seg. 12 | BC3: Estado Acción Seg. 12 | BD3: Desafíos en la Ejecución del Plan Seg 12
B4: 1 | C4: =planaccion[[#This Row],[Práctica Segura]] | D4: =planaccion[[#This Row],[Criterio]] | E4: =planaccion[[#This Row],[Oportunidad de Mejora]] | F4: =planaccion[[#This Row],[Qué / Acción]] -> P: H: V: A: | G4: =planaccion[[#This Row],[Cuándo inicia]] -> 0 | H4: =IF(seguimientoplan[[#This Row],[Práctica segura]]="","",IFERROR(IF(MATCH("Cerrada",seguimientoplan[[#This Row],[Estado Acción Seg. 1]:[Estado Acción Seg. 12]],0),"Cerrada"),"Abierta"))
B5: 2 | C5: =planaccion[[#This Row],[Práctica Segura]] | D5: =planaccion[[#This Row],[Criterio]] | E5: =planaccion[[#This Row],[Oportunidad de Mejora]] | F5: =planaccion[[#This Row],[Qué / Acción]] -> P: H: V: A: | G5: =planaccion[[#This Row],[Cuándo inicia]] -> 0 | H5: =IF(seguimientoplan[[#This Row],[Práctica segura]]="","",IFERROR(IF(MATCH("Cerrada",seguimientoplan[[#This Row],[Estado Acción Seg. 1]:[Estado Acción Seg. 12]],0),"Cerrada"),"Abierta"))
B6: 3 | C6: =planaccion[[#This Row],[Práctica Segura]] | D6: =planaccion[[#This Row],[Criterio]] | E6: =planaccion[[#This Row],[Oportunidad de Mejora]] | F6: =planaccion[[#This Row],[Qué / Acción]] -> P: H: V: A: | G6: =planaccion[[#This Row],[Cuándo inicia]] -> 0 | H6: =IF(seguimientoplan[[#This Row],[Práctica segura]]="","",IFERROR(IF(MATCH("Cerrada",seguimientoplan[[#This Row],[Estado Acción Seg. 1]:[Estado Acción Seg. 12]],0),"Cerrada"),"Abierta"))
B7: 4 | C7: =planaccion[[#This Row],[Práctica Segura]] | D7: =planaccion[[#This Row],[Criterio]] | E7: =planaccion[[#This Row],[Oportunidad de Mejora]] | F7: =planaccion[[#This Row],[Qué / Acción]] -> P: H: V: A: | G7: =planaccion[[#This Row],[Cuándo inicia]] -> 0 | H7: =IF(seguimientoplan[[#This Row],[Práctica segura]]="","",IFERROR(IF(MATCH("Cerrada",seguimientoplan[[#This Row],[Estado Acción Seg. 1]:[Estado Acción Seg. 12]],0),"Cerrada"),"Abierta"))
B8: 5 | C8: =planaccion[[#This Row],[Práctica Segura]] | D8: =planaccion[[#This Row],[Criterio]] | E8: =planaccion[[#This Row],[Oportunidad de Mejora]] | F8: =planaccion[[#This Row],[Qué / Acción]] -> P: H: V: A: | G8: =planaccion[[#This Row],[Cuándo inicia]] -> 0 | H8: =IF(seguimientoplan[[#This Row],[Práctica segura]]="","",IFERROR(IF(MATCH("Cerrada",seguimientoplan[[#This Row],[Estado Acción Seg. 1]:[Estado Acción Seg. 12]],0),"Cerrada"),"Abierta"))
B9: 6 | C9: =planaccion[[#This Row],[Práctica Segura]] | D9: =planaccion[[#This Row],[Criterio]] | E9: =planaccion[[#This Row],[Oportunidad de Mejora]] | F9: =planaccion[[#This Row],[Qué / Acción]] -> P: H: V: A: | G9: =planaccion[[#This Row],[Cuándo inicia]] -> 0 | H9: =IF(seguimientoplan[[#This Row],[Práctica segura]]="","",IFERROR(IF(MATCH("Cerrada",seguimientoplan[[#This Row],[Estado Acción Seg. 1]:[Estado Acción Seg. 12]],0),"Cerrada"),"Abierta"))
B10: 7 | C10: =planaccion[[#This Row],[Práctica Segura]] | D10: =planaccion[[#This Row],[Criterio]] | E10: =planaccion[[#This Row],[Oportunidad de Mejora]] | F10: =planaccion[[#This Row],[Qué / Acción]] -> P: H: V: A: | G10: =planaccion[[#This Row],[Cuándo inicia]] -> 0 | H10: =IF(seguimientoplan[[#This Row],[Práctica segura]]="","",IFERROR(IF(MATCH("Cerrada",seguimientoplan[[#This Row],[Estado Acción Seg. 1]:[Estado Acción Seg. 12]],0),"Cerrada"),"Abierta"))
B11: 8 | C11: =planaccion[[#This Row],[Práctica Segura]] | D11: =planaccion[[#This Row],[Criterio]] | E11: =planaccion[[#This Row],[Oportunidad de Mejora]] | F11: =planaccion[[#This Row],[Qué / Acción]] -> P: H: V: A: | G11: =planaccion[[#This Row],[Cuándo inicia]] -> 0 | H11: =IF(seguimientoplan[[#This Row],[Práctica segura]]="","",IFERROR(IF(MATCH("Cerrada",seguimientoplan[[#This Row],[Estado Acción Seg. 1]:[Estado Acción Seg. 12]],0),"Cerrada"),"Abierta"))
B12: 9 | C12: =planaccion[[#This Row],[Práctica Segura]] | D12: =planaccion[[#This Row],[Criterio]] | E12: =planaccion[[#This Row],[Oportunidad de Mejora]] | F12: =planaccion[[#This Row],[Qué / Acción]] -> P: H: V: A: | G12: =planaccion[[#This Row],[Cuándo inicia]] -> 0 | H12: =IF(seguimientoplan[[#This Row],[Práctica segura]]="","",IFERROR(IF(MATCH("Cerrada",seguimientoplan[[#This Row],[Estado Acción Seg. 1]:[Estado Acción Seg. 12]],0),"Cerrada"),"Abierta"))
B13: 10 | C13: =planaccion[[#This Row],[Práctica Segura]] | D13: =planaccion[[#This Row],[Criterio]] | E13: =planaccion[[#This Row],[Oportunidad de Mejora]] | F13: =planaccion[[#This Row],[Qué / Acción]] -> P: H: V: A: | G13: =planaccion[[#This Row],[Cuándo inicia]] -> 0 | H13: =IF(seguimientoplan[[#This Row],[Práctica segura]]="","",IFERROR(IF(MATCH("Cerrada",seguimientoplan[[#This Row],[Estado Acción Seg. 1]:[Estado Acción Seg. 12]],0),"Cerrada"),"Abierta"))
B14: 11 | C14: =planaccion[[#This Row],[Práctica Segura]] | D14: =planaccion[[#This Row],[Criterio]] | E14: =planaccion[[#This Row],[Oportunidad de Mejora]] | F14: =planaccion[[#This Row],[Qué / Acción]] -> P: H: V: A: | G14: =planaccion[[#This Row],[Cuándo inicia]] -> 0 | H14: =IF(seguimientoplan[[#This Row],[Práctica segura]]="","",IFERROR(IF(MATCH("Cerrada",seguimientoplan[[#This Row],[Estado Acción Seg. 1]:[Estado Acción Seg. 12]],0),"Cerrada"),"Abierta"))
B15: 12 | C15: =planaccion[[#This Row],[Práctica Segura]] | D15: =planaccion[[#This Row],[Criterio]] | E15: =planaccion[[#This Row],[Oportunidad de Mejora]] | F15: =planaccion[[#This Row],[Qué / Acción]] -> P: H: V: A: | G15: =planaccion[[#This Row],[Cuándo inicia]] -> 0 | H15: =IF(seguimientoplan[[#This Row],[Práctica segura]]="","",IFERROR(IF(MATCH("Cerrada",seguimientoplan[[#This Row],[Estado Acción Seg. 1]:[Estado Acción Seg. 12]],0),"Cerrada"),"Abierta"))
... B203: 200 | C203: =planaccion[[#This Row],[Práctica Segura]] | D203: =planaccion[[#This Row],[Criterio]] | E203: =planaccion[[#This Row],[Oportunidad de Mejora]] | F203: =planaccion[[#This Row],[Qué / Acción]] -> P: H: V: A: | G203: =planaccion[[#This Row],[Cuándo inicia]] -> 0 | H203: =IF(seguimientoplan[[#This Row],[Práctica segura]]="","",IFERROR(IF(MATCH("Cerrada",seguimientoplan[[#This Row],[Estado Acción Seg. 1]:[Estado Acción Seg. 12]],0),"Cerrada"),"Abierta"))

Sheet RESUMEN SEGUIM
B1: Resumen Plan de Acción: Estado de Acciones por Práctica Segura
A4: Cuenta de Estado | B4: Estado
A5: Práctica Segura
B6: 200
A7: Total general | B7: 200

Sheet APREND
C1: Aprendizaje Organizacional
B3: Indicadores de Efectividad e Implementación de la Ruta Critica del PAMEC
D5: Resultado | E5: Meta | F5: Oportunidades de mejora
B6: Ejecución del plan de acción | C6: Cantidad de acciones ejecutadas/Cantidad de acciones programadas | D6: =IFERROR(COUNTIFS(seguimientoplan[Estado Actual],"Cerrada")/(200-COUNTBLANK(seguimientoplan[Criterio])),"") | E6: 1
B8: Ejecución del programa de auditoria | C8: Cantidad de auditorias ejecutadas / Cantidad de auditorias programadas | D8: =IFERROR(COUNTIFS(auditorias[Fecha de ejecución de la auditoria],"<>"&"")/COUNTIFS(auditorias[Fecha programada de la auditoria],"<>"&""),"") | E8: 1
B10: Indicador de Desempeño de Procesos Auditados | C10: Número de auditorías con resultados óptimos y aceptables / Total de auditorías a procesos realizadas | D10: =IFERROR((COUNTIFS(resultadoauditorias[Calificación cualitativa],"Óptimo")+COUNTIFS(resultadoauditorias[Calificación cualitativa],"Aceptable"))/COUNTIFS(auditorias[Fecha de ejecución de la auditoria],"<>"&""),"") | E10: 1
B12: Aprendizaje Organizacional
B13: Eje Seguridad | C13: Práctica Segura | D13: Criterio | E13: Oportunidad de Mejora | F13: Acciones de mejoramiento | G13: Procedimientos / Procesos estandarizados o ajustados | H13: Descripción Aprendizaje Organizacional / Lecciones Aprendidas | I13: Acciones de socialización y capacitación de las mejoras implementadas | J13: Continuidad de la mejora (Describir acciones pendientes)
B14: {=eje_priorizado} | C14: {=practica_priorizada} | D14: {=criterio_priorizado} | E14: {=om_priorizada} | F14: {=acciones} -> P: H: V: A:
F15: P: H: V: A:
F16: P: H: V: A:
F17: P: H: V: A:
F18: P: H: V: A:
F19: P: H: V: A:
F20: P: H: V: A:
F21: P: H: V: A:
F22: P: H: V: A:
F23: P: H: V: A:
F24: P: H: V: A:
F25: P: H: V: A:
F26: P: H: V: A:
... F213: P: H: V: A:

Sheet LISTA CHEQUEO
C1: Lista de Chequeo para la Evaluación del Programa de Auditoría para el Mejoramiento Continuo de la Calidad en Salud
B3: Cumplimiento
B4: =IFERROR(COUNTIFS(E9:E40,"<>")/(COUNTIFS(E9:E40,"<>")+COUNTIFS(F9:F40,"<>")),"")
B6: INSTITUCIONES PRESTADORAS DE SERVICIOS DE SALUD
B7: RUTA CRÍTICA DEL PAMEC | D7: ASPECTO CHEQUEABLE | E7: CUMPLE | F7: NO CUMPLE | G7: NO APLICA | H7: OBSERVACIONES
B8: ALCANCE DEL MEJORAMIENTO CONTINUO DE LA CALIDAD
B9: El alcance del mejoramiento de la calidad de la entidad, debe ser explícito y se debe orientar en uno o varios de los siguientes temas: 1. Sistema Único de Acreditación 2. Mejoramiento del resultado de los indicadores del Sistema de Información para la Calidad 3. Fortalecimiento de la gestión del riesgo para los procesos misionales 4. Fortalecimiento del Programa de Seguridad del paciente documentado en la entidad e implementación de las buenas prácticas de seguridad del paciente recomendadas en la Guía Técnica correspondiente. En todo caso, el PAMEC, debe ser superior al cumplimiento de estándares de Habilitación. | D9: Escrito incorporado en el documento PAMEC donde se evidencie el alcance y propósito del mejoramiento de la calidad emprendido por la entidad
B10: Duración de la implementación del PAMEC, evidenciando el periodo en el que se estará implementando el plan de auditoría para el mejoramiento de la calidad | D10: Periodo de implementación y evaluación del PAMEC debidamente documentado
B11: RUTA CRÍTICA DEL PAMEC
B12: 1. AUTOEVALAUCIÓN
B13: Evidencia del análisis de la siguiente información, como base del inicio del PAMEC:
B14: Si el enfoque es el Sistema Único de Acreditación: 1. La conformación de los equipos de autoevaluación por grupos de estándares 2. La metodología a implementar para efectuar la autoevaluación con estándares del SUA. 3. Los formatos adoptados para la realización de la autoevaluación 4. Los resultados de la autoevaluación con estándares del SUA si hay una previa | D14: Instructivo para la preparación para la acreditación de la entidad | G14: X
B15: Resultado de las auditorías Internas que realiza la IPS, que deben tener el objetivo de monitorizar y verificar el avance de la entidad en el aseguramiento de los procesos misionales, estratégicos y de apoyo. Los resultados de dichas auditorías proveerán información para cada uno de los procesos sobre la consistencia del mejoramiento implementado | D15: Principales hallazgos de las auditorías realizadas en el periodo
B16: Resultado de las Auditorías externas que proveen información de las partes interesadas y/o clientes y que reflejan la medición objetiva de aspectos claves en la prestación de servicios de salud de índole legal que también orientan a la IPS en la mejora continua de la calidad | D16: Principales hallazgos de las auditorías realizadas en el periodo
B17: Resultados de la gestión de los Comités Institucionales a partir de sus planes de acción definidos para cada vigencia. El cumplimiento de dichos planes reflejará el compromiso de la entidad en el mejoramiento continuo de la calidad | D17: Evidencia del análisis de la gestión de los comités institucionales
B18: Análisis de los resultados de los indicadores reglamentarios y de los institucionales que reflejen el estado de los mismos frente a unos estándares o metas definidas. | D18: Evidencia del análisis de los resultados de los indicadores
B19: Análisis de la escucha de la voz del cliente que arroja resultados sobre el impacto en el usuario y su familia de todas las acciones de mejoramiento emprendidas en la institución y es el medidor por excelencia del enfoque en el cliente de una entidad | D19: Evidencia del análisis de la voz del cliente
B20: 2. SELECCIÓN DE PROCESOS A MEJORAR
B21: Si el alcance del PAMEC es la preparación para la acreditación, se debe evidenciar la correlación de los grupos de estándares de acreditación con los procesos del mapa de procesos de la entidad, a fin de evidenciar el compromiso de cada proceso institucional con la implementación de los estándares de calidad superior que apliquen | D21: Matriz de correlación de estándares de Acreditación con procesos institucionales | G21: X
B22: Si el alcance del PAMEC no es acreditación, la entidad debe contar con una evidencia del listado de los procesos que fueron seleccionados para mejorar, debidamente justificada y con base en el diagnóstico o autoevalauación realizada en el primer paso de la ruta crítica del PAMEC | D22: Listado de procesos seleccionados a mejorar
B23: 3. PRIORIZACIÓN DE PROCESOS
B24: Si el alcance del PAMEC es acreditación, se debe evidenciar la priorización de oportunidades de mejoramiento para cada uno de los grupos y subgrupos de estándares de acreditación. Se sugiere utilizar el documento ABC de planes de mejoramiento de la calidad. | D24: Instrumento técnico con la priorización de oportunidades de mejoramiento formuladas en la autoevaluación de estándares de acreditación | G24: X
B25: Si el alcance del PAMEC no es acreditación, se debe evidenciar una metodología validada de priorización de procesos, como la matriz de factor crítico de éxito | D25: Metodología validada y aplicada para la priorización de procesos
B26: 4. DEFINICIÓN DE LA CALIDAD ESPERADA
B27: Si el alcance del PAMEC es la preparación para la acreditación, se debe evidenciar en él, a qué nivel de la calificación cuantitativa de los estándares de acreditación que le apliquen se espera llegar en el período de implementación de dicho PAMEC. | D27: Evidencia de la definición de la calificación cuantitativa de los estándares de acreditación que espera alcanzarse en el periodo de vigencia del PAMEC | G27: X
B28: Si el alcance del PAMEC no es la acreditación, se debe evidenciar a dónde se espera llegar con la implementación del PAMEC en la vigencia así: 1. Si el alcance es el Mejoramiento del resultado de los indicadores del Sistema de Información para la Calidad, indicar la meta a cumplir 3. Si el alcance es el fortalecimiento de la gestión del riesgo para los procesos misionales, indicar el nivel deseado de riesgo al que se espera llegar. 4. Si el alcance es el fortalecimiento del Programa de Seguridad de paciente documentado en la entidad e implementación de las buenas prácticas de seguridad del paciente recomendadas en la Guía Técnica correspondiente, indicar el logro esperado | D28: Definición explícita del nivel al que se espera alcanzar en cada uno de los alcances definidos del PAMEC
B29: 5. CALIDAD OBSERVADA
B30: Listado de las auditorías planeadas en la vigencia del PAMEC, para evidenciar los avances logrados en su implementación | D30: Listado de las auditorías internas a realizarse en el periodo del PAMEC
B31: Evidencia gradual de la implementación de las auditorías planeadas con la identificación de hallazgos y oportunidades de mejoramiento recomendadas | D31: Informe de las auditorías realizadas frente a las planeadas
B32: Si el enfoque es la preparación para la acreditación, además de lo anterior, evidencia de los resultados de la autoevaluación de estándares de acreditación si en el periodo se realizó la misma | D32: Autoevaluación de todos los estándares de acreditación que le aplican | G32: X
B33: 6. FORMULACIÓN DE PLANES DE MEJORAMIENTO PARA ALCANZAR LA CALIDAD ESPERADA
B34: Evidencia documental de la formulación de planes de mejoramiento tendientes a alcanzar la calidad esperada. Si el alcance del PAMEC es la acreditación, se debe contar con planes de mejoramiento para cada grupo de estándares de acreditación, a saber, direccionamiento, gerencia, proceso de atención al cliente asistencial, gerencia de la información, gerencia del talento humano, gerencia del ambente físico, gestión de la tecnología y mejoramiento de la calidad | D34: Planes de mejoramiento formulados
B35: 7. IMPLEMENTACIÓN DE PLANES DE MEJORAMIENTO PARA ALCANZAR LA CALIDAD ESPERADA
B36: Evidencia documental de la implementación de las acciones de mejora documentadas en los planes de mejoramientos formulados para alcanzar la calidad esperada | D36: Evidencia documental de la implementación de las acciones de mejora documentadas en los planes de mejoramientos formulados para alcanzar la calidad esperada
B37: 8. EVALUACIÓN DE LA EJECUACIÓN DE LOS PLANES DE MEJORAMIENTO PARA ALCANZAR LA CALIDAD ESPERADA
B38: Evidencia documental del seguimiento realizado a la ejecución de las acciones de mejoramiento documentadas en los planes de mejoramiento formulados para alcanzar la calidad esperada. Incluye el seguimientos desde el autocontrol y de la auditoría interna | D38: Evidencia documental del seguimiento realizado a la ejecución de las acciones de mejoramiento documentadas en los planes de mejoramiento formulados para alcanzar la calidad esperada. Incluye el seguimientos desde el autocontrol y de auditoría interna. Semaforiazación del cumplimiento de los planes de mejoramiento.
B39: 9. APRENDIZAJE ORGANIZACIONAL
B40: Documento que evidencie el análisis de la ejecución del PAMEC, luego de finalizado el periodo de implementación definido, con el fin de identificar las acciones que deben estandarizarse en la entidad | D40: Documento de análisis de las acciones que deben estandarizarse en la entidad

Sheet FT1
H2: Ficha Técnica de Indicador
B5: DATOS DEL INDICADOR
C7: NOMBRE INDICADOR | N7: OBJETIVO INDICADOR
C9: PROCESO(S) RELACIONADO (S)
C11: PRÁCTICA(S) SEGURA RELACIONADA
C13: FÓRMULA PARA CÁLCULO DEL INDICADOR | F13: FÓRMULA | N13: FRECUENCIA MEDICIÓN | V13: META
F15: Numerador | N15: Denominador | V15: Unidad de medida
F17: Fuente Numerador | N17: Fuente Denominador
C19: RESPONSABLE INDICADOR | P19: RESPONSABLE ANALIZAR Y GESTIONAR
B22: MEDICIÓN
C24: AÑO ______ | F24: MED INICIAL | H24: ENE | J24: FEB | L24: MAR | N24: ABR | P24: MAY | R24: JUN | T24: JUL | V24: AGO | X24: SEP | Z24: OCT | AB24: NOV
C25: META
C26: RESULTADO
C28: AÑO ______ | F28: DIC | H28: ENE | J28: FEB | L28: MAR | N28: ABR | P28: MAY | R28: JUN | T28: JUL | V28: AGO | X28: SEP | Z28: OCT | AB28: NOV
C29: META
C30: RESULTADO
B41: ANÁLISIS
C43: MES | D43: CAUSAS DESVIACIÓN | L43: ACCION(ES) DE MEJORA | T43: RESPONSABLE | Z43: FECHA PROGRAMADA DE CIERRE | AD43: ESTADO DE LA ACCIÓN | AF43: OBSERVACIONES / SEGUIMIENTO
C44: ENE
C45: FEB
C46: MAR
C47: ABR
C48: MAY
C49: JUN
C50: JUL
C51: AGO
C52: SEP
C53: OCT
C54: DIC
C55: ENE
... C65: DIC

Sheet FT2
H2: Ficha Técnica de Indicador
B5: DATOS DEL INDICADOR
C7: NOMBRE INDICADOR | N7: OBJETIVO INDICADOR
C9: PROCESO(S) RELACIONADO (S)
C11: PRÁCTICA(S) SEGURA RELACIONADA
C13: FÓRMULA PARA CÁLCULO DEL INDICADOR | F13: FÓRMULA | N13: FRECUENCIA MEDICIÓN | V13: META
F15: Numerador | N15: Denominador | V15: Unidad de medida
F17: Fuente Numerador | N17: Fuente Denominador
C19: RESPONSABLE INDICADOR | P19: RESPONSABLE ANALIZAR Y GESTIONAR
B22: MEDICIÓN
C24: AÑO 2023 | F24: MED INICIAL | H24: Nov | J24: Dic | L24: Ene | N24: Feb | P24: Mar | R24: Abr | T24: May | V24: Jun | X24: Jul | Z24: Ago | AB24: Sep
C25: META
C26: RESULTADO
C28: AÑO 2024 | F28: Oct | H28: Nov | J28: Dic
C29: META
C30: RESULTADO
B41: ANÁLISIS
C43: MES | D43: CAUSAS DESVIACIÓN | L43: ACCION(ES) DE MEJORA | T43: RESPONSABLE | Z43: FECHA PROGRAMADA DE CIERRE | AD43: ESTADO DE LA ACCIÓN | AF43: OBSERVACIONES / SEGUIMIENTO
C44: ENE
C45: FEB
C46: MAR
C47: ABR
C48: MAY
C49: JUN
C50: JUL
C51: AGO
C52: SEP
C53: OCT
C54: DIC
C55: ENE
... C65: DIC

Sheet FT3
H2: Ficha Técnica de Indicador
B5: DATOS DEL INDICADOR
C7: NOMBRE INDICADOR | N7: OBJETIVO INDICADOR
C9: PROCESO(S) RELACIONADO (S)
C11: PRÁCTICA(S) SEGURA RELACIONADA
C13: FÓRMULA PARA CÁLCULO DEL INDICADOR | F13: FÓRMULA | N13: FRECUENCIA MEDICIÓN | V13: META
F15: Numerador | N15: Denominador | V15: Unidad de medida
F17: Fuente Numerador | N17: Fuente Denominador
C19: RESPONSABLE INDICADOR | P19: RESPONSABLE ANALIZAR Y GESTIONAR
B22: MEDICIÓN
C24: AÑO ______ | F24: MED INICIAL | H24: ENE | J24: FEB | L24: MAR | N24: ABR | P24: MAY | R24: JUN | T24: JUL | V24: AGO | X24: SEP | Z24: OCT | AB24: NOV
C25: META
C26: RESULTADO
C28: AÑO ______ | F28: DIC | H28: ENE | J28: FEB | L28: MAR | N28: ABR | P28: MAY | R28: JUN | T28: JUL | V28: AGO | X28: SEP | Z28: OCT | AB28: NOV
C29: META
C30: RESULTADO
B41: ANÁLISIS
C43: MES | D43: CAUSAS DESVIACIÓN | L43: ACCION(ES) DE MEJORA | T43: RESPONSABLE | Z43: FECHA PROGRAMADA DE CIERRE | AD43: ESTADO DE LA ACCIÓN | AF43: OBSERVACIONES / SEGUIMIENTO
C44: ENE
C45: FEB
C46: MAR
C47: ABR
C48: MAY
C49: JUN
C50: JUL
C51: AGO
C52: SEP
C53: OCT
C54: DIC
C55: ENE
... C65: DIC

Sheet FT4
H2: Ficha Técnica de Indicador
B5: DATOS DEL INDICADOR
C7: NOMBRE INDICADOR | N7: OBJETIVO INDICADOR
C9: PROCESO(S) RELACIONADO (S)
C11: PRÁCTICA(S) SEGURA RELACIONADA
C13: FÓRMULA PARA CÁLCULO DEL INDICADOR | F13: FÓRMULA | N13: FRECUENCIA MEDICIÓN | V13: META
F15: Numerador | N15: Denominador | V15: Unidad de medida
F17: Fuente Numerador | N17: Fuente Denominador
C19: RESPONSABLE INDICADOR | P19: RESPONSABLE ANALIZAR Y GESTIONAR
B22: MEDICIÓN
C24: AÑO ______ | F24: MED INICIAL | H24: ENE | J24: FEB | L24: MAR | N24: ABR | P24: MAY | R24: JUN | T24: JUL | V24: AGO | X24: SEP | Z24: OCT | AB24: NOV
C25: META
C26: RESULTADO
C28: AÑO ______ | F28: DIC | H28: ENE | J28: FEB | L28: MAR | N28: ABR | P28: MAY | R28: JUN | T28: JUL | V28: AGO | X28: SEP | Z28: OCT | AB28: NOV
C29: META
C30: RESULTADO
B41: ANÁLISIS
C43: MES | D43: CAUSAS DESVIACIÓN | L43: ACCION(ES) DE MEJORA | T43: RESPONSABLE | Z43: FECHA PROGRAMADA DE CIERRE | AD43: ESTADO DE LA ACCIÓN | AF43: OBSERVACIONES / SEGUIMIENTO
C44: ENE
C45: FEB
C46: MAR
C47: ABR
C48: MAY
C49: JUN
C50: JUL
C51: AGO
C52: SEP
C53: OCT
C54: DIC
C55: ENE
... C65: DIC

Sheet FT5
H2: Ficha Técnica de Indicador
B5: DATOS DEL INDICADOR
C7: NOMBRE INDICADOR | N7: OBJETIVO INDICADOR
C9: PROCESO(S) RELACIONADO (S)
C11: PRÁCTICA(S) SEGURA RELACIONADA
C13: FÓRMULA PARA CÁLCULO DEL INDICADOR | F13: FÓRMULA | N13: FRECUENCIA MEDICIÓN | V13: META
F15: Numerador | N15: Denominador | V15: Unidad de medida
F17: Fuente Numerador | N17: Fuente Denominador
C19: RESPONSABLE INDICADOR | P19: RESPONSABLE ANALIZAR Y GESTIONAR
B22: MEDICIÓN
C24: AÑO ______ | F24: MED INICIAL | H24: ENE | J24: FEB | L24: MAR | N24: ABR | P24: MAY | R24: JUN | T24: JUL | V24: AGO | X24: SEP | Z24: OCT | AB24: NOV
C25: META
C26: RESULTADO
C28: AÑO ______ | F28: DIC | H28: ENE | J28: FEB | L28: MAR | N28: ABR | P28: MAY | R28: JUN | T28: JUL | V28: AGO | X28: SEP | Z28: OCT | AB28: NOV
C29: META
C30: RESULTADO
B41: ANÁLISIS
C43: MES | D43: CAUSAS DESVIACIÓN | L43: ACCION(ES) DE MEJORA | T43: RESPONSABLE | Z43: FECHA PROGRAMADA DE CIERRE | AD43: ESTADO DE LA ACCIÓN | AF43: OBSERVACIONES / SEGUIMIENTO
C44: ENE
C45: FEB
C46: MAR
C47: ABR
C48: MAY
C49: JUN
C50: JUL
C51: AGO
C52: SEP
C53: OCT
C54: DIC
C55: ENE
... C65: DIC

Sheet FT6
H2: Ficha Técnica de Indicador
B5: DATOS DEL INDICADOR
C7: NOMBRE INDICADOR | N7: OBJETIVO INDICADOR
C9: PROCESO(S) RELACIONADO (S)
C11: PRÁCTICA(S) SEGURA RELACIONADA
C13: FÓRMULA PARA CÁLCULO DEL INDICADOR | F13: FÓRMULA | N13: FRECUENCIA MEDICIÓN | V13: META
F15: Numerador | N15: Denominador | V15: Unidad de medida
F17: Fuente Numerador | N17: Fuente Denominador
C19: RESPONSABLE INDICADOR | P19: RESPONSABLE ANALIZAR Y GESTIONAR
B22: MEDICIÓN
C24: AÑO ______ | F24: MED INICIAL | H24: ENE | J24: FEB | L24: MAR | N24: ABR | P24: MAY | R24: JUN | T24: JUL | V24: AGO | X24: SEP | Z24: OCT | AB24: NOV
C25: META
C26: RESULTADO
C28: AÑO ______ | F28: DIC | H28: ENE | J28: FEB | L28: MAR | N28: ABR | P28: MAY | R28: JUN | T28: JUL | V28: AGO | X28: SEP | Z28: OCT | AB28: NOV
C29: META
C30: RESULTADO
B41: ANÁLISIS
C43: MES | D43: CAUSAS DESVIACIÓN | L43: ACCION(ES) DE MEJORA | T43: RESPONSABLE | Z43: FECHA PROGRAMADA DE CIERRE | AD43: ESTADO DE LA ACCIÓN | AF43: OBSERVACIONES / SEGUIMIENTO
C44: ENE
C45: FEB
C46: MAR
C47: ABR
C48: MAY
C49: JUN
C50: JUL
C51: AGO
C52: SEP
C53: OCT
C54: DIC
C55: ENE
... C65: DIC

Sheet FT7
H2: Ficha Técnica de Indicador
B5: DATOS DEL INDICADOR
C7: NOMBRE INDICADOR | N7: OBJETIVO INDICADOR
C9: PROCESO(S) RELACIONADO (S)
C11: PRÁCTICA(S) SEGURA RELACIONADA
C13: FÓRMULA PARA CÁLCULO DEL INDICADOR | F13: FÓRMULA | N13: FRECUENCIA MEDICIÓN | V13: META
F15: Numerador | N15: Denominador | V15: Unidad de medida
F17: Fuente Numerador | N17: Fuente Denominador
C19: RESPONSABLE INDICADOR | P19: RESPONSABLE ANALIZAR Y GESTIONAR
B22: MEDICIÓN
C24: AÑO ______ | F24: MED INICIAL | H24: ENE | J24: FEB | L24: MAR | N24: ABR | P24: MAY | R24: JUN | T24: JUL | V24: AGO | X24: SEP | Z24: OCT | AB24: NOV
C25: META
C26: RESULTADO
C28: AÑO ______ | F28: DIC | H28: ENE | J28: FEB | L28: MAR | N28: ABR | P28: MAY | R28: JUN | T28: JUL | V28: AGO | X28: SEP | Z28: OCT | AB28: NOV
C29: META
C30: RESULTADO
B41: ANÁLISIS
C43: MES | D43: CAUSAS DESVIACIÓN | L43: ACCION(ES) DE MEJORA | T43: RESPONSABLE | Z43: FECHA PROGRAMADA DE CIERRE | AD43: ESTADO DE LA ACCIÓN | AF43: OBSERVACIONES / SEGUIMIENTO
C44: ENE
C45: FEB
C46: MAR
C47: ABR
C48: MAY
C49: JUN
C50: JUL
C51: AGO
C52: SEP
C53: OCT
C54: DIC
C55: ENE
... C65: DIC

Sheet FT8
H2: Ficha Técnica de Indicador
B5: DATOS DEL INDICADOR
C7: NOMBRE INDICADOR | N7: OBJETIVO INDICADOR
C9: PROCESO(S) RELACIONADO (S)
C11: PRÁCTICA(S) SEGURA RELACIONADA
C13: FÓRMULA PARA CÁLCULO DEL INDICADOR | F13: FÓRMULA | N13: FRECUENCIA MEDICIÓN | V13: META
F15: Numerador | N15: Denominador | V15: Unidad de medida
F17: Fuente Numerador | N17: Fuente Denominador
C19: RESPONSABLE INDICADOR | P19: RESPONSABLE ANALIZAR Y GESTIONAR
B22: MEDICIÓN
C24: AÑO ______ | F24: MED INICIAL | H24: ENE | J24: FEB | L24: MAR | N24: ABR | P24: MAY | R24: JUN | T24: JUL | V24: AGO | X24: SEP | Z24: OCT | AB24: NOV
C25: META
C26: RESULTADO
C28: AÑO ______ | F28: DIC | H28: ENE | J28: FEB | L28: MAR | N28: ABR | P28: MAY | R28: JUN | T28: JUL | V28: AGO | X28: SEP | Z28: OCT | AB28: NOV
C29: META
C30: RESULTADO
B41: ANÁLISIS
C43: MES | D43: CAUSAS DESVIACIÓN | L43: ACCION(ES) DE MEJORA | T43: RESPONSABLE | Z43: FECHA PROGRAMADA DE CIERRE | AD43: ESTADO DE LA ACCIÓN | AF43: OBSERVACIONES / SEGUIMIENTO
C44: ENE
C45: FEB
C46: MAR
C47: ABR
C48: MAY
C49: JUN
C50: JUL
C51: AGO
C52: SEP
C53: OCT
C54: DIC
C55: ENE
... C65: DIC

Sheet FT9
H2: Ficha Técnica de Indicador
B5: DATOS DEL INDICADOR
C7: NOMBRE INDICADOR | N7: OBJETIVO INDICADOR
C9: PROCESO(S) RELACIONADO (S)
C11: PRÁCTICA(S) SEGURA RELACIONADA
C13: FÓRMULA PARA CÁLCULO DEL INDICADOR | F13: FÓRMULA | N13: FRECUENCIA MEDICIÓN | V13: META
F15: Numerador | N15: Denominador | V15: Unidad de medida
F17: Fuente Numerador | N17: Fuente Denominador
C19: RESPONSABLE INDICADOR | P19: RESPONSABLE ANALIZAR Y GESTIONAR
B22: MEDICIÓN
C24: AÑO ______ | F24: MED INICIAL | H24: ENE | J24: FEB | L24: MAR | N24: ABR | P24: MAY | R24: JUN | T24: JUL | V24: AGO | X24: SEP | Z24: OCT | AB24: NOV
C25: META
C26: RESULTADO
C28: AÑO ______ | F28: DIC | H28: ENE | J28: FEB | L28: MAR | N28: ABR | P28: MAY | R28: JUN | T28: JUL | V28: AGO | X28: SEP | Z28: OCT | AB28: NOV
C29: META
C30: RESULTADO
B41: ANÁLISIS
C43: MES | D43: CAUSAS DESVIACIÓN | L43: ACCION(ES) DE MEJORA | T43: RESPONSABLE | Z43: FECHA PROGRAMADA DE CIERRE | AD43: ESTADO DE LA ACCIÓN | AF43: OBSERVACIONES / SEGUIMIENTO
C44: ENE
C45: FEB
C46: MAR
C47: ABR
C48: MAY
C49: JUN
C50: JUL
C51: AGO
C52: SEP
C53: OCT
C54: DIC
C55: ENE
... C65: DIC

Sheet FT10
H2: Ficha Técnica de Indicador
B5: DATOS DEL INDICADOR
C7: NOMBRE INDICADOR | N7: OBJETIVO INDICADOR
C9: PROCESO(S) RELACIONADO (S)
C11: PRÁCTICA(S) SEGURA RELACIONADA
C13: FÓRMULA PARA CÁLCULO DEL INDICADOR | F13: FÓRMULA | N13: FRECUENCIA MEDICIÓN | V13: META
F15: Numerador | N15: Denominador | V15: Unidad de medida
F17: Fuente Numerador | N17: Fuente Denominador
C19: RESPONSABLE INDICADOR | P19: RESPONSABLE ANALIZAR Y GESTIONAR
B22: MEDICIÓN
C24: AÑO ______ | F24: MED INICIAL | H24: ENE | J24: FEB | L24: MAR | N24: ABR | P24: MAY | R24: JUN | T24: JUL | V24: AGO | X24: SEP | Z24: OCT | AB24: NOV
C25: META
C26: RESULTADO
C28: AÑO ______ | F28: DIC | H28: ENE | J28: FEB | L28: MAR | N28: ABR | P28: MAY | R28: JUN | T28: JUL | V28: AGO | X28: SEP | Z28: OCT | AB28: NOV
C29: META
C30: RESULTADO
B41: ANÁLISIS
C43: MES | D43: CAUSAS DESVIACIÓN | L43: ACCION(ES) DE MEJORA | T43: RESPONSABLE | Z43: FECHA PROGRAMADA DE CIERRE | AD43: ESTADO DE LA ACCIÓN | AF43: OBSERVACIONES / SEGUIMIENTO
C44: ENE
C45: FEB
C46: MAR
C47: ABR
C48: MAY
C49: JUN
C50: JUL
C51: AGO
C52: SEP
C53: OCT
C54: DIC
C55: ENE
... C65: DIC

Sheet FT11
H2: Ficha Técnica de Indicador
B5: DATOS DEL INDICADOR
C7: NOMBRE INDICADOR | N7: OBJETIVO INDICADOR
C9: PROCESO(S) RELACIONADO (S)
C11: PRÁCTICA(S) SEGURA RELACIONADA
C13: FÓRMULA PARA CÁLCULO DEL INDICADOR | F13: FÓRMULA | N13: FRECUENCIA MEDICIÓN | V13: META
F15: Numerador | N15: Denominador | V15: Unidad de medida
F17: Fuente Numerador | N17: Fuente Denominador
C19: RESPONSABLE INDICADOR | P19: RESPONSABLE ANALIZAR Y GESTIONAR
B22: MEDICIÓN
C24: AÑO ______ | F24: MED INICIAL | H24: ENE | J24: FEB | L24: MAR | N24: ABR | P24: MAY | R24: JUN | T24: JUL | V24: AGO | X24: SEP | Z24: OCT | AB24: NOV
C25: META
C26: RESULTADO
C28: AÑO ______ | F28: DIC | H28: ENE | J28: FEB | L28: MAR | N28: ABR | P28: MAY | R28: JUN | T28: JUL | V28: AGO | X28: SEP | Z28: OCT | AB28: NOV
C29: META
C30: RESULTADO
B41: ANÁLISIS
C43: MES | D43: CAUSAS DESVIACIÓN | L43: ACCION(ES) DE MEJORA | T43: RESPONSABLE | Z43: FECHA PROGRAMADA DE CIERRE | AD43: ESTADO DE LA ACCIÓN | AF43: OBSERVACIONES / SEGUIMIENTO
C44: ENE
C45: FEB
C46: MAR
C47: ABR
C48: MAY
C49: JUN
C50: JUL
C51: AGO
C52: SEP
C53: OCT
C54: DIC
C55: ENE
... C65: DIC

Sheet FT12
H2: Ficha Técnica de Indicador
B5: DATOS DEL INDICADOR
C7: NOMBRE INDICADOR | N7: OBJETIVO INDICADOR
C9: PROCESO(S) RELACIONADO (S)
C11: PRÁCTICA(S) SEGURA RELACIONADA
C13: FÓRMULA PARA CÁLCULO DEL INDICADOR | F13: FÓRMULA | N13: FRECUENCIA MEDICIÓN | V13: META
F15: Numerador | N15: Denominador | V15: Unidad de medida
F17: Fuente Numerador | N17: Fuente Denominador
C19: RESPONSABLE INDICADOR | P19: RESPONSABLE ANALIZAR Y GESTIONAR
B22: MEDICIÓN
C24: AÑO ______ | F24: MED INICIAL | H24: ENE | J24: FEB | L24: MAR | N24: ABR | P24: MAY | R24: JUN | T24: JUL | V24: AGO | X24: SEP | Z24: OCT | AB24: NOV
C25: META
C26: RESULTADO
C28: AÑO ______ | F28: DIC | H28: ENE | J28: FEB | L28: MAR | N28: ABR | P28: MAY | R28: JUN | T28: JUL | V28: AGO | X28: SEP | Z28: OCT | AB28: NOV
C29: META
C30: RESULTADO
B41: ANÁLISIS
C43: MES | D43: CAUSAS DESVIACIÓN | L43: ACCION(ES) DE MEJORA | T43: RESPONSABLE | Z43: FECHA PROGRAMADA DE CIERRE | AD43: ESTADO DE LA ACCIÓN | AF43: OBSERVACIONES / SEGUIMIENTO
C44: ENE
C45: FEB
C46: MAR
C47: ABR
C48: MAY
C49: JUN
C50: JUL
C51: AGO
C52: SEP
C53: OCT
C54: DIC
C55: ENE
... C65: DIC

Sheet FT13
H2: Ficha Técnica de Indicador
B5: DATOS DEL INDICADOR
C7: NOMBRE INDICADOR | N7: OBJETIVO INDICADOR
C9: PROCESO(S) RELACIONADO (S)
C11: PRÁCTICA(S) SEGURA RELACIONADA
C13: FÓRMULA PARA CÁLCULO DEL INDICADOR | F13: FÓRMULA | N13: FRECUENCIA MEDICIÓN | V13: META
F15: Numerador | N15: Denominador | V15: Unidad de medida
F17: Fuente Numerador | N17: Fuente Denominador
C19: RESPONSABLE INDICADOR | P19: RESPONSABLE ANALIZAR Y GESTIONAR
B22: MEDICIÓN
C24: AÑO ______ | F24: MED INICIAL | H24: ENE | J24: FEB | L24: MAR | N24: ABR | P24: MAY | R24: JUN | T24: JUL | V24: AGO | X24: SEP | Z24: OCT | AB24: NOV
C25: META
C26: RESULTADO
C28: AÑO ______ | F28: DIC | H28: ENE | J28: FEB | L28: MAR | N28: ABR | P28: MAY | R28: JUN | T28: JUL | V28: AGO | X28: SEP | Z28: OCT | AB28: NOV
C29: META
C30: RESULTADO
B41: ANÁLISIS
C43: MES | D43: CAUSAS DESVIACIÓN | L43: ACCION(ES) DE MEJORA | T43: RESPONSABLE | Z43: FECHA PROGRAMADA DE CIERRE | AD43: ESTADO DE LA ACCIÓN | AF43: OBSERVACIONES / SEGUIMIENTO
C44: ENE
C45: FEB
C46: MAR
C47: ABR
C48: MAY
C49: JUN
C50: JUL
C51: AGO
C52: SEP
C53: OCT
C54: DIC
C55: ENE
... C65: DIC

Sheet FT14
H2: Ficha Técnica de Indicador
B5: DATOS DEL INDICADOR
C7: NOMBRE INDICADOR | N7: OBJETIVO INDICADOR
C9: PROCESO(S) RELACIONADO (S)
C11: PRÁCTICA(S) SEGURA RELACIONADA
C13: FÓRMULA PARA CÁLCULO DEL INDICADOR | F13: FÓRMULA | N13: FRECUENCIA MEDICIÓN | V13: META
F15: Numerador | N15: Denominador | V15: Unidad de medida
F17: Fuente Numerador | N17: Fuente Denominador
C19: RESPONSABLE INDICADOR | P19: RESPONSABLE ANALIZAR Y GESTIONAR
B22: MEDICIÓN
C24: AÑO ______ | F24: MED INICIAL | H24: ENE | J24: FEB | L24: MAR | N24: ABR | P24: MAY | R24: JUN | T24: JUL | V24: AGO | X24: SEP | Z24: OCT | AB24: NOV
C25: META
C26: RESULTADO
C28: AÑO ______ | F28: DIC | H28: ENE | J28: FEB | L28: MAR | N28: ABR | P28: MAY | R28: JUN | T28: JUL | V28: AGO | X28: SEP | Z28: OCT | AB28: NOV
C29: META
C30: RESULTADO
B41: ANÁLISIS
C43: MES | D43: CAUSAS DESVIACIÓN | L43: ACCION(ES) DE MEJORA | T43: RESPONSABLE | Z43: FECHA PROGRAMADA DE CIERRE | AD43: ESTADO DE LA ACCIÓN | AF43: OBSERVACIONES / SEGUIMIENTO
C44: ENE
C45: FEB
C46: MAR
C47: ABR
C48: MAY
C49: JUN
C50: JUL
C51: AGO
C52: SEP
C53: OCT
C54: DIC
C55: ENE
... C65: DIC

Sheet FT15
H2: Ficha Técnica de Indicador
B5: DATOS DEL INDICADOR
C7: NOMBRE INDICADOR | N7: OBJETIVO INDICADOR
C9: PROCESO(S) RELACIONADO (S)
C11: PRÁCTICA(S) SEGURA RELACIONADA
C13: FÓRMULA PARA CÁLCULO DEL INDICADOR | F13: FÓRMULA | N13: FRECUENCIA MEDICIÓN | V13: META
F15: Numerador | N15: Denominador | V15: Unidad de medida
F17: Fuente Numerador | N17: Fuente Denominador
C19: RESPONSABLE INDICADOR | P19: RESPONSABLE ANALIZAR Y GESTIONAR
B22: MEDICIÓN
C24: AÑO ______ | F24: MED INICIAL | H24: ENE | J24: FEB | L24: MAR | N24: ABR | P24: MAY | R24: JUN | T24: JUL | V24: AGO | X24: SEP | Z24: OCT | AB24: NOV
C25: META
C26: RESULTADO
C28: AÑO ______ | F28: DIC | H28: ENE | J28: FEB | L28: MAR | N28: ABR | P28: MAY | R28: JUN | T28: JUL | V28: AGO | X28: SEP | Z28: OCT | AB28: NOV
C29: META
C30: RESULTADO
B41: ANÁLISIS
C43: MES | D43: CAUSAS DESVIACIÓN | L43: ACCION(ES) DE MEJORA | T43: RESPONSABLE | Z43: FECHA PROGRAMADA DE CIERRE | AD43: ESTADO DE LA ACCIÓN | AF43: OBSERVACIONES / SEGUIMIENTO
C44: ENE
C45: FEB
C46: MAR
C47: ABR
C48: MAY
C49: JUN
C50: JUL
C51: AGO
C52: SEP
C53: OCT
C54: DIC
C55: ENE
... C65: DIC

Sheet FT16
H2: Ficha Técnica de Indicador
B5: DATOS DEL INDICADOR
C7: NOMBRE INDICADOR | N7: OBJETIVO INDICADOR
C9: PROCESO(S) RELACIONADO (S)
C11: PRÁCTICA(S) SEGURA RELACIONADA
C13: FÓRMULA PARA CÁLCULO DEL INDICADOR | F13: FÓRMULA | N13: FRECUENCIA MEDICIÓN | V13: META
F15: Numerador | N15: Denominador | V15: Unidad de medida
F17: Fuente Numerador | N17: Fuente Denominador
C19: RESPONSABLE INDICADOR | P19: RESPONSABLE ANALIZAR Y GESTIONAR
B22: MEDICIÓN
C24: AÑO ______ | F24: MED INICIAL | H24: ENE | J24: FEB | L24: MAR | N24: ABR | P24: MAY | R24: JUN | T24: JUL | V24: AGO | X24: SEP | Z24: OCT | AB24: NOV
C25: META
C26: RESULTADO
C28: AÑO ______ | F28: DIC | H28: ENE | J28: FEB | L28: MAR | N28: ABR | P28: MAY | R28: JUN | T28: JUL | V28: AGO | X28: SEP | Z28: OCT | AB28: NOV
C29: META
C30: RESULTADO
B41: ANÁLISIS
C43: MES | D43: CAUSAS DESVIACIÓN | L43: ACCION(ES) DE MEJORA | T43: RESPONSABLE | Z43: FECHA PROGRAMADA DE CIERRE | AD43: ESTADO DE LA ACCIÓN | AF43: OBSERVACIONES / SEGUIMIENTO
C44: ENE
C45: FEB
C46: MAR
C47: ABR
C48: MAY
C49: JUN
C50: JUL
C51: AGO
C52: SEP
C53: OCT
C54: DIC
C55: ENE
... C65: DIC

Sheet FT17
H2: Ficha Técnica de Indicador
B5: DATOS DEL INDICADOR
C7: NOMBRE INDICADOR | N7: OBJETIVO INDICADOR
C9: PROCESO(S) RELACIONADO (S)
C11: PRÁCTICA(S) SEGURA RELACIONADA
C13: FÓRMULA PARA CÁLCULO DEL INDICADOR | F13: FÓRMULA | N13: FRECUENCIA MEDICIÓN | V13: META
F15: Numerador | N15: Denominador | V15: Unidad de medida
F17: Fuente Numerador | N17: Fuente Denominador
C19: RESPONSABLE INDICADOR | P19: RESPONSABLE ANALIZAR Y GESTIONAR
B22: MEDICIÓN
C24: AÑO ______ | F24: MED INICIAL | H24: ENE | J24: FEB | L24: MAR | N24: ABR | P24: MAY | R24: JUN | T24: JUL | V24: AGO | X24: SEP | Z24: OCT | AB24: NOV
C25: META
C26: RESULTADO
C28: AÑO ______ | F28: DIC | H28: ENE | J28: FEB | L28: MAR | N28: ABR | P28: MAY | R28: JUN | T28: JUL | V28: AGO | X28: SEP | Z28: OCT | AB28: NOV
C29: META
C30: RESULTADO
B41: ANÁLISIS
C43: MES | D43: CAUSAS DESVIACIÓN | L43: ACCION(ES) DE MEJORA | T43: RESPONSABLE | Z43: FECHA PROGRAMADA DE CIERRE | AD43: ESTADO DE LA ACCIÓN | AF43: OBSERVACIONES / SEGUIMIENTO
C44: ENE
C45: FEB
C46: MAR
C47: ABR
C48: MAY
C49: JUN
C50: JUL
C51: AGO
C52: SEP
C53: OCT
C54: DIC
C55: ENE
... C65: DIC

Sheet FT18
H2: Ficha Técnica de Indicador
B5: DATOS DEL INDICADOR
C7: NOMBRE INDICADOR | N7: OBJETIVO INDICADOR
C9: PROCESO(S) RELACIONADO (S)
C11: PRÁCTICA(S) SEGURA RELACIONADA
C13: FÓRMULA PARA CÁLCULO DEL INDICADOR | F13: FÓRMULA | N13: FRECUENCIA MEDICIÓN | V13: META
F15: Numerador | N15: Denominador | V15: Unidad de medida
F17: Fuente Numerador | N17: Fuente Denominador
C19: RESPONSABLE INDICADOR | P19: RESPONSABLE ANALIZAR Y GESTIONAR
B22: MEDICIÓN
C24: AÑO ______ | F24: MED INICIAL | H24: ENE | J24: FEB | L24: MAR | N24: ABR | P24: MAY | R24: JUN | T24: JUL | V24: AGO | X24: SEP | Z24: OCT | AB24: NOV
C25: META
C26: RESULTADO
C28: AÑO ______ | F28: DIC | H28: ENE | J28: FEB | L28: MAR | N28: ABR | P28: MAY | R28: JUN | T28: JUL | V28: AGO | X28: SEP | Z28: OCT | AB28: NOV
C29: META
C30: RESULTADO
B41: ANÁLISIS
C43: MES | D43: CAUSAS DESVIACIÓN | L43: ACCION(ES) DE MEJORA | T43: RESPONSABLE | Z43: FECHA PROGRAMADA DE CIERRE | AD43: ESTADO DE LA ACCIÓN | AF43: OBSERVACIONES / SEGUIMIENTO
C44: ENE
C45: FEB
C46: MAR
C47: ABR
C48: MAY
C49: JUN
C50: JUL
C51: AGO
C52: SEP
C53: OCT
C54: DIC
C55: ENE
... C65: DIC

Sheet FT19
H2: Ficha Técnica de Indicador
B5: DATOS DEL INDICADOR
C7: NOMBRE INDICADOR | N7: OBJETIVO INDICADOR
C9: PROCESO(S) RELACIONADO (S)
C11: PRÁCTICA(S) SEGURA RELACIONADA
C13: FÓRMULA PARA CÁLCULO DEL INDICADOR | F13: FÓRMULA | N13: FRECUENCIA MEDICIÓN | V13: META
F15: Numerador | N15: Denominador | V15: Unidad de medida
F17: Fuente Numerador | N17: Fuente Denominador
C19: RESPONSABLE INDICADOR | P19: RESPONSABLE ANALIZAR Y GESTIONAR
B22: MEDICIÓN
C24: AÑO ______ | F24: MED INICIAL | H24: ENE | J24: FEB | L24: MAR | N24: ABR | P24: MAY | R24: JUN | T24: JUL | V24: AGO | X24: SEP | Z24: OCT | AB24: NOV
C25: META
C26: RESULTADO
C28: AÑO ______ | F28: DIC | H28: ENE | J28: FEB | L28: MAR | N28: ABR | P28: MAY | R28: JUN | T28: JUL | V28: AGO | X28: SEP | Z28: OCT | AB28: NOV
C29: META
C30: RESULTADO
B41: ANÁLISIS
C43: MES | D43: CAUSAS DESVIACIÓN | L43: ACCION(ES) DE MEJORA | T43: RESPONSABLE | Z43: FECHA PROGRAMADA DE CIERRE | AD43: ESTADO DE LA ACCIÓN | AF43: OBSERVACIONES / SEGUIMIENTO
C44: ENE
C45: FEB
C46: MAR
C47: ABR
C48: MAY
C49: JUN
C50: JUL
C51: AGO
C52: SEP
C53: OCT
C54: DIC
C55: ENE
... C65: DIC

Sheet FT20
H2: Ficha Técnica de Indicador
B5: DATOS DEL INDICADOR
C7: NOMBRE INDICADOR | N7: OBJETIVO INDICADOR
C9: PROCESO(S) RELACIONADO (S)
C11: PRÁCTICA(S) SEGURA RELACIONADA
C13: FÓRMULA PARA CÁLCULO DEL INDICADOR | F13: FÓRMULA | N13: FRECUENCIA MEDICIÓN | V13: META
F15: Numerador | N15: Denominador | V15: Unidad de medida
F17: Fuente Numerador | N17: Fuente Denominador
C19: RESPONSABLE INDICADOR | P19: RESPONSABLE ANALIZAR Y GESTIONAR
B22: MEDICIÓN
C24: AÑO ______ | F24: MED INICIAL | H24: ENE | J24: FEB | L24: MAR | N24: ABR | P24: MAY | R24: JUN | T24: JUL | V24: AGO | X24: SEP | Z24: OCT | AB24: NOV
C25: META
C26: RESULTADO
C28: AÑO ______ | F28: DIC | H28: ENE | J28: FEB | L28: MAR | N28: ABR | P28: MAY | R28: JUN | T28: JUL | V28: AGO | X28: SEP | Z28: OCT | AB28: NOV
C29: META
C30: RESULTADO
B41: ANÁLISIS
C43: MES | D43: CAUSAS DESVIACIÓN | L43: ACCION(ES) DE MEJORA | T43: RESPONSABLE | Z43: FECHA PROGRAMADA DE CIERRE | AD43: ESTADO DE LA ACCIÓN | AF43: OBSERVACIONES / SEGUIMIENTO
C44: ENE
C45: FEB
C46: MAR
C47: ABR
C48: MAY
C49: JUN
C50: JUL
C51: AGO
C52: SEP
C53: OCT
C54: DIC
C55: ENE
... C65: DIC

Sheet FT21
H2: Ficha Técnica de Indicador
B5: DATOS DEL INDICADOR
C7: NOMBRE INDICADOR | N7: OBJETIVO INDICADOR
C9: PROCESO(S) RELACIONADO (S)
C11: PRÁCTICA(S) SEGURA RELACIONADA
C13: FÓRMULA PARA CÁLCULO DEL INDICADOR | F13: FÓRMULA | N13: FRECUENCIA MEDICIÓN | V13: META
F15: Numerador | N15: Denominador | V15: Unidad de medida
F17: Fuente Numerador | N17: Fuente Denominador
C19: RESPONSABLE INDICADOR | P19: RESPONSABLE ANALIZAR Y GESTIONAR
B22: MEDICIÓN
C24: AÑO ______ | F24: MED INICIAL | H24: ENE | J24: FEB | L24: MAR | N24: ABR | P24: MAY | R24: JUN | T24: JUL | V24: AGO | X24: SEP | Z24: OCT | AB24: NOV
C25: META
C26: RESULTADO
C28: AÑO ______ | F28: DIC | H28: ENE | J28: FEB | L28: MAR | N28: ABR | P28: MAY | R28: JUN | T28: JUL | V28: AGO | X28: SEP | Z28: OCT | AB28: NOV
C29: META
C30: RESULTADO
B41: ANÁLISIS
C43: MES | D43: CAUSAS DESVIACIÓN | L43: ACCION(ES) DE MEJORA | T43: RESPONSABLE | Z43: FECHA PROGRAMADA DE CIERRE | AD43: ESTADO DE LA ACCIÓN | AF43: OBSERVACIONES / SEGUIMIENTO
C44: ENE
C45: FEB
C46: MAR
C47: ABR
C48: MAY
C49: JUN
C50: JUL
C51: AGO
C52: SEP
C53: OCT
C54: DIC
C55: ENE
... C65: DIC

Sheet FT22
H2: Ficha Técnica de Indicador
B5: DATOS DEL INDICADOR
C7: NOMBRE INDICADOR | N7: OBJETIVO INDICADOR
C9: PROCESO(S) RELACIONADO (S)
C11: PRÁCTICA(S) SEGURA RELACIONADA
C13: FÓRMULA PARA CÁLCULO DEL INDICADOR | F13: FÓRMULA | N13: FRECUENCIA MEDICIÓN | V13: META
F15: Numerador | N15: Denominador | V15: Unidad de medida
F17: Fuente Numerador | N17: Fuente Denominador
C19: RESPONSABLE INDICADOR | P19: RESPONSABLE ANALIZAR Y GESTIONAR
B22: MEDICIÓN
C24: AÑO ______ | F24: MED INICIAL | H24: ENE | J24: FEB | L24: MAR | N24: ABR | P24: MAY | R24: JUN | T24: JUL | V24: AGO | X24: SEP | Z24: OCT | AB24: NOV
C25: META
C26: RESULTADO
C28: AÑO ______ | F28: DIC | H28: ENE | J28: FEB | L28: MAR | N28: ABR | P28: MAY | R28: JUN | T28: JUL | V28: AGO | X28: SEP | Z28: OCT | AB28: NOV
C29: META
C30: RESULTADO
B41: ANÁLISIS
C43: MES | D43: CAUSAS DESVIACIÓN | L43: ACCION(ES) DE MEJORA | T43: RESPONSABLE | Z43: FECHA PROGRAMADA DE CIERRE | AD43: ESTADO DE LA ACCIÓN | AF43: OBSERVACIONES / SEGUIMIENTO
C44: ENE
C45: FEB
C46: MAR
C47: ABR
C48: MAY
C49: JUN
C50: JUL
C51: AGO
C52: SEP
C53: OCT
C54: DIC
C55: ENE
... C65: DIC

Sheet FT23
H2: Ficha Técnica de Indicador
B5: DATOS DEL INDICADOR
C7: NOMBRE INDICADOR | N7: OBJETIVO INDICADOR
C9: PROCESO(S) RELACIONADO (S)
C11: PRÁCTICA(S) SEGURA RELACIONADA
C13: FÓRMULA PARA CÁLCULO DEL INDICADOR | F13: FÓRMULA | N13: FRECUENCIA MEDICIÓN | V13: META
F15: Numerador | N15: Denominador | V15: Unidad de medida
F17: Fuente Numerador | N17: Fuente Denominador
C19: RESPONSABLE INDICADOR | P19: RESPONSABLE ANALIZAR Y GESTIONAR
B22: MEDICIÓN
C24: AÑO ______ | F24: MED INICIAL | H24: ENE | J24: FEB | L24: MAR | N24: ABR | P24: MAY | R24: JUN | T24: JUL | V24: AGO | X24: SEP | Z24: OCT | AB24: NOV
C25: META
C26: RESULTADO
C28: AÑO ______ | F28: DIC | H28: ENE | J28: FEB | L28: MAR | N28: ABR | P28: MAY | R28: JUN | T28: JUL | V28: AGO | X28: SEP | Z28: OCT | AB28: NOV
C29: META
C30: RESULTADO
B41: ANÁLISIS
C43: MES | D43: CAUSAS DESVIACIÓN | L43: ACCION(ES) DE MEJORA | T43: RESPONSABLE | Z43: FECHA PROGRAMADA DE CIERRE | AD43: ESTADO DE LA ACCIÓN | AF43: OBSERVACIONES / SEGUIMIENTO
C44: ENE
C45: FEB
C46: MAR
C47: ABR
C48: MAY
C49: JUN
C50: JUL
C51: AGO
C52: SEP
C53: OCT
C54: DIC
C55: ENE
... C65: DIC

Sheet FT24
H2: Ficha Técnica de Indicador
B5: DATOS DEL INDICADOR
C7: NOMBRE INDICADOR | N7: OBJETIVO INDICADOR
C9: PROCESO(S) RELACIONADO (S)
C11: PRÁCTICA(S) SEGURA RELACIONADA
C13: FÓRMULA PARA CÁLCULO DEL INDICADOR | F13: FÓRMULA | N13: FRECUENCIA MEDICIÓN | V13: META
F15: Numerador | N15: Denominador | V15: Unidad de medida
F17: Fuente Numerador | N17: Fuente Denominador
C19: RESPONSABLE INDICADOR | P19: RESPONSABLE ANALIZAR Y GESTIONAR
B22: MEDICIÓN
C24: AÑO ______ | F24: MED INICIAL | H24: ENE | J24: FEB | L24: MAR | N24: ABR | P24: MAY | R24: JUN | T24: JUL | V24: AGO | X24: SEP | Z24: OCT | AB24: NOV
C25: META
C26: RESULTADO
C28: AÑO ______ | F28: DIC | H28: ENE | J28: FEB | L28: MAR | N28: ABR | P28: MAY | R28: JUN | T28: JUL | V28: AGO | X28: SEP | Z28: OCT | AB28: NOV
C29: META
C30: RESULTADO
B41: ANÁLISIS
C43: MES | D43: CAUSAS DESVIACIÓN | L43: ACCION(ES) DE MEJORA | T43: RESPONSABLE | Z43: FECHA PROGRAMADA DE CIERRE | AD43: ESTADO DE LA ACCIÓN | AF43: OBSERVACIONES / SEGUIMIENTO
C44: ENE
C45: FEB
C46: MAR
C47: ABR
C48: MAY
C49: JUN
C50: JUL
C51: AGO
C52: SEP
C53: OCT
C54: DIC
C55: ENE
... C65: DIC

Sheet FT25
H2: Ficha Técnica de Indicador
B5: DATOS DEL INDICADOR
C7: NOMBRE INDICADOR | N7: OBJETIVO INDICADOR
C9: PROCESO(S) RELACIONADO (S)
C11: PRÁCTICA(S) SEGURA RELACIONADA
C13: FÓRMULA PARA CÁLCULO DEL INDICADOR | F13: FÓRMULA | N13: FRECUENCIA MEDICIÓN | V13: META
F15: Numerador | N15: Denominador | V15: Unidad de medida
F17: Fuente Numerador | N17: Fuente Denominador
C19: RESPONSABLE INDICADOR | P19: RESPONSABLE ANALIZAR Y GESTIONAR
B22: MEDICIÓN
C24: AÑO ______ | F24: MED INICIAL | H24: ENE | J24: FEB | L24: MAR | N24: ABR | P24: MAY | R24: JUN | T24: JUL | V24: AGO | X24: SEP | Z24: OCT | AB24: NOV
C25: META
C26: RESULTADO
C28: AÑO ______ | F28: DIC | H28: ENE | J28: FEB | L28: MAR | N28: ABR | P28: MAY | R28: JUN | T28: JUL | V28: AGO | X28: SEP | Z28: OCT | AB28: NOV
C29: META
C30: RESULTADO
B41: ANÁLISIS
C43: MES | D43: CAUSAS DESVIACIÓN | L43: ACCION(ES) DE MEJORA | T43: RESPONSABLE | Z43: FECHA PROGRAMADA DE CIERRE | AD43: ESTADO DE LA ACCIÓN | AF43: OBSERVACIONES / SEGUIMIENTO
C44: ENE
C45: FEB
C46: MAR
C47: ABR
C48: MAY
C49: JUN
C50: JUL
C51: AGO
C52: SEP
C53: OCT
C54: DIC
C55: ENE
... C65: DIC

Sheet FT26
H2: Ficha Técnica de Indicador
B5: DATOS DEL INDICADOR
C7: NOMBRE INDICADOR | N7: OBJETIVO INDICADOR
C9: PROCESO(S) RELACIONADO (S)
C11: PRÁCTICA(S) SEGURA RELACIONADA
C13: FÓRMULA PARA CÁLCULO DEL INDICADOR | F13: FÓRMULA | N13: FRECUENCIA MEDICIÓN | V13: META
F15: Numerador | N15: Denominador | V15: Unidad de medida
F17: Fuente Numerador | N17: Fuente Denominador
C19: RESPONSABLE INDICADOR | P19: RESPONSABLE ANALIZAR Y GESTIONAR
B22: MEDICIÓN
C24: AÑO ______ | F24: MED INICIAL | H24: ENE | J24: FEB | L24: MAR | N24: ABR | P24: MAY | R24: JUN | T24: JUL | V24: AGO | X24: SEP | Z24: OCT | AB24: NOV
C25: META
C26: RESULTADO
C28: AÑO ______ | F28: DIC | H28: ENE | J28: FEB | L28: MAR | N28: ABR | P28: MAY | R28: JUN | T28: JUL | V28: AGO | X28: SEP | Z28: OCT | AB28: NOV
C29: META
C30: RESULTADO
B41: ANÁLISIS
C43: MES | D43: CAUSAS DESVIACIÓN | L43: ACCION(ES) DE MEJORA | T43: RESPONSABLE | Z43: FECHA PROGRAMADA DE CIERRE | AD43: ESTADO DE LA ACCIÓN | AF43: OBSERVACIONES / SEGUIMIENTO
C44: ENE
C45: FEB
C46: MAR
C47: ABR
C48: MAY
C49: JUN
C50: JUL
C51: AGO
C52: SEP
C53: OCT
C54: DIC
C55: ENE
... C65: DIC

Sheet FT27
H2: Ficha Técnica de Indicador
B5: DATOS DEL INDICADOR
C7: NOMBRE INDICADOR | N7: OBJETIVO INDICADOR
C9: PROCESO(S) RELACIONADO (S)
C11: PRÁCTICA(S) SEGURA RELACIONADA
C13: FÓRMULA PARA CÁLCULO DEL INDICADOR | F13: FÓRMULA | N13: FRECUENCIA MEDICIÓN | V13: META
F15: Numerador | N15: Denominador | V15: Unidad de medida
F17: Fuente Numerador | N17: Fuente Denominador
C19: RESPONSABLE INDICADOR | P19: RESPONSABLE ANALIZAR Y GESTIONAR
B22: MEDICIÓN
C24: AÑO ______ | F24: MED INICIAL | H24: ENE | J24: FEB | L24: MAR | N24: ABR | P24: MAY | R24: JUN | T24: JUL | V24: AGO | X24: SEP | Z24: OCT | AB24: NOV
C25: META
C26: RESULTADO
C28: AÑO ______ | F28: DIC | H28: ENE | J28: FEB | L28: MAR | N28: ABR | P28: MAY | R28: JUN | T28: JUL | V28: AGO | X28: SEP | Z28: OCT | AB28: NOV
C29: META
C30: RESULTADO
B41: ANÁLISIS
C43: MES | D43: CAUSAS DESVIACIÓN | L43: ACCION(ES) DE MEJORA | T43: RESPONSABLE | Z43: FECHA PROGRAMADA DE CIERRE | AD43: ESTADO DE LA ACCIÓN | AF43: OBSERVACIONES / SEGUIMIENTO
C44: ENE
C45: FEB
C46: MAR
C47: ABR
C48: MAY
C49: JUN
C50: JUL
C51: AGO
C52: SEP
C53: OCT
C54: DIC
C55: ENE
... C65: DIC

Sheet FT28
H2: Ficha Técnica de Indicador
B5: DATOS DEL INDICADOR
C7: NOMBRE INDICADOR | N7: OBJETIVO INDICADOR
C9: PROCESO(S) RELACIONADO (S)
C11: PRÁCTICA(S) SEGURA RELACIONADA
C13: FÓRMULA PARA CÁLCULO DEL INDICADOR | F13: FÓRMULA | N13: FRECUENCIA MEDICIÓN | V13: META
F15: Numerador | N15: Denominador | V15: Unidad de medida
F17: Fuente Numerador | N17: Fuente Denominador
C19: RESPONSABLE INDICADOR | P19: RESPONSABLE ANALIZAR Y GESTIONAR
B22: MEDICIÓN
C24: AÑO ______ | F24: MED INICIAL | H24: ENE | J24: FEB | L24: MAR | N24: ABR | P24: MAY | R24: JUN | T24: JUL | V24: AGO | X24: SEP | Z24: OCT | AB24: NOV
C25: META
C26: RESULTADO
C28: AÑO ______ | F28: DIC | H28: ENE | J28: FEB | L28: MAR | N28: ABR | P28: MAY | R28: JUN | T28: JUL | V28: AGO | X28: SEP | Z28: OCT | AB28: NOV
C29: META
C30: RESULTADO
B41: ANÁLISIS
C43: MES | D43: CAUSAS DESVIACIÓN | L43: ACCION(ES) DE MEJORA | T43: RESPONSABLE | Z43: FECHA PROGRAMADA DE CIERRE | AD43: ESTADO DE LA ACCIÓN | AF43: OBSERVACIONES / SEGUIMIENTO
C44: ENE
C45: FEB
C46: MAR
C47: ABR
C48: MAY
C49: JUN
C50: JUL
C51: AGO
C52: SEP
C53: OCT
C54: DIC
C55: ENE
... C65: DIC

Sheet FT29
H2: Ficha Técnica de Indicador
B5: DATOS DEL INDICADOR
C7: NOMBRE INDICADOR | N7: OBJETIVO INDICADOR
C9: PROCESO(S) RELACIONADO (S)
C11: PRÁCTICA(S) SEGURA RELACIONADA
C13: FÓRMULA PARA CÁLCULO DEL INDICADOR | F13: FÓRMULA | N13: FRECUENCIA MEDICIÓN | V13: META
F15: Numerador | N15: Denominador | V15: Unidad de medida
F17: Fuente Numerador | N17: Fuente Denominador
C19: RESPONSABLE INDICADOR | P19: RESPONSABLE ANALIZAR Y GESTIONAR
B22: MEDICIÓN
C24: AÑO ______ | F24: MED INICIAL | H24: ENE | J24: FEB | L24: MAR | N24: ABR | P24: MAY | R24: JUN | T24: JUL | V24: AGO | X24: SEP | Z24: OCT | AB24: NOV
C25: META
C26: RESULTADO
C28: AÑO ______ | F28: DIC | H28: ENE | J28: FEB | L28: MAR | N28: ABR | P28: MAY | R28: JUN | T28: JUL | V28: AGO | X28: SEP | Z28: OCT | AB28: NOV
C29: META
C30: RESULTADO
B41: ANÁLISIS
C43: MES | D43: CAUSAS DESVIACIÓN | L43: ACCION(ES) DE MEJORA | T43: RESPONSABLE | Z43: FECHA PROGRAMADA DE CIERRE | AD43: ESTADO DE LA ACCIÓN | AF43: OBSERVACIONES / SEGUIMIENTO
C44: ENE
C45: FEB
C46: MAR
C47: ABR
C48: MAY
C49: JUN
C50: JUL
C51: AGO
C52: SEP
C53: OCT
C54: DIC
C55: ENE
... C65: DIC

Sheet FT30
H2: Ficha Técnica de Indicador
B5: DATOS DEL INDICADOR
C7: NOMBRE INDICADOR | N7: OBJETIVO INDICADOR
C9: PROCESO(S) RELACIONADO (S)
C11: PRÁCTICA(S) SEGURA RELACIONADA
C13: FÓRMULA PARA CÁLCULO DEL INDICADOR | F13: FÓRMULA | N13: FRECUENCIA MEDICIÓN | V13: META
F15: Numerador | N15: Denominador | V15: Unidad de medida
F17: Fuente Numerador | N17: Fuente Denominador
C19: RESPONSABLE INDICADOR | P19: RESPONSABLE ANALIZAR Y GESTIONAR
B22: MEDICIÓN
C24: AÑO ______ | F24: MED INICIAL | H24: ENE | J24: FEB | L24: MAR | N24: ABR | P24: MAY | R24: JUN | T24: JUL | V24: AGO | X24: SEP | Z24: OCT | AB24: NOV
C25: META
C26: RESULTADO
C28: AÑO ______ | F28: DIC | H28: ENE | J28: FEB | L28: MAR | N28: ABR | P28: MAY | R28: JUN | T28: JUL | V28: AGO | X28: SEP | Z28: OCT | AB28: NOV
C29: META
C30: RESULTADO
B41: ANÁLISIS
C43: MES | D43: CAUSAS DESVIACIÓN | L43: ACCION(ES) DE MEJORA | T43: RESPONSABLE | Z43: FECHA PROGRAMADA DE CIERRE | AD43: ESTADO DE LA ACCIÓN | AF43: OBSERVACIONES / SEGUIMIENTO
C44: ENE
C45: FEB
C46: MAR
C47: ABR
C48: MAY
C49: JUN
C50: JUL
C51: AGO
C52: SEP
C53: OCT
C54: DIC
C55: ENE
... C65: DIC

Sheet INFO
A2: Version 2.2 Build date: 2023-11
