Workbook

Sheet Instructivo de Uso
A1: 📋 INSTRUCTIVO DE USO — HERRAMIENTA DE AUDITORÍA PROFESIONAL INDEPENDIENTE EN SALUD
A2: Resolución 3100 de 2019 | Sistema Único de Habilitación | Audisalud Colombia S.A.S. | Versión 2.0
A4: 1. PROPÓSITO Y ALCANCE DE LA HERRAMIENTA
B5: ASPECTO | C5: DETALLE
B6: ¿Para qué sirve? | C6: Auditar el cumplimiento de los estándares de habilitación (Res. 3100/2019) para PROFESIONALES INDEPENDIENTES. Cubre Talento Humano, Infraestructura, Dotación, Medicamentos/DM/Insumos, Procesos Prioritarios, Historia Clínica e Interdependencia para todos los servicios que puede habilitar un profesional independiente.
B7: ¿A quién aplica? | C7: Profesionales independientes habilitados individualmente: médicos, enfermeras, nutricionistas, psicólogos, optómetras, fisioterapeutas, fonoaudiólogos, terapeutas ocupacionales, terapeutas respiratorios, bacteriólogos y demás profesionales con habilitación individual ante la Secretaría de Salud.
B8: ¿Qué NO cubre? | C8: No cubre IPS, servicios hospitalarios, UCI, urgencias complejas, cirugías mayores, bancos de sangre, servicios de internación ni radioterapia / medicina nuclear. Para estos servicios se requieren instrumentos adicionales.
B9: Normativa base | C9: Resolución 3100 de 2019 — MinSalud Colombia. La herramienta usa el texto LITERAL de la norma, organizado por sección, número de referencia (11.1.1 – 11.3.12) y modalidad de prestación (intramural, extramural, telemedicina).
A11: 2. ESTRUCTURA DEL LIBRO — DESCRIPCIÓN DE CADA HOJA
A12: # | B12: PESTAÑA | C12: DESCRIPCIÓN | D12: CUÁNDO USARLA
A13: 1 | B13: Instructivo de Uso | C13: Este documento. Explica la herramienta, íconos y flujo de trabajo recomendado. | D13: Leer SIEMPRE antes de iniciar una auditoría
A14: 2 | B14: Recomendaciones | C14: Recomendaciones prácticas por estándar con nivel de riesgo 🔴🟡🟠🟢. | D14: Consultar antes de cada visita para anticipar hallazgos
A15: 3 | B15: Diferencias Servicios | C15: Tabla comparativa de exigencias entre servicios y puntos críticos por tipo de servicio. | D15: Consultar cuando el prestador tiene más de un servicio habilitado
A16: 4 | B16: Dashboard | C16: Panel de control: % cumplimiento, semáforo y alertas críticas. Se actualiza automáticamente al marcar X. | D16: Ver durante y después de cada auditoría
A17: 5 | B17: Criterios Generales | C17: Criterios generales (Sec. 11.1.1–11.1.7) filtrados para profesional independiente. | D17: Aplicar PRIMERO — aplica a todos los servicios habilitados
A18: 6 | B18: Ficha Prestador | C18: Datos del prestador, habilitación, auditoría y semáforo automático de vencimientos de documentos. | D18: Diligenciar al inicio de TODA visita
A19: 7 | B19: Auditoría Documental | C19: Lista de chequeo de documentos requeridos por los estándares generales. | D19: Verificación de carpetas y archivos del prestador
A20: 8 | B20: Auditoría Infraestructura | C20: Criterios de infraestructura física según la Resolución 3100/2019. | D20: Recorrido físico por las instalaciones
A21: 9 | B21: Consulta Externa | C21: Criterios específicos CE General (Baja) y CE Especializada (Mediana), todas las modalidades incluida telemedicina. | D21: Cuando el prestador tiene habilitado servicio de CE
A22: 10 | B22: Terapias | C22: Criterios del servicio de Terapias Física, Ocupacional, Lenguaje y Respiratoria — Sec. 11.3.1. | D22: Cuando el prestador es fisioterapeuta, fonoaudiólogo, TO o TR
A23: 11 | B23: Laboratorio Clínico | C23: Criterios de Laboratorio Clínico Baja Complejidad — Sec. 11.3.12, incluye modalidad telemedicina. | D23: Cuando el prestador es bacteriólogo con laboratorio habilitado
... A26: 14 | B26: Claude Log | C26: Registro de versiones y cambios realizados en la herramienta. | D26: Consultar para verificar versión
A28: 3. FLUJO DE TRABAJO RECOMENDADO — PASO A PASO
A29: ANTES DE LA VISITA
A30: 1. Descarga y abre una COPIA del archivo (no trabajes sobre el original).
A31: 2. Revisa el semáforo de vencimientos en la Ficha Prestador para identificar alertas previas.
A32: 3. Identifica qué servicios tiene habilitados el prestador (CE, Terapias, Lab…).
A33: 4. Prepara los formatos a aplicar según los servicios habilitados.
A35: DURANTE LA VISITA
A36: 5. Diligencia la Ficha Prestador con datos del prestador y de la auditoría.
A37: 6. Aplica Criterios Generales (aplican a TODOS los servicios).
A38: 7. Aplica las hojas de servicio específico según lo habilitado.
A39: 8. Marca X en columna C (Cumple), NC (No Cumple) o NA (No Aplica) en cada criterio.
A40: 9. Registra el hallazgo exacto en la columna 'Hallazgo / Evidencia'.
... A53: 4. ÍCONOS, COLORES Y CONVENCIONES
B54: ÍCONO / COLOR | C54: SIGNIFICADO | D54: ACCIÓN REQUERIDA
B55: ⚠️ Fondo AMARILLO en fila | C55: Criterio CRÍTICO — incumplimiento puede generar requerimiento o cierre del servicio | D55: Documentar con detalle. Si NC → Requerimiento formal obligatorio
B56: ★ Número con estrella | C56: Criterio explícito para Profesional Independiente en la norma | D56: Verificar con prioridad — la norma hace distinción específica
B57: ⊘ Fila GRIS tachada | C57: Criterio EXCLUIDO: no aplica al profesional independiente (aplica a IPS, hospitales) | D57: No evaluar — marcar NA si el sistema lo requiere
B58: Fila 🟢 VERDE | C58: Criterio marcado C (Cumple) | D58: Documenta la evidencia en la columna Hallazgo
B59: Fila 🔴 ROJA | C59: Criterio marcado NC (No Cumple) | D59: OBLIGATORIO: llenar Plan de Mejora, Responsable y Fecha
B60: Fila ⬜ GRIS | C60: Criterio marcado NA (No Aplica) | D60: Justificar brevemente en columna Hallazgo
B61: Dashboard 🟢 CUMPLE | C61: ≥ 90% de criterios evaluados cumplen | D61: Estado ideal — revisión de mantenimiento
B62: Dashboard 🟡 EN PROCESO | C62: Entre 70% y 89% de criterios cumplen | D62: Plan de mejora en curso — seguimiento requerido
B63: Dashboard 🔴 NO CUMPLE | C63: Menos del 70% de criterios cumplen | D63: Situación crítica — posibles requerimientos
B64: Ficha 🟠 PRÓXIMO A VENCER | C64: Documento vence en menos de 30 días | D64: Notificar al prestador para renovación inmediata
B65: Ficha 🔴 VENCIDO | C65: Documento ya vencido | D65: Criterio crítico — consignar como hallazgo en el Acta
B66: C / NC / NA en columnas | C66: Desplegable de marcación: escribe o selecciona X en la columna correspondiente | D66: Solo una X por fila — columnas G, H o I según aplique

Sheet Dashboard
A1: DASHBOARD DE AUDITORIA — HABILITACION EN SALUD — PROFESIONAL INDEPENDIENTE
A2: Resolucion 3100 de 2019 | Sistema Unico de Habilitacion | Audisalud Colombia S.A.S.
A3: PRESTADOR: | F3: FECHA:
A4: AUDITOR: | E4: HORA INICIO: | G4: TIPO AUDITORIA:
A5: LEYENDA: C = Cumple | NC = No Cumple | NA = No Aplica — Marque X en cada criterio en la hoja correspondiente
A6: CUMPLIMIENTO POR INSTRUMENTO DE AUDITORIA
A7: # | B7: INSTRUMENTO | C7: TOTAL | D7: CUMPLE (C) | E7: NO CUMPLE (NC) | F7: NO APLICA (NA) | G7: % CUMPL. | H7: SEMAFORO | I7: ESTADO NC
A8: 1 | B8: Criterios Generales | C8: =COUNTA('Criterios Generales'!D8:D174) -> 138 | D8: =COUNTIF('Criterios Generales'!G8:G174,"X") -> 1 | E8: =COUNTIF('Criterios Generales'!H8:H174,"X") -> 0 | F8: =COUNTIF('Criterios Generales'!I8:I174,"X") -> 0 | G8: =IF((D8+E8)=0,0,D8/(D8+E8)) -> 1 | H8: =IF((D8+E8)=0,"SIN EVALUAR",IF(G8>=0.9,"CUMPLE",IF(G8>=0.7,"EN PROCESO","NO CUMPLE"))) -> CUMPLE | I8: =IF(E8=0,"Sin hallazgos NC","ATENCION: "&E8&" hallazgo(s) NC") -> Sin hallazgos NC
A9: 2 | B9: Auditoria Documental | C9: =COUNTA('Auditoría Documental'!D8:D97) -> 87 | D9: =COUNTIF('Auditoría Documental'!F8:F97,"X") -> 0 | E9: =COUNTIF('Auditoría Documental'!G8:G97,"X") -> 0 | F9: =COUNTIF('Auditoría Documental'!H8:H97,"X") -> 0 | G9: =IF((D9+E9)=0,0,D9/(D9+E9)) -> 0 | H9: =IF((D9+E9)=0,"SIN EVALUAR",IF(G9>=0.9,"CUMPLE",IF(G9>=0.7,"EN PROCESO","NO CUMPLE"))) -> SIN EVALUAR | I9: =IF(E9=0,"Sin hallazgos NC","ATENCION: "&E9&" hallazgo(s) NC") -> Sin hallazgos NC
A10: 3 | B10: Auditoria Infraestructura | C10: =COUNTA('Auditoría Infraestructura'!D8:D62) -> 55 | D10: =COUNTIF('Auditoría Infraestructura'!F8:F62,"X") -> 0 | E10: =COUNTIF('Auditoría Infraestructura'!G8:G62,"X") -> 0 | F10: =COUNTIF('Auditoría Infraestructura'!H8:H62,"X") -> 0 | G10: =IF((D10+E10)=0,0,D10/(D10+E10)) -> 0 | H10: =IF((D10+E10)=0,"SIN EVALUAR",IF(G10>=0.9,"CUMPLE",IF(G10>=0.7,"EN PROCESO","NO CUMPLE"))) -> SIN EVALUAR | I10: =IF(E10=0,"Sin hallazgos NC","ATENCION: "&E10&" hallazgo(s) NC") -> Sin hallazgos NC
A11: 4 | B11: Consulta Externa | C11: =COUNTA('Consulta Externa'!D11:D203) -> 131 | D11: =COUNTIF('Consulta Externa'!F11:F203,"X") -> 0 | E11: =COUNTIF('Consulta Externa'!G11:G203,"X") -> 0 | F11: =COUNTIF('Consulta Externa'!H11:H203,"X") -> 0 | G11: =IF((D11+E11)=0,0,D11/(D11+E11)) -> 0 | H11: =IF((D11+E11)=0,"SIN EVALUAR",IF(G11>=0.9,"CUMPLE",IF(G11>=0.7,"EN PROCESO","NO CUMPLE"))) -> SIN EVALUAR | I11: =IF(E11=0,"Sin hallazgos NC","ATENCION: "&E11&" hallazgo(s) NC") -> Sin hallazgos NC
A12: 5 | B12: Terapias | C12: =COUNTA(Terapias!D8:D55) -> 45 | D12: =COUNTIF(Terapias!F8:F55,"X") -> 0 | E12: =COUNTIF(Terapias!G8:G55,"X") -> 0 | F12: =COUNTIF(Terapias!H8:H55,"X") -> 0 | G12: =IF((D12+E12)=0,0,D12/(D12+E12)) -> 0 | H12: =IF((D12+E12)=0,"SIN EVALUAR",IF(G12>=0.9,"CUMPLE",IF(G12>=0.7,"EN PROCESO","NO CUMPLE"))) -> SIN EVALUAR | I12: =IF(E12=0,"Sin hallazgos NC","ATENCION: "&E12&" hallazgo(s) NC") -> Sin hallazgos NC
A13: 6 | B13: Laboratorio Clinico | C13: =COUNTA('Laboratorio Clínico'!D10:D97) -> 66 | D13: =COUNTIF('Laboratorio Clínico'!G10:G97,"X") -> 0 | E13: =COUNTIF('Laboratorio Clínico'!H10:H97,"X") -> 0 | F13: =COUNTIF('Laboratorio Clínico'!I10:I97,"X") -> 0 | G13: =IF((D13+E13)=0,0,D13/(D13+E13)) -> 0 | H13: =IF((D13+E13)=0,"SIN EVALUAR",IF(G13>=0.9,"CUMPLE",IF(G13>=0.7,"EN PROCESO","NO CUMPLE"))) -> SIN EVALUAR | I13: =IF(E13=0,"Sin hallazgos NC","ATENCION: "&E13&" hallazgo(s) NC") -> Sin hallazgos NC
A14: 7 | B14: Toma de Muestras Lab | C14: =COUNTA('Toma de Muestras Lab'!D10:D60) -> 35 | D14: =COUNTIF('Toma de Muestras Lab'!G10:G60,"X") -> 0 | E14: =COUNTIF('Toma de Muestras Lab'!H10:H60,"X") -> 0 | F14: =COUNTIF('Toma de Muestras Lab'!I10:I60,"X") -> 0 | G14: =IF((D14+E14)=0,0,D14/(D14+E14)) -> 0 | H14: =IF((D14+E14)=0,"SIN EVALUAR",IF(G14>=0.9,"CUMPLE",IF(G14>=0.7,"EN PROCESO","NO CUMPLE"))) -> SIN EVALUAR | I14: =IF(E14=0,"Sin hallazgos NC","ATENCION: "&E14&" hallazgo(s) NC") -> Sin hallazgos NC
A15: TOTAL GENERAL | C15: =SUM(C8:C14) -> 557 | D15: =SUM(D8:D14) -> 1 | E15: =SUM(E8:E14) -> 0 | F15: =SUM(F8:F14) -> 0 | G15: =IF((D15+E15)=0,0,D15/(D15+E15)) -> 1 | H15: =IF((D15+E15)=0,"SIN EVALUAR",IF(G15>=0.9,"CUMPLE",IF(G15>=0.7,"EN PROCESO","NO CUMPLE"))) -> CUMPLE | I15: =IF(E15=0,"Sin hallazgos","ATENCION: "&E15&" NC") -> Sin hallazgos
A17: ALERTAS CRITICAS — CRITERIOS CON CAUSAL DE CIERRE O SANCION
A18: # | B18: CRITERIO CRITICO | C18: INSTRUMENTO / HOJA | I18: ESTADO
A19: 1 | B19: Tarjeta profesional VIGENTE del prestador | C19: CE / Terapias / Lab Clinico / Toma Muestras | I19: Pendiente
A20: 2 | B20: Habilitacion vigente en REPS | C20: Ficha Prestador | I20: Pendiente
A21: 3 | B21: Concepto sanitario vigente | C21: Ficha Prestador / Auditoria Infraestructura | I21: Pendiente
A22: 4 | B22: Certificado RETIE vigente | C22: Ficha Prestador / Auditoria Documental | I22: Pendiente
A23: 5 | B23: Programa de seguridad del paciente documentado | C23: Criterios Generales / CE / Terapias / Lab | I23: Pendiente
A24: 6 | B24: Consentimiento informado funcional y verificable | C24: Criterios Generales / CE / Terapias | I24: Pendiente
A25: 7 | B25: Protocolo de higiene de manos con insumos | C25: Criterios Generales / CE / Terapias / Lab | I25: Pendiente
A26: 8 | B26: Historia clinica con componentes minimos (Res. 1995/99) | C26: CE / Terapias | I26: Pendiente
A27: 9 | B27: Plan de gestion integral de residuos (PGIRHS) | C27: Auditoria Documental / Infraestructura | I27: Pendiente
A28: 10 | B28: Reactivos con registro sanitario INVIMA vigente | C28: Laboratorio Clinico | I28: Pendiente
A29: 11 | B29: Doc. atencion victimas de violencias sexuales | C29: Criterios Generales / Consulta Externa | I29: Pendiente
A30: 12 | B30: Protocolo de bioseguridad especifico del servicio | C30: Criterios Generales / CE / Terapias / Lab | I30: Pendiente
A32: LEYENDA DE SEMAFOROS
A33: CUMPLE | C33: 90% o mas de criterios cumplen
A34: EN PROCESO | C34: Entre 70% y 89% cumplen
A35: NO CUMPLE | C35: Menos del 70% cumplen
A36: SIN EVALUAR | C36: Sin datos marcados aun

Sheet Recomendaciones
A1: 💡 RECOMENDACIONES DE AUDITORÍA Y HABILITACIÓN — PROFESIONAL INDEPENDIENTE
A2: Basadas en Res. 3100/2019 y experiencia práctica en el Sistema Único de Habilitación | Audisalud Colombia S.A.S.
A4: TALENTO HUMANO
A5: # | B5: ASPECTO | C5: RIESGO | D5: RECOMENDACIÓN PRÁCTICA
A6: 1 | B6: Tarjeta profesional vigente | C6: 🔴 CRÍTICO | D6: El criterio más verificado y más incumplido. La tarjeta no puede estar vencida ni cancelada. Verificar siempre en el portal ReTHUS (https://web.sispro.gov.co/THS/Cliente/ConsultasPublicas/ConsultaPublicaDeTHxIdentificacion.aspx) — el registro electrónico prevalece sobre el documento físico. Es causal de cierre inmediato del servicio.
A7: 2 | B7: ReTHUS actualizado | C7: 🔴 CRÍTICO | D7: Todo profesional debe estar inscrito en el Registro Único Nacional de Talento Humano en Salud. Si hay discrepancia entre la tarjeta profesional y el ReTHUS, prevalece el ReTHUS. Verificar en línea en el momento de la visita.incluyendo especialistas.
A8: 3 | B8: Formación continua | C8: 🟡 ATENCIÓN | D8: La norma NO exige horas mínimas — basta con evidenciar continuidad en la actualización. Guardar constancias de cursos, congresos y talleres. Si cuenta con personal de apoyo incluye formacion continuia
A9: 4 | B9: Formación en telemedicina | C9: 🟡 ATENCIÓN | D9: Si presta servicios en modalidad telemedicina, debe tener constancia de formación en el manejo de la tecnología utilizada. Es uno de los criterios más omitidos en habilitación de modalidad virtual.
A10: 5 | B10: Estudiantes en práctica formativa | C10: No aplica | D10: NO APLICA AL PROFESIONAL INDEPENDIENTE — El criterio de escenarios de práctica formativa (convenio con IES y estudio de capacidad instalada) aplica a IPS y entidades con objeto social diferente que tienen estudiantes en práctica. El profesional independiente NO puede tener estudiantes asignados como escenario de práctica formativa; si lo hace, cambia su naturaleza jurídica de independiente a institución.
A11: 6 | B11: Sedación: talento humano requerido | C11: 🔴 CRÍTICO | D11: Si realiza procedimientos bajo sedación fuera de salas de cirugía: verificar grado de sedación y el profesional anestesiólogo requerido. Grado I y II pueden ser realizados con médico capacitado en soporte vital y sedación. Grado IV requiere anestesiólogo obligatorio.
A12: 7 | B12: Facturación como profesional independiente | C12: Critico | D12: El profesional independiente DEBE facturar como persona natural (cédula), NO como persona jurídica (NIT). Facturar bajo un NIT cambia automáticamente la naturaleza jurídica del prestador de 'Profesional Independiente' a 'Entidad con Objeto Social Diferente (EOSD)' o IPS, lo que implica requisitos de habilitación completamente distintos y más exigentes. IMPLICACIONES PRÁCTICAS: • La habilitación en REPS debe estar registrada a nombre del profesional (cédula), no a nombre de una empresa. • Las facturas de venta de servicios de salud deben llevar el número de cédula del profesional. • Si tiene empleados o contrata otros profesionales a su nombre, puede perder la categoría de independiente. • El RUT del profesional debe reflejar la actividad de prestación de servicios de salud (código CIIU correspondiente). • En la DIAN: registrarse como persona natural responsable de IVA o no responsable, según ingresos. VERIFICAR EN AUDITORIA: Solicitar la factura de servicios o el contrato con la entidad pagadora — debe aparecer el nombre y cédula del profesional, NO una razón social ni un NIT de empresa.
A15: INFRAESTRUCTURA
A16: # | B16: ASPECTO | C16: RIESGO | D16: RECOMENDACIÓN PRÁCTICA
A17: 1 | B17: Concepto sanitario vigente | C17: 🔴 CRÍTICO | D17: Es el documento que más demora en obtenerse (puede tardar 2-3 meses). Tramitar con anticipación ante la Secretaría de Salud. Su vencimiento afecta directamente la habilitación vigente en REPS.
A18: 2 | B18: Certificado RETIE | C18: 🔴 CRÍTICO | D18: Debe ser emitido por ingeniero eléctrico con matrícula vigente. Aplica incluso en consultorios pequeños. Verificar que cubra las instalaciones actuales y que la matrícula del ingeniero esté vigente. Si la infraestructura es antes de mayo 2025 si es posterior se debe hacer con una empresa avalada por la onac
A19: 3 | B19: Certificado de Bomberos | C19: 🔴 CRÍTICO | D19: Gestionarlo con la Secretaría de Gobierno o el Cuerpo de Bomberos local. En municipios pequeños puede tramitarse con la administración municipal. Renovar con la misma periodicidad que define la entidad emisora.
A20: 4 | B20: Consultorio: dimensiones mínimas | C20: 🔴 CRÍTICO | D20: Consultorio con examen físico: mínimo 10 m² SIN incluir la unidad sanitaria. Consultorio solo entrevista: mínimo 4 m². Medir siempre — el incumplimiento es más frecuente de lo que parece en consultorios pequeños.
A21: 5 | B21: Pisos en media caña | C21: 🟡 ATENCIÓN | D21: Obligatorio en laboratorios, consultorios de procedimientos y consulta odontológica. La unión entre pared y piso debe ser en media caña (sin aristas). Verificar visualmente durante el recorrido.
A22: 6 | B22: Accesibilidad (ascensor / rampa) | C22: 🟡 ATENCIÓN | D22: Si el consultorio está en 2° o 3° piso, es obligatorio contar con ascensor, rampa o sistema alternativo de elevación (incluso para prestadores pequeños). Verificar el tipo de sistema y sus condiciones. Aplica para los inscritos despues de el 25 noviembre 2019 (resolucion 544)
A23: 7 | B23: Edificación mixta — infraestructura | C23: 🟢 OPORTUNIDAD | D23: La norma permite edificios mixtos (consultorio en edificio residencial/comercial). Cada prestador debe tener área delimitada físicamente. Pueden compartir: sala de espera y unidades sanitarias.
A24: 8 | B24: Señalización rutas de evacuación | C24: 🟡 ATENCIÓN | D24: Cada piso debe tener planos y señalización de rutas de evacuación, salidas de emergencia y puntos de encuentro, visibles al público. Es un criterio frecuentemente olvidado en consultorios pequeños.
A26: DOTACIÓN
A27: # | B27: ASPECTO | C27: RIESGO | D27: RECOMENDACIÓN PRÁCTICA
A28: 1 | B28: Hoja de vida de equipos | C28: 🟡 ATENCIÓN | D28: Cada equipo biomédico — incluidos tensiómetros, fonendos y báscula — debe tener hoja de vida con registro de mantenimientos. Error frecuente: omitir equipos de bajo costo pensando que no aplica.
A29: 2 | B29: Calibración y mantenimiento | C29: 🔴 CRÍTICO | D29: Los equipos que miden variables fisiológicas (tensiómetros, glucómetros, balanzas) deben tener certificado de calibración vigente. Verificar fechas. El mantenimiento puede ser del fabricante o de técnico contratado.
A30: 3 | B30: Programa de mantenimiento preventivo | C30: 🟡 ATENCIÓN | D30: Puede ser un cronograma anual simple, pero debe existir. Incluir las recomendaciones del fabricante para cada equipo. El mantenimiento correctivo también debe registrarse.
A31: 4 | B31: Suficiencia de dotación | C31: 🟢 OPORTUNIDAD | D31: La norma NO exige número mínimo de equipos — exige que la dotación sea suficiente para la demanda del servicio. El prestador debe documentar su análisis de suficiencia según carga asistencial.
A32: 5 | B32: No adaptar DM en extramural | C32: 🔴 CRÍTICO | D32: En modalidad extramural está PROHIBIDO adaptar o fabricar dispositivos médicos sobre medida. Solo se pueden usar equipos con registro sanitario INVIMA vigente.
A33: 6 | B33: Equipos telemedicina: certificación | C33: 🟡 ATENCIÓN | D33: Los equipos de captura y transmisión de información deben estar certificados por ingeniero biomédico y/o de sistemas. Las pantallas para diagnóstico deben cumplir especificaciones técnicas de dot pitch y resolución.
A35: MEDICAMENTOS, DM E INSUMOS
A36: # | B36: ASPECTO | C36: RIESGO | D36: RECOMENDACIÓN PRÁCTICA
A37: 1 | B37: Registro INVIMA vigente | C37: 🔴 CRÍTICO | D37: Todos los medicamentos y dispositivos médicos deben tener registro sanitario INVIMA vigente. Verificar en vía.invima.gov.co en el momento de la visita. Las fechas de vencimiento físicas también deben estar visibles y controladas.
A38: 2 | B38: Cadena de frío | C38: 🔴 CRÍTICO | D38: Si maneja insulinas, vacunas, biológicos o reactivos termolábiles: la cadena de frío es obligatoria. Debe tener nevera, termómetro calibrado y registro DIARIO de temperatura documentado.
A39: 3 | B39: Kit de derrames | C39: 🟡 ATENCIÓN | D39: Obligatorio para todo prestador que maneje medicamentos. Debe estar señalizado, accesible y documentado. El prestador define su contenido según los medicamentos que usa y las fichas técnicas del fabricante.
A40: 4 | B40: Farmacovigilancia / Tecnovigilancia | C40: 🟡 ATENCIÓN | D40: El profesional independiente que dispensa o administra medicamentos debe estar inscrito en el programa de Farmacovigilancia del INVIMA. Es uno de los criterios más frecuentemente incumplidos en independientes.
A41: 5 | B41: Control de cadena de frío en extramural | C41: 🟠 VIGILAR | D41: En modalidad domiciliaria y extramural, los medicamentos e insumos deben mantenerse en condiciones apropiadas durante el transporte. Documentar el procedimiento de manejo de temperatura en extramural.
A42: 6 | B42: Relaciones de insumos actualizadas | C42: 🟢 OPORTUNIDAD | D42: Las relaciones de medicamentos, DM y reactivos deben estar actualizadas. Mantenerlas en formato digital facilita la actualización y la presentación durante la auditoría.
A44: PROCESOS PRIORITARIOS
A45: # | B45: ASPECTO | C45: RIESGO | D45: RECOMENDACIÓN PRÁCTICA
A46: 1 | B46: Política de seguridad del paciente | C46: 🔴 CRÍTICO | D46: Es el documento estratégico más importante. Para el profesional independiente debe existir, estar firmado, fechado y socializado. La norma permite que el mismo prestador sea el comité.
A47: 2 | B47: Consentimiento informado funcional | C47: 🔴 CRÍTICO | D47: Debe existir un formato por tipo de procedimiento, firmado por el paciente o su acudiente ANTES del procedimiento, y conservado en la historia clínica. Verificar que el proceso sea real, no solo documental.
A48: 3 | B48: Protocolo de higiene de manos | C48: 🔴 CRÍTICO | D48: Debe estar visible en el consultorio. Verificar que haya jabón, agua, toallas/papel desechable y/o gel de alcohol. Es un criterio de inspección visual directa — se verifica en el momento del recorrido.
A49: 4 | B49: Violencias sexuales — independiente | C49: 🔴 CRÍTICO | D49: La norma exige EXPLÍCITAMENTE que el Profesional Independiente de CE cuente con el documento del proceso para atención de víctimas de violencias sexuales. Es un criterio diferencial específico del independiente.
A50: 5 | B50: Guías de práctica clínica | C50: 🟡 ATENCIÓN | D50: Priorizar GPC del MinSalud. Si no existen para la especialidad: GPC de sociedades científicas nacionales o internacionales. Documentar la selección realizada. Mínimo una GPC por patología más frecuente del servicio.
A51: 6 | B51: Referencia y contrarreferencia | C51: 🟡 ATENCIÓN | D51: Debe haber un protocolo escrito. Para el profesional independiente puede ser básico: a dónde refiere, cómo documenta la referencia, cómo hace seguimiento. Incluir datos de la red de referencia local.
A52: 7 | B52: Pruebas POCT — inscripción RELAB | C52: 🟠 VIGILAR | D52: Si realiza pruebas rápidas (glucometría, prueba de embarazo, hemoglobina, etc.) debe inscribirse en RELAB y tener documentado el proceso de control de calidad. Verificar inscripción en línea.
A53: 8 | B53: Bioseguridad específica del servicio | C53: 🟡 ATENCIÓN | D53: El protocolo de bioseguridad debe ser específico para el tipo de servicio. Para CE puede ser una página; para laboratorio clínico debe ser detallado incluyendo manejo de residuos biológicos peligrosos.
A54: 9 | B54: Sedación — información documentada | C54: 🟠 VIGILAR | D54: Si realiza procedimientos bajo sedación fuera de salas de cirugía: debe haber información documentada para realizar la sedación, manejo de emergencias, lista de chequeo en HC y recomendaciones de egreso al acompañante.
A56: HISTORIA CLÍNICA Y REGISTROS
A57: # | B57: ASPECTO | C57: RIESGO | D57: RECOMENDACIÓN PRÁCTICA
A58: 1 | B58: Apertura obligatoria en primera atención | C58: 🔴 CRÍTICO | D58: Toda primera atención debe generar apertura de historia clínica. Verificar que no se atienden pacientes sin HC. El auditor puede solicitar al azar la HC de pacientes recientes.
A59: 2 | B59: HC digital: requisitos legales | C59: 🔴 CRÍTICO | D59: Si usa software de HC digital: debe tener contrato de licencia vigente, backup automático, y el sistema no debe permitir modificar registros guardados. Requiere certificado de ingeniero de sistemas.
A60: 3 | B60: Consentimiento informado en HC | C60: 🔴 CRÍTICO | D60: La norma exige que el CI esté incorporado al proceso de HC. Verificar que los formatos firmados estén archivados junto a la HC correspondiente de cada paciente.
A61: 4 | B61: Legibilidad de HC física | C61: 🟡 ATENCIÓN | D61: Las HC físicas deben ser legibles, sin tachones, sin corrector, con fecha, hora y firma en CADA anotación. En visitas de campo, este es el hallazgo más frecuente en todos los servicios.
A62: 5 | B62: Custodia y archivo de HC | C62: 🟡 ATENCIÓN | D62: Las HC deben conservarse mínimo 15 años desde la última atención (Res. 1995/99). Verificar condiciones: sin humedad, sin plagas, sin acceso de terceros no autorizados, con mecanismo de registro de préstamos.
A63: 6 | B63: HC en telemedicina — certificación especial | C63: 🟠 VIGILAR | D63: Requiere certificación de ingeniero de sistemas que avale: custodia, compresión sin pérdidas, firma electrónica, encriptación y sistemas de control de acceso. Es un requisito técnico complejo pero obligatorio.
A64: 7 | B64: HC en extramural domiciliario | C64: 🟠 VIGILAR | D64: La HC del servicio domiciliario es custodiada por el prestador (no queda en el domicilio del paciente). Debe incluir: valoración de ingreso, plan de tratamiento, cuidados del personal y cuidados encargados a la familia.

Sheet Diferencias entre Servicios
A1: 🔍 DIFERENCIAS ENTRE SERVICIOS Y PUNTOS CRÍTICOS POR SERVICIO HABILITADO
A2: Resolución 3100 de 2019 | Comparación de exigencias por tipo de servicio | Profesional Independiente | Audisalud Colombia S.A.S.
A4: 1. COMPARATIVA DE EXIGENCIAS POR SERVICIO HABILITADO
A5: # | B5: ASPECTO / CRITERIO | C5: CE General | D5: CE Especializada | E5: Terapias | F5: Lab Clínico | G5: Toma Muestras
A6: 1 | B6: PROFESIONAL HABILITANTE | C6: Médico/Enf/Nut/Psic/u otro | D6: Especialista (MEN) | E6: Fisio/Fono/TO/TR | F6: Bacteriólogo | G6: Bacteriólogo o auxiliar
A7: 2 | B7: COMPLEJIDAD EXIGIDA | C7: Baja | D7: Mediana | E7: ❌ | F7: ❌ | G7: ❌
A8: 3 | B8: Consultorio examen físico ≥10 m² | C8: ✅ | D8: ✅ | E8: ❌ | F8: ❌ | G8: ❌
A9: 4 | B9: Barrera física entre áreas | C9: ✅ | D9: ✅ | E9: ⚙️ Cond. | F9: ❌ | G9: ❌
A10: 5 | B10: Área de procedimientos separada | C10: ⚙️ Cond. | D10: ⚙️ Cond. | E10: ❌ | F10: ❌ | G10: ❌
A11: 6 | B11: Ambiente técnico de procesamiento | C11: ❌ | D11: ❌ | E11: ❌ | F11: ✅ | G11: ❌
A12: 7 | B12: Cubículo específico toma de muestras | C12: ❌ | D12: ❌ | E12: ❌ | F12: ⚙️ Cond. | G12: ✅
A13: 8 | B13: Ducha/lavaojos en área técnica | C13: ❌ | D13: ❌ | E13: ❌ | F13: ✅ | G13: ❌
A14: 9 | B14: Área hidroterapia o húmeda | C14: ❌ | D14: ❌ | E14: ⚙️ Cond. | F14: ❌ | G14: ❌
A15: 10 | B15: Cabina sono-amortiguada / audiometría | C15: ❌ | D15: ❌ | E15: ⚙️ Cond. | F15: ❌ | G15: ❌
A16: 11 | B16: Camilla fija + escalerilla | C16: ✅ | D16: ✅ | E16: ⚙️ Cond. | F16: ❌ | G16: ❌
... A35: 30 | B35: Inscripción RELAB (pruebas ISP) | C35: ⚙️ Cond. | D35: ⚙️ Cond. | E35: ❌ | F35: ✅ | G35: ❌
A37: LEYENDA: | C37: ✅ Aplica siempre | D37: ❌ No aplica / No exigido | E37: ⚙️ Cond. Condicional
A39: 2. PUNTOS CRÍTICOS POR SERVICIO — LO QUE NO PUEDE FALTAR EN NINGUNA VISITA
A40: ⚠️ CE GENERAL — Baja Complejidad
B41: NIVEL | C41: PUNTO CRÍTICO
A42: 1 | B42: ⚠️ CRÍTICO | C42: Tarjeta profesional VIGENTE del profesional — verificar en ReTHUS en tiempo real
A43: 2 | B43: ⚠️ CRÍTICO | C43: Concepto sanitario vigente — emitido por la Secretaría de Salud
A44: 3 | B44: ⚠️ CRÍTICO | C44: Certificado RETIE vigente — emitido por ingeniero eléctrico matriculado
A45: 4 | B45: ⚠️ CRÍTICO | C45: Protocolo de higiene de manos documentado, visible y con insumos disponibles
A46: 5 | B46: ⚠️ CRÍTICO | C46: Consentimiento informado firmado, funcional y archivado en HC
A47: 6 | B47: ⚠️ CRÍTICO | C47: Historia clínica con componentes mínimos de la Resolución 1995/99
A48: 7 | B48: ⚠️ CRÍTICO | C48: Documento para atención de víctimas de violencias sexuales (criterio específico del independiente)
A49: 8 | B49: ⚠️ CRÍTICO | C49: Programa de seguridad del paciente — puede ser el mismo prestador en el caso del independiente
A50: 9 | B50: Importante | C50: Consultorio con examen físico: mínimo 10 m² con áreas separadas por barrera física
A51: 10 | B51: Importante | C51: Tensiómetro y fonendoscopio disponibles y con mantenimiento / calibración
A52: 11 | B52: Importante | C52: Sala de espera disponible con unidades sanitarias accesibles
A53: 12 | B53: Condicional | C53: Para ERA: sala señalizada + protocolo de tiempos y condiciones de manejo documentado
A55: ⚠️ CE ESPECIALIZADA — Mediana Complejidad
B56: NIVEL | C56: PUNTO CRÍTICO
A57: 1 | B57: ⚠️ CRÍTICO | C57: Título de ESPECIALISTA reconocido— sin este título no puede habilitar CE especializada
A58: 2 | B58: ⚠️ CRÍTICO | C58: Para medicina/terapias alternativas: certificación académica de la especialidad expedida reconocida
A59: 3 | B59: ⚠️ CRÍTICO | C59: TODOS los criterios de CE General aplican como base — no son opcionales
A60: 4 | B60: Importante | C60: Dotación específica para los procedimientos de la especialidad documentada en Procesos Prioritarios
A61: 5 | B61: Importante | C61: GPC adoptadas / adaptadas / desarrolladas para las patologías más frecuentes de la especialidad
A62: 6 | B62: Importante | C62: Información al paciente sobre preparación, complicaciones y controles post-procedimiento
A63: 7 | B63: Condicional | C63: Ginecoobstetricia y urología: unidad sanitaria DENTRO del consultorio
A64: 8 | B64: Condicional | C64: Para med. alternativa: criterios explícitos sobre qué procedimientos se pueden y no se pueden realizar
A66: ⚠️ TERAPIAS — Física, Ocupacional, Lenguaje, Respiratoria
B67: NIVEL | C67: PUNTO CRÍTICO
A68: 1 | B68: ⚠️ CRÍTICO | C68: Título en el ámbito de la rehabilitación — fisioterapia, fonoaudiología, TO o TR
A69: 2 | B69: ⚠️ CRÍTICO | C69: Tarjeta profesional vigente y ReTHUS actualizado
A70: 3 | B70: ⚠️ CRÍTICO | C70: Dotación para los procedimientos documentada en PP — es la forma de acreditar suficiencia
A71: 4 | B71: Importante | C71: Procedimientos documentados con áreas, equipos, DM e insumos requeridos para cada tipo de terapia
A72: 5 | B72: Importante | C72: Área con barrera física fija o móvil cuando la terapia requiere privacidad para el paciente
A73: 6 | B73: Condicional | C73: Si oferta integración neurosensorial: constancia de formación continua OBLIGATORIA
A74: 7 | B74: Condicional | C74: Fonoaudiología: área de sillas y mesas de trabajo individual y grupal según oferta
A75: 8 | B75: Condicional | C75: Si oferta audiometría: cabina sono-amortiguada o equipo de audiometría disponible
A76: 9 | B76: Condicional | C76: Si oferta hidroterapia: pisos antideslizantes y tomas eléctricas con protección para ambientes húmedos
A78: ⚠️ LABORATORIO CLÍNICO — Baja Complejidad (Sec. 11.3.12)
B79: NIVEL | C79: PUNTO CRÍTICO
A80: 1 | B80: ⚠️ CRÍTICO | C80: Profesional de bacteriología con tarjeta profesional vigente — exigencia ABSOLUTA
A81: 2 | B81: ⚠️ CRÍTICO | C81: Ambiente técnico de procesamiento completo: mesón, lavaojos/ducha manual, área neveras, lavamanos
A82: 3 | B82: ⚠️ CRÍTICO | C82: Área de recepción de muestras e información separada del área técnica
A83: 4 | B83: ⚠️ CRÍTICO | C83: Reactivos con registro sanitario INVIMA vigente — verificar fechas de vencimiento
A84: 5 | B84: ⚠️ CRÍTICO | C84: Programa de control de calidad interno Y participación en PEEC (evaluación externa de calidad)
A85: 6 | B85: ⚠️ CRÍTICO | C85: Registro de pacientes y resultados firmados por el bacteriólogo responsable
A86: 7 | B86: Importante | C86: Nevera o refrigeración con termómetro calibrado para conservación de muestras y reactivos
A87: 8 | B87: Importante | C87: Validación secundaria o verificación documentada
A88: 9 | B88: Importante | C88: Unión pared-piso en media caña en el área de procesamiento
A89: 10 | B89: Condicional | C89: Si recibe biopsias o material citológico: contrato con servicio de patología
A90: 11 | B90: Condicional | C90: Si procesa bacterias anaerobias o técnicas de biología molecular: cabina de bioseguridad
A91: 12 | B91: Condicional | C91: Si realiza pruebas de interés en salud pública: inscripción en RELAB obligatoria
A93: ⚠️ TOMA DE MUESTRAS DE LABORATORIO CLÍNICO (Sec. 11.3.11)
B94: NIVEL | C94: PUNTO CRÍTICO
A95: 1 | B95: ⚠️ CRÍTICO | C95: Profesional de bacteriología, auxiliar de laboratorio o auxiliar de enfermería habilitado
A96: 2 | B96: ⚠️ CRÍTICO | C96: Bacteriólogo disponible para supervisión cuando la toma la realiza el auxiliar — esto es obligatorio
A97: 3 | B97: ⚠️ CRÍTICO | C97: Cubículo específico para toma de muestras
A98: 4 | B98: ⚠️ CRÍTICO | C98: Área de preparación, embalaje y remisión con mesón de trabajo
A99: 5 | B99: ⚠️ CRÍTICO | C99: Lavamanos disponible en el área de toma de muestras
A100: 6 | B100: ⚠️ CRÍTICO | C100: Protocolo documentado de toma, identificación, transporte, conservación y remisión de muestras
A101: 7 | B101: ⚠️ CRÍTICO | C101: Registro de pacientes, muestras tomadas, exámenes solicitados y muestras remitidas
A102: 8 | B102: ⚠️ CRÍTICO | C102: Interdependencia documentada con servicio de laboratorio clínico (propio o contratado)
A103: 9 | B103: Importante | C103: Contrato con laboratorio de referencia para el procesamiento de muestras
A104: 10 | B104: Condicional | C104: Contrato con servicio de patología cuando se recepcionen biopsias o material citológico
A105: 11 | B105: Condicional | C105: Procedimiento y condiciones para toma de muestras en modalidad extramural cuando se realicen

Sheet Ficha Prestador
A1: FICHA TÉCNICA DEL PRESTADOR DE SERVICIOS DE SALUD
A2: Resolución 3100 de 2019 — Habilitación de Servicios de Salud — Profesionales Independientes
A3: 1. DATOS BÁSICOS DEL PRESTADOR
A4: Nombre y apellido | E4: Cédula:
A5: Código REPS: | E5: Código de Habilitación:
A6: Dirección: | E6: Municipio / Departamento:
A7: Teléfono: | E7: Correo electrónico:
A8: Representante Legal: | E8: Tipo de prestador:
A9: Profesión: | E9: N°. Tarjeta Profesional:
A10: Naturaleza jurídica: | E10: Complejidad:
A12: 2. INFORMACIÓN DE HABILITACIÓN
A13: Servicios habilitados:
A14: Modalidad de prestación: | E14: Horario de atención:
A15: Fecha de habilitación: | E15: Fecha vencimiento:
A16: Sede: | E16: N° de sede:
A17: Estado actual REPS: | E17: Fecha última actualización:
A19: 3. INFORMACIÓN DE LA AUDITORÍA
A20: Tipo de auditoría: | E20: Fecha de auditoría:
A21: Hora inicio: | E21: Hora finalización:
A22: Nombre del auditor: | E22: Cargo:
A23: Profesión del auditor: | E23: N°. Tarjeta profesional:
A24: Entidad contratante: | E24: Objeto de la auditoría:
A25: Hallazgos previos:
A26: Plan de mejora vigente:
A27: Fecha próxima visita: | E27: Responsable seguimiento:
A29: 4. CONTROL DE DOCUMENTOS Y VENCIMIENTOS
A30: N° | B30: DOCUMENTO | C30: FECHA VENCIMIENTO | D30: DÍAS RESTANTES | E30: ESTADO
A31: 1 | B31: Licencia de construcción / Uso de suelos | D31: =IF(C31="","",C31-TODAY()) | E31: =IF(C31="","Sin fecha registrada",IF(D31<0,"VENCIDO",IF(D31<30,"PROXIMO A VENCER",IF(D31<90,"ATENCION","VIGENTE")))) -> Sin fecha registrada
A32: 2 | B32: Certificado de Bomberos | D32: =IF(C32="","",C32-TODAY()) | E32: =IF(C32="","Sin fecha registrada",IF(D32<0,"VENCIDO",IF(D32<30,"PROXIMO A VENCER",IF(D32<90,"ATENCION","VIGENTE")))) -> Sin fecha registrada
A33: 3 | B33: Certificado RETIE (Ingeniero eléctrico) | D33: =IF(C33="","",C33-TODAY()) | E33: =IF(C33="","Sin fecha registrada",IF(D33<0,"VENCIDO",IF(D33<30,"PROXIMO A VENCER",IF(D33<90,"ATENCION","VIGENTE")))) -> Sin fecha registrada
A34: 4 | B34: Concepto sanitario (Salud Pública) | D34: =IF(C34="","",C34-TODAY()) | E34: =IF(C34="","Sin fecha registrada",IF(D34<0,"VENCIDO",IF(D34<30,"PROXIMO A VENCER",IF(D34<90,"ATENCION","VIGENTE")))) -> Sin fecha registrada
A35: 5 | B35: Habilitación vigente REPS | D35: =IF(C35="","",C35-TODAY()) | E35: =IF(C35="","Sin fecha registrada",IF(D35<0,"VENCIDO",IF(D35<30,"PROXIMO A VENCER",IF(D35<90,"ATENCION","VIGENTE")))) -> Sin fecha registrada
A36: 6 | B36: Seguro de responsabilidad civil profesional | D36: =IF(C36="","",C36-TODAY()) | E36: =IF(C36="","Sin fecha registrada",IF(D36<0,"VENCIDO",IF(D36<30,"PROXIMO A VENCER",IF(D36<90,"ATENCION","VIGENTE")))) -> Sin fecha registrada
A37: 7 | B37: Plan de gestión integral de residuos (PGIRHS) | D37: =IF(C37="","",C37-TODAY()) | E37: =IF(C37="","Sin fecha registrada",IF(D37<0,"VENCIDO",IF(D37<30,"PROXIMO A VENCER",IF(D37<90,"ATENCION","VIGENTE")))) -> Sin fecha registrada
A38: 8 | B38: Certificado de fumigación | D38: =IF(C38="","",C38-TODAY()) | E38: =IF(C38="","Sin fecha registrada",IF(D38<0,"VENCIDO",IF(D38<30,"PROXIMO A VENCER",IF(D38<90,"ATENCION","VIGENTE")))) -> Sin fecha registrada
A39: 9 | B39: Certificado lavado de tanques de agua | D39: =IF(C39="","",C39-TODAY()) | E39: =IF(C39="","Sin fecha registrada",IF(D39<0,"VENCIDO",IF(D39<30,"PROXIMO A VENCER",IF(D39<90,"ATENCION","VIGENTE")))) -> Sin fecha registrada
A40: 10 | B40: Licencia práctica radiológica (si aplica) | D40: =IF(C40="","",C40-TODAY()) | E40: =IF(C40="","Sin fecha registrada",IF(D40<0,"VENCIDO",IF(D40<30,"PROXIMO A VENCER",IF(D40<90,"ATENCION","VIGENTE")))) -> Sin fecha registrada
A41: 11 | B41: Tarjeta profesional del prestador | D41: =IF(C41="","",C41-TODAY()) | E41: =IF(C41="","Sin fecha registrada",IF(D41<0,"VENCIDO",IF(D41<30,"PROXIMO A VENCER",IF(D41<90,"ATENCION","VIGENTE")))) -> Sin fecha registrada
A42: 12 | B42: Inscripción Farmacovigilancia / Tecnovigilancia | D42: =IF(C42="","",C42-TODAY()) | E42: =IF(C42="","Sin fecha registrada",IF(D42<0,"VENCIDO",IF(D42<30,"PROXIMO A VENCER",IF(D42<90,"ATENCION","VIGENTE")))) -> Sin fecha registrada

Sheet Criterios Generales
A1: CRITERIOS GENERALES APLICABLES AL PROFESIONAL INDEPENDIENTE DE SALUD
A2: Resolución 3100 de 2019 | Secciones 11.1.1 a 11.1.7 | Filtrado: Excluye servicios hospitalarios, urgencias, cirugía mayor, UCI, parto y transfusional
A3: PRESTADOR: | I3: FECHA:
A4: LEYENDA: ⚠️ = Crítico | ★ = Criterio explícito para Profesional Independiente en la norma | C = Condicional (cuando aplique según servicios ofertados) | G = General (aplica a todos) | Fila GRIS = No aplica a independiente (excluido del instrumento)
A5: ⚠️ Los criterios marcados son CRÍTICOS. Su incumplimiento puede generar requerimiento o cierre del servicio. Los criterios en fondo amarillo son de marcación crítica directa en la Resolución 3100/2019.
A6: N° | B6: N° REF | C6: ESTÁNDAR | D6: CRITERIO — SOLO APLICABLE A PROFESIONAL INDEPENDIENTE | E6: MODO VERIFICACIÓN | F6: ⚠️ | G6: C | H6: NC | I6: NA | J6: HALLAZGO / EVIDENCIA | K6: PLAN DE MEJORA | L6: RESPONSABLE | M6: FECHA COMPROMISO
A7: ESTÁNDAR DE TALENTO HUMANO — Sección 11.1.1 | Todas las modalidades
A8: 1 | B8: 1 | C8: TALENTO HUMANO | D8: El talento humano en salud y otros profesionales que se relacionan con la atención cuentan con los títulos de educación superior o certificados de aptitud ocupacional expedidos por la entidad educativa competente. En el caso de títulos obtenidos en el extranjero: copia de la resolución de convalidación expedida por el MEN | E8: Inspección Documental | F8: ⚠️ | G8: X
A9: 2 | B9: 2 | C9: TALENTO HUMANO | D9: El talento humano en salud cuenta con copia de la resolución de autorización del ejercicio expedida por la autoridad competente o inscripción en el Registro Único Nacional de Talento Humano en Salud — ReTHUS | E9: Inspección Documental | F9: ⚠️
A10: ⊘ EXCLUIDO [3 ⚠️ EXCLUIDO] — CRITERIO NO APLICA PARA PROFESIONAL INDEPENDIENTE: Criterio 3 sobre determinación de cantidad de talento humano requerido — la norma establece explícitamente que no aplica para el profesional independiente
A11: 3 | B11: 4 | C11: TALENTO HUMANO | D11: Cuando el prestador actúe como escenario de práctica formativa cuenta con: convenio vigente con institución educativa autorizada, información documentada de mecanismos de supervisión permanente del personal en entrenamiento y estudio de capacidad instalada que determine el número máximo de estudiantes según los lineamientos del MinSalud | E11: Inspección Documental
A12: 4 | B12: 5 | C12: TALENTO HUMANO | D12: En los servicios donde se atienden pacientes con enfermedades terminales, crónicas, degenerativas e irreversibles con conducta médica de manejo del dolor y cuidado paliativo: el profesional de la medicina tratante cuenta con constancia de formación continua en manejo del dolor y cuidado paliativo, cuando no sea especialista en la materia | E12: Inspección Documental
A13: 5 | B13: 10 | C13: TALENTO HUMANO | D13: El talento humano en salud de los servicios de CE, internación y urgencias cuenta con constancia de formación continua en atención integral en salud de personas víctimas de violencia sexual | E13: Inspección Documental
A14: 6 | B14: 12 | C14: TALENTO HUMANO | D14: Cuando en un servicio se realicen pruebas en el punto de atención del paciente (POCT): el talento humano que las realice, con excepción del profesional de bacteriología, cuenta con constancia de formación continua en el manejo de estas pruebas | E14: Inspección Documental
A15: 7 | B15: 13 – Sedación | C15: TALENTO HUMANO | D15: Cuando se realicen procedimientos bajo sedación Grado I y II fuera de salas de cirugía: adicional al profesional que realiza el procedimiento, cuenta con: profesional de medicina especialista en anestesiología o profesional de medicina/odontología encargado de administrar el medicamento y monitoreo continuo; todos con constancia de formación en soporte vital básico y sedación (excepto anestesiólogo) | E15: Inspección Documental
A16: 8 | B16: 13 – Sedación III | C16: TALENTO HUMANO | D16: Cuando fuera de salas de cirugía se realicen procedimientos bajo sedación Grado III: profesional de medicina con especialidad médico-quirúrgica responsable de administrar la sedación | E16: Inspección Documental
A17: 9 | B17: 13 – Sedación IV | C17: TALENTO HUMANO | D17: Cuando fuera de salas de cirugía se realicen procedimientos bajo sedación Grado IV: profesional de medicina especialista en anestesiología responsable de administrar la sedación | E17: Inspección Documental
A18: ▸ Modalidad Telemedicina — Prestador Remisor y Prestador de Referencia
A19: 10 | B19: 14 | C19: TALENTO HUMANO – Telemedicina | D19: El talento humano que presta directamente servicios bajo la modalidad de telemedicina cuenta con constancia de formación continua en el manejo de la tecnología utilizada, los procesos y herramientas inherentes a la prestación bajo esta modalidad | E19: Inspección Documental | F19: ⚠️
A20: ESTÁNDAR DE INFRAESTRUCTURA — Sección 11.1.2
A21: ▸ Edificaciones de Uso Mixto — Aplica para profesional independiente en consultorio compartido
A22: 11 | B22: 6 | C22: INFRAESTRUCTURA – Uso Mixto | D22: Cuando en una edificación de uso mixto funcionen varios prestadores de servicios de salud, cada uno cuenta con infraestructura separada y delimitada físicamente. Se pueden compartir salas de espera y unidades sanitarias | E22: Inspección Visual | F22: ⚠️
A23: 12 | B23: 7 | C23: INFRAESTRUCTURA – Uso Mixto | D23: En edificaciones de uso mixto pueden funcionar prestadores que oferten servicios de los grupos de consulta externa, apoyo diagnóstico y complementación terapéutica y cirugía ambulatoria | E23: Inspección Visual
A24: 13 | B24: 3 | C24: INFRAESTRUCTURA – Uso Exclusivo Salud | D24: Cuando en una edificación de uso exclusivo de salud funcionen varios prestadores con CE y apoyo diagnóstico, cada prestador cuenta con infraestructura separada y delimitada físicamente. Pueden compartir: aseo, salas de espera y unidades sanitarias | E24: Inspección Visual
A25: ▸ Accesibilidad — Aplica para todos
A26: 14 | B26: 8 | C26: INFRAESTRUCTURA – Accesibilidad | D26: Prestadores ubicados en edificaciones hasta 3 pisos que funcionen en 2° o 3° nivel cuentan con ascensor, rampa o sistema alternativo de elevación (el sistema alternativo no aplica para servicios hospitalarios, cirugía, urgencias, parto — estos no aplican a profesional independiente) | E26: Inspección Visual | F26: ⚠️
A27: 15 | B27: 9.1 a 9.4 | C27: INFRAESTRUCTURA – Accesibilidad | D27: Sistemas alternativos de elevación: su ubicación no interfiere con la evacuación, disponibles para acceso y evacuación, manejo autónomo y garantizan seguridad durante su uso | E27: Inspección Visual
A28: 16 | B28: 10 | C28: INFRAESTRUCTURA – Accesibilidad | D28: Las edificaciones con más de 3 pisos cuentan con ascensor | E28: Inspección Visual | F28: ⚠️
A29: 17 | B29: 12 | C29: INFRAESTRUCTURA – Accesibilidad | D29: Si se tienen escaleras o rampas: piso uniforme, antideslizante, pasamanos a uno o ambos lados y protecciones laterales hacia espacios libres | E29: Inspección Visual
A30: ▸ Servicios Básicos y Concepto Sanitario
A31: 18 | B31: 13 | C31: INFRAESTRUCTURA – Servicios Básicos | D31: Las edificaciones donde se presten servicios de salud cuentan con suministro de agua, energía eléctrica, conexión a la red de alcantarillado y sistemas de comunicaciones | E31: Inspección Visual | F31: ⚠️
A32: 19 | B32: 15 | C32: INFRAESTRUCTURA – Servicios Básicos | D32: Cuando se utilicen equipos generadores de radiaciones ionizantes: licencia de práctica médica vigente expedida por la entidad competente | E32: Inspección Documental | F32: ⚠️
A33: ⊘ NO APLICA PARA PROFESIONAL INDEPENDIENTE — [16] Fuentes radioactivas: aplica exclusivamente a medicina nuclear e imágenes diagnósticas con isótopos. No es aplicable al perfil de profesional independiente en CE y apoyo diagnóstico.
A34: 21 | B34: 17 | C34: INFRAESTRUCTURA – Servicios Básicos | D34: Concepto sanitario vigente que dé cumplimiento a la normatividad sanitaria: agua para consumo humano, gestión de residuos, control de vectores, orden y aseo, condiciones locativas, entre otros | E34: Inspección Documental | F34: ⚠️
A35: ▸ Generalidades de Ambientes y Áreas — Aplica para profesional independiente
A36: 22 | B36: 18 | C36: INFRAESTRUCTURA – Generalidades | D36: Las áreas y ambientes de todos los servicios cuentan con ventilación e iluminación natural o artificial | E36: Inspección Visual | F36: ⚠️
A37: 23 | B37: 19 | C37: INFRAESTRUCTURA – Generalidades | D37: Las áreas de circulación están libres de obstáculos que permitan la movilización de pacientes, talento humano, usuarios y equipos biomédicos | E37: Inspección Visual | F37: ⚠️
A38: 24 | B38: 20 | C38: INFRAESTRUCTURA – Generalidades | D38: Los ambientes y áreas permiten la instalación y movilización de equipos biomédicos y personal para la atención del paciente en condiciones de rutina o emergencia | E38: Inspección Visual
A39: 25 | B39: 22 | C39: INFRAESTRUCTURA – Generalidades | D39: Cada piso o nivel cuenta con señalización y planos indicativos de rutas de evacuación, salidas de emergencia y puntos de encuentro, visibles al público | E39: Inspección Visual | F39: ⚠️
A40: 26 | B40: 24 | C40: INFRAESTRUCTURA – Generalidades | D40: Cuando se realicen procedimientos bajo sedación fuera de salas de cirugía: disponibilidad de área o ambiente para recuperación del paciente garantizando privacidad del usuario | E40: Inspección Visual
A41: ▸ Características de Ambientes y Áreas — Los más relevantes para profesional independiente
A42: 27 | B42: 28.1 | C42: INFRAESTRUCTURA – Consultorios | D42: Consultorio donde se realiza examen físico: mínimo 10 m² (sin incluir la unidad sanitaria) con área de entrevista, área de examen, lavamanos; áreas separadas por barrera física fija o móvil (excepto urgencias, optometría y oftalmología) | E42: Inspección Visual | F42: ⚠️
A43: 28 | B43: 28.2 | C43: INFRAESTRUCTURA – Consultorios | D43: Consultorio donde se realizan procedimientos: mínimo 10 m², área de entrevista, área de procedimientos separadas por barrera física fija, mesón de trabajo, poceta (cuando la requiera según PP), lavamanos | E43: Inspección Visual | F43: ⚠️
A44: 29 | B44: 28.3 | C44: INFRAESTRUCTURA – Consultorios | D44: Consultorio odontológico con una unidad odontológica: mínimo 10 m², área para entrevista (si la requiere), área para unidad, lavamanos, área con mesón de trabajo con poceta | E44: Inspección Visual
A45: 30 | B45: 29 | C45: INFRAESTRUCTURA – Consultorios | D45: Consultorio donde se realiza únicamente entrevista, sin examen físico ni procedimientos: mínimo 4 m², área para entrevista y lavamanos (no se exige adicional si cuenta con unidad sanitaria) | E45: Inspección Visual
A46: 31 | B46: 30.1 | C46: INFRAESTRUCTURA – Salas | D46: Sala de procedimientos / curaciones: mínimo 8 m², mesón de trabajo, poceta (cuando la requiera según PP) y lavamanos | E46: Inspección Visual
A47: 32 | B47: 31 | C47: INFRAESTRUCTURA – Salas | D47: Sistema de alarma cuando se cuente con red de distribución de gases medicinales | E47: Inspección Visual
A48: 33 | B48: 37 | C48: INFRAESTRUCTURA – Unidades Sanitarias | D48: Unidad sanitaria: sanitario y lavamanos | E48: Inspección Visual | F48: ⚠️
A49: 34 | B49: 38 | C49: INFRAESTRUCTURA – Unidades Sanitarias | D49: Unidad sanitaria adaptada para personas con movilidad reducida: sanitario, lavamanos, dimensiones para silla de ruedas, puertas corredizas o con apertura hacia el exterior, accesorios de accesibilidad, alarma o sistema de llamado | E49: Inspección Visual | F49: ⚠️
A50: 35 | B50: 40 | C50: INFRAESTRUCTURA – Sala de Espera | D50: Sala de espera: área variable, independiente de áreas de circulación, con ventilación e iluminación natural/artificial; disponibilidad de unidades sanitarias discriminadas por sexo o baterías sanitarias | E50: Inspección Visual
A51: ▸ Condiciones de Orden, Aseo, Limpieza y Desinfección
A52: 36 | B52: 41 | C52: INFRAESTRUCTURA – Aseo y Limpieza | D52: Las condiciones de orden, aseo, limpieza y desinfección son evidentes y responden a un proceso dinámico de acuerdo con los servicios prestados | E52: Inspección Visual | F52: ⚠️
A53: 37 | B53: 42 | C53: INFRAESTRUCTURA – Aseo y Limpieza | D53: Pisos: resistentes a factores ambientales, continuos, antideslizantes, impermeables, lavables, sólidos, resistentes a procesos de lavado y desinfección. Dilataciones y juntas selladas | E53: Inspección Visual | F53: ⚠️
A54: 38 | B54: 43 | C54: INFRAESTRUCTURA – Aseo y Limpieza | D54: Cielo rasos o techos y paredes o muros: impermeables, lavables, sólidos, resistentes a factores ambientales e incombustibles y de superficie lisa y continua | E54: Inspección Visual | F54: ⚠️
A55: 39 | B55: 44 | C55: INFRAESTRUCTURA – Aseo y Limpieza | D55: En salas de procedimientos, consultorios donde se realicen procedimientos, laboratorios, consulta odontológica y ambientes con procesos de limpieza y asepsia profundos: unión pared-piso en media caña (evita aristas o esquinas) | E55: Inspección Visual
A56: ▸ Modalidad Extramural — Aplica cuando el profesional presta servicios en esta modalidad
A57: 40 | B57: 46 | C57: INFRAESTRUCTURA – Extramural General | D57: Cuando se presten servicios exclusivamente en modalidad extramural, la sede cuenta con: almacenamiento de medicamentos/DM/insumos (cuando se requiera), almacenamiento de equipos biomédicos y archivo de historias clínicas y registros | E57: Inspección Visual
A58: 41 | B58: 47 | C58: INFRAESTRUCTURA – Extramural General | D58: Disponibilidad de área para labores de aseo, limpieza y desinfección para las unidades móviles | E58: Inspección Visual
A59: 42 | B59: 48 | C59: INFRAESTRUCTURA – Domiciliaria | D59: Modalidad domiciliaria — El domicilio del paciente cumple: servicios públicos domiciliarios (acueducto, alcantarillado, energía eléctrica, sistema de comunicación) y unidad sanitaria o baño | E59: Inspección Visual
A60: 43 | B60: 49-50 | C60: INFRAESTRUCTURA – Unidad Móvil | D60: Modalidad unidad móvil: condiciones de orden, aseo, limpieza dinámicas; suministro de agua potable; tanque de aguas residuales; identificación visual; energía eléctrica o alternativa; señalización de seguridad y acceso; estructuras firmes para ingreso/salida; señalización de áreas restringidas | E60: Inspección Visual
A61: ▸ Modalidad Telemedicina
A62: 44 | B62: 51 | C62: INFRAESTRUCTURA – Telemedicina Remisor | D62: Prestador remisor: conectividad con integridad y continuidad (sincrónico o asincrónico); plataformas tecnológicas con seguridad y privacidad de la información; suministro de energía eléctrica o baterías; nivel de iluminación homogénea con luz fluorescente blanca fría | E62: Inspección Visual | F62: ⚠️
A63: 45 | B63: 52 | C63: INFRAESTRUCTURA – Telemedicina Referencia | D63: Prestador de referencia: conectividad con integridad y continuidad; plataformas tecnológicas con seguridad y privacidad; suministro de energía eléctrica o baterías; nivel de iluminación homogénea | E63: Inspección Visual | F63: ⚠️
A64: 46 | B64: 53 | C64: INFRAESTRUCTURA – Telemedicina Ref. Exclusivo | D64: Prestador de referencia exclusivo: ambiente exclusivo para atención a distancia (privacidad, confidencialidad, libre de interferencias); conectividad; plataformas tecnológicas; suministro de energía | E64: Inspección Visual | F64: ⚠️
A65: ESTÁNDAR DE DOTACIÓN — Sección 11.1.3 | Todas las modalidades
A66: 47 | B66: 1 | C66: DOTACIÓN | D66: Registro de la relación de equipos biomédicos con: nombre, marca, modelo, serie, registro sanitario/permiso de comercialización cuando lo requiera, clasificación por riesgo cuando aplique | E66: Inspección Documental | F66: ⚠️
A67: 48 | B67: 2.1 | C67: DOTACIÓN | D67: Programa de mantenimiento preventivo de equipos biomédicos, que incluya cumplimiento de recomendaciones del fabricante o protocolo definido por el prestador cuando el fabricante no lo haya definido | E67: Inspección Documental | F67: ⚠️
A68: 49 | B68: 2.2 | C68: DOTACIÓN | D68: Hoja(s) de vida del(los) equipo(s) biomédico(s) con registros de mantenimientos preventivos y correctivos según corresponda | E68: Inspección Documental | F68: ⚠️
A69: 50 | B69: 3 | C69: DOTACIÓN | D69: Programa de capacitación en el uso de dispositivos médicos cuando éstos lo requieran (puede ser desarrollado por el fabricante, importador o el mismo prestador) | E69: Inspección Documental
A70: 51 | B70: 4 | C70: DOTACIÓN | D70: La dotación de los servicios de salud está en concordancia con lo definido por el prestador en el estándar de procesos prioritarios | E70: Inspección Visual | F70: ⚠️
A71: 52 | B71: 5 | C71: DOTACIÓN | D71: La suficiencia de equipos biomédicos está relacionada con la frecuencia de uso, incluyendo los tiempos del proceso de esterilización cuando aplique | E71: Inspección Visual
A72: 53 | B72: 6 | C72: DOTACIÓN | D72: El mantenimiento de equipos biomédicos es ejecutado por talento humano profesional, tecnólogo o técnico en áreas relacionadas (directamente o mediante contrato con un tercero) | E72: Inspección Documental
A73: 54 | B73: 7 | C73: DOTACIÓN | D73: Los prestadores que oferten servicios en la modalidad extramural no pueden elaborar ni adaptar dispositivos médicos sobre medida | E73: Inspección Documental
A74: 55 | B74: 12 | C74: DOTACIÓN | D74: El prestador que realice el proceso de esterilización cuenta con los equipos biomédicos y dotación de acuerdo con el método utilizado | E74: Inspección Visual
A75: 56 | B75: 14 | C75: DOTACIÓN | D75: Los servicios donde se realicen procedimientos bajo sedación fuera de salas de cirugía y monitorización electroencefalográfica con video y radio, cuentan con carro de paro | E75: Inspección Visual
A76: ▸ Modalidad Extramural
A77: 57 | B77: 16.1 | C77: DOTACIÓN – Extramural | D77: Sistemas de telecomunicaciones de doble vía | E77: Inspección Visual
A78: 58 | B78: 16.2 | C78: DOTACIÓN – Extramural | D78: Cuando se realicen pruebas para la detección de eventos de interés en salud pública: microscopio, cinta métrica y báscula | E78: Inspección Visual
A79: ▸ Modalidad Telemedicina
A80: 59 | B80: 17.1.1 | C80: DOTACIÓN – Telemedicina Remisor | D80: Documento firmado por ingeniero biomédico con tarjeta profesional vigente que certifique: dispositivos periféricos según oferta, equipos de captura que garanticen calidad equivalente al original, parámetros de digitalización y compresión que garanticen resolución para diagnóstico | E80: Inspección Documental | F80: ⚠️
A81: 60 | B81: 17.1.2 | C81: DOTACIÓN – Telemedicina Remisor | D81: Documento firmado por ingeniero de sistemas con tarjeta profesional vigente que certifique: dispositivos de videoconferencia con óptima fidelidad de video y sonido; software que se adapta al cambio de ancho de banda; pantallas/monitores grado médico con dot pitch máximo de 0.25 mm | E81: Inspección Documental | F81: ⚠️
A82: 61 | B82: 17.2 | C82: DOTACIÓN – Telemedicina Referencia | D82: Documento firmado por ingeniero de sistemas con tarjeta profesional vigente que certifique: dispositivos de videoconferencia con óptima fidelidad; software adaptable; pantallas/monitores grado médico con dot pitch máximo de 0.19 mm, resolución mínima 1024x768, contraste mínimo 500:1, luminancia mínima 250 cd/m² | E82: Inspección Documental | F82: ⚠️
A83: ESTÁNDAR DE MEDICAMENTOS, DM E INSUMOS — Sección 11.1.4 | Todas las modalidades
A84: 62 | B84: 1 | C84: MEDICAMENTOS, DM E INSUMOS | D84: Registros de todos los medicamentos para uso humano requeridos, con: principio activo, forma farmacéutica, concentración, lote, fecha de vencimiento, presentación comercial, unidad de medida, registro sanitario vigente o permiso de comercialización (INVIMA) | E84: Inspección Documental | F84: ⚠️
A85: 63 | B85: 2 | C85: MEDICAMENTOS, DM E INSUMOS | D85: Información documentada de dispositivos médicos: descripción, marca, serie (cuando aplique), presentación comercial, registro sanitario o permiso de comercialización (INVIMA), clasificación por riesgo, vida útil (cuando aplique), lote, fecha de vencimiento | E85: Inspección Documental | F85: ⚠️
A86: 64 | B86: 3 | C86: MEDICAMENTOS, DM E INSUMOS | D86: Información documentada de reactivos de diagnóstico in vitro: nombre, marca, presentación comercial, registro sanitario o permiso de comercialización (INVIMA), clasificación de riesgo sanitario, vida útil (cuando aplique), fecha de vencimiento y lote | E86: Inspección Documental | F86: ⚠️
A87: 65 | B87: 4 | C87: MEDICAMENTOS, DM E INSUMOS | D87: Información documentada de los procesos generales para: selección, adquisición, transporte, recepción, almacenamiento, conservación, control de fechas de vencimiento, control de cadena de frío y manejo de contingencias, distribución, dispensación, devolución, disposición final y seguimiento al uso | E87: Inspección Documental | F87: ⚠️
A88: 66 | B88: 5 | C88: MEDICAMENTOS, DM E INSUMOS | D88: Cuando se realicen actividades con medicamentos de control especial: resolución de autorización vigente expedida por el Fondo Nacional de Estupefacientes o entidad que haga sus veces | E88: Inspección Documental | F88: ⚠️
A89: 67 | B89: 6 | C89: MEDICAMENTOS, DM E INSUMOS | D89: Información documentada de planeación y ejecución de los programas de farmacovigilancia, tecnovigilancia y reactivovigilancia, según aplique | E89: Inspección Documental | F89: ⚠️
A90: 68 | B90: 7 | C90: MEDICAMENTOS, DM E INSUMOS | D90: Las reservas de medicamentos, DM, reactivos e insumos se almacenan en condiciones apropiadas de temperatura, humedad, ventilación, segregación y seguridad. Cuenta con instrumento para medir humedad relativa y temperatura y evidencia su registro, control y gestión | E90: Inspección Visual y Documental | F90: ⚠️
A91: 69 | B91: 8 | C91: MEDICAMENTOS, DM E INSUMOS | D91: Para el protocolo de lavado de manos o higienización: los servicios cuentan con los insumos de aseo, limpieza y secado que garanticen su cumplimiento | E91: Inspección Visual | F91: ⚠️
A92: 70 | B92: 9 | C92: MEDICAMENTOS, DM E INSUMOS | D92: La suficiencia de dispositivos médicos está relacionada con la frecuencia de uso, incluyendo los tiempos del proceso de esterilización cuando aplique | E92: Inspección Visual
A93: 71 | B93: 10 | C93: MEDICAMENTOS, DM E INSUMOS | D93: Paquete para el manejo de derrames y rupturas de medicamentos, ubicado en lugar de fácil acceso, visible y con señalización, disponible en los servicios donde se requiera. El prestador define su contenido según medicamentos utilizados y fichas técnicas del fabricante | E93: Inspección Visual
A94: ▸ Modalidad Extramural — Unidad Móvil, Jornada de Salud y Domiciliaria
A95: 72 | B95: 16.1 | C95: MEDICAMENTOS, DM E INSUMOS – Extramural | D95: Dispositivos médicos e insumos asistenciales según la patología del paciente o eventos de interés en salud pública cuando se requiera | E95: Inspección Visual
A96: 73 | B96: 16.2 | C96: MEDICAMENTOS, DM E INSUMOS – Extramural | D96: Medicamentos de acuerdo con inventario establecido por el prestador acorde a lo documentado en sus procesos prioritarios, cuando se requiera | E96: Inspección Documental
A97: ▸ Modalidad Telemedicina — Prestador Remisor y Prestador de Referencia
A98: 74 | B98: 17 | C98: MEDICAMENTOS, DM E INSUMOS – Telemedicina | D98: Cumple con los criterios que le apliquen del presente estándar | E98: Inspección Documental
A99: ESTÁNDAR DE PROCESOS PRIORITARIOS — Sección 11.1.5 | Todas las modalidades
A100: 75 | B100: 1 | C100: PROCESOS PRIORITARIOS | D100: Política de seguridad del paciente acorde con los lineamientos expedidos por el MinSalud | E100: Inspección Documental | F100: ⚠️
...

Sheet Auditoría Documental
A1: AUDITORÍA DE PROCESOS DOCUMENTALES — HABILITACIÓN EN SALUD
A2: Resolución 3100 de 2019 | Profesionales Independientes
A3: PRESTADOR:
A4: FECHA: | C4: AUDITOR: | F4: HORA INICIO: | I4: HORA FINAL:
A5: ⚠️ Los criterios marcados con este símbolo son de carácter CRÍTICO. Su incumplimiento puede generar requerimiento o cierre del servicio.
A7: N° | B7: ESTÁNDAR | C7: CRITERIO | D7: MODO DE VERIFICACIÓN | E7: ⚠️ | F7: C | G7: NC | H7: NA | I7: HALLAZGO / EVIDENCIA | J7: PLAN DE MEJORA | K7: RESPONSABLE | L7: FECHA COMPROMISO
A8: 1 | B8: TALENTO HUMANO | C8: Programa de capacitación al personal: i) análisis de necesidades, ii) planificación, iii) contenidos, iv) duración, v) formadores, vi) ejecución, evaluación y seguimiento | D8: Inspección Documental | E8: ⚠️
A9: 2 | B9: TALENTO HUMANO | C9: Cronograma del programa de capacitación | D9: Inspección Documental
A10: 3 | B10: TALENTO HUMANO | C10: Soportes de ejecución del programa de capacitación (listas de asistencia, certificados) | D10: Inspección Documental
A11: 4 | B11: TALENTO HUMANO | C11: Listado de documentos para hoja de vida del personal | D11: Inspección Documental
A12: 5 | B12: INFRAESTRUCTURA | C12: Licencia de construcción | D12: Inspección Documental | E12: ⚠️
A13: 6 | B13: INFRAESTRUCTURA | C13: Uso de suelos | D13: Inspección Documental | E13: ⚠️
A14: 7 | B14: INFRAESTRUCTURA | C14: Certificado de Bomberos | D14: Inspección Documental | E14: ⚠️
A15: 8 | B15: INFRAESTRUCTURA | C15: Certificado RETIE / Ingeniero eléctrico | D15: Inspección Documental | E15: ⚠️
A16: 9 | B16: INFRAESTRUCTURA | C16: Acta de visita de salud pública (concepto sanitario) | D16: Inspección Documental | E16: ⚠️
A17: 10 | B17: INFRAESTRUCTURA | C17: Programa de mantenimiento de infraestructura y equipos fijos | D17: Inspección Documental
A18: 11 | B18: INFRAESTRUCTURA | C18: Protocolo de lavado de tanques y caracterización del agua | D18: Inspección Documental
A19: 12 | B19: INFRAESTRUCTURA | C19: Protocolo de fumigación | D19: Inspección Documental
A20: 13 | B20: INFRAESTRUCTURA | C20: Plan hospitalario de emergencia | D20: Inspección Documental
A21: 14 | B21: INFRAESTRUCTURA | C21: Plan de gestión integral de residuos hospitalarios y RH1 | D21: Inspección Documental | E21: ⚠️
A22: 15 | B22: INFRAESTRUCTURA | C22: Formato RH1 | D22: Inspección Documental
A23: 16 | B23: INFRAESTRUCTURA | C23: Planillas de limpieza y desinfección | D23: Inspección Documental
A24: 17 | B24: INFRAESTRUCTURA | C24: Ruta de evacuación por piso (señalizada y visible) | D24: Inspección Documental y Visual
A25: 18 | B25: INFRAESTRUCTURA | C25: Ruta sanitaria de residuos | D25: Inspección Documental y Visual
A26: 19 | B26: DOTACIÓN | C26: Relación de equipos biomédicos: nombre, marca, modelo, serie, registro sanitario, clasificación del riesgo | D26: Inspección Documental
A27: 20 | B27: DOTACIÓN | C27: Formato hoja de vida de equipos biomédicos | D27: Inspección Documental
A28: 21 | B28: DOTACIÓN | C28: Formato cronograma de mantenimientos de los equipos biomédicos | D28: Inspección Documental
A29: 22 | B29: DOTACIÓN | C29: Registro de mantenimientos de equipos biomédicos (preventivo, correctivo, calibraciones) | D29: Inspección Documental
A30: 23 | B30: DOTACIÓN | C30: Programa de mantenimiento preventivo de equipos biomédicos, incluye recomendaciones del fabricante | D30: Inspección Documental
A31: 24 | B31: DOTACIÓN | C31: Capacitaciones en equipos biomédicos (cuando se requieran), incluidas dentro del programa de capacitaciones | D31: Inspección Documental
A32: 25 | B32: DOTACIÓN | C32: Registro de suficiencia de equipos biomédicos | D32: Inspección Documental
A33: 26 | B33: DOTACIÓN | C33: Hoja de vida del responsable de mantenimiento de equipos con soportes y/o contrato | D33: Inspección Documental
... A37: 30 | B37: INSUMOS | C37: Relación de reactivos: nombre, marca, presentación comercial, registro sanitario, clasificación del riesgo, vida útil, fecha de vencimiento, lote | D37: Inspección Documental
A38: 31 | B38: INSUMOS | C38: Información documentada: selección, adquisición, transporte, recepción, almacenamiento, conservación, control de fechas de vencimiento, cadena de frío, distribución, dispensación, devolución, disposición final | D38: Inspección Documental | E38: ⚠️
A39: 32 | B39: INSUMOS | C39: Medicamentos de control: resolución de autorización vigente expedida por el Fondo Nacional de Estupefacientes (cuando aplique) | D39: Inspección Documental | E39: ⚠️
A40: 33 | B40: INSUMOS | C40: Programa de Farmacovigilancia: inscripción y reportes mensuales | D40: Inspección Documental
A41: 34 | B41: INSUMOS | C41: Programa de Tecnovigilancia: inscripción y reportes trimestrales | D41: Inspección Documental
A42: 35 | B42: INSUMOS | C42: Programa de Reactivovigilancia: inscripción y reportes trimestrales (cuando aplique) | D42: Inspección Documental
A43: 36 | B43: INSUMOS | C43: Alertas sanitarias y seguimiento a las mismas | D43: Inspección Documental
A44: 37 | B44: INSUMOS | C44: Formato control de temperatura y humedad | D44: Inspección Documental
A45: 38 | B45: INSUMOS | C45: Protocolo de lavado de manos o higienización (jabón, sistema de secado) | D45: Inspección Documental | E45: ⚠️
A46: 39 | B46: INSUMOS | C46: Información documentada sobre derrame de medicamentos con respectivo kit | D46: Inspección Documental
A47: 40 | B47: PROCESOS PRIORITARIOS | C47: Programa de seguridad del paciente: incluye lista de chequeo de seguridad del paciente | D47: Inspección Documental | E47: ⚠️
A48: 41 | B48: PROCESOS PRIORITARIOS | C48: Acta de creación del comité de seguridad del paciente y seguimientos | D48: Inspección Documental
A49: 42 | B49: PROCESOS PRIORITARIOS | C49: Información documentada para correcta identificación del paciente (mínimo 2 identificadores: nombre completo y número de identificación) | D49: Inspección Documental | E49: ⚠️
A50: 43 | B50: PROCESOS PRIORITARIOS | C50: Gestión de comunicación adecuada con enfoque diferencial (género, etnia, ciclo de vida u otros) | D50: Inspección Documental
A51: 44 | B51: PROCESOS PRIORITARIOS | C51: Detección, prevención y reducción de infecciones asociadas a la atención en salud. Incluye protocolo de higiene de manos con soluciones a base de alcohol | D51: Inspección Documental | E51: ⚠️
A52: 45 | B52: PROCESOS PRIORITARIOS | C52: Detección, análisis y gestión de eventos adversos | D52: Inspección Documental
A53: 46 | B53: PROCESOS PRIORITARIOS | C53: Garantizar la funcionalidad de los procedimientos de consentimiento informado | D53: Inspección Documental | E53: ⚠️
A54: 47 | B54: PROCESOS PRIORITARIOS | C54: Mejorar la seguridad en la utilización de medicamentos (cuando aplique) | D54: Inspección Documental
A55: 48 | B55: PROCESOS PRIORITARIOS | C55: Prevenir y reducir la frecuencia de caídas | D55: Inspección Documental
A56: 49 | B56: PROCESOS PRIORITARIOS | C56: Garantizar la atención segura de la gestante y el recién nacido (donde aplique) | D56: Inspección Documental
A57: 50 | B57: PROCESOS PRIORITARIOS | C57: Prevenir complicaciones asociadas a disponibilidad y manejo de sangre y transfusión sanguínea (donde aplique) | D57: Inspección Documental
A58: 51 | B58: PROCESOS PRIORITARIOS | C58: Prevenir úlceras por presión (donde aplique) | D58: Inspección Documental
A59: 52 | B59: PROCESOS PRIORITARIOS | C59: Mejorar la seguridad en los procedimientos quirúrgicos (donde aplique) | D59: Inspección Documental
A60: 53 | B60: PROCESOS PRIORITARIOS | C60: Capacitación del personal en seguridad del paciente y principales riesgos de la atención | D60: Inspección Documental
A61: 54 | B61: PROCESOS PRIORITARIOS | C61: Actividades de ilustración al paciente y allegados en el autocuidado de su seguridad | D61: Inspección Documental
A62: 55 | B62: PROCESOS PRIORITARIOS | C62: Modelo de atención: incluye talento humano, enfoque diferencial, equipos biomédicos, medicamentos y dispositivos médicos e insumos | D62: Inspección Documental
A63: 56 | B63: PROCESOS PRIORITARIOS | C63: Socialización de los procesos documentales al personal (cronograma, listas de asistencia, certificados) | D63: Inspección Documental
A64: 57 | B64: PROCESOS PRIORITARIOS | C64: Guías de manejo (nacionales o internacionales basadas en evidencia científica) | D64: Inspección Documental | E64: ⚠️
A65: 58 | B65: PROCESOS PRIORITARIOS | C65: Información documentada de la adopción, adaptación o desarrollo de guías | D65: Inspección Documental
A66: 59 | B66: PROCESOS PRIORITARIOS | C66: Protocolos de manejo clínico | D66: Inspección Documental
A67: 60 | B67: PROCESOS PRIORITARIOS | C67: Información documentada: detección, prevención y disminución del riesgo de accidentes radiológicos (donde aplique) | D67: Inspección Documental
A68: 61 | B68: PROCESOS PRIORITARIOS | C68: Protocolo de aseo, limpieza y desinfección de áreas y superficies | D68: Inspección Documental | E68: ⚠️
A69: 62 | B69: PROCESOS PRIORITARIOS | C69: Procedimiento de reanimación cerebro-cardio-pulmonar (donde se realice) | D69: Inspección Documental
A70: 63 | B70: PROCESOS PRIORITARIOS | C70: Acciones para prevenir flebitis infecciosas, químicas y mecánicas (donde aplique) | D70: Inspección Documental
A71: 64 | B71: PROCESOS PRIORITARIOS | C71: Aspectos de bioseguridad acordes con las condiciones y características del servicio | D71: Inspección Documental | E71: ⚠️
A72: 65 | B72: PROCESOS PRIORITARIOS | C72: Descontaminación por derrames de sangre u otros fluidos corporales | D72: Inspección Documental
A73: 66 | B73: PROCESOS PRIORITARIOS | C73: Manejo de gases medicinales: atención de emergencias y sistema de alarma (cuando aplique) | D73: Inspección Documental
A74: 67 | B74: PROCESOS PRIORITARIOS | C74: Manual de Esterilización (cuando aplique): recibo, transporte, lavado, empaque, etiquetado, esterilización, almacenamiento, verificación, control de calidad | D74: Inspección Documental
A75: 68 | B75: PROCESOS PRIORITARIOS | C75: Política de no reúso y reúso de dispositivos médicos | D75: Inspección Documental
A76: 69 | B76: PROCESOS PRIORITARIOS | C76: Protocolo de referencia y contrarreferencia | D76: Inspección Documental | E76: ⚠️
A77: 70 | B77: PROCESOS PRIORITARIOS | C77: Documento del proceso institucional para atención en salud de víctimas de violencias sexuales (donde aplique) | D77: Inspección Documental
A78: 71 | B78: PROCESOS PRIORITARIOS | C78: Documento de conformación del equipo institucional para atención de víctimas de violencias sexuales (donde aplique) | D78: Inspección Documental
A79: 72 | B79: HISTORIA CLÍNICA | C79: Información documentada: procedimientos para utilizar historia única y registro de entrada/salida del archivo físico | D79: Inspección Documental
A80: 73 | B80: HISTORIA CLÍNICA | C80: HC digital: licencia de software, backup, registro no modificable (cuando aplique) | D80: Inspección Documental
A81: 74 | B81: HISTORIA CLÍNICA | C81: Las historias clínicas cuentan con componentes y contenidos mínimos (Resolución 1995/99) | D81: Inspección Documental | E81: ⚠️
A82: 75 | B82: HISTORIA CLÍNICA | C82: La historia clínica y registros asistenciales se diligencian en forma clara, legible, sin tachones ni enmendaduras | D82: Inspección Documental | E82: ⚠️
A83: 76 | B83: HISTORIA CLÍNICA | C83: Cada anotación lleva fecha, hora, nombre completo y firma del autor | D83: Inspección Documental
A84: 77 | B84: HISTORIA CLÍNICA | C84: El prestador cuenta con procedimiento de consentimiento informado con mecanismos para verificar su aplicación | D84: Inspección Documental | E84: ⚠️
A85: 78 | B85: HISTORIA CLÍNICA | C85: Cuando se usan mecanismos electrónicos: certificado de ingeniero de sistemas con tarjeta profesional vigente | D85: Inspección Documental
A86: 79 | B86: HISTORIA CLÍNICA | C86: Proceso de esterilización: actividades documentadas, registro de cargas, resultados de control de calidad, listas de contenido de paquetes, etiquetado de trazabilidad (cuando aplique) | D86: Inspección Documental
A89: RESUMEN DE CUMPLIMIENTO POR ESTÁNDAR
A90: ESTÁNDAR | B90: TOTAL CRITERIOS | C90: CUMPLE (C) | D90: NO CUMPLE (NC) | E90: NO APLICA (NA) | F90: % CUMPLIMIENTO | G90: NIVEL
A91: TALENTO HUMANO | B91: =COUNTIF(B8:B86,"*TALENTO HUMANO*") -> 4 | C91: =COUNTIFS(B8:B86,"*TALENTO HUMANO*",F8:F86,"X") -> 0 | D91: =COUNTIFS(B8:B86,"*TALENTO HUMANO*",G8:G86,"X") -> 0 | E91: =COUNTIFS(B8:B86,"*TALENTO HUMANO*",H8:H86,"X") -> 0 | F91: =IF((C91+D91)=0,0,C91/(C91+D91)) -> 0 | G91: =IF(F91>=0.9,"ALTO",IF(F91>=0.7,"MEDIO",IF(F91>0,"BAJO","SIN EVALUAR"))) -> SIN EVALUAR
A92: INFRAESTRUCTURA | B92: =COUNTIF(B8:B86,"*INFRAESTRUCTURA*") -> 14 | C92: =COUNTIFS(B8:B86,"*INFRAESTRUCTURA*",F8:F86,"X") -> 0 | D92: =COUNTIFS(B8:B86,"*INFRAESTRUCTURA*",G8:G86,"X") -> 0 | E92: =COUNTIFS(B8:B86,"*INFRAESTRUCTURA*",H8:H86,"X") -> 0 | F92: =IF((C92+D92)=0,0,C92/(C92+D92)) -> 0 | G92: =IF(F92>=0.9,"ALTO",IF(F92>=0.7,"MEDIO",IF(F92>0,"BAJO","SIN EVALUAR"))) -> SIN EVALUAR
A93: DOTACIÓN | B93: =COUNTIF(B8:B86,"*DOTACIÓN*") -> 9 | C93: =COUNTIFS(B8:B86,"*DOTACIÓN*",F8:F86,"X") -> 0 | D93: =COUNTIFS(B8:B86,"*DOTACIÓN*",G8:G86,"X") -> 0 | E93: =COUNTIFS(B8:B86,"*DOTACIÓN*",H8:H86,"X") -> 0 | F93: =IF((C93+D93)=0,0,C93/(C93+D93)) -> 0 | G93: =IF(F93>=0.9,"ALTO",IF(F93>=0.7,"MEDIO",IF(F93>0,"BAJO","SIN EVALUAR"))) -> SIN EVALUAR
A94: INSUMOS | B94: =COUNTIF(B8:B86,"*INSUMOS*") -> 12 | C94: =COUNTIFS(B8:B86,"*INSUMOS*",F8:F86,"X") -> 0 | D94: =COUNTIFS(B8:B86,"*INSUMOS*",G8:G86,"X") -> 0 | E94: =COUNTIFS(B8:B86,"*INSUMOS*",H8:H86,"X") -> 0 | F94: =IF((C94+D94)=0,0,C94/(C94+D94)) -> 0 | G94: =IF(F94>=0.9,"ALTO",IF(F94>=0.7,"MEDIO",IF(F94>0,"BAJO","SIN EVALUAR"))) -> SIN EVALUAR
A95: PROCESOS PRIORITARIOS | B95: =COUNTIF(B8:B86,"*PROCESOS PRIORITARIOS*") -> 32 | C95: =COUNTIFS(B8:B86,"*PROCESOS PRIORITARIOS*",F8:F86,"X") -> 0 | D95: =COUNTIFS(B8:B86,"*PROCESOS PRIORITARIOS*",G8:G86,"X") -> 0 | E95: =COUNTIFS(B8:B86,"*PROCESOS PRIORITARIOS*",H8:H86,"X") -> 0 | F95: =IF((C95+D95)=0,0,C95/(C95+D95)) -> 0 | G95: =IF(F95>=0.9,"ALTO",IF(F95>=0.7,"MEDIO",IF(F95>0,"BAJO","SIN EVALUAR"))) -> SIN EVALUAR
A96: HISTORIA CLÍNICA | B96: =COUNTIF(B8:B86,"*HISTORIA CLÍNICA*") -> 8 | C96: =COUNTIFS(B8:B86,"*HISTORIA CLÍNICA*",F8:F86,"X") -> 0 | D96: =COUNTIFS(B8:B86,"*HISTORIA CLÍNICA*",G8:G86,"X") -> 0 | E96: =COUNTIFS(B8:B86,"*HISTORIA CLÍNICA*",H8:H86,"X") -> 0 | F96: =IF((C96+D96)=0,0,C96/(C96+D96)) -> 0 | G96: =IF(F96>=0.9,"ALTO",IF(F96>=0.7,"MEDIO",IF(F96>0,"BAJO","SIN EVALUAR"))) -> SIN EVALUAR
A97: TOTAL GENERAL | B97: =SUM(B91:B96) -> 79 | C97: =SUM(C91:C96) -> 0 | D97: =SUM(D91:D96) -> 0 | E97: =SUM(E91:E96) -> 0 | F97: =SUM(F91:F96) -> 0 | G97: =IF(F97>=0.9,"ALTO",IF(F97>=0.7,"MEDIO",IF(F97>0,"BAJO","SIN EVALUAR"))) -> SIN EVALUAR

Sheet Auditoría Infraestructura
A1: AUDITORÍA DE INFRAESTRUCTURA — HABILITACIÓN EN SALUD
A2: Resolución 3100 de 2019 | Profesionales Independientes
A3: PRESTADOR:
A4: FECHA: | C4: AUDITOR: | F4: HORA INICIO: | I4: HORA FINAL:
A5: ⚠️ Los criterios marcados con este símbolo son de carácter CRÍTICO. Su incumplimiento puede generar requerimiento o cierre del servicio.
A7: N° | B7: ESTÁNDAR | C7: CRITERIO | D7: MODO DE VERIFICACIÓN | E7: ⚠️ | F7: C | G7: NC | H7: NA | I7: HALLAZGO / EVIDENCIA | J7: PLAN DE MEJORA | K7: RESPONSABLE | L7: FECHA COMPROMISO
A8: 1 | B8: INFRAESTRUCTURA: Edificaciones de uso exclusivo en salud | C8: Los servicios de urgencias, atención del parto, hospitalarios y cirugía con procedimientos quirúrgicos no ambulatorios, solo se prestan en edificaciones de uso exclusivo de salud | D8: Inspección Visual | E8: ⚠️
A9: 2 | B9: INFRAESTRUCTURA: Edificaciones de uso exclusivo en salud | C9: Servicios de urgencias, cirugía e internación y donde se realice esterilización, cuentan con ambiente de aseo de uso exclusivo | D9: Inspección Visual
A10: 3 | B10: INFRAESTRUCTURA: Edificaciones de uso exclusivo en salud | C10: Cuando funcionen más de un prestador con servicios de consulta externa y apoyo diagnóstico, cada prestador tiene infraestructura separada y delimitada. Pueden compartir: aseo, salas de espera y unidades sanitarias | D10: Inspección Visual
A11: 4 | B11: INFRAESTRUCTURA: Edificaciones de uso exclusivo en salud | C11: Edificaciones donde se presten servicios de urgencias e internación cuentan con tanque de almacenamiento de agua (mínimo 24 horas, 600 lt por cama/camilla/día) | D11: Inspección Visual
A12: 5 | B12: INFRAESTRUCTURA: Edificaciones de uso mixto | C12: Cuando en edificación de uso mixto funcionen varios prestadores, cada uno cuenta con infraestructura separada y delimitada. Pueden compartir salas de espera y unidades sanitarias | D12: Inspección Visual
A13: 6 | B13: INFRAESTRUCTURA: Edificaciones de uso mixto | C13: En edificaciones de uso mixto pueden funcionar prestadores de consulta externa, apoyo diagnóstico y cirugía ambulatoria | D13: Inspección Visual
A14: 7 | B14: INFRAESTRUCTURA: Accesibilidad | C14: Edificaciones hasta 3 pisos con servicios en 2° o 3° nivel cuentan con ascensor, rampa o sistema alternativo de elevación (no aplica para hospitalizaci, cirugía, urgencias, parto) | D14: Inspección Visual | E14: ⚠️
A15: 8 | B15: INFRAESTRUCTURA: Accesibilidad | C15: Si hay escaleras o rampas: piso uniforme, antideslizante, pasamanos a uno o ambos lados y protecciones laterales hacia espacios libres | D15: Inspección Visual
A16: 9 | B16: INFRAESTRUCTURA: Accesibilidad | C16: Edificaciones con más de 3 pisos cuentan con ascensor | D16: Inspección Visual
A17: 10 | B17: INFRAESTRUCTURA: Servicios básicos | C17: Las edificaciones donde se presten servicios de salud cuentan con suministro de agua, energía eléctrica, conexión a la red de alcantarillado y sistemas de comunicaciones | D17: Inspección Visual | E17: ⚠️
A18: 11 | B18: INFRAESTRUCTURA: Servicios básicos | C18: Servicios de cirugía, parto, laboratorio clínico, urgencias, gestión pre-transfusional, diálisis, hospitalarios, imágenes diagnósticas, vacunación, farmacéutico y cadena de frío, cuentan con planta eléctrica | D18: Inspección Visual
A19: 12 | B19: INFRAESTRUCTURA: Servicios básicos | C19: Cada prestador cuenta con concepto sanitario vigente (agua, residuos, vectores, orden y aseo, condiciones locativas) | D19: Inspección Documental | E19: ⚠️
A20: 13 | B20: INFRAESTRUCTURA: Servicios básicos | C20: Prestador que use equipos generadores de radiaciones ionizantes cuenta con licencia de práctica médica vigente (entidad competente) | D20: Inspección Documental | E20: ⚠️
A21: 14 | B21: INFRAESTRUCTURA: Servicios básicos | C21: Prestador que use fuentes radioactivas cuenta con autorización vigente de empleo de material radiactivo | D21: Inspección Documental | E21: ⚠️
A22: 15 | B22: INFRAESTRUCTURA: Gestión ambiental | C22: Protocolo de lavado de tanques y caracterización del agua | D22: Inspección Documental
A23: 16 | B23: INFRAESTRUCTURA: Gestión ambiental | C23: Protocolo de fumigación | D23: Inspección Documental
A24: 17 | B24: INFRAESTRUCTURA: Gestión ambiental | C24: Plan hospitalario de emergencia | D24: Inspección Documental
A25: 18 | B25: INFRAESTRUCTURA: Gestión ambiental | C25: Plan de gestión integral de residuos hospitalarios y RH1 (15 puntos o 7 según aplique) | D25: Inspección Documental | E25: ⚠️
A26: 19 | B26: INFRAESTRUCTURA: Gestión ambiental | C26: Formato RH1 | D26: Inspección Documental
A27: 20 | B27: INFRAESTRUCTURA: Gestión ambiental | C27: Planillas de limpieza y desinfección | D27: Inspección Documental
A28: 21 | B28: INFRAESTRUCTURA: Gestión ambiental | C28: Ruta sanitaria de residuos | D28: Inspección Documental y Visual
A29: 22 | B29: INFRAESTRUCTURA: Generalidades de ambientes y áreas | C29: Las áreas y ambientes de todos los servicios cuentan con ventilación e iluminación natural o artificial | D29: Inspección Visual | E29: ⚠️
A30: 23 | B30: INFRAESTRUCTURA: Generalidades de ambientes y áreas | C30: Las áreas de circulación están libres de obstáculos para movilización de pacientes, talento humano, usuarios y equipos | D30: Inspección Visual | E30: ⚠️
A31: 24 | B31: INFRAESTRUCTURA: Generalidades de ambientes y áreas | C31: Los ambientes permiten la instalación y movilización de equipos biomédicos y personal para atención en condiciones de rutina o emergencia | D31: Inspección Visual
A32: 25 | B32: INFRAESTRUCTURA: Generalidades de ambientes y áreas | C32: Cada piso cuenta con señalización y planos de rutas de evacuación, salidas de emergencia y puntos de encuentro, visibles al público | D32: Inspección Visual | E32: ⚠️
A33: 26 | B33: INFRAESTRUCTURA: Generalidades de ambientes y áreas | C33: Si se realizan procedimientos bajo sedación fuera de salas de cirugía: disponibilidad de área o ambiente para recuperación de pacientes garantizando privacidad | D33: Inspección Visual
A34: 27 | B34: INFRAESTRUCTURA: Características de ambientes | C34: Consultorio donde se realiza examen físico: mínimo 10 m² (sin incluir unidad sanitaria) con área de entrevista, área de examen y lavamanos | D34: Inspección Visual | E34: ⚠️
A35: 28 | B35: INFRAESTRUCTURA: Características de ambientes | C35: Áreas de entrevista y examen separadas por barrera física fija o móvil (excepto urgencias, optometría y oftalmología) | D35: Inspección Visual | E35: ⚠️
A36: 29 | B36: INFRAESTRUCTURA: Características de ambientes | C36: Consultorio donde se realizan procedimientos: mínimo 10 m², área de entrevista, área de procedimientos separadas por barrera fija, mesón de trabajo, poceta y lavamanos | D36: Inspección Visual | E36: ⚠️
A37: 30 | B37: INFRAESTRUCTURA: Características de ambientes | C37: Consultorio de entrevista (sin examen físico ni procedimientos): mínimo 4 m² con lavamanos | D37: Inspección Visual
A38: 31 | B38: INFRAESTRUCTURA: Características de ambientes | C38: Consultorio odontológico con una unidad: mínimo 10 m² con área de entrevista, área para unidad, lavamanos y mesón con poceta | D38: Inspección Visual
A39: 32 | B39: INFRAESTRUCTURA: Características de ambientes | C39: Sala de procedimientos / curaciones: mínimo 8 m², mesón de trabajo, poceta (cuando requiera) y lavamanos | D39: Inspección Visual
A40: 33 | B40: INFRAESTRUCTURA: Características de ambientes | C40: Sistema de alarma cuando cuente con red de distribución de gases medicinales | D40: Inspección Visual
A41: 34 | B41: INFRAESTRUCTURA: Características de ambientes | C41: Sala de espera: área variable, independiente de circulación, con ventilación e iluminación natural/artificial; disponibilidad de unidades sanitarias por sexo | D41: Inspección Visual
A42: 35 | B42: INFRAESTRUCTURA: Características de ambientes | C42: Ambiente o área de trabajo limpio: mesón de trabajo, área para almacenamiento y alistamiento de medicamentos, lavamanos | D42: Inspección Visual
A43: 36 | B43: INFRAESTRUCTURA: Características de ambientes | C43: Ambiente de trabajo sucio: mesón de trabajo con poceta y lavamanos | D43: Inspección Visual
A44: 37 | B44: INFRAESTRUCTURA: Esterilización | C44: Prestador que realice el proceso de esterilización cuenta con: área recibo material contaminado, lavado, secado, empaque, esterilización, almacenamiento material estéril, mesón con poceta, lavamanos | D44: Inspección Visual
A45: 38 | B45: INFRAESTRUCTURA: Esterilización | C45: Prestador que contrate esterilización cuenta con: área para lavado/limpieza y entrega al proveedor; área para recepción y almacenamiento de material estéril | D45: Inspección Visual
A46: 39 | B46: INFRAESTRUCTURA: Condiciones de orden y aseo | C46: Condiciones de orden, aseo, limpieza y desinfección evidentes y dinámicas acordes con los servicios prestados | D46: Inspección Visual | E46: ⚠️
A47: 40 | B47: INFRAESTRUCTURA: Condiciones de orden y aseo | C47: Pisos: resistentes a factores ambientales, continuos, antideslizantes, impermeables, lavables, sólidos, resistentes a lavado y desinfección. Dilataciones y juntas selladas | D47: Inspección Visual | E47: ⚠️
A48: 41 | B48: INFRAESTRUCTURA: Condiciones de orden y aseo | C48: Cielo rasos, techos y paredes: impermeables, lavables, sólidos, resistentes a factores ambientales, incombustibles, de superficie lisa y continua | D48: Inspección Visual | E48: ⚠️
A49: 42 | B49: INFRAESTRUCTURA: Condiciones de orden y aseo | C49: En servicios de cirugía, parto, TPR, procedimientos, consultorios con procedimientos, internación, urgencias, diálisis, hemodinamia, laboratorio, odontología: unión pared-piso en media caña | D49: Inspección Visual
A50: 43 | B50: INFRAESTRUCTURA: Condiciones de orden y aseo | C50: En servicios de cirugía, parto, TPR y esterilización: unión cielo raso-pared y unión entre paredes en media caña | D50: Inspección Visual
A51: 44 | B51: INFRAESTRUCTURA: Modalidad extramural | C51: Cuando el prestador preste servicios exclusivamente en modalidad extramural, la sede cuenta con: almacenamiento de medicamentos/DM/insumos, almacenamiento equipos biomédicos, archivo historias clínicas | D51: Inspección Visual
A52: 45 | B52: INFRAESTRUCTURA: Modalidad extramural | C52: Disponibilidad de área para labores de aseo, limpieza y desinfección para unidades móviles | D52: Inspección Visual
A53: 46 | B53: INFRAESTRUCTURA: Modalidad domiciliaria | C53: El domicilio del paciente cumple: acueducto, alcantarillado, energía eléctrica, sistema de comunicación y unidad sanitaria | D53: Inspección Visual
A54: 47 | B54: INFRAESTRUCTURA: Unidad móvil | C54: La unidad móvil cumple condiciones de orden, aseo, limpieza y desinfección dinámicas | D54: Inspección Visual
A55: 48 | B55: INFRAESTRUCTURA: Unidad móvil | C55: Unidad móvil: suministro de agua potable permanente; tanque para almacenamiento de aguas residuales; identificación visual; acceso a energía eléctrica o alternativa; señalización y seguridad | D55: Inspección Visual
A56: 49 | B56: INFRAESTRUCTURA: Telemedicina - Remisor | C56: Conectividad que garantice prestación con integridad y continuidad (sincrónico o asincrónico) | D56: Inspección Visual y Documental
A57: 50 | B57: INFRAESTRUCTURA: Telemedicina - Remisor | C57: Plataformas tecnológicas con seguridad y privacidad de la información, disponibilidad permanente, cumpliendo normatividad de protección de datos | D57: Inspección Visual y Documental | E57: ⚠️
A58: 51 | B58: INFRAESTRUCTURA: Telemedicina - Remisor | C58: Suministro de energía eléctrica o baterías para instrumentos de comunicación y equipos biomédicos | D58: Inspección Visual
A59: 52 | B59: INFRAESTRUCTURA: Telemedicina - Remisor | C59: Nivel de iluminación homogénea con luz fluorescente blanca fría (no mezclar cálida con fría) | D59: Inspección Visual
A60: 53 | B60: INFRAESTRUCTURA: Telemedicina - Referencia exclusivo | C60: Ambiente exclusivo para atención a distancia: garantía de privacidad, confidencialidad, seguridad de equipos y condiciones para funcionamiento, libre de interferencias visuales y sonoras | D60: Inspección Visual
A61: 54 | B61: INFRAESTRUCTURA: Telemedicina - Referencia exclusivo | C61: Conectividad que garantice prestación con integridad y continuidad | D61: Inspección Visual y Documental
A62: 55 | B62: INFRAESTRUCTURA: Telemedicina - Referencia exclusivo | C62: Plataformas tecnológicas con seguridad, privacidad y disponibilidad permanente | D62: Inspección Visual y Documental | E62: ⚠️

Sheet Consulta Externa
A1: AUDITORÍA — SERVICIO DE CONSULTA EXTERNA | General y Especializada
A2: Resolución 3100 de 2019 | Criterios por Estándar, Complejidad y Modalidad de Prestación
A3: PRESTADOR:
A4: FECHA: | D4: AUDITOR: | H4: HORA INICIO: | K4: HORA FINAL:
A5: ⚠️ Los criterios marcados con este símbolo son CRÍTICOS según la Resolución 3100/2019. Su incumplimiento puede generar requerimiento o cierre del servicio.
A6: LEYENDA: C = Cumple · NC = No Cumple · NA = No Aplica | Marque X en la columna correspondiente. La fila cambia de color automáticamente.
A7: N° | B7: ESTÁNDAR | C7: CRITERIO | D7: MODO DE VERIFICACIÓN | E7: ⚠️ | F7: C | G7: NC | H7: NA | I7: HALLAZGO / EVIDENCIA | J7: PLAN DE MEJORA | K7: RESPONSABLE | L7: FECHA COMPROMISO
A8: 11.2.1 SERVICIO DE CONSULTA EXTERNA GENERAL | Complejidad: Baja | Resolución 3100 de 2019, Pág. 80-93
A9: ESTÁNDAR DE TALENTO HUMANO
A10: ▸ Modalidades: Intramural · Extramural Unidad Móvil · Jornada de Salud · Domiciliaria
A11: 1 | B11: TALENTO HUMANO | C11: Profesional de la salud de acuerdo con el servicio a ofertar (medicina, enfermería, nutrición, psicología, optometría u otra especialidad) | D11: Inspección Documental | E11: ⚠️
A12: 2 | B12: TALENTO HUMANO | C12: Tarjeta profesional vigente del profesional independiente (criterio crítico de habilitación) | D12: Inspección Documental | E12: ⚠️
A13: 3 | B13: TALENTO HUMANO | C13: Resolución de autorización del servicio cuando aplique según normatividad | D13: Inspección Documental | E13: ⚠️
A14: 4 | B14: TALENTO HUMANO | C14: Constancia de formación continua en las actividades relacionadas con el servicio ofertado | D14: Inspección Documental
A15: 5 | B15: TALENTO HUMANO | C15: ERA – Disponibilidad de: Profesional de medicina | D15: Inspección Documental
A16: 6 | B16: TALENTO HUMANO | C16: ERA – Disponibilidad de: Profesional de enfermería o terapia respiratoria o fisioterapia | D16: Inspección Documental
A17: ▸ Modalidad Telemedicina – Categoría Interactiva y No Interactiva (Prestador de Referencia)
A18: 7 | B18: TALENTO HUMANO – Telemedicina Interactiva/No Interactiva | C18: Profesional de la salud de acuerdo con el servicio a ofertar (criterios aplicables de todos los servicios) | D18: Inspección Documental | E18: ⚠️
A19: ▸ Modalidad Telemedicina – Categoría Telexperticia (Prestador Remisor)
A20: 8 | B20: TALENTO HUMANO – Telexperticia Remisor | C20: Cuando se realice telexperticia entre profesionales: profesional de la salud de acuerdo con el servicio a ofertar | D20: Inspección Documental
A21: 9 | B21: TALENTO HUMANO – Telexperticia Remisor | C21: Cuando se realice telexperticia entre personal no profesional y profesional: técnico, tecnólogo o auxiliar que atiende presencialmente al usuario | D21: Inspección Documental
A22: ▸ Modalidad Telemedicina – Categoría Telexperticia (Prestador de Referencia)
A23: 10 | B23: TALENTO HUMANO – Telexperticia Referencia | C23: Profesional de la salud que atiende a distancia, de acuerdo con el servicio a ofertar | D23: Inspección Documental
A24: ▸ Modalidad Telemedicina – Categoría Telemonitoreo (Prestador de Referencia)
A25: 11 | B25: TALENTO HUMANO – Telemonitoreo Referencia | C25: Personal de salud profesional requerido para realizar el telemonitoreo según lo documentado en el estándar de procesos prioritarios | D25: Inspección Documental
A26: ESTÁNDAR DE INFRAESTRUCTURA
A27: ▸ Modalidades: Intramural · Extramural Unidad Móvil · Jornada de Salud · Domiciliaria
A28: 12 | B28: INFRAESTRUCTURA | C28: Cumple con los criterios que le sean aplicables de todos los servicios (criterios generales de infraestructura Res. 3100/2019) | D28: Inspección Visual y Documental
A29: 13 | B29: INFRAESTRUCTURA | C29: Consultorio donde se realiza examen físico: mínimo 10 m² (sin unidad sanitaria), con área de entrevista, área de examen y lavamanos | D29: Inspección Visual | E29: ⚠️
A30: 14 | B30: INFRAESTRUCTURA | C30: Áreas de entrevista y examen separadas por barrera física fija o móvil (excepto CE urgencias, optometría y oftalmología) | D30: Inspección Visual | E30: ⚠️
A31: 15 | B31: INFRAESTRUCTURA | C31: Consultorio donde se realizan procedimientos: mínimo 10 m², área de entrevista, área de procedimientos separadas por barrera fija, mesón de trabajo, poceta (cuando la requiera) y lavamanos | D31: Inspección Visual | E31: ⚠️
A32: 16 | B32: INFRAESTRUCTURA | C32: Ambiente de entrevista donde no se realiza examen físico ni procedimientos: mínimo 4 m² con lavamanos | D32: Inspección Visual
A33: 17 | B33: INFRAESTRUCTURA | C33: Consultorio odontológico con una unidad odontológica: mínimo 10 m², área entrevista, área para unidad, lavamanos, mesón de trabajo con poceta | D33: Inspección Visual
A34: 18 | B34: INFRAESTRUCTURA | C34: Sala de procedimientos cuando se requiera (ver criterio 30 generalidades) | D34: Inspección Visual
A35: 19 | B35: INFRAESTRUCTURA | C35: Disponibilidad de sala de espera (área variable, independiente de circulación, ventilación e iluminación natural/artificial) | D35: Inspección Visual
A36: 20 | B36: INFRAESTRUCTURA | C36: Hasta 2 consultorios: mínimo 1 unidad sanitaria de uso mixto apta para personas con movilidad reducida | D36: Inspección Visual
A37: 21 | B37: INFRAESTRUCTURA | C37: Más de 2 consultorios: mínimo 1 unidad sanitaria discriminada por sexo apta para personas con movilidad reducida o batería sanitaria discriminada por sexo | D37: Inspección Visual
A38: 22 | B38: INFRAESTRUCTURA | C38: ERA – El ambiente cuenta con: lavamanos, mesón de trabajo, poceta (cuando la requiera según procedimientos documentados), barrera física móvil o fija para separación entre sillas | D38: Inspección Visual
A39: 23 | B39: INFRAESTRUCTURA | C39: Cuando se realicen terapias/intervenciones grupales para consumo de sustancias psicoactivas o alteraciones en salud mental: ambiente con dimensión variable | D39: Inspección Visual
A40: 24 | B40: INFRAESTRUCTURA | C40: Cuando se realicen actividades grupales de educación para la salud: disponibilidad de ambiente con dimensión variable | D40: Inspección Visual
A41: ▸ Modalidad Extramural: Unidad Móvil · Jornada de Salud · Domiciliaria
A42: 25 | B42: INFRAESTRUCTURA – Extramural | C42: Cumple con los criterios que le sean aplicables de todos los servicios (criterios generales extramural) | D42: Inspección Visual
A43: ▸ Modalidad Telemedicina – Categoría Interactiva y No Interactiva (Prestador de Referencia)
A44: 26 | B44: INFRAESTRUCTURA – Telemedicina Interactiva | C44: Cumple con los criterios que le sean aplicables de todos los servicios | D44: Inspección Visual y Documental
A45: ▸ Modalidad Telemedicina – Categoría Telexperticia (Prestador Remisor)
A46: 27 | B46: INFRAESTRUCTURA – Telexperticia Remisor | C46: Cumple con los criterios establecidos en el servicio de consulta externa general | D46: Inspección Visual y Documental
A47: ▸ Modalidad Telemedicina – Categoría Telexperticia (Prestador de Referencia)
A48: 28 | B48: INFRAESTRUCTURA – Telexperticia Referencia | C48: Cumple con los criterios que le sean aplicables de todos los servicios | D48: Inspección Visual
A49: ▸ Modalidad Telemedicina – Categoría Telemonitoreo (Prestador de Referencia)
A50: 29 | B50: INFRAESTRUCTURA – Telemonitoreo | C50: Cumple con los criterios que le sean aplicables de todos los servicios | D50: Inspección Visual
A51: ESTÁNDAR DE DOTACIÓN
A52: ▸ Modalidad Intramural – Complejidad Baja
A53: 30 | B53: DOTACIÓN – Intramural | C53: Consultorio donde se realice examen físico: camilla fija | D53: Inspección Visual | E53: ⚠️
A54: 31 | B54: DOTACIÓN – Intramural | C54: Consultorio donde se realice examen físico: escalerilla | D54: Inspección Visual
A55: 32 | B55: DOTACIÓN – Intramural | C55: Tensiómetro para adulto o pediátrico según la oferta del servicio | D55: Inspección Visual | E55: ⚠️
A56: 33 | B56: DOTACIÓN – Intramural | C56: Fonendoscopio para adulto o pediátrico según la oferta del servicio | D56: Inspección Visual | E56: ⚠️
A57: 34 | B57: DOTACIÓN – Intramural | C57: Equipo de órganos de los sentidos | D57: Inspección Visual
A58: 35 | B58: DOTACIÓN – Intramural | C58: Martillo de reflejos | D58: Inspección Visual
A59: 36 | B59: DOTACIÓN – Intramural | C59: Tallímetro o infantómetro según la oferta del servicio | D59: Inspección Visual
A60: 37 | B60: DOTACIÓN – Intramural | C60: Cinta métrica | D60: Inspección Visual
A61: 38 | B61: DOTACIÓN – Intramural | C61: Báscula grado médico o pesa bebé, según la oferta del servicio | D61: Inspección Visual
A62: 39 | B62: DOTACIÓN – Intramural | C62: Termómetro cuando lo requiera | D62: Inspección Visual
A63: 40 | B63: DOTACIÓN – Intramural | C63: Negatoscopio cuando se requiera o sistema de visualización según la tecnología utilizada por el prestador | D63: Inspección Visual
A64: 41 | B64: DOTACIÓN – Intramural | C64: Consultorio sin examen físico ni procedimientos: dotación según lo documentado en el estándar de procesos prioritarios (no se exige dotación anterior) | D64: Inspección Visual
A65: 42 | B65: DOTACIÓN – Intramural | C65: Consultorio donde se realicen procedimientos: dotación mínima definida para consultorio de examen físico + dotación para procedimientos documentados en procesos prioritarios | D65: Inspección Visual
A66: 43 | B66: DOTACIÓN – Intramural | C66: Sala de procedimientos: dotación para procedimientos documentados + camilla con barandas, ruedas y freno (cuando los procedimientos requieran estas características) | D66: Inspección Visual
A67: 44 | B67: DOTACIÓN – Odontología Intramural | C67: Consultorio odontológico: unidad odontológica fija | D67: Inspección Visual | E67: ⚠️
A68: 45 | B68: DOTACIÓN – Odontología Intramural | C68: Consultorio odontológico: lámpara de fotocurado o amalgamador según la oferta | D68: Inspección Visual
A69: 46 | B69: DOTACIÓN – Odontología Intramural | C69: Consultorio odontológico: negatoscopio o sistema de visualización según tecnología | D69: Inspección Visual
A70: 47 | B70: DOTACIÓN – Odontología Intramural | C70: Consultorio odontológico: sistema de succión (puede estar incorporado a la unidad) | D70: Inspección Visual
A71: 48 | B71: DOTACIÓN – Odontología Intramural | C71: Consultorio odontológico: compresor de aire para uso odontológico | D71: Inspección Visual
A72: 49 | B72: DOTACIÓN – Odontología Intramural | C72: Consultorio odontológico: instrumental básico definido por el prestador según oferta (adultos/pediatría), capacidad instalada, procedimientos en PP y técnica de esterilización | D72: Inspección Visual
A73: 50 | B73: DOTACIÓN – Odontología Intramural | C73: Cuando se realice esterilización dentro del servicio: equipos para esterilización según procedimientos realizados y documentados en PP | D73: Inspección Visual
A74: ▸ Modalidad Extramural: Unidad Móvil · Jornada de Salud · Domiciliaria
A75: 51 | B75: DOTACIÓN – Extramural Medicina General | C75: Medicina general extramural: fonendoscopio para adulto o pediátrico según oferta | D75: Inspección Visual | E75: ⚠️
A76: 52 | B76: DOTACIÓN – Extramural Medicina General | C76: Medicina general extramural: tensiómetro para adulto o pediátrico según oferta | D76: Inspección Visual | E76: ⚠️
A77: 53 | B77: DOTACIÓN – Extramural Medicina General | C77: Medicina general extramural: equipo de órganos de los sentidos | D77: Inspección Visual
A78: 54 | B78: DOTACIÓN – Extramural Medicina General | C78: Medicina general extramural: oxímetro | D78: Inspección Visual
A79: 55 | B79: DOTACIÓN – Extramural Medicina General | C79: Medicina general extramural: glucómetro | D79: Inspección Visual
A80: 56 | B80: DOTACIÓN – Extramural Medicina General | C80: Medicina general extramural: martillo de reflejos | D80: Inspección Visual
A81: 57 | B81: DOTACIÓN – Extramural Medicina General | C81: Medicina general extramural: termómetro cuando lo requiera | D81: Inspección Visual
A82: 58 | B82: DOTACIÓN – Extramural Medicina General | C82: Medicina general extramural: cinta métrica | D82: Inspección Visual
A83: 59 | B83: DOTACIÓN – Extramural Medicina General | C83: Medicina general extramural: báscula grado médico o pesa bebé según oferta | D83: Inspección Visual
A84: 60 | B84: DOTACIÓN – Extramural Medicina General | C84: Dotación necesaria para realizar los procedimientos documentados en el estándar de procesos prioritarios | D84: Inspección Visual
A85: 61 | B85: DOTACIÓN – Odontología Extramural | C85: Odontología extramural: unidad odontológica portátil | D85: Inspección Visual | E85: ⚠️
A86: 62 | B86: DOTACIÓN – Odontología Extramural | C86: Odontología extramural: lámpara de fotocurado o amalgamador según oferta | D86: Inspección Visual
A87: 63 | B87: DOTACIÓN – Odontología Extramural | C87: Odontología extramural: negatoscopio o sistema de visualización según tecnología | D87: Inspección Visual
A88: 64 | B88: DOTACIÓN – Odontología Extramural | C88: Odontología extramural: sistema de succión (puede estar incorporado a la unidad) | D88: Inspección Visual
A89: 65 | B89: DOTACIÓN – Odontología Extramural | C89: Odontología extramural: compresor de aire para uso odontológico | D89: Inspección Visual
A90: 66 | B90: DOTACIÓN – Odontología Extramural | C90: Odontología extramural: instrumental básico estéril según oferta (adultos/pediatría), capacidad instalada y procedimientos documentados en PP | D90: Inspección Visual
A91: 67 | B91: DOTACIÓN – Extramural General | C91: Cumple con los criterios que le sean aplicables de todos los servicios | D91: Inspección Visual
A92: ▸ Modalidad Telemedicina – Categoría Interactiva y No Interactiva (Prestador de Referencia)
A93: 68 | B93: DOTACIÓN – Telemedicina Interactiva | C93: Cumple con los criterios que le sean aplicables de todos los servicios | D93: Inspección Visual
A94: ▸ Modalidad Telemedicina – Categoría Telexperticia (Prestador Remisor)
A95: 69 | B95: DOTACIÓN – Telexperticia Remisor | C95: Cumple con los criterios que le sean aplicables de todos los servicios y los establecidos en el servicio de consulta externa general | D95: Inspección Visual
A96: ▸ Modalidad Telemedicina – Categoría Telexperticia (Prestador de Referencia)
A97: 70 | B97: DOTACIÓN – Telexperticia Referencia | C97: Cumple con los criterios que le sean aplicables de todos los servicios | D97: Inspección Visual
A98: ▸ Modalidad Telemedicina – Categoría Telemonitoreo (Prestador de Referencia)
A99: 71 | B99: DOTACIÓN – Telemonitoreo | C99: Cumple con los criterios que le sean aplicables de todos los servicios | D99: Inspección Visual
A100: ESTÁNDAR DE MEDICAMENTOS, DISPOSITIVOS MÉDICOS E INSUMOS
...

Sheet Terapias
A1: AUDITORÍA — SERVICIO DE TERAPIAS (Física, Ocupacional, Lenguaje, Respiratoria)
A2: Resolución 3100 de 2019 | Criterios Específicos del Servicio
A3: PRESTADOR:
A4: FECHA: | C4: AUDITOR: | F4: HORA INICIO: | I4: HORA FINAL:
A5: ⚠️ Los criterios marcados con este símbolo son de carácter CRÍTICO. Su incumplimiento puede generar requerimiento o cierre del servicio.
A7: N° | B7: ESTÁNDAR | C7: CRITERIO | D7: MODO DE VERIFICACIÓN | E7: ⚠️ | F7: C | G7: NC | H7: NA | I7: HALLAZGO / EVIDENCIA | J7: PLAN DE MEJORA | K7: RESPONSABLE | L7: FECHA COMPROMISO
A8: 1 | B8: TALENTO HUMANO | C8: Profesional de la salud con título según programas autorizados por el MEN en el ámbito de la rehabilitación (fisioterapia, fonoaudiología, terapia ocupacional, terapia respiratoria) | D8: Inspección Documental | E8: ⚠️
A9: 2 | B9: TALENTO HUMANO | C9: Tarjeta profesional vigente | D9: Inspección Documental | E9: ⚠️
A10: 3 | B10: TALENTO HUMANO | C10: Si oferta integración neurosensorial: constancia de formación continua | D10: Inspección Documental
A11: 4 | B11: INFRAESTRUCTURA | C11: Área para camillas, sillas de ruedas y aditamentos ortopédicos (cuando se requiera) | D11: Inspección Visual
A12: 5 | B12: INFRAESTRUCTURA | C12: Vestidor de pacientes con área para casilleros y unidad sanitaria de uso mixto (cuando el tipo de terapia lo requiera) | D12: Inspección Visual
A13: 6 | B13: INFRAESTRUCTURA | C13: Ambiente para realizar entrevista (cuando se requiera según procesos prioritarios) | D13: Inspección Visual
A14: 7 | B14: INFRAESTRUCTURA | C14: Área para atención individual con barrera física fija o móvil (cuando se requiera privacidad) | D14: Inspección Visual
A15: 8 | B15: INFRAESTRUCTURA | C15: Área de depósito para almacenamiento de insumos, equipos biomédicos y materiales | D15: Inspección Visual
A16: 9 | B16: INFRAESTRUCTURA | C16: Área con equipamiento para actividades de terapia ocupacional (cuando se requiera) | D16: Inspección Visual
A17: 10 | B17: INFRAESTRUCTURA | C17: Área húmeda o hidroterapia (si se oferta): pisos antideslizantes y tomas eléctricas con protección para ambientes húmedos | D17: Inspección Visual
A18: 11 | B18: INFRAESTRUCTURA | C18: Para fonoaudiología o terapia ocupacional: área para sillas y mesas de trabajo individual o grupal | D18: Inspección Visual
A19: 12 | B19: INFRAESTRUCTURA | C19: Cabina sono-amortiguada o equipo de audiometría (según procedimientos ofertados en fonoaudiología) | D19: Inspección Visual
A20: 13 | B20: INFRAESTRUCTURA | C20: Disponibilidad de sala de espera | D20: Inspección Visual
A21: 14 | B21: INFRAESTRUCTURA | C21: Unidades sanitarias discriminadas por sexo | D21: Inspección Visual
... A23: 16 | B23: INFRAESTRUCTURA | C23: Pisos resistentes, continuos, antideslizantes, impermeables y lavables | D23: Inspección Visual
A24: 17 | B24: DOTACIÓN | C24: Dotación requerida para realizar procedimientos documentados en procesos prioritarios | D24: Inspección Visual | E24: ⚠️
A25: 18 | B25: DOTACIÓN | C25: Equipos biomédicos para fisioterapia según oferta (TENS, ultrasonido terapéutico, etc.) | D25: Inspección Visual
A26: 19 | B26: DOTACIÓN | C26: Equipos y materiales para fonoaudiología según oferta | D26: Inspección Visual
A27: 20 | B27: DOTACIÓN | C27: Equipos y materiales para terapia ocupacional según oferta | D27: Inspección Visual
A28: 21 | B28: MEDICAMENTOS E INSUMOS | C28: Medicamentos, dispositivos médicos e insumos según criterios generales aplicables | D28: Inspección Documental
A29: 22 | B29: PROCESOS PRIORITARIOS | C29: Información documentada de procedimientos (áreas/ambientes, equipos, dispositivos e insumos requeridos) | D29: Inspección Documental | E29: ⚠️
A30: 23 | B30: PROCESOS PRIORITARIOS | C30: Programa de seguridad del paciente con lista de chequeo | D30: Inspección Documental | E30: ⚠️
A31: 24 | B31: PROCESOS PRIORITARIOS | C31: Protocolo para correcta identificación del paciente | D31: Inspección Documental | E31: ⚠️
A32: 25 | B32: PROCESOS PRIORITARIOS | C32: Protocolo de higiene de manos | D32: Inspección Documental | E32: ⚠️
A33: 26 | B33: PROCESOS PRIORITARIOS | C33: Detección, análisis y gestión de eventos adversos | D33: Inspección Documental
A34: 27 | B34: PROCESOS PRIORITARIOS | C34: Consentimiento informado | D34: Inspección Documental | E34: ⚠️
A35: 28 | B35: PROCESOS PRIORITARIOS | C35: Prevenir y reducir la frecuencia de caídas | D35: Inspección Documental
A36: 29 | B36: PROCESOS PRIORITARIOS | C36: Guías y protocolos de manejo para los tipos de terapia ofertados | D36: Inspección Documental | E36: ⚠️
A37: 30 | B37: PROCESOS PRIORITARIOS | C37: Modelo de atención con enfoque diferencial | D37: Inspección Documental
A38: 31 | B38: PROCESOS PRIORITARIOS | C38: Protocolo de aseo, limpieza y desinfección | D38: Inspección Documental | E38: ⚠️
A39: 32 | B39: PROCESOS PRIORITARIOS | C39: Aspectos de bioseguridad acordes con el servicio | D39: Inspección Documental | E39: ⚠️
A40: 33 | B40: PROCESOS PRIORITARIOS | C40: Protocolo de referencia y contrarreferencia | D40: Inspección Documental | E40: ⚠️
A41: 34 | B41: HISTORIA CLÍNICA | C41: Historias clínicas con componentes mínimos según normatividad (Res. 1995/99) | D41: Inspección Documental | E41: ⚠️
A42: 35 | B42: HISTORIA CLÍNICA | C42: HC diligenciadas clara y legiblemente, sin tachones ni enmendaduras | D42: Inspección Documental
A43: 36 | B43: HISTORIA CLÍNICA | C43: Cada anotación con fecha, hora, nombre completo y firma | D43: Inspección Documental
A44: 37 | B44: HISTORIA CLÍNICA | C44: Consentimiento informado documentado y verificable | D44: Inspección Documental | E44: ⚠️
A47: RESUMEN DE CUMPLIMIENTO POR ESTÁNDAR
A48: ESTÁNDAR | B48: TOTAL CRITERIOS | C48: CUMPLE (C) | D48: NO CUMPLE (NC) | E48: NO APLICA (NA) | F48: % CUMPLIMIENTO | G48: NIVEL
A49: TALENTO HUMANO | B49: =COUNTIF(B8:B44,"*TALENTO HUMANO*") -> 3 | C49: =COUNTIFS(B8:B44,"*TALENTO HUMANO*",F8:F44,"X") -> 0 | D49: =COUNTIFS(B8:B44,"*TALENTO HUMANO*",G8:G44,"X") -> 0 | E49: =COUNTIFS(B8:B44,"*TALENTO HUMANO*",H8:H44,"X") -> 0 | F49: =IF((C49+D49)=0,0,C49/(C49+D49)) -> 0 | G49: =IF(F49>=0.9,"ALTO",IF(F49>=0.7,"MEDIO",IF(F49>0,"BAJO","SIN EVALUAR"))) -> SIN EVALUAR
A50: INFRAESTRUCTURA | B50: =COUNTIF(B8:B44,"*INFRAESTRUCTURA*") -> 13 | C50: =COUNTIFS(B8:B44,"*INFRAESTRUCTURA*",F8:F44,"X") -> 0 | D50: =COUNTIFS(B8:B44,"*INFRAESTRUCTURA*",G8:G44,"X") -> 0 | E50: =COUNTIFS(B8:B44,"*INFRAESTRUCTURA*",H8:H44,"X") -> 0 | F50: =IF((C50+D50)=0,0,C50/(C50+D50)) -> 0 | G50: =IF(F50>=0.9,"ALTO",IF(F50>=0.7,"MEDIO",IF(F50>0,"BAJO","SIN EVALUAR"))) -> SIN EVALUAR
A51: DOTACIÓN | B51: =COUNTIF(B8:B44,"*DOTACIÓN*") -> 4 | C51: =COUNTIFS(B8:B44,"*DOTACIÓN*",F8:F44,"X") -> 0 | D51: =COUNTIFS(B8:B44,"*DOTACIÓN*",G8:G44,"X") -> 0 | E51: =COUNTIFS(B8:B44,"*DOTACIÓN*",H8:H44,"X") -> 0 | F51: =IF((C51+D51)=0,0,C51/(C51+D51)) -> 0 | G51: =IF(F51>=0.9,"ALTO",IF(F51>=0.7,"MEDIO",IF(F51>0,"BAJO","SIN EVALUAR"))) -> SIN EVALUAR
A52: MEDICAMENTOS E INSUMOS | B52: =COUNTIF(B8:B44,"*MEDICAMENTOS E INSUMOS*") -> 1 | C52: =COUNTIFS(B8:B44,"*MEDICAMENTOS E INSUMOS*",F8:F44,"X") -> 0 | D52: =COUNTIFS(B8:B44,"*MEDICAMENTOS E INSUMOS*",G8:G44,"X") -> 0 | E52: =COUNTIFS(B8:B44,"*MEDICAMENTOS E INSUMOS*",H8:H44,"X") -> 0 | F52: =IF((C52+D52)=0,0,C52/(C52+D52)) -> 0 | G52: =IF(F52>=0.9,"ALTO",IF(F52>=0.7,"MEDIO",IF(F52>0,"BAJO","SIN EVALUAR"))) -> SIN EVALUAR
A53: PROCESOS PRIORITARIOS | B53: =COUNTIF(B8:B44,"*PROCESOS PRIORITARIOS*") -> 12 | C53: =COUNTIFS(B8:B44,"*PROCESOS PRIORITARIOS*",F8:F44,"X") -> 0 | D53: =COUNTIFS(B8:B44,"*PROCESOS PRIORITARIOS*",G8:G44,"X") -> 0 | E53: =COUNTIFS(B8:B44,"*PROCESOS PRIORITARIOS*",H8:H44,"X") -> 0 | F53: =IF((C53+D53)=0,0,C53/(C53+D53)) -> 0 | G53: =IF(F53>=0.9,"ALTO",IF(F53>=0.7,"MEDIO",IF(F53>0,"BAJO","SIN EVALUAR"))) -> SIN EVALUAR
A54: HISTORIA CLÍNICA | B54: =COUNTIF(B8:B44,"*HISTORIA CLÍNICA*") -> 4 | C54: =COUNTIFS(B8:B44,"*HISTORIA CLÍNICA*",F8:F44,"X") -> 0 | D54: =COUNTIFS(B8:B44,"*HISTORIA CLÍNICA*",G8:G44,"X") -> 0 | E54: =COUNTIFS(B8:B44,"*HISTORIA CLÍNICA*",H8:H44,"X") -> 0 | F54: =IF((C54+D54)=0,0,C54/(C54+D54)) -> 0 | G54: =IF(F54>=0.9,"ALTO",IF(F54>=0.7,"MEDIO",IF(F54>0,"BAJO","SIN EVALUAR"))) -> SIN EVALUAR
A55: TOTAL GENERAL | B55: =SUM(B49:B54) -> 37 | C55: =SUM(C49:C54) -> 0 | D55: =SUM(D49:D54) -> 0 | E55: =SUM(E49:E54) -> 0 | F55: =SUM(F49:F54) -> 0 | G55: =IF(F55>=0.9,"ALTO",IF(F55>=0.7,"MEDIO",IF(F55>0,"BAJO","SIN EVALUAR"))) -> SIN EVALUAR

Sheet Laboratorio Clínico
A1: AUDITORÍA — SERVICIO DE LABORATORIO CLÍNICO | Baja Complejidad
A2: Resolución 3100 de 2019 | Sección 11.3.12 | Criterios por Estándar y Modalidad de Prestación
A3: PRESTADOR:
A4: FECHA: | E4: AUDITOR: | K4: HORA INICIO:
A5: ⚠️ Los criterios marcados son CRÍTICOS. Su incumplimiento puede generar requerimiento o cierre del servicio. | Referencia normativa: Res. 3100/2019, Sección 11.3.12, Pág. 132
A6: LEYENDA: C = Cumple · NC = No Cumple · NA = No Aplica | Marque X en la columna correspondiente. La fila cambia de color automáticamente.
A7: N° | B7: N° CRITERIO | C7: ESTÁNDAR | D7: CRITERIO | E7: MODO DE VERIFICACIÓN | F7: ⚠️ | G7: C | H7: NC | I7: NA | J7: HALLAZGO / EVIDENCIA | K7: PLAN DE MEJORA | L7: RESPONSABLE | M7: FECHA COMPROMISO
A8: ESTÁNDAR DE TALENTO HUMANO — Sección 11.3.12
A9: ▸ Modalidades: Intramural · Extramural Unidad Móvil · Jornada de Salud · Telemedicina Prestador Remisor
A10: 1 | B10: 1 | C10: TALENTO HUMANO | D10: Cumple con los criterios que le sean aplicables de todos los servicios y adicionalmente, cuenta con: | E10: Inspección Documental
A11: 2 | B11: 1.1 | C11: TALENTO HUMANO | D11: Profesional de bacteriología | E11: Inspección Documental | F11: ⚠️
A12: 3 | B12: 1.2 | C12: TALENTO HUMANO | D12: Talento humano profesional que cuenta con constancia de asistencia en las acciones de formación continua en las actividades relacionadas con el laboratorio clínico, cuando se requiera | E12: Inspección Documental
A13: 4 | B13: 1.3 | C13: TALENTO HUMANO | D13: Auxiliar de laboratorio clínico o de enfermería, cuando se requiera | E13: Inspección Documental
A14: 5 | B14: 1.4 | C14: TALENTO HUMANO | D14: Cuenta con gestor comunitario en salud con constancia de asistencia en acciones de formación continua para la detección temprana y diagnóstico de enfermedades de interés en salud pública, entre otras, cuando se requiera | E14: Inspección Documental
A15: 6 | B15: 2 | C15: TALENTO HUMANO | D15: Disponibilidad de bacteriólogo en zonas especiales de dispersión geográfica con permanencia de acuerdo con lo definido por el prestador en el estándar de procesos prioritarios | E15: Inspección Documental
A16: 7 | B16: 3 | C16: TALENTO HUMANO | D16: Cuando se realicen pruebas de inmunología para trasplantes: el profesional de bacteriología cuenta con constancia de asistencia en acciones de formación continua en la realización de dichas pruebas | E16: Inspección Documental
A17: 8 | B17: 4 | C17: TALENTO HUMANO | D17: Cuando se realicen controles de calidad a pruebas en el punto de atención del paciente (POCT) a otros servicios: el profesional de bacteriología cuenta con constancia de asistencia en acciones de formación continua en el manejo de las mismas | E17: Inspección Documental
A18: ▸ Modalidad Telemedicina — Prestador de Referencia
A19: 9 | B19: 5 | C19: TALENTO HUMANO – Telemedicina Referencia | D19: Cumple con los criterios que le sean aplicables de todos los servicios | E19: Inspección Documental
A20: 10 | B20: 6 | C20: TALENTO HUMANO – Telemedicina Referencia | D20: El profesional de bacteriología puede hacer uso de la categoría telexperticia sincrónica o asincrónica entre profesionales de la salud, de acuerdo con lo definido por el prestador en el estándar de procesos prioritarios | E20: Inspección Documental
A21: ESTÁNDAR DE INFRAESTRUCTURA — Sección 11.3.12
A22: ▸ Modalidades: Intramural · Telemedicina Prestador Remisor
A23: 11 | B23: 7 | C23: INFRAESTRUCTURA | D23: Cumple con los criterios que le sean aplicables de todos los servicios | E23: Inspección Visual
A24: 12 | B24: 8 | C24: INFRAESTRUCTURA | D24: Cuenta con: | E24: Inspección Visual | F24: ⚠️
A25: 13 | B25: 8.1 | C25: INFRAESTRUCTURA | D25: Área para recepción de muestras, información y entrega de resultados | E25: Inspección Visual | F25: ⚠️
A26: 14 | B26: 8.2 | C26: INFRAESTRUCTURA | D26: Ambiente(s) técnico(s) de procedimientos que cuenta con todos los sub-ítems 8.2.1 a 8.2.5: | E26: Inspección Visual | F26: ⚠️
A27: 15 | B27: 8.2.1 | C27: INFRAESTRUCTURA | D27: Mesón de trabajo, con poceta cuando ésta se requiera | E27: Inspección Visual | F27: ⚠️
A28: 16 | B28: 8.2.2 | C28: INFRAESTRUCTURA | D28: Ducha manual o lavaojos que puede ser compartida entre los ambientes técnicos | E28: Inspección Visual | F28: ⚠️
A29: 17 | B29: 8.2.3 | C29: INFRAESTRUCTURA | D29: Área para neveras o cuarto frío | E29: Inspección Visual | F29: ⚠️
A30: 18 | B30: 8.2.4 | C30: INFRAESTRUCTURA | D30: Lavamanos | E30: Inspección Visual | F30: ⚠️
A31: 19 | B31: 8.2.5 | C31: INFRAESTRUCTURA | D31: Ambiente oscuro, cuando se requiera | E31: Inspección Visual
A32: 20 | B32: 8.3 | C32: INFRAESTRUCTURA | D32: Área o ambiente para el almacenamiento de materiales, insumos y reactivos | E32: Inspección Visual | F32: ⚠️
A33: 21 | B33: 8.4 | C33: INFRAESTRUCTURA | D33: Ambiente para la toma de muestras especiales (cuando las realice), que cumple con los criterios definidos para el servicio de toma de muestras de laboratorio clínico | E33: Inspección Visual
A34: 22 | B34: 8.5 | C34: INFRAESTRUCTURA | D34: Cubículo para toma de muestras (cuando se realice), que cumple con los criterios definidos para el servicio de toma de muestras de laboratorio clínico | E34: Inspección Visual
A35: 23 | B35: 9 | C35: INFRAESTRUCTURA | D35: Disponibilidad de: | E35: Inspección Visual
A36: 24 | B36: 9.1 | C36: INFRAESTRUCTURA | D36: Sala de espera | E36: Inspección Visual
A37: 25 | B37: 9.2 | C37: INFRAESTRUCTURA | D37: Unidades sanitarias discriminadas por sexo o de uso mixto para profesional independiente | E37: Inspección Visual
A38: ▸ Modalidades: Extramural Unidad Móvil · Jornada de Salud
A39: 26 | B39: 10 | C39: INFRAESTRUCTURA – Extramural | D39: Cumple con los criterios que le sean aplicables de todos los servicios | E39: Inspección Visual
A40: ▸ Modalidad Telemedicina — Prestador de Referencia
A41: 27 | B41: 11 | C41: INFRAESTRUCTURA – Telemedicina Referencia | D41: Cumple con los criterios que le sean aplicables de todos los servicios | E41: Inspección Visual
A42: ESTÁNDAR DE DOTACIÓN — Sección 11.3.12
A43: ▸ Modalidades: Intramural · Extramural Unidad Móvil · Jornada de Salud · Telemedicina Prestador Remisor
A44: 28 | B44: 12 | C44: DOTACIÓN | D44: Cumple con los criterios que le sean aplicables de todos los servicios y adicionalmente, cuenta con: | E44: Inspección Visual
A45: 29 | B45: 12.1 | C45: DOTACIÓN | D45: Equipos biomédicos manuales, semi-automatizados o automatizados para los procedimientos que realice | E45: Inspección Visual | F45: ⚠️
A46: 30 | B46: 12.2 | C46: DOTACIÓN | D46: Cabina de bioseguridad, si procesa muestras para el análisis de bacterias anaerobias, micosis subcutáneas o profundas y pruebas por técnica de biología molecular, cuando se requiera | E46: Inspección Visual
A47: 31 | B47: 12.3 | C47: DOTACIÓN | D47: Microscopio para toma e interpretación de pruebas para enfermedades transmitidas por vectores en zonas rurales, zonas especiales de dispersión geográfica y endémica | E47: Inspección Visual
A48: ▸ Modalidad Telemedicina — Prestador de Referencia
A49: 32 | B49: 13 | C49: DOTACIÓN – Telemedicina Referencia | D49: Cumple con los criterios que le sean aplicables de todos los servicios | E49: Inspección Visual
A50: ESTÁNDAR DE MEDICAMENTOS, DISPOSITIVOS MÉDICOS E INSUMOS — Sección 11.3.12
A51: ▸ Modalidades: Intramural · Extramural Unidad Móvil · Jornada de Salud · Telemedicina Prestador Remisor
A52: 33 | B52: 14 | C52: MEDICAMENTOS, DM E INSUMOS | D52: Cumple con los criterios que le sean aplicables de todos los servicios y adicionalmente cuenta con medicamentos, dispositivos médicos e insumos requeridos para el procesamiento de las muestras, de acuerdo con las pruebas que realice | E52: Inspección Documental | F52: ⚠️
A53: ▸ Modalidad Telemedicina — Prestador de Referencia
A54: 34 | B54: 15 | C54: MEDICAMENTOS, DM E INSUMOS – Telemedicina Referencia | D54: Cumple con los criterios que le sean aplicables de todos los servicios | E54: Inspección Documental
A55: ESTÁNDAR DE PROCESOS PRIORITARIOS — Sección 11.3.12
A56: ▸ Modalidades: Intramural · Extramural Unidad Móvil · Jornada de Salud · Telemedicina Prestador Remisor
A57: 35 | B57: 16 | C57: PROCESOS PRIORITARIOS | D57: Cumple con los criterios que le sean aplicables de todos los servicios y adicionalmente cuenta con la siguiente información documentada: | E57: Inspección Documental
A58: 36 | B58: 16.1 | C58: PROCESOS PRIORITARIOS | D58: Programa de control de calidad interno y externo, que contemple las pruebas realizadas | E58: Inspección Documental | F58: ⚠️
A59: 37 | B59: 16.2 | C59: PROCESOS PRIORITARIOS | D59: Validación secundaria o verificación | E59: Inspección Documental | F59: ⚠️
A60: 38 | B60: 16.3 | C60: PROCESOS PRIORITARIOS | D60: Análisis de los reportes del control de calidad y toma de medidas preventivas y correctivas | E60: Inspección Documental
A61: 39 | B61: 16.4 | C61: PROCESOS PRIORITARIOS | D61: Toma, identificación, transporte, conservación, embalaje y remisión de las muestras, cuando aplique | E61: Inspección Documental | F61: ⚠️
A62: 40 | B62: 16.5 | C62: PROCESOS PRIORITARIOS | D62: Entrega de resultados | E62: Inspección Documental
A63: 41 | B63: 16.6 | C63: PROCESOS PRIORITARIOS | D63: Supervisión de la toma de muestras cuando sea realizada por los auxiliares, cuando aplique | E63: Inspección Documental
A64: 42 | B64: 16.7 | C64: PROCESOS PRIORITARIOS | D64: Limpieza y desinfección del material que se utilice en el procesamiento de las muestras, cuando aplique | E64: Inspección Documental
A65: 43 | B65: 16.8 | C65: PROCESOS PRIORITARIOS | D65: Control de calidad de las pruebas en el punto de atención del paciente (point of care testing - POCT), cuando aplique | E65: Inspección Documental
A66: 44 | B66: 16.9 | C66: PROCESOS PRIORITARIOS | D66: Procedimiento y condiciones para la toma de muestras, que incluya los equipos biomédicos y medicamentos, dispositivos médicos e insumos requeridos, según las muestras que se tomen | E66: Inspección Documental | F66: ⚠️
A67: ▸ Modalidad Telemedicina — Prestador de Referencia
A68: 45 | B68: 17 | C68: PROCESOS PRIORITARIOS – Telemedicina Referencia | D68: Cumple con los criterios que le sean aplicables de todos los servicios | E68: Inspección Documental
A69: ESTÁNDAR DE HISTORIA CLÍNICA Y REGISTROS — Sección 11.3.12
A70: ▸ Modalidades: Intramural · Extramural Unidad Móvil · Jornada de Salud · Telemedicina Prestador Remisor
A71: 46 | B71: 18 | C71: HISTORIA CLÍNICA Y REGISTROS | D71: Cumple con los criterios que le sean aplicables de todos los servicios y adicionalmente cuenta con: | E71: Inspección Documental
A72: 47 | B72: 18.1 | C72: HISTORIA CLÍNICA Y REGISTROS | D72: Registro de pacientes, exámenes solicitados y pruebas realizadas | E72: Inspección Documental | F72: ⚠️
A73: 48 | B73: 18.2 | C73: HISTORIA CLÍNICA Y REGISTROS | D73: Registro de muestras tomadas y muestras remitidas, cuando aplique | E73: Inspección Documental
A74: 49 | B74: 18.3 | C74: HISTORIA CLÍNICA Y REGISTROS | D74: Registro de validación secundaria o verificación | E74: Inspección Documental | F74: ⚠️
A75: 50 | B75: 18.4 | C75: HISTORIA CLÍNICA Y REGISTROS | D75: Formato de reporte de resultados | E75: Inspección Documental | F75: ⚠️
A76: 51 | B76: 18.5 | C76: HISTORIA CLÍNICA Y REGISTROS | D76: Registro de resultados de los exámenes remitidos. Los resultados deben ser entregados al paciente con el nombre del laboratorio clínico y la persona que los realizó | E76: Inspección Documental | F76: ⚠️
A77: 52 | B77: 18.6 | C77: HISTORIA CLÍNICA Y REGISTROS | D77: Registro de control de calidad interno y externo | E77: Inspección Documental | F77: ⚠️
A78: 53 | B78: 18.7 | C78: HISTORIA CLÍNICA Y REGISTROS | D78: Registro de control de calidad de las pruebas en el punto de atención del paciente (POCT), cuando aplique | E78: Inspección Documental
A79: 54 | B79: 18.8 | C79: HISTORIA CLÍNICA Y REGISTROS | D79: Contrato o convenio escrito con el/los laboratorios que realizan el procesamiento de las muestras, cuando lo requiera. Cuando se trate de sedes del mismo prestador no requiere convenio o contrato. Si el laboratorio está en otro país: copia del documento que autorice el funcionamiento en dicho país | E79: Inspección Documental
A80: 55 | B80: 18.9 | C80: HISTORIA CLÍNICA Y REGISTROS | D80: Contrato o convenio escrito con el servicio de patología cuando se recepcionen fragmentos de tejidos, órganos (biopsias) y material citológico de origen humano. Si el servicio de patología está en otro país: copia del documento que autorice su funcionamiento. Cuando se trate de sedes del mismo prestador no requiere convenio o contrato | E80: Inspección Documental
A81: ▸ Modalidad Telemedicina — Prestador de Referencia
A82: 56 | B82: 19 | C82: HISTORIA CLÍNICA Y REGISTROS – Telemedicina Referencia | D82: Cumple con los criterios que le sean aplicables de todos los servicios | E82: Inspección Documental
A83: ESTÁNDAR DE INTERDEPENDENCIA — Sección 11.3.12
A84: ▸ Modalidades: Intramural · Extramural · Telemedicina (Prestador Remisor y Prestador de Referencia)
A85: 57 | B85: 20 | C85: INTERDEPENDENCIA | D85: No aplica | E85: Inspección Documental
A88: RESUMEN DE CUMPLIMIENTO POR ESTÁNDAR — LABORATORIO CLÍNICO BAJA COMPLEJIDAD
A89: ESTÁNDAR | B89: TOTAL CRITERIOS | C89: CUMPLE (C) | D89: NO CUMPLE (NC) | E89: NO APLICA (NA) | F89: % CUMPLIMIENTO | G89: NIVEL
A90: TALENTO HUMANO | B90: =COUNTIF(C10:C85,"*TALENTO HUMANO*") -> 10 | C90: =COUNTIFS(C10:C85,"*TALENTO HUMANO*",G10:G85,"X") -> 0 | D90: =COUNTIFS(C10:C85,"*TALENTO HUMANO*",H10:H85,"X") -> 0 | E90: =COUNTIFS(C10:C85,"*TALENTO HUMANO*",I10:I85,"X") -> 0 | F90: =IF((C90+D90)=0,0,C90/(C90+D90)) -> 0 | G90: =IF(F90>=0.9,"ALTO",IF(F90>=0.7,"MEDIO",IF(F90>0,"BAJO","SIN EVALUAR"))) -> SIN EVALUAR
A91: INFRAESTRUCTURA | B91: =COUNTIF(C10:C85,"*INFRAESTRUCTURA*") -> 17 | C91: =COUNTIFS(C10:C85,"*INFRAESTRUCTURA*",G10:G85,"X") -> 0 | D91: =COUNTIFS(C10:C85,"*INFRAESTRUCTURA*",H10:H85,"X") -> 0 | E91: =COUNTIFS(C10:C85,"*INFRAESTRUCTURA*",I10:I85,"X") -> 0 | F91: =IF((C91+D91)=0,0,C91/(C91+D91)) -> 0 | G91: =IF(F91>=0.9,"ALTO",IF(F91>=0.7,"MEDIO",IF(F91>0,"BAJO","SIN EVALUAR"))) -> SIN EVALUAR
A92: DOTACIÓN | B92: =COUNTIF(C10:C85,"*DOTACIÓN*") -> 5 | C92: =COUNTIFS(C10:C85,"*DOTACIÓN*",G10:G85,"X") -> 0 | D92: =COUNTIFS(C10:C85,"*DOTACIÓN*",H10:H85,"X") -> 0 | E92: =COUNTIFS(C10:C85,"*DOTACIÓN*",I10:I85,"X") -> 0 | F92: =IF((C92+D92)=0,0,C92/(C92+D92)) -> 0 | G92: =IF(F92>=0.9,"ALTO",IF(F92>=0.7,"MEDIO",IF(F92>0,"BAJO","SIN EVALUAR"))) -> SIN EVALUAR
A93: MEDICAMENTOS, DM E INSUMOS | B93: =COUNTIF(C10:C85,"*MEDICAMENTOS, DM E INSUMOS*") -> 2 | C93: =COUNTIFS(C10:C85,"*MEDICAMENTOS, DM E INSUMOS*",G10:G85,"X") -> 0 | D93: =COUNTIFS(C10:C85,"*MEDICAMENTOS, DM E INSUMOS*",H10:H85,"X") -> 0 | E93: =COUNTIFS(C10:C85,"*MEDICAMENTOS, DM E INSUMOS*",I10:I85,"X") -> 0 | F93: =IF((C93+D93)=0,0,C93/(C93+D93)) -> 0 | G93: =IF(F93>=0.9,"ALTO",IF(F93>=0.7,"MEDIO",IF(F93>0,"BAJO","SIN EVALUAR"))) -> SIN EVALUAR
A94: PROCESOS PRIORITARIOS | B94: =COUNTIF(C10:C85,"*PROCESOS PRIORITARIOS*") -> 11 | C94: =COUNTIFS(C10:C85,"*PROCESOS PRIORITARIOS*",G10:G85,"X") -> 0 | D94: =COUNTIFS(C10:C85,"*PROCESOS PRIORITARIOS*",H10:H85,"X") -> 0 | E94: =COUNTIFS(C10:C85,"*PROCESOS PRIORITARIOS*",I10:I85,"X") -> 0 | F94: =IF((C94+D94)=0,0,C94/(C94+D94)) -> 0 | G94: =IF(F94>=0.9,"ALTO",IF(F94>=0.7,"MEDIO",IF(F94>0,"BAJO","SIN EVALUAR"))) -> SIN EVALUAR
A95: HISTORIA CLÍNICA Y REGISTROS | B95: =COUNTIF(C10:C85,"*HISTORIA CLÍNICA Y REGISTROS*") -> 11 | C95: =COUNTIFS(C10:C85,"*HISTORIA CLÍNICA Y REGISTROS*",G10:G85,"X") -> 0 | D95: =COUNTIFS(C10:C85,"*HISTORIA CLÍNICA Y REGISTROS*",H10:H85,"X") -> 0 | E95: =COUNTIFS(C10:C85,"*HISTORIA CLÍNICA Y REGISTROS*",I10:I85,"X") -> 0 | F95: =IF((C95+D95)=0,0,C95/(C95+D95)) -> 0 | G95: =IF(F95>=0.9,"ALTO",IF(F95>=0.7,"MEDIO",IF(F95>0,"BAJO","SIN EVALUAR"))) -> SIN EVALUAR
A96: INTERDEPENDENCIA | B96: =COUNTIF(C10:C85,"*INTERDEPENDENCIA*") -> 1 | C96: =COUNTIFS(C10:C85,"*INTERDEPENDENCIA*",G10:G85,"X") -> 0 | D96: =COUNTIFS(C10:C85,"*INTERDEPENDENCIA*",H10:H85,"X") -> 0 | E96: =COUNTIFS(C10:C85,"*INTERDEPENDENCIA*",I10:I85,"X") -> 0 | F96: =IF((C96+D96)=0,0,C96/(C96+D96)) -> 0 | G96: =IF(F96>=0.9,"ALTO",IF(F96>=0.7,"MEDIO",IF(F96>0,"BAJO","SIN EVALUAR"))) -> SIN EVALUAR
A97: TOTAL GENERAL | B97: =SUM(B90:B96) -> 57 | C97: =SUM(C90:C96) -> 0 | D97: =SUM(D90:D96) -> 0 | E97: =SUM(E90:E96) -> 0 | F97: =SUM(F90:F96) -> 0 | G97: =IF(F97>=0.9,"ALTO",IF(F97>=0.7,"MEDIO",IF(F97>0,"BAJO","SIN EVALUAR"))) -> SIN EVALUAR

Sheet Toma de Muestras Lab
A1: AUDITORÍA — SERVICIO DE TOMA DE MUESTRAS DE LABORATORIO CLÍNICO
A2: Resolución 3100 de 2019 | Sección 11.3.11 | Criterios por Estándar y Modalidad de Prestación
A3: PRESTADOR:
A4: FECHA: | F4: AUDITOR: | L4: HORA INICIO:
A5: ⚠️ Los criterios marcados son CRÍTICOS. Su incumplimiento puede generar requerimiento o cierre del servicio. | Ref: Res. 3100/2019, Sección 11.3.11, Pág. 130-131
A6: LEYENDA: C = Cumple · NC = No Cumple · NA = No Aplica | Marque X en la columna correspondiente. La fila cambia de color automáticamente.
A7: N° | B7: N° CRITERIO | C7: ESTÁNDAR | D7: CRITERIO | E7: MODO DE VERIFICACIÓN | F7: ⚠️ | G7: C | H7: NC | I7: NA | J7: HALLAZGO / EVIDENCIA | K7: PLAN DE MEJORA | L7: RESPONSABLE | M7: FECHA COMPROMISO
A8: ESTÁNDAR DE TALENTO HUMANO — Sección 11.3.11
A9: ▸ Modalidades: Intramural · Extramural Unidad Móvil · Jornada de Salud · Domiciliaria
A10: 1 | B10: 1 | C10: TALENTO HUMANO | D10: Cumple con los criterios que le sean aplicables de todos los servicios y adicionalmente cuenta con: profesional de bacteriología o auxiliar de laboratorio clínico o auxiliar de enfermería | E10: Inspección Documental | F10: ⚠️
A11: 2 | B11: 2 | C11: TALENTO HUMANO | D11: Disponibilidad de: profesional de bacteriología quien realiza la supervisión cuando la toma de muestras es realizada por el auxiliar | E11: Inspección Documental | F11: ⚠️
A12: ESTÁNDAR DE INFRAESTRUCTURA — Sección 11.3.11
A13: ▸ Modalidad Intramural
A14: 3 | B14: 3 | C14: INFRAESTRUCTURA | D14: Cumple con los criterios que le sean aplicables de todos los servicios (criterios generales de infraestructura Res. 3100/2019 — sección 11.1.2) | E14: Inspección Visual
A15: 4 | B15: 4 | C15: INFRAESTRUCTURA | D15: Cuenta con: | E15: Inspección Visual | F15: ⚠️
A16: 5 | B16: 4.1 | C16: INFRAESTRUCTURA | D16: Área para recepción de muestras, información y entrega de resultados | E16: Inspección Visual | F16: ⚠️
A17: 6 | B17: 4.2 | C17: INFRAESTRUCTURA | D17: Cubículo para la toma de muestras | E17: Inspección Visual | F17: ⚠️
A18: 7 | B18: 4.3 | C18: INFRAESTRUCTURA | D18: Ambiente para la toma de muestras especiales cuando lo oferte, con unidad sanitaria y perchero (si el procedimiento lo indica) | E18: Inspección Visual
A19: 8 | B19: 4.4 | C19: INFRAESTRUCTURA | D19: Lavamanos | E19: Inspección Visual | F19: ⚠️
A20: 9 | B20: 4.5 / 4.5.1 | C20: INFRAESTRUCTURA | D20: Área de preparación, embalaje y remisión de las muestras que cuenta con: mesón de trabajo, con poceta cuando ésta se requiera | E20: Inspección Visual | F20: ⚠️
A21: 10 | B21: 5 | C21: INFRAESTRUCTURA | D21: Disponibilidad de: | E21: Inspección Visual
A22: 11 | B22: 5.1 | C22: INFRAESTRUCTURA | D22: Sala de espera | E22: Inspección Visual
A23: 12 | B23: 5.2 | C23: INFRAESTRUCTURA | D23: Unidades sanitarias discriminadas por sexo | E23: Inspección Visual
A24: ▸ Modalidades: Extramural Unidad Móvil · Jornada de Salud · Domiciliaria
A25: 13 | B25: 6 | C25: INFRAESTRUCTURA – Extramural | D25: Cumple con los criterios que le sean aplicables de todos los servicios | E25: Inspección Visual
A26: ESTÁNDAR DE DOTACIÓN — Sección 11.3.11
A27: ▸ Modalidades: Intramural · Extramural Unidad Móvil · Jornada de Salud · Domiciliaria
A28: 14 | B28: 7 | C28: DOTACIÓN | D28: Cumple con los criterios que le sean aplicables de todos los servicios y adicionalmente cuenta con: equipos biomédicos necesarios según las muestras que se tomen, de acuerdo con lo documentado en el estándar de procesos prioritarios | E28: Inspección Visual | F28: ⚠️
A29: ESTÁNDAR DE MEDICAMENTOS, DISPOSITIVOS MÉDICOS E INSUMOS — Sección 11.3.11
A30: ▸ Modalidades: Intramural · Extramural Unidad Móvil · Jornada de Salud · Domiciliaria
A31: 15 | B31: 8 | C31: MEDICAMENTOS, DM E INSUMOS | D31: Cumple con los criterios que le sean aplicables de todos los servicios y adicionalmente cuenta con: medicamentos, dispositivos médicos e insumos requeridos para la toma de las muestras, de acuerdo con lo documentado en el estándar de procesos prioritarios | E31: Inspección Documental | F31: ⚠️
A32: ESTÁNDAR DE PROCESOS PRIORITARIOS — Sección 11.3.11
A33: ▸ Modalidades: Intramural · Extramural Unidad Móvil · Jornada de Salud · Domiciliaria
A34: 16 | B34: 9 | C34: PROCESOS PRIORITARIOS | D34: Cumple con los criterios que le sean aplicables de todos los servicios y adicionalmente cuenta con la siguiente información documentada: | E34: Inspección Documental
A35: 17 | B35: 9.1 | C35: PROCESOS PRIORITARIOS | D35: Toma, recepción, identificación, transporte, conservación, embalaje y remisión de las muestras | E35: Inspección Documental | F35: ⚠️
A36: 18 | B36: 9.2 | C36: PROCESOS PRIORITARIOS | D36: Entrega de resultados | E36: Inspección Documental | F36: ⚠️
A37: 19 | B37: 9.3 | C37: PROCESOS PRIORITARIOS | D37: Supervisión de la toma de muestras cuando sea realizada por los auxiliares | E37: Inspección Documental | F37: ⚠️
A38: 20 | B38: 9.4 | C38: PROCESOS PRIORITARIOS | D38: Procedimiento y condiciones para la toma de muestras en la modalidad extramural cuando se realicen | E38: Inspección Documental
A39: ESTÁNDAR DE HISTORIA CLÍNICA Y REGISTROS — Sección 11.3.11
A40: ▸ Modalidades: Intramural · Extramural Unidad Móvil · Jornada de Salud · Domiciliaria
A41: 21 | B41: 10 | C41: HISTORIA CLÍNICA Y REGISTROS | D41: Cumple con los criterios que le sean aplicables de todos los servicios y adicionalmente cuenta con: | E41: Inspección Documental
A42: 22 | B42: 10.1 | C42: HISTORIA CLÍNICA Y REGISTROS | D42: Registro de pacientes, muestras tomadas, exámenes solicitados y muestras remitidas | E42: Inspección Documental | F42: ⚠️
A43: 23 | B43: 10.2 | C43: HISTORIA CLÍNICA Y REGISTROS | D43: Registro de los resultados de los exámenes remitidos. Los resultados deben ser entregados al paciente con el nombre del laboratorio clínico y la persona que los realizó | E43: Inspección Documental | F43: ⚠️
A44: 24 | B44: 10.3 | C44: HISTORIA CLÍNICA Y REGISTROS | D44: Contrato o convenio escrito con el/los laboratorios que realizan el procesamiento de las muestras. Cuando se trate de sedes de un mismo prestador no requiere convenio o contrato | E44: Inspección Documental
A45: 25 | B45: 10.4 | C45: HISTORIA CLÍNICA Y REGISTROS | D45: Contrato o convenio escrito con el servicio de patología cuando se recepcionen fragmentos de tejidos, órganos (biopsias) y material citológico de origen humano. Cuando se trate de sedes de un mismo prestador no requiere convenio o contrato | E45: Inspección Documental
A46: ESTÁNDAR DE INTERDEPENDENCIA — Sección 11.3.11
A47: ▸ Modalidades: Intramural · Extramural Unidad Móvil · Jornada de Salud · Domiciliaria
A48: 26 | B48: 11 | C48: INTERDEPENDENCIA | D48: Cumple con los criterios que le sean aplicables de todos los servicios y adicionalmente disponibilidad de: servicio de laboratorio clínico (propio o contratado mediante convenio escrito) | E48: Inspección Documental | F48: ⚠️
A51: RESUMEN DE CUMPLIMIENTO POR ESTÁNDAR — TOMA DE MUESTRAS DE LABORATORIO CLÍNICO
A52: ESTÁNDAR | B52: TOTAL CRITERIOS | C52: CUMPLE (C) | D52: NO CUMPLE (NC) | E52: NO APLICA (NA) | F52: % CUMPLIMIENTO | G52: NIVEL
A53: TALENTO HUMANO | B53: =COUNTIF(C10:C48,"*TALENTO HUMANO*") -> 2 | C53: =COUNTIFS(C10:C48,"*TALENTO HUMANO*",G10:G48,"X") -> 0 | D53: =COUNTIFS(C10:C48,"*TALENTO HUMANO*",H10:H48,"X") -> 0 | E53: =COUNTIFS(C10:C48,"*TALENTO HUMANO*",I10:I48,"X") -> 0 | F53: =IF((C53+D53)=0,0,C53/(C53+D53)) -> 0 | G53: =IF(F53>=0.9,"ALTO",IF(F53>=0.7,"MEDIO",IF(F53>0,"BAJO","SIN EVALUAR"))) -> SIN EVALUAR
A54: INFRAESTRUCTURA | B54: =COUNTIF(C10:C48,"*INFRAESTRUCTURA*") -> 11 | C54: =COUNTIFS(C10:C48,"*INFRAESTRUCTURA*",G10:G48,"X") -> 0 | D54: =COUNTIFS(C10:C48,"*INFRAESTRUCTURA*",H10:H48,"X") -> 0 | E54: =COUNTIFS(C10:C48,"*INFRAESTRUCTURA*",I10:I48,"X") -> 0 | F54: =IF((C54+D54)=0,0,C54/(C54+D54)) -> 0 | G54: =IF(F54>=0.9,"ALTO",IF(F54>=0.7,"MEDIO",IF(F54>0,"BAJO","SIN EVALUAR"))) -> SIN EVALUAR
A55: DOTACIÓN | B55: =COUNTIF(C10:C48,"*DOTACIÓN*") -> 1 | C55: =COUNTIFS(C10:C48,"*DOTACIÓN*",G10:G48,"X") -> 0 | D55: =COUNTIFS(C10:C48,"*DOTACIÓN*",H10:H48,"X") -> 0 | E55: =COUNTIFS(C10:C48,"*DOTACIÓN*",I10:I48,"X") -> 0 | F55: =IF((C55+D55)=0,0,C55/(C55+D55)) -> 0 | G55: =IF(F55>=0.9,"ALTO",IF(F55>=0.7,"MEDIO",IF(F55>0,"BAJO","SIN EVALUAR"))) -> SIN EVALUAR
A56: MEDICAMENTOS, DM E INSUMOS | B56: =COUNTIF(C10:C48,"*MEDICAMENTOS, DM E INSUMOS*") -> 1 | C56: =COUNTIFS(C10:C48,"*MEDICAMENTOS, DM E INSUMOS*",G10:G48,"X") -> 0 | D56: =COUNTIFS(C10:C48,"*MEDICAMENTOS, DM E INSUMOS*",H10:H48,"X") -> 0 | E56: =COUNTIFS(C10:C48,"*MEDICAMENTOS, DM E INSUMOS*",I10:I48,"X") -> 0 | F56: =IF((C56+D56)=0,0,C56/(C56+D56)) -> 0 | G56: =IF(F56>=0.9,"ALTO",IF(F56>=0.7,"MEDIO",IF(F56>0,"BAJO","SIN EVALUAR"))) -> SIN EVALUAR
A57: PROCESOS PRIORITARIOS | B57: =COUNTIF(C10:C48,"*PROCESOS PRIORITARIOS*") -> 5 | C57: =COUNTIFS(C10:C48,"*PROCESOS PRIORITARIOS*",G10:G48,"X") -> 0 | D57: =COUNTIFS(C10:C48,"*PROCESOS PRIORITARIOS*",H10:H48,"X") -> 0 | E57: =COUNTIFS(C10:C48,"*PROCESOS PRIORITARIOS*",I10:I48,"X") -> 0 | F57: =IF((C57+D57)=0,0,C57/(C57+D57)) -> 0 | G57: =IF(F57>=0.9,"ALTO",IF(F57>=0.7,"MEDIO",IF(F57>0,"BAJO","SIN EVALUAR"))) -> SIN EVALUAR
A58: HISTORIA CLÍNICA Y REGISTROS | B58: =COUNTIF(C10:C48,"*HISTORIA CLÍNICA Y REGISTROS*") -> 5 | C58: =COUNTIFS(C10:C48,"*HISTORIA CLÍNICA Y REGISTROS*",G10:G48,"X") -> 0 | D58: =COUNTIFS(C10:C48,"*HISTORIA CLÍNICA Y REGISTROS*",H10:H48,"X") -> 0 | E58: =COUNTIFS(C10:C48,"*HISTORIA CLÍNICA Y REGISTROS*",I10:I48,"X") -> 0 | F58: =IF((C58+D58)=0,0,C58/(C58+D58)) -> 0 | G58: =IF(F58>=0.9,"ALTO",IF(F58>=0.7,"MEDIO",IF(F58>0,"BAJO","SIN EVALUAR"))) -> SIN EVALUAR
A59: INTERDEPENDENCIA | B59: =COUNTIF(C10:C48,"*INTERDEPENDENCIA*") -> 1 | C59: =COUNTIFS(C10:C48,"*INTERDEPENDENCIA*",G10:G48,"X") -> 0 | D59: =COUNTIFS(C10:C48,"*INTERDEPENDENCIA*",H10:H48,"X") -> 0 | E59: =COUNTIFS(C10:C48,"*INTERDEPENDENCIA*",I10:I48,"X") -> 0 | F59: =IF((C59+D59)=0,0,C59/(C59+D59)) -> 0 | G59: =IF(F59>=0.9,"ALTO",IF(F59>=0.7,"MEDIO",IF(F59>0,"BAJO","SIN EVALUAR"))) -> SIN EVALUAR
A60: TOTAL GENERAL | B60: =SUM(B53:B59) -> 26 | C60: =SUM(C53:C59) -> 0 | D60: =SUM(D53:D59) -> 0 | E60: =SUM(E53:E59) -> 0 | F60: =SUM(F53:F59) -> 0 | G60: =IF(F60>=0.9,"ALTO",IF(F60>=0.7,"MEDIO",IF(F60>0,"BAJO","SIN EVALUAR"))) -> SIN EVALUAR

Sheet Acta de Visita
A1: ACTA DE VISITA — AUDITORÍA DE HABILITACIÓN EN SALUD
A2: Resolución 3100 de 2019 | Sistema Único de Habilitación | Audisalud Colombia S.A.S.
A4: 1. IDENTIFICACIÓN DEL PROCESO
A5: CAMPO | D5: DATO
A6: N°. de Acta: | E6: Fecha de la visita:
A7: Hora inicio: | E7: Hora finalización:
A8: Tipo de visita: | E8: Modalidad:
A9: Entidad contratante: | E9: Objeto:
A10: Nombre del auditor: | E10: Cargo / Tarjeta:
A11: Nombre del prestador: | E11: Cédula:
A12: Dirección: | E12: Municipio:
A13: Servicios auditados: | E13: Sede:
A15: 2. INSTRUMENTOS APLICADOS
A16: INSTRUMENTO | B16: APLICADO (SÍ/NO) | C16: N° CRITERIOS EVALUADOS | D16: N° CUMPLE | E16: N° NO CUMPLE | F16: % CUMPLIMIENTO
A17: Auditoría Documental
A18: Auditoría Infraestructura
A19: Consulta Externa
A20: Terapias
A21: Laboratorio Clínico
A23: 3. DESCRIPCIÓN DE HALLAZGOS POR INSTRUMENTO
A24: N° | B24: INSTRUMENTO / ESTÁNDAR | C24: CRITERIO | D24: HALLAZGO / EVIDENCIA | E24: CALIFICACIÓN
A41: 4. CONCEPTO DE LA VISITA
A43: Seleccione el concepto de la visita en la celda anterior
A45: 5. REQUERIMIENTOS PARA HABILITACIÓN (si aplica)
A46: N° | B46: REQUERIMIENTO | C46: CRITERIO BASE | D46: PLAZO OTORGADO | E46: RESPONSABLE
A56: 6. FIRMAS Y COMPROMISOS
A57: AUDITOR Nombre: ________________________ Cargo: _________________________ No. Tarjeta: ___________________ Firma: _________________________ Fecha: ________________________ | D57: PRESTADOR AUDITADO Nombre: ________________________ Cargo: _________________________ No. Identificación: ______________ Firma: _________________________ Fecha: ________________________
